Workbook

Sheet MOP_Mes_Corriente
C1: 1.620347 | D1: 1.620347 | E1: 1.620347 | F1: 1.620347 | G1: 1.620347 | H1: 1.620347 | I1: 1.620347 | J1: 1.620347 | K1: 1.620347 | L1: 1.620347 | M1: 1.620347 | N1: 1.620347 | P1: 1.5522091 | Q1: 1.5522091 | R1: 1.5522091 | S1: 1.5522091 | T1: 1.5522091 | U1: 1.5522091 | V1: 1.5522091 | W1: 1.5522091 | X1: 1.5522091 | Y1: 1.5522091 | Z1: 1.5522091 | AA1: 1.5522091 | AC1: 1.5114124 | AD1: 1.5114124 | AE1: 1.5114124 | AF1: 1.5114124 | AG1: 1.5114124 | AH1: 1.5114124 | AI1: 1.5114124 | AJ1: 1.5114124 | AK1: 1.5114124 | AL1: 1.5114124 | AM1: 1.5114124 | AN1: 1.5114124 | AP1: 1.4778845 | AQ1: 1.4778845 | AR1: 1.4778845 | AS1: 1.4778845 | AT1: 1.4778845 | AU1: 1.4778845 | AV1: 1.4778845 | AW1: 1.4778845 | AX1: 1.4778845 | AY1: 1.4778845 | AZ1: 1.4778845 | BA1: 1.4778845 | BC1: 1.4408545 | BD1: 1.4408545 | BE1: 1.4408545 | BF1: 1.4408545 | BG1: 1.4408545 | BH1: 1.4408545 | BI1: 1.4408545 | BJ1: 1.4408545 | BK1: 1.4408545 | BL1: 1.4408545 | BM1: 1.4408545 | BN1: 1.4408545 | BP1: 1.3989757 | BQ1: 1.3989757 | BR1: 1.3989757 | BS1: 1.3989757 | BT1: 1.3989757 | BU1: 1.3989757 | BV1: 1.3989757 | BW1: 1.3989757 | BX1: 1.3989757 | BY1: 1.3989757 | BZ1: 1.3989757 | CA1: 1.3989757 | CC1: 1.3584483 | CD1: 1.3584483 | CE1: 1.3584483 | CF1: 1.3584483 | CG1: 1.3584483 | CH1: 1.3584483 | CI1: 1.3584483 | CJ1: 1.3584483 | CK1: 1.3584483 | CL1: 1.3584483 | CM1: 1.3584483 | CN1: 1.3584483 | CP1: 1.2675174 | CQ1: 1.2675174 | CR1: 1.2675174 | CS1: 1.2675174 | CT1: 1.2675174 | CU1: 1.2675174 | CV1: 1.2675174 | CW1: 1.2675174 | CX1: 1.2675174 | CY1: 1.2675174 | CZ1: 1.2675174 | DA1: 1.2675174 | DC1: 1.1239584 | DD1: 1.1239584 | DE1: 1.1239584 | DF1: 1.1239584 | DG1: 1.1239584 | DH1: 1.1239584 | DI1: 1.1239584 | DJ1: 1.1239584 | DK1: 1.1239584 | DL1: 1.1239584 | DM1: 1.1239584 | DN1: 1.1239584 | DP1: 1.0813539 | DQ1: 1.0813539 | DR1: 1.0813539 | DS1: 1.0813539 | DT1: 1.0813539 | DU1: 1.0813539 | DV1: 1.0813539 | DW1: 1.0813539 | DX1: 1.0813539 | DY1: 1.0813539 | DZ1: 1.0813539 | EA1: 1.0813539 | EC1: 1.0344632 | ED1: 1.0344632 | EE1: 1.0344632 | EF1: 1.0344632 | EG1: 1.0344632 | EH1: 1.0344632 | EI1: 1.0344632 | EJ1: 1.0344632 | EK1: 1.0344632 | EL1: 1.0344632 | EM1: 1.0344632 | EN1: 1.0344632 | EP1: 1 | EQ1: 1 | ER1: 1 | ES1: 1 | ET1: 1 | EU1: 1 | EV1: 1 | EW1: 1 | EX1: 1 | EY1: 1 | EZ1: 1 | FA1: 1
B3: Ministerio de Obras Públicas – Partida 12
B4: Miles de pesos – moneda corriente – montos devengados
B5: Subtítulo 31 – Iniciativas de Inversión
B7: Presupuesto Ley de Inversión en Infraestructura Pública del Ministerio de Obras Públicas, 2014-2026 (Subtítulo 31 – Iniciativas de Inversión, miles de pesos)
C8: 2014 | P8: 2015 | AC8: 2016 | AP8: 2017 | BC8: 2018 | BP8: 2019 | CC8: 2020 | CP8: 2021(1) | DC8: 2022(1) | DP8: 2023 | EC8: 2024 | EP8: 2025 | FC8: 2026
B9: Programa | C9: Ene | D9: Feb | E9: Mar | F9: Abr | G9: May | H9: Jun | I9: Jul | J9: Ago | K9: Sep | L9: Oct | M9: Nov | N9: Dic | O9: Total 2014 | P9: Ene | Q9: Feb | R9: Mar | S9: Abr | T9: May | U9: Jun | V9: Jul | W9: Ago | X9: Sep | Y9: Oct | Z9: Nov | AA9: Dic | AB9: Total 2015 | AC9: Ene | AD9: Feb | AE9: Mar | AF9: Abr | AG9: May | AH9: Jun | AI9: Jul | AJ9: Ago | AK9: Sep | AL9: Oct | AM9: Nov | AN9: Dic | AO9: Total 2016 | AP9: Ene | AQ9: Feb | AR9: Mar | AS9: Abr | AT9: May | AU9: Jun | AV9: Jul | AW9: Ago | AX9: Sep | AY9: Oct | AZ9: Nov | BA9: Dic | BB9: Total 2017 | BC9: Ene | BD9: Feb | BE9: Mar | BF9: Abr | BG9: May | BH9: Jun | BI9: Jul | BJ9: Ago | BK9: Sep | BL9: Oct | BM9: Nov | BN9: Dic | BO9: Total 2018 | BP9: Ene | BQ9: Feb | BR9: Mar | BS9: Abr | BT9: May | BU9: Jun | BV9: Jul | BW9: Ago | BX9: Sep | BY9: Oct | BZ9: Nov | CA9: Dic | CB9: Total 2019 | CC9: Ene | CD9: Feb | CE9: Mar | CF9: Abr | CG9: May | CH9: Jun | CI9: Jul | CJ9: Ago | CK9: Sep | CL9: Oct | CM9: Nov | CN9: Dic | CO9: Total 2020 | CP9: Ene | CQ9: Feb | CR9: Mar | CS9: Abr | CT9: May | CU9: Jun | CV9: Jul | CW9: Ago | CX9: Sep | CY9: Oct | CZ9: Nov | DA9: Dic | DB9: Total 2021 | DC9: Ene | DD9: Feb | DE9: Mar | DF9: Abr | DG9: May | DH9: Jun | DI9: Jul | DJ9: Ago | DK9: Sep | DL9: Oct | DM9: Nov | DN9: Dic | DO9: Total 2022 | DP9: Ene | DQ9: Feb | DR9: Mar | DS9: Abr | DT9: May | DU9: Jun | DV9: Jul | DW9: Ago | DX9: Sep | DY9: Oct | DZ9: Nov | EA9: Dic | EB9: Total 2023 | EC9: Ene | ED9: Feb | EE9: Mar | EF9: Abr | EG9: May | EH9: Jun | EI9: Jul | EJ9: Ago | EK9: Sep | EL9: Oct | EM9: Nov | EN9: Dic | EO9: Total 2024 | EP9: Ene | EQ9: Feb | ER9: Mar | ES9: Abr | ET9: May | EU9: Jun | EV9: Jul | EW9: Ago | EX9: Sep | EY9: Oct | EZ9: Nov | FA9: Dic | FB9: Total 2025 | FC9: Ene | FD9: Feb | FE9: Mar | FF9: Abr | FG9: May | FH9: Jun | FI9: Jul | FJ9: Ago | FK9: Sep | FL9: Oct | FM9: Nov | FN9: Dic | FO9: Total 2026
B10: Dirección de Vialidad | C10: 806907228 | D10: 806907228 | E10: 806907228 | F10: 806907228 | G10: 806907228 | H10: 806907228 | I10: 806907228 | J10: 806907228 | K10: 806907228 | L10: 806907228 | M10: 806907228 | N10: 806907228 | O10: =N10 -> 806907228 | P10: 957407656 | Q10: 957407656 | R10: 957407656 | S10: 957407656 | T10: 957407656 | U10: 957407656 | V10: 957407656 | W10: 957407656 | X10: 957407656 | Y10: 957407656 | Z10: 957407656 | AA10: 957407656 | AB10: =AA10 -> 957407656 | AC10: 937156766 | AD10: 937156766 | AE10: 937156766 | AF10: 937156766 | AG10: 937156766 | AH10: 937156766 | AI10: 937156766 | AJ10: 937156766 | AK10: 937156766 | AL10: 937156766 | AM10: 937156766 | AN10: 937156766 | AO10: =AN10 -> 937156766 | AP10: 982538421 | AQ10: 982538421 | AR10: 982538421 | AS10: 982538421 | AT10: 982538421 | AU10: 982538421 | AV10: 982538421 | AW10: 982538421 | AX10: 982538421 | AY10: 982538421 | AZ10: 982538421 | BA10: 982538421 | BB10: =BA10 -> 982538421 | BC10: 998447263 | BD10: 998447263 | BE10: 998447263 | BF10: 998447263 | BG10: 998447263 | BH10: 998447263 | BI10: 998447263 | BJ10: 998447263 | BK10: 998447263 | BL10: 998447263 | BM10: 998447263 | BN10: 998447263 | BO10: =BN10 -> 998447263 | BP10: 1056398949 | BQ10: 1056398949 | BR10: 1056398949 | BS10: 1056398949 | BT10: 1056398949 | BU10: 1056398949 | BV10: 1056398949 | BW10: 1056398949 | BX10: 1056398949 | BY10: 1056398949 | BZ10: 1056398949 | CA10: 1056398949 | CB10: =CA10 -> 1056398949 | CC10: 1148358839 | CD10: 1148358839 | CE10: 1148358839 | CF10: 1148358839 | CG10: 1148358839 | CH10: 1148358839 | CI10: 1148358839 | CJ10: 1148358839 | CK10: 1148358839 | CL10: 1148358839 | CM10: 1148358839 | CN10: 1148358839 | CO10: =CN10 -> 1148358839 | CP10: =1224421462+380805877 -> 1605227339 | CQ10: =1224421462+380805877 -> 1605227339 | CR10: =1224421462+380805877 -> 1605227339 | CS10: =1224421462+380805877 -> 1605227339 | CT10: =1224421462+380805877 -> 1605227339 | CU10: =1224421462+380805877 -> 1605227339 | CV10: =1224421462+380805877 -> 1605227339 | CW10: =1224421462+380805877 -> 1605227339 | ... DA10: =1224421462+380805877 -> 1605227339 | DB10: =DA10 -> 1605227339 | DC10: =1220635546+581829225 -> 1802464771 | DD10: =1220635546+581829225 -> 1802464771 | DE10: =1220635546+581829225 -> 1802464771 | DF10: =1220635546+581829225 -> 1802464771 | DG10: =1220635546+581829225 -> 1802464771 | DH10: =1220635546+581829225 -> 1802464771 | DI10: =1220635546+581829225 -> 1802464771 | DJ10: =1220635546+581829225 -> 1802464771 | ... DN10: =1220635546+581829225 -> 1802464771 | DO10: =DN10 -> 1802464771 | DP10: 1913855137 | DQ10: 1913855137 | DR10: 1913855137 | DS10: 1913855137 | DT10: 1913855137 | DU10: 1913855137 | DV10: 1913855137 | DW10: 1913855137 | DX10: 1913855137 | DY10: 1913855137 | DZ10: 1913855137 | EA10: 1913855137 | EB10: =EA10 -> 1913855137 | EC10: 2012684680 | ED10: 2012684680 | EE10: 2012684680 | EF10: 2012684680 | EG10: 2012684680 | EH10: 2012684680 | EI10: 2012684680 | EJ10: 2012684680 | EK10: 2012684680 | EL10: 2012684680 | EM10: 2012684680 | EN10: 2012684680 | EO10: =EN10 -> 2012684680 | EP10: 2083103023 | EQ10: 2083103023 | ER10: 2083103023 | ES10: 2083103023 | ET10: 2083103023 | EU10: 2083103023 | EV10: 2083103023 | EW10: 2083103023 | EX10: 2083103023 | EY10: 2083103023 | EZ10: 2083103023 | FA10: 2083103023 | FB10: =FA10 -> 2083103023 | FC10: 1951485600 | FD10: 1951485600 | FE10: 1951485600 | FF10: 1951485600 | FG10: 1951485600 | FH10: 1951485600 | FI10: 1951485600 | FO10: =FI10 -> 1951485600
B11: Dirección de Obras Hidráulicas | C11: 101236706 | D11: 101236706 | E11: 101236706 | F11: 101236706 | G11: 101236706 | H11: 101236706 | I11: 101236706 | J11: 101236706 | K11: 101236706 | L11: 101236706 | M11: 101236706 | N11: 101236706 | O11: =N11 -> 101236706 | P11: 117398169 | Q11: 117398169 | R11: 117398169 | S11: 117398169 | T11: 117398169 | U11: 117398169 | V11: 117398169 | W11: 117398169 | X11: 117398169 | Y11: 117398169 | Z11: 117398169 | AA11: 117398169 | AB11: =AA11 -> 117398169 | AC11: 127292924 | AD11: 127292924 | AE11: 127292924 | AF11: 127292924 | AG11: 127292924 | AH11: 127292924 | AI11: 127292924 | AJ11: 127292924 | AK11: 127292924 | AL11: 127292924 | AM11: 127292924 | AN11: 127292924 | AO11: =AN11 -> 127292924 | AP11: 121635713 | AQ11: 121635713 | AR11: 121635713 | AS11: 121635713 | AT11: 121635713 | AU11: 121635713 | AV11: 121635713 | AW11: 121635713 | AX11: 121635713 | AY11: 121635713 | AZ11: 121635713 | BA11: 121635713 | BB11: =BA11 -> 121635713 | BC11: 119785354 | BD11: 119785354 | BE11: 119785354 | BF11: 119785354 | BG11: 119785354 | BH11: 119785354 | BI11: 119785354 | BJ11: 119785354 | BK11: 119785354 | BL11: 119785354 | BM11: 119785354 | BN11: 119785354 | BO11: =BN11 -> 119785354 | BP11: 129182602 | BQ11: 129182602 | BR11: 129182602 | BS11: 129182602 | BT11: 129182602 | BU11: 129182602 | BV11: 129182602 | BW11: 129182602 | BX11: 129182602 | BY11: 129182602 | BZ11: 129182602 | CA11: 129182602 | CB11: =CA11 -> 129182602 | CC11: 137671350 | CD11: 137671350 | CE11: 137671350 | CF11: 137671350 | CG11: 137671350 | CH11: 137671350 | CI11: 137671350 | CJ11: 137671350 | CK11: 137671350 | CL11: 137671350 | CM11: 137671350 | CN11: 137671350 | CO11: =CN11 -> 137671350 | CP11: =140801596+100700947 -> 241502543 | CQ11: =140801596+100700947 -> 241502543 | CR11: =140801596+100700947 -> 241502543 | CS11: =140801596+100700947 -> 241502543 | CT11: =140801596+100700947 -> 241502543 | CU11: =140801596+100700947 -> 241502543 | CV11: =140801596+100700947 -> 241502543 | CW11: =140801596+100700947 -> 241502543 | ... DA11: =140801596+100700947 -> 241502543 | DB11: =DA11 -> 241502543 | DC11: =147022684+130812721 -> 277835405 | DD11: =147022684+130812721 -> 277835405 | DE11: =147022684+130812721 -> 277835405 | DF11: =147022684+130812721 -> 277835405 | DG11: =147022684+130812721 -> 277835405 | DH11: =147022684+130812721 -> 277835405 | DI11: =147022684+130812721 -> 277835405 | DJ11: =147022684+130812721 -> 277835405 | ... DN11: =147022684+130812721 -> 277835405 | DO11: =DN11 -> 277835405 | DP11: 293591805 | DQ11: 293591805 | DR11: 293591805 | DS11: 293591805 | DT11: 293591805 | DU11: 293591805 | DV11: 293591805 | DW11: 293591805 | DX11: 293591805 | DY11: 293591805 | DZ11: 293591805 | EA11: 293591805 | EB11: =EA11 -> 293591805 | EC11: 295701947 | ED11: 295701947 | EE11: 295701947 | EF11: 295701947 | EG11: 295701947 | EH11: 295701947 | EI11: 295701947 | EJ11: 295701947 | EK11: 295701947 | EL11: 295701947 | EM11: 295701947 | EN11: 295701947 | EO11: =EN11 -> 295701947 | EP11: 308121429 | EQ11: 308121429 | ER11: 308121429 | ES11: 308121429 | ET11: 308121429 | EU11: 308121429 | EV11: 308121429 | EW11: 308121429 | EX11: 308121429 | EY11: 308121429 | EZ11: 308121429 | FA11: 308121429 | FB11: =FA11 -> 308121429 | FC11: 195906100 | FD11: 195906100 | FE11: 195906100 | FF11: 195906100 | FG11: 195906100 | FH11: 195906100 | FI11: 195906100 | FO11: =FI11 -> 195906100
B12: Subdirección de APR | C12: 49407947 | D12: 49407947 | E12: 49407947 | F12: 49407947 | G12: 49407947 | H12: 49407947 | I12: 49407947 | J12: 49407947 | K12: 49407947 | L12: 49407947 | M12: 49407947 | N12: 49407947 | O12: =N12 -> 49407947 | P12: 68884752 | Q12: 68884752 | R12: 68884752 | S12: 68884752 | T12: 68884752 | U12: 68884752 | V12: 68884752 | W12: 68884752 | X12: 68884752 | Y12: 68884752 | Z12: 68884752 | AA12: 68884752 | AB12: =AA12 -> 68884752 | AC12: 71502372 | AD12: 71502372 | AE12: 71502372 | AF12: 71502372 | AG12: 71502372 | AH12: 71502372 | AI12: 71502372 | AJ12: 71502372 | AK12: 71502372 | AL12: 71502372 | AM12: 71502372 | AN12: 71502372 | AO12: =AN12 -> 71502372 | AP12: 89991483 | AQ12: 89991483 | AR12: 89991483 | AS12: 89991483 | AT12: 89991483 | AU12: 89991483 | AV12: 89991483 | AW12: 89991483 | AX12: 89991483 | AY12: 89991483 | AZ12: 89991483 | BA12: 89991483 | BB12: =BA12 -> 89991483 | BC12: 102433801 | BD12: 102433801 | BE12: 102433801 | BF12: 102433801 | BG12: 102433801 | BH12: 102433801 | BI12: 102433801 | BJ12: 102433801 | BK12: 102433801 | BL12: 102433801 | BM12: 102433801 | BN12: 102433801 | BO12: =BN12 -> 102433801 | BP12: 114691671 | BQ12: 114691671 | BR12: 114691671 | BS12: 114691671 | BT12: 114691671 | BU12: 114691671 | BV12: 114691671 | BW12: 114691671 | BX12: 114691671 | BY12: 114691671 | BZ12: 114691671 | CA12: 114691671 | CB12: =CA12 -> 114691671 | CC12: 135338654 | CD12: 135338654 | CE12: 135338654 | CF12: 135338654 | CG12: 135338654 | CH12: 135338654 | CI12: 135338654 | CJ12: 135338654 | CK12: 135338654 | CL12: 135338654 | CM12: 135338654 | CN12: 135338654 | CO12: =CN12 -> 135338654 | CP12: =142048072+104543895 -> 246591967 | CQ12: =142048072+104543895 -> 246591967 | CR12: =142048072+104543895 -> 246591967 | CS12: =142048072+104543895 -> 246591967 | CT12: =142048072+104543895 -> 246591967 | CU12: =142048072+104543895 -> 246591967 | CV12: =142048072+104543895 -> 246591967 | CW12: =142048072+104543895 -> 246591967 | ... DA12: =142048072+104543895 -> 246591967 | DB12: =DA12 -> 246591967 | DC12: =148440561+129907392 -> 278347953 | DD12: =148440561+129907392 -> 278347953 | DE12: =148440561+129907392 -> 278347953 | DF12: =148440561+129907392 -> 278347953 | DG12: =148440561+129907392 -> 278347953 | DH12: =148440561+129907392 -> 278347953 | DI12: =148440561+129907392 -> 278347953 | DJ12: =148440561+129907392 -> 278347953 | ... DN12: =148440561+129907392 -> 278347953 | DO12: =DN12 -> 278347953 | DP12: 295780655 | DQ12: 295780655 | DR12: 295780655 | DS12: 295780655 | DT12: 295780655 | DU12: 295780655 | DV12: 295780655 | DW12: 295780655 | DX12: 295780655 | DY12: 295780655 | DZ12: 295780655 | EA12: 295780655 | EB12: =EA12 -> 295780655 | EC12: 315696642 | ED12: 315696642 | EE12: 315696642 | EF12: 315696642 | EG12: 315696642 | EH12: 315696642 | EI12: 315696642 | EJ12: 315696642 | EK12: 315696642 | EL12: 315696642 | EM12: 315696642 | EN12: 315696642 | EO12: =EN12 -> 315696642 | EP12: 329603442 | EQ12: 329603442 | ER12: 329603442 | ES12: 329603442 | ET12: 329603442 | EU12: 329603442 | EV12: 329603442 | EW12: 329603442 | EX12: 329603442 | EY12: 329603442 | EZ12: 329603442 | FA12: 329603442 | FB12: =FA12 -> 329603442 | FC12: 290113797 | FD12: 290113797 | FE12: 290113797 | FF12: 290113797 | FG12: 290113797 | FH12: 290113797 | FI12: 290113797 | FO12: =FI12 -> 290113797
B13: Dirección de Obras Portuarias | C13: 55038550 | D13: 55038550 | E13: 55038550 | F13: 55038550 | G13: 55038550 | H13: 55038550 | I13: 55038550 | J13: 55038550 | K13: 55038550 | L13: 55038550 | M13: 55038550 | N13: 55038550 | O13: =N13 -> 55038550 | P13: 63737311 | Q13: 63737311 | R13: 63737311 | S13: 63737311 | T13: 63737311 | U13: 63737311 | V13: 63737311 | W13: 63737311 | X13: 63737311 | Y13: 63737311 | Z13: 63737311 | AA13: 63737311 | AB13: =AA13 -> 63737311 | AC13: 66005341 | AD13: 66005341 | AE13: 66005341 | AF13: 66005341 | AG13: 66005341 | AH13: 66005341 | AI13: 66005341 | AJ13: 66005341 | AK13: 66005341 | AL13: 66005341 | AM13: 66005341 | AN13: 66005341 | AO13: =AN13 -> 66005341 | AP13: 68152361 | AQ13: 68152361 | AR13: 68152361 | AS13: 68152361 | AT13: 68152361 | AU13: 68152361 | AV13: 68152361 | AW13: 68152361 | AX13: 68152361 | AY13: 68152361 | AZ13: 68152361 | BA13: 68152361 | BB13: =BA13 -> 68152361 | BC13: 69097793 | BD13: 69097793 | BE13: 69097793 | BF13: 69097793 | BG13: 69097793 | BH13: 69097793 | BI13: 69097793 | BJ13: 69097793 | BK13: 69097793 | BL13: 69097793 | BM13: 69097793 | BN13: 69097793 | BO13: =BN13 -> 69097793 | BP13: 69888575 | BQ13: 69888575 | BR13: 69888575 | BS13: 69888575 | BT13: 69888575 | BU13: 69888575 | BV13: 69888575 | BW13: 69888575 | BX13: 69888575 | BY13: 69888575 | BZ13: 69888575 | CA13: 69888575 | CB13: =CA13 -> 69888575 | CC13: 71705676 | CD13: 71705676 | CE13: 71705676 | CF13: 71705676 | CG13: 71705676 | CH13: 71705676 | CI13: 71705676 | CJ13: 71705676 | CK13: 71705676 | CL13: 71705676 | CM13: 71705676 | CN13: 71705676 | CO13: =CN13 -> 71705676 | CP13: =73670723+10507533 -> 84178256 | CQ13: =73670723+10507533 -> 84178256 | CR13: =73670723+10507533 -> 84178256 | CS13: =73670723+10507533 -> 84178256 | CT13: =73670723+10507533 -> 84178256 | CU13: =73670723+10507533 -> 84178256 | CV13: =73670723+10507533 -> 84178256 | CW13: =73670723+10507533 -> 84178256 | ... DA13: =73670723+10507533 -> 84178256 | DB13: =DA13 -> 84178256 | DC13: =76882481+23172423 -> 100054904 | DD13: =76882481+23172423 -> 100054904 | DE13: =76882481+23172423 -> 100054904 | DF13: =76882481+23172423 -> 100054904 | DG13: =76882481+23172423 -> 100054904 | DH13: =76882481+23172423 -> 100054904 | DI13: =76882481+23172423 -> 100054904 | DJ13: =76882481+23172423 -> 100054904 | ... DN13: =76882481+23172423 -> 100054904 | DO13: =DN13 -> 100054904 | DP13: 115171552 | DQ13: 115171552 | DR13: 115171552 | DS13: 115171552 | DT13: 115171552 | DU13: 115171552 | DV13: 115171552 | DW13: 115171552 | DX13: 115171552 | DY13: 115171552 | DZ13: 115171552 | EA13: 115171552 | EB13: =EA13 -> 115171552 | EC13: 127117895 | ED13: 127117895 | EE13: 127117895 | EF13: 127117895 | EG13: 127117895 | EH13: 127117895 | EI13: 127117895 | EJ13: 127117895 | EK13: 127117895 | EL13: 127117895 | EM13: 127117895 | EN13: 127117895 | EO13: =EN13 -> 127117895 | EP13: 125417585 | EQ13: 125417585 | ER13: 125417585 | ES13: 125417585 | ET13: 125417585 | EU13: 125417585 | EV13: 125417585 | EW13: 125417585 | EX13: 125417585 | EY13: 125417585 | EZ13: 125417585 | FA13: 125417585 | FB13: =FA13 -> 125417585 | FC13: 109909690 | FD13: 109909690 | FE13: 109909690 | FF13: 109909690 | FG13: 109909690 | FH13: 109909690 | FI13: 109909690 | FO13: =FI13 -> 109909690
B14: Dirección de Aeropuertos | C14: 41285665 | D14: 41285665 | E14: 41285665 | F14: 41285665 | G14: 41285665 | H14: 41285665 | I14: 41285665 | J14: 41285665 | K14: 41285665 | L14: 41285665 | M14: 41285665 | N14: 41285665 | O14: =N14 -> 41285665 | P14: 41009608 | Q14: 41009608 | R14: 41009608 | S14: 41009608 | T14: 41009608 | U14: 41009608 | V14: 41009608 | W14: 41009608 | X14: 41009608 | Y14: 41009608 | Z14: 41009608 | AA14: 41009608 | AB14: =AA14 -> 41009608 | AC14: 43953347 | AD14: 43953347 | AE14: 43953347 | AF14: 43953347 | AG14: 43953347 | AH14: 43953347 | AI14: 43953347 | AJ14: 43953347 | AK14: 43953347 | AL14: 43953347 | AM14: 43953347 | AN14: 43953347 | AO14: =AN14 -> 43953347 | AP14: 45271947 | AQ14: 45271947 | AR14: 45271947 | AS14: 45271947 | AT14: 45271947 | AU14: 45271947 | AV14: 45271947 | AW14: 45271947 | AX14: 45271947 | AY14: 45271947 | AZ14: 45271947 | BA14: 45271947 | BB14: =BA14 -> 45271947 | BC14: 35602336 | BD14: 35602336 | BE14: 35602336 | BF14: 35602336 | BG14: 35602336 | BH14: 35602336 | BI14: 35602336 | BJ14: 35602336 | BK14: 35602336 | BL14: 35602336 | BM14: 35602336 | BN14: 35602336 | BO14: =BN14 -> 35602336 | BP14: 53068499 | BQ14: 53068499 | BR14: 53068499 | BS14: 53068499 | BT14: 53068499 | BU14: 53068499 | BV14: 53068499 | BW14: 53068499 | BX14: 53068499 | BY14: 53068499 | BZ14: 53068499 | CA14: 53068499 | CB14: =CA14 -> 53068499 | CC14: 58584599 | CD14: 58584599 | CE14: 58584599 | CF14: 58584599 | CG14: 58584599 | CH14: 58584599 | CI14: 58584599 | CJ14: 58584599 | CK14: 58584599 | CL14: 58584599 | CM14: 58584599 | CN14: 58584599 | CO14: =CN14 -> 58584599 | CP14: =60144148+46830346 -> 106974494 | CQ14: =60144148+46830346 -> 106974494 | CR14: =60144148+46830346 -> 106974494 | CS14: =60144148+46830346 -> 106974494 | CT14: =60144148+46830346 -> 106974494 | CU14: =60144148+46830346 -> 106974494 | CV14: =60144148+46830346 -> 106974494 | CW14: =60144148+46830346 -> 106974494 | ... DA14: =60144148+46830346 -> 106974494 | DB14: =DA14 -> 106974494 | DC14: =62797413+55033938 -> 117831351 | DD14: =62797413+55033938 -> 117831351 | DE14: =62797413+55033938 -> 117831351 | DF14: =62797413+55033938 -> 117831351 | DG14: =62797413+55033938 -> 117831351 | DH14: =62797413+55033938 -> 117831351 | DI14: =62797413+55033938 -> 117831351 | DJ14: =62797413+55033938 -> 117831351 | ... DN14: =62797413+55033938 -> 117831351 | DO14: =DN14 -> 117831351 | DP14: 135318267 | DQ14: 135318267 | DR14: 135318267 | DS14: 135318267 | DT14: 135318267 | DU14: 135318267 | DV14: 135318267 | DW14: 135318267 | DX14: 135318267 | DY14: 135318267 | DZ14: 135318267 | EA14: 135318267 | EB14: =EA14 -> 135318267 | EC14: 137741639 | ED14: 137741639 | EE14: 137741639 | EF14: 137741639 | EG14: 137741639 | EH14: 137741639 | EI14: 137741639 | EJ14: 137741639 | EK14: 137741639 | EL14: 137741639 | EM14: 137741639 | EN14: 137741639 | EO14: =EN14 -> 137741639 | EP14: 141825431 | EQ14: 141825431 | ER14: 141825431 | ES14: 141825431 | ET14: 141825431 | EU14: 141825431 | EV14: 141825431 | EW14: 141825431 | EX14: 141825431 | EY14: 141825431 | EZ14: 141825431 | FA14: 141825431 | FB14: =FA14 -> 141825431 | FC14: 127610750 | FD14: 127610750 | FE14: 127610750 | FF14: 127610750 | FG14: 127610750 | FH14: 127610750 | FI14: 127610750 | FO14: =FI14 -> 127610750
B15: Dirección de Arquitectura | C15: 26272563 | D15: 26272563 | E15: 26272563 | F15: 26272563 | G15: 26272563 | H15: 26272563 | I15: 26272563 | J15: 26272563 | K15: 26272563 | L15: 26272563 | M15: 26272563 | N15: 26272563 | O15: =N15 -> 26272563 | P15: 28203580 | Q15: 28203580 | R15: 28203580 | S15: 28203580 | T15: 28203580 | U15: 28203580 | V15: 28203580 | W15: 28203580 | X15: 28203580 | Y15: 28203580 | Z15: 28203580 | AA15: 28203580 | AB15: =AA15 -> 28203580 | AC15: 25719874 | AD15: 25719874 | AE15: 25719874 | AF15: 25719874 | AG15: 25719874 | AH15: 25719874 | AI15: 25719874 | AJ15: 25719874 | AK15: 25719874 | AL15: 25719874 | AM15: 25719874 | AN15: 25719874 | AO15: =AN15 -> 25719874 | AP15: 28283754 | AQ15: 28283754 | AR15: 28283754 | AS15: 28283754 | AT15: 28283754 | AU15: 28283754 | AV15: 28283754 | AW15: 28283754 | AX15: 28283754 | AY15: 28283754 | AZ15: 28283754 | BA15: 28283754 | BB15: =BA15 -> 28283754 | BC15: 30504194 | BD15: 30504194 | BE15: 30504194 | BF15: 30504194 | BG15: 30504194 | BH15: 30504194 | BI15: 30504194 | BJ15: 30504194 | BK15: 30504194 | BL15: 30504194 | BM15: 30504194 | BN15: 30504194 | BO15: =BN15 -> 30504194 | BP15: 25853361 | BQ15: 25853361 | BR15: 25853361 | BS15: 25853361 | BT15: 25853361 | BU15: 25853361 | BV15: 25853361 | BW15: 25853361 | BX15: 25853361 | BY15: 25853361 | BZ15: 25853361 | CA15: 25853361 | CB15: =CA15 -> 25853361 | CC15: 22096777 | CD15: 22096777 | CE15: 22096777 | CF15: 22096777 | CG15: 22096777 | CH15: 22096777 | CI15: 22096777 | CJ15: 22096777 | CK15: 22096777 | CL15: 22096777 | CM15: 22096777 | CN15: 22096777 | CO15: =CN15 -> 22096777 | CP15: =11904427+25061381 -> 36965808 | CQ15: =11904427+25061381 -> 36965808 | CR15: =11904427+25061381 -> 36965808 | CS15: =11904427+25061381 -> 36965808 | CT15: =11904427+25061381 -> 36965808 | CU15: =11904427+25061381 -> 36965808 | CV15: =11904427+25061381 -> 36965808 | CW15: =11904427+25061381 -> 36965808 | ... DA15: =11904427+25061381 -> 36965808 | DB15: =DA15 -> 36965808 | DC15: =8974172+32064677 -> 41038849 | DD15: =8974172+32064677 -> 41038849 | DE15: =8974172+32064677 -> 41038849 | DF15: =8974172+32064677 -> 41038849 | DG15: =8974172+32064677 -> 41038849 | DH15: =8974172+32064677 -> 41038849 | DI15: =8974172+32064677 -> 41038849 | DJ15: =8974172+32064677 -> 41038849 | ... DN15: =8974172+32064677 -> 41038849 | DO15: =DN15 -> 41038849 | DP15: 37590026 | DQ15: 37590026 | DR15: 37590026 | DS15: 37590026 | DT15: 37590026 | DU15: 37590026 | DV15: 37590026 | DW15: 37590026 | DX15: 37590026 | DY15: 37590026 | DZ15: 37590026 | EA15: 37590026 | EB15: =EA15 -> 37590026 | EC15: 44570138 | ED15: 44570138 | EE15: 44570138 | EF15: 44570138 | EG15: 44570138 | EH15: 44570138 | EI15: 44570138 | EJ15: 44570138 | EK15: 44570138 | EL15: 44570138 | EM15: 44570138 | EN15: 44570138 | EO15: =EN15 -> 44570138 | EP15: 57109595 | EQ15: 57109595 | ER15: 57109595 | ES15: 57109595 | ET15: 57109595 | EU15: 57109595 | EV15: 57109595 | EW15: 57109595 | EX15: 57109595 | EY15: 57109595 | EZ15: 57109595 | FA15: 57109595 | FB15: =FA15 -> 57109595 | FC15: 30479549 | FD15: 30479549 | FE15: 30479549 | FF15: 30479549 | FG15: 30479549 | FH15: 30479549 | FI15: 30479549 | FO15: =FI15 -> 30479549
B16: Total | C16: =SUM(C10:C15) -> 1080148659 | D16: =SUM(D10:D15) -> 1080148659 | E16: =SUM(E10:E15) -> 1080148659 | F16: =SUM(F10:F15) -> 1080148659 | G16: =SUM(G10:G15) -> 1080148659 | H16: =SUM(H10:H15) -> 1080148659 | I16: =SUM(I10:I15) -> 1080148659 | J16: =SUM(J10:J15) -> 1080148659 | ... FO16: =SUM(FO10:FO15) -> 2705505486
B17: (1) Los años 2021 y 2022 incluyen el Presupuesto Ley del Subtítulo 30, Ítem 10. Fuente: elaboración propia, Dipres.
B19: Presupuesto Vigente de Inversión en Infraestructura Pública del Ministerio de Obras Públicas, 2014-2026 (Subtítulo 31 – Iniciativas de Inversión, miles de pesos)
C20: 2014 | P20: 2015 | AC20: 2016 | AP20: 2017 | BC20: 2018 | BP20: 2019 | CC20: 2020 | CP20: 2021(1) | DC20: 2022(1) | DP20: 2023 | EC20: 2024 | EP20: 2025 | FC20: 2026
B21: Programa | C21: Ene | D21: Feb | E21: Mar | F21: Abr | G21: May | H21: Jun | I21: Jul | J21: Ago | K21: Sep | L21: Oct | M21: Nov | N21: Dic | O21: Total 2014 | P21: Ene | Q21: Feb | R21: Mar | S21: Abr | T21: May | U21: Jun | V21: Jul | W21: Ago | X21: Sep | Y21: Oct | Z21: Nov | AA21: Dic | AB21: Total 2015 | AC21: Ene | AD21: Feb | AE21: Mar | AF21: Abr | AG21: May | AH21: Jun | AI21: Jul | AJ21: Ago | AK21: Sep | AL21: Oct | AM21: Nov | AN21: Dic | AO21: Total 2016 | AP21: Ene | AQ21: Feb | AR21: Mar | AS21: Abr | AT21: May | AU21: Jun | AV21: Jul | AW21: Ago | AX21: Sep | AY21: Oct | AZ21: Nov | BA21: Dic | BB21: Total 2017 | BC21: Ene | BD21: Feb | BE21: Mar | BF21: Abr | BG21: May | BH21: Jun | BI21: Jul | BJ21: Ago | BK21: Sep | BL21: Oct | BM21: Nov | BN21: Dic | BO21: Total 2018 | BP21: Ene | BQ21: Feb | BR21: Mar | BS21: Abr | BT21: May | BU21: Jun | BV21: Jul | BW21: Ago | BX21: Sep | BY21: Oct | BZ21: Nov | CA21: Dic | CB21: Total 2019 | CC21: Ene | CD21: Feb | CE21: Mar | CF21: Abr | CG21: May | CH21: Jun | CI21: Jul | CJ21: Ago | CK21: Sep | CL21: Oct | CM21: Nov | CN21: Dic | CO21: Total 2020 | CP21: Ene | CQ21: Feb | CR21: Mar | CS21: Abr | CT21: May | CU21: Jun | CV21: Jul | CW21: Ago | CX21: Sep | CY21: Oct | CZ21: Nov | DA21: Dic | DB21: Total 2021 | DC21: Ene | DD21: Feb | DE21: Mar | DF21: Abr | DG21: May | DH21: Jun | DI21: Jul | DJ21: Ago | DK21: Sep | DL21: Oct | DM21: Nov | DN21: Dic | DO21: Total 2022 | DP21: Ene | DQ21: Feb | DR21: Mar | DS21: Abr | DT21: May | DU21: Jun | DV21: Jul | DW21: Ago | DX21: Sep | DY21: Oct | DZ21: Nov | EA21: Dic | EB21: Total 2023 | EC21: Ene | ED21: Feb | EE21: Mar | EF21: Abr | EG21: May | EH21: Jun | EI21: Jul | EJ21: Ago | EK21: Sep | EL21: Oct | EM21: Nov | EN21: Dic | EO21: Total 2024 | EP21: Ene | EQ21: Feb | ER21: Mar | ES21: Abr | ET21: May | EU21: Jun | EV21: Jul | EW21: Ago | EX21: Sep | EY21: Oct | EZ21: Nov | FA21: Dic | FB21: Total 2025 | FC21: Ene | FD21: Feb | FE21: Mar | FF21: Abr | FG21: May | FH21: Jun | FI21: Jul | FJ21: Ago | FK21: Sep | FL21: Oct | FM21: Nov | FN21: Dic | FO21: Total 2026
B22: Dirección de Vialidad | C22: 806907228 | D22: 806907228 | E22: 797207228 | F22: 797207228 | G22: 799193228 | H22: 801043262 | I22: 797883262 | J22: 817043262 | K22: 818043262 | L22: 842704970 | M22: 843143806 | N22: 853032416 | O22: =N22 -> 853032416 | P22: 957407656 | Q22: 958801347 | R22: 952446725 | S22: 944486725 | T22: 948962726 | U22: 949105726 | V22: 949005726 | W22: 949071698 | X22: 949071698 | Y22: 949071698 | Z22: 978416698 | AA22: 978378698 | AB22: =AA22 -> 978378698 | AC22: 937156766 | AD22: 930976766 | AE22: 939666557 | AF22: 937705385 | AG22: 937705385 | AH22: 937166385 | AI22: 937166385 | AJ22: 937166385 | AK22: 937166385 | AL22: 937166385 | AM22: 937073385 | AN22: 940884842 | AO22: =AN22 -> 940884842 | AP22: 982538421 | AQ22: 982538421 | AR22: 982260421 | AS22: 982260421 | AT22: 982060421 | AU22: 963745421 | AV22: 963304221 | AW22: 951169721 | AX22: 951169721 | AY22: 934145882 | AZ22: 931388882 | BA22: 909483945 | BB22: =BA22 -> 909483945 | BC22: 998447263 | BD22: 998447263 | BE22: 992502179 | BF22: 997730439 | BG22: 997415248 | BH22: 989715248 | BI22: 987815248 | BJ22: 987280248 | BK22: 987280248 | BL22: 987265248 | BM22: 986833548 | BN22: 903724337 | BO22: =BN22 -> 903724337 | BP22: 1056398949 | BQ22: 1056398949 | BR22: 1056398949 | BS22: 1061857019 | BT22: 1066368519 | BU22: 1061536519 | BV22: 1061502269 | BW22: 1074213648 | BX22: 1085679831 | BY22: 1085679831 | BZ22: 1085679831 | CA22: 1085267877 | CB22: =CA22 -> 1085267877 | CC22: 1148358839 | CD22: 1151054581 | CE22: 1248782581 | CF22: 1248782581 | CG22: 1216917979 | CH22: 1216917979 | CI22: 1216383979 | CJ22: 1216383979 | CK22: 1216383979 | CL22: 1197726086 | CM22: 1197588086 | CN22: 961564167 | CO22: =CN22 -> 961564167 | CP22: 1224421462 | CQ22: 1224421462 | CR22: 1139453884 | CS22: 1067186833 | CT22: 1048239333 | CU22: 1048217333 | CV22: 1048217333 | CW22: 1048116163 | CX22: 1048116163 | CY22: 1035718353 | CZ22: 1035625353 | DA22: =991797481+130932798 -> 1122730279 | DB22: =DA22 -> 1122730279 | DC22: 1220635546 | DD22: 1220635546 | DE22: 1220279119 | DF22: 1220279119 | DG22: 1218682119 | DH22: 1218249119 | DI22: 1092879968 | DJ22: 1092879968 | DK22: 1082339533 | DL22: 1082339533 | DM22: 1081913803 | DN22: 967670999 | DO22: =DN22 -> 967670999 | DP22: 1913855137 | DQ22: 1913855137 | DR22: 1913855137 | DS22: 1893896951 | DT22: 1850161211 | DU22: 1774161211 | DV22: 1774161211 | DW22: 1623406641 | DX22: 1620225968 | DY22: 1542961468 | DZ22: 1542961468 | EA22: 1427470479 | EB22: =EA22 -> 1427470479 | EC22: 2012684680 | ED22: 2012684680 | EE22: 1959842560 | EF22: 1959842560 | EG22: 1959505267 | EH22: 1939427267 | EI22: 1939427267 | EJ22: 1938757501 | EK22: 1937457501 | EL22: 1929646738 | EM22: 1891922336 | EN22: 1608652526 | EO22: =EN22 -> 1608652526 | EP22: 2083103023 | EQ22: 2083103023 | ER22: 2068572694 | ES22: 2068438694 | ET22: 2067139640 | EU22: 1962984489 | EV22: 1968056577 | EW22: 1968056577 | EX22: 1968056577 | EY22: 1968056577 | EZ22: 1968056577 | FA22: 1976677470 | FB22: =FA22 -> 1976677470 | FC22: 1951485600 | FD22: 1951485600 | FE22: 1905464563 | FF22: 1905464563 | FG22: 1817932962 | FH22: 1801311962 | FI22: 1801311962 | FO22: =FI22 -> 1801311962
B23: Dirección de Obras Hidráulicas | C23: 101236706 | D23: 101236706 | E23: 101236706 | F23: 101236706 | G23: 101236706 | H23: 101236706 | I23: 101236706 | J23: 101236706 | K23: 101236706 | L23: 104448787 | M23: 104448787 | N23: 105052138 | O23: =N23 -> 105052138 | P23: 117398169 | Q23: 117398169 | R23: 117398169 | S23: 117398169 | T23: 117398169 | U23: 119398169 | V23: 119398169 | W23: 119398169 | X23: 119398169 | Y23: 126602707 | Z23: 126602707 | AA23: 127586435 | AB23: =AA23 -> 127586435 | AC23: 127292924 | AD23: 127292924 | AE23: 127292924 | AF23: 127292924 | AG23: 127292924 | AH23: 127292924 | AI23: 127292924 | AJ23: 127292924 | AK23: 127292924 | AL23: 127292924 | AM23: 127292924 | AN23: 125791938 | AO23: =AN23 -> 125791938 | AP23: 121635713 | AQ23: 121635713 | AR23: 121635713 | AS23: 121635713 | AT23: 121635713 | AU23: 129989213 | AV23: 129989213 | AW23: 141642213 | AX23: 141642213 | AY23: 147144690 | AZ23: 147144690 | BA23: 146472297 | BB23: =BA23 -> 146472297 | BC23: 119785354 | BD23: 119785354 | BE23: 119835354 | BF23: 119835354 | BG23: 119835354 | BH23: 119835354 | BI23: 119601854 | BJ23: 119601854 | BK23: 121911854 | BL23: 125699985 | BM23: 125699985 | BN23: 120161746 | BO23: =BN23 -> 120161746 | BP23: 129182602 | BQ23: 129182602 | BR23: 129182602 | BS23: 129182602 | BT23: 129182602 | BU23: 129182602 | BV23: 129182602 | BW23: 131234832 | BX23: 140899926 | BY23: 140899926 | BZ23: 140899926 | CA23: 138342165 | CB23: =CA23 -> 138342165 | CC23: 137671350 | CD23: 137671350 | CE23: 152971350 | CF23: 152971350 | CG23: 143861214 | CH23: 143861214 | CI23: 143861214 | CJ23: 143861214 | CK23: 143861214 | CL23: 143861214 | CM23: 143861214 | CN23: 141821958 | CO23: =CN23 -> 141821958 | CP23: 140801596 | CQ23: 140801596 | CR23: 140801596 | CS23: 140801596 | CT23: 133918279 | CU23: 133918279 | CV23: 133918279 | CW23: 133918279 | CX23: 133918279 | CY23: 133918279 | CZ23: 133918279 | DA23: =131504761+8520124 -> 140024885 | DB23: =DA23 -> 140024885 | DC23: 147022684 | DD23: 147022684 | DE23: 147022684 | DF23: 147022684 | DG23: 147022684 | DH23: 147022684 | DI23: 147022684 | DJ23: 146848818 | DK23: 144824178 | DL23: 130697780 | DM23: 130518293 | DN23: 129672445 | DO23: =DN23 -> 129672445 | DP23: 293591805 | DQ23: 293591805 | DR23: 293591805 | DS23: 293591805 | DT23: 293591805 | DU23: 255048822 | DV23: 219099761 | DW23: 212099761 | DX23: 212099761 | DY23: 212099761 | DZ23: 212099761 | EA23: 198709088 | EB23: =EA23 -> 198709088 | EC23: 295701947 | ED23: 295701947 | EE23: 278607232 | EF23: 278607232 | EG23: 278543079 | EH23: 278543079 | EI23: 278543079 | EJ23: 282942267 | EK23: 282942267 | EL23: 282942267 | EM23: 282942267 | EN23: 244313644 | EO23: =EN23 -> 244313644 | EP23: 308121429 | EQ23: 308121429 | ER23: 308121429 | ES23: 308121429 | ET23: 308121429 | EU23: 288121429 | EV23: 288121429 | EW23: 288121429 | EX23: 288121429 | EY23: 284126983 | EZ23: 284126983 | FA23: 255720965 | FB23: =FA23 -> 255720965 | FC23: 195906100 | FD23: 195906100 | FE23: 192119100 | FF23: 192119100 | FG23: 186241917 | FH23: 202307917 | FI23: 202307917 | FO23: =FI23 -> 202307917
B24: Subdirección de APR | C24: 49407947 | D24: 49407947 | E24: 49407947 | F24: 49407947 | G24: 49407947 | H24: 55507947 | I24: 55507947 | J24: 60507947 | K24: 60507947 | L24: 65278980 | M24: 65278980 | N24: 67579947 | O24: =N24 -> 67579947 | P24: 68884752 | Q24: 68884752 | R24: 68884752 | S24: 68884752 | T24: 68884752 | U24: 85940845 | V24: 85940845 | W24: 87740845 | X24: 87740845 | Y24: 88355845 | Z24: 93717760 | AA24: 93689760 | AB24: =AA24 -> 93689760 | AC24: 71502372 | AD24: 71502372 | AE24: 71502372 | AF24: 71502372 | AG24: 71502372 | AH24: 71502372 | AI24: 71502372 | AJ24: 75002372 | AK24: 75002372 | AL24: 75002372 | AM24: 79147193 | AN24: 80579039 | AO24: =AN24 -> 80579039 | AP24: 89991483 | AQ24: 89991483 | AR24: 89991483 | AS24: 89991483 | AT24: 89991483 | AU24: 92696068 | AV24: 92696068 | AW24: 92696068 | AX24: 92696068 | AY24: 98217166 | AZ24: 98217166 | BA24: 100477231 | BB24: =BA24 -> 100477231 | BC24: 102433801 | BD24: 102433801 | BE24: 102433801 | BF24: 102433801 | BG24: 102433801 | BH24: 102433801 | BI24: 102433801 | BJ24: 102433801 | BK24: 102433801 | BL24: 106891813 | BM24: 106891813 | BN24: 102680557 | BO24: =BN24 -> 102680557 | BP24: 114691671 | BQ24: 114691671 | BR24: 114691671 | BS24: 114691671 | BT24: 114691671 | BU24: 114691671 | BV24: 114691671 | BW24: 123071862 | BX24: 118010898 | BY24: 118010898 | BZ24: 118010898 | CA24: 112674850 | CB24: =CA24 -> 112674850 | CC24: 135338654 | CD24: 135338654 | CE24: 135338654 | CF24: 158338654 | CG24: 155319586 | CH24: 155319586 | CI24: 155319586 | CJ24: 155319586 | CK24: 155319586 | CL24: 155319586 | CM24: 155319586 | CN24: 148506367 | CO24: =CN24 -> 148506367 | CP24: 142048072 | CQ24: 142048072 | CR24: 142048072 | CS24: 142048072 | CT24: 160995572 | CU24: 160995572 | CV24: 160995572 | CW24: 160995572 | CX24: 160995572 | CY24: 160995572 | CZ24: 160995572 | DA24: =142300803+21041416 -> 163342219 | DB24: =DA24 -> 163342219 | DC24: 148440561 | DD24: 148440561 | DE24: 148440561 | DF24: 148440561 | DG24: 148440561 | DH24: 148440561 | DI24: 148440561 | DJ24: 148440561 | DK24: 148440561 | DL24: 141404870 | DM24: 141404870 | DN24: 110932143 | DO24: =DN24 -> 110932143 | DP24: 295780655 | DQ24: 295780655 | DR24: 295780655 | DS24: 295780655 | DT24: 295780655 | DU24: 275780655 | DV24: 309887671 | DW24: 309887671 | DX24: 309887671 | DY24: 299857312 | DZ24: 265750296 | EA24: 249472319 | EB24: =EA24 -> 249472319 | EC24: 315696642 | ED24: 315696642 | EE24: 315696642 | EF24: 232705862 | EG24: 232705862 | EH24: 232705862 | EI24: 232705862 | EJ24: 227906674 | EK24: 227906674 | EL24: 227906674 | EM24: 227906674 | EN24: 192186387 | EO24: =EN24 -> 192186387 | EP24: 329603442 | EQ24: 329603442 | ER24: 307603442 | ES24: 307603442 | ET24: 307603442 | EU24: 284751010 | EV24: 284751010 | EW24: 284751010 | EX24: 284751010 | EY24: 273184204 | EZ24: 273184204 | FA24: 234336066 | FB24: =FA24 -> 234336066 | FC24: 290113797 | FD24: 290113797 | FE24: 282113797 | FF24: 282113797 | FG24: 273410383 | FH24: 273410383 | FI24: 273410383 | FO24: =FI24 -> 273410383
B25: Dirección de Obras Portuarias | C25: 55038550 | D25: 55038550 | E25: 55038550 | F25: 55038550 | G25: 55038550 | H25: 55038550 | I25: 56087343 | J25: 56087343 | K25: 56087343 | L25: 56087343 | M25: 56087343 | N25: 55967642 | O25: =N25 -> 55967642 | P25: 63737311 | Q25: 63737311 | R25: 63737311 | S25: 63737311 | T25: 63737311 | U25: 63737311 | V25: 63737311 | W25: 63737311 | X25: 63737311 | Y25: 60537311 | Z25: 66537311 | AA25: 66227311 | AB25: =AA25 -> 66227311 | AC25: 66005341 | AD25: 66005341 | AE25: 66005341 | AF25: 66005341 | AG25: 66005341 | AH25: 66005341 | AI25: 66005341 | AJ25: 66005341 | AK25: 66005341 | AL25: 66005341 | AM25: 66005341 | AN25: 66601585 | AO25: =AN25 -> 66601585 | AP25: 68152361 | AQ25: 68152361 | AR25: 68152361 | AS25: 68152361 | AT25: 68152361 | AU25: 68152361 | AV25: 68152361 | AW25: 68152361 | AX25: 68152361 | AY25: 68292361 | AZ25: 70792361 | BA25: 72233361 | BB25: =BA25 -> 72233361 | BC25: 69097793 | BD25: 69097793 | BE25: 69097793 | BF25: 69097793 | BG25: 69097793 | BH25: 69097793 | BI25: 68963100 | BJ25: 68963100 | BK25: 66653100 | BL25: 64364969 | BM25: 64332418 | BN25: 60805995 | BO25: =BN25 -> 60805995 | BP25: 69888575 | BQ25: 69888575 | BR25: 69888575 | BS25: 69888575 | BT25: 69888575 | BU25: 69888575 | BV25: 69888575 | BW25: 69888575 | BX25: 68888575 | BY25: 68888575 | BZ25: 68888575 | CA25: 62099040 | CB25: =CA25 -> 62099040 | CC25: 71705676 | CD25: 71705676 | CE25: 80110666 | CF25: 80110666 | CG25: 79796573 | CH25: 79796573 | CI25: 74160268 | CJ25: 74160268 | CK25: 74160268 | CL25: 74160268 | CM25: 73045737 | CN25: 71705970 | CO25: =CN25 -> 71705970 | CP25: 73670723 | CQ25: 73670723 | CR25: 73670723 | CS25: 73670723 | CT25: 73670723 | CU25: 73670723 | CV25: 73670723 | CW25: 73670723 | CX25: 73670723 | CY25: 73670723 | CZ25: 73670723 | DA25: =73116242+62000 -> 73178242 | DB25: =DA25 -> 73178242 | DC25: 76882481 | DD25: 76882481 | DE25: 76882481 | DF25: 76882481 | DG25: 76882481 | DH25: 76882481 | DI25: 76882481 | DJ25: 76882481 | DK25: 76882481 | DL25: 76882481 | DM25: 76882481 | DN25: 64614673 | DO25: =DN25 -> 64614673 | DP25: 115171552 | DQ25: 115171552 | DR25: 115171552 | DS25: 115171552 | DT25: 115171552 | DU25: 115171552 | DV25: 115171552 | DW25: 115171552 | DX25: 115171552 | DY25: 108472329 | DZ25: 108472329 | EA25: 104861138 | EB25: =EA25 -> 104861138 | EC25: 127117895 | ED25: 127117895 | EE25: 127117895 | EF25: 127117895 | EG25: 127117895 | EH25: 127117895 | EI25: 127117895 | EJ25: 127117895 | EK25: 127117895 | EL25: 127117895 | EM25: 127117895 | EN25: 123682417 | EO25: =EN25 -> 123682417 | EP25: 125417585 | EQ25: 125417585 | ER25: 139947914 | ES25: 139947914 | ET25: 139947914 | EU25: 139947914 | EV25: 145917564 | EW25: 145917564 | EX25: 145917564 | EY25: 151478816 | EZ25: 151478816 | FA25: 143006856 | FB25: =FA25 -> 143006856 | FC25: 109909690 | FD25: 109909690 | FE25: 109909690 | FF25: 109909690 | FG25: 106612399 | FH25: 106612399 | FI25: 106612399 | FO25: =FI25 -> 106612399
B26: Dirección de Aeropuertos | C26: 41285665 | D26: 41285665 | E26: 41285665 | F26: 41285665 | G26: 41769665 | H26: 41769665 | I26: 41769665 | J26: 43790807 | K26: 43790807 | L26: 44708207 | M26: 44708207 | N26: 45507263 | O26: =N26 -> 45507263 | P26: 41009608 | Q26: 41009608 | R26: 41009608 | S26: 41009608 | T26: 41009608 | U26: 41009608 | V26: 41009608 | W26: 39209608 | X26: 39209608 | Y26: 39209608 | Z26: 38038808 | AA26: 34834080 | AB26: =AA26 -> 34834080 | AC26: 43953347 | AD26: 43953347 | AE26: 43953347 | AF26: 43633347 | AG26: 43633347 | AH26: 43633347 | AI26: 43633347 | AJ26: 43633347 | AK26: 43633347 | AL26: 43171347 | AM26: 43171347 | AN26: 43860342 | AO26: =AN26 -> 43860342 | AP26: 45271947 | AQ26: 45271947 | AR26: 45271947 | AS26: 45271947 | AT26: 45271947 | AU26: 45271947 | AV26: 45271947 | AW26: 45271947 | AX26: 45271947 | AY26: 46889947 | AZ26: 46889947 | BA26: 49070760 | BB26: =BA26 -> 49070760 | BC26: 35602336 | BD26: 35602336 | BE26: 35602336 | BF26: 35602336 | BG26: 35602336 | BH26: 43302336 | BI26: 43302336 | BJ26: 43802336 | BK26: 43802336 | BL26: 43802336 | BM26: 43802336 | BN26: 34299269 | BO26: =BN26 -> 34299269 | BP26: 53068499 | BQ26: 53068499 | BR26: 53068499 | BS26: 53068499 | BT26: 53068499 | BU26: 53068499 | BV26: 53068499 | BW26: 55300713 | BX26: 55300713 | BY26: 55300713 | BZ26: 55300713 | CA26: 54338642 | CB26: =CA26 -> 54338642 | CC26: 58584599 | CD26: 58584599 | CE26: 58584599 | CF26: 66247946 | CG26: 66247946 | CH26: 66247946 | CI26: 66147946 | CJ26: 64991732 | CK26: 64991732 | CL26: 64570095 | CM26: 64570095 | CN26: 58584599 | CO26: =CN26 -> 58584599 | CP26: 60144148 | CQ26: 60144148 | CR26: 60144148 | CS26: 60144148 | CT26: 60144148 | CU26: 60144148 | CV26: 60144148 | CW26: 60144148 | CX26: 60144148 | CY26: 60144148 | CZ26: 60144148 | DA26: =57087148+74000 -> 57161148 | DB26: =DA26 -> 57161148 | DC26: 62797413 | DD26: 62797413 | DE26: 62797413 | DF26: 62797413 | DG26: 62712374 | DH26: 62712374 | DI26: 62487413 | DJ26: 62487413 | DK26: 62487413 | DL26: 62487413 | DM26: 62487413 | DN26: 66143610 | DO26: =DN26 -> 66143610 | DP26: 135318267 | DQ26: 135318267 | DR26: 135318267 | DS26: 135318267 | DT26: 135318267 | DU26: 135318267 | DV26: 135318267 | DW26: 135318267 | DX26: 135318267 | DY26: 131318267 | DZ26: 131318267 | EA26: 123846968 | EB26: =EA26 -> 123846968 | EC26: 137741639 | ED26: 137741639 | EE26: 137741639 | EF26: 135914151 | EG26: 135885801 | EH26: 135885801 | EI26: 135885801 | EJ26: 135885801 | EK26: 135885801 | EL26: 137734161 | EM26: 137734161 | EN26: 121300022 | EO26: =EN26 -> 121300022 | EP26: 141825431 | EQ26: 141825431 | ER26: 141825431 | ES26: 141825431 | ET26: 141825431 | EU26: 141825431 | EV26: 141825431 | EW26: 141825431 | EX26: 141825431 | EY26: 141825431 | EZ26: 141825431 | FA26: 143001334 | FB26: =FA26 -> 143001334 | FC26: 127610750 | FD26: 127610750 | FE26: 127610750 | FF26: 127610750 | FG26: 124345173 | FH26: 124345173 | FI26: 124345173 | FO26: =FI26 -> 124345173
B27: Dirección de Arquitectura | C27: 26272563 | D27: 26272563 | E27: 26955763 | F27: 26955763 | G27: 26955763 | H27: 26955763 | I27: 26955763 | J27: 27252763 | K27: 27252763 | L27: 27252763 | M27: 27558870 | N27: 25516525 | O27: =N27 -> 25516525 | P27: 28203580 | Q27: 28203580 | R27: 28176903 | S27: 28176903 | T27: 28176903 | U27: 22493729 | V27: 22493729 | W27: 22477989 | X27: 22277989 | Y27: 17658451 | Z27: 14124507 | AA27: 12055801 | AB27: =AA27 -> 12055801 | AC27: 25719874 | AD27: 25719874 | AE27: 25719874 | AF27: 25719874 | AG27: 25719874 | AH27: 25684874 | AI27: 25684874 | AJ27: 22184874 | AK27: 19898360 | AL27: 19898360 | AM27: 19898360 | AN27: 16279503 | AO27: =AN27 -> 16279503 | AP27: 28283754 | AQ27: 28283754 | AR27: 28283754 | AS27: 28283754 | AT27: 28283754 | AU27: 28260646 | AV27: 28337248 | AW27: 28337248 | AX27: 28337248 | AY27: 31399972 | AZ27: 31399972 | BA27: 21498175 | BB27: =BA27 -> 21498175 | BC27: 30504194 | BD27: 30504194 | BE27: 30504194 | BF27: 30504194 | BG27: 30445086 | BH27: 30445086 | BI27: 30385624 | BJ27: 30385624 | BK27: 30385624 | BL27: 24302238 | BM27: 24302238 | BN27: 20961721 | BO27: =BN27 -> 20961721 | BP27: 25853361 | BQ27: 25853361 | BR27: 25853361 | BS27: 25853361 | BT27: 25853361 | BU27: 25853361 | BV27: 25853361 | BW27: 21612552 | BX27: 17506566 | BY27: 17506566 | BZ27: 17506566 | CA27: 15189077 | CB27: =CA27 -> 15189077 | CC27: 22096777 | CD27: 22096777 | CE27: 22096777 | CF27: 22096777 | CG27: 8619318 | CH27: 8619318 | CI27: 8619318 | CJ27: 8619318 | CK27: 8619318 | CL27: 8619318 | CM27: 5194154 | CN27: 5194154 | CO27: =CN27 -> 5194154 | CP27: 15515216 | CQ27: 17211034 | CR27: 17211034 | CS27: 17211034 | CT27: 17211034 | CU27: 15949460 | CV27: 15949460 | CW27: 15949460 | CX27: 15514843 | CY27: 15514843 | CZ27: 15514843 | DA27: =7205919+7501242 -> 14707161 | DB27: =DA27 -> 14707161 | DC27: 31608353 | DD27: 31608353 | DE27: 19272005 | DF27: 19272005 | DG27: 19272005 | DH27: 18848017 | DI27: 8974172 | DJ27: 8890172 | DK27: 8890172 | DL27: 8663807 | DM27: 7863807 | DN27: 7392258 | DO27: =DN27 -> 7392258 | DP27: 37590026 | DQ27: 36790026 | DR27: 36790026 | DS27: 36790026 | DT27: 36790026 | DU27: 32790026 | DV27: 32790026 | DW27: 32707536 | DX27: 32707536 | DY27: 31426536 | DZ27: 8720551 | EA27: 8559879 | EB27: =EA27 -> 8559879 | EC27: 44570138 | ED27: 44570138 | EE27: 44570138 | EF27: 44570138 | EG27: 44670138 | EH27: 44670138 | EI27: 44670138 | EJ27: 41933638 | EK27: 41744274 | EL27: 41744274 | EM27: 41673300 | EN27: 33685852 | EO27: =EN27 -> 33685852 | EP27: 57109595 | EQ27: 57109595 | ER27: 84609595 | ES27: 84609595 | ET27: 77572649 | EU27: 77572649 | EV27: 77594122 | EW27: 77456003 | EX27: 77456003 | EY27: 77456003 | EZ27: 77456003 | FA27: 55621639 | FB27: =FA27 -> 55621639 | FC27: 30479549 | FD27: 30479549 | FE27: 30479549 | FF27: 30479549 | FG27: 29565163 | FH27: 29565163 | FI27: 29565163 | FO27: =FI27 -> 29565163
B28: Total | C28: =SUM(C22:C27) -> 1080148659 | D28: =SUM(D22:D27) -> 1080148659 | E28: =SUM(E22:E27) -> 1071131859 | F28: =SUM(F22:F27) -> 1071131859 | G28: =SUM(G22:G27) -> 1073601859 | H28: =SUM(H22:H27) -> 1081551893 | I28: =SUM(I22:I27) -> 1079440686 | J28: =SUM(J22:J27) -> 1105918828 | ... FO28: =SUM(FO22:FO27) -> 2537552997
B29: (1) Los años 2021 y 2022 incluyen el Presupuesto Vigente del Subtítulo 30, Ítem 10. Fuente: elaboración propia, Dipres.
B31: Ejecución de Inversión en Infraestructura Pública del Ministerio de Obras Públicas, 2014-2026 (Subtítulo 31 – Iniciativas de Inversión, miles de pesos)
C32: 2014 | P32: 2015 | AC32: 2016 | AP32: 2017 | BC32: 2018 | BP32: 2019 | CC32: 2020 | CP32: 2021(1) | DC32: 2022(1) | DP32: 2023 | EC32: 2024 | EP32: 2025 | FC32: 2026
B33: Programa | C33: Ene | D33: Feb | E33: Mar | F33: Abr | G33: May | H33: Jun | I33: Jul | J33: Ago | K33: Sep | L33: Oct | M33: Nov | N33: Dic | O33: Total 2014 | P33: Ene | Q33: Feb | R33: Mar | S33: Abr | T33: May | U33: Jun | V33: Jul | W33: Ago | X33: Sep | Y33: Oct | Z33: Nov | AA33: Dic | AB33: Total 2015 | AC33: Ene | AD33: Feb | AE33: Mar | AF33: Abr | AG33: May | AH33: Jun | AI33: Jul | AJ33: Ago | AK33: Sep | AL33: Oct | AM33: Nov | AN33: Dic | AO33: Total 2016 | AP33: Ene | AQ33: Feb | AR33: Mar | AS33: Abr | AT33: May | AU33: Jun | AV33: Jul | AW33: Ago | AX33: Sep | AY33: Oct | AZ33: Nov | BA33: Dic | BB33: Total 2017 | BC33: Ene | BD33: Feb | BE33: Mar | BF33: Abr | BG33: May | BH33: Jun | BI33: Jul | BJ33: Ago | BK33: Sep | BL33: Oct | BM33: Nov | BN33: Dic | BO33: Total 2018 | BP33: Ene | BQ33: Feb | BR33: Mar | BS33: Abr | BT33: May | BU33: Jun | BV33: Jul | BW33: Ago | BX33: Sep | BY33: Oct | BZ33: Nov | CA33: Dic | CB33: Total 2019 | CC33: Ene | CD33: Feb | CE33: Mar | CF33: Abr | CG33: May | CH33: Jun | CI33: Jul | CJ33: Ago | CK33: Sep | CL33: Oct | CM33: Nov | CN33: Dic | CO33: Total 2020 | CP33: Ene | CQ33: Feb | CR33: Mar | CS33: Abr | CT33: May | CU33: Jun | CV33: Jul | CW33: Ago | CX33: Sep | CY33: Oct | CZ33: Nov | DA33: Dic | DB33: Total 2021 | DC33: Ene | DD33: Feb | DE33: Mar | DF33: Abr | DG33: May | DH33: Jun | DI33: Jul | DJ33: Ago | DK33: Sep | DL33: Oct | DM33: Nov | DN33: Dic | DO33: Total 2022 | DP33: Ene | DQ33: Feb | DR33: Mar | DS33: Abr | DT33: May | DU33: Jun | DV33: Jul | DW33: Ago | DX33: Sep | DY33: Oct | DZ33: Nov | EA33: Dic | EB33: Total 2023 | EC33: Ene | ED33: Feb | EE33: Mar | EF33: Abr | EG33: May | EH33: Jun | EI33: Jul | EJ33: Ago | EK33: Sep | EL33: Oct | EM33: Nov | EN33: Dic | EO33: Total 2024 | EP33: Ene | EQ33: Feb | ER33: Mar | ES33: Abr | ET33: May | EU33: Jun | EV33: Jul | EW33: Ago | EX33: Sep | EY33: Oct | EZ33: Nov | FA33: Dic | FB33: Total 2025 | FC33: Ene | FD33: Feb | FE33: Mar | FF33: Abr | FG33: May | FH33: Jun | FI33: Jul | FJ33: Ago | FK33: Sep | FL33: Oct | FM33: Nov | FN33: Dic | FO33: Total 2026
B34: Dirección de Vialidad | C34: 0 | D34: 109495507 | E34: 187847739 | F34: 265238101 | G34: 332568897 | H34: 394278543 | I34: 446664037 | J34: 504805550 | K34: 557993422 | L34: 619454289 | M34: 701289585 | N34: 852007357 | O34: =N34 -> 852007357 | P34: 35691957 | Q34: 115879618 | R34: 210457678 | S34: 292947200 | T34: 361894458 | U34: 419786083 | V34: 476513994 | W34: 546526929 | X34: 608703218 | Y34: 688327936 | Z34: 772280679 | AA34: 976840711 | AB34: =AA34 -> 976840711 | AC34: 40005015 | AD34: 118158110 | AE34: 206609169 | AF34: 287881130 | AG34: 358249243 | AH34: 428512091 | AI34: 493195502 | AJ34: 565430649 | AK34: 635240221 | AL34: 720114806 | AM34: 799381459 | AN34: 939632633 | AO34: =AN34 -> 939632633 | AP34: 40701104 | AQ34: 108107750 | AR34: 184856578 | AS34: 252856020 | AT34: 319104639 | AU34: 374972572 | AV34: 431914072 | AW34: 497890053 | AX34: 572274603 | AY34: 640444837 | AZ34: 725045158 | BA34: 907408172 | BB34: =BA34 -> 907408172 | BC34: 0 | BD34: 80673042 | BE34: 168539648 | BF34: 237340393 | BG34: 309376504 | BH34: 379148992 | BI34: 442209871 | BJ34: 504027341 | BK34: 570803171 | BL34: 654884646 | BM34: 732454087 | BN34: 901443445 | BO34: =BN34 -> 901443445 | BP34: 0 | BQ34: 102696407 | BR34: 193837202 | BS34: 287563262 | BT34: 363596898 | BU34: 432817167 | BV34: 525171083 | BW34: 613755849 | BX34: 681368937 | BY34: 768886920 | BZ34: 859787144 | CA34: 1081677766 | CB34: =CA34 -> 1081677766 | CC34: 0 | CD34: 96871169 | CE34: 193870511 | CF34: 272631717 | CG34: 327561887 | CH34: 418295604 | CI34: 502258190 | CJ34: 574520045 | CK34: 633600171 | CL34: 713927353 | CM34: 800349975 | CN34: 945847843 | CO34: =CN34 -> 945847843 | CP34: 0 | CQ34: 101383549 | CR34: 198441247 | CS34: 284324137 | CT34: 358590676 | CU34: 433048907 | CV34: 503354400 | CW34: 586218042 | CX34: 653892258 | CY34: 714435373 | CZ34: 802149786 | DA34: 979979167 | DB34: =DA34 -> 979979167 | DC34: 0 | DD34: 58153045 | DE34: 139608998 | DF34: 206666427 | DG34: 283374746 | DH34: 345265825 | DI34: 405594742 | DJ34: 472550892 | DK34: 616595780 | DL34: 680714110 | DM34: 760339461 | DN34: 955760345 | DO34: =DN34 -> 955760345 | DP34: 0 | DQ34: 18205266 | DR34: 138456688 | DS34: 309745351 | DT34: 436281161 | DU34: 544941612 | DV34: 643572937 | DW34: 731872328 | DX34: 824719400 | DY34: 940512329 | DZ34: 1088998456 | EA34: 1417380025 | EB34: =EA34 -> 1417380025 | EC34: 0 | ED34: 115017803 | EE34: 245067556 | EF34: 379975864 | EG34: 521874015 | EH34: 774852600 | EI34: 856290603 | EJ34: 943020316 | EK34: 1073272838 | EL34: 1212620083 | EM34: 1411133522 | EN34: 1603559540 | EO34: =EN34 -> 1603559540 | EP34: 1418928 | EQ34: 262166719 | ER34: 478250448 | ES34: 666185288 | ET34: 837833362 | EU34: 982362882 | EV34: 1108324387 | EW34: 1217723031 | EX34: 1369623467 | EY34: 1492337572 | EZ34: 1632445535 | FA34: 1947648753 | FB34: =FA34 -> 1947648753 | FC34: 0 | FD34: 162224034 | FE34: 321332158 | FF34: 469566556 | FG34: 614978745 | FH34: 776558972 | FI34: 909487841 | FO34: =FI34 -> 909487841
B35: Dirección de Obras Hidráulicas | C35: 0 | D35: 0 | E35: 0 | F35: 12849023 | G35: 18502602 | H35: 24001975 | I35: 28200302 | J35: 35581648 | K35: 44712998 | L35: 54749457 | M35: 68221191 | N35: 104714724 | O35: =N35 -> 104714724 | P35: 4135149 | Q35: 12016222 | R35: 22838957 | S35: 31173658 | T35: 38126481 | U35: 48008563 | V35: 54996009 | W35: 62015391 | X35: 73214656 | Y35: 81368537 | Z35: 95966048 | AA35: 127205691 | AB35: =AA35 -> 127205691 | AC35: 1644472 | AD35: 6760437 | AE35: 14482109 | AF35: 20055802 | AG35: 26700349 | AH35: 38755843 | AI35: 45496469 | AJ35: 52480551 | AK35: 60402105 | AL35: 68110654 | AM35: 84499774 | AN35: 125549909 | AO35: =AN35 -> 125549909 | AP35: 1269137 | AQ35: 5677714 | AR35: 11079172 | AS35: 19699660 | AT35: 26881172 | AU35: 36009564 | AV35: 43753678 | AW35: 54111195 | AX35: 65957670 | AY35: 79535288 | AZ35: 98614598 | BA35: 145867704 | BB35: =BA35 -> 145867704 | BC35: 0 | BD35: 8476734 | BE35: 15590064 | BF35: 22689725 | BG35: 31479542 | BH35: 41016085 | BI35: 50471408 | BJ35: 56335889 | BK35: 65509002 | BL35: 73476914 | BM35: 84787919 | BN35: 119645504 | BO35: =BN35 -> 119645504 | BP35: 0 | BQ35: 0 | BR35: 0 | BS35: 14799182 | BT35: 20928761 | BU35: 27050471 | BV35: 36175836 | BW35: 44639401 | BX35: 52882663 | BY35: 68082147 | BZ35: 91945190 | CA35: 132633546 | CB35: =CA35 -> 132633546 | CC35: 0 | CD35: 0 | CE35: 15933925 | CF35: 27347698 | CG35: 34970453 | CH35: 42227599 | CI35: 50004801 | CJ35: 60357141 | CK35: 71496670 | CL35: 87043293 | CM35: 108285783 | CN35: 139288956 | CO35: =CN35 -> 139288956 | CP35: 0 | CQ35: 9524739 | CR35: 18778382 | CS35: 27058037 | CT35: 38359267 | CU35: 46029534 | CV35: 54019806 | CW35: 63431000 | CX35: 74898419 | CY35: 87833845 | CZ35: 101123468 | DA35: 129806818 | DB35: =DA35 -> 129806818 | DC35: 0 | DD35: 2161172 | DE35: 9902695 | DF35: 17446259 | DG35: 23088738 | DH35: 30830389 | DI35: 40520841 | DJ35: 46926966 | DK35: 55522281 | DL35: 68952930 | DM35: 83462172 | DN35: 128495787 | DO35: =DN35 -> 128495787 | DP35: 0 | DQ35: 6431623 | DR35: 21339974 | DS35: 32945027 | DT35: 47577177 | DU35: 63593303 | DV35: 79376685 | DW35: 92813663 | DX35: 104125697 | DY35: 112739918 | DZ35: 129397461 | EA35: 195957467 | EB35: =EA35 -> 195957467 | EC35: 0 | ED35: 6377090 | EE35: 23890040 | EF35: 39902005 | EG35: 58620170 | EH35: 119341758 | EI35: 136670909 | EJ35: 157100022 | EK35: 175138873 | EL35: 193499950 | EM35: 211590153 | EN35: 243896208 | EO35: =EN35 -> 243896208 | EP35: 2068692 | EQ35: 14027617 | ER35: 36168803 | ES35: 53822571 | ET35: 71880596 | EU35: 92473645 | EV35: 108898696 | EW35: 131234326 | EX35: 152827107 | EY35: 173770614 | EZ35: 201417551 | FA35: 252789386 | FB35: =FA35 -> 252789386 | FC35: 0 | FD35: 9585447 | FE35: 24838996 | FF35: 36118123 | FG35: 47381569 | FH35: 59374806 | FI35: 73650703 | FO35: =FI35 -> 73650703
B36: Subdirección de APR | C36: 0 | D36: 0 | E36: 2123137 | F36: 11318242 | G36: 16412231 | H36: 21503320 | I36: 26571960 | J36: 31336635 | K36: 36845348 | L36: 42847765 | M36: 49413111 | N36: 67417598 | O36: =N36 -> 67417598 | P36: 3681645 | Q36: 8539463 | R36: 18555701 | S36: 26344808 | T36: 33283091 | U36: 38882927 | V36: 45906320 | W36: 51669887 | X36: 58317963 | Y36: 63943837 | Z36: 72706421 | AA36: 93526873 | AB36: =AA36 -> 93526873 | AC36: 0 | AD36: 7489256 | AE36: 14608985 | AF36: 20077326 | AG36: 25109701 | AH36: 31740697 | AI36: 36595708 | AJ36: 43957889 | AK36: 48847708 | AL36: 53992956 | AM36: 60335109 | AN36: 80271976 | AO36: =AN36 -> 80271976 | AP36: 0 | AQ36: 7437942 | AR36: 15597962 | AS36: 22904045 | AT36: 29421513 | AU36: 37145004 | AV36: 44696488 | AW36: 52727926 | AX36: 60463520 | AY36: 67026822 | AZ36: 76122310 | BA36: 100202686 | BB36: =BA36 -> 100202686 | BC36: 0 | BD36: 1539829 | BE36: 9980097 | BF36: 15990396 | BG36: 26512540 | BH36: 32634743 | BI36: 38873532 | BJ36: 44503197 | BK36: 51124646 | BL36: 58962002 | BM36: 71960162 | BN36: 101837360 | BO36: =BN36 -> 101837360 | BP36: 0 | BQ36: 8543845 | BR36: 16492779 | BS36: 25420378 | BT36: 33246158 | BU36: 39464017 | BV36: 45418356 | BW36: 54819773 | BX36: 62481533 | BY36: 71071550 | BZ36: 80774307 | CA36: 109754082 | CB36: =CA36 -> 109754082 | CC36: 0 | CD36: 0 | CE36: 14046798 | CF36: 23975486 | CG36: 32933206 | CH36: 44476459 | CI36: 54767019 | CJ36: 64603134 | CK36: 75187064 | CL36: 91643647 | CM36: 112911790 | CN36: 145498589 | CO36: =CN36 -> 145498589 | CP36: 0 | CQ36: 6666332 | CR36: 21867716 | CS36: 35651365 | CT36: 47287710 | CU36: 58269490 | CV36: 67196224 | CW36: 76194121 | CX36: 86850665 | CY36: 100525220 | CZ36: 114625930 | DA36: 138846156 | DB36: =DA36 -> 138846156 | DC36: 0 | DD36: 0 | DE36: 7252609 | DF36: 18124947 | DG36: 26400403 | DH36: 33265233 | DI36: 41025465 | DJ36: 48098388 | DK36: 56515227 | DL36: 64874125 | DM36: 77789880 | DN36: 108974292 | DO36: =DN36 -> 108974292 | DP36: 0 | DQ36: 2303161 | DR36: 29583551 | DS36: 49465414 | DT36: 68683761 | DU36: 84807286 | DV36: 102765834 | DW36: 120298096 | DX36: 135987986 | DY36: 156018552 | DZ36: 183226741 | EA36: 244037387 | EB36: =EA36 -> 244037387 | EC36: 0 | ED36: 11025007 | EE36: 25342159 | EF36: 43422173 | EG36: 59731566 | EH36: 80871277 | EI36: 90939725 | EJ36: 104887838 | EK36: 121545898 | EL36: 134718420 | EM36: 150454729 | EN36: 189747396 | EO36: =EN36 -> 189747396 | EP36: 2010108 | EQ36: 18132777 | ER36: 36591973 | ES36: 55560502 | ET36: 73627660 | EU36: 93134581 | EV36: 109996503 | EW36: 127458124 | EX36: 147026821 | EY36: 167611651 | EZ36: 186253362 | FA36: 231742834 | FB36: =FA36 -> 231742834 | FC36: 0 | FD36: 19469514 | FE36: 40366706 | FF36: 60258504 | FG36: 79539794 | FH36: 99543928 | FI36: 119758712 | FO36: =FI36 -> 119758712
B37: Dirección de Obras Portuarias | C37: 0 | D37: 7450429 | E37: 13193802 | F37: 18293446 | G37: 22626920 | H37: 26415122 | I37: 30372078 | J37: 34891139 | K37: 39425450 | L37: 44372578 | M37: 49575185 | N37: 55862229 | O37: =N37 -> 55862229 | P37: 2407710 | Q37: 5910699 | R37: 9882174 | S37: 13108974 | T37: 15732284 | U37: 19553181 | V37: 24349229 | W37: 30187369 | X37: 35622534 | Y37: 42257897 | Z37: 50178950 | AA37: 66160697 | AB37: =AA37 -> 66160697 | AC37: 5244325 | AD37: 10266262 | AE37: 16219822 | AF37: 21648618 | AG37: 27387993 | AH37: 33761936 | AI37: 38844614 | AJ37: 43222678 | AK37: 47526334 | AL37: 53352145 | AM37: 57473232 | AN37: 66424573 | AO37: =AN37 -> 66424573 | AP37: 5239069 | AQ37: 9634272 | AR37: 14245421 | AS37: 19009524 | AT37: 23475477 | AU37: 27885034 | AV37: 32415133 | AW37: 37252785 | AX37: 41640505 | AY37: 48309815 | AZ37: 56401587 | BA37: 72170849 | BB37: =BA37 -> 72170849 | BC37: 3794605 | BD37: 8887650 | BE37: 13076526 | BF37: 16300776 | BG37: 19258274 | BH37: 22907994 | BI37: 26103926 | BJ37: 29804745 | BK37: 33918911 | BL37: 41523749 | BM37: 48730813 | BN37: 60699920 | BO37: =BN37 -> 60699920 | BP37: 0 | BQ37: 4959518 | BR37: 8623561 | BS37: 12610274 | BT37: 15677706 | BU37: 18815030 | BV37: 21774664 | BW37: 25278290 | BX37: 30144344 | BY37: 37764237 | BZ37: 48335683 | CA37: 61662087 | CB37: =CA37 -> 61662087 | CC37: 2667250 | CD37: 10044327 | CE37: 16258240 | CF37: 20216983 | CG37: 23232514 | CH37: 27197118 | CI37: 32144233 | CJ37: 38307654 | CK37: 44833503 | CL37: 52317209 | CM37: 59444391 | CN37: 71411475 | CO37: =CN37 -> 71411475 | CP37: 3825181 | CQ37: 8964985 | CR37: 15055911 | CS37: 20048280 | CT37: 26317106 | CU37: 31688072 | CV37: 36444446 | CW37: 42554997 | CX37: 48413592 | CY37: 53825635 | CZ37: 60943515 | DA37: 72860066 | DB37: =DA37 -> 72860066 | DC37: 0 | DD37: 6831369 | DE37: 12735359 | DF37: 17744111 | DG37: 21871504 | DH37: 26590987 | DI37: 29792299 | DJ37: 33545628 | DK37: 38180759 | DL37: 44900676 | DM37: 49875536 | DN37: 63389831 | DO37: =DN37 -> 63389831 | DP37: 0 | DQ37: 9852119 | DR37: 18996634 | DS37: 27251266 | DT37: 35013028 | DU37: 43003795 | DV37: 50751095 | DW37: 58156520 | DX37: 66259094 | DY37: 74165411 | DZ37: 86349973 | EA37: 104365673 | EB37: =EA37 -> 104365673 | EC37: 0 | ED37: 14355305 | EE37: 24004310 | EF37: 34981155 | EG37: 44329314 | EH37: 57184018 | EI37: 67266994 | EJ37: 77238997 | EK37: 87016951 | EL37: 98032816 | EM37: 108856624 | EN37: 122976500 | EO37: =EN37 -> 122976500 | EP37: 11343929 | EQ37: 22880886 | ER37: 31954442 | ES37: 40743206 | ET37: 50003253 | EU37: 61155170 | EV37: 73000387 | EW37: 82403582 | EX37: 91424463 | EY37: 102261627 | EZ37: 115278067 | FA37: 140810158 | FB37: =FA37 -> 140810158 | FC37: 5334724 | FD37: 18823694 | FE37: 29721986 | FF37: 39558533 | FG37: 50252046 | FH37: 57851838 | FI37: 65221155 | FO37: =FI37 -> 65221155
B38: Dirección de Aeropuertos | C38: 0 | D38: 3153629 | E38: 6333205 | F38: 10206572 | G38: 13380354 | H38: 15204069 | I38: 18935291 | J38: 22710901 | K38: 27092685 | L38: 30577580 | M38: 35648923 | N38: 45255795 | O38: =N38 -> 45255795 | P38: 2264225 | Q38: 4541595 | R38: 8911305 | S38: 11084249 | T38: 12623921 | U38: 14560264 | V38: 16520085 | W38: 18590642 | X38: 20057752 | Y38: 21728752 | Z38: 25609920 | AA38: 34520713 | AB38: =AA38 -> 34520713 | AC38: 1294891 | AD38: 3230391 | AE38: 6707771 | AF38: 9854285 | AG38: 12462996 | AH38: 14578473 | AI38: 18444600 | AJ38: 21445778 | AK38: 24594268 | AL38: 28879386 | AM38: 34953390 | AN38: 43649710 | AO38: =AN38 -> 43649710 | AP38: 1701148 | AQ38: 4989185 | AR38: 8908051 | AS38: 11712516 | AT38: 15151391 | AU38: 18220822 | AV38: 21901116 | AW38: 24950352 | AX38: 28607785 | AY38: 32972810 | AZ38: 38268304 | BA38: 48861397 | BB38: =BA38 -> 48861397 | BC38: 2321145 | BD38: 7642086 | BE38: 9990190 | BF38: 11333440 | BG38: 13219960 | BH38: 14644250 | BI38: 17565409 | BJ38: 19503920 | BK38: 21067209 | BL38: 23658290 | BM38: 27309272 | BN38: 34089377 | BO38: =BN38 -> 34089377 | BP38: 0 | BQ38: 2918777 | BR38: 8655533 | BS38: 12471449 | BT38: 15294277 | BU38: 17720411 | BV38: 19806946 | BW38: 21796811 | BX38: 24959259 | BY38: 30963792 | BZ38: 38358537 | CA38: 53939967 | CB38: =CA38 -> 53939967 | CC38: 303665 | CD38: 4282732 | CE38: 8015041 | CF38: 10962085 | CG38: 13797288 | CH38: 16103675 | CI38: 17499070 | CJ38: 18841178 | CK38: 20956225 | CL38: 26897713 | CM38: 39607854 | CN38: 58248413 | CO38: =CN38 -> 58248413 | CP38: 5238741 | CQ38: 10943486 | CR38: 18457428 | CS38: 27356255 | CT38: 33912011 | CU38: 39164650 | CV38: 41928107 | CW38: 45570244 | CX38: 48624248 | CY38: 50023582 | CZ38: 51847218 | DA38: 56686190 | DB38: =DA38 -> 56686190 | DC38: 839540 | DD38: 1930275 | DE38: 5065401 | DF38: 7642514 | DG38: 8217159 | DH38: 9505928 | DI38: 12107075 | DJ38: 14547935 | DK38: 17494128 | DL38: 27673768 | DM38: 40027308 | DN38: 65439532 | DO38: =DN38 -> 65439532 | DP38: 0 | DQ38: 13210998 | DR38: 26801255 | DS38: 34566510 | DT38: 40280060 | DU38: 46287111 | DV38: 50590434 | DW38: 60655017 | DX38: 67496353 | DY38: 74862435 | DZ38: 89687930 | EA38: 122803224 | EB38: =EA38 -> 122803224 | EC38: 0 | ED38: 10801902 | EE38: 21691356 | EF38: 33317068 | EG38: 44122345 | EH38: 59135603 | EI38: 66601938 | EJ38: 74752243 | EK38: 86852892 | EL38: 99348688 | EM38: 111690617 | EN38: 121236421 | EO38: =EN38 -> 121236421 | EP38: 5480453 | EQ38: 18789767 | ER38: 33876924 | ES38: 51049771 | ET38: 63060218 | EU38: 70081917 | EV38: 74458174 | EW38: 78656297 | EX38: 86517922 | EY38: 100099974 | EZ38: 112429460 | FA38: 142638019 | FB38: =FA38 -> 142638019 | FC38: 8605874 | FD38: 22342962 | FE38: 30219385 | FF38: 33540799 | FG38: 36963751 | FH38: 51185776 | FI38: 55356746 | FO38: =FI38 -> 55356746
B39: Dirección de Arquitectura | C39: 0 | D39: 57591 | E39: 2904221 | F39: 4181638 | G39: 8599963 | H39: 17353835 | I39: 19639160 | J39: 20130486 | K39: 20287005 | L39: 20566868 | M39: 23635450 | N39: 25363607 | O39: =N39 -> 25363607 | P39: 298118 | Q39: 929191 | R39: 1348993 | S39: 1710614 | T39: 1997677 | U39: 2275739 | V39: 3467099 | W39: 4389984 | X39: 5606304 | Y39: 7175069 | Z39: 9072251 | AA39: 11974051 | AB39: =AA39 -> 11974051 | AC39: 0 | AD39: 1722584 | AE39: 2423350 | AF39: 4116924 | AG39: 5773095 | AH39: 7187484 | AI39: 8310819 | AJ39: 8643566 | AK39: 10276104 | AL39: 11991317 | AM39: 13830342 | AN39: 16091959 | AO39: =AN39 -> 16091959 | AP39: 0 | AQ39: 1930720 | AR39: 3039686 | AS39: 4280290 | AT39: 5593090 | AU39: 8744083 | AV39: 10181331 | AW39: 11686410 | AX39: 13119459 | AY39: 14292697 | AZ39: 15490579 | BA39: 21241804 | BB39: =BA39 -> 21241804 | BC39: 0 | BD39: 5886400 | BE39: 7481295 | BF39: 8719920 | BG39: 11153942 | BH39: 12155230 | BI39: 13134856 | BJ39: 14455606 | BK39: 16064457 | BL39: 17132589 | BM39: 17904381 | BN39: 20784765 | BO39: =BN39 -> 20784765 | BP39: 0 | BQ39: 1041613 | BR39: 1825993 | BS39: 2954492 | BT39: 3961108 | BU39: 4263265 | BV39: 5067001 | BW39: 5568722 | BX39: 6156946 | BY39: 7114240 | BZ39: 12100538 | CA39: 14179880 | CB39: =CA39 -> 14179880 | CC39: 0 | CD39: 30830 | CE39: 126373 | CF39: 260932 | CG39: 271532 | CH39: 391694 | CI39: 448090 | CJ39: 1130221 | CK39: 1726167 | CL39: 2486239 | CM39: 3563594 | CN39: 4911613 | CO39: =CN39 -> 4911613 | CP39: 0 | CQ39: 185308 | CR39: 472311 | CS39: 867432 | CT39: 1160606 | CU39: 1516702 | CV39: 2083480 | CW39: 2750574 | CX39: 3861743 | CY39: 4604946 | CZ39: 5590277 | DA39: 7136830 | DB39: =DA39 -> 7136830 | DC39: 0 | DD39: 0 | DE39: 112783 | DF39: 865235 | DG39: 1090968 | DH39: 1329914 | DI39: 1964401 | DJ39: 2518748 | DK39: 3753691 | DL39: 4505699 | DM39: 5158128 | DN39: 6961523 | DO39: =DN39 -> 6961523 | DP39: 0 | DQ39: 14295 | DR39: 519418 | DS39: 818017 | DT39: 1410647 | DU39: 2049207 | DV39: 2506834 | DW39: 3618243 | DX39: 4988476 | DY39: 5883654 | DZ39: 7168509 | EA39: 8421473 | EB39: =EA39 -> 8421473 | EC39: 0 | ED39: 1265774 | EE39: 2147162 | EF39: 4222816 | EG39: 6702483 | EH39: 11199330 | EI39: 13041635 | EJ39: 16175866 | EK39: 20074880 | EL39: 23775698 | EM39: 27727701 | EN39: 33523348 | EO39: =EN39 -> 33523348 | EP39: 1010340 | EQ39: 5400393 | ER39: 9140892 | ES39: 13609867 | ET39: 16763840 | EU39: 19193589 | EV39: 22131755 | EW39: 27614100 | EX39: 31105744 | EY39: 35933608 | EZ39: 40868830 | FA39: 48235342 | FB39: =FA39 -> 48235342 | FC39: 506557 | FD39: 3068948 | FE39: 4760248 | FF39: 6527517 | FG39: 9351673 | FH39: 11151630 | FI39: 13543806 | FO39: =FI39 -> 13543806
B40: Total | C40: =SUM(C34:C39) -> 0 | D40: =SUM(D34:D39) -> 120157156 | E40: =SUM(E34:E39) -> 212402104 | F40: =SUM(F34:F39) -> 322087022 | G40: =SUM(G34:G39) -> 412090967 | H40: =SUM(H34:H39) -> 498756864 | I40: =SUM(I34:I39) -> 570382828 | J40: =SUM(J34:J39) -> 649456359 | ... FO40: =SUM(FO34:FO39) -> 1237018963
B41: Fuente: elaboración propia, Dipres.
B44: Subtítulo 29 – Adquisición de Activos No Financieros
B46: Presupuesto Ley de Inversión en Infraestructura Pública del Ministerio de Obras Públicas, 2014-2026 (Subtítulo 29 – Adquisición de Activos No Financieros, miles de pesos)
C47: 2014 | P47: 2015 | AC47: 2016 | AP47: 2017 | BC47: 2018 | BP47: 2019 | CC47: 2020 | CP47: 2021 | DC47: 2022 | DP47: 2023 | EC47: 2024 | EP47: 2025 | FC47: 2026
B48: Programa | C48: Ene | D48: Feb | E48: Mar | F48: Abr | G48: May | H48: Jun | I48: Jul | J48: Ago | K48: Sep | L48: Oct | M48: Nov | N48: Dic | O48: Total 2014 | P48: Ene | Q48: Feb | R48: Mar | S48: Abr | T48: May | U48: Jun | V48: Jul | W48: Ago | X48: Sep | Y48: Oct | Z48: Nov | AA48: Dic | AB48: Total 2015 | AC48: Ene | AD48: Feb | AE48: Mar | AF48: Abr | AG48: May | AH48: Jun | AI48: Jul | AJ48: Ago | AK48: Sep | AL48: Oct | AM48: Nov | AN48: Dic | AO48: Total 2016 | AP48: Ene | AQ48: Feb | AR48: Mar | AS48: Abr | AT48: May | AU48: Jun | AV48: Jul | AW48: Ago | AX48: Sep | AY48: Oct | AZ48: Nov | BA48: Dic | BB48: Total 2017 | BC48: Ene | BD48: Feb | BE48: Mar | BF48: Abr | BG48: May | BH48: Jun | BI48: Jul | BJ48: Ago | BK48: Sep | BL48: Oct | BM48: Nov | BN48: Dic | BO48: Total 2018 | BP48: Ene | BQ48: Feb | BR48: Mar | BS48: Abr | BT48: May | BU48: Jun | BV48: Jul | BW48: Ago | BX48: Sep | BY48: Oct | BZ48: Nov | CA48: Dic | CB48: Total 2019 | CC48: Ene | CD48: Feb | CE48: Mar | CF48: Abr | CG48: May | CH48: Jun | CI48: Jul | CJ48: Ago | CK48: Sep | CL48: Oct | CM48: Nov | CN48: Dic | CO48: Total 2020 | CP48: Ene | CQ48: Feb | CR48: Mar | CS48: Abr | CT48: May | CU48: Jun | CV48: Jul | CW48: Ago | CX48: Sep | CY48: Oct | CZ48: Nov | DA48: Dic | DB48: Total 2021 | DC48: Ene | DD48: Feb | DE48: Mar | DF48: Abr | DG48: May | DH48: Jun | DI48: Jul | DJ48: Ago | DK48: Sep | DL48: Oct | DM48: Nov | DN48: Dic | DO48: Total 2022 | DP48: Ene | DQ48: Feb | DR48: Mar | DS48: Abr | DT48: May | DU48: Jun | DV48: Jul | DW48: Ago | DX48: Sep | DY48: Oct | DZ48: Nov | EA48: Dic | EB48: Total 2023 | EC48: Ene | ED48: Feb | EE48: Mar | EF48: Abr | EG48: May | EH48: Jun | EI48: Jul | EJ48: Ago | EK48: Sep | EL48: Oct | EM48: Nov | EN48: Dic | EO48: Total 2024 | EP48: Ene | EQ48: Feb | ER48: Mar | ES48: Abr | ET48: May | EU48: Jun | EV48: Jul | EW48: Ago | EX48: Sep | EY48: Oct | EZ48: Nov | FA48: Dic | FB48: Total 2025 | FC48: Ene | FD48: Feb | FE48: Mar | FF48: Abr | FG48: May | FH48: Jun | FI48: Jul | FJ48: Ago | FK48: Sep | FL48: Oct | FM48: Nov | FN48: Dic | FO48: Total 2026
B49: Dirección de Vialidad | C49: 2953248 | D49: 2953248 | E49: 2953248 | F49: 2953248 | G49: 2953248 | H49: 2953248 | I49: 2953248 | J49: 2953248 | K49: 2953248 | L49: 2953248 | M49: 2953248 | N49: 2953248 | O49: =N49 -> 2953248 | P49: 1753030 | Q49: 1753030 | R49: 1753030 | S49: 1753030 | T49: 1753030 | U49: 1753030 | V49: 1753030 | W49: 1753030 | X49: 1753030 | Y49: 1753030 | Z49: 1753030 | AA49: 1753030 | AB49: =AA49 -> 1753030 | AC49: 1791359 | AD49: 1791359 | AE49: 1791359 | AF49: 1791359 | AG49: 1791359 | AH49: 1791359 | AI49: 1791359 | AJ49: 1791359 | AK49: 1791359 | AL49: 1791359 | AM49: 1791359 | AN49: 1791359 | AO49: =AN49 -> 1791359 | AP49: 1779405 | AQ49: 1779405 | AR49: 1779405 | AS49: 1779405 | AT49: 1779405 | AU49: 1779405 | AV49: 1779405 | AW49: 1779405 | AX49: 1779405 | AY49: 1779405 | AZ49: 1779405 | BA49: 1779405 | BB49: =BA49 -> 1779405 | BC49: 1606877 | BD49: 1606877 | BE49: 1606877 | BF49: 1606877 | BG49: 1606877 | BH49: 1606877 | BI49: 1606877 | BJ49: 1606877 | BK49: 1606877 | BL49: 1606877 | BM49: 1606877 | BN49: 1606877 | BO49: =BN49 -> 1606877 | BP49: 1639746 | BQ49: 1639746 | BR49: 1639746 | BS49: 1639746 | BT49: 1639746 | BU49: 1639746 | BV49: 1639746 | BW49: 1639746 | BX49: 1639746 | BY49: 1639746 | BZ49: 1639746 | CA49: 1639746 | CB49: =CA49 -> 1639746 | CC49: 1704539 | CD49: 1704539 | CE49: 1704539 | CF49: 1704539 | CG49: 1704539 | CH49: 1704539 | CI49: 1704539 | CJ49: 1704539 | CK49: 1704539 | CL49: 1704539 | CM49: 1704539 | CN49: 1704539 | CO49: =CN49 -> 1704539 | CP49: 1930914 | CQ49: 1930914 | CR49: 1930914 | CS49: 1930914 | CT49: 1930914 | CU49: 1930914 | CV49: 1930914 | CW49: 1930914 | CX49: 1930914 | CY49: 1930914 | CZ49: 1930914 | DA49: 1930914 | DB49: =DA49 -> 1930914 | DC49: 298233 | DD49: 298233 | DE49: 298233 | DF49: 298233 | DG49: 298233 | DH49: 298233 | DI49: 298233 | DJ49: 298233 | DK49: 298233 | DL49: 298233 | DM49: 298233 | DN49: 298233 | DO49: =DN49 -> 298233 | DP49: 22089448 | DQ49: 22089448 | DR49: 22089448 | DS49: 22089448 | DT49: 22089448 | DU49: 22089448 | DV49: 22089448 | DW49: 22089448 | DX49: 22089448 | DY49: 22089448 | DZ49: 22089448 | EA49: 22089448 | EB49: =EA49 -> 22089448 | EC49: 1135861 | ED49: 1135861 | EE49: 1135861 | EF49: 1135861 | EG49: 1135861 | EH49: 1135861 | EI49: 1135861 | EJ49: 1135861 | EK49: 1135861 | EL49: 1135861 | EM49: 1135861 | EN49: 1135861 | EO49: =EN49 -> 1135861 | EP49: 6540884 | EQ49: 6540884 | ER49: 6540884 | ES49: 6540884 | ET49: 6540884 | EU49: 6540884 | EV49: 6540884 | EW49: 6540884 | EX49: 6540884 | EY49: 6540884 | EZ49: 6540884 | FA49: 6540884 | FB49: =FA49 -> 6540884 | FC49: 1062955 | FD49: 1062955 | FE49: 1062955 | FF49: 1062955 | FG49: 1062955 | FH49: 1062955 | FI49: 1062955 | FO49: =FI49 -> 1062955
B50: Dirección de Obras Hidráulicas | C50: 381750 | D50: 381750 | E50: 381750 | F50: 381750 | G50: 381750 | H50: 381750 | I50: 381750 | J50: 381750 | K50: 381750 | L50: 381750 | M50: 381750 | N50: 381750 | O50: =N50 -> 381750 | P50: 362280 | Q50: 362280 | R50: 362280 | S50: 362280 | T50: 362280 | U50: 362280 | V50: 362280 | W50: 362280 | X50: 362280 | Y50: 362280 | Z50: 362280 | AA50: 362280 | AB50: =AA50 -> 362280 | AC50: 327142 | AD50: 327142 | AE50: 327142 | AF50: 327142 | AG50: 327142 | AH50: 327142 | AI50: 327142 | AJ50: 327142 | AK50: 327142 | AL50: 327142 | AM50: 327142 | AN50: 327142 | AO50: =AN50 -> 327142 | AP50: 174624 | AQ50: 174624 | AR50: 174624 | AS50: 174624 | AT50: 174624 | AU50: 174624 | AV50: 174624 | AW50: 174624 | AX50: 174624 | AY50: 174624 | AZ50: 174624 | BA50: 174624 | BB50: =BA50 -> 174624 | BC50: 139517 | BD50: 139517 | BE50: 139517 | BF50: 139517 | BG50: 139517 | BH50: 139517 | BI50: 139517 | BJ50: 139517 | BK50: 139517 | BL50: 139517 | BM50: 139517 | BN50: 139517 | BO50: =BN50 -> 139517 | BP50: 115465 | BQ50: 115465 | BR50: 115465 | BS50: 115465 | BT50: 115465 | BU50: 115465 | BV50: 115465 | BW50: 115465 | BX50: 115465 | BY50: 115465 | BZ50: 115465 | CA50: 115465 | CB50: =CA50 -> 115465 | CC50: 188388 | CD50: 188388 | CE50: 188388 | CF50: 188388 | CG50: 188388 | CH50: 188388 | CI50: 188388 | CJ50: 188388 | CK50: 188388 | CL50: 188388 | CM50: 188388 | CN50: 188388 | CO50: =CN50 -> 188388 | CP50: 128859 | CQ50: 128859 | CR50: 128859 | CS50: 128859 | CT50: 128859 | CU50: 128859 | CV50: 128859 | CW50: 128859 | CX50: 128859 | CY50: 128859 | CZ50: 128859 | DA50: 128859 | DB50: =DA50 -> 128859 | DC50: 130362 | DD50: 130362 | DE50: 130362 | DF50: 130362 | DG50: 130362 | DH50: 130362 | DI50: 130362 | DJ50: 130362 | DK50: 130362 | DL50: 130362 | DM50: 130362 | DN50: 130362 | DO50: =DN50 -> 130362 | DP50: 647086 | DQ50: 647086 | DR50: 647086 | DS50: 647086 | DT50: 647086 | DU50: 647086 | DV50: 647086 | DW50: 647086 | DX50: 647086 | DY50: 647086 | DZ50: 647086 | EA50: 647086 | EB50: =EA50 -> 647086 | EC50: 856525 | ED50: 856525 | EE50: 856525 | EF50: 856525 | EG50: 856525 | EH50: 856525 | EI50: 856525 | EJ50: 856525 | EK50: 856525 | EL50: 856525 | EM50: 856525 | EN50: 856525 | EO50: =EN50 -> 856525 | EP50: 1233864 | EQ50: 1233864 | ER50: 1233864 | ES50: 1233864 | ET50: 1233864 | EU50: 1233864 | EV50: 1233864 | EW50: 1233864 | EX50: 1233864 | EY50: 1233864 | EZ50: 1233864 | FA50: 1233864 | FB50: =FA50 -> 1233864 | FC50: 651088 | FD50: 651088 | FE50: 651088 | FF50: 651088 | FG50: 651088 | FH50: 651088 | FI50: 651088 | FO50: =FI50 -> 651088
B51: Subdirección de APR | C51: 40007 | D51: 40007 | E51: 40007 | F51: 40007 | G51: 40007 | H51: 40007 | I51: 40007 | J51: 40007 | K51: 40007 | L51: 40007 | M51: 40007 | N51: 40007 | O51: =N51 -> 40007 | P51: 78467 | Q51: 78467 | R51: 78467 | S51: 78467 | T51: 78467 | U51: 78467 | V51: 78467 | W51: 78467 | X51: 78467 | Y51: 78467 | Z51: 78467 | AA51: 78467 | AB51: =AA51 -> 78467 | AC51: 62947 | AD51: 62947 | AE51: 62947 | AF51: 62947 | AG51: 62947 | AH51: 62947 | AI51: 62947 | AJ51: 62947 | AK51: 62947 | AL51: 62947 | AM51: 62947 | AN51: 62947 | AO51: =AN51 -> 62947 | AP51: 49257 | AQ51: 49257 | AR51: 49257 | AS51: 49257 | AT51: 49257 | AU51: 49257 | AV51: 49257 | AW51: 49257 | AX51: 49257 | AY51: 49257 | AZ51: 49257 | BA51: 49257 | BB51: =BA51 -> 49257 | BC51: 610722 | BD51: 610722 | BE51: 610722 | BF51: 610722 | BG51: 610722 | BH51: 610722 | BI51: 610722 | BJ51: 610722 | BK51: 610722 | BL51: 610722 | BM51: 610722 | BN51: 610722 | BO51: =BN51 -> 610722 | BP51: 166534 | BQ51: 166534 | BR51: 166534 | BS51: 166534 | BT51: 166534 | BU51: 166534 | BV51: 166534 | BW51: 166534 | BX51: 166534 | BY51: 166534 | BZ51: 166534 | CA51: 166534 | CB51: =CA51 -> 166534 | CC51: 206665 | CD51: 206665 | CE51: 206665 | CF51: 206665 | CG51: 206665 | CH51: 206665 | CI51: 206665 | CJ51: 206665 | CK51: 206665 | CL51: 206665 | CM51: 206665 | CN51: 206665 | CO51: =CN51 -> 206665 | CP51: 160447 | CQ51: 160447 | CR51: 160447 | CS51: 160447 | CT51: 160447 | CU51: 160447 | CV51: 160447 | CW51: 160447 | CX51: 160447 | CY51: 160447 | CZ51: 160447 | DA51: 160447 | DB51: =DA51 -> 160447 | DC51: 455326 | DD51: 455326 | DE51: 455326 | DF51: 455326 | DG51: 455326 | DH51: 455326 | DI51: 455326 | DJ51: 455326 | DK51: 455326 | DL51: 455326 | DM51: 455326 | DN51: 455326 | DO51: =DN51 -> 455326 | DP51: 622609 | DQ51: 622609 | DR51: 622609 | DS51: 622609 | DT51: 622609 | DU51: 622609 | DV51: 622609 | DW51: 622609 | DX51: 622609 | DY51: 622609 | DZ51: 622609 | EA51: 622609 | EB51: =EA51 -> 622609 | EC51: 636104 | ED51: 636104 | EE51: 636104 | EF51: 636104 | EG51: 636104 | EH51: 636104 | EI51: 636104 | EJ51: 636104 | EK51: 636104 | EL51: 636104 | EM51: 636104 | EN51: 636104 | EO51: =EN51 -> 636104 | EP51: 1352415 | EQ51: 1352415 | ER51: 1352415 | ES51: 1352415 | ET51: 1352415 | EU51: 1352415 | EV51: 1352415 | EW51: 1352415 | EX51: 1352415 | EY51: 1352415 | EZ51: 1352415 | FA51: 1352415 | FB51: =FA51 -> 1352415 | FC51: 667445 | FD51: 667445 | FE51: 667445 | FF51: 667445 | FG51: 667445 | FH51: 667445 | FI51: 667445 | FO51: =FI51 -> 667445
B52: Dirección de Obras Portuarias | C52: 166373 | D52: 166373 | E52: 166373 | F52: 166373 | G52: 166373 | H52: 166373 | I52: 166373 | J52: 166373 | K52: 166373 | L52: 166373 | M52: 166373 | N52: 166373 | O52: =N52 -> 166373 | P52: 1590037 | Q52: 1590037 | R52: 1590037 | S52: 1590037 | T52: 1590037 | U52: 1590037 | V52: 1590037 | W52: 1590037 | X52: 1590037 | Y52: 1590037 | Z52: 1590037 | AA52: 1590037 | AB52: =AA52 -> 1590037 | AC52: 6130543 | AD52: 6130543 | AE52: 6130543 | AF52: 6130543 | AG52: 6130543 | AH52: 6130543 | AI52: 6130543 | AJ52: 6130543 | AK52: 6130543 | AL52: 6130543 | AM52: 6130543 | AN52: 6130543 | AO52: =AN52 -> 6130543 | AP52: 3892493 | AQ52: 3892493 | AR52: 3892493 | AS52: 3892493 | AT52: 3892493 | AU52: 3892493 | AV52: 3892493 | AW52: 3892493 | AX52: 3892493 | AY52: 3892493 | AZ52: 3892493 | BA52: 3892493 | BB52: =BA52 -> 3892493 | BC52: 1987092 | BD52: 1987092 | BE52: 1987092 | BF52: 1987092 | BG52: 1987092 | BH52: 1987092 | BI52: 1987092 | BJ52: 1987092 | BK52: 1987092 | BL52: 1987092 | BM52: 1987092 | BN52: 1987092 | BO52: =BN52 -> 1987092 | BP52: 2440271 | BQ52: 2440271 | BR52: 2440271 | BS52: 2440271 | BT52: 2440271 | BU52: 2440271 | BV52: 2440271 | BW52: 2440271 | BX52: 2440271 | BY52: 2440271 | BZ52: 2440271 | CA52: 2440271 | CB52: =CA52 -> 2440271 | CC52: 2488259 | CD52: 2488259 | CE52: 2488259 | CF52: 2488259 | CG52: 2488259 | CH52: 2488259 | CI52: 2488259 | CJ52: 2488259 | CK52: 2488259 | CL52: 2488259 | CM52: 2488259 | CN52: 2488259 | CO52: =CN52 -> 2488259 | CP52: 2902086 | CQ52: 2902086 | CR52: 2902086 | CS52: 2902086 | CT52: 2902086 | CU52: 2902086 | CV52: 2902086 | CW52: 2902086 | CX52: 2902086 | CY52: 2902086 | CZ52: 2902086 | DA52: 2902086 | DB52: =DA52 -> 2902086 | DC52: 1322297 | DD52: 1322297 | DE52: 1322297 | DF52: 1322297 | DG52: 1322297 | DH52: 1322297 | DI52: 1322297 | DJ52: 1322297 | DK52: 1322297 | DL52: 1322297 | DM52: 1322297 | DN52: 1322297 | DO52: =DN52 -> 1322297 | DP52: 1814843 | DQ52: 1814843 | DR52: 1814843 | DS52: 1814843 | DT52: 1814843 | DU52: 1814843 | DV52: 1814843 | DW52: 1814843 | DX52: 1814843 | DY52: 1814843 | DZ52: 1814843 | EA52: 1814843 | EB52: =EA52 -> 1814843 | EC52: 5152528 | ED52: 5152528 | EE52: 5152528 | EF52: 5152528 | EG52: 5152528 | EH52: 5152528 | EI52: 5152528 | EJ52: 5152528 | EK52: 5152528 | EL52: 5152528 | EM52: 5152528 | EN52: 5152528 | EO52: =EN52 -> 5152528 | EP52: 2635679 | EQ52: 2635679 | ER52: 2635679 | ES52: 2635679 | ET52: 2635679 | EU52: 2635679 | EV52: 2635679 | EW52: 2635679 | EX52: 2635679 | EY52: 2635679 | EZ52: 2635679 | FA52: 2635679 | FB52: =FA52 -> 2635679 | FC52: 2135157 | FD52: 2135157 | FE52: 2135157 | FF52: 2135157 | FG52: 2135157 | FH52: 2135157 | FI52: 2135157 | FO52: =FI52 -> 2135157
B53: Dirección de Aeropuertos | C53: 231070 | D53: 231070 | E53: 231070 | F53: 231070 | G53: 231070 | H53: 231070 | I53: 231070 | J53: 231070 | K53: 231070 | L53: 231070 | M53: 231070 | N53: 231070 | O53: =N53 -> 231070 | P53: 467863 | Q53: 467863 | R53: 467863 | S53: 467863 | T53: 467863 | U53: 467863 | V53: 467863 | W53: 467863 | X53: 467863 | Y53: 467863 | Z53: 467863 | AA53: 467863 | AB53: =AA53 -> 467863 | AC53: 173175 | AD53: 173175 | AE53: 173175 | AF53: 173175 | AG53: 173175 | AH53: 173175 | AI53: 173175 | AJ53: 173175 | AK53: 173175 | AL53: 173175 | AM53: 173175 | AN53: 173175 | AO53: =AN53 -> 173175 | AP53: 100131 | AQ53: 100131 | AR53: 100131 | AS53: 100131 | AT53: 100131 | AU53: 100131 | AV53: 100131 | AW53: 100131 | AX53: 100131 | AY53: 100131 | AZ53: 100131 | BA53: 100131 | BB53: =BA53 -> 100131 | BC53: 95500 | BD53: 95500 | BE53: 95500 | BF53: 95500 | BG53: 95500 | BH53: 95500 | BI53: 95500 | BJ53: 95500 | BK53: 95500 | BL53: 95500 | BM53: 95500 | BN53: 95500 | BO53: =BN53 -> 95500 | BP53: 97653 | BQ53: 97653 | BR53: 97653 | BS53: 97653 | BT53: 97653 | BU53: 97653 | BV53: 97653 | BW53: 97653 | BX53: 97653 | BY53: 97653 | BZ53: 97653 | CA53: 97653 | CB53: =CA53 -> 97653 | CC53: 72183 | CD53: 72183 | CE53: 72183 | CF53: 72183 | CG53: 72183 | CH53: 72183 | CI53: 72183 | CJ53: 72183 | CK53: 72183 | CL53: 72183 | CM53: 72183 | CN53: 72183 | CO53: =CN53 -> 72183 | CP53: 103404 | CQ53: 103404 | CR53: 103404 | CS53: 103404 | CT53: 103404 | CU53: 103404 | CV53: 103404 | CW53: 103404 | CX53: 103404 | CY53: 103404 | CZ53: 103404 | DA53: 103404 | DB53: =DA53 -> 103404 | DC53: 76973 | DD53: 76973 | DE53: 76973 | DF53: 76973 | DG53: 76973 | DH53: 76973 | DI53: 76973 | DJ53: 76973 | DK53: 76973 | DL53: 76973 | DM53: 76973 | DN53: 76973 | DO53: =DN53 -> 76973 | DP53: 240323 | DQ53: 240323 | DR53: 240323 | DS53: 240323 | DT53: 240323 | DU53: 240323 | DV53: 240323 | DW53: 240323 | DX53: 240323 | DY53: 240323 | DZ53: 240323 | EA53: 240323 | EB53: =EA53 -> 240323 | EC53: 251537 | ED53: 251537 | EE53: 251537 | EF53: 251537 | EG53: 251537 | EH53: 251537 | EI53: 251537 | EJ53: 251537 | EK53: 251537 | EL53: 251537 | EM53: 251537 | EN53: 251537 | EO53: =EN53 -> 251537 | EP53: 924967 | EQ53: 924967 | ER53: 924967 | ES53: 924967 | ET53: 924967 | EU53: 924967 | EV53: 924967 | EW53: 924967 | EX53: 924967 | EY53: 924967 | EZ53: 924967 | FA53: 924967 | FB53: =FA53 -> 924967 | FC53: 294239 | FD53: 294239 | FE53: 294239 | FF53: 294239 | FG53: 294239 | FH53: 294239 | FI53: 294239 | FO53: =FI53 -> 294239
B54: Dirección de Arquitectura | C54: 104782 | D54: 104782 | E54: 104782 | F54: 104782 | G54: 104782 | H54: 104782 | I54: 104782 | J54: 104782 | K54: 104782 | L54: 104782 | M54: 104782 | N54: 104782 | O54: =N54 -> 104782 | P54: 95648 | Q54: 95648 | R54: 95648 | S54: 95648 | T54: 95648 | U54: 95648 | V54: 95648 | W54: 95648 | X54: 95648 | Y54: 95648 | Z54: 95648 | AA54: 95648 | AB54: =AA54 -> 95648 | AC54: 96011 | AD54: 96011 | AE54: 96011 | AF54: 96011 | AG54: 96011 | AH54: 96011 | AI54: 96011 | AJ54: 96011 | AK54: 96011 | AL54: 96011 | AM54: 96011 | AN54: 96011 | AO54: =AN54 -> 96011 | AP54: 123692 | AQ54: 123692 | AR54: 123692 | AS54: 123692 | AT54: 123692 | AU54: 123692 | AV54: 123692 | AW54: 123692 | AX54: 123692 | AY54: 123692 | AZ54: 123692 | BA54: 123692 | BB54: =BA54 -> 123692 | BC54: 101075 | BD54: 101075 | BE54: 101075 | BF54: 101075 | BG54: 101075 | BH54: 101075 | BI54: 101075 | BJ54: 101075 | BK54: 101075 | BL54: 101075 | BM54: 101075 | BN54: 101075 | BO54: =BN54 -> 101075 | BP54: 111887 | BQ54: 111887 | BR54: 111887 | BS54: 111887 | BT54: 111887 | BU54: 111887 | BV54: 111887 | BW54: 111887 | BX54: 111887 | BY54: 111887 | BZ54: 111887 | CA54: 111887 | CB54: =CA54 -> 111887 | CC54: 185782 | CD54: 185782 | CE54: 185782 | CF54: 185782 | CG54: 185782 | CH54: 185782 | CI54: 185782 | CJ54: 185782 | CK54: 185782 | CL54: 185782 | CM54: 185782 | CN54: 185782 | CO54: =CN54 -> 185782 | CP54: 107372 | CQ54: 107372 | CR54: 107372 | CS54: 107372 | CT54: 107372 | CU54: 107372 | CV54: 107372 | CW54: 107372 | CX54: 107372 | CY54: 107372 | CZ54: 107372 | DA54: 107372 | DB54: =DA54 -> 107372 | DC54: 169485 | DD54: 169485 | DE54: 169485 | DF54: 169485 | DG54: 169485 | DH54: 169485 | DI54: 169485 | DJ54: 169485 | DK54: 169485 | DL54: 169485 | DM54: 169485 | DN54: 169485 | DO54: =DN54 -> 169485 | DP54: 556957 | DQ54: 556957 | DR54: 556957 | DS54: 556957 | DT54: 556957 | DU54: 556957 | DV54: 556957 | DW54: 556957 | DX54: 556957 | DY54: 556957 | DZ54: 556957 | EA54: 556957 | EB54: =EA54 -> 556957 | EC54: 615757 | ED54: 615757 | EE54: 615757 | EF54: 615757 | EG54: 615757 | EH54: 615757 | EI54: 615757 | EJ54: 615757 | EK54: 615757 | EL54: 615757 | EM54: 615757 | EN54: 615757 | EO54: =EN54 -> 615757 | EP54: 555640 | EQ54: 555640 | ER54: 555640 | ES54: 555640 | ET54: 555640 | EU54: 555640 | EV54: 555640 | EW54: 555640 | EX54: 555640 | EY54: 555640 | EZ54: 555640 | FA54: 555640 | FB54: =FA54 -> 555640 | FC54: 392933 | FD54: 392933 | FE54: 392933 | FF54: 392933 | FG54: 392933 | FH54: 392933 | FI54: 392933 | FO54: =FI54 -> 392933
B55: Total | C55: =SUM(C49:C54) -> 3877230 | D55: =SUM(D49:D54) -> 3877230 | E55: =SUM(E49:E54) -> 3877230 | F55: =SUM(F49:F54) -> 3877230 | G55: =SUM(G49:G54) -> 3877230 | H55: =SUM(H49:H54) -> 3877230 | I55: =SUM(I49:I54) -> 3877230 | J55: =SUM(J49:J54) -> 3877230 | ... FO55: =SUM(FO49:FO54) -> 5203817
B56: Fuente: elaboración propia, Dipres.
B58: Presupuesto Vigente de Inversión en Infraestructura Pública del Ministerio de Obras Públicas, 2014-2026 (Subtítulo 29 – Adquisición de Activos No Financieros, miles de pesos)
C59: 2014 | P59: 2015 | AC59: 2016 | AP59: 2017 | BC59: 2018 | BP59: 2019 | CC59: 2020 | CP59: 2021 | DC59: 2022 | DP59: 2023 | EC59: 2024 | EP59: 2025 | FC59: 2026
B60: Programa | C60: Ene | D60: Feb | E60: Mar | F60: Abr | G60: May | H60: Jun | I60: Jul | J60: Ago | K60: Sep | L60: Oct | M60: Nov | N60: Dic | O60: Total 2014 | P60: Ene | Q60: Feb | R60: Mar | S60: Abr | T60: May | U60: Jun | V60: Jul | W60: Ago | X60: Sep | Y60: Oct | Z60: Nov | AA60: Dic | AB60: Total 2015 | AC60: Ene | AD60: Feb | AE60: Mar | AF60: Abr | AG60: May | AH60: Jun | AI60: Jul | AJ60: Ago | AK60: Sep | AL60: Oct | AM60: Nov | AN60: Dic | AO60: Total 2016 | AP60: Ene | AQ60: Feb | AR60: Mar | AS60: Abr | AT60: May | AU60: Jun | AV60: Jul | AW60: Ago | AX60: Sep | AY60: Oct | AZ60: Nov | BA60: Dic | BB60: Total 2017 | BC60: Ene | BD60: Feb | BE60: Mar | BF60: Abr | BG60: May | BH60: Jun | BI60: Jul | BJ60: Ago | BK60: Sep | BL60: Oct | BM60: Nov | BN60: Dic | BO60: Total 2018 | BP60: Ene | BQ60: Feb | BR60: Mar | BS60: Abr | BT60: May | BU60: Jun | BV60: Jul | BW60: Ago | BX60: Sep | BY60: Oct | BZ60: Nov | CA60: Dic | CB60: Total 2019 | CC60: Ene | CD60: Feb | CE60: Mar | CF60: Abr | CG60: May | CH60: Jun | CI60: Jul | CJ60: Ago | CK60: Sep | CL60: Oct | CM60: Nov | CN60: Dic | CO60: Total 2020 | CP60: Ene | CQ60: Feb | CR60: Mar | CS60: Abr | CT60: May | CU60: Jun | CV60: Jul | CW60: Ago | CX60: Sep | CY60: Oct | CZ60: Nov | DA60: Dic | DB60: Total 2021 | DC60: Ene | DD60: Feb | DE60: Mar | DF60: Abr | DG60: May | DH60: Jun | DI60: Jul | DJ60: Ago | DK60: Sep | DL60: Oct | DM60: Nov | DN60: Dic | DO60: Total 2022 | DP60: Ene | DQ60: Feb | DR60: Mar | DS60: Abr | DT60: May | DU60: Jun | DV60: Jul | DW60: Ago | DX60: Sep | DY60: Oct | DZ60: Nov | EA60: Dic | EB60: Total 2023 | EC60: Ene | ED60: Feb | EE60: Mar | EF60: Abr | EG60: May | EH60: Jun | EI60: Jul | EJ60: Ago | EK60: Sep | EL60: Oct | EM60: Nov | EN60: Dic | EO60: Total 2024 | EP60: Ene | EQ60: Feb | ER60: Mar | ES60: Abr | ET60: May | EU60: Jun | EV60: Jul | EW60: Ago | EX60: Sep | EY60: Oct | EZ60: Nov | FA60: Dic | FB60: Total 2025 | FC60: Ene | FD60: Feb | FE60: Mar | FF60: Abr | FG60: May | FH60: Jun | FI60: Jul | FJ60: Ago | FK60: Sep | FL60: Oct | FM60: Nov | FN60: Dic | FO60: Total 2026
B61: Dirección de Vialidad | C61: 2953248 | D61: 2953248 | E61: 2953248 | F61: 2953248 | G61: 2967248 | H61: 13617214 | I61: 16777214 | J61: 16777214 | K61: 16777214 | L61: 18277214 | M61: 18638378 | N61: 12770620 | O61: =N61 -> 12770620 | P61: 1753030 | Q61: 1753030 | R61: 8107652 | S61: 8107652 | T61: 8642652 | U61: 8642652 | V61: 8742652 | W61: 8742652 | X61: 8742652 | Y61: 8742652 | Z61: 11742652 | AA61: 11742652 | AB61: =AA61 -> 11742652 | AC61: 1791359 | AD61: 1791359 | AE61: 1791359 | AF61: 1721359 | AG61: 1721359 | AH61: 2260359 | AI61: 2260359 | AJ61: 2260359 | AK61: 2260359 | AL61: 2260359 | AM61: 2353359 | AN61: 2665605 | AO61: =AN61 -> 2665605 | AP61: 1779405 | AQ61: 1779405 | AR61: 2057405 | AS61: 2057405 | AT61: 2257405 | AU61: 18725105 | AV61: 18941005 | AW61: 19075505 | AX61: 19084105 | AY61: 19084105 | AZ61: 19100105 | BA61: 14280017 | BB61: =BA61 -> 14280017 | BC61: 1606877 | BD61: 1606877 | BE61: 7551961 | BF61: 7551961 | BG61: 7867152 | BH61: 7867152 | BI61: 7603828 | BJ61: 7641450 | BK61: 7641450 | BL61: 7656450 | BM61: 8088150 | BN61: 8261850 | BO61: =BN61 -> 8261850 | BP61: 1639746 | BQ61: 1639746 | BR61: 1639746 | BS61: 1708546 | BT61: 1708546 | BU61: 6540546 | BV61: 6574796 | BW61: 6624796 | BX61: 6624796 | BY61: 6624796 | BZ61: 6624796 | CA61: 6641796 | CB61: =CA61 -> 6641796 | CC61: 1704539 | CD61: 1704539 | CE61: 1704539 | CF61: 1155557 | CG61: 803695 | CH61: 803695 | CI61: 1337695 | CJ61: 1337695 | CK61: 1337695 | CL61: 8003088 | CM61: 8003088 | CN61: 7435088 | CO61: =CN61 -> 7435088 | CP61: 1930914 | CQ61: 1930914 | CR61: 3898492 | CS61: 4709492 | CT61: 4709492 | CU61: 4731492 | CV61: 4731492 | CW61: 4832662 | CX61: 4832662 | CY61: 4832662 | CZ61: 4925662 | DA61: 4819159 | DB61: =DA61 -> 4819159 | DC61: 298233 | DD61: 298233 | DE61: 298233 | DF61: 298233 | DG61: 1895233 | DH61: 1895233 | DI61: 1895233 | DJ61: 1895233 | DK61: 11893879 | DL61: 11893879 | DM61: 11893879 | DN61: 8468149 | DO61: =DN61 -> 8468149 | DP61: 22089448 | DQ61: 22089448 | DR61: 22089448 | DS61: 42047634 | DT61: 42281504 | DU61: 42281504 | DV61: 42281504 | DW61: 42281504 | DX61: 44698344 | DY61: 44698344 | DZ61: 44698344 | EA61: 7233990 | EB61: =EA61 -> 7233990 | EC61: 1135861 | ED61: 1135861 | EE61: 1135861 | EF61: 1135861 | EG61: 1135861 | EH61: 1135861 | EI61: 1135861 | EJ61: 1135861 | EK61: 1135861 | EL61: 1135861 | EM61: 1135861 | EN61: 1135861 | EO61: =EN61 -> 1135861 | EP61: 6213840 | EQ61: 6213840 | ER61: 6213840 | ES61: 6347840 | ET61: 6347840 | EU61: 6347840 | EV61: 6347840 | EW61: 6347840 | EX61: 4559840 | EY61: 4559840 | EZ61: 4559840 | FA61: 2245535 | FB61: =FA61 -> 2245535 | FC61: 1062955 | FD61: 1062955 | FE61: 1582955 | FF61: 1582955 | FG61: 1551066 | FH61: 1551066 | FI61: 1551066 | FO61: =FI61 -> 1551066
B62: Dirección de Obras Hidráulicas | C62: 381750 | D62: 381750 | E62: 381750 | F62: 381750 | G62: 381750 | H62: 381750 | I62: 381750 | J62: 381750 | K62: 381750 | L62: 381750 | M62: 381750 | N62: 381750 | O62: =N62 -> 381750 | P62: 362280 | Q62: 362280 | R62: 362280 | S62: 362280 | T62: 362280 | U62: 362280 | V62: 362280 | W62: 362280 | X62: 362280 | Y62: 362280 | Z62: 362280 | AA62: 362280 | AB62: =AA62 -> 362280 | AC62: 327142 | AD62: 327142 | AE62: 327142 | AF62: 258142 | AG62: 258142 | AH62: 258142 | AI62: 258142 | AJ62: 258142 | AK62: 258142 | AL62: 258142 | AM62: 258142 | AN62: 258142 | AO62: =AN62 -> 258142 | AP62: 174624 | AQ62: 174624 | AR62: 174624 | AS62: 174624 | AT62: 174624 | AU62: 174624 | AV62: 174624 | AW62: 521624 | AX62: 521624 | AY62: 521624 | AZ62: 521624 | BA62: 546624 | BB62: =BA62 -> 546624 | BC62: 139517 | BD62: 139517 | BE62: 139517 | BF62: 139517 | BG62: 139517 | BH62: 139517 | BI62: 131028 | BJ62: 138040 | BK62: 138040 | BL62: 138040 | BM62: 138040 | BN62: 3231423 | BO62: =BN62 -> 3231423 | BP62: 115465 | BQ62: 115465 | BR62: 115465 | BS62: 115465 | BT62: 115465 | BU62: 115465 | BV62: 115465 | BW62: 162235 | BX62: 162235 | BY62: 162235 | BZ62: 162235 | CA62: 754307 | CB62: =CA62 -> 754307 | CC62: 188388 | CD62: 188388 | CE62: 188388 | CF62: 173698 | CG62: 94575 | CH62: 94575 | CI62: 94575 | CJ62: 94575 | CK62: 94575 | CL62: 92075 | CM62: 92075 | CN62: 112017 | CO62: =CN62 -> 112017 | CP62: 128859 | CQ62: 128859 | CR62: 128859 | CS62: 128859 | CT62: 128859 | CU62: 128859 | CV62: 128859 | CW62: 128859 | CX62: 128859 | CY62: 128859 | CZ62: 128859 | DA62: 708689 | DB62: =DA62 -> 708689 | DC62: 130362 | DD62: 130362 | DE62: 130362 | DF62: 130362 | DG62: 130362 | DH62: 130362 | DI62: 130362 | DJ62: 130362 | DK62: 1013888 | DL62: 1013888 | DM62: 1193375 | DN62: 1193375 | DO62: =DN62 -> 1193375 | DP62: 647086 | DQ62: 647086 | DR62: 647086 | DS62: 647086 | DT62: 647086 | DU62: 647086 | DV62: 647086 | DW62: 647086 | DX62: 647086 | DY62: 647086 | DZ62: 647086 | EA62: 647086 | EB62: =EA62 -> 647086 | EC62: 856525 | ED62: 856525 | EE62: 856525 | EF62: 856525 | EG62: 913626 | EH62: 913626 | EI62: 913626 | EJ62: 913626 | EK62: 913626 | EL62: 913626 | EM62: 913626 | EN62: 913626 | EO62: =EN62 -> 913626 | EP62: 1172171 | EQ62: 1172171 | ER62: 1172171 | ES62: 1172171 | ET62: 1172171 | EU62: 1172171 | EV62: 1172171 | EW62: 1172171 | EX62: 1172171 | EY62: 1172171 | EZ62: 1172171 | FA62: 992552 | FB62: =FA62 -> 992552 | FC62: 651088 | FD62: 651088 | FE62: 651088 | FF62: 651088 | FG62: 517480 | FH62: 517480 | FI62: 517480 | FO62: =FI62 -> 517480
B63: Subdirección de APR | C63: 40007 | D63: 40007 | E63: 40007 | F63: 40007 | G63: 40007 | H63: 40007 | I63: 40007 | J63: 40007 | K63: 40007 | L63: 40007 | M63: 40007 | N63: 40007 | O63: =N63 -> 40007 | P63: 78467 | Q63: 78467 | R63: 78467 | S63: 78467 | T63: 78467 | U63: 78467 | V63: 78467 | W63: 78467 | X63: 78467 | Y63: 78467 | Z63: 78467 | AA63: 78467 | AB63: =AA63 -> 78467 | AC63: 62947 | AD63: 62947 | AE63: 62947 | AF63: 62947 | AG63: 62947 | AH63: 62947 | AI63: 62947 | AJ63: 62947 | AK63: 62947 | AL63: 62947 | AM63: 62947 | AN63: 62947 | AO63: =AN63 -> 62947 | AP63: 49257 | AQ63: 49257 | AR63: 49257 | AS63: 49257 | AT63: 49257 | AU63: 49257 | AV63: 49257 | AW63: 49257 | AX63: 49257 | AY63: 49257 | AZ63: 49257 | BA63: 49257 | BB63: =BA63 -> 49257 | BC63: 610722 | BD63: 610722 | BE63: 610722 | BF63: 610722 | BG63: 610722 | BH63: 610722 | BI63: 566060 | BJ63: 566060 | BK63: 566060 | BL63: 566060 | BM63: 566060 | BN63: 566060 | BO63: =BN63 -> 566060 | BP63: 166534 | BQ63: 166534 | BR63: 166534 | BS63: 166534 | BT63: 166534 | BU63: 166534 | BV63: 177586 | BW63: 177586 | BX63: 177586 | BY63: 177586 | BZ63: 177586 | CA63: 177586 | CB63: =CA63 -> 177586 | CC63: 206665 | CD63: 206665 | CE63: 206665 | CF63: 182934 | CG63: 182934 | CH63: 182934 | CI63: 182934 | CJ63: 182934 | CK63: 182934 | CL63: 182934 | CM63: 182934 | CN63: 183383 | CO63: =CN63 -> 183383 | CP63: 160447 | CQ63: 160447 | CR63: 160447 | CS63: 160447 | CT63: 160447 | CU63: 160447 | CV63: 160447 | CW63: 160447 | CX63: 160447 | CY63: 160447 | CZ63: 160447 | DA63: 160447 | DB63: =DA63 -> 160447 | DC63: 455326 | DD63: 455326 | DE63: 455326 | DF63: 455326 | DG63: 455326 | DH63: 455326 | DI63: 455326 | DJ63: 455326 | DK63: 455326 | DL63: 979017 | DM63: 979017 | DN63: 979017 | DO63: =DN63 -> 979017 | DP63: 622609 | DQ63: 622609 | DR63: 622609 | DS63: 622609 | DT63: 622609 | DU63: 622609 | DV63: 622609 | DW63: 622609 | DX63: 622609 | DY63: 622609 | DZ63: 622609 | EA63: 428444 | EB63: =EA63 -> 428444 | EC63: 636104 | ED63: 636104 | EE63: 636104 | EF63: 636104 | EG63: 636104 | EH63: 636104 | EI63: 636104 | EJ63: 636104 | EK63: 636104 | EL63: 636104 | EM63: 636104 | EN63: 636104 | EO63: =EN63 -> 636104 | EP63: 1284794 | EQ63: 1284794 | ER63: 1284794 | ES63: 1284794 | ET63: 1284794 | EU63: 1284794 | EV63: 1284794 | EW63: 1284794 | EX63: 1284794 | EY63: 1284794 | EZ63: 1284794 | FA63: 1212027 | FB63: =FA63 -> 1212027 | FC63: 667445 | FD63: 667445 | FE63: 667445 | FF63: 667445 | FG63: 488932 | FH63: 488932 | FI63: 488932 | FO63: =FI63 -> 488932
B64: Dirección de Obras Portuarias | C64: 166373 | D64: 166373 | E64: 166373 | F64: 166373 | G64: 166373 | H64: 166373 | I64: 166373 | J64: 166373 | K64: 166373 | L64: 166373 | M64: 166373 | N64: 166373 | O64: =N64 -> 166373 | P64: 1590037 | Q64: 1590037 | R64: 1590037 | S64: 1590037 | T64: 1590037 | U64: 1590037 | V64: 1590037 | W64: 1590037 | X64: 1590037 | Y64: 1590037 | Z64: 1590037 | AA64: 1900037 | AB64: =AA64 -> 1900037 | AC64: 6130543 | AD64: 6130543 | AE64: 6130543 | AF64: 6108543 | AG64: 6108543 | AH64: 6108543 | AI64: 6108543 | AJ64: 6108543 | AK64: 6108543 | AL64: 6108543 | AM64: 6108543 | AN64: 4530168 | AO64: =AN64 -> 4530168 | AP64: 3892493 | AQ64: 3892493 | AR64: 3892493 | AS64: 3892493 | AT64: 3892493 | AU64: 3892493 | AV64: 3892493 | AW64: 3892493 | AX64: 3892493 | AY64: 3718873 | AZ64: 3718873 | BA64: 3718873 | BB64: =BA64 -> 3718873 | BC64: 1987092 | BD64: 1987092 | BE64: 1987092 | BF64: 1987092 | BG64: 1987092 | BH64: 1987092 | BI64: 1594960 | BJ64: 1594960 | BK64: 1594960 | BL64: 1594960 | BM64: 1627511 | BN64: 353432 | BO64: =BN64 -> 353432 | BP64: 2440271 | BQ64: 2440271 | BR64: 2390271 | BS64: 2390271 | BT64: 2390271 | BU64: 2390271 | BV64: 2379219 | BW64: 2379219 | BX64: 2379219 | BY64: 2379219 | BZ64: 2379219 | CA64: 869395 | CB64: =CA64 -> 869395 | CC64: 2488259 | CD64: 2488259 | CE64: 2488259 | CF64: 1571869 | CG64: 1541383 | CH64: 1541383 | CI64: 1541383 | CJ64: 1541383 | CK64: 1541383 | CL64: 1538683 | CM64: 2653214 | CN64: 1949794 | CO64: =CN64 -> 1949794 | CP64: 2902086 | CQ64: 2902086 | CR64: 2902086 | CS64: 2902086 | CT64: 2902086 | CU64: 2902086 | CV64: 2902086 | CW64: 2902086 | CX64: 2902086 | CY64: 2902086 | CZ64: 2902086 | DA64: 486360 | DB64: =DA64 -> 486360 | DC64: 1322297 | DD64: 1322297 | DE64: 1322297 | DF64: 1322297 | DG64: 1322297 | DH64: 1322297 | DI64: 1322297 | DJ64: 1322297 | DK64: 1322297 | DL64: 1322297 | DM64: 1322297 | DN64: 958297 | DO64: =DN64 -> 958297 | DP64: 1814843 | DQ64: 1814843 | DR64: 1814843 | DS64: 1814843 | DT64: 1814843 | DU64: 1814843 | DV64: 1814843 | DW64: 1814843 | DX64: 1814843 | DY64: 1814843 | DZ64: 1814843 | EA64: 687226 | EB64: =EA64 -> 687226 | EC64: 5152528 | ED64: 5152528 | EE64: 5152528 | EF64: 5152528 | EG64: 5152528 | EH64: 5152528 | EI64: 5152528 | EJ64: 5152528 | EK64: 5006428 | EL64: 5006428 | EM64: 1731272 | EN64: 1731272 | EO64: =EN64 -> 1731272 | EP64: 2503895 | EQ64: 2503895 | ER64: 2503895 | ES64: 2503895 | ET64: 2503895 | EU64: 2503895 | EV64: 2503895 | EW64: 2503895 | EX64: 2503895 | EY64: 2503895 | EZ64: 2503895 | FA64: 391705 | FB64: =FA64 -> 391705 | FC64: 2135157 | FD64: 2135157 | FE64: 2135157 | FF64: 2135157 | FG64: 2071102 | FH64: 2071102 | FI64: 2071102 | FO64: =FI64 -> 2071102
B65: Dirección de Aeropuertos | C65: 231070 | D65: 231070 | E65: 231070 | F65: 231070 | G65: 231070 | H65: 231070 | I65: 231070 | J65: 231070 | K65: 231070 | L65: 231070 | M65: 231070 | N65: 231070 | O65: =N65 -> 231070 | P65: 467863 | Q65: 467863 | R65: 467863 | S65: 467863 | T65: 467863 | U65: 467863 | V65: 467863 | W65: 467863 | X65: 467863 | Y65: 467863 | Z65: 838663 | AA65: 838663 | AB65: =AA65 -> 838663 | AC65: 173175 | AD65: 173175 | AE65: 173175 | AF65: 173175 | AG65: 173175 | AH65: 173175 | AI65: 173175 | AJ65: 173175 | AK65: 173175 | AL65: 635175 | AM65: 635175 | AN65: 635175 | AO65: =AN65 -> 635175 | AP65: 100131 | AQ65: 100131 | AR65: 100131 | AS65: 100131 | AT65: 100131 | AU65: 100131 | AV65: 100131 | AW65: 100131 | AX65: 100131 | AY65: 1082131 | AZ65: 1082131 | BA65: 1762131 | BB65: =BA65 -> 1762131 | BC65: 95500 | BD65: 95500 | BE65: 95500 | BF65: 95500 | BG65: 95500 | BH65: 95500 | BI65: 85076 | BJ65: 85076 | BK65: 85076 | BL65: 85076 | BM65: 85076 | BN65: 1689211 | BO65: =BN65 -> 1689211 | BP65: 97653 | BQ65: 97653 | BR65: 97653 | BS65: 97653 | BT65: 97653 | BU65: 97653 | BV65: 97653 | BW65: 97653 | BX65: 97653 | BY65: 97653 | BZ65: 97653 | CA65: 97653 | CB65: =CA65 -> 97653 | CC65: 72183 | CD65: 72183 | CE65: 72183 | CF65: 58992 | CG65: 41722 | CH65: 41722 | CI65: 41722 | CJ65: 41722 | CK65: 41722 | CL65: 383162 | CM65: 383162 | CN65: 383162 | CO65: =CN65 -> 383162 | CP65: 103404 | CQ65: 103404 | CR65: 103404 | CS65: 103404 | CT65: 103404 | CU65: 103404 | CV65: 103404 | CW65: 103404 | CX65: 103404 | CY65: 103404 | CZ65: 103404 | DA65: 103404 | DB65: =DA65 -> 103404 | DC65: 76973 | DD65: 76973 | DE65: 76973 | DF65: 76973 | DG65: 162012 | DH65: 162012 | DI65: 162012 | DJ65: 162012 | DK65: 162012 | DL65: 162012 | DM65: 162012 | DN65: 162012 | DO65: =DN65 -> 162012 | DP65: 240323 | DQ65: 240323 | DR65: 240323 | DS65: 240323 | DT65: 240323 | DU65: 240323 | DV65: 240323 | DW65: 240323 | DX65: 240323 | DY65: 240323 | DZ65: 240323 | EA65: 240323 | EB65: =EA65 -> 240323 | EC65: 251537 | ED65: 251537 | EE65: 251537 | EF65: 2079025 | EG65: 2107375 | EH65: 2107375 | EI65: 2107375 | EJ65: 2107375 | EK65: 2107375 | EL65: 2107375 | EM65: 2107375 | EN65: 1998403 | EO65: =EN65 -> 1998403 | EP65: 878719 | EQ65: 878719 | ER65: 878719 | ES65: 878719 | ET65: 878719 | EU65: 878719 | EV65: 878719 | EW65: 878719 | EX65: 878719 | EY65: 878719 | EZ65: 878719 | FA65: 812930 | FB65: =FA65 -> 812930 | FC65: 294239 | FD65: 294239 | FE65: 294239 | FF65: 294239 | FG65: 292976 | FH65: 292976 | FI65: 292976 | FO65: =FI65 -> 292976
B66: Dirección de Arquitectura | C66: 104782 | D66: 104782 | E66: 104782 | F66: 104782 | G66: 142001 | H66: 142001 | I66: 142001 | J66: 142001 | K66: 142001 | L66: 142001 | M66: 142001 | N66: 142001 | O66: =N66 -> 142001 | P66: 95648 | Q66: 95648 | R66: 95648 | S66: 95648 | T66: 95648 | U66: 95648 | V66: 95648 | W66: 95648 | X66: 295648 | Y66: 295648 | Z66: 295648 | AA66: 295648 | AB66: =AA66 -> 295648 | AC66: 96011 | AD66: 96011 | AE66: 96011 | AF66: 96011 | AG66: 96011 | AH66: 131011 | AI66: 131011 | AJ66: 131011 | AK66: 131011 | AL66: 131011 | AM66: 131011 | AN66: 131011 | AO66: =AN66 -> 131011 | AP66: 123692 | AQ66: 123692 | AR66: 131707 | AS66: 131707 | AT66: 131707 | AU66: 154815 | AV66: 154815 | AW66: 154815 | AX66: 154815 | AY66: 154815 | AZ66: 154815 | BA66: 95707 | BB66: =BA66 -> 95707 | BC66: 101075 | BD66: 101075 | BE66: 101075 | BF66: 101075 | BG66: 160183 | BH66: 160183 | BI66: 145935 | BJ66: 165021 | BK66: 165021 | BL66: 290395 | BM66: 290395 | BN66: 304643 | BO66: =BN66 -> 304643 | BP66: 111887 | BQ66: 111887 | BR66: 111887 | BS66: 111887 | BT66: 111887 | BU66: 111887 | BV66: 111887 | BW66: 111887 | BX66: 111887 | BY66: 111887 | BZ66: 111887 | CA66: 111887 | CB66: =CA66 -> 111887 | CC66: 185782 | CD66: 185782 | CE66: 185782 | CF66: 159768 | CG66: 107382 | CH66: 107382 | CI66: 107382 | CJ66: 107382 | CK66: 107382 | CL66: 107382 | CM66: 107382 | CN66: 107382 | CO66: =CN66 -> 107382 | CP66: 107372 | CQ66: 107372 | CR66: 107372 | CS66: 107372 | CT66: 107372 | CU66: 107372 | CV66: 107372 | CW66: 107372 | CX66: 107372 | CY66: 107372 | CZ66: 107372 | DA66: 107372 | DB66: =DA66 -> 107372 | DC66: 169485 | DD66: 169485 | DE66: 169485 | DF66: 169485 | DG66: 169485 | DH66: 169485 | DI66: 169485 | DJ66: 169485 | DK66: 169485 | DL66: 395850 | DM66: 395850 | DN66: 395850 | DO66: =DN66 -> 395850 | DP66: 556957 | DQ66: 556957 | DR66: 556957 | DS66: 556957 | DT66: 556957 | DU66: 556957 | DV66: 556957 | DW66: 556957 | DX66: 556957 | DY66: 556957 | DZ66: 556957 | EA66: 556957 | EB66: =EA66 -> 556957 | EC66: 615757 | ED66: 615757 | EE66: 615757 | EF66: 615757 | EG66: 615757 | EH66: 615757 | EI66: 615757 | EJ66: 632257 | EK66: 632257 | EL66: 632257 | EM66: 632257 | EN66: 632257 | EO66: =EN66 -> 632257 | EP66: 527858 | EQ66: 527858 | ER66: 527858 | ES66: 527858 | ET66: 527858 | EU66: 527858 | EV66: 527858 | EW66: 527858 | EX66: 527858 | EY66: 527858 | EZ66: 527858 | FA66: 527858 | FB66: =FA66 -> 527858 | FC66: 392933 | FD66: 392933 | FE66: 392933 | FF66: 392933 | FG66: 381145 | FH66: 381145 | FI66: 381145 | FO66: =FI66 -> 381145
B67: Total | C67: =SUM(C61:C66) -> 3877230 | D67: =SUM(D61:D66) -> 3877230 | E67: =SUM(E61:E66) -> 3877230 | F67: =SUM(F61:F66) -> 3877230 | G67: =SUM(G61:G66) -> 3928449 | H67: =SUM(H61:H66) -> 14578415 | I67: =SUM(I61:I66) -> 17738415 | J67: =SUM(J61:J66) -> 17738415 | ... FO67: =SUM(FO61:FO66) -> 5302701
B68: Fuente: elaboración propia, Dipres.
B70: Ejecución de Inversión en Infraestructura Pública del Ministerio de Obras Públicas, 2014-2026 (Subtítulo 29 – Adquisición de Activos No Financieros, miles de pesos)
C71: 2014 | P71: 2015 | AC71: 2016 | AP71: 2017 | BC71: 2018 | BP71: 2019 | CC71: 2020 | CP71: 2021 | DC71: 2022 | DP71: 2023 | EC71: 2024 | EP71: 2025 | FC71: 2026
B72: Programa | C72: Ene | D72: Feb | E72: Mar | F72: Abr | G72: May | H72: Jun | I72: Jul | J72: Ago | K72: Sep | L72: Oct | M72: Nov | N72: Dic | O72: Total 2014 | P72: Ene | Q72: Feb | R72: Mar | S72: Abr | T72: May | U72: Jun | V72: Jul | W72: Ago | X72: Sep | Y72: Oct | Z72: Nov | AA72: Dic | AB72: Total 2015 | AC72: Ene | AD72: Feb | AE72: Mar | AF72: Abr | AG72: May | AH72: Jun | AI72: Jul | AJ72: Ago | AK72: Sep | AL72: Oct | AM72: Nov | AN72: Dic | AO72: Total 2016 | AP72: Ene | AQ72: Feb | AR72: Mar | AS72: Abr | AT72: May | AU72: Jun | AV72: Jul | AW72: Ago | AX72: Sep | AY72: Oct | AZ72: Nov | BA72: Dic | BB72: Total 2017 | BC72: Ene | BD72: Feb | BE72: Mar | BF72: Abr | BG72: May | BH72: Jun | BI72: Jul | BJ72: Ago | BK72: Sep | BL72: Oct | BM72: Nov | BN72: Dic | BO72: Total 2018 | BP72: Ene | BQ72: Feb | BR72: Mar | BS72: Abr | BT72: May | BU72: Jun | BV72: Jul | BW72: Ago | BX72: Sep | BY72: Oct | BZ72: Nov | CA72: Dic | CB72: Total 2019 | CC72: Ene | CD72: Feb | CE72: Mar | CF72: Abr | CG72: May | CH72: Jun | CI72: Jul | CJ72: Ago | CK72: Sep | CL72: Oct | CM72: Nov | CN72: Dic | CO72: Total 2020 | CP72: Ene | CQ72: Feb | CR72: Mar | CS72: Abr | CT72: May | CU72: Jun | CV72: Jul | CW72: Ago | CX72: Sep | CY72: Oct | CZ72: Nov | DA72: Dic | DB72: Total 2021 | DC72: Ene | DD72: Feb | DE72: Mar | DF72: Abr | DG72: May | DH72: Jun | DI72: Jul | DJ72: Ago | DK72: Sep | DL72: Oct | DM72: Nov | DN72: Dic | DO72: Total 2022 | DP72: Ene | DQ72: Feb | DR72: Mar | DS72: Abr | DT72: May | DU72: Jun | DV72: Jul | DW72: Ago | DX72: Sep | DY72: Oct | DZ72: Nov | EA72: Dic | EB72: Total 2023 | EC72: Ene | ED72: Feb | EE72: Mar | EF72: Abr | EG72: May | EH72: Jun | EI72: Jul | EJ72: Ago | EK72: Sep | EL72: Oct | EM72: Nov | EN72: Dic | EO72: Total 2024 | EP72: Ene | EQ72: Feb | ER72: Mar | ES72: Abr | ET72: May | EU72: Jun | EV72: Jul | EW72: Ago | EX72: Sep | EY72: Oct | EZ72: Nov | FA72: Dic | FB72: Total 2025 | FC72: Ene | FD72: Feb | FE72: Mar | FF72: Abr | FG72: May | FH72: Jun | FI72: Jul | FJ72: Ago | FK72: Sep | FL72: Oct | FM72: Nov | FN72: Dic | FO72: Total 2026
B73: Dirección de Vialidad | C73: 0 | D73: 3363 | E73: 89766 | F73: 177873 | G73: 347371 | H73: 768455 | I73: 1122871 | J73: 1568088 | K73: 2263223 | L73: 3127503 | M73: 3633055 | N73: 12762763 | O73: =N73 -> 12762763 | P73: 0 | Q73: 2870 | R73: 6339 | S73: 61172 | T73: 711583 | U73: 1495390 | V73: 1891893 | W73: 5438346 | X73: 6548037 | Y73: 6819195 | Z73: 7620746 | AA73: 11724749 | AB73: =AA73 -> 11724749 | AC73: 109 | AD73: 109 | AE73: 251411 | AF73: 311698 | AG73: 338921 | AH73: 351062 | AI73: 353892 | AJ73: 600284 | AK73: 745907 | AL73: 1013149 | AM73: 1394994 | AN73: 2658727 | AO73: =AN73 -> 2658727 | AP73: 309 | AQ73: 845 | AR73: 11077 | AS73: 123120 | AT73: 196933 | AU73: 285370 | AV73: 547537 | AW73: 1009460 | AX73: 1211237 | AY73: 1293769 | AZ73: 1785704 | BA73: 14200656 | BB73: =BA73 -> 14200656 | BC73: 0 | BD73: 0 | BE73: 724 | BF73: 1893231 | BG73: 2311385 | BH73: 4280160 | BI73: 4296433 | BJ73: 4363606 | BK73: 4486603 | BL73: 5980395 | BM73: 6124209 | BN73: 8256058 | BO73: =BN73 -> 8256058 | BP73: 48 | BQ73: 1255 | BR73: 3121 | BS73: 11999 | BT73: 16209 | BU73: 43534 | BV73: 168962 | BW73: 238287 | BX73: 426172 | BY73: 469766 | BZ73: 1120608 | CA73: 6641118 | CB73: =CA73 -> 6641118 | CC73: 0 | CD73: 585 | CE73: 52513 | CF73: 57523 | CG73: 76947 | CH73: 149037 | CI73: 167768 | CJ73: 176713 | CK73: 779715 | CL73: 783383 | CM73: 1097528 | CN73: 5843319 | CO73: =CN73 -> 5843319 | CP73: 0 | CQ73: 425938 | CR73: 1462761 | CS73: 1465974 | CT73: 1481099 | CU73: 1512434 | CV73: 2183844 | CW73: 2347779 | CX73: 2386510 | CY73: 2529946 | CZ73: 3094655 | DA73: 4799532 | DB73: =DA73 -> 4799532 | DC73: 0 | DD73: 0 | DE73: 0 | DF73: 0 | DG73: 109962 | DH73: 110961 | DI73: 111701 | DJ73: 117198 | DK73: 205350 | DL73: 218231 | DM73: 306659 | DN73: 8421395 | DO73: =DN73 -> 8421395 | DP73: 0 | DQ73: 0 | DR73: 2948 | DS73: 4062 | DT73: 190131 | DU73: 222054 | DV73: 245430 | DW73: 275973 | DX73: 456665 | DY73: 720929 | DZ73: 963668 | EA73: 7135336 | EB73: =EA73 -> 7135336 | EC73: 0 | ED73: 0 | EE73: 0 | EF73: 0 | EG73: 1714 | EH73: 3731 | EI73: 3731 | EJ73: 53443 | EK73: 187144 | EL73: 187248 | EM73: 221037 | EN73: 1123525 | EO73: =EN73 -> 1123525 | EP73: 0 | EQ73: 0 | ER73: 0 | ES73: 3488 | ET73: 3488 | EU73: 6802 | EV73: 6802 | EW73: 205085 | EX73: 215026 | EY73: 319809 | EZ73: 541271 | FA73: 2174604 | FB73: =FA73 -> 2174604 | FC73: 0 | FD73: 0 | FE73: 0 | FF73: 1547 | FG73: 1547 | FH73: 4001 | FI73: 4001 | FO73: =FI73 -> 4001
B74: Dirección de Obras Hidráulicas | C74: 1034 | D74: 1034 | E74: 54953 | F74: 56185 | G74: 56766 | H74: 58287 | I74: 81035 | J74: 124589 | K74: 127877 | L74: 227166 | M74: 271989 | N74: 381174 | O74: =N74 -> 381174 | P74: 0 | Q74: 600 | R74: 2848 | S74: 35886 | T74: 37141 | U74: 46047 | V74: 56945 | W74: 89534 | X74: 202171 | Y74: 217407 | Z74: 234284 | AA74: 362008 | AB74: =AA74 -> 362008 | AC74: 81 | AD74: 6200 | AE74: 42765 | AF74: 67427 | AG74: 221926 | AH74: 224260 | AI74: 226362 | AJ74: 229974 | AK74: 231250 | AL74: 232453 | AM74: 234657 | AN74: 257788 | AO74: =AN74 -> 257788 | AP74: 883 | AQ74: 883 | AR74: 883 | AS74: 883 | AT74: 1928 | AU74: 15652 | AV74: 23980 | AW74: 46130 | AX74: 130300 | AY74: 484366 | AZ74: 489621 | BA74: 521394 | BB74: =BA74 -> 521394 | BC74: 0 | BD74: 0 | BE74: 68075 | BF74: 70711 | BG74: 70737 | BH74: 71042 | BI74: 72990 | BJ74: 75523 | BK74: 76055 | BL74: 76160 | BM74: 82646 | BN74: 3222076 | BO74: =BN74 -> 3222076 | BP74: 0 | BQ74: 8598 | BR74: 8707 | BS74: 9293 | BT74: 18342 | BU74: 19070 | BV74: 23140 | BW74: 58242 | BX74: 74817 | BY74: 83298 | BZ74: 90462 | CA74: 735491 | CB74: =CA74 -> 735491 | CC74: 94 | CD74: 586 | CE74: 2824 | CF74: 2824 | CG74: 2903 | CH74: 4098 | CI74: 4690 | CJ74: 16234 | CK74: 16234 | CL74: 21529 | CM74: 21819 | CN74: 106457 | CO74: =CN74 -> 106457 | CP74: 0 | CQ74: 0 | CR74: 0 | CS74: 690 | CT74: 690 | CU74: 890 | CV74: 890 | CW74: 890 | CX74: 26583 | CY74: 37934 | CZ74: 117361 | DA74: 703694 | DB74: =DA74 -> 703694 | DC74: 0 | DD74: 0 | DE74: 397 | DF74: 397 | DG74: 892 | DH74: 20063 | DI74: 21996 | DJ74: 21996 | DK74: 75465 | DL74: 107933 | DM74: 907010 | DN74: 1149989 | DO74: =DN74 -> 1149989 | DP74: 0 | DQ74: 0 | DR74: 30519 | DS74: 34103 | DT74: 58501 | DU74: 58501 | DV74: 103636 | DW74: 103700 | DX74: 192664 | DY74: 195641 | DZ74: 499753 | EA74: 628857 | EB74: =EA74 -> 628857 | EC74: 0 | ED74: 0 | EE74: 563 | EF74: 2527 | EG74: 3420 | EH74: 355096 | EI74: 359380 | EJ74: 402900 | EK74: 466045 | EL74: 466045 | EM74: 466045 | EN74: 899916 | EO74: =EN74 -> 899916 | EP74: 0 | EQ74: 0 | ER74: 0 | ES74: 2009 | ET74: 37835 | EU74: 73615 | EV74: 253012 | EW74: 572413 | EX74: 586562 | EY74: 603974 | EZ74: 818043 | FA74: 963962 | FB74: =FA74 -> 963962 | FC74: 0 | FD74: 0 | FE74: 0 | FF74: 1508 | FG74: 129364 | FH74: 434033 | FI74: 452929 | FO74: =FI74 -> 452929
B75: Subdirección de APR | C75: 0 | D75: 0 | E75: 0 | F75: 158 | G75: 158 | H75: 2851 | I75: 3091 | J75: 4209 | K75: 4548 | L75: 19543 | M75: 20114 | N75: 39562 | O75: =N75 -> 39562 | P75: 0 | Q75: 0 | R75: 0 | S75: 0 | T75: 50 | U75: 219 | V75: 3752 | W75: 4034 | X75: 15970 | Y75: 48323 | Z75: 48523 | AA75: 78328 | AB75: =AA75 -> 78328 | AC75: 0 | AD75: 0 | AE75: 18172 | AF75: 18172 | AG75: 18909 | AH75: 33441 | AI75: 47973 | AJ75: 47973 | AK75: 47973 | AL75: 47973 | AM75: 47973 | AN75: 62859 | AO75: =AN75 -> 62859 | AP75: 0 | AQ75: 0 | AR75: 0 | AS75: 4582 | AT75: 4582 | AU75: 4910 | AV75: 4910 | AW75: 19278 | AX75: 39213 | AY75: 40363 | AZ75: 43648 | BA75: 48831 | BB75: =BA75 -> 48831 | BC75: 0 | BD75: 0 | BE75: 192566 | BF75: 338581 | BG75: 338766 | BH75: 338897 | BI75: 339144 | BJ75: 340166 | BK75: 352012 | BL75: 354410 | BM75: 359566 | BN75: 371308 | BO75: =BN75 -> 371308 | BP75: 0 | BQ75: 0 | BR75: 6370 | BS75: 28886 | BT75: 28886 | BU75: 32938 | BV75: 33031 | BW75: 113263 | BX75: 129421 | BY75: 134520 | BZ75: 152937 | CA75: 176605 | CB75: =CA75 -> 176605 | CC75: 0 | CD75: 96 | CE75: 5191 | CF75: 5191 | CG75: 5191 | CH75: 6386 | CI75: 6923 | CJ75: 22582 | CK75: 33560 | CL75: 46486 | CM75: 49066 | CN75: 172891 | CO75: =CN75 -> 172891 | CP75: 0 | CQ75: 0 | CR75: 8167 | CS75: 8833 | CT75: 8833 | CU75: 8833 | CV75: 8833 | CW75: 12555 | CX75: 61123 | CY75: 70203 | CZ75: 155639 | DA75: 160231 | DB75: =DA75 -> 160231 | DC75: 0 | DD75: 0 | DE75: 0 | DF75: 0 | DG75: 0 | DH75: 10407 | DI75: 16277 | DJ75: 16277 | DK75: 101440 | DL75: 232681 | DM75: 571170 | DN75: 709579 | DO75: =DN75 -> 709579 | DP75: 20554 | DQ75: 20554 | DR75: 20857 | DS75: 41459 | DT75: 41551 | DU75: 41551 | DV75: 163019 | DW75: 163019 | DX75: 209557 | DY75: 209557 | DZ75: 236874 | EA75: 366748 | EB75: =EA75 -> 366748 | EC75: 10076 | ED75: 10269 | EE75: 10269 | EF75: 10269 | EG75: 13954 | EH75: 337449 | EI75: 337449 | EJ75: 444295 | EK75: 461458 | EL75: 470252 | EM75: 470252 | EN75: 612897 | EO75: =EN75 -> 612897 | EP75: 0 | EQ75: 160 | ER75: 160 | ES75: 160 | ET75: 4515 | EU75: 13374 | EV75: 133195 | EW75: 499807 | EX75: 541550 | EY75: 568299 | EZ75: 873723 | FA75: 1203592 | FB75: =FA75 -> 1203592 | FC75: 0 | FD75: 0 | FE75: 0 | FF75: 13239 | FG75: 126731 | FH75: 371354 | FI75: 409008 | FO75: =FI75 -> 409008
B76: Dirección de Obras Portuarias | C76: 28 | D76: 1653 | E76: 2688 | F76: 4655 | G76: 12025 | H76: 62826 | I76: 63775 | J76: 95480 | K76: 126024 | L76: 127041 | M76: 138557 | N76: 164578 | O76: =N76 -> 164578 | P76: 0 | Q76: 0 | R76: 8688 | S76: 76594 | T76: 147628 | U76: 148375 | V76: 148375 | W76: 180831 | X76: 299063 | Y76: 831232 | Z76: 841681 | AA76: 1887067 | AB76: =AA76 -> 1887067 | AC76: 0 | AD76: 0 | AE76: 3725 | AF76: 21787 | AG76: 600528 | AH76: 600638 | AI76: 1677304 | AJ76: 2766835 | AK76: 3300940 | AL76: 4100106 | AM76: 4283586 | AN76: 4478644 | AO76: =AN76 -> 4478644 | AP76: 42 | AQ76: 799133 | AR76: 799559 | AS76: 815806 | AT76: 928261 | AU76: 932834 | AV76: 949476 | AW76: 1550892 | AX76: 2352528 | AY76: 2352966 | AZ76: 3418204 | BA76: 3716927 | BB76: =BA76 -> 3716927 | BC76: 0 | BD76: 1961 | BE76: 3246 | BF76: 3246 | BG76: 5694 | BH76: 28528 | BI76: 41565 | BJ76: 41622 | BK76: 41622 | BL76: 42767 | BM76: 83821 | BN76: 330448 | BO76: =BN76 -> 330448 | BP76: 29 | BQ76: 29 | BR76: 29 | BS76: 116 | BT76: 208 | BU76: 399 | BV76: 399 | BW76: 399 | BX76: 1919 | BY76: 3160 | BZ76: 299768 | CA76: 863900 | CB76: =CA76 -> 863900 | CC76: 0 | CD76: 176042 | CE76: 176719 | CF76: 176794 | CG76: 441735 | CH76: 442125 | CI76: 443658 | CJ76: 735258 | CK76: 735258 | CL76: 1044245 | CM76: 1483899 | CN76: 1947994 | CO76: =CN76 -> 1947994 | CP76: 0 | CQ76: 20 | CR76: 20 | CS76: 40 | CT76: 40 | CU76: 263823 | CV76: 439678 | CW76: 439678 | CX76: 444855 | CY76: 444855 | CZ76: 458920 | DA76: 485917 | DB76: =DA76 -> 485917 | DC76: 0 | DD76: 0 | DE76: 0 | DF76: 22 | DG76: 22 | DH76: 22 | DI76: 22 | DJ76: 22 | DK76: 21191 | DL76: 82685 | DM76: 447234 | DN76: 865046 | DO76: =DN76 -> 865046 | DP76: 0 | DQ76: 6359 | DR76: 7689 | DS76: 49168 | DT76: 90437 | DU76: 151090 | DV76: 151090 | DW76: 152637 | DX76: 367133 | DY76: 367430 | DZ76: 409162 | EA76: 620613 | EB76: =EA76 -> 620613 | EC76: 0 | ED76: 0 | EE76: 0 | EF76: 1891 | EG76: 25269 | EH76: 68307 | EI76: 92369 | EJ76: 255657 | EK76: 297429 | EL76: 650218 | EM76: 722119 | EN76: 1508486 | EO76: =EN76 -> 1508486 | EP76: 0 | EQ76: 0 | ER76: 0 | ES76: 5944 | ET76: 41309 | EU76: 91749 | EV76: 93532 | EW76: 93532 | EX76: 96960 | EY76: 112867 | EZ76: 143043 | FA76: 248096 | FB76: =FA76 -> 248096 | FC76: 70510 | FD76: 70510 | FE76: 77071 | FF76: 91088 | FG76: 155966 | FH76: 155966 | FI76: 161164 | FO76: =FI76 -> 161164
B77: Dirección de Aeropuertos | C77: 169 | D77: 435 | E77: 39580 | F77: 54505 | G77: 56186 | H77: 57808 | I77: 69634 | J77: 114793 | K77: 128678 | L77: 129341 | M77: 205814 | N77: 230680 | O77: =N77 -> 230680 | P77: 98 | Q77: 907 | R77: 1747 | S77: 39102 | T77: 50749 | U77: 52117 | V77: 53586 | W77: 55733 | X77: 63697 | Y77: 82932 | Z77: 158015 | AA77: 838373 | AB77: =AA77 -> 838373 | AC77: 0 | AD77: 17902 | AE77: 25945 | AF77: 51062 | AG77: 54469 | AH77: 55416 | AI77: 56875 | AJ77: 60356 | AK77: 64353 | AL77: 74033 | AM77: 75711 | AN77: 634425 | AO77: =AN77 -> 634425 | AP77: 0 | AQ77: 269 | AR77: 269 | AS77: 22119 | AT77: 22119 | AU77: 22695 | AV77: 46097 | AW77: 48260 | AX77: 48861 | AY77: 61420 | AZ77: 74200 | BA77: 1758867 | BB77: =BA77 -> 1758867 | BC77: 198 | BD77: 1102 | BE77: 5726 | BF77: 28536 | BG77: 48499 | BH77: 53855 | BI77: 60520 | BJ77: 69445 | BK77: 70064 | BL77: 73093 | BM77: 73356 | BN77: 1605443 | BO77: =BN77 -> 1605443 | BP77: 147 | BQ77: 229 | BR77: 344 | BS77: 3873 | BT77: 25548 | BU77: 41488 | BV77: 43633 | BW77: 48371 | BX77: 69965 | BY77: 76233 | BZ77: 80516 | CA77: 97338 | CB77: =CA77 -> 97338 | CC77: 607 | CD77: 1736 | CE77: 2472 | CF77: 2472 | CG77: 18311 | CH77: 18311 | CI77: 18985 | CJ77: 18985 | CK77: 21184 | CL77: 31168 | CM77: 33157 | CN77: 382693 | CO77: =CN77 -> 382693 | CP77: 0 | CQ77: 0 | CR77: 0 | CS77: 0 | CT77: 375 | CU77: 375 | CV77: 375 | CW77: 375 | CX77: 16453 | CY77: 16738 | CZ77: 59581 | DA77: 101089 | DB77: =DA77 -> 101089 | DC77: 0 | DD77: 0 | DE77: 0 | DF77: 43 | DG77: 43 | DH77: 638 | DI77: 3960 | DJ77: 60216 | DK77: 61185 | DL77: 67106 | DM77: 95932 | DN77: 160797 | DO77: =DN77 -> 160797 | DP77: 0 | DQ77: 0 | DR77: 0 | DS77: 0 | DT77: 3085 | DU77: 82381 | DV77: 125991 | DW77: 140950 | DX77: 158342 | DY77: 163795 | DZ77: 191564 | EA77: 237804 | EB77: =EA77 -> 237804 | EC77: 0 | ED77: 0 | EE77: 0 | EF77: 2262 | EG77: 74380 | EH77: 161068 | EI77: 226500 | EJ77: 235972 | EK77: 1485698 | EL77: 1613690 | EM77: 1931498 | EN77: 1997225 | EO77: =EN77 -> 1997225 | EP77: 0 | EQ77: 97469 | ER77: 97751 | ES77: 98001 | ET77: 170182 | EU77: 170245 | EV77: 421065 | EW77: 428624 | EX77: 444757 | EY77: 610730 | EZ77: 614072 | FA77: 809633 | FB77: =FA77 -> 809633 | FC77: 0 | FD77: 0 | FE77: 0 | FF77: 0 | FG77: 0 | FH77: 64950 | FI77: 127454 | FO77: =FI77 -> 127454
B78: Dirección de Arquitectura | C78: 140 | D78: 8109 | E78: 8109 | F78: 8613 | G78: 84253 | H78: 84548 | I78: 86349 | J78: 86349 | K78: 86399 | L78: 98968 | M78: 117677 | N78: 141920 | O78: =N78 -> 141920 | P78: 0 | Q78: 60 | R78: 60 | S78: 2161 | T78: 36520 | U78: 61061 | V78: 74560 | W78: 75213 | X78: 75636 | Y78: 79205 | Z78: 177440 | AA78: 295571 | AB78: =AA78 -> 295571 | AC78: 0 | AD78: 19653 | AE78: 32728 | AF78: 33680 | AG78: 35995 | AH78: 38174 | AI78: 38528 | AJ78: 39517 | AK78: 41442 | AL78: 42876 | AM78: 54418 | AN78: 95971 | AO78: =AN78 -> 95971 | AP78: 0 | AQ78: 1007 | AR78: 1387 | AS78: 4088 | AT78: 18570 | AU78: 18846 | AV78: 38317 | AW78: 42381 | AX78: 45866 | AY78: 54771 | AZ78: 81489 | BA78: 95609 | BB78: =BA78 -> 95609 | BC78: 0 | BD78: 3271 | BE78: 3271 | BF78: 3389 | BG78: 4357 | BH78: 10454 | BI78: 14421 | BJ78: 18234 | BK78: 59217 | BL78: 60033 | BM78: 68642 | BN78: 297380 | BO78: =BN78 -> 297380 | BP78: 693 | BQ78: 15530 | BR78: 15631 | BS78: 20846 | BT78: 65721 | BU78: 89898 | BV78: 92591 | BW78: 100668 | BX78: 100991 | BY78: 103952 | BZ78: 109621 | CA78: 111876 | CB78: =CA78 -> 111876 | CC78: 0 | CD78: 1098 | CE78: 3137 | CF78: 17987 | CG78: 22135 | CH78: 22135 | CI78: 29972 | CJ78: 79295 | CK78: 84364 | CL78: 87854 | CM78: 95431 | CN78: 107174 | CO78: =CN78 -> 107174 | CP78: 0 | CQ78: 0 | CR78: 0 | CS78: 0 | CT78: 0 | CU78: 0 | CV78: 0 | CW78: 0 | CX78: 0 | CY78: 0 | CZ78: 38499 | DA78: 107372 | DB78: =DA78 -> 107372 | DC78: 0 | DD78: 0 | DE78: 0 | DF78: 0 | DG78: 0 | DH78: 0 | DI78: 1222 | DJ78: 9602 | DK78: 92334 | DL78: 96189 | DM78: 319595 | DN78: 395574 | DO78: =DN78 -> 395574 | DP78: 0 | DQ78: 333 | DR78: 581 | DS78: 17754 | DT78: 70246 | DU78: 92472 | DV78: 321438 | DW78: 325356 | DX78: 420771 | DY78: 450435 | DZ78: 501604 | EA78: 554997 | EB78: =EA78 -> 554997 | EC78: 0 | ED78: 47980 | EE78: 92337 | EF78: 95895 | EG78: 268337 | EH78: 389981 | EI78: 421650 | EJ78: 428305 | EK78: 503200 | EL78: 506685 | EM78: 563895 | EN78: 631827 | EO78: =EN78 -> 631827 | EP78: 0 | EQ78: 33966 | ER78: 39677 | ES78: 68547 | ET78: 184933 | EU78: 316527 | EV78: 324773 | EW78: 324773 | EX78: 329257 | EY78: 333451 | EZ78: 436896 | FA78: 504566 | FB78: =FA78 -> 504566 | FC78: 0 | FD78: 0 | FE78: 59187 | FF78: 68554 | FG78: 87338 | FH78: 87338 | FI78: 87338 | FO78: =FI78 -> 87338
B79: Total | C79: =SUM(C73:C78) -> 1371 | D79: =SUM(D73:D78) -> 14594 | E79: =SUM(E73:E78) -> 195096 | F79: =SUM(F73:F78) -> 301989 | G79: =SUM(G73:G78) -> 556759 | H79: =SUM(H73:H78) -> 1034775 | I79: =SUM(I73:I78) -> 1426755 | J79: =SUM(J73:J78) -> 1993508 | ... FO79: =SUM(FO73:FO78) -> 1241894
B80: Fuente: elaboración propia, Dipres.
B83: Subtítulo 33 – Transferencias de Capital
B85: Presupuesto Ley de Inversión en Infraestructura Pública del Ministerio de Obras Públicas, 2014-2026 (Subtítulo 33 – Transferencias de Capital, miles de pesos)
C86: 2014 | P86: 2015 | AC86: 2016 | AP86: 2017 | BC86: 2018 | BP86: 2019 | CC86: 2020 | CP86: 2021 | DC86: 2022 | DP86: 2023 | EC86: 2024 | EP86: 2025 | FC86: 2026
B87: Programa | C87: Ene | D87: Feb | E87: Mar | F87: Abr | G87: May | H87: Jun | I87: Jul | J87: Ago | K87: Sep | L87: Oct | M87: Nov | N87: Dic | O87: Total 2014 | P87: Ene | Q87: Feb | R87: Mar | S87: Abr | T87: May | U87: Jun | V87: Jul | W87: Ago | X87: Sep | Y87: Oct | Z87: Nov | AA87: Dic | AB87: Total 2015 | AC87: Ene | AD87: Feb | AE87: Mar | AF87: Abr | AG87: May | AH87: Jun | AI87: Jul | AJ87: Ago | AK87: Sep | AL87: Oct | AM87: Nov | AN87: Dic | AO87: Total 2016 | AP87: Ene | AQ87: Feb | AR87: Mar | AS87: Abr | AT87: May | AU87: Jun | AV87: Jul | AW87: Ago | AX87: Sep | AY87: Oct | AZ87: Nov | BA87: Dic | BB87: Total 2017 | BC87: Ene | BD87: Feb | BE87: Mar | BF87: Abr | BG87: May | BH87: Jun | BI87: Jul | BJ87: Ago | BK87: Sep | BL87: Oct | BM87: Nov | BN87: Dic | BO87: Total 2018 | BP87: Ene | BQ87: Feb | BR87: Mar | BS87: Abr | BT87: May | BU87: Jun | BV87: Jul | BW87: Ago | BX87: Sep | BY87: Oct | BZ87: Nov | CA87: Dic | CB87: Total 2019 | CC87: Ene | CD87: Feb | CE87: Mar | CF87: Abr | CG87: May | CH87: Jun | CI87: Jul | CJ87: Ago | CK87: Sep | CL87: Oct | CM87: Nov | CN87: Dic | CO87: Total 2020 | CP87: Ene | CQ87: Feb | CR87: Mar | CS87: Abr | CT87: May | CU87: Jun | CV87: Jul | CW87: Ago | CX87: Sep | CY87: Oct | CZ87: Nov | DA87: Dic | DB87: Total 2021 | DC87: Ene | DD87: Feb | DE87: Mar | DF87: Abr | DG87: May | DH87: Jun | DI87: Jul | DJ87: Ago | DK87: Sep | DL87: Oct | DM87: Nov | DN87: Dic | DO87: Total 2022 | DP87: Ene | DQ87: Feb | DR87: Mar | DS87: Abr | DT87: May | DU87: Jun | DV87: Jul | DW87: Ago | DX87: Sep | DY87: Oct | DZ87: Nov | EA87: Dic | EB87: Total 2023 | EC87: Ene | ED87: Feb | EE87: Mar | EF87: Abr | EG87: May | EH87: Jun | EI87: Jul | EJ87: Ago | EK87: Sep | EL87: Oct | EM87: Nov | EN87: Dic | EO87: Total 2024 | EP87: Ene | EQ87: Feb | ER87: Mar | ES87: Abr | ET87: May | EU87: Jun | EV87: Jul | EW87: Ago | EX87: Sep | EY87: Oct | EZ87: Nov | FA87: Dic | FB87: Total 2025 | FC87: Ene | FD87: Feb | FE87: Mar | FF87: Abr | FG87: May | FH87: Jun | FI87: Jul | FJ87: Ago | FK87: Sep | FL87: Oct | FM87: Nov | FN87: Dic | FO87: Total 2026
B88: Dirección de Vialidad | C88: 0 | D88: 0 | E88: 0 | F88: 0 | G88: 0 | H88: 0 | I88: 0 | J88: 0 | K88: 0 | L88: 0 | M88: 0 | N88: 0 | O88: =N88 -> 0 | P88: 0 | Q88: 0 | R88: 0 | S88: 0 | T88: 0 | U88: 0 | V88: 0 | W88: 0 | X88: 0 | Y88: 0 | Z88: 0 | AA88: 0 | AB88: =AA88 -> 0 | AC88: 0 | AD88: 0 | AE88: 0 | AF88: 0 | AG88: 0 | AH88: 0 | AI88: 0 | AJ88: 0 | AK88: 0 | AL88: 0 | AM88: 0 | AN88: 0 | AO88: =AN88 -> 0 | AP88: 0 | AQ88: 0 | AR88: 0 | AS88: 0 | AT88: 0 | AU88: 0 | AV88: 0 | AW88: 0 | AX88: 0 | AY88: 0 | AZ88: 0 | BA88: 0 | BB88: =BA88 -> 0 | BC88: 0 | BD88: 0 | BE88: 0 | BF88: 0 | BG88: 0 | BH88: 0 | BI88: 0 | BJ88: 0 | BK88: 0 | BL88: 0 | BM88: 0 | BN88: 0 | BO88: =BN88 -> 0 | BP88: 0 | BQ88: 0 | BR88: 0 | BS88: 0 | BT88: 0 | BU88: 0 | BV88: 0 | BW88: 0 | BX88: 0 | BY88: 0 | BZ88: 0 | CA88: 0 | CB88: =CA88 -> 0 | CC88: 0 | CD88: 0 | CE88: 0 | CF88: 0 | CG88: 0 | CH88: 0 | CI88: 0 | CJ88: 0 | CK88: 0 | CL88: 0 | CM88: 0 | CN88: 0 | CO88: =CN88 -> 0 | CP88: 0 | CQ88: 0 | CR88: 0 | CS88: 0 | CT88: 0 | CU88: 0 | CV88: 0 | CW88: 0 | CX88: 0 | CY88: 0 | CZ88: 0 | DA88: 0 | DB88: =DA88 -> 0 | DC88: 0 | DD88: 0 | DE88: 0 | DF88: 0 | DG88: 0 | DH88: 0 | DI88: 0 | DJ88: 0 | DK88: 0 | DL88: 0 | DM88: 0 | DN88: 0 | DO88: =DN88 -> 0 | DP88: 0 | DQ88: 0 | DR88: 0 | DS88: 0 | DT88: 0 | DU88: 0 | DV88: 0 | DW88: 0 | DX88: 0 | DY88: 0 | DZ88: 0 | EA88: 0 | EB88: =EA88 -> 0 | EC88: 0 | ED88: 0 | EE88: 0 | EF88: 0 | EG88: 0 | EH88: 0 | EI88: 0 | EJ88: 0 | EK88: 0 | EL88: 0 | EM88: 0 | EN88: 0 | EO88: =EN88 -> 0 | EP88: 0 | EQ88: 0 | ER88: 0 | ES88: 0 | ET88: 0 | EU88: 0 | EV88: 0 | EW88: 0 | EX88: 0 | EY88: 0 | EZ88: 0 | FA88: 0 | FB88: =FA88 -> 0 | FC88: 0 | FD88: 0 | FE88: 0 | FF88: 0 | FG88: 0 | FH88: 0 | FI88: 0 | FO88: =FI88 -> 0
B89: Dirección de Obras Hidráulicas | C89: 0 | D89: 0 | E89: 0 | F89: 0 | G89: 0 | H89: 0 | I89: 0 | J89: 0 | K89: 0 | L89: 0 | M89: 0 | N89: 0 | O89: =N89 -> 0 | P89: 0 | Q89: 0 | R89: 0 | S89: 0 | T89: 0 | U89: 0 | V89: 0 | W89: 0 | X89: 0 | Y89: 0 | Z89: 0 | AA89: 0 | AB89: =AA89 -> 0 | AC89: 0 | AD89: 0 | AE89: 0 | AF89: 0 | AG89: 0 | AH89: 0 | AI89: 0 | AJ89: 0 | AK89: 0 | AL89: 0 | AM89: 0 | AN89: 0 | AO89: =AN89 -> 0 | AP89: 0 | AQ89: 0 | AR89: 0 | AS89: 0 | AT89: 0 | AU89: 0 | AV89: 0 | AW89: 0 | AX89: 0 | AY89: 0 | AZ89: 0 | BA89: 0 | BB89: =BA89 -> 0 | BC89: 0 | BD89: 0 | BE89: 0 | BF89: 0 | BG89: 0 | BH89: 0 | BI89: 0 | BJ89: 0 | BK89: 0 | BL89: 0 | BM89: 0 | BN89: 0 | BO89: =BN89 -> 0 | BP89: 0 | BQ89: 0 | BR89: 0 | BS89: 0 | BT89: 0 | BU89: 0 | BV89: 0 | BW89: 0 | BX89: 0 | BY89: 0 | BZ89: 0 | CA89: 0 | CB89: =CA89 -> 0 | CC89: 0 | CD89: 0 | CE89: 0 | CF89: 0 | CG89: 0 | CH89: 0 | CI89: 0 | CJ89: 0 | CK89: 0 | CL89: 0 | CM89: 0 | CN89: 0 | CO89: =CN89 -> 0 | CP89: 0 | CQ89: 0 | CR89: 0 | CS89: 0 | CT89: 0 | CU89: 0 | CV89: 0 | CW89: 0 | CX89: 0 | CY89: 0 | CZ89: 0 | DA89: 0 | DB89: =DA89 -> 0 | DC89: 0 | DD89: 0 | DE89: 0 | DF89: 0 | DG89: 0 | DH89: 0 | DI89: 0 | DJ89: 0 | DK89: 0 | DL89: 0 | DM89: 0 | DN89: 0 | DO89: =DN89 -> 0 | DP89: 0 | DQ89: 0 | DR89: 0 | DS89: 0 | DT89: 0 | DU89: 0 | DV89: 0 | DW89: 0 | DX89: 0 | DY89: 0 | DZ89: 0 | EA89: 0 | EB89: =EA89 -> 0 | EC89: 0 | ED89: 0 | EE89: 0 | EF89: 0 | EG89: 0 | EH89: 0 | EI89: 0 | EJ89: 0 | EK89: 0 | EL89: 0 | EM89: 0 | EN89: 0 | EO89: =EN89 -> 0 | EP89: 0 | EQ89: 0 | ER89: 0 | ES89: 0 | ET89: 0 | EU89: 0 | EV89: 0 | EW89: 0 | EX89: 0 | EY89: 0 | EZ89: 0 | FA89: 0 | FB89: =FA89 -> 0 | FC89: 0 | FD89: 0 | FE89: 0 | FF89: 0 | FG89: 0 | FH89: 0 | FI89: 0 | FO89: =FI89 -> 0
B90: Subdirección de APR | C90: 0 | D90: 0 | E90: 0 | F90: 0 | G90: 0 | H90: 0 | I90: 0 | J90: 0 | K90: 0 | L90: 0 | M90: 0 | N90: 0 | O90: =N90 -> 0 | P90: 0 | Q90: 0 | R90: 0 | S90: 0 | T90: 0 | U90: 0 | V90: 0 | W90: 0 | X90: 0 | Y90: 0 | Z90: 0 | AA90: 0 | AB90: =AA90 -> 0 | AC90: 0 | AD90: 0 | AE90: 0 | AF90: 0 | AG90: 0 | AH90: 0 | AI90: 0 | AJ90: 0 | AK90: 0 | AL90: 0 | AM90: 0 | AN90: 0 | AO90: =AN90 -> 0 | AP90: 0 | AQ90: 0 | AR90: 0 | AS90: 0 | AT90: 0 | AU90: 0 | AV90: 0 | AW90: 0 | AX90: 0 | AY90: 0 | AZ90: 0 | BA90: 0 | BB90: =BA90 -> 0 | BC90: 0 | BD90: 0 | BE90: 0 | BF90: 0 | BG90: 0 | BH90: 0 | BI90: 0 | BJ90: 0 | BK90: 0 | BL90: 0 | BM90: 0 | BN90: 0 | BO90: =BN90 -> 0 | BP90: 0 | BQ90: 0 | BR90: 0 | BS90: 0 | BT90: 0 | BU90: 0 | BV90: 0 | BW90: 0 | BX90: 0 | BY90: 0 | BZ90: 0 | CA90: 0 | CB90: =CA90 -> 0 | CC90: 0 | CD90: 0 | CE90: 0 | CF90: 0 | CG90: 0 | CH90: 0 | CI90: 0 | CJ90: 0 | CK90: 0 | CL90: 0 | CM90: 0 | CN90: 0 | CO90: =CN90 -> 0 | CP90: 0 | CQ90: 0 | CR90: 0 | CS90: 0 | CT90: 0 | CU90: 0 | CV90: 0 | CW90: 0 | CX90: 0 | CY90: 0 | CZ90: 0 | DA90: 0 | DB90: =DA90 -> 0 | DC90: 0 | DD90: 0 | DE90: 0 | DF90: 0 | DG90: 0 | DH90: 0 | DI90: 0 | DJ90: 0 | DK90: 0 | DL90: 0 | DM90: 0 | DN90: 0 | DO90: =DN90 -> 0 | DP90: 17877772 | DQ90: 17877772 | DR90: 17877772 | DS90: 17877772 | DT90: 17877772 | DU90: 17877772 | DV90: 17877772 | DW90: 17877772 | DX90: 17877772 | DY90: 17877772 | DZ90: 17877772 | EA90: 17877772 | EB90: =EA90 -> 17877772 | EC90: 0 | ED90: 0 | EE90: 0 | EF90: 0 | EG90: 0 | EH90: 0 | EI90: 0 | EJ90: 0 | EK90: 0 | EL90: 0 | EM90: 0 | EN90: 0 | EO90: =EN90 -> 0 | EP90: 0 | EQ90: 0 | ER90: 0 | ES90: 0 | ET90: 0 | EU90: 0 | EV90: 0 | EW90: 0 | EX90: 0 | EY90: 0 | EZ90: 0 | FA90: 0 | FB90: =FA90 -> 0 | FC90: 0 | FD90: 0 | FE90: 0 | FF90: 0 | FG90: 0 | FH90: 0 | FI90: 0 | FO90: =FI90 -> 0
B91: Dirección de Obras Portuarias | C91: 0 | D91: 0 | E91: 0 | F91: 0 | G91: 0 | H91: 0 | I91: 0 | J91: 0 | K91: 0 | L91: 0 | M91: 0 | N91: 0 | O91: =N91 -> 0 | P91: 0 | Q91: 0 | R91: 0 | S91: 0 | T91: 0 | U91: 0 | V91: 0 | W91: 0 | X91: 0 | Y91: 0 | Z91: 0 | AA91: 0 | AB91: =AA91 -> 0 | AC91: 0 | AD91: 0 | AE91: 0 | AF91: 0 | AG91: 0 | AH91: 0 | AI91: 0 | AJ91: 0 | AK91: 0 | AL91: 0 | AM91: 0 | AN91: 0 | AO91: =AN91 -> 0 | AP91: 0 | AQ91: 0 | AR91: 0 | AS91: 0 | AT91: 0 | AU91: 0 | AV91: 0 | AW91: 0 | AX91: 0 | AY91: 0 | AZ91: 0 | BA91: 0 | BB91: =BA91 -> 0 | BC91: 0 | BD91: 0 | BE91: 0 | BF91: 0 | BG91: 0 | BH91: 0 | BI91: 0 | BJ91: 0 | BK91: 0 | BL91: 0 | BM91: 0 | BN91: 0 | BO91: =BN91 -> 0 | BP91: 0 | BQ91: 0 | BR91: 0 | BS91: 0 | BT91: 0 | BU91: 0 | BV91: 0 | BW91: 0 | BX91: 0 | BY91: 0 | BZ91: 0 | CA91: 0 | CB91: =CA91 -> 0 | CC91: 0 | CD91: 0 | CE91: 0 | CF91: 0 | CG91: 0 | CH91: 0 | CI91: 0 | CJ91: 0 | CK91: 0 | CL91: 0 | CM91: 0 | CN91: 0 | CO91: =CN91 -> 0 | CP91: 0 | CQ91: 0 | CR91: 0 | CS91: 0 | CT91: 0 | CU91: 0 | CV91: 0 | CW91: 0 | CX91: 0 | CY91: 0 | CZ91: 0 | DA91: 0 | DB91: =DA91 -> 0 | DC91: 0 | DD91: 0 | DE91: 0 | DF91: 0 | DG91: 0 | DH91: 0 | DI91: 0 | DJ91: 0 | DK91: 0 | DL91: 0 | DM91: 0 | DN91: 0 | DO91: =DN91 -> 0 | DP91: 0 | DQ91: 0 | DR91: 0 | DS91: 0 | DT91: 0 | DU91: 0 | DV91: 0 | DW91: 0 | DX91: 0 | DY91: 0 | DZ91: 0 | EA91: 0 | EB91: =EA91 -> 0 | EC91: 0 | ED91: 0 | EE91: 0 | EF91: 0 | EG91: 0 | EH91: 0 | EI91: 0 | EJ91: 0 | EK91: 0 | EL91: 0 | EM91: 0 | EN91: 0 | EO91: =EN91 -> 0 | EP91: 0 | EQ91: 0 | ER91: 0 | ES91: 0 | ET91: 0 | EU91: 0 | EV91: 0 | EW91: 0 | EX91: 0 | EY91: 0 | EZ91: 0 | FA91: 0 | FB91: =FA91 -> 0 | FC91: 0 | FD91: 0 | FE91: 0 | FF91: 0 | FG91: 0 | FH91: 0 | FI91: 0 | FO91: =FI91 -> 0
B92: Dirección de Aeropuertos | C92: 0 | D92: 0 | E92: 0 | F92: 0 | G92: 0 | H92: 0 | I92: 0 | J92: 0 | K92: 0 | L92: 0 | M92: 0 | N92: 0 | O92: =N92 -> 0 | P92: 0 | Q92: 0 | R92: 0 | S92: 0 | T92: 0 | U92: 0 | V92: 0 | W92: 0 | X92: 0 | Y92: 0 | Z92: 0 | AA92: 0 | AB92: =AA92 -> 0 | AC92: 0 | AD92: 0 | AE92: 0 | AF92: 0 | AG92: 0 | AH92: 0 | AI92: 0 | AJ92: 0 | AK92: 0 | AL92: 0 | AM92: 0 | AN92: 0 | AO92: =AN92 -> 0 | AP92: 0 | AQ92: 0 | AR92: 0 | AS92: 0 | AT92: 0 | AU92: 0 | AV92: 0 | AW92: 0 | AX92: 0 | AY92: 0 | AZ92: 0 | BA92: 0 | BB92: =BA92 -> 0 | BC92: 0 | BD92: 0 | BE92: 0 | BF92: 0 | BG92: 0 | BH92: 0 | BI92: 0 | BJ92: 0 | BK92: 0 | BL92: 0 | BM92: 0 | BN92: 0 | BO92: =BN92 -> 0 | BP92: 0 | BQ92: 0 | BR92: 0 | BS92: 0 | BT92: 0 | BU92: 0 | BV92: 0 | BW92: 0 | BX92: 0 | BY92: 0 | BZ92: 0 | CA92: 0 | CB92: =CA92 -> 0 | CC92: 0 | CD92: 0 | CE92: 0 | CF92: 0 | CG92: 0 | CH92: 0 | CI92: 0 | CJ92: 0 | CK92: 0 | CL92: 0 | CM92: 0 | CN92: 0 | CO92: =CN92 -> 0 | CP92: 0 | CQ92: 0 | CR92: 0 | CS92: 0 | CT92: 0 | CU92: 0 | CV92: 0 | CW92: 0 | CX92: 0 | CY92: 0 | CZ92: 0 | DA92: 0 | DB92: =DA92 -> 0 | DC92: 0 | DD92: 0 | DE92: 0 | DF92: 0 | DG92: 0 | DH92: 0 | DI92: 0 | DJ92: 0 | DK92: 0 | DL92: 0 | DM92: 0 | DN92: 0 | DO92: =DN92 -> 0 | DP92: 0 | DQ92: 0 | DR92: 0 | DS92: 0 | DT92: 0 | DU92: 0 | DV92: 0 | DW92: 0 | DX92: 0 | DY92: 0 | DZ92: 0 | EA92: 0 | EB92: =EA92 -> 0 | EC92: 0 | ED92: 0 | EE92: 0 | EF92: 0 | EG92: 0 | EH92: 0 | EI92: 0 | EJ92: 0 | EK92: 0 | EL92: 0 | EM92: 0 | EN92: 0 | EO92: =EN92 -> 0 | EP92: 0 | EQ92: 0 | ER92: 0 | ES92: 0 | ET92: 0 | EU92: 0 | EV92: 0 | EW92: 0 | EX92: 0 | EY92: 0 | EZ92: 0 | FA92: 0 | FB92: =FA92 -> 0 | FC92: 0 | FD92: 0 | FE92: 0 | FF92: 0 | FG92: 0 | FH92: 0 | FI92: 0 | FO92: =FI92 -> 0
B93: Dirección de Arquitectura | C93: 0 | D93: 0 | E93: 0 | F93: 0 | G93: 0 | H93: 0 | I93: 0 | J93: 0 | K93: 0 | L93: 0 | M93: 0 | N93: 0 | O93: =N93 -> 0 | P93: 0 | Q93: 0 | R93: 0 | S93: 0 | T93: 0 | U93: 0 | V93: 0 | W93: 0 | X93: 0 | Y93: 0 | Z93: 0 | AA93: 0 | AB93: =AA93 -> 0 | AC93: 0 | AD93: 0 | AE93: 0 | AF93: 0 | AG93: 0 | AH93: 0 | AI93: 0 | AJ93: 0 | AK93: 0 | AL93: 0 | AM93: 0 | AN93: 0 | AO93: =AN93 -> 0 | AP93: 0 | AQ93: 0 | AR93: 0 | AS93: 0 | AT93: 0 | AU93: 0 | AV93: 0 | AW93: 0 | AX93: 0 | AY93: 0 | AZ93: 0 | BA93: 0 | BB93: =BA93 -> 0 | BC93: 0 | BD93: 0 | BE93: 0 | BF93: 0 | BG93: 0 | BH93: 0 | BI93: 0 | BJ93: 0 | BK93: 0 | BL93: 0 | BM93: 0 | BN93: 0 | BO93: =BN93 -> 0 | BP93: 0 | BQ93: 0 | BR93: 0 | BS93: 0 | BT93: 0 | BU93: 0 | BV93: 0 | BW93: 0 | BX93: 0 | BY93: 0 | BZ93: 0 | CA93: 0 | CB93: =CA93 -> 0 | CC93: 0 | CD93: 0 | CE93: 0 | CF93: 0 | CG93: 0 | CH93: 0 | CI93: 0 | CJ93: 0 | CK93: 0 | CL93: 0 | CM93: 0 | CN93: 0 | CO93: =CN93 -> 0 | CP93: 0 | CQ93: 0 | CR93: 0 | CS93: 0 | CT93: 0 | CU93: 0 | CV93: 0 | CW93: 0 | CX93: 0 | CY93: 0 | CZ93: 0 | DA93: 0 | DB93: =DA93 -> 0 | DC93: 0 | DD93: 0 | DE93: 0 | DF93: 0 | DG93: 0 | DH93: 0 | DI93: 0 | DJ93: 0 | DK93: 0 | DL93: 0 | DM93: 0 | DN93: 0 | DO93: =DN93 -> 0 | DP93: 0 | DQ93: 0 | DR93: 0 | DS93: 0 | DT93: 0 | DU93: 0 | DV93: 0 | DW93: 0 | DX93: 0 | DY93: 0 | DZ93: 0 | EA93: 0 | EB93: =EA93 -> 0 | EC93: 0 | ED93: 0 | EE93: 0 | EF93: 0 | EG93: 0 | EH93: 0 | EI93: 0 | EJ93: 0 | EK93: 0 | EL93: 0 | EM93: 0 | EN93: 0 | EO93: =EN93 -> 0 | EP93: 0 | EQ93: 0 | ER93: 0 | ES93: 0 | ET93: 0 | EU93: 0 | EV93: 0 | EW93: 0 | EX93: 0 | EY93: 0 | EZ93: 0 | FA93: 0 | FB93: =FA93 -> 0 | FC93: 0 | FD93: 0 | FE93: 0 | FF93: 0 | FG93: 0 | FH93: 0 | FI93: 0 | FO93: =FI93 -> 0
B94: Total | C94: =SUM(C88:C93) -> 0 | D94: =SUM(D88:D93) -> 0 | E94: =SUM(E88:E93) -> 0 | F94: =SUM(F88:F93) -> 0 | G94: =SUM(G88:G93) -> 0 | H94: =SUM(H88:H93) -> 0 | I94: =SUM(I88:I93) -> 0 | J94: =SUM(J88:J93) -> 0 | ... FO94: =SUM(FO88:FO93) -> 0
B95: El Subtítulo 33 solo aparece en APR, desde 2023. En los demás Programas y años no está en los informes de ejecución. Fuente: elaboración propia, Dipres.
B97: Presupuesto Vigente de Inversión en Infraestructura Pública del Ministerio de Obras Públicas, 2014-2026 (Subtítulo 33 – Transferencias de Capital, miles de pesos)
C98: 2014 | P98: 2015 | AC98: 2016 | AP98: 2017 | BC98: 2018 | BP98: 2019 | CC98: 2020 | CP98: 2021 | DC98: 2022 | DP98: 2023 | EC98: 2024 | EP98: 2025 | FC98: 2026
B99: Programa | C99: Ene | D99: Feb | E99: Mar | F99: Abr | G99: May | H99: Jun | I99: Jul | J99: Ago | K99: Sep | L99: Oct | M99: Nov | N99: Dic | O99: Total 2014 | P99: Ene | Q99: Feb | R99: Mar | S99: Abr | T99: May | U99: Jun | V99: Jul | W99: Ago | X99: Sep | Y99: Oct | Z99: Nov | AA99: Dic | AB99: Total 2015 | AC99: Ene | AD99: Feb | AE99: Mar | AF99: Abr | AG99: May | AH99: Jun | AI99: Jul | AJ99: Ago | AK99: Sep | AL99: Oct | AM99: Nov | AN99: Dic | AO99: Total 2016 | AP99: Ene | AQ99: Feb | AR99: Mar | AS99: Abr | AT99: May | AU99: Jun | AV99: Jul | AW99: Ago | AX99: Sep | AY99: Oct | AZ99: Nov | BA99: Dic | BB99: Total 2017 | BC99: Ene | BD99: Feb | BE99: Mar | BF99: Abr | BG99: May | BH99: Jun | BI99: Jul | BJ99: Ago | BK99: Sep | BL99: Oct | BM99: Nov | BN99: Dic | BO99: Total 2018 | BP99: Ene | BQ99: Feb | BR99: Mar | BS99: Abr | BT99: May | BU99: Jun | BV99: Jul | BW99: Ago | BX99: Sep | BY99: Oct | BZ99: Nov | CA99: Dic | CB99: Total 2019 | CC99: Ene | CD99: Feb | CE99: Mar | CF99: Abr | CG99: May | CH99: Jun | CI99: Jul | CJ99: Ago | CK99: Sep | CL99: Oct | CM99: Nov | CN99: Dic | CO99: Total 2020 | CP99: Ene | CQ99: Feb | CR99: Mar | CS99: Abr | CT99: May | CU99: Jun | CV99: Jul | CW99: Ago | CX99: Sep | CY99: Oct | CZ99: Nov | DA99: Dic | DB99: Total 2021 | DC99: Ene | DD99: Feb | DE99: Mar | DF99: Abr | DG99: May | DH99: Jun | DI99: Jul | DJ99: Ago | DK99: Sep | DL99: Oct | DM99: Nov | DN99: Dic | DO99: Total 2022 | DP99: Ene | DQ99: Feb | DR99: Mar | DS99: Abr | DT99: May | DU99: Jun | DV99: Jul | DW99: Ago | DX99: Sep | DY99: Oct | DZ99: Nov | EA99: Dic | EB99: Total 2023 | EC99: Ene | ED99: Feb | EE99: Mar | EF99: Abr | EG99: May | EH99: Jun | EI99: Jul | EJ99: Ago | EK99: Sep | EL99: Oct | EM99: Nov | EN99: Dic | EO99: Total 2024 | EP99: Ene | EQ99: Feb | ER99: Mar | ES99: Abr | ET99: May | EU99: Jun | EV99: Jul | EW99: Ago | EX99: Sep | EY99: Oct | EZ99: Nov | FA99: Dic | FB99: Total 2025 | FC99: Ene | FD99: Feb | FE99: Mar | FF99: Abr | FG99: May | FH99: Jun | FI99: Jul | FJ99: Ago | FK99: Sep | FL99: Oct | FM99: Nov | FN99: Dic | FO99: Total 2026
B100: Dirección de Vialidad | C100: 0 | D100: 0 | E100: 0 | F100: 0 | G100: 0 | H100: 0 | I100: 0 | J100: 0 | K100: 0 | L100: 0 | M100: 0 | N100: 0 | O100: =N100 -> 0 | P100: 0 | Q100: 0 | R100: 0 | S100: 0 | T100: 0 | U100: 0 | V100: 0 | W100: 0 | X100: 0 | Y100: 0 | Z100: 0 | AA100: 0 | AB100: =AA100 -> 0 | AC100: 0 | AD100: 0 | AE100: 0 | AF100: 0 | AG100: 0 | AH100: 0 | AI100: 0 | AJ100: 0 | AK100: 0 | AL100: 0 | AM100: 0 | AN100: 0 | AO100: =AN100 -> 0 | AP100: 0 | AQ100: 0 | AR100: 0 | AS100: 0 | AT100: 0 | AU100: 0 | AV100: 0 | AW100: 0 | AX100: 0 | AY100: 0 | AZ100: 0 | BA100: 0 | BB100: =BA100 -> 0 | BC100: 0 | BD100: 0 | BE100: 0 | BF100: 0 | BG100: 0 | BH100: 0 | BI100: 0 | BJ100: 0 | BK100: 0 | BL100: 0 | BM100: 0 | BN100: 0 | BO100: =BN100 -> 0 | BP100: 0 | BQ100: 0 | BR100: 0 | BS100: 0 | BT100: 0 | BU100: 0 | BV100: 0 | BW100: 0 | BX100: 0 | BY100: 0 | BZ100: 0 | CA100: 0 | CB100: =CA100 -> 0 | CC100: 0 | CD100: 0 | CE100: 0 | CF100: 0 | CG100: 0 | CH100: 0 | CI100: 0 | CJ100: 0 | CK100: 0 | CL100: 0 | CM100: 0 | CN100: 0 | CO100: =CN100 -> 0 | CP100: 0 | CQ100: 0 | CR100: 0 | CS100: 0 | CT100: 0 | CU100: 0 | CV100: 0 | CW100: 0 | CX100: 0 | CY100: 0 | CZ100: 0 | DA100: 0 | DB100: =DA100 -> 0 | DC100: 0 | DD100: 0 | DE100: 0 | DF100: 0 | DG100: 0 | DH100: 0 | DI100: 0 | DJ100: 0 | DK100: 0 | DL100: 0 | DM100: 0 | DN100: 0 | DO100: =DN100 -> 0 | DP100: 0 | DQ100: 0 | DR100: 0 | DS100: 0 | DT100: 0 | DU100: 0 | DV100: 0 | DW100: 0 | DX100: 0 | DY100: 0 | DZ100: 0 | EA100: 0 | EB100: =EA100 -> 0 | EC100: 0 | ED100: 0 | EE100: 0 | EF100: 0 | EG100: 0 | EH100: 0 | EI100: 0 | EJ100: 0 | EK100: 0 | EL100: 0 | EM100: 0 | EN100: 0 | EO100: =EN100 -> 0 | EP100: 0 | EQ100: 0 | ER100: 0 | ES100: 0 | ET100: 0 | EU100: 0 | EV100: 0 | EW100: 0 | EX100: 0 | EY100: 0 | EZ100: 0 | FA100: 0 | FB100: =FA100 -> 0 | FC100: 0 | FD100: 0 | FE100: 0 | FF100: 0 | FG100: 0 | FH100: 0 | FI100: 0 | FO100: =FI100 -> 0
B101: Dirección de Obras Hidráulicas | C101: 0 | D101: 0 | E101: 0 | F101: 0 | G101: 0 | H101: 0 | I101: 0 | J101: 0 | K101: 0 | L101: 0 | M101: 0 | N101: 0 | O101: =N101 -> 0 | P101: 0 | Q101: 0 | R101: 0 | S101: 0 | T101: 0 | U101: 0 | V101: 0 | W101: 0 | X101: 0 | Y101: 0 | Z101: 0 | AA101: 0 | AB101: =AA101 -> 0 | AC101: 0 | AD101: 0 | AE101: 0 | AF101: 0 | AG101: 0 | AH101: 0 | AI101: 0 | AJ101: 0 | AK101: 0 | AL101: 0 | AM101: 0 | AN101: 0 | AO101: =AN101 -> 0 | AP101: 0 | AQ101: 0 | AR101: 0 | AS101: 0 | AT101: 0 | AU101: 0 | AV101: 0 | AW101: 0 | AX101: 0 | AY101: 0 | AZ101: 0 | BA101: 0 | BB101: =BA101 -> 0 | BC101: 0 | BD101: 0 | BE101: 0 | BF101: 0 | BG101: 0 | BH101: 0 | BI101: 0 | BJ101: 0 | BK101: 0 | BL101: 0 | BM101: 0 | BN101: 0 | BO101: =BN101 -> 0 | BP101: 0 | BQ101: 0 | BR101: 0 | BS101: 0 | BT101: 0 | BU101: 0 | BV101: 0 | BW101: 0 | BX101: 0 | BY101: 0 | BZ101: 0 | CA101: 0 | CB101: =CA101 -> 0 | CC101: 0 | CD101: 0 | CE101: 0 | CF101: 0 | CG101: 0 | CH101: 0 | CI101: 0 | CJ101: 0 | CK101: 0 | CL101: 0 | CM101: 0 | CN101: 0 | CO101: =CN101 -> 0 | CP101: 0 | CQ101: 0 | CR101: 0 | CS101: 0 | CT101: 0 | CU101: 0 | CV101: 0 | CW101: 0 | CX101: 0 | CY101: 0 | CZ101: 0 | DA101: 0 | DB101: =DA101 -> 0 | DC101: 0 | DD101: 0 | DE101: 0 | DF101: 0 | DG101: 0 | DH101: 0 | DI101: 0 | DJ101: 0 | DK101: 0 | DL101: 0 | DM101: 0 | DN101: 0 | DO101: =DN101 -> 0 | DP101: 0 | DQ101: 0 | DR101: 0 | DS101: 0 | DT101: 0 | DU101: 0 | DV101: 0 | DW101: 0 | DX101: 0 | DY101: 0 | DZ101: 0 | EA101: 0 | EB101: =EA101 -> 0 | EC101: 0 | ED101: 0 | EE101: 0 | EF101: 0 | EG101: 0 | EH101: 0 | EI101: 0 | EJ101: 0 | EK101: 0 | EL101: 0 | EM101: 0 | EN101: 0 | EO101: =EN101 -> 0 | EP101: 0 | EQ101: 0 | ER101: 0 | ES101: 0 | ET101: 0 | EU101: 0 | EV101: 0 | EW101: 0 | EX101: 0 | EY101: 0 | EZ101: 0 | FA101: 0 | FB101: =FA101 -> 0 | FC101: 0 | FD101: 0 | FE101: 0 | FF101: 0 | FG101: 0 | FH101: 0 | FI101: 0 | FO101: =FI101 -> 0
B102: Subdirección de APR | C102: 0 | D102: 0 | E102: 0 | F102: 0 | G102: 0 | H102: 0 | I102: 0 | J102: 0 | K102: 0 | L102: 0 | M102: 0 | N102: 0 | O102: =N102 -> 0 | P102: 0 | Q102: 0 | R102: 0 | S102: 0 | T102: 0 | U102: 0 | V102: 0 | W102: 0 | X102: 0 | Y102: 0 | Z102: 0 | AA102: 0 | AB102: =AA102 -> 0 | AC102: 0 | AD102: 0 | AE102: 0 | AF102: 0 | AG102: 0 | AH102: 0 | AI102: 0 | AJ102: 0 | AK102: 0 | AL102: 0 | AM102: 0 | AN102: 0 | AO102: =AN102 -> 0 | AP102: 0 | AQ102: 0 | AR102: 0 | AS102: 0 | AT102: 0 | AU102: 0 | AV102: 0 | AW102: 0 | AX102: 0 | AY102: 0 | AZ102: 0 | BA102: 0 | BB102: =BA102 -> 0 | BC102: 0 | BD102: 0 | BE102: 0 | BF102: 0 | BG102: 0 | BH102: 0 | BI102: 0 | BJ102: 0 | BK102: 0 | BL102: 0 | BM102: 0 | BN102: 0 | BO102: =BN102 -> 0 | BP102: 0 | BQ102: 0 | BR102: 0 | BS102: 0 | BT102: 0 | BU102: 0 | BV102: 0 | BW102: 0 | BX102: 0 | BY102: 0 | BZ102: 0 | CA102: 0 | CB102: =CA102 -> 0 | CC102: 0 | CD102: 0 | CE102: 0 | CF102: 0 | CG102: 0 | CH102: 0 | CI102: 0 | CJ102: 0 | CK102: 0 | CL102: 0 | CM102: 0 | CN102: 0 | CO102: =CN102 -> 0 | CP102: 0 | CQ102: 0 | CR102: 0 | CS102: 0 | CT102: 0 | CU102: 0 | CV102: 0 | CW102: 0 | CX102: 0 | CY102: 0 | CZ102: 0 | DA102: 0 | DB102: =DA102 -> 0 | DC102: 0 | DD102: 0 | DE102: 0 | DF102: 0 | DG102: 0 | DH102: 0 | DI102: 0 | DJ102: 0 | DK102: 0 | DL102: 0 | DM102: 0 | DN102: 0 | DO102: =DN102 -> 0 | DP102: 17877772 | DQ102: 17877772 | DR102: 17877772 | DS102: 17877772 | DT102: 17877772 | DU102: 17877772 | DV102: 17877772 | DW102: 17772523 | DX102: 17772523 | DY102: 17772523 | DZ102: 10123523 | EA102: 10123523 | EB102: =EA102 -> 10123523 | EC102: 0 | ED102: 0 | EE102: 0 | EF102: 0 | EG102: 0 | EH102: 0 | EI102: 0 | EJ102: 0 | EK102: 0 | EL102: 0 | EM102: 0 | EN102: 0 | EO102: =EN102 -> 0 | EP102: 0 | EQ102: 0 | ER102: 0 | ES102: 0 | ET102: 0 | EU102: 0 | EV102: 0 | EW102: 0 | EX102: 0 | EY102: 0 | EZ102: 0 | FA102: 0 | FB102: =FA102 -> 0 | FC102: 0 | FD102: 0 | FE102: 0 | FF102: 0 | FG102: 0 | FH102: 0 | FI102: 0 | FO102: =FI102 -> 0
B103: Dirección de Obras Portuarias | C103: 0 | D103: 0 | E103: 0 | F103: 0 | G103: 0 | H103: 0 | I103: 0 | J103: 0 | K103: 0 | L103: 0 | M103: 0 | N103: 0 | O103: =N103 -> 0 | P103: 0 | Q103: 0 | R103: 0 | S103: 0 | T103: 0 | U103: 0 | V103: 0 | W103: 0 | X103: 0 | Y103: 0 | Z103: 0 | AA103: 0 | AB103: =AA103 -> 0 | AC103: 0 | AD103: 0 | AE103: 0 | AF103: 0 | AG103: 0 | AH103: 0 | AI103: 0 | AJ103: 0 | AK103: 0 | AL103: 0 | AM103: 0 | AN103: 0 | AO103: =AN103 -> 0 | AP103: 0 | AQ103: 0 | AR103: 0 | AS103: 0 | AT103: 0 | AU103: 0 | AV103: 0 | AW103: 0 | AX103: 0 | AY103: 0 | AZ103: 0 | BA103: 0 | BB103: =BA103 -> 0 | BC103: 0 | BD103: 0 | BE103: 0 | BF103: 0 | BG103: 0 | BH103: 0 | BI103: 0 | BJ103: 0 | BK103: 0 | BL103: 0 | BM103: 0 | BN103: 0 | BO103: =BN103 -> 0 | BP103: 0 | BQ103: 0 | BR103: 0 | BS103: 0 | BT103: 0 | BU103: 0 | BV103: 0 | BW103: 0 | BX103: 0 | BY103: 0 | BZ103: 0 | CA103: 0 | CB103: =CA103 -> 0 | CC103: 0 | CD103: 0 | CE103: 0 | CF103: 0 | CG103: 0 | CH103: 0 | CI103: 0 | CJ103: 0 | CK103: 0 | CL103: 0 | CM103: 0 | CN103: 0 | CO103: =CN103 -> 0 | CP103: 0 | CQ103: 0 | CR103: 0 | CS103: 0 | CT103: 0 | CU103: 0 | CV103: 0 | CW103: 0 | CX103: 0 | CY103: 0 | CZ103: 0 | DA103: 0 | DB103: =DA103 -> 0 | DC103: 0 | DD103: 0 | DE103: 0 | DF103: 0 | DG103: 0 | DH103: 0 | DI103: 0 | DJ103: 0 | DK103: 0 | DL103: 0 | DM103: 0 | DN103: 0 | DO103: =DN103 -> 0 | DP103: 0 | DQ103: 0 | DR103: 0 | DS103: 0 | DT103: 0 | DU103: 0 | DV103: 0 | DW103: 0 | DX103: 0 | DY103: 0 | DZ103: 0 | EA103: 0 | EB103: =EA103 -> 0 | EC103: 0 | ED103: 0 | EE103: 0 | EF103: 0 | EG103: 0 | EH103: 0 | EI103: 0 | EJ103: 0 | EK103: 0 | EL103: 0 | EM103: 0 | EN103: 0 | EO103: =EN103 -> 0 | EP103: 0 | EQ103: 0 | ER103: 0 | ES103: 0 | ET103: 0 | EU103: 0 | EV103: 0 | EW103: 0 | EX103: 0 | EY103: 0 | EZ103: 0 | FA103: 0 | FB103: =FA103 -> 0 | FC103: 0 | FD103: 0 | FE103: 0 | FF103: 0 | FG103: 0 | FH103: 0 | FI103: 0 | FO103: =FI103 -> 0
B104: Dirección de Aeropuertos | C104: 0 | D104: 0 | E104: 0 | F104: 0 | G104: 0 | H104: 0 | I104: 0 | J104: 0 | K104: 0 | L104: 0 | M104: 0 | N104: 0 | O104: =N104 -> 0 | P104: 0 | Q104: 0 | R104: 0 | S104: 0 | T104: 0 | U104: 0 | V104: 0 | W104: 0 | X104: 0 | Y104: 0 | Z104: 0 | AA104: 0 | AB104: =AA104 -> 0 | AC104: 0 | AD104: 0 | AE104: 0 | AF104: 0 | AG104: 0 | AH104: 0 | AI104: 0 | AJ104: 0 | AK104: 0 | AL104: 0 | AM104: 0 | AN104: 0 | AO104: =AN104 -> 0 | AP104: 0 | AQ104: 0 | AR104: 0 | AS104: 0 | AT104: 0 | AU104: 0 | AV104: 0 | AW104: 0 | AX104: 0 | AY104: 0 | AZ104: 0 | BA104: 0 | BB104: =BA104 -> 0 | BC104: 0 | BD104: 0 | BE104: 0 | BF104: 0 | BG104: 0 | BH104: 0 | BI104: 0 | BJ104: 0 | BK104: 0 | BL104: 0 | BM104: 0 | BN104: 0 | BO104: =BN104 -> 0 | BP104: 0 | BQ104: 0 | BR104: 0 | BS104: 0 | BT104: 0 | BU104: 0 | BV104: 0 | BW104: 0 | BX104: 0 | BY104: 0 | BZ104: 0 | CA104: 0 | CB104: =CA104 -> 0 | CC104: 0 | CD104: 0 | CE104: 0 | CF104: 0 | CG104: 0 | CH104: 0 | CI104: 0 | CJ104: 0 | CK104: 0 | CL104: 0 | CM104: 0 | CN104: 0 | CO104: =CN104 -> 0 | CP104: 0 | CQ104: 0 | CR104: 0 | CS104: 0 | CT104: 0 | CU104: 0 | CV104: 0 | CW104: 0 | CX104: 0 | CY104: 0 | CZ104: 0 | DA104: 0 | DB104: =DA104 -> 0 | DC104: 0 | DD104: 0 | DE104: 0 | DF104: 0 | DG104: 0 | DH104: 0 | DI104: 0 | DJ104: 0 | DK104: 0 | DL104: 0 | DM104: 0 | DN104: 0 | DO104: =DN104 -> 0 | DP104: 0 | DQ104: 0 | DR104: 0 | DS104: 0 | DT104: 0 | DU104: 0 | DV104: 0 | DW104: 0 | DX104: 0 | DY104: 0 | DZ104: 0 | EA104: 0 | EB104: =EA104 -> 0 | EC104: 0 | ED104: 0 | EE104: 0 | EF104: 0 | EG104: 0 | EH104: 0 | EI104: 0 | EJ104: 0 | EK104: 0 | EL104: 0 | EM104: 0 | EN104: 0 | EO104: =EN104 -> 0 | EP104: 0 | EQ104: 0 | ER104: 0 | ES104: 0 | ET104: 0 | EU104: 0 | EV104: 0 | EW104: 0 | EX104: 0 | EY104: 0 | EZ104: 0 | FA104: 0 | FB104: =FA104 -> 0 | FC104: 0 | FD104: 0 | FE104: 0 | FF104: 0 | FG104: 0 | FH104: 0 | FI104: 0 | FO104: =FI104 -> 0
B105: Dirección de Arquitectura | C105: 0 | D105: 0 | E105: 0 | F105: 0 | G105: 0 | H105: 0 | I105: 0 | J105: 0 | K105: 0 | L105: 0 | M105: 0 | N105: 0 | O105: =N105 -> 0 | P105: 0 | Q105: 0 | R105: 0 | S105: 0 | T105: 0 | U105: 0 | V105: 0 | W105: 0 | X105: 0 | Y105: 0 | Z105: 0 | AA105: 0 | AB105: =AA105 -> 0 | AC105: 0 | AD105: 0 | AE105: 0 | AF105: 0 | AG105: 0 | AH105: 0 | AI105: 0 | AJ105: 0 | AK105: 0 | AL105: 0 | AM105: 0 | AN105: 0 | AO105: =AN105 -> 0 | AP105: 0 | AQ105: 0 | AR105: 0 | AS105: 0 | AT105: 0 | AU105: 0 | AV105: 0 | AW105: 0 | AX105: 0 | AY105: 0 | AZ105: 0 | BA105: 0 | BB105: =BA105 -> 0 | BC105: 0 | BD105: 0 | BE105: 0 | BF105: 0 | BG105: 0 | BH105: 0 | BI105: 0 | BJ105: 0 | BK105: 0 | BL105: 0 | BM105: 0 | BN105: 0 | BO105: =BN105 -> 0 | BP105: 0 | BQ105: 0 | BR105: 0 | BS105: 0 | BT105: 0 | BU105: 0 | BV105: 0 | BW105: 0 | BX105: 0 | BY105: 0 | BZ105: 0 | CA105: 0 | CB105: =CA105 -> 0 | CC105: 0 | CD105: 0 | CE105: 0 | CF105: 0 | CG105: 0 | CH105: 0 | CI105: 0 | CJ105: 0 | CK105: 0 | CL105: 0 | CM105: 0 | CN105: 0 | CO105: =CN105 -> 0 | CP105: 0 | CQ105: 0 | CR105: 0 | CS105: 0 | CT105: 0 | CU105: 0 | CV105: 0 | CW105: 0 | CX105: 0 | CY105: 0 | CZ105: 0 | DA105: 0 | DB105: =DA105 -> 0 | DC105: 0 | DD105: 0 | DE105: 0 | DF105: 0 | DG105: 0 | DH105: 0 | DI105: 0 | DJ105: 0 | DK105: 0 | DL105: 0 | DM105: 0 | DN105: 0 | DO105: =DN105 -> 0 | DP105: 0 | DQ105: 0 | DR105: 0 | DS105: 0 | DT105: 0 | DU105: 0 | DV105: 0 | DW105: 0 | DX105: 0 | DY105: 0 | DZ105: 0 | EA105: 0 | EB105: =EA105 -> 0 | EC105: 0 | ED105: 0 | EE105: 0 | EF105: 0 | EG105: 0 | EH105: 0 | EI105: 0 | EJ105: 0 | EK105: 0 | EL105: 0 | EM105: 0 | EN105: 0 | EO105: =EN105 -> 0 | EP105: 0 | EQ105: 0 | ER105: 0 | ES105: 0 | ET105: 0 | EU105: 0 | EV105: 0 | EW105: 0 | EX105: 0 | EY105: 0 | EZ105: 0 | FA105: 0 | FB105: =FA105 -> 0 | FC105: 0 | FD105: 0 | FE105: 0 | FF105: 0 | FG105: 0 | FH105: 0 | FI105: 0 | FO105: =FI105 -> 0
B106: Total | C106: =SUM(C100:C105) -> 0 | D106: =SUM(D100:D105) -> 0 | E106: =SUM(E100:E105) -> 0 | F106: =SUM(F100:F105) -> 0 | G106: =SUM(G100:G105) -> 0 | H106: =SUM(H100:H105) -> 0 | I106: =SUM(I100:I105) -> 0 | J106: =SUM(J100:J105) -> 0 | ... FO106: =SUM(FO100:FO105) -> 0
B107: El Subtítulo 33 solo aparece en APR, desde 2023. En los demás Programas y años no está en los informes de ejecución. Fuente: elaboración propia, Dipres.
B109: Ejecución de Inversión en Infraestructura Pública del Ministerio de Obras Públicas, 2014-2026 (Subtítulo 33 – Transferencias de Capital, miles de pesos)
C110: 2014 | P110: 2015 | AC110: 2016 | AP110: 2017 | BC110: 2018 | BP110: 2019 | CC110: 2020 | CP110: 2021 | DC110: 2022 | DP110: 2023 | EC110: 2024 | EP110: 2025 | FC110: 2026
B111: Programa | C111: Ene | D111: Feb | E111: Mar | F111: Abr | G111: May | H111: Jun | I111: Jul | J111: Ago | K111: Sep | L111: Oct | M111: Nov | N111: Dic | O111: Total 2014 | P111: Ene | Q111: Feb | R111: Mar | S111: Abr | T111: May | U111: Jun | V111: Jul | W111: Ago | X111: Sep | Y111: Oct | Z111: Nov | AA111: Dic | AB111: Total 2015 | AC111: Ene | AD111: Feb | AE111: Mar | AF111: Abr | AG111: May | AH111: Jun | AI111: Jul | AJ111: Ago | AK111: Sep | AL111: Oct | AM111: Nov | AN111: Dic | AO111: Total 2016 | AP111: Ene | AQ111: Feb | AR111: Mar | AS111: Abr | AT111: May | AU111: Jun | AV111: Jul | AW111: Ago | AX111: Sep | AY111: Oct | AZ111: Nov | BA111: Dic | BB111: Total 2017 | BC111: Ene | BD111: Feb | BE111: Mar | BF111: Abr | BG111: May | BH111: Jun | BI111: Jul | BJ111: Ago | BK111: Sep | BL111: Oct | BM111: Nov | BN111: Dic | BO111: Total 2018 | BP111: Ene | BQ111: Feb | BR111: Mar | BS111: Abr | BT111: May | BU111: Jun | BV111: Jul | BW111: Ago | BX111: Sep | BY111: Oct | BZ111: Nov | CA111: Dic | CB111: Total 2019 | CC111: Ene | CD111: Feb | CE111: Mar | CF111: Abr | CG111: May | CH111: Jun | CI111: Jul | CJ111: Ago | CK111: Sep | CL111: Oct | CM111: Nov | CN111: Dic | CO111: Total 2020 | CP111: Ene | CQ111: Feb | CR111: Mar | CS111: Abr | CT111: May | CU111: Jun | CV111: Jul | CW111: Ago | CX111: Sep | CY111: Oct | CZ111: Nov | DA111: Dic | DB111: Total 2021 | DC111: Ene | DD111: Feb | DE111: Mar | DF111: Abr | DG111: May | DH111: Jun | DI111: Jul | DJ111: Ago | DK111: Sep | DL111: Oct | DM111: Nov | DN111: Dic | DO111: Total 2022 | DP111: Ene | DQ111: Feb | DR111: Mar | DS111: Abr | DT111: May | DU111: Jun | DV111: Jul | DW111: Ago | DX111: Sep | DY111: Oct | DZ111: Nov | EA111: Dic | EB111: Total 2023 | EC111: Ene | ED111: Feb | EE111: Mar | EF111: Abr | EG111: May | EH111: Jun | EI111: Jul | EJ111: Ago | EK111: Sep | EL111: Oct | EM111: Nov | EN111: Dic | EO111: Total 2024 | EP111: Ene | EQ111: Feb | ER111: Mar | ES111: Abr | ET111: May | EU111: Jun | EV111: Jul | EW111: Ago | EX111: Sep | EY111: Oct | EZ111: Nov | FA111: Dic | FB111: Total 2025 | FC111: Ene | FD111: Feb | FE111: Mar | FF111: Abr | FG111: May | FH111: Jun | FI111: Jul | FJ111: Ago | FK111: Sep | FL111: Oct | FM111: Nov | FN111: Dic | FO111: Total 2026
B112: Dirección de Vialidad | C112: 0 | D112: 0 | E112: 0 | F112: 0 | G112: 0 | H112: 0 | I112: 0 | J112: 0 | K112: 0 | L112: 0 | M112: 0 | N112: 0 | O112: =N112 -> 0 | P112: 0 | Q112: 0 | R112: 0 | S112: 0 | T112: 0 | U112: 0 | V112: 0 | W112: 0 | X112: 0 | Y112: 0 | Z112: 0 | AA112: 0 | AB112: =AA112 -> 0 | AC112: 0 | AD112: 0 | AE112: 0 | AF112: 0 | AG112: 0 | AH112: 0 | AI112: 0 | AJ112: 0 | AK112: 0 | AL112: 0 | AM112: 0 | AN112: 0 | AO112: =AN112 -> 0 | AP112: 0 | AQ112: 0 | AR112: 0 | AS112: 0 | AT112: 0 | AU112: 0 | AV112: 0 | AW112: 0 | AX112: 0 | AY112: 0 | AZ112: 0 | BA112: 0 | BB112: =BA112 -> 0 | BC112: 0 | BD112: 0 | BE112: 0 | BF112: 0 | BG112: 0 | BH112: 0 | BI112: 0 | BJ112: 0 | BK112: 0 | BL112: 0 | BM112: 0 | BN112: 0 | BO112: =BN112 -> 0 | BP112: 0 | BQ112: 0 | BR112: 0 | BS112: 0 | BT112: 0 | BU112: 0 | BV112: 0 | BW112: 0 | BX112: 0 | BY112: 0 | BZ112: 0 | CA112: 0 | CB112: =CA112 -> 0 | CC112: 0 | CD112: 0 | CE112: 0 | CF112: 0 | CG112: 0 | CH112: 0 | CI112: 0 | CJ112: 0 | CK112: 0 | CL112: 0 | CM112: 0 | CN112: 0 | CO112: =CN112 -> 0 | CP112: 0 | CQ112: 0 | CR112: 0 | CS112: 0 | CT112: 0 | CU112: 0 | CV112: 0 | CW112: 0 | CX112: 0 | CY112: 0 | CZ112: 0 | DA112: 0 | DB112: =DA112 -> 0 | DC112: 0 | DD112: 0 | DE112: 0 | DF112: 0 | DG112: 0 | DH112: 0 | DI112: 0 | DJ112: 0 | DK112: 0 | DL112: 0 | DM112: 0 | DN112: 0 | DO112: =DN112 -> 0 | DP112: 0 | DQ112: 0 | DR112: 0 | DS112: 0 | DT112: 0 | DU112: 0 | DV112: 0 | DW112: 0 | DX112: 0 | DY112: 0 | DZ112: 0 | EA112: 0 | EB112: =EA112 -> 0 | EC112: 0 | ED112: 0 | EE112: 0 | EF112: 0 | EG112: 0 | EH112: 0 | EI112: 0 | EJ112: 0 | EK112: 0 | EL112: 0 | EM112: 0 | EN112: 0 | EO112: =EN112 -> 0 | EP112: 0 | EQ112: 0 | ER112: 0 | ES112: 0 | ET112: 0 | EU112: 0 | EV112: 0 | EW112: 0 | EX112: 0 | EY112: 0 | EZ112: 0 | FA112: 0 | FB112: =FA112 -> 0 | FC112: 0 | FD112: 0 | FE112: 0 | FF112: 0 | FG112: 0 | FH112: 0 | FI112: 0 | FO112: =FI112 -> 0
B113: Dirección de Obras Hidráulicas | C113: 0 | D113: 0 | E113: 0 | F113: 0 | G113: 0 | H113: 0 | I113: 0 | J113: 0 | K113: 0 | L113: 0 | M113: 0 | N113: 0 | O113: =N113 -> 0 | P113: 0 | Q113: 0 | R113: 0 | S113: 0 | T113: 0 | U113: 0 | V113: 0 | W113: 0 | X113: 0 | Y113: 0 | Z113: 0 | AA113: 0 | AB113: =AA113 -> 0 | AC113: 0 | AD113: 0 | AE113: 0 | AF113: 0 | AG113: 0 | AH113: 0 | AI113: 0 | AJ113: 0 | AK113: 0 | AL113: 0 | AM113: 0 | AN113: 0 | AO113: =AN113 -> 0 | AP113: 0 | AQ113: 0 | AR113: 0 | AS113: 0 | AT113: 0 | AU113: 0 | AV113: 0 | AW113: 0 | AX113: 0 | AY113: 0 | AZ113: 0 | BA113: 0 | BB113: =BA113 -> 0 | BC113: 0 | BD113: 0 | BE113: 0 | BF113: 0 | BG113: 0 | BH113: 0 | BI113: 0 | BJ113: 0 | BK113: 0 | BL113: 0 | BM113: 0 | BN113: 0 | BO113: =BN113 -> 0 | BP113: 0 | BQ113: 0 | BR113: 0 | BS113: 0 | BT113: 0 | BU113: 0 | BV113: 0 | BW113: 0 | BX113: 0 | BY113: 0 | BZ113: 0 | CA113: 0 | CB113: =CA113 -> 0 | CC113: 0 | CD113: 0 | CE113: 0 | CF113: 0 | CG113: 0 | CH113: 0 | CI113: 0 | CJ113: 0 | CK113: 0 | CL113: 0 | CM113: 0 | CN113: 0 | CO113: =CN113 -> 0 | CP113: 0 | CQ113: 0 | CR113: 0 | CS113: 0 | CT113: 0 | CU113: 0 | CV113: 0 | CW113: 0 | CX113: 0 | CY113: 0 | CZ113: 0 | DA113: 0 | DB113: =DA113 -> 0 | DC113: 0 | DD113: 0 | DE113: 0 | DF113: 0 | DG113: 0 | DH113: 0 | DI113: 0 | DJ113: 0 | DK113: 0 | DL113: 0 | DM113: 0 | DN113: 0 | DO113: =DN113 -> 0 | DP113: 0 | DQ113: 0 | DR113: 0 | DS113: 0 | DT113: 0 | DU113: 0 | DV113: 0 | DW113: 0 | DX113: 0 | DY113: 0 | DZ113: 0 | EA113: 0 | EB113: =EA113 -> 0 | EC113: 0 | ED113: 0 | EE113: 0 | EF113: 0 | EG113: 0 | EH113: 0 | EI113: 0 | EJ113: 0 | EK113: 0 | EL113: 0 | EM113: 0 | EN113: 0 | EO113: =EN113 -> 0 | EP113: 0 | EQ113: 0 | ER113: 0 | ES113: 0 | ET113: 0 | EU113: 0 | EV113: 0 | EW113: 0 | EX113: 0 | EY113: 0 | EZ113: 0 | FA113: 0 | FB113: =FA113 -> 0 | FC113: 0 | FD113: 0 | FE113: 0 | FF113: 0 | FG113: 0 | FH113: 0 | FI113: 0 | FO113: =FI113 -> 0
B114: Subdirección de APR | C114: 0 | D114: 0 | E114: 0 | F114: 0 | G114: 0 | H114: 0 | I114: 0 | J114: 0 | K114: 0 | L114: 0 | M114: 0 | N114: 0 | O114: =N114 -> 0 | P114: 0 | Q114: 0 | R114: 0 | S114: 0 | T114: 0 | U114: 0 | V114: 0 | W114: 0 | X114: 0 | Y114: 0 | Z114: 0 | AA114: 0 | AB114: =AA114 -> 0 | AC114: 0 | AD114: 0 | AE114: 0 | AF114: 0 | AG114: 0 | AH114: 0 | AI114: 0 | AJ114: 0 | AK114: 0 | AL114: 0 | AM114: 0 | AN114: 0 | AO114: =AN114 -> 0 | AP114: 0 | AQ114: 0 | AR114: 0 | AS114: 0 | AT114: 0 | AU114: 0 | AV114: 0 | AW114: 0 | AX114: 0 | AY114: 0 | AZ114: 0 | BA114: 0 | BB114: =BA114 -> 0 | BC114: 0 | BD114: 0 | BE114: 0 | BF114: 0 | BG114: 0 | BH114: 0 | BI114: 0 | BJ114: 0 | BK114: 0 | BL114: 0 | BM114: 0 | BN114: 0 | BO114: =BN114 -> 0 | BP114: 0 | BQ114: 0 | BR114: 0 | BS114: 0 | BT114: 0 | BU114: 0 | BV114: 0 | BW114: 0 | BX114: 0 | BY114: 0 | BZ114: 0 | CA114: 0 | CB114: =CA114 -> 0 | CC114: 0 | CD114: 0 | CE114: 0 | CF114: 0 | CG114: 0 | CH114: 0 | CI114: 0 | CJ114: 0 | CK114: 0 | CL114: 0 | CM114: 0 | CN114: 0 | CO114: =CN114 -> 0 | CP114: 0 | CQ114: 0 | CR114: 0 | CS114: 0 | CT114: 0 | CU114: 0 | CV114: 0 | CW114: 0 | CX114: 0 | CY114: 0 | CZ114: 0 | DA114: 0 | DB114: =DA114 -> 0 | DC114: 0 | DD114: 0 | DE114: 0 | DF114: 0 | DG114: 0 | DH114: 0 | DI114: 0 | DJ114: 0 | DK114: 0 | DL114: 0 | DM114: 0 | DN114: 0 | DO114: =DN114 -> 0 | DP114: 0 | DQ114: 0 | DR114: 0 | DS114: 0 | DT114: 0 | DU114: 0 | DV114: 1050 | DW114: 1050 | DX114: 37795 | DY114: 169483 | DZ114: 843033 | EA114: 3861859 | EB114: =EA114 -> 3861859 | EC114: 0 | ED114: 0 | EE114: 0 | EF114: 0 | EG114: 0 | EH114: 0 | EI114: 0 | EJ114: 0 | EK114: 0 | EL114: 0 | EM114: 0 | EN114: 0 | EO114: =EN114 -> 0 | EP114: 0 | EQ114: 0 | ER114: 0 | ES114: 0 | ET114: 0 | EU114: 0 | EV114: 0 | EW114: 0 | EX114: 0 | EY114: 0 | EZ114: 0 | FA114: 0 | FB114: =FA114 -> 0 | FC114: 0 | FD114: 0 | FE114: 0 | FF114: 0 | FG114: 0 | FH114: 0 | FI114: 0 | FO114: =FI114 -> 0
...

Sheet MOP_Mes_Constante
C1: 1.620347 | D1: 1.620347 | E1: 1.620347 | F1: 1.620347 | G1: 1.620347 | H1: 1.620347 | I1: 1.620347 | J1: 1.620347 | K1: 1.620347 | L1: 1.620347 | M1: 1.620347 | N1: 1.620347 | P1: 1.5522091 | Q1: 1.5522091 | R1: 1.5522091 | S1: 1.5522091 | T1: 1.5522091 | U1: 1.5522091 | V1: 1.5522091 | W1: 1.5522091 | X1: 1.5522091 | Y1: 1.5522091 | Z1: 1.5522091 | AA1: 1.5522091 | AC1: 1.5114124 | AD1: 1.5114124 | AE1: 1.5114124 | AF1: 1.5114124 | AG1: 1.5114124 | AH1: 1.5114124 | AI1: 1.5114124 | AJ1: 1.5114124 | AK1: 1.5114124 | AL1: 1.5114124 | AM1: 1.5114124 | AN1: 1.5114124 | AP1: 1.4778845 | AQ1: 1.4778845 | AR1: 1.4778845 | AS1: 1.4778845 | AT1: 1.4778845 | AU1: 1.4778845 | AV1: 1.4778845 | AW1: 1.4778845 | AX1: 1.4778845 | AY1: 1.4778845 | AZ1: 1.4778845 | BA1: 1.4778845 | BC1: 1.4408545 | BD1: 1.4408545 | BE1: 1.4408545 | BF1: 1.4408545 | BG1: 1.4408545 | BH1: 1.4408545 | BI1: 1.4408545 | BJ1: 1.4408545 | BK1: 1.4408545 | BL1: 1.4408545 | BM1: 1.4408545 | BN1: 1.4408545 | BP1: 1.3989757 | BQ1: 1.3989757 | BR1: 1.3989757 | BS1: 1.3989757 | BT1: 1.3989757 | BU1: 1.3989757 | BV1: 1.3989757 | BW1: 1.3989757 | BX1: 1.3989757 | BY1: 1.3989757 | BZ1: 1.3989757 | CA1: 1.3989757 | CC1: 1.3584483 | CD1: 1.3584483 | CE1: 1.3584483 | CF1: 1.3584483 | CG1: 1.3584483 | CH1: 1.3584483 | CI1: 1.3584483 | CJ1: 1.3584483 | CK1: 1.3584483 | CL1: 1.3584483 | CM1: 1.3584483 | CN1: 1.3584483 | CP1: 1.2675174 | CQ1: 1.2675174 | CR1: 1.2675174 | CS1: 1.2675174 | CT1: 1.2675174 | CU1: 1.2675174 | CV1: 1.2675174 | CW1: 1.2675174 | CX1: 1.2675174 | CY1: 1.2675174 | CZ1: 1.2675174 | DA1: 1.2675174 | DC1: 1.1239584 | DD1: 1.1239584 | DE1: 1.1239584 | DF1: 1.1239584 | DG1: 1.1239584 | DH1: 1.1239584 | DI1: 1.1239584 | DJ1: 1.1239584 | DK1: 1.1239584 | DL1: 1.1239584 | DM1: 1.1239584 | DN1: 1.1239584 | DP1: 1.0813539 | DQ1: 1.0813539 | DR1: 1.0813539 | DS1: 1.0813539 | DT1: 1.0813539 | DU1: 1.0813539 | DV1: 1.0813539 | DW1: 1.0813539 | DX1: 1.0813539 | DY1: 1.0813539 | DZ1: 1.0813539 | EA1: 1.0813539 | EC1: 1.0344632 | ED1: 1.0344632 | EE1: 1.0344632 | EF1: 1.0344632 | EG1: 1.0344632 | EH1: 1.0344632 | EI1: 1.0344632 | EJ1: 1.0344632 | EK1: 1.0344632 | EL1: 1.0344632 | EM1: 1.0344632 | EN1: 1.0344632 | EP1: 1 | EQ1: 1 | ER1: 1 | ES1: 1 | ET1: 1 | EU1: 1 | EV1: 1 | EW1: 1 | EX1: 1 | EY1: 1 | EZ1: 1 | FA1: 1 | FC1: 1 | FD1: 1 | FE1: 1 | FF1: 1 | FG1: 1 | FH1: 1 | FI1: 1 | FJ1: 1 | FK1: 1 | FL1: 1 | FM1: 1 | FN1: 1
B2: Ministerio de Obras Públicas – Partida 12
B3: Miles de pesos – moneda corriente – montos devengados
B4: Subtítulo 31 – Iniciativas de Inversión
B6: Presupuesto Ley de Inversión en Infraestructura Pública del Ministerio de Obras Públicas, 2014-2026 (Subtítulo 31 – Iniciativas de Inversión, miles de pesos)
C7: 2014 | P7: 2015 | AC7: 2016 | AP7: 2017 | BC7: 2018 | BP7: 2019 | CC7: 2020 | CP7: 2021(1) | DC7: 2022(1) | DP7: 2023 | EC7: 2024 | EP7: 2025 | FC7: 2026
B8: Programa | C8: Ene | D8: Feb | E8: Mar | F8: Abr | G8: May | H8: Jun | I8: Jul | J8: Ago | K8: Sep | L8: Oct | M8: Nov | N8: Dic | O8: Total 2014 | P8: Ene | Q8: Feb | R8: Mar | S8: Abr | T8: May | U8: Jun | V8: Jul | W8: Ago | X8: Sep | Y8: Oct | Z8: Nov | AA8: Dic | AB8: Total 2015 | AC8: Ene | AD8: Feb | AE8: Mar | AF8: Abr | AG8: May | AH8: Jun | AI8: Jul | AJ8: Ago | AK8: Sep | AL8: Oct | AM8: Nov | AN8: Dic | AO8: Total 2016 | AP8: Ene | AQ8: Feb | AR8: Mar | AS8: Abr | AT8: May | AU8: Jun | AV8: Jul | AW8: Ago | AX8: Sep | AY8: Oct | AZ8: Nov | BA8: Dic | BB8: Total 2017 | BC8: Ene | BD8: Feb | BE8: Mar | BF8: Abr | BG8: May | BH8: Jun | BI8: Jul | BJ8: Ago | BK8: Sep | BL8: Oct | BM8: Nov | BN8: Dic | BO8: Total 2018 | BP8: Ene | BQ8: Feb | BR8: Mar | BS8: Abr | BT8: May | BU8: Jun | BV8: Jul | BW8: Ago | BX8: Sep | BY8: Oct | BZ8: Nov | CA8: Dic | CB8: Total 2019 | CC8: Ene | CD8: Feb | CE8: Mar | CF8: Abr | CG8: May | CH8: Jun | CI8: Jul | CJ8: Ago | CK8: Sep | CL8: Oct | CM8: Nov | CN8: Dic | CO8: Total 2020 | CP8: Ene | CQ8: Feb | CR8: Mar | CS8: Abr | CT8: May | CU8: Jun | CV8: Jul | CW8: Ago | CX8: Sep | CY8: Oct | CZ8: Nov | DA8: Dic | DB8: Total 2021 | DC8: Ene | DD8: Feb | DE8: Mar | DF8: Abr | DG8: May | DH8: Jun | DI8: Jul | DJ8: Ago | DK8: Sep | DL8: Oct | DM8: Nov | DN8: Dic | DO8: Total 2022 | DP8: Ene | DQ8: Feb | DR8: Mar | DS8: Abr | DT8: May | DU8: Jun | DV8: Jul | DW8: Ago | DX8: Sep | DY8: Oct | DZ8: Nov | EA8: Dic | EB8: Total 2023 | EC8: Ene | ED8: Feb | EE8: Mar | EF8: Abr | EG8: May | EH8: Jun | EI8: Jul | EJ8: Ago | EK8: Sep | EL8: Oct | EM8: Nov | EN8: Dic | EO8: Total 2024 | EP8: Ene | EQ8: Feb | ER8: Mar | ES8: Abr | ET8: May | EU8: Jun | EV8: Jul | EW8: Ago | EX8: Sep | EY8: Oct | EZ8: Nov | FA8: Dic | FB8: Total 2025 | FC8: Ene | FD8: Feb | FE8: Mar | FF8: Abr | FG8: May | FH8: Jun | FI8: Jul | FJ8: Ago | FK8: Sep | FL8: Oct | FM8: Nov | FN8: Dic | FO8: Total 2026
B9: Dirección de Vialidad | C9: =+MOP_Mes_Corriente!C10*MOP_Mes_Constante!$C$1 -> 1.3074697e+09 | D9: =+MOP_Mes_Corriente!D10*MOP_Mes_Constante!$C$1 -> 1.3074697e+09 | E9: =+MOP_Mes_Corriente!E10*MOP_Mes_Constante!$C$1 -> 1.3074697e+09 | F9: =+MOP_Mes_Corriente!F10*MOP_Mes_Constante!$C$1 -> 1.3074697e+09 | G9: =+MOP_Mes_Corriente!G10*MOP_Mes_Constante!$C$1 -> 1.3074697e+09 | H9: =+MOP_Mes_Corriente!H10*MOP_Mes_Constante!$C$1 -> 1.3074697e+09 | I9: =+MOP_Mes_Corriente!I10*MOP_Mes_Constante!$C$1 -> 1.3074697e+09 | J9: =+MOP_Mes_Corriente!J10*MOP_Mes_Constante!$C$1 -> 1.3074697e+09 | ... N9: =+MOP_Mes_Corriente!N10*MOP_Mes_Constante!$C$1 -> 1.3074697e+09 | O9: =N9 -> 1.3074697e+09 | P9: =+MOP_Mes_Corriente!P10*MOP_Mes_Constante!$P$1 -> 1.4860969e+09 | Q9: =+MOP_Mes_Corriente!Q10*MOP_Mes_Constante!$P$1 -> 1.4860969e+09 | R9: =+MOP_Mes_Corriente!R10*MOP_Mes_Constante!$P$1 -> 1.4860969e+09 | S9: =+MOP_Mes_Corriente!S10*MOP_Mes_Constante!$P$1 -> 1.4860969e+09 | T9: =+MOP_Mes_Corriente!T10*MOP_Mes_Constante!$P$1 -> 1.4860969e+09 | U9: =+MOP_Mes_Corriente!U10*MOP_Mes_Constante!$P$1 -> 1.4860969e+09 | V9: =+MOP_Mes_Corriente!V10*MOP_Mes_Constante!$P$1 -> 1.4860969e+09 | W9: =+MOP_Mes_Corriente!W10*MOP_Mes_Constante!$P$1 -> 1.4860969e+09 | ... AA9: =+MOP_Mes_Corriente!AA10*MOP_Mes_Constante!$P$1 -> 1.4860969e+09 | AB9: =AA9 -> 1.4860969e+09 | AC9: =+MOP_Mes_Corriente!AC10*MOP_Mes_Constante!$AC$1 -> 1.4164303e+09 | AD9: =+MOP_Mes_Corriente!AD10*MOP_Mes_Constante!$AC$1 -> 1.4164303e+09 | AE9: =+MOP_Mes_Corriente!AE10*MOP_Mes_Constante!$AC$1 -> 1.4164303e+09 | AF9: =+MOP_Mes_Corriente!AF10*MOP_Mes_Constante!$AC$1 -> 1.4164303e+09 | AG9: =+MOP_Mes_Corriente!AG10*MOP_Mes_Constante!$AC$1 -> 1.4164303e+09 | AH9: =+MOP_Mes_Corriente!AH10*MOP_Mes_Constante!$AC$1 -> 1.4164303e+09 | AI9: =+MOP_Mes_Corriente!AI10*MOP_Mes_Constante!$AC$1 -> 1.4164303e+09 | AJ9: =+MOP_Mes_Corriente!AJ10*MOP_Mes_Constante!$AC$1 -> 1.4164303e+09 | ... AN9: =+MOP_Mes_Corriente!AN10*MOP_Mes_Constante!$AC$1 -> 1.4164303e+09 | AO9: =AN9 -> 1.4164303e+09 | AP9: =+MOP_Mes_Corriente!AP10*MOP_Mes_Constante!$AP$1 -> 1.4520783e+09 | AQ9: =+MOP_Mes_Corriente!AQ10*MOP_Mes_Constante!$AP$1 -> 1.4520783e+09 | AR9: =+MOP_Mes_Corriente!AR10*MOP_Mes_Constante!$AP$1 -> 1.4520783e+09 | AS9: =+MOP_Mes_Corriente!AS10*MOP_Mes_Constante!$AP$1 -> 1.4520783e+09 | AT9: =+MOP_Mes_Corriente!AT10*MOP_Mes_Constante!$AP$1 -> 1.4520783e+09 | AU9: =+MOP_Mes_Corriente!AU10*MOP_Mes_Constante!$AP$1 -> 1.4520783e+09 | AV9: =+MOP_Mes_Corriente!AV10*MOP_Mes_Constante!$AP$1 -> 1.4520783e+09 | AW9: =+MOP_Mes_Corriente!AW10*MOP_Mes_Constante!$AP$1 -> 1.4520783e+09 | ... BA9: =+MOP_Mes_Corriente!BA10*MOP_Mes_Constante!$AP$1 -> 1.4520783e+09 | BB9: =BA9 -> 1.4520783e+09 | BC9: =+MOP_Mes_Corriente!BC10*MOP_Mes_Constante!$BC$1 -> 1.4386173e+09 | BD9: =+MOP_Mes_Corriente!BD10*MOP_Mes_Constante!$BC$1 -> 1.4386173e+09 | BE9: =+MOP_Mes_Corriente!BE10*MOP_Mes_Constante!$BC$1 -> 1.4386173e+09 | BF9: =+MOP_Mes_Corriente!BF10*MOP_Mes_Constante!$BC$1 -> 1.4386173e+09 | BG9: =+MOP_Mes_Corriente!BG10*MOP_Mes_Constante!$BC$1 -> 1.4386173e+09 | BH9: =+MOP_Mes_Corriente!BH10*MOP_Mes_Constante!$BC$1 -> 1.4386173e+09 | BI9: =+MOP_Mes_Corriente!BI10*MOP_Mes_Constante!$BC$1 -> 1.4386173e+09 | BJ9: =+MOP_Mes_Corriente!BJ10*MOP_Mes_Constante!$BC$1 -> 1.4386173e+09 | ... BN9: =+MOP_Mes_Corriente!BN10*MOP_Mes_Constante!$BC$1 -> 1.4386173e+09 | BO9: =BN9 -> 1.4386173e+09 | BP9: =+MOP_Mes_Corriente!BP10*MOP_Mes_Constante!$BP$1 -> 1.4778764e+09 | BQ9: =+MOP_Mes_Corriente!BQ10*MOP_Mes_Constante!$BP$1 -> 1.4778764e+09 | BR9: =+MOP_Mes_Corriente!BR10*MOP_Mes_Constante!$BP$1 -> 1.4778764e+09 | BS9: =+MOP_Mes_Corriente!BS10*MOP_Mes_Constante!$BP$1 -> 1.4778764e+09 | BT9: =+MOP_Mes_Corriente!BT10*MOP_Mes_Constante!$BP$1 -> 1.4778764e+09 | BU9: =+MOP_Mes_Corriente!BU10*MOP_Mes_Constante!$BP$1 -> 1.4778764e+09 | BV9: =+MOP_Mes_Corriente!BV10*MOP_Mes_Constante!$BP$1 -> 1.4778764e+09 | BW9: =+MOP_Mes_Corriente!BW10*MOP_Mes_Constante!$BP$1 -> 1.4778764e+09 | ... CA9: =+MOP_Mes_Corriente!CA10*MOP_Mes_Constante!$BP$1 -> 1.4778764e+09 | CB9: =CA9 -> 1.4778764e+09 | CC9: =+MOP_Mes_Corriente!CC10*MOP_Mes_Constante!$CC$1 -> 1.5599862e+09 | CD9: =+MOP_Mes_Corriente!CD10*MOP_Mes_Constante!$CC$1 -> 1.5599862e+09 | CE9: =+MOP_Mes_Corriente!CE10*MOP_Mes_Constante!$CC$1 -> 1.5599862e+09 | CF9: =+MOP_Mes_Corriente!CF10*MOP_Mes_Constante!$CC$1 -> 1.5599862e+09 | CG9: =+MOP_Mes_Corriente!CG10*MOP_Mes_Constante!$CC$1 -> 1.5599862e+09 | CH9: =+MOP_Mes_Corriente!CH10*MOP_Mes_Constante!$CC$1 -> 1.5599862e+09 | CI9: =+MOP_Mes_Corriente!CI10*MOP_Mes_Constante!$CC$1 -> 1.5599862e+09 | CJ9: =+MOP_Mes_Corriente!CJ10*MOP_Mes_Constante!$CC$1 -> 1.5599862e+09 | ... CN9: =+MOP_Mes_Corriente!CN10*MOP_Mes_Constante!$CC$1 -> 1.5599862e+09 | CO9: =CN9 -> 1.5599862e+09 | CP9: =+MOP_Mes_Corriente!CP10*MOP_Mes_Constante!$CP$1 -> 2.0346536e+09 | CQ9: =+MOP_Mes_Corriente!CQ10*MOP_Mes_Constante!$CP$1 -> 2.0346536e+09 | CR9: =+MOP_Mes_Corriente!CR10*MOP_Mes_Constante!$CP$1 -> 2.0346536e+09 | CS9: =+MOP_Mes_Corriente!CS10*MOP_Mes_Constante!$CP$1 -> 2.0346536e+09 | CT9: =+MOP_Mes_Corriente!CT10*MOP_Mes_Constante!$CP$1 -> 2.0346536e+09 | CU9: =+MOP_Mes_Corriente!CU10*MOP_Mes_Constante!$CP$1 -> 2.0346536e+09 | CV9: =+MOP_Mes_Corriente!CV10*MOP_Mes_Constante!$CP$1 -> 2.0346536e+09 | CW9: =+MOP_Mes_Corriente!CW10*MOP_Mes_Constante!$CP$1 -> 2.0346536e+09 | ... DA9: =+MOP_Mes_Corriente!DA10*MOP_Mes_Constante!$CP$1 -> 2.0346536e+09 | DB9: =DA9 -> 2.0346536e+09 | DC9: =+MOP_Mes_Corriente!DC10*MOP_Mes_Constante!$DC$1 -> 2.0258955e+09 | DD9: =+MOP_Mes_Corriente!DD10*MOP_Mes_Constante!$DC$1 -> 2.0258955e+09 | DE9: =+MOP_Mes_Corriente!DE10*MOP_Mes_Constante!$DC$1 -> 2.0258955e+09 | DF9: =+MOP_Mes_Corriente!DF10*MOP_Mes_Constante!$DC$1 -> 2.0258955e+09 | DG9: =+MOP_Mes_Corriente!DG10*MOP_Mes_Constante!$DC$1 -> 2.0258955e+09 | DH9: =+MOP_Mes_Corriente!DH10*MOP_Mes_Constante!$DC$1 -> 2.0258955e+09 | DI9: =+MOP_Mes_Corriente!DI10*MOP_Mes_Constante!$DC$1 -> 2.0258955e+09 | DJ9: =+MOP_Mes_Corriente!DJ10*MOP_Mes_Constante!$DC$1 -> 2.0258955e+09 | ... DN9: =+MOP_Mes_Corriente!DN10*MOP_Mes_Constante!$DC$1 -> 2.0258955e+09 | DO9: =DN9 -> 2.0258955e+09 | DP9: =+MOP_Mes_Corriente!DP10*MOP_Mes_Constante!$DP$1 -> 2.0695548e+09 | DQ9: =+MOP_Mes_Corriente!DQ10*MOP_Mes_Constante!$DP$1 -> 2.0695548e+09 | DR9: =+MOP_Mes_Corriente!DR10*MOP_Mes_Constante!$DP$1 -> 2.0695548e+09 | DS9: =+MOP_Mes_Corriente!DS10*MOP_Mes_Constante!$DP$1 -> 2.0695548e+09 | DT9: =+MOP_Mes_Corriente!DT10*MOP_Mes_Constante!$DP$1 -> 2.0695548e+09 | DU9: =+MOP_Mes_Corriente!DU10*MOP_Mes_Constante!$DP$1 -> 2.0695548e+09 | DV9: =+MOP_Mes_Corriente!DV10*MOP_Mes_Constante!$DP$1 -> 2.0695548e+09 | DW9: =+MOP_Mes_Corriente!DW10*MOP_Mes_Constante!$DP$1 -> 2.0695548e+09 | ... EA9: =+MOP_Mes_Corriente!EA10*MOP_Mes_Constante!$DP$1 -> 2.0695548e+09 | EB9: =EA9 -> 2.0695548e+09 | EC9: =+MOP_Mes_Corriente!EC10*MOP_Mes_Constante!$EC$1 -> 2.0820482e+09 | ED9: =+MOP_Mes_Corriente!ED10*MOP_Mes_Constante!$EC$1 -> 2.0820482e+09 | EE9: =+MOP_Mes_Corriente!EE10*MOP_Mes_Constante!$EC$1 -> 2.0820482e+09 | EF9: =+MOP_Mes_Corriente!EF10*MOP_Mes_Constante!$EC$1 -> 2.0820482e+09 | EG9: =+MOP_Mes_Corriente!EG10*MOP_Mes_Constante!$EC$1 -> 2.0820482e+09 | EH9: =+MOP_Mes_Corriente!EH10*MOP_Mes_Constante!$EC$1 -> 2.0820482e+09 | EI9: =+MOP_Mes_Corriente!EI10*MOP_Mes_Constante!$EC$1 -> 2.0820482e+09 | EJ9: =+MOP_Mes_Corriente!EJ10*MOP_Mes_Constante!$EC$1 -> 2.0820482e+09 | ... EN9: =+MOP_Mes_Corriente!EN10*MOP_Mes_Constante!$EC$1 -> 2.0820482e+09 | EO9: =EN9 -> 2.0820482e+09 | EP9: =+MOP_Mes_Corriente!EP10*MOP_Mes_Constante!$EP$1 -> 2083103023 | EQ9: =+MOP_Mes_Corriente!EQ10*MOP_Mes_Constante!$EP$1 -> 2083103023 | ER9: =+MOP_Mes_Corriente!ER10*MOP_Mes_Constante!$EP$1 -> 2083103023 | ES9: =+MOP_Mes_Corriente!ES10*MOP_Mes_Constante!$EP$1 -> 2083103023 | ET9: =+MOP_Mes_Corriente!ET10*MOP_Mes_Constante!$EP$1 -> 2083103023 | EU9: =+MOP_Mes_Corriente!EU10*MOP_Mes_Constante!$EP$1 -> 2083103023 | EV9: =+MOP_Mes_Corriente!EV10*MOP_Mes_Constante!$EP$1 -> 2083103023 | EW9: =+MOP_Mes_Corriente!EW10*MOP_Mes_Constante!$EP$1 -> 2083103023 | ... FA9: =+MOP_Mes_Corriente!FA10*MOP_Mes_Constante!$EP$1 -> 2083103023 | FB9: =FA9 -> 2083103023 | FC9: =+MOP_Mes_Corriente!FC10*MOP_Mes_Constante!$FC$1 -> 1951485600 | FD9: =+MOP_Mes_Corriente!FD10*MOP_Mes_Constante!$FC$1 -> 1951485600 | FE9: =+MOP_Mes_Corriente!FE10*MOP_Mes_Constante!$FC$1 -> 1951485600 | FF9: =+MOP_Mes_Corriente!FF10*MOP_Mes_Constante!$FC$1 -> 1951485600 | FG9: =+MOP_Mes_Corriente!FG10*MOP_Mes_Constante!$FC$1 -> 1951485600 | FH9: =+MOP_Mes_Corriente!FH10*MOP_Mes_Constante!$FC$1 -> 1951485600 | FI9: =+MOP_Mes_Corriente!FI10*MOP_Mes_Constante!$FC$1 -> 1951485600 | FO9: =FI9 -> 1951485600
B10: Dirección de Obras Hidráulicas | C10: =+MOP_Mes_Corriente!C11*MOP_Mes_Constante!$C$1 -> 1.640386e+08 | D10: =+MOP_Mes_Corriente!D11*MOP_Mes_Constante!$C$1 -> 1.640386e+08 | E10: =+MOP_Mes_Corriente!E11*MOP_Mes_Constante!$C$1 -> 1.640386e+08 | F10: =+MOP_Mes_Corriente!F11*MOP_Mes_Constante!$C$1 -> 1.640386e+08 | G10: =+MOP_Mes_Corriente!G11*MOP_Mes_Constante!$C$1 -> 1.640386e+08 | H10: =+MOP_Mes_Corriente!H11*MOP_Mes_Constante!$C$1 -> 1.640386e+08 | I10: =+MOP_Mes_Corriente!I11*MOP_Mes_Constante!$C$1 -> 1.640386e+08 | J10: =+MOP_Mes_Corriente!J11*MOP_Mes_Constante!$C$1 -> 1.640386e+08 | ... N10: =+MOP_Mes_Corriente!N11*MOP_Mes_Constante!$C$1 -> 1.640386e+08 | O10: =N10 -> 1.640386e+08 | P10: =+MOP_Mes_Corriente!P11*MOP_Mes_Constante!$P$1 -> 1.8222651e+08 | Q10: =+MOP_Mes_Corriente!Q11*MOP_Mes_Constante!$P$1 -> 1.8222651e+08 | R10: =+MOP_Mes_Corriente!R11*MOP_Mes_Constante!$P$1 -> 1.8222651e+08 | S10: =+MOP_Mes_Corriente!S11*MOP_Mes_Constante!$P$1 -> 1.8222651e+08 | T10: =+MOP_Mes_Corriente!T11*MOP_Mes_Constante!$P$1 -> 1.8222651e+08 | U10: =+MOP_Mes_Corriente!U11*MOP_Mes_Constante!$P$1 -> 1.8222651e+08 | V10: =+MOP_Mes_Corriente!V11*MOP_Mes_Constante!$P$1 -> 1.8222651e+08 | W10: =+MOP_Mes_Corriente!W11*MOP_Mes_Constante!$P$1 -> 1.8222651e+08 | ... AA10: =+MOP_Mes_Corriente!AA11*MOP_Mes_Constante!$P$1 -> 1.8222651e+08 | AB10: =AA10 -> 1.8222651e+08 | AC10: =+MOP_Mes_Corriente!AC11*MOP_Mes_Constante!$AC$1 -> 1.923921e+08 | AD10: =+MOP_Mes_Corriente!AD11*MOP_Mes_Constante!$AC$1 -> 1.923921e+08 | AE10: =+MOP_Mes_Corriente!AE11*MOP_Mes_Constante!$AC$1 -> 1.923921e+08 | AF10: =+MOP_Mes_Corriente!AF11*MOP_Mes_Constante!$AC$1 -> 1.923921e+08 | AG10: =+MOP_Mes_Corriente!AG11*MOP_Mes_Constante!$AC$1 -> 1.923921e+08 | AH10: =+MOP_Mes_Corriente!AH11*MOP_Mes_Constante!$AC$1 -> 1.923921e+08 | AI10: =+MOP_Mes_Corriente!AI11*MOP_Mes_Constante!$AC$1 -> 1.923921e+08 | AJ10: =+MOP_Mes_Corriente!AJ11*MOP_Mes_Constante!$AC$1 -> 1.923921e+08 | ... AN10: =+MOP_Mes_Corriente!AN11*MOP_Mes_Constante!$AC$1 -> 1.923921e+08 | AO10: =AN10 -> 1.923921e+08 | AP10: =+MOP_Mes_Corriente!AP11*MOP_Mes_Constante!$AP$1 -> 1.7976353e+08 | AQ10: =+MOP_Mes_Corriente!AQ11*MOP_Mes_Constante!$AP$1 -> 1.7976353e+08 | AR10: =+MOP_Mes_Corriente!AR11*MOP_Mes_Constante!$AP$1 -> 1.7976353e+08 | AS10: =+MOP_Mes_Corriente!AS11*MOP_Mes_Constante!$AP$1 -> 1.7976353e+08 | AT10: =+MOP_Mes_Corriente!AT11*MOP_Mes_Constante!$AP$1 -> 1.7976353e+08 | AU10: =+MOP_Mes_Corriente!AU11*MOP_Mes_Constante!$AP$1 -> 1.7976353e+08 | AV10: =+MOP_Mes_Corriente!AV11*MOP_Mes_Constante!$AP$1 -> 1.7976353e+08 | AW10: =+MOP_Mes_Corriente!AW11*MOP_Mes_Constante!$AP$1 -> 1.7976353e+08 | ... BA10: =+MOP_Mes_Corriente!BA11*MOP_Mes_Constante!$AP$1 -> 1.7976353e+08 | BB10: =BA10 -> 1.7976353e+08 | BC10: =+MOP_Mes_Corriente!BC11*MOP_Mes_Constante!$BC$1 -> 1.7259327e+08 | BD10: =+MOP_Mes_Corriente!BD11*MOP_Mes_Constante!$BC$1 -> 1.7259327e+08 | BE10: =+MOP_Mes_Corriente!BE11*MOP_Mes_Constante!$BC$1 -> 1.7259327e+08 | BF10: =+MOP_Mes_Corriente!BF11*MOP_Mes_Constante!$BC$1 -> 1.7259327e+08 | BG10: =+MOP_Mes_Corriente!BG11*MOP_Mes_Constante!$BC$1 -> 1.7259327e+08 | BH10: =+MOP_Mes_Corriente!BH11*MOP_Mes_Constante!$BC$1 -> 1.7259327e+08 | BI10: =+MOP_Mes_Corriente!BI11*MOP_Mes_Constante!$BC$1 -> 1.7259327e+08 | BJ10: =+MOP_Mes_Corriente!BJ11*MOP_Mes_Constante!$BC$1 -> 1.7259327e+08 | ... BN10: =+MOP_Mes_Corriente!BN11*MOP_Mes_Constante!$BC$1 -> 1.7259327e+08 | BO10: =BN10 -> 1.7259327e+08 | BP10: =+MOP_Mes_Corriente!BP11*MOP_Mes_Constante!$BP$1 -> 1.8072332e+08 | BQ10: =+MOP_Mes_Corriente!BQ11*MOP_Mes_Constante!$BP$1 -> 1.8072332e+08 | BR10: =+MOP_Mes_Corriente!BR11*MOP_Mes_Constante!$BP$1 -> 1.8072332e+08 | BS10: =+MOP_Mes_Corriente!BS11*MOP_Mes_Constante!$BP$1 -> 1.8072332e+08 | BT10: =+MOP_Mes_Corriente!BT11*MOP_Mes_Constante!$BP$1 -> 1.8072332e+08 | BU10: =+MOP_Mes_Corriente!BU11*MOP_Mes_Constante!$BP$1 -> 1.8072332e+08 | BV10: =+MOP_Mes_Corriente!BV11*MOP_Mes_Constante!$BP$1 -> 1.8072332e+08 | BW10: =+MOP_Mes_Corriente!BW11*MOP_Mes_Constante!$BP$1 -> 1.8072332e+08 | ... CA10: =+MOP_Mes_Corriente!CA11*MOP_Mes_Constante!$BP$1 -> 1.8072332e+08 | CB10: =CA10 -> 1.8072332e+08 | CC10: =+MOP_Mes_Corriente!CC11*MOP_Mes_Constante!$CC$1 -> 1.8701942e+08 | CD10: =+MOP_Mes_Corriente!CD11*MOP_Mes_Constante!$CC$1 -> 1.8701942e+08 | CE10: =+MOP_Mes_Corriente!CE11*MOP_Mes_Constante!$CC$1 -> 1.8701942e+08 | CF10: =+MOP_Mes_Corriente!CF11*MOP_Mes_Constante!$CC$1 -> 1.8701942e+08 | CG10: =+MOP_Mes_Corriente!CG11*MOP_Mes_Constante!$CC$1 -> 1.8701942e+08 | CH10: =+MOP_Mes_Corriente!CH11*MOP_Mes_Constante!$CC$1 -> 1.8701942e+08 | CI10: =+MOP_Mes_Corriente!CI11*MOP_Mes_Constante!$CC$1 -> 1.8701942e+08 | CJ10: =+MOP_Mes_Corriente!CJ11*MOP_Mes_Constante!$CC$1 -> 1.8701942e+08 | ... CN10: =+MOP_Mes_Corriente!CN11*MOP_Mes_Constante!$CC$1 -> 1.8701942e+08 | CO10: =CN10 -> 1.8701942e+08 | CP10: =+MOP_Mes_Corriente!CP11*MOP_Mes_Constante!$CP$1 -> 3.0610868e+08 | CQ10: =+MOP_Mes_Corriente!CQ11*MOP_Mes_Constante!$CP$1 -> 3.0610868e+08 | CR10: =+MOP_Mes_Corriente!CR11*MOP_Mes_Constante!$CP$1 -> 3.0610868e+08 | CS10: =+MOP_Mes_Corriente!CS11*MOP_Mes_Constante!$CP$1 -> 3.0610868e+08 | CT10: =+MOP_Mes_Corriente!CT11*MOP_Mes_Constante!$CP$1 -> 3.0610868e+08 | CU10: =+MOP_Mes_Corriente!CU11*MOP_Mes_Constante!$CP$1 -> 3.0610868e+08 | CV10: =+MOP_Mes_Corriente!CV11*MOP_Mes_Constante!$CP$1 -> 3.0610868e+08 | CW10: =+MOP_Mes_Corriente!CW11*MOP_Mes_Constante!$CP$1 -> 3.0610868e+08 | ... DA10: =+MOP_Mes_Corriente!DA11*MOP_Mes_Constante!$CP$1 -> 3.0610868e+08 | DB10: =DA10 -> 3.0610868e+08 | DC10: =+MOP_Mes_Corriente!DC11*MOP_Mes_Constante!$DC$1 -> 3.1227545e+08 | DD10: =+MOP_Mes_Corriente!DD11*MOP_Mes_Constante!$DC$1 -> 3.1227545e+08 | DE10: =+MOP_Mes_Corriente!DE11*MOP_Mes_Constante!$DC$1 -> 3.1227545e+08 | DF10: =+MOP_Mes_Corriente!DF11*MOP_Mes_Constante!$DC$1 -> 3.1227545e+08 | DG10: =+MOP_Mes_Corriente!DG11*MOP_Mes_Constante!$DC$1 -> 3.1227545e+08 | DH10: =+MOP_Mes_Corriente!DH11*MOP_Mes_Constante!$DC$1 -> 3.1227545e+08 | DI10: =+MOP_Mes_Corriente!DI11*MOP_Mes_Constante!$DC$1 -> 3.1227545e+08 | DJ10: =+MOP_Mes_Corriente!DJ11*MOP_Mes_Constante!$DC$1 -> 3.1227545e+08 | ... DN10: =+MOP_Mes_Corriente!DN11*MOP_Mes_Constante!$DC$1 -> 3.1227545e+08 | DO10: =DN10 -> 3.1227545e+08 | DP10: =+MOP_Mes_Corriente!DP11*MOP_Mes_Constante!$DP$1 -> 3.1747665e+08 | DQ10: =+MOP_Mes_Corriente!DQ11*MOP_Mes_Constante!$DP$1 -> 3.1747665e+08 | DR10: =+MOP_Mes_Corriente!DR11*MOP_Mes_Constante!$DP$1 -> 3.1747665e+08 | DS10: =+MOP_Mes_Corriente!DS11*MOP_Mes_Constante!$DP$1 -> 3.1747665e+08 | DT10: =+MOP_Mes_Corriente!DT11*MOP_Mes_Constante!$DP$1 -> 3.1747665e+08 | DU10: =+MOP_Mes_Corriente!DU11*MOP_Mes_Constante!$DP$1 -> 3.1747665e+08 | DV10: =+MOP_Mes_Corriente!DV11*MOP_Mes_Constante!$DP$1 -> 3.1747665e+08 | DW10: =+MOP_Mes_Corriente!DW11*MOP_Mes_Constante!$DP$1 -> 3.1747665e+08 | ... EA10: =+MOP_Mes_Corriente!EA11*MOP_Mes_Constante!$DP$1 -> 3.1747665e+08 | EB10: =EA10 -> 3.1747665e+08 | EC10: =+MOP_Mes_Corriente!EC11*MOP_Mes_Constante!$EC$1 -> 3.0589277e+08 | ED10: =+MOP_Mes_Corriente!ED11*MOP_Mes_Constante!$EC$1 -> 3.0589277e+08 | EE10: =+MOP_Mes_Corriente!EE11*MOP_Mes_Constante!$EC$1 -> 3.0589277e+08 | EF10: =+MOP_Mes_Corriente!EF11*MOP_Mes_Constante!$EC$1 -> 3.0589277e+08 | EG10: =+MOP_Mes_Corriente!EG11*MOP_Mes_Constante!$EC$1 -> 3.0589277e+08 | EH10: =+MOP_Mes_Corriente!EH11*MOP_Mes_Constante!$EC$1 -> 3.0589277e+08 | EI10: =+MOP_Mes_Corriente!EI11*MOP_Mes_Constante!$EC$1 -> 3.0589277e+08 | EJ10: =+MOP_Mes_Corriente!EJ11*MOP_Mes_Constante!$EC$1 -> 3.0589277e+08 | ... EN10: =+MOP_Mes_Corriente!EN11*MOP_Mes_Constante!$EC$1 -> 3.0589277e+08 | EO10: =EN10 -> 3.0589277e+08 | EP10: =+MOP_Mes_Corriente!EP11*MOP_Mes_Constante!$EP$1 -> 308121429 | EQ10: =+MOP_Mes_Corriente!EQ11*MOP_Mes_Constante!$EP$1 -> 308121429 | ER10: =+MOP_Mes_Corriente!ER11*MOP_Mes_Constante!$EP$1 -> 308121429 | ES10: =+MOP_Mes_Corriente!ES11*MOP_Mes_Constante!$EP$1 -> 308121429 | ET10: =+MOP_Mes_Corriente!ET11*MOP_Mes_Constante!$EP$1 -> 308121429 | EU10: =+MOP_Mes_Corriente!EU11*MOP_Mes_Constante!$EP$1 -> 308121429 | EV10: =+MOP_Mes_Corriente!EV11*MOP_Mes_Constante!$EP$1 -> 308121429 | EW10: =+MOP_Mes_Corriente!EW11*MOP_Mes_Constante!$EP$1 -> 308121429 | ... FA10: =+MOP_Mes_Corriente!FA11*MOP_Mes_Constante!$EP$1 -> 308121429 | FB10: =FA10 -> 308121429 | FC10: =+MOP_Mes_Corriente!FC11*MOP_Mes_Constante!$FC$1 -> 195906100 | FD10: =+MOP_Mes_Corriente!FD11*MOP_Mes_Constante!$FC$1 -> 195906100 | FE10: =+MOP_Mes_Corriente!FE11*MOP_Mes_Constante!$FC$1 -> 195906100 | FF10: =+MOP_Mes_Corriente!FF11*MOP_Mes_Constante!$FC$1 -> 195906100 | FG10: =+MOP_Mes_Corriente!FG11*MOP_Mes_Constante!$FC$1 -> 195906100 | FH10: =+MOP_Mes_Corriente!FH11*MOP_Mes_Constante!$FC$1 -> 195906100 | FI10: =+MOP_Mes_Corriente!FI11*MOP_Mes_Constante!$FC$1 -> 195906100 | FO10: =FI10 -> 195906100
B11: Subdirección de APR | C11: =+MOP_Mes_Corriente!C12*MOP_Mes_Constante!$C$1 -> 80058020 | D11: =+MOP_Mes_Corriente!D12*MOP_Mes_Constante!$C$1 -> 80058020 | E11: =+MOP_Mes_Corriente!E12*MOP_Mes_Constante!$C$1 -> 80058020 | F11: =+MOP_Mes_Corriente!F12*MOP_Mes_Constante!$C$1 -> 80058020 | G11: =+MOP_Mes_Corriente!G12*MOP_Mes_Constante!$C$1 -> 80058020 | H11: =+MOP_Mes_Corriente!H12*MOP_Mes_Constante!$C$1 -> 80058020 | I11: =+MOP_Mes_Corriente!I12*MOP_Mes_Constante!$C$1 -> 80058020 | J11: =+MOP_Mes_Corriente!J12*MOP_Mes_Constante!$C$1 -> 80058020 | ... N11: =+MOP_Mes_Corriente!N12*MOP_Mes_Constante!$C$1 -> 80058020 | O11: =N11 -> 80058020 | P11: =+MOP_Mes_Corriente!P12*MOP_Mes_Constante!$P$1 -> 1.0692354e+08 | Q11: =+MOP_Mes_Corriente!Q12*MOP_Mes_Constante!$P$1 -> 1.0692354e+08 | R11: =+MOP_Mes_Corriente!R12*MOP_Mes_Constante!$P$1 -> 1.0692354e+08 | S11: =+MOP_Mes_Corriente!S12*MOP_Mes_Constante!$P$1 -> 1.0692354e+08 | T11: =+MOP_Mes_Corriente!T12*MOP_Mes_Constante!$P$1 -> 1.0692354e+08 | U11: =+MOP_Mes_Corriente!U12*MOP_Mes_Constante!$P$1 -> 1.0692354e+08 | V11: =+MOP_Mes_Corriente!V12*MOP_Mes_Constante!$P$1 -> 1.0692354e+08 | W11: =+MOP_Mes_Corriente!W12*MOP_Mes_Constante!$P$1 -> 1.0692354e+08 | ... AA11: =+MOP_Mes_Corriente!AA12*MOP_Mes_Constante!$P$1 -> 1.0692354e+08 | AB11: =AA11 -> 1.0692354e+08 | AC11: =+MOP_Mes_Corriente!AC12*MOP_Mes_Constante!$AC$1 -> 1.0806957e+08 | AD11: =+MOP_Mes_Corriente!AD12*MOP_Mes_Constante!$AC$1 -> 1.0806957e+08 | AE11: =+MOP_Mes_Corriente!AE12*MOP_Mes_Constante!$AC$1 -> 1.0806957e+08 | AF11: =+MOP_Mes_Corriente!AF12*MOP_Mes_Constante!$AC$1 -> 1.0806957e+08 | AG11: =+MOP_Mes_Corriente!AG12*MOP_Mes_Constante!$AC$1 -> 1.0806957e+08 | AH11: =+MOP_Mes_Corriente!AH12*MOP_Mes_Constante!$AC$1 -> 1.0806957e+08 | AI11: =+MOP_Mes_Corriente!AI12*MOP_Mes_Constante!$AC$1 -> 1.0806957e+08 | AJ11: =+MOP_Mes_Corriente!AJ12*MOP_Mes_Constante!$AC$1 -> 1.0806957e+08 | ... AN11: =+MOP_Mes_Corriente!AN12*MOP_Mes_Constante!$AC$1 -> 1.0806957e+08 | AO11: =AN11 -> 1.0806957e+08 | AP11: =+MOP_Mes_Corriente!AP12*MOP_Mes_Constante!$AP$1 -> 1.3299702e+08 | AQ11: =+MOP_Mes_Corriente!AQ12*MOP_Mes_Constante!$AP$1 -> 1.3299702e+08 | AR11: =+MOP_Mes_Corriente!AR12*MOP_Mes_Constante!$AP$1 -> 1.3299702e+08 | AS11: =+MOP_Mes_Corriente!AS12*MOP_Mes_Constante!$AP$1 -> 1.3299702e+08 | AT11: =+MOP_Mes_Corriente!AT12*MOP_Mes_Constante!$AP$1 -> 1.3299702e+08 | AU11: =+MOP_Mes_Corriente!AU12*MOP_Mes_Constante!$AP$1 -> 1.3299702e+08 | AV11: =+MOP_Mes_Corriente!AV12*MOP_Mes_Constante!$AP$1 -> 1.3299702e+08 | AW11: =+MOP_Mes_Corriente!AW12*MOP_Mes_Constante!$AP$1 -> 1.3299702e+08 | ... BA11: =+MOP_Mes_Corriente!BA12*MOP_Mes_Constante!$AP$1 -> 1.3299702e+08 | BB11: =BA11 -> 1.3299702e+08 | BC11: =+MOP_Mes_Corriente!BC12*MOP_Mes_Constante!$BC$1 -> 1.4759221e+08 | BD11: =+MOP_Mes_Corriente!BD12*MOP_Mes_Constante!$BC$1 -> 1.4759221e+08 | BE11: =+MOP_Mes_Corriente!BE12*MOP_Mes_Constante!$BC$1 -> 1.4759221e+08 | BF11: =+MOP_Mes_Corriente!BF12*MOP_Mes_Constante!$BC$1 -> 1.4759221e+08 | BG11: =+MOP_Mes_Corriente!BG12*MOP_Mes_Constante!$BC$1 -> 1.4759221e+08 | BH11: =+MOP_Mes_Corriente!BH12*MOP_Mes_Constante!$BC$1 -> 1.4759221e+08 | BI11: =+MOP_Mes_Corriente!BI12*MOP_Mes_Constante!$BC$1 -> 1.4759221e+08 | BJ11: =+MOP_Mes_Corriente!BJ12*MOP_Mes_Constante!$BC$1 -> 1.4759221e+08 | ... BN11: =+MOP_Mes_Corriente!BN12*MOP_Mes_Constante!$BC$1 -> 1.4759221e+08 | BO11: =BN11 -> 1.4759221e+08 | BP11: =+MOP_Mes_Corriente!BP12*MOP_Mes_Constante!$BP$1 -> 1.6045086e+08 | BQ11: =+MOP_Mes_Corriente!BQ12*MOP_Mes_Constante!$BP$1 -> 1.6045086e+08 | BR11: =+MOP_Mes_Corriente!BR12*MOP_Mes_Constante!$BP$1 -> 1.6045086e+08 | BS11: =+MOP_Mes_Corriente!BS12*MOP_Mes_Constante!$BP$1 -> 1.6045086e+08 | BT11: =+MOP_Mes_Corriente!BT12*MOP_Mes_Constante!$BP$1 -> 1.6045086e+08 | BU11: =+MOP_Mes_Corriente!BU12*MOP_Mes_Constante!$BP$1 -> 1.6045086e+08 | BV11: =+MOP_Mes_Corriente!BV12*MOP_Mes_Constante!$BP$1 -> 1.6045086e+08 | BW11: =+MOP_Mes_Corriente!BW12*MOP_Mes_Constante!$BP$1 -> 1.6045086e+08 | ... CA11: =+MOP_Mes_Corriente!CA12*MOP_Mes_Constante!$BP$1 -> 1.6045086e+08 | CB11: =CA11 -> 1.6045086e+08 | CC11: =+MOP_Mes_Corriente!CC12*MOP_Mes_Constante!$CC$1 -> 1.8385057e+08 | CD11: =+MOP_Mes_Corriente!CD12*MOP_Mes_Constante!$CC$1 -> 1.8385057e+08 | CE11: =+MOP_Mes_Corriente!CE12*MOP_Mes_Constante!$CC$1 -> 1.8385057e+08 | CF11: =+MOP_Mes_Corriente!CF12*MOP_Mes_Constante!$CC$1 -> 1.8385057e+08 | CG11: =+MOP_Mes_Corriente!CG12*MOP_Mes_Constante!$CC$1 -> 1.8385057e+08 | CH11: =+MOP_Mes_Corriente!CH12*MOP_Mes_Constante!$CC$1 -> 1.8385057e+08 | CI11: =+MOP_Mes_Corriente!CI12*MOP_Mes_Constante!$CC$1 -> 1.8385057e+08 | CJ11: =+MOP_Mes_Corriente!CJ12*MOP_Mes_Constante!$CC$1 -> 1.8385057e+08 | ... CN11: =+MOP_Mes_Corriente!CN12*MOP_Mes_Constante!$CC$1 -> 1.8385057e+08 | CO11: =CN11 -> 1.8385057e+08 | CP11: =+MOP_Mes_Corriente!CP12*MOP_Mes_Constante!$CP$1 -> 3.1255961e+08 | CQ11: =+MOP_Mes_Corriente!CQ12*MOP_Mes_Constante!$CP$1 -> 3.1255961e+08 | CR11: =+MOP_Mes_Corriente!CR12*MOP_Mes_Constante!$CP$1 -> 3.1255961e+08 | CS11: =+MOP_Mes_Corriente!CS12*MOP_Mes_Constante!$CP$1 -> 3.1255961e+08 | CT11: =+MOP_Mes_Corriente!CT12*MOP_Mes_Constante!$CP$1 -> 3.1255961e+08 | CU11: =+MOP_Mes_Corriente!CU12*MOP_Mes_Constante!$CP$1 -> 3.1255961e+08 | CV11: =+MOP_Mes_Corriente!CV12*MOP_Mes_Constante!$CP$1 -> 3.1255961e+08 | CW11: =+MOP_Mes_Corriente!CW12*MOP_Mes_Constante!$CP$1 -> 3.1255961e+08 | ... DA11: =+MOP_Mes_Corriente!DA12*MOP_Mes_Constante!$CP$1 -> 3.1255961e+08 | DB11: =DA11 -> 3.1255961e+08 | DC11: =+MOP_Mes_Corriente!DC12*MOP_Mes_Constante!$DC$1 -> 3.1285153e+08 | DD11: =+MOP_Mes_Corriente!DD12*MOP_Mes_Constante!$DC$1 -> 3.1285153e+08 | DE11: =+MOP_Mes_Corriente!DE12*MOP_Mes_Constante!$DC$1 -> 3.1285153e+08 | DF11: =+MOP_Mes_Corriente!DF12*MOP_Mes_Constante!$DC$1 -> 3.1285153e+08 | DG11: =+MOP_Mes_Corriente!DG12*MOP_Mes_Constante!$DC$1 -> 3.1285153e+08 | DH11: =+MOP_Mes_Corriente!DH12*MOP_Mes_Constante!$DC$1 -> 3.1285153e+08 | DI11: =+MOP_Mes_Corriente!DI12*MOP_Mes_Constante!$DC$1 -> 3.1285153e+08 | DJ11: =+MOP_Mes_Corriente!DJ12*MOP_Mes_Constante!$DC$1 -> 3.1285153e+08 | ... DN11: =+MOP_Mes_Corriente!DN12*MOP_Mes_Constante!$DC$1 -> 3.1285153e+08 | DO11: =DN11 -> 3.1285153e+08 | DP11: =+MOP_Mes_Corriente!DP12*MOP_Mes_Constante!$DP$1 -> 3.1984357e+08 | DQ11: =+MOP_Mes_Corriente!DQ12*MOP_Mes_Constante!$DP$1 -> 3.1984357e+08 | DR11: =+MOP_Mes_Corriente!DR12*MOP_Mes_Constante!$DP$1 -> 3.1984357e+08 | DS11: =+MOP_Mes_Corriente!DS12*MOP_Mes_Constante!$DP$1 -> 3.1984357e+08 | DT11: =+MOP_Mes_Corriente!DT12*MOP_Mes_Constante!$DP$1 -> 3.1984357e+08 | DU11: =+MOP_Mes_Corriente!DU12*MOP_Mes_Constante!$DP$1 -> 3.1984357e+08 | DV11: =+MOP_Mes_Corriente!DV12*MOP_Mes_Constante!$DP$1 -> 3.1984357e+08 | DW11: =+MOP_Mes_Corriente!DW12*MOP_Mes_Constante!$DP$1 -> 3.1984357e+08 | ... EA11: =+MOP_Mes_Corriente!EA12*MOP_Mes_Constante!$DP$1 -> 3.1984357e+08 | EB11: =EA11 -> 3.1984357e+08 | EC11: =+MOP_Mes_Corriente!EC12*MOP_Mes_Constante!$EC$1 -> 3.2657655e+08 | ED11: =+MOP_Mes_Corriente!ED12*MOP_Mes_Constante!$EC$1 -> 3.2657655e+08 | EE11: =+MOP_Mes_Corriente!EE12*MOP_Mes_Constante!$EC$1 -> 3.2657655e+08 | EF11: =+MOP_Mes_Corriente!EF12*MOP_Mes_Constante!$EC$1 -> 3.2657655e+08 | EG11: =+MOP_Mes_Corriente!EG12*MOP_Mes_Constante!$EC$1 -> 3.2657655e+08 | EH11: =+MOP_Mes_Corriente!EH12*MOP_Mes_Constante!$EC$1 -> 3.2657655e+08 | EI11: =+MOP_Mes_Corriente!EI12*MOP_Mes_Constante!$EC$1 -> 3.2657655e+08 | EJ11: =+MOP_Mes_Corriente!EJ12*MOP_Mes_Constante!$EC$1 -> 3.2657655e+08 | ... EN11: =+MOP_Mes_Corriente!EN12*MOP_Mes_Constante!$EC$1 -> 3.2657655e+08 | EO11: =EN11 -> 3.2657655e+08 | EP11: =+MOP_Mes_Corriente!EP12*MOP_Mes_Constante!$EP$1 -> 329603442 | EQ11: =+MOP_Mes_Corriente!EQ12*MOP_Mes_Constante!$EP$1 -> 329603442 | ER11: =+MOP_Mes_Corriente!ER12*MOP_Mes_Constante!$EP$1 -> 329603442 | ES11: =+MOP_Mes_Corriente!ES12*MOP_Mes_Constante!$EP$1 -> 329603442 | ET11: =+MOP_Mes_Corriente!ET12*MOP_Mes_Constante!$EP$1 -> 329603442 | EU11: =+MOP_Mes_Corriente!EU12*MOP_Mes_Constante!$EP$1 -> 329603442 | EV11: =+MOP_Mes_Corriente!EV12*MOP_Mes_Constante!$EP$1 -> 329603442 | EW11: =+MOP_Mes_Corriente!EW12*MOP_Mes_Constante!$EP$1 -> 329603442 | ... FA11: =+MOP_Mes_Corriente!FA12*MOP_Mes_Constante!$EP$1 -> 329603442 | FB11: =FA11 -> 329603442 | FC11: =+MOP_Mes_Corriente!FC12*MOP_Mes_Constante!$FC$1 -> 290113797 | FD11: =+MOP_Mes_Corriente!FD12*MOP_Mes_Constante!$FC$1 -> 290113797 | FE11: =+MOP_Mes_Corriente!FE12*MOP_Mes_Constante!$FC$1 -> 290113797 | FF11: =+MOP_Mes_Corriente!FF12*MOP_Mes_Constante!$FC$1 -> 290113797 | FG11: =+MOP_Mes_Corriente!FG12*MOP_Mes_Constante!$FC$1 -> 290113797 | FH11: =+MOP_Mes_Corriente!FH12*MOP_Mes_Constante!$FC$1 -> 290113797 | FI11: =+MOP_Mes_Corriente!FI12*MOP_Mes_Constante!$FC$1 -> 290113797 | FO11: =FI11 -> 290113797
B12: Dirección de Obras Portuarias | C12: =+MOP_Mes_Corriente!C13*MOP_Mes_Constante!$C$1 -> 89181551 | D12: =+MOP_Mes_Corriente!D13*MOP_Mes_Constante!$C$1 -> 89181551 | E12: =+MOP_Mes_Corriente!E13*MOP_Mes_Constante!$C$1 -> 89181551 | F12: =+MOP_Mes_Corriente!F13*MOP_Mes_Constante!$C$1 -> 89181551 | G12: =+MOP_Mes_Corriente!G13*MOP_Mes_Constante!$C$1 -> 89181551 | H12: =+MOP_Mes_Corriente!H13*MOP_Mes_Constante!$C$1 -> 89181551 | I12: =+MOP_Mes_Corriente!I13*MOP_Mes_Constante!$C$1 -> 89181551 | J12: =+MOP_Mes_Corriente!J13*MOP_Mes_Constante!$C$1 -> 89181551 | ... N12: =+MOP_Mes_Corriente!N13*MOP_Mes_Constante!$C$1 -> 89181551 | O12: =N12 -> 89181551 | P12: =+MOP_Mes_Corriente!P13*MOP_Mes_Constante!$P$1 -> 98933635 | Q12: =+MOP_Mes_Corriente!Q13*MOP_Mes_Constante!$P$1 -> 98933635 | R12: =+MOP_Mes_Corriente!R13*MOP_Mes_Constante!$P$1 -> 98933635 | S12: =+MOP_Mes_Corriente!S13*MOP_Mes_Constante!$P$1 -> 98933635 | T12: =+MOP_Mes_Corriente!T13*MOP_Mes_Constante!$P$1 -> 98933635 | U12: =+MOP_Mes_Corriente!U13*MOP_Mes_Constante!$P$1 -> 98933635 | V12: =+MOP_Mes_Corriente!V13*MOP_Mes_Constante!$P$1 -> 98933635 | W12: =+MOP_Mes_Corriente!W13*MOP_Mes_Constante!$P$1 -> 98933635 | ... AA12: =+MOP_Mes_Corriente!AA13*MOP_Mes_Constante!$P$1 -> 98933635 | AB12: =AA12 -> 98933635 | AC12: =+MOP_Mes_Corriente!AC13*MOP_Mes_Constante!$AC$1 -> 99761289 | AD12: =+MOP_Mes_Corriente!AD13*MOP_Mes_Constante!$AC$1 -> 99761289 | AE12: =+MOP_Mes_Corriente!AE13*MOP_Mes_Constante!$AC$1 -> 99761289 | AF12: =+MOP_Mes_Corriente!AF13*MOP_Mes_Constante!$AC$1 -> 99761289 | AG12: =+MOP_Mes_Corriente!AG13*MOP_Mes_Constante!$AC$1 -> 99761289 | AH12: =+MOP_Mes_Corriente!AH13*MOP_Mes_Constante!$AC$1 -> 99761289 | AI12: =+MOP_Mes_Corriente!AI13*MOP_Mes_Constante!$AC$1 -> 99761289 | AJ12: =+MOP_Mes_Corriente!AJ13*MOP_Mes_Constante!$AC$1 -> 99761289 | ... AN12: =+MOP_Mes_Corriente!AN13*MOP_Mes_Constante!$AC$1 -> 99761289 | AO12: =AN12 -> 99761289 | AP12: =+MOP_Mes_Corriente!AP13*MOP_Mes_Constante!$AP$1 -> 1.0072132e+08 | AQ12: =+MOP_Mes_Corriente!AQ13*MOP_Mes_Constante!$AP$1 -> 1.0072132e+08 | AR12: =+MOP_Mes_Corriente!AR13*MOP_Mes_Constante!$AP$1 -> 1.0072132e+08 | AS12: =+MOP_Mes_Corriente!AS13*MOP_Mes_Constante!$AP$1 -> 1.0072132e+08 | AT12: =+MOP_Mes_Corriente!AT13*MOP_Mes_Constante!$AP$1 -> 1.0072132e+08 | AU12: =+MOP_Mes_Corriente!AU13*MOP_Mes_Constante!$AP$1 -> 1.0072132e+08 | AV12: =+MOP_Mes_Corriente!AV13*MOP_Mes_Constante!$AP$1 -> 1.0072132e+08 | AW12: =+MOP_Mes_Corriente!AW13*MOP_Mes_Constante!$AP$1 -> 1.0072132e+08 | ... BA12: =+MOP_Mes_Corriente!BA13*MOP_Mes_Constante!$AP$1 -> 1.0072132e+08 | BB12: =BA12 -> 1.0072132e+08 | BC12: =+MOP_Mes_Corriente!BC13*MOP_Mes_Constante!$BC$1 -> 99559869 | BD12: =+MOP_Mes_Corriente!BD13*MOP_Mes_Constante!$BC$1 -> 99559869 | BE12: =+MOP_Mes_Corriente!BE13*MOP_Mes_Constante!$BC$1 -> 99559869 | BF12: =+MOP_Mes_Corriente!BF13*MOP_Mes_Constante!$BC$1 -> 99559869 | BG12: =+MOP_Mes_Corriente!BG13*MOP_Mes_Constante!$BC$1 -> 99559869 | BH12: =+MOP_Mes_Corriente!BH13*MOP_Mes_Constante!$BC$1 -> 99559869 | BI12: =+MOP_Mes_Corriente!BI13*MOP_Mes_Constante!$BC$1 -> 99559869 | BJ12: =+MOP_Mes_Corriente!BJ13*MOP_Mes_Constante!$BC$1 -> 99559869 | ... BN12: =+MOP_Mes_Corriente!BN13*MOP_Mes_Constante!$BC$1 -> 99559869 | BO12: =BN12 -> 99559869 | BP12: =+MOP_Mes_Corriente!BP13*MOP_Mes_Constante!$BP$1 -> 97772416 | BQ12: =+MOP_Mes_Corriente!BQ13*MOP_Mes_Constante!$BP$1 -> 97772416 | BR12: =+MOP_Mes_Corriente!BR13*MOP_Mes_Constante!$BP$1 -> 97772416 | BS12: =+MOP_Mes_Corriente!BS13*MOP_Mes_Constante!$BP$1 -> 97772416 | BT12: =+MOP_Mes_Corriente!BT13*MOP_Mes_Constante!$BP$1 -> 97772416 | BU12: =+MOP_Mes_Corriente!BU13*MOP_Mes_Constante!$BP$1 -> 97772416 | BV12: =+MOP_Mes_Corriente!BV13*MOP_Mes_Constante!$BP$1 -> 97772416 | BW12: =+MOP_Mes_Corriente!BW13*MOP_Mes_Constante!$BP$1 -> 97772416 | ... CA12: =+MOP_Mes_Corriente!CA13*MOP_Mes_Constante!$BP$1 -> 97772416 | CB12: =CA12 -> 97772416 | CC12: =+MOP_Mes_Corriente!CC13*MOP_Mes_Constante!$CC$1 -> 97408457 | CD12: =+MOP_Mes_Corriente!CD13*MOP_Mes_Constante!$CC$1 -> 97408457 | CE12: =+MOP_Mes_Corriente!CE13*MOP_Mes_Constante!$CC$1 -> 97408457 | CF12: =+MOP_Mes_Corriente!CF13*MOP_Mes_Constante!$CC$1 -> 97408457 | CG12: =+MOP_Mes_Corriente!CG13*MOP_Mes_Constante!$CC$1 -> 97408457 | CH12: =+MOP_Mes_Corriente!CH13*MOP_Mes_Constante!$CC$1 -> 97408457 | CI12: =+MOP_Mes_Corriente!CI13*MOP_Mes_Constante!$CC$1 -> 97408457 | CJ12: =+MOP_Mes_Corriente!CJ13*MOP_Mes_Constante!$CC$1 -> 97408457 | ... CN12: =+MOP_Mes_Corriente!CN13*MOP_Mes_Constante!$CC$1 -> 97408457 | CO12: =CN12 -> 97408457 | CP12: =+MOP_Mes_Corriente!CP13*MOP_Mes_Constante!$CP$1 -> 1.066974e+08 | CQ12: =+MOP_Mes_Corriente!CQ13*MOP_Mes_Constante!$CP$1 -> 1.066974e+08 | CR12: =+MOP_Mes_Corriente!CR13*MOP_Mes_Constante!$CP$1 -> 1.066974e+08 | CS12: =+MOP_Mes_Corriente!CS13*MOP_Mes_Constante!$CP$1 -> 1.066974e+08 | CT12: =+MOP_Mes_Corriente!CT13*MOP_Mes_Constante!$CP$1 -> 1.066974e+08 | CU12: =+MOP_Mes_Corriente!CU13*MOP_Mes_Constante!$CP$1 -> 1.066974e+08 | CV12: =+MOP_Mes_Corriente!CV13*MOP_Mes_Constante!$CP$1 -> 1.066974e+08 | CW12: =+MOP_Mes_Corriente!CW13*MOP_Mes_Constante!$CP$1 -> 1.066974e+08 | ... DA12: =+MOP_Mes_Corriente!DA13*MOP_Mes_Constante!$CP$1 -> 1.066974e+08 | DB12: =DA12 -> 1.066974e+08 | DC12: =+MOP_Mes_Corriente!DC13*MOP_Mes_Constante!$DC$1 -> 1.1245755e+08 | DD12: =+MOP_Mes_Corriente!DD13*MOP_Mes_Constante!$DC$1 -> 1.1245755e+08 | DE12: =+MOP_Mes_Corriente!DE13*MOP_Mes_Constante!$DC$1 -> 1.1245755e+08 | DF12: =+MOP_Mes_Corriente!DF13*MOP_Mes_Constante!$DC$1 -> 1.1245755e+08 | DG12: =+MOP_Mes_Corriente!DG13*MOP_Mes_Constante!$DC$1 -> 1.1245755e+08 | DH12: =+MOP_Mes_Corriente!DH13*MOP_Mes_Constante!$DC$1 -> 1.1245755e+08 | DI12: =+MOP_Mes_Corriente!DI13*MOP_Mes_Constante!$DC$1 -> 1.1245755e+08 | DJ12: =+MOP_Mes_Corriente!DJ13*MOP_Mes_Constante!$DC$1 -> 1.1245755e+08 | ... DN12: =+MOP_Mes_Corriente!DN13*MOP_Mes_Constante!$DC$1 -> 1.1245755e+08 | DO12: =DN12 -> 1.1245755e+08 | DP12: =+MOP_Mes_Corriente!DP13*MOP_Mes_Constante!$DP$1 -> 1.2454121e+08 | DQ12: =+MOP_Mes_Corriente!DQ13*MOP_Mes_Constante!$DP$1 -> 1.2454121e+08 | DR12: =+MOP_Mes_Corriente!DR13*MOP_Mes_Constante!$DP$1 -> 1.2454121e+08 | DS12: =+MOP_Mes_Corriente!DS13*MOP_Mes_Constante!$DP$1 -> 1.2454121e+08 | DT12: =+MOP_Mes_Corriente!DT13*MOP_Mes_Constante!$DP$1 -> 1.2454121e+08 | DU12: =+MOP_Mes_Corriente!DU13*MOP_Mes_Constante!$DP$1 -> 1.2454121e+08 | DV12: =+MOP_Mes_Corriente!DV13*MOP_Mes_Constante!$DP$1 -> 1.2454121e+08 | DW12: =+MOP_Mes_Corriente!DW13*MOP_Mes_Constante!$DP$1 -> 1.2454121e+08 | ... EA12: =+MOP_Mes_Corriente!EA13*MOP_Mes_Constante!$DP$1 -> 1.2454121e+08 | EB12: =EA12 -> 1.2454121e+08 | EC12: =+MOP_Mes_Corriente!EC13*MOP_Mes_Constante!$EC$1 -> 1.3149878e+08 | ED12: =+MOP_Mes_Corriente!ED13*MOP_Mes_Constante!$EC$1 -> 1.3149878e+08 | EE12: =+MOP_Mes_Corriente!EE13*MOP_Mes_Constante!$EC$1 -> 1.3149878e+08 | EF12: =+MOP_Mes_Corriente!EF13*MOP_Mes_Constante!$EC$1 -> 1.3149878e+08 | EG12: =+MOP_Mes_Corriente!EG13*MOP_Mes_Constante!$EC$1 -> 1.3149878e+08 | EH12: =+MOP_Mes_Corriente!EH13*MOP_Mes_Constante!$EC$1 -> 1.3149878e+08 | EI12: =+MOP_Mes_Corriente!EI13*MOP_Mes_Constante!$EC$1 -> 1.3149878e+08 | EJ12: =+MOP_Mes_Corriente!EJ13*MOP_Mes_Constante!$EC$1 -> 1.3149878e+08 | ... EN12: =+MOP_Mes_Corriente!EN13*MOP_Mes_Constante!$EC$1 -> 1.3149878e+08 | EO12: =EN12 -> 1.3149878e+08 | EP12: =+MOP_Mes_Corriente!EP13*MOP_Mes_Constante!$EP$1 -> 125417585 | EQ12: =+MOP_Mes_Corriente!EQ13*MOP_Mes_Constante!$EP$1 -> 125417585 | ER12: =+MOP_Mes_Corriente!ER13*MOP_Mes_Constante!$EP$1 -> 125417585 | ES12: =+MOP_Mes_Corriente!ES13*MOP_Mes_Constante!$EP$1 -> 125417585 | ET12: =+MOP_Mes_Corriente!ET13*MOP_Mes_Constante!$EP$1 -> 125417585 | EU12: =+MOP_Mes_Corriente!EU13*MOP_Mes_Constante!$EP$1 -> 125417585 | EV12: =+MOP_Mes_Corriente!EV13*MOP_Mes_Constante!$EP$1 -> 125417585 | EW12: =+MOP_Mes_Corriente!EW13*MOP_Mes_Constante!$EP$1 -> 125417585 | ... FA12: =+MOP_Mes_Corriente!FA13*MOP_Mes_Constante!$EP$1 -> 125417585 | FB12: =FA12 -> 125417585 | FC12: =+MOP_Mes_Corriente!FC13*MOP_Mes_Constante!$FC$1 -> 109909690 | FD12: =+MOP_Mes_Corriente!FD13*MOP_Mes_Constante!$FC$1 -> 109909690 | FE12: =+MOP_Mes_Corriente!FE13*MOP_Mes_Constante!$FC$1 -> 109909690 | FF12: =+MOP_Mes_Corriente!FF13*MOP_Mes_Constante!$FC$1 -> 109909690 | FG12: =+MOP_Mes_Corriente!FG13*MOP_Mes_Constante!$FC$1 -> 109909690 | FH12: =+MOP_Mes_Corriente!FH13*MOP_Mes_Constante!$FC$1 -> 109909690 | FI12: =+MOP_Mes_Corriente!FI13*MOP_Mes_Constante!$FC$1 -> 109909690 | FO12: =FI12 -> 109909690
