Workbook

Sheet Dashboard
B2: MINISTERIO DE VIVIENDA Y URBANISMO — DASHBOARD DE INVERSIÓN Y EJECUCIÓN PRESUPUESTARIA
B3: Visualizador Analítico Interactivo Tabla a Tabla | Subtítulos 33 (Subsidios/Capital), 31 (Inversión Directa), 29 (Activos) y Consolidado | Cifras en miles de pesos ($)
B4: AÑO SELECCIONADO: | C4: 2024 | D4: COBERTURA TEMPORAL: | F4: 2021 - 2026 (Ene - Dic) | H4: UNIDAD MONETARIA: | J4: Miles de $ Corrientes (DIPRES)
B6: PRESUPUESTO LEY (INICIAL) | D6: PRESUPUESTO VIGENTE | F6: EJECUCIÓN ACUMULADA | H6: % CUMPLIMIENTO PRESUPUESTARIO | J6: SALDO POR EJECUTAR
B7: =D17 -> 3320541734 | D7: =E17 -> 3332768183 | F7: =F17 -> 3312699040 | H7: =H17 -> 0.99397824 | J7: =G17 -> 20069143
B9: Aprobado Ley de Presupuesto | D9: Presupuesto anual actualizado | F9: Total devengado en el ejercicio | H9: Ejecución devengada / Presupuesto vigente | J9: Monto disponible no devengado
B11: TABLA 1: RESUMEN CONSOLIDADO POR SUBTÍTULO PRESUPUESTARIO
B13: Subtítulo Presupuestario | C13: Cód. | D13: Presupuesto Ley | E13: Presupuesto Vigente | F13: Ejecución Acumulada | G13: Saldo por Ejecutar | H13: % Ejecución | I13: % Participación
B14: Subtítulo 33 – Transferencias de Capital (Subsidios) | C14: 33 | D14: =INDEX(MINVU_Mes_Corriente!$1:$300, 164, 3 + ($C$4 - 2021)*13 + 12) -> 2729162964 | E14: =INDEX(MINVU_Mes_Corriente!$1:$300, 186, 3 + ($C$4 - 2021)*13 + 12) -> 2913408485 | F14: =INDEX(MINVU_Mes_Corriente!$1:$300, 208, 3 + ($C$4 - 2021)*13 + 12) -> 2904924599 | G14: =E14 - F14 -> 8483886 | H14: =IF(E14>0, F14/E14, 0) -> 0.99708799 | I14: =IF($E$17>0, E14/$E$17, 0) -> 0.87417076
B15: Subtítulo 31 – Iniciativas de Inversión | C15: 31 | D15: =INDEX(MINVU_Mes_Corriente!$1:$300, 26, 3 + ($C$4 - 2021)*13 + 12) -> 560704016 | E15: =INDEX(MINVU_Mes_Corriente!$1:$300, 48, 3 + ($C$4 - 2021)*13 + 12) -> 400142072 | F15: =INDEX(MINVU_Mes_Corriente!$1:$300, 70, 3 + ($C$4 - 2021)*13 + 12) -> 388712182 | G15: =E15 - F15 -> 11429890 | H15: =IF(E15>0, F15/E15, 0) -> 0.97143542 | I15: =IF($E$17>0, E15/$E$17, 0) -> 0.12006298
B16: Subtítulo 29 – Activos No Financieros | C16: 29 | D16: =INDEX(MINVU_Mes_Corriente!$1:$300, 95, 3 + ($C$4 - 2021)*13 + 12) -> 30674754 | E16: =INDEX(MINVU_Mes_Corriente!$1:$300, 117, 3 + ($C$4 - 2021)*13 + 12) -> 19217626 | F16: =INDEX(MINVU_Mes_Corriente!$1:$300, 139, 3 + ($C$4 - 2021)*13 + 12) -> 19062259 | G16: =E16 - F16 -> 155367 | H16: =IF(E16>0, F16/E16, 0) -> 0.99191539 | I16: =IF($E$17>0, E16/$E$17, 0) -> 0.0057662654
B17: TOTAL INVERSIÓN MINVU (33 + 31 + 29) | C17: TOTAL | D17: =SUM(D14:D16) -> 3320541734 | E17: =SUM(E14:E16) -> 3332768183 | F17: =SUM(F14:F16) -> 3312699040 | G17: =E17 - F17 -> 20069143 | H17: =IF(E17>0, F17/E17, 0) -> 0.99397824 | I17: =SUM(I14:I16) -> 1
B19: TABLA 2: DESGLOSE COMPLETO POR ENTIDAD / PROGRAMA / SERVIU (AÑO SELECCIONADO)
B21: Entidad / SERVIU Regional | C21: Subt. 33 Vigente | D21: Subt. 33 Ejecución | E21: Subt. 31 Vigente | F21: Subt. 31 Ejecución | G21: Subt. 29 Vigente | H21: Subt. 29 Ejecución | I21: Total Vigente | J21: Total Ejecución | K21: Saldo | L21: % Ejecución | M21: % Part. MINVU
B22: Subsecretaría y Programas Centrales | C22: =INDEX(MINVU_Mes_Corriente!$1:$300, 168, 3 + ($C$4 - 2021)*13 + 12) -> 253260952 | D22: =INDEX(MINVU_Mes_Corriente!$1:$300, 190, 3 + ($C$4 - 2021)*13 + 12) -> 249185192 | E22: =INDEX(MINVU_Mes_Corriente!$1:$300, 30, 3 + ($C$4 - 2021)*13 + 12) -> 1858597 | F22: =INDEX(MINVU_Mes_Corriente!$1:$300, 52, 3 + ($C$4 - 2021)*13 + 12) -> 1765056 | G22: =INDEX(MINVU_Mes_Corriente!$1:$300, 99, 3 + ($C$4 - 2021)*13 + 12) -> 3168714 | H22: =INDEX(MINVU_Mes_Corriente!$1:$300, 121, 3 + ($C$4 - 2021)*13 + 12) -> 3071041 | I22: =C22 + E22 + G22 -> 258288263 | J22: =D22 + F22 + H22 -> 254021289 | K22: =I22 - J22 -> 4266974 | L22: =IF(I22>0, J22/I22, 0) -> 0.9834798 | M22: =IF($I$40>0, I22/$I$40, 0) -> 0.077499619
B23: Parque Metropolitano (PARQUEMET) | C23: =INDEX(MINVU_Mes_Corriente!$1:$300, 169, 3 + ($C$4 - 2021)*13 + 12) -> 0 | D23: =INDEX(MINVU_Mes_Corriente!$1:$300, 191, 3 + ($C$4 - 2021)*13 + 12) -> 0 | E23: =INDEX(MINVU_Mes_Corriente!$1:$300, 31, 3 + ($C$4 - 2021)*13 + 12) -> 27933416 | F23: =INDEX(MINVU_Mes_Corriente!$1:$300, 53, 3 + ($C$4 - 2021)*13 + 12) -> 27847917 | G23: =INDEX(MINVU_Mes_Corriente!$1:$300, 100, 3 + ($C$4 - 2021)*13 + 12) -> 240920 | H23: =INDEX(MINVU_Mes_Corriente!$1:$300, 122, 3 + ($C$4 - 2021)*13 + 12) -> 240208 | I23: =C23 + E23 + G23 -> 28174336 | J23: =D23 + F23 + H23 -> 28088125 | K23: =I23 - J23 -> 86211 | L23: =IF(I23>0, J23/I23, 0) -> 0.99694009 | M23: =IF($I$40>0, I23/$I$40, 0) -> 0.0084537341
B24: SERVIU Arica y Parinacota | C24: =INDEX(MINVU_Mes_Corriente!$1:$300, 170, 3 + ($C$4 - 2021)*13 + 12) -> 83210671 | D24: =INDEX(MINVU_Mes_Corriente!$1:$300, 192, 3 + ($C$4 - 2021)*13 + 12) -> 83196155 | E24: =INDEX(MINVU_Mes_Corriente!$1:$300, 32, 3 + ($C$4 - 2021)*13 + 12) -> 4403210 | F24: =INDEX(MINVU_Mes_Corriente!$1:$300, 54, 3 + ($C$4 - 2021)*13 + 12) -> 4379123 | G24: =INDEX(MINVU_Mes_Corriente!$1:$300, 101, 3 + ($C$4 - 2021)*13 + 12) -> 7496 | H24: =INDEX(MINVU_Mes_Corriente!$1:$300, 123, 3 + ($C$4 - 2021)*13 + 12) -> 7431 | I24: =C24 + E24 + G24 -> 87621377 | J24: =D24 + F24 + H24 -> 87582709 | K24: =I24 - J24 -> 38668 | L24: =IF(I24>0, J24/I24, 0) -> 0.99955869 | M24: =IF($I$40>0, I24/$I$40, 0) -> 0.026290871
B25: SERVIU Tarapacá | C25: =INDEX(MINVU_Mes_Corriente!$1:$300, 171, 3 + ($C$4 - 2021)*13 + 12) -> 81745804 | D25: =INDEX(MINVU_Mes_Corriente!$1:$300, 193, 3 + ($C$4 - 2021)*13 + 12) -> 81667751 | E25: =INDEX(MINVU_Mes_Corriente!$1:$300, 33, 3 + ($C$4 - 2021)*13 + 12) -> 8998445 | F25: =INDEX(MINVU_Mes_Corriente!$1:$300, 55, 3 + ($C$4 - 2021)*13 + 12) -> 8453266 | G25: =INDEX(MINVU_Mes_Corriente!$1:$300, 102, 3 + ($C$4 - 2021)*13 + 12) -> 3479 | H25: =INDEX(MINVU_Mes_Corriente!$1:$300, 124, 3 + ($C$4 - 2021)*13 + 12) -> 3340 | I25: =C25 + E25 + G25 -> 90747728 | J25: =D25 + F25 + H25 -> 90124357 | K25: =I25 - J25 -> 623371 | L25: =IF(I25>0, J25/I25, 0) -> 0.99313073 | M25: =IF($I$40>0, I25/$I$40, 0) -> 0.027228935
B26: SERVIU Antofagasta | C26: =INDEX(MINVU_Mes_Corriente!$1:$300, 172, 3 + ($C$4 - 2021)*13 + 12) -> 73119497 | D26: =INDEX(MINVU_Mes_Corriente!$1:$300, 194, 3 + ($C$4 - 2021)*13 + 12) -> 73069447 | E26: =INDEX(MINVU_Mes_Corriente!$1:$300, 34, 3 + ($C$4 - 2021)*13 + 12) -> 15465604 | F26: =INDEX(MINVU_Mes_Corriente!$1:$300, 56, 3 + ($C$4 - 2021)*13 + 12) -> 14221677 | G26: =INDEX(MINVU_Mes_Corriente!$1:$300, 103, 3 + ($C$4 - 2021)*13 + 12) -> 6270 | H26: =INDEX(MINVU_Mes_Corriente!$1:$300, 125, 3 + ($C$4 - 2021)*13 + 12) -> 4665 | I26: =C26 + E26 + G26 -> 88591371 | J26: =D26 + F26 + H26 -> 87295789 | K26: =I26 - J26 -> 1295582 | L26: =IF(I26>0, J26/I26, 0) -> 0.98537575 | M26: =IF($I$40>0, I26/$I$40, 0) -> 0.026581918
B27: SERVIU Atacama | C27: =INDEX(MINVU_Mes_Corriente!$1:$300, 173, 3 + ($C$4 - 2021)*13 + 12) -> 50339570 | D27: =INDEX(MINVU_Mes_Corriente!$1:$300, 195, 3 + ($C$4 - 2021)*13 + 12) -> 50275024 | E27: =INDEX(MINVU_Mes_Corriente!$1:$300, 35, 3 + ($C$4 - 2021)*13 + 12) -> 8570431 | F27: =INDEX(MINVU_Mes_Corriente!$1:$300, 57, 3 + ($C$4 - 2021)*13 + 12) -> 8070989 | G27: =INDEX(MINVU_Mes_Corriente!$1:$300, 104, 3 + ($C$4 - 2021)*13 + 12) -> 6646 | H27: =INDEX(MINVU_Mes_Corriente!$1:$300, 126, 3 + ($C$4 - 2021)*13 + 12) -> 6646 | I27: =C27 + E27 + G27 -> 58916647 | J27: =D27 + F27 + H27 -> 58352659 | K27: =I27 - J27 -> 563988 | L27: =IF(I27>0, J27/I27, 0) -> 0.99042736 | M27: =IF($I$40>0, I27/$I$40, 0) -> 0.017677991
B28: SERVIU Coquimbo | C28: =INDEX(MINVU_Mes_Corriente!$1:$300, 174, 3 + ($C$4 - 2021)*13 + 12) -> 107360177 | D28: =INDEX(MINVU_Mes_Corriente!$1:$300, 196, 3 + ($C$4 - 2021)*13 + 12) -> 106974951 | E28: =INDEX(MINVU_Mes_Corriente!$1:$300, 36, 3 + ($C$4 - 2021)*13 + 12) -> 18466482 | F28: =INDEX(MINVU_Mes_Corriente!$1:$300, 58, 3 + ($C$4 - 2021)*13 + 12) -> 18304746 | G28: =INDEX(MINVU_Mes_Corriente!$1:$300, 105, 3 + ($C$4 - 2021)*13 + 12) -> 6092813 | H28: =INDEX(MINVU_Mes_Corriente!$1:$300, 127, 3 + ($C$4 - 2021)*13 + 12) -> 6065343 | I28: =C28 + E28 + G28 -> 131919472 | J28: =D28 + F28 + H28 -> 131345040 | K28: =I28 - J28 -> 574432 | L28: =IF(I28>0, J28/I28, 0) -> 0.99564559 | M28: =IF($I$40>0, I28/$I$40, 0) -> 0.039582553
B29: SERVIU Valparaíso | C29: =INDEX(MINVU_Mes_Corriente!$1:$300, 175, 3 + ($C$4 - 2021)*13 + 12) -> 226125474 | D29: =INDEX(MINVU_Mes_Corriente!$1:$300, 197, 3 + ($C$4 - 2021)*13 + 12) -> 225998740 | E29: =INDEX(MINVU_Mes_Corriente!$1:$300, 37, 3 + ($C$4 - 2021)*13 + 12) -> 37750186 | F29: =INDEX(MINVU_Mes_Corriente!$1:$300, 59, 3 + ($C$4 - 2021)*13 + 12) -> 35664606 | G29: =INDEX(MINVU_Mes_Corriente!$1:$300, 106, 3 + ($C$4 - 2021)*13 + 12) -> 21887 | H29: =INDEX(MINVU_Mes_Corriente!$1:$300, 128, 3 + ($C$4 - 2021)*13 + 12) -> 21833 | I29: =C29 + E29 + G29 -> 263897547 | J29: =D29 + F29 + H29 -> 261685179 | K29: =I29 - J29 -> 2212368 | L29: =IF(I29>0, J29/I29, 0) -> 0.99161656 | M29: =IF($I$40>0, I29/$I$40, 0) -> 0.079182689
B30: SERVIU Metropolitano | C30: =INDEX(MINVU_Mes_Corriente!$1:$300, 176, 3 + ($C$4 - 2021)*13 + 12) -> 536507887 | D30: =INDEX(MINVU_Mes_Corriente!$1:$300, 198, 3 + ($C$4 - 2021)*13 + 12) -> 535781681 | E30: =INDEX(MINVU_Mes_Corriente!$1:$300, 38, 3 + ($C$4 - 2021)*13 + 12) -> 86087430 | F30: =INDEX(MINVU_Mes_Corriente!$1:$300, 60, 3 + ($C$4 - 2021)*13 + 12) -> 84329419 | G30: =INDEX(MINVU_Mes_Corriente!$1:$300, 107, 3 + ($C$4 - 2021)*13 + 12) -> 44560 | H30: =INDEX(MINVU_Mes_Corriente!$1:$300, 129, 3 + ($C$4 - 2021)*13 + 12) -> 44534 | I30: =C30 + E30 + G30 -> 622639877 | J30: =D30 + F30 + H30 -> 620155634 | K30: =I30 - J30 -> 2484243 | L30: =IF(I30>0, J30/I30, 0) -> 0.99601014 | M30: =IF($I$40>0, I30/$I$40, 0) -> 0.18682364
B31: SERVIU O'Higgins | C31: =INDEX(MINVU_Mes_Corriente!$1:$300, 177, 3 + ($C$4 - 2021)*13 + 12) -> 172944682 | D31: =INDEX(MINVU_Mes_Corriente!$1:$300, 199, 3 + ($C$4 - 2021)*13 + 12) -> 172843913 | E31: =INDEX(MINVU_Mes_Corriente!$1:$300, 39, 3 + ($C$4 - 2021)*13 + 12) -> 5515173 | F31: =INDEX(MINVU_Mes_Corriente!$1:$300, 61, 3 + ($C$4 - 2021)*13 + 12) -> 5186229 | G31: =INDEX(MINVU_Mes_Corriente!$1:$300, 108, 3 + ($C$4 - 2021)*13 + 12) -> 300457 | H31: =INDEX(MINVU_Mes_Corriente!$1:$300, 130, 3 + ($C$4 - 2021)*13 + 12) -> 300441 | I31: =C31 + E31 + G31 -> 178760312 | J31: =D31 + F31 + H31 -> 178330583 | K31: =I31 - J31 -> 429729 | L31: =IF(I31>0, J31/I31, 0) -> 0.99759606 | M31: =IF($I$40>0, I31/$I$40, 0) -> 0.053637188
B32: SERVIU Maule | C32: =INDEX(MINVU_Mes_Corriente!$1:$300, 178, 3 + ($C$4 - 2021)*13 + 12) -> 213444748 | D32: =INDEX(MINVU_Mes_Corriente!$1:$300, 200, 3 + ($C$4 - 2021)*13 + 12) -> 213325058 | E32: =INDEX(MINVU_Mes_Corriente!$1:$300, 40, 3 + ($C$4 - 2021)*13 + 12) -> 20053849 | F32: =INDEX(MINVU_Mes_Corriente!$1:$300, 62, 3 + ($C$4 - 2021)*13 + 12) -> 19302172 | G32: =INDEX(MINVU_Mes_Corriente!$1:$300, 109, 3 + ($C$4 - 2021)*13 + 12) -> 6865 | H32: =INDEX(MINVU_Mes_Corriente!$1:$300, 131, 3 + ($C$4 - 2021)*13 + 12) -> 6833 | I32: =C32 + E32 + G32 -> 233505462 | J32: =D32 + F32 + H32 -> 232634063 | K32: =I32 - J32 -> 871399 | L32: =IF(I32>0, J32/I32, 0) -> 0.99626819 | M32: =IF($I$40>0, I32/$I$40, 0) -> 0.070063518
B33: SERVIU Ñuble | C33: =INDEX(MINVU_Mes_Corriente!$1:$300, 179, 3 + ($C$4 - 2021)*13 + 12) -> 154702362 | D33: =INDEX(MINVU_Mes_Corriente!$1:$300, 201, 3 + ($C$4 - 2021)*13 + 12) -> 154664738 | E33: =INDEX(MINVU_Mes_Corriente!$1:$300, 41, 3 + ($C$4 - 2021)*13 + 12) -> 19120001 | F33: =INDEX(MINVU_Mes_Corriente!$1:$300, 63, 3 + ($C$4 - 2021)*13 + 12) -> 17950052 | G33: =INDEX(MINVU_Mes_Corriente!$1:$300, 110, 3 + ($C$4 - 2021)*13 + 12) -> 6270 | H33: =INDEX(MINVU_Mes_Corriente!$1:$300, 132, 3 + ($C$4 - 2021)*13 + 12) -> 6042 | I33: =C33 + E33 + G33 -> 173828633 | J33: =D33 + F33 + H33 -> 172620832 | K33: =I33 - J33 -> 1207801 | L33: =IF(I33>0, J33/I33, 0) -> 0.99305177 | M33: =IF($I$40>0, I33/$I$40, 0) -> 0.052157433
B34: SERVIU Biobío | C34: =INDEX(MINVU_Mes_Corriente!$1:$300, 180, 3 + ($C$4 - 2021)*13 + 12) -> 303934966 | D34: =INDEX(MINVU_Mes_Corriente!$1:$300, 202, 3 + ($C$4 - 2021)*13 + 12) -> 303859023 | E34: =INDEX(MINVU_Mes_Corriente!$1:$300, 42, 3 + ($C$4 - 2021)*13 + 12) -> 52850218 | F34: =INDEX(MINVU_Mes_Corriente!$1:$300, 64, 3 + ($C$4 - 2021)*13 + 12) -> 52001305 | G34: =INDEX(MINVU_Mes_Corriente!$1:$300, 111, 3 + ($C$4 - 2021)*13 + 12) -> 12960 | H34: =INDEX(MINVU_Mes_Corriente!$1:$300, 133, 3 + ($C$4 - 2021)*13 + 12) -> 12190 | I34: =C34 + E34 + G34 -> 356798144 | J34: =D34 + F34 + H34 -> 355872518 | K34: =I34 - J34 -> 925626 | L34: =IF(I34>0, J34/I34, 0) -> 0.99740574 | M34: =IF($I$40>0, I34/$I$40, 0) -> 0.10705759
B35: SERVIU La Araucanía | C35: =INDEX(MINVU_Mes_Corriente!$1:$300, 181, 3 + ($C$4 - 2021)*13 + 12) -> 266347073 | D35: =INDEX(MINVU_Mes_Corriente!$1:$300, 203, 3 + ($C$4 - 2021)*13 + 12) -> 265754901 | E35: =INDEX(MINVU_Mes_Corriente!$1:$300, 43, 3 + ($C$4 - 2021)*13 + 12) -> 36728957 | F35: =INDEX(MINVU_Mes_Corriente!$1:$300, 65, 3 + ($C$4 - 2021)*13 + 12) -> 36426224 | G35: =INDEX(MINVU_Mes_Corriente!$1:$300, 112, 3 + ($C$4 - 2021)*13 + 12) -> 12161 | H35: =INDEX(MINVU_Mes_Corriente!$1:$300, 134, 3 + ($C$4 - 2021)*13 + 12) -> 12134 | I35: =C35 + E35 + G35 -> 303088191 | J35: =D35 + F35 + H35 -> 302193259 | K35: =I35 - J35 -> 894932 | L35: =IF(I35>0, J35/I35, 0) -> 0.99704729 | M35: =IF($I$40>0, I35/$I$40, 0) -> 0.090941876
B36: SERVIU Los Ríos | C36: =INDEX(MINVU_Mes_Corriente!$1:$300, 182, 3 + ($C$4 - 2021)*13 + 12) -> 73852164 | D36: =INDEX(MINVU_Mes_Corriente!$1:$300, 204, 3 + ($C$4 - 2021)*13 + 12) -> 72195760 | E36: =INDEX(MINVU_Mes_Corriente!$1:$300, 44, 3 + ($C$4 - 2021)*13 + 12) -> 13330524 | F36: =INDEX(MINVU_Mes_Corriente!$1:$300, 66, 3 + ($C$4 - 2021)*13 + 12) -> 12655537 | G36: =INDEX(MINVU_Mes_Corriente!$1:$300, 113, 3 + ($C$4 - 2021)*13 + 12) -> 9216 | H36: =INDEX(MINVU_Mes_Corriente!$1:$300, 135, 3 + ($C$4 - 2021)*13 + 12) -> 9209 | I36: =C36 + E36 + G36 -> 87191904 | J36: =D36 + F36 + H36 -> 84860506 | K36: =I36 - J36 -> 2331398 | L36: =IF(I36>0, J36/I36, 0) -> 0.9732613 | M36: =IF($I$40>0, I36/$I$40, 0) -> 0.026162007
B37: SERVIU Los Lagos | C37: =INDEX(MINVU_Mes_Corriente!$1:$300, 183, 3 + ($C$4 - 2021)*13 + 12) -> 209110935 | D37: =INDEX(MINVU_Mes_Corriente!$1:$300, 205, 3 + ($C$4 - 2021)*13 + 12) -> 209043392 | E37: =INDEX(MINVU_Mes_Corriente!$1:$300, 45, 3 + ($C$4 - 2021)*13 + 12) -> 17300120 | F37: =INDEX(MINVU_Mes_Corriente!$1:$300, 67, 3 + ($C$4 - 2021)*13 + 12) -> 16578842 | G37: =INDEX(MINVU_Mes_Corriente!$1:$300, 114, 3 + ($C$4 - 2021)*13 + 12) -> 9262299 | H37: =INDEX(MINVU_Mes_Corriente!$1:$300, 136, 3 + ($C$4 - 2021)*13 + 12) -> 9235856 | I37: =C37 + E37 + G37 -> 235673354 | J37: =D37 + F37 + H37 -> 234858090 | K37: =I37 - J37 -> 815264 | L37: =IF(I37>0, J37/I37, 0) -> 0.9965407 | M37: =IF($I$40>0, I37/$I$40, 0) -> 0.070713995
B38: SERVIU Aysén | C38: =INDEX(MINVU_Mes_Corriente!$1:$300, 184, 3 + ($C$4 - 2021)*13 + 12) -> 40911462 | D38: =INDEX(MINVU_Mes_Corriente!$1:$300, 206, 3 + ($C$4 - 2021)*13 + 12) -> 40629172 | E38: =INDEX(MINVU_Mes_Corriente!$1:$300, 46, 3 + ($C$4 - 2021)*13 + 12) -> 7723948 | F38: =INDEX(MINVU_Mes_Corriente!$1:$300, 68, 3 + ($C$4 - 2021)*13 + 12) -> 7636879 | G38: =INDEX(MINVU_Mes_Corriente!$1:$300, 115, 3 + ($C$4 - 2021)*13 + 12) -> 6270 | H38: =INDEX(MINVU_Mes_Corriente!$1:$300, 137, 3 + ($C$4 - 2021)*13 + 12) -> 6224 | I38: =C38 + E38 + G38 -> 48641680 | J38: =D38 + F38 + H38 -> 48272275 | K38: =I38 - J38 -> 369405 | L38: =IF(I38>0, J38/I38, 0) -> 0.99240559 | M38: =IF($I$40>0, I38/$I$40, 0) -> 0.014594979
B39: SERVIU Magallanes | C39: =INDEX(MINVU_Mes_Corriente!$1:$300, 185, 3 + ($C$4 - 2021)*13 + 12) -> 66490061 | D39: =INDEX(MINVU_Mes_Corriente!$1:$300, 207, 3 + ($C$4 - 2021)*13 + 12) -> 66459701 | E39: =INDEX(MINVU_Mes_Corriente!$1:$300, 47, 3 + ($C$4 - 2021)*13 + 12) -> 17985481 | F39: =INDEX(MINVU_Mes_Corriente!$1:$300, 69, 3 + ($C$4 - 2021)*13 + 12) -> 17938143 | G39: =INDEX(MINVU_Mes_Corriente!$1:$300, 116, 3 + ($C$4 - 2021)*13 + 12) -> 8343 | H39: =INDEX(MINVU_Mes_Corriente!$1:$300, 138, 3 + ($C$4 - 2021)*13 + 12) -> 8289 | I39: =C39 + E39 + G39 -> 84483885 | J39: =D39 + F39 + H39 -> 84406133 | K39: =I39 - J39 -> 77752 | L39: =IF(I39>0, J39/I39, 0) -> 0.99907968 | M39: =IF($I$40>0, I39/$I$40, 0) -> 0.025349463
B40: TOTAL MINVU | C40: =SUM(C22:C39) -> 2913408485 | D40: =SUM(D22:D39) -> 2904924599 | E40: =SUM(E22:E39) -> 400142072 | F40: =SUM(F22:F39) -> 388712182 | G40: =SUM(G22:G39) -> 19217626 | H40: =SUM(H22:H39) -> 19062259 | I40: =SUM(I22:I39) -> 3332768183 | J40: =SUM(J22:J39) -> 3312699040 | K40: =SUM(K22:K39) -> 20069143 | L40: =IF(I40>0, J40/I40, 0) -> 0.99397824 | M40: =SUM(M22:M39) -> 1
B42: TABLA 3: EVOLUCIÓN MENSUAL DEL AÑO SELECCIONADO (ENERO A DICIEMBRE)
B44: Concepto / Mes | C44: Ene | D44: Feb | E44: Mar | F44: Abr | G44: May | H44: Jun | I44: Jul | J44: Ago | K44: Sep | L44: Oct | M44: Nov | N44: Dic | O44: Cierre Total
B45: Presupuesto Ley | C45: =INDEX(MINVU_Mes_Corriente!$1:$300, 164, 3 + ($C$4 - 2021)*13 + 0) + INDEX(MINVU_Mes_Corriente!$1:$300, 26, 3 + ($C$4 - 2021)*13 + 0) + INDEX(MINVU_Mes_Corriente!$1:$300, 95, 3 + ($C$4 - 2021)*13 + 0) -> 3320541734 | D45: =INDEX(MINVU_Mes_Corriente!$1:$300, 164, 3 + ($C$4 - 2021)*13 + 1) + INDEX(MINVU_Mes_Corriente!$1:$300, 26, 3 + ($C$4 - 2021)*13 + 1) + INDEX(MINVU_Mes_Corriente!$1:$300, 95, 3 + ($C$4 - 2021)*13 + 1) -> 3320541734 | E45: =INDEX(MINVU_Mes_Corriente!$1:$300, 164, 3 + ($C$4 - 2021)*13 + 2) + INDEX(MINVU_Mes_Corriente!$1:$300, 26, 3 + ($C$4 - 2021)*13 + 2) + INDEX(MINVU_Mes_Corriente!$1:$300, 95, 3 + ($C$4 - 2021)*13 + 2) -> 3320541734 | F45: =INDEX(MINVU_Mes_Corriente!$1:$300, 164, 3 + ($C$4 - 2021)*13 + 3) + INDEX(MINVU_Mes_Corriente!$1:$300, 26, 3 + ($C$4 - 2021)*13 + 3) + INDEX(MINVU_Mes_Corriente!$1:$300, 95, 3 + ($C$4 - 2021)*13 + 3) -> 3320541734 | G45: =INDEX(MINVU_Mes_Corriente!$1:$300, 164, 3 + ($C$4 - 2021)*13 + 4) + INDEX(MINVU_Mes_Corriente!$1:$300, 26, 3 + ($C$4 - 2021)*13 + 4) + INDEX(MINVU_Mes_Corriente!$1:$300, 95, 3 + ($C$4 - 2021)*13 + 4) -> 3320541734 | H45: =INDEX(MINVU_Mes_Corriente!$1:$300, 164, 3 + ($C$4 - 2021)*13 + 5) + INDEX(MINVU_Mes_Corriente!$1:$300, 26, 3 + ($C$4 - 2021)*13 + 5) + INDEX(MINVU_Mes_Corriente!$1:$300, 95, 3 + ($C$4 - 2021)*13 + 5) -> 3320541734 | I45: =INDEX(MINVU_Mes_Corriente!$1:$300, 164, 3 + ($C$4 - 2021)*13 + 6) + INDEX(MINVU_Mes_Corriente!$1:$300, 26, 3 + ($C$4 - 2021)*13 + 6) + INDEX(MINVU_Mes_Corriente!$1:$300, 95, 3 + ($C$4 - 2021)*13 + 6) -> 3320541734 | J45: =INDEX(MINVU_Mes_Corriente!$1:$300, 164, 3 + ($C$4 - 2021)*13 + 7) + INDEX(MINVU_Mes_Corriente!$1:$300, 26, 3 + ($C$4 - 2021)*13 + 7) + INDEX(MINVU_Mes_Corriente!$1:$300, 95, 3 + ($C$4 - 2021)*13 + 7) -> 3320541734 | K45: =INDEX(MINVU_Mes_Corriente!$1:$300, 164, 3 + ($C$4 - 2021)*13 + 8) + INDEX(MINVU_Mes_Corriente!$1:$300, 26, 3 + ($C$4 - 2021)*13 + 8) + INDEX(MINVU_Mes_Corriente!$1:$300, 95, 3 + ($C$4 - 2021)*13 + 8) -> 3320541734 | L45: =INDEX(MINVU_Mes_Corriente!$1:$300, 164, 3 + ($C$4 - 2021)*13 + 9) + INDEX(MINVU_Mes_Corriente!$1:$300, 26, 3 + ($C$4 - 2021)*13 + 9) + INDEX(MINVU_Mes_Corriente!$1:$300, 95, 3 + ($C$4 - 2021)*13 + 9) -> 3320541734 | M45: =INDEX(MINVU_Mes_Corriente!$1:$300, 164, 3 + ($C$4 - 2021)*13 + 10) + INDEX(MINVU_Mes_Corriente!$1:$300, 26, 3 + ($C$4 - 2021)*13 + 10) + INDEX(MINVU_Mes_Corriente!$1:$300, 95, 3 + ($C$4 - 2021)*13 + 10) -> 3320541734 | N45: =INDEX(MINVU_Mes_Corriente!$1:$300, 164, 3 + ($C$4 - 2021)*13 + 11) + INDEX(MINVU_Mes_Corriente!$1:$300, 26, 3 + ($C$4 - 2021)*13 + 11) + INDEX(MINVU_Mes_Corriente!$1:$300, 95, 3 + ($C$4 - 2021)*13 + 11) -> 3320541734 | O45: =INDEX(MINVU_Mes_Corriente!$1:$300, 164, 3 + ($C$4 - 2021)*13 + 12) + INDEX(MINVU_Mes_Corriente!$1:$300, 26, 3 + ($C$4 - 2021)*13 + 12) + INDEX(MINVU_Mes_Corriente!$1:$300, 95, 3 + ($C$4 - 2021)*13 + 12) -> 3320541734
B46: Presupuesto Vigente | C46: =INDEX(MINVU_Mes_Corriente!$1:$300, 186, 3 + ($C$4 - 2021)*13 + 0) + INDEX(MINVU_Mes_Corriente!$1:$300, 48, 3 + ($C$4 - 2021)*13 + 0) + INDEX(MINVU_Mes_Corriente!$1:$300, 117, 3 + ($C$4 - 2021)*13 + 0) -> 3320541734 | D46: =INDEX(MINVU_Mes_Corriente!$1:$300, 186, 3 + ($C$4 - 2021)*13 + 1) + INDEX(MINVU_Mes_Corriente!$1:$300, 48, 3 + ($C$4 - 2021)*13 + 1) + INDEX(MINVU_Mes_Corriente!$1:$300, 117, 3 + ($C$4 - 2021)*13 + 1) -> 3320541734 | E46: =INDEX(MINVU_Mes_Corriente!$1:$300, 186, 3 + ($C$4 - 2021)*13 + 2) + INDEX(MINVU_Mes_Corriente!$1:$300, 48, 3 + ($C$4 - 2021)*13 + 2) + INDEX(MINVU_Mes_Corriente!$1:$300, 117, 3 + ($C$4 - 2021)*13 + 2) -> 3320541734 | F46: =INDEX(MINVU_Mes_Corriente!$1:$300, 186, 3 + ($C$4 - 2021)*13 + 3) + INDEX(MINVU_Mes_Corriente!$1:$300, 48, 3 + ($C$4 - 2021)*13 + 3) + INDEX(MINVU_Mes_Corriente!$1:$300, 117, 3 + ($C$4 - 2021)*13 + 3) -> 3320541734 | G46: =INDEX(MINVU_Mes_Corriente!$1:$300, 186, 3 + ($C$4 - 2021)*13 + 4) + INDEX(MINVU_Mes_Corriente!$1:$300, 48, 3 + ($C$4 - 2021)*13 + 4) + INDEX(MINVU_Mes_Corriente!$1:$300, 117, 3 + ($C$4 - 2021)*13 + 4) -> 3320643534 | H46: =INDEX(MINVU_Mes_Corriente!$1:$300, 186, 3 + ($C$4 - 2021)*13 + 5) + INDEX(MINVU_Mes_Corriente!$1:$300, 48, 3 + ($C$4 - 2021)*13 + 5) + INDEX(MINVU_Mes_Corriente!$1:$300, 117, 3 + ($C$4 - 2021)*13 + 5) -> 3320643534 | I46: =INDEX(MINVU_Mes_Corriente!$1:$300, 186, 3 + ($C$4 - 2021)*13 + 6) + INDEX(MINVU_Mes_Corriente!$1:$300, 48, 3 + ($C$4 - 2021)*13 + 6) + INDEX(MINVU_Mes_Corriente!$1:$300, 117, 3 + ($C$4 - 2021)*13 + 6) -> 3329424159 | J46: =INDEX(MINVU_Mes_Corriente!$1:$300, 186, 3 + ($C$4 - 2021)*13 + 7) + INDEX(MINVU_Mes_Corriente!$1:$300, 48, 3 + ($C$4 - 2021)*13 + 7) + INDEX(MINVU_Mes_Corriente!$1:$300, 117, 3 + ($C$4 - 2021)*13 + 7) -> 3376717372 | K46: =INDEX(MINVU_Mes_Corriente!$1:$300, 186, 3 + ($C$4 - 2021)*13 + 8) + INDEX(MINVU_Mes_Corriente!$1:$300, 48, 3 + ($C$4 - 2021)*13 + 8) + INDEX(MINVU_Mes_Corriente!$1:$300, 117, 3 + ($C$4 - 2021)*13 + 8) -> 3421717372 | L46: =INDEX(MINVU_Mes_Corriente!$1:$300, 186, 3 + ($C$4 - 2021)*13 + 9) + INDEX(MINVU_Mes_Corriente!$1:$300, 48, 3 + ($C$4 - 2021)*13 + 9) + INDEX(MINVU_Mes_Corriente!$1:$300, 117, 3 + ($C$4 - 2021)*13 + 9) -> 3491232791 | M46: =INDEX(MINVU_Mes_Corriente!$1:$300, 186, 3 + ($C$4 - 2021)*13 + 10) + INDEX(MINVU_Mes_Corriente!$1:$300, 48, 3 + ($C$4 - 2021)*13 + 10) + INDEX(MINVU_Mes_Corriente!$1:$300, 117, 3 + ($C$4 - 2021)*13 + 10) -> 3488688633 | N46: =INDEX(MINVU_Mes_Corriente!$1:$300, 186, 3 + ($C$4 - 2021)*13 + 11) + INDEX(MINVU_Mes_Corriente!$1:$300, 48, 3 + ($C$4 - 2021)*13 + 11) + INDEX(MINVU_Mes_Corriente!$1:$300, 117, 3 + ($C$4 - 2021)*13 + 11) -> 3332768183 | O46: =INDEX(MINVU_Mes_Corriente!$1:$300, 186, 3 + ($C$4 - 2021)*13 + 12) + INDEX(MINVU_Mes_Corriente!$1:$300, 48, 3 + ($C$4 - 2021)*13 + 12) + INDEX(MINVU_Mes_Corriente!$1:$300, 117, 3 + ($C$4 - 2021)*13 + 12) -> 3332768183
B47: Ejecución Acumulada | C47: =INDEX(MINVU_Mes_Corriente!$1:$300, 208, 3 + ($C$4 - 2021)*13 + 0) + INDEX(MINVU_Mes_Corriente!$1:$300, 70, 3 + ($C$4 - 2021)*13 + 0) + INDEX(MINVU_Mes_Corriente!$1:$300, 139, 3 + ($C$4 - 2021)*13 + 0) -> 144905537 | D47: =INDEX(MINVU_Mes_Corriente!$1:$300, 208, 3 + ($C$4 - 2021)*13 + 1) + INDEX(MINVU_Mes_Corriente!$1:$300, 70, 3 + ($C$4 - 2021)*13 + 1) + INDEX(MINVU_Mes_Corriente!$1:$300, 139, 3 + ($C$4 - 2021)*13 + 1) -> 392112901 | E47: =INDEX(MINVU_Mes_Corriente!$1:$300, 208, 3 + ($C$4 - 2021)*13 + 2) + INDEX(MINVU_Mes_Corriente!$1:$300, 70, 3 + ($C$4 - 2021)*13 + 2) + INDEX(MINVU_Mes_Corriente!$1:$300, 139, 3 + ($C$4 - 2021)*13 + 2) -> 734004289 | F47: =INDEX(MINVU_Mes_Corriente!$1:$300, 208, 3 + ($C$4 - 2021)*13 + 3) + INDEX(MINVU_Mes_Corriente!$1:$300, 70, 3 + ($C$4 - 2021)*13 + 3) + INDEX(MINVU_Mes_Corriente!$1:$300, 139, 3 + ($C$4 - 2021)*13 + 3) -> 1004471755 | G47: =INDEX(MINVU_Mes_Corriente!$1:$300, 208, 3 + ($C$4 - 2021)*13 + 4) + INDEX(MINVU_Mes_Corriente!$1:$300, 70, 3 + ($C$4 - 2021)*13 + 4) + INDEX(MINVU_Mes_Corriente!$1:$300, 139, 3 + ($C$4 - 2021)*13 + 4) -> 1303821878 | H47: =INDEX(MINVU_Mes_Corriente!$1:$300, 208, 3 + ($C$4 - 2021)*13 + 5) + INDEX(MINVU_Mes_Corriente!$1:$300, 70, 3 + ($C$4 - 2021)*13 + 5) + INDEX(MINVU_Mes_Corriente!$1:$300, 139, 3 + ($C$4 - 2021)*13 + 5) -> 1551877586 | I47: =INDEX(MINVU_Mes_Corriente!$1:$300, 208, 3 + ($C$4 - 2021)*13 + 6) + INDEX(MINVU_Mes_Corriente!$1:$300, 70, 3 + ($C$4 - 2021)*13 + 6) + INDEX(MINVU_Mes_Corriente!$1:$300, 139, 3 + ($C$4 - 2021)*13 + 6) -> 1800513314 | J47: =INDEX(MINVU_Mes_Corriente!$1:$300, 208, 3 + ($C$4 - 2021)*13 + 7) + INDEX(MINVU_Mes_Corriente!$1:$300, 70, 3 + ($C$4 - 2021)*13 + 7) + INDEX(MINVU_Mes_Corriente!$1:$300, 139, 3 + ($C$4 - 2021)*13 + 7) -> 2056646958 | K47: =INDEX(MINVU_Mes_Corriente!$1:$300, 208, 3 + ($C$4 - 2021)*13 + 8) + INDEX(MINVU_Mes_Corriente!$1:$300, 70, 3 + ($C$4 - 2021)*13 + 8) + INDEX(MINVU_Mes_Corriente!$1:$300, 139, 3 + ($C$4 - 2021)*13 + 8) -> 2287303377 | L47: =INDEX(MINVU_Mes_Corriente!$1:$300, 208, 3 + ($C$4 - 2021)*13 + 9) + INDEX(MINVU_Mes_Corriente!$1:$300, 70, 3 + ($C$4 - 2021)*13 + 9) + INDEX(MINVU_Mes_Corriente!$1:$300, 139, 3 + ($C$4 - 2021)*13 + 9) -> 2541084845 | M47: =INDEX(MINVU_Mes_Corriente!$1:$300, 208, 3 + ($C$4 - 2021)*13 + 10) + INDEX(MINVU_Mes_Corriente!$1:$300, 70, 3 + ($C$4 - 2021)*13 + 10) + INDEX(MINVU_Mes_Corriente!$1:$300, 139, 3 + ($C$4 - 2021)*13 + 10) -> 2810519043 | N47: =INDEX(MINVU_Mes_Corriente!$1:$300, 208, 3 + ($C$4 - 2021)*13 + 11) + INDEX(MINVU_Mes_Corriente!$1:$300, 70, 3 + ($C$4 - 2021)*13 + 11) + INDEX(MINVU_Mes_Corriente!$1:$300, 139, 3 + ($C$4 - 2021)*13 + 11) -> 3312699040 | O47: =INDEX(MINVU_Mes_Corriente!$1:$300, 208, 3 + ($C$4 - 2021)*13 + 12) + INDEX(MINVU_Mes_Corriente!$1:$300, 70, 3 + ($C$4 - 2021)*13 + 12) + INDEX(MINVU_Mes_Corriente!$1:$300, 139, 3 + ($C$4 - 2021)*13 + 12) -> 3312699040
B48: % Avance Ejecución | C48: =IF(C46>0, C47/C46, 0) -> 0.043639125 | D48: =IF(D46>0, D47/D46, 0) -> 0.11808703 | E48: =IF(E46>0, E47/E46, 0) -> 0.22104956 | F48: =IF(F46>0, F47/F46, 0) -> 0.30250237 | G48: =IF(G46>0, G47/G46, 0) -> 0.39264133 | H48: =IF(H46>0, H47/H46, 0) -> 0.46734242 | I48: =IF(I46>0, I47/I46, 0) -> 0.5407882 | J48: =IF(J46>0, J47/J46, 0) -> 0.60906695 | ... O48: =IF(O46>0, O47/O46, 0) -> 0.99397824
B50: TABLA 4: COMPARATIVA HISTÓRICA MULTIANUAL (2021 - 2026)
B52: Año | C52: Presupuesto Ley | D52: Presupuesto Vigente | E52: Ejecución Acumulada | F52: Saldo por Ejecutar | G52: % Ejecución | H52: Crec. Vigente (YoY) | I52: Crec. Ejecución (YoY)
B53: 2021 | C53: =MINVU_Mes_Corriente!O164 + MINVU_Mes_Corriente!O26 + MINVU_Mes_Corriente!O95 -> 2165166433 | D53: =MINVU_Mes_Corriente!O186 + MINVU_Mes_Corriente!O48 + MINVU_Mes_Corriente!O117 -> 2390342927 | E53: =MINVU_Mes_Corriente!O208 + MINVU_Mes_Corriente!O70 + MINVU_Mes_Corriente!O139 -> 2353204514 | F53: =D53 - E53 -> 37138413 | G53: =IF(D53>0, E53/D53, 0) -> 0.98446314 | H53: - | I53: -
B54: 2022 | C54: =MINVU_Mes_Corriente!AB164 + MINVU_Mes_Corriente!AB26 + MINVU_Mes_Corriente!AB95 -> 2517555200 | D54: =MINVU_Mes_Corriente!AB186 + MINVU_Mes_Corriente!AB48 + MINVU_Mes_Corriente!AB117 -> 2807365504 | E54: =MINVU_Mes_Corriente!AB208 + MINVU_Mes_Corriente!AB70 + MINVU_Mes_Corriente!AB139 -> 2782762948 | F54: =D54 - E54 -> 24602556 | G54: =IF(D54>0, E54/D54, 0) -> 0.99123643 | H54: =IF(D53>0, (D54-D53)/D53, 0) -> 0.1744614 | I54: =IF(E53>0, (E54-E53)/E53, 0) -> 0.1825419
B55: 2023 | C55: =MINVU_Mes_Corriente!AO164 + MINVU_Mes_Corriente!AO26 + MINVU_Mes_Corriente!AO95 -> 2940348026 | D55: =MINVU_Mes_Corriente!AO186 + MINVU_Mes_Corriente!AO48 + MINVU_Mes_Corriente!AO117 -> 2931817014 | E55: =MINVU_Mes_Corriente!AO208 + MINVU_Mes_Corriente!AO70 + MINVU_Mes_Corriente!AO139 -> 2900163375 | F55: =D55 - E55 -> 31653639 | G55: =IF(D55>0, E55/D55, 0) -> 0.98920341 | H55: =IF(D54>0, (D55-D54)/D54, 0) -> 0.044330355 | I55: =IF(E54>0, (E55-E54)/E54, 0) -> 0.04218844
B56: 2024 | C56: =MINVU_Mes_Corriente!BB164 + MINVU_Mes_Corriente!BB26 + MINVU_Mes_Corriente!BB95 -> 3320541734 | D56: =MINVU_Mes_Corriente!BB186 + MINVU_Mes_Corriente!BB48 + MINVU_Mes_Corriente!BB117 -> 3332768183 | E56: =MINVU_Mes_Corriente!BB208 + MINVU_Mes_Corriente!BB70 + MINVU_Mes_Corriente!BB139 -> 3312699040 | F56: =D56 - E56 -> 20069143 | G56: =IF(D56>0, E56/D56, 0) -> 0.99397824 | H56: =IF(D55>0, (D56-D55)/D55, 0) -> 0.13675859 | I56: =IF(E55>0, (E56-E55)/E55, 0) -> 0.14224566
B57: 2025 | C57: =MINVU_Mes_Corriente!BO164 + MINVU_Mes_Corriente!BO26 + MINVU_Mes_Corriente!BO95 -> 3720328808 | D57: =MINVU_Mes_Corriente!BO186 + MINVU_Mes_Corriente!BO48 + MINVU_Mes_Corriente!BO117 -> 3742940536 | E57: =MINVU_Mes_Corriente!BO208 + MINVU_Mes_Corriente!BO70 + MINVU_Mes_Corriente!BO139 -> 3692492363 | F57: =D57 - E57 -> 50448173 | G57: =IF(D57>0, E57/D57, 0) -> 0.98652178 | H57: =IF(D56>0, (D57-D56)/D56, 0) -> 0.12307257 | I57: =IF(E56>0, (E57-E56)/E56, 0) -> 0.1146477
B58: 2026 | C58: =MINVU_Mes_Corriente!CB164 + MINVU_Mes_Corriente!CB26 + MINVU_Mes_Corriente!CB95 -> 4149679420 | D58: =MINVU_Mes_Corriente!CB186 + MINVU_Mes_Corriente!CB48 + MINVU_Mes_Corriente!CB117 -> 4153039902 | E58: =MINVU_Mes_Corriente!CB208 + MINVU_Mes_Corriente!CB70 + MINVU_Mes_Corriente!CB139 -> 2142379287 | F58: =D58 - E58 -> 2010660615 | G58: =IF(D58>0, E58/D58, 0) -> 0.5158581 | H58: =IF(D57>0, (D58-D57)/D57, 0) -> 0.10956609 | I58: =IF(E57>0, (E58-E57)/E57, 0) -> -0.4198013

Sheet MINVU_Mes_Corriente
B1: Ministerio de Vivienda y Urbanismo — Partida 18
B2: Miles de pesos — moneda corriente — montos devengados
B4: SUBTÍTULO 31 – INICIATIVAS DE INVERSIÓN
B5: Presupuesto Ley (Subtítulo 31)
C6: 2021 | P6: 2022 | AC6: 2023 | AP6: 2024 | BC6: 2025 | BP6: 2026
B7: Programa / Entidad | C7: Ene | D7: Feb | E7: Mar | F7: Abr | G7: May | H7: Jun | I7: Jul | J7: Ago | K7: Sep | L7: Oct | M7: Nov | N7: Dic | O7: Total 2021 | P7: Ene | Q7: Feb | R7: Mar | S7: Abr | T7: May | U7: Jun | V7: Jul | W7: Ago | X7: Sep | Y7: Oct | Z7: Nov | AA7: Dic | AB7: Total 2022 | AC7: Ene | AD7: Feb | AE7: Mar | AF7: Abr | AG7: May | AH7: Jun | AI7: Jul | AJ7: Ago | AK7: Sep | AL7: Oct | AM7: Nov | AN7: Dic | AO7: Total 2023 | AP7: Ene | AQ7: Feb | AR7: Mar | AS7: Abr | AT7: May | AU7: Jun | AV7: Jul | AW7: Ago | AX7: Sep | AY7: Oct | AZ7: Nov | BA7: Dic | BB7: Total 2024 | BC7: Ene | BD7: Feb | BE7: Mar | BF7: Abr | BG7: May | BH7: Jun | BI7: Jul | BJ7: Ago | BK7: Sep | BL7: Oct | BM7: Nov | BN7: Dic | BO7: Total 2025 | BP7: Ene | BQ7: Feb | BR7: Mar | BS7: Abr | BT7: May | BU7: Jun | BV7: Jul | BW7: Ago | BX7: Sep | BY7: Oct | BZ7: Nov | CA7: Dic | CB7: Total 2026
B8: Subsecretaría y Programas Centrales | C8: 35339308 | D8: 35339308 | E8: 35339308 | F8: 35339308 | G8: 35339308 | H8: 35339308 | I8: 35339308 | J8: 35339308 | K8: 35339308 | L8: 35339308 | M8: 35339308 | N8: 35339308 | O8: 35339308 | P8: 22751821 | Q8: 22751821 | R8: 22751821 | S8: 22751821 | T8: 22751821 | U8: 22751821 | V8: 22751821 | W8: 22751821 | X8: 22751821 | Y8: 22751821 | Z8: 22751821 | AA8: 22751821 | AB8: 22751821 | AC8: 22326757 | AD8: 22326757 | AE8: 22326757 | AF8: 22326757 | AG8: 22326757 | AH8: 22326757 | AI8: 22326757 | AJ8: 22326757 | AK8: 22326757 | AL8: 22326757 | AM8: 22326757 | AN8: 22326757 | AO8: 22326757 | AP8: 65885700 | AQ8: 65885700 | AR8: 65885700 | AS8: 65885700 | AT8: 65885700 | AU8: 65885700 | AV8: 65885700 | AW8: 65885700 | AX8: 65885700 | AY8: 65885700 | AZ8: 65885700 | BA8: 65885700 | BB8: 65885700 | BC8: 31496963 | BD8: 31496963 | BE8: 31496963 | BF8: 31496963 | BG8: 31496963 | BH8: 31496963 | BI8: 31496963 | BJ8: 31496963 | BK8: 31496963 | BL8: 31496963 | BM8: 31496963 | BN8: 31496963 | BO8: 31496963 | BP8: 15772873 | BQ8: 15772873 | BR8: 15772873 | BS8: 15772873 | BT8: 15772873 | BU8: 15772873 | BV8: 15772873 | BW8: 15772873 | BX8: 15772873 | BY8: 15772873 | BZ8: 15772873 | CA8: 15772873 | CB8: 15772873
B9: Parque Metropolitano (PARQUEMET) | C9: 28313204 | D9: 28313204 | E9: 28313204 | F9: 28313204 | G9: 28313204 | H9: 28313204 | I9: 28313204 | J9: 28313204 | K9: 28313204 | L9: 28313204 | M9: 28313204 | N9: 28313204 | O9: 28313204 | P9: 26279513 | Q9: 26279513 | R9: 26279513 | S9: 26279513 | T9: 26279513 | U9: 26279513 | V9: 26279513 | W9: 26279513 | X9: 26279513 | Y9: 26279513 | Z9: 26279513 | AA9: 26279513 | AB9: 26279513 | AC9: 23921092 | AD9: 23921092 | AE9: 23921092 | AF9: 23921092 | AG9: 23921092 | AH9: 23921092 | AI9: 23921092 | AJ9: 23921092 | AK9: 23921092 | AL9: 23921092 | AM9: 23921092 | AN9: 23921092 | AO9: 23921092 | AP9: 32623118 | AQ9: 32623118 | AR9: 32623118 | AS9: 32623118 | AT9: 32623118 | AU9: 32623118 | AV9: 32623118 | AW9: 32623118 | AX9: 32623118 | AY9: 32623118 | AZ9: 32623118 | BA9: 32623118 | BB9: 32623118 | BC9: 31388552 | BD9: 31388552 | BE9: 31388552 | BF9: 31388552 | BG9: 31388552 | BH9: 31388552 | BI9: 31388552 | BJ9: 31388552 | BK9: 31388552 | BL9: 31388552 | BM9: 31388552 | BN9: 31388552 | BO9: 31388552 | BP9: 32099544 | BQ9: 32099544 | BR9: 32099544 | BS9: 32099544 | BT9: 32099544 | BU9: 32099544 | BV9: 32099544 | BW9: 32099544 | BX9: 32099544 | BY9: 32099544 | BZ9: 32099544 | CA9: 32099544 | CB9: 32099544
B10: SERVIU Arica y Parinacota | C10: 9734344 | D10: 9734344 | E10: 9734344 | F10: 9734344 | G10: 9734344 | H10: 9734344 | I10: 9734344 | J10: 9734344 | K10: 9734344 | L10: 9734344 | M10: 9734344 | N10: 9734344 | O10: 9734344 | P10: 8027524 | Q10: 8027524 | R10: 8027524 | S10: 8027524 | T10: 8027524 | U10: 8027524 | V10: 8027524 | W10: 8027524 | X10: 8027524 | Y10: 8027524 | Z10: 8027524 | AA10: 8027524 | AB10: 8027524 | AC10: 9623696 | AD10: 9623696 | AE10: 9623696 | AF10: 9623696 | AG10: 9623696 | AH10: 9623696 | AI10: 9623696 | AJ10: 9623696 | AK10: 9623696 | AL10: 9623696 | AM10: 9623696 | AN10: 9623696 | AO10: 9623696 | AP10: 7002032 | AQ10: 7002032 | AR10: 7002032 | AS10: 7002032 | AT10: 7002032 | AU10: 7002032 | AV10: 7002032 | AW10: 7002032 | AX10: 7002032 | AY10: 7002032 | AZ10: 7002032 | BA10: 7002032 | BB10: 7002032 | BC10: 7819491 | BD10: 7819491 | BE10: 7819491 | BF10: 7819491 | BG10: 7819491 | BH10: 7819491 | BI10: 7819491 | BJ10: 7819491 | BK10: 7819491 | BL10: 7819491 | BM10: 7819491 | BN10: 7819491 | BO10: 7819491 | BP10: 2323330 | BQ10: 2323330 | BR10: 2323330 | BS10: 2323330 | BT10: 2323330 | BU10: 2323330 | BV10: 2323330 | BW10: 2323330 | BX10: 2323330 | BY10: 2323330 | BZ10: 2323330 | CA10: 2323330 | CB10: 2323330
B11: SERVIU Tarapacá | C11: 7005376 | D11: 7005376 | E11: 7005376 | F11: 7005376 | G11: 7005376 | H11: 7005376 | I11: 7005376 | J11: 7005376 | K11: 7005376 | L11: 7005376 | M11: 7005376 | N11: 7005376 | O11: 7005376 | P11: 4659283 | Q11: 4659283 | R11: 4659283 | S11: 4659283 | T11: 4659283 | U11: 4659283 | V11: 4659283 | W11: 4659283 | X11: 4659283 | Y11: 4659283 | Z11: 4659283 | AA11: 4659283 | AB11: 4659283 | AC11: 9013306 | AD11: 9013306 | AE11: 9013306 | AF11: 9013306 | AG11: 9013306 | AH11: 9013306 | AI11: 9013306 | AJ11: 9013306 | AK11: 9013306 | AL11: 9013306 | AM11: 9013306 | AN11: 9013306 | AO11: 9013306 | AP11: 11846836 | AQ11: 11846836 | AR11: 11846836 | AS11: 11846836 | AT11: 11846836 | AU11: 11846836 | AV11: 11846836 | AW11: 11846836 | AX11: 11846836 | AY11: 11846836 | AZ11: 11846836 | BA11: 11846836 | BB11: 11846836 | BC11: 9956278 | BD11: 9956278 | BE11: 9956278 | BF11: 9956278 | BG11: 9956278 | BH11: 9956278 | BI11: 9956278 | BJ11: 9956278 | BK11: 9956278 | BL11: 9956278 | BM11: 9956278 | BN11: 9956278 | BO11: 9956278 | BP11: 8706346 | BQ11: 8706346 | BR11: 8706346 | BS11: 8706346 | BT11: 8706346 | BU11: 8706346 | BV11: 8706346 | BW11: 8706346 | BX11: 8706346 | BY11: 8706346 | BZ11: 8706346 | CA11: 8706346 | CB11: 8706346
B12: SERVIU Antofagasta | C12: 35181732 | D12: 35181732 | E12: 35181732 | F12: 35181732 | G12: 35181732 | H12: 35181732 | I12: 35181732 | J12: 35181732 | K12: 35181732 | L12: 35181732 | M12: 35181732 | N12: 35181732 | O12: 35181732 | P12: 35548395 | Q12: 35548395 | R12: 35548395 | S12: 35548395 | T12: 35548395 | U12: 35548395 | V12: 35548395 | W12: 35548395 | X12: 35548395 | Y12: 35548395 | Z12: 35548395 | AA12: 35548395 | AB12: 35548395 | AC12: 30263070 | AD12: 30263070 | AE12: 30263070 | AF12: 30263070 | AG12: 30263070 | AH12: 30263070 | AI12: 30263070 | AJ12: 30263070 | AK12: 30263070 | AL12: 30263070 | AM12: 30263070 | AN12: 30263070 | AO12: 30263070 | AP12: 10878804 | AQ12: 10878804 | AR12: 10878804 | AS12: 10878804 | AT12: 10878804 | AU12: 10878804 | AV12: 10878804 | AW12: 10878804 | AX12: 10878804 | AY12: 10878804 | AZ12: 10878804 | BA12: 10878804 | BB12: 10878804 | BC12: 13585888 | BD12: 13585888 | BE12: 13585888 | BF12: 13585888 | BG12: 13585888 | BH12: 13585888 | BI12: 13585888 | BJ12: 13585888 | BK12: 13585888 | BL12: 13585888 | BM12: 13585888 | BN12: 13585888 | BO12: 13585888 | BP12: 13197867 | BQ12: 13197867 | BR12: 13197867 | BS12: 13197867 | BT12: 13197867 | BU12: 13197867 | BV12: 13197867 | BW12: 13197867 | BX12: 13197867 | BY12: 13197867 | BZ12: 13197867 | CA12: 13197867 | CB12: 13197867
B13: SERVIU Atacama | C13: 18709251 | D13: 18709251 | E13: 18709251 | F13: 18709251 | G13: 18709251 | H13: 18709251 | I13: 18709251 | J13: 18709251 | K13: 18709251 | L13: 18709251 | M13: 18709251 | N13: 18709251 | O13: 18709251 | P13: 24875325 | Q13: 24875325 | R13: 24875325 | S13: 24875325 | T13: 24875325 | U13: 24875325 | V13: 24875325 | W13: 24875325 | X13: 24875325 | Y13: 24875325 | Z13: 24875325 | AA13: 24875325 | AB13: 24875325 | AC13: 21315123 | AD13: 21315123 | AE13: 21315123 | AF13: 21315123 | AG13: 21315123 | AH13: 21315123 | AI13: 21315123 | AJ13: 21315123 | AK13: 21315123 | AL13: 21315123 | AM13: 21315123 | AN13: 21315123 | AO13: 21315123 | AP13: 21518444 | AQ13: 21518444 | AR13: 21518444 | AS13: 21518444 | AT13: 21518444 | AU13: 21518444 | AV13: 21518444 | AW13: 21518444 | AX13: 21518444 | AY13: 21518444 | AZ13: 21518444 | BA13: 21518444 | BB13: 21518444 | BC13: 24183340 | BD13: 24183340 | BE13: 24183340 | BF13: 24183340 | BG13: 24183340 | BH13: 24183340 | BI13: 24183340 | BJ13: 24183340 | BK13: 24183340 | BL13: 24183340 | BM13: 24183340 | BN13: 24183340 | BO13: 24183340 | BP13: 9416801 | BQ13: 9416801 | BR13: 9416801 | BS13: 9416801 | BT13: 9416801 | BU13: 9416801 | BV13: 9416801 | BW13: 9416801 | BX13: 9416801 | BY13: 9416801 | BZ13: 9416801 | CA13: 9416801 | CB13: 9416801
B14: SERVIU Coquimbo | C14: 16689514 | D14: 16689514 | E14: 16689514 | F14: 16689514 | G14: 16689514 | H14: 16689514 | I14: 16689514 | J14: 16689514 | K14: 16689514 | L14: 16689514 | M14: 16689514 | N14: 16689514 | O14: 16689514 | P14: 29291800 | Q14: 29291800 | R14: 29291800 | S14: 29291800 | T14: 29291800 | U14: 29291800 | V14: 29291800 | W14: 29291800 | X14: 29291800 | Y14: 29291800 | Z14: 29291800 | AA14: 29291800 | AB14: 29291800 | AC14: 36352142 | AD14: 36352142 | AE14: 36352142 | AF14: 36352142 | AG14: 36352142 | AH14: 36352142 | AI14: 36352142 | AJ14: 36352142 | AK14: 36352142 | AL14: 36352142 | AM14: 36352142 | AN14: 36352142 | AO14: 36352142 | AP14: 38254690 | AQ14: 38254690 | AR14: 38254690 | AS14: 38254690 | AT14: 38254690 | AU14: 38254690 | AV14: 38254690 | AW14: 38254690 | AX14: 38254690 | AY14: 38254690 | AZ14: 38254690 | BA14: 38254690 | BB14: 38254690 | BC14: 27966487 | BD14: 27966487 | BE14: 27966487 | BF14: 27966487 | BG14: 27966487 | BH14: 27966487 | BI14: 27966487 | BJ14: 27966487 | BK14: 27966487 | BL14: 27966487 | BM14: 27966487 | BN14: 27966487 | BO14: 27966487 | BP14: 30615904 | BQ14: 30615904 | BR14: 30615904 | BS14: 30615904 | BT14: 30615904 | BU14: 30615904 | BV14: 30615904 | BW14: 30615904 | BX14: 30615904 | BY14: 30615904 | BZ14: 30615904 | CA14: 30615904 | CB14: 30615904
B15: SERVIU Valparaíso | C15: 53755591 | D15: 53755591 | E15: 53755591 | F15: 53755591 | G15: 53755591 | H15: 53755591 | I15: 53755591 | J15: 53755591 | K15: 53755591 | L15: 53755591 | M15: 53755591 | N15: 53755591 | O15: 53755591 | P15: 43170852 | Q15: 43170852 | R15: 43170852 | S15: 43170852 | T15: 43170852 | U15: 43170852 | V15: 43170852 | W15: 43170852 | X15: 43170852 | Y15: 43170852 | Z15: 43170852 | AA15: 43170852 | AB15: 43170852 | AC15: 40478579 | AD15: 40478579 | AE15: 40478579 | AF15: 40478579 | AG15: 40478579 | AH15: 40478579 | AI15: 40478579 | AJ15: 40478579 | AK15: 40478579 | AL15: 40478579 | AM15: 40478579 | AN15: 40478579 | AO15: 40478579 | AP15: 44262543 | AQ15: 44262543 | AR15: 44262543 | AS15: 44262543 | AT15: 44262543 | AU15: 44262543 | AV15: 44262543 | AW15: 44262543 | AX15: 44262543 | AY15: 44262543 | AZ15: 44262543 | BA15: 44262543 | BB15: 44262543 | BC15: 42009797 | BD15: 42009797 | BE15: 42009797 | BF15: 42009797 | BG15: 42009797 | BH15: 42009797 | BI15: 42009797 | BJ15: 42009797 | BK15: 42009797 | BL15: 42009797 | BM15: 42009797 | BN15: 42009797 | BO15: 42009797 | BP15: 36533880 | BQ15: 36533880 | BR15: 36533880 | BS15: 36533880 | BT15: 36533880 | BU15: 36533880 | BV15: 36533880 | BW15: 36533880 | BX15: 36533880 | BY15: 36533880 | BZ15: 36533880 | CA15: 36533880 | CB15: 36533880
B16: SERVIU Metropolitano | C16: 75469606 | D16: 75469606 | E16: 75469606 | F16: 75469606 | G16: 75469606 | H16: 75469606 | I16: 75469606 | J16: 75469606 | K16: 75469606 | L16: 75469606 | M16: 75469606 | N16: 75469606 | O16: 75469606 | P16: 100098472 | Q16: 100098472 | R16: 100098472 | S16: 100098472 | T16: 100098472 | U16: 100098472 | V16: 100098472 | W16: 100098472 | X16: 100098472 | Y16: 100098472 | Z16: 100098472 | AA16: 100098472 | AB16: 100098472 | AC16: 105488522 | AD16: 105488522 | AE16: 105488522 | AF16: 105488522 | AG16: 105488522 | AH16: 105488522 | AI16: 105488522 | AJ16: 105488522 | AK16: 105488522 | AL16: 105488522 | AM16: 105488522 | AN16: 105488522 | AO16: 105488522 | AP16: 87253576 | AQ16: 87253576 | AR16: 87253576 | AS16: 87253576 | AT16: 87253576 | AU16: 87253576 | AV16: 87253576 | AW16: 87253576 | AX16: 87253576 | AY16: 87253576 | AZ16: 87253576 | BA16: 87253576 | BB16: 87253576 | BC16: 74587862 | BD16: 74587862 | BE16: 74587862 | BF16: 74587862 | BG16: 74587862 | BH16: 74587862 | BI16: 74587862 | BJ16: 74587862 | BK16: 74587862 | BL16: 74587862 | BM16: 74587862 | BN16: 74587862 | BO16: 74587862 | BP16: 90590002 | BQ16: 90590002 | BR16: 90590002 | BS16: 90590002 | BT16: 90590002 | BU16: 90590002 | BV16: 90590002 | BW16: 90590002 | BX16: 90590002 | BY16: 90590002 | BZ16: 90590002 | CA16: 90590002 | CB16: 90590002
B17: SERVIU O'Higgins | C17: 9595472 | D17: 9595472 | E17: 9595472 | F17: 9595472 | G17: 9595472 | H17: 9595472 | I17: 9595472 | J17: 9595472 | K17: 9595472 | L17: 9595472 | M17: 9595472 | N17: 9595472 | O17: 9595472 | P17: 11870060 | Q17: 11870060 | R17: 11870060 | S17: 11870060 | T17: 11870060 | U17: 11870060 | V17: 11870060 | W17: 11870060 | X17: 11870060 | Y17: 11870060 | Z17: 11870060 | AA17: 11870060 | AB17: 11870060 | AC17: 16473882 | AD17: 16473882 | AE17: 16473882 | AF17: 16473882 | AG17: 16473882 | AH17: 16473882 | AI17: 16473882 | AJ17: 16473882 | AK17: 16473882 | AL17: 16473882 | AM17: 16473882 | AN17: 16473882 | AO17: 16473882 | AP17: 16690085 | AQ17: 16690085 | AR17: 16690085 | AS17: 16690085 | AT17: 16690085 | AU17: 16690085 | AV17: 16690085 | AW17: 16690085 | AX17: 16690085 | AY17: 16690085 | AZ17: 16690085 | BA17: 16690085 | BB17: 16690085 | BC17: 17865780 | BD17: 17865780 | BE17: 17865780 | BF17: 17865780 | BG17: 17865780 | BH17: 17865780 | BI17: 17865780 | BJ17: 17865780 | BK17: 17865780 | BL17: 17865780 | BM17: 17865780 | BN17: 17865780 | BO17: 17865780 | BP17: 14196992 | BQ17: 14196992 | BR17: 14196992 | BS17: 14196992 | BT17: 14196992 | BU17: 14196992 | BV17: 14196992 | BW17: 14196992 | BX17: 14196992 | BY17: 14196992 | BZ17: 14196992 | CA17: 14196992 | CB17: 14196992
B18: SERVIU Maule | C18: 32317785 | D18: 32317785 | E18: 32317785 | F18: 32317785 | G18: 32317785 | H18: 32317785 | I18: 32317785 | J18: 32317785 | K18: 32317785 | L18: 32317785 | M18: 32317785 | N18: 32317785 | O18: 32317785 | P18: 41575245 | Q18: 41575245 | R18: 41575245 | S18: 41575245 | T18: 41575245 | U18: 41575245 | V18: 41575245 | W18: 41575245 | X18: 41575245 | Y18: 41575245 | Z18: 41575245 | AA18: 41575245 | AB18: 41575245 | AC18: 34076619 | AD18: 34076619 | AE18: 34076619 | AF18: 34076619 | AG18: 34076619 | AH18: 34076619 | AI18: 34076619 | AJ18: 34076619 | AK18: 34076619 | AL18: 34076619 | AM18: 34076619 | AN18: 34076619 | AO18: 34076619 | AP18: 28318956 | AQ18: 28318956 | AR18: 28318956 | AS18: 28318956 | AT18: 28318956 | AU18: 28318956 | AV18: 28318956 | AW18: 28318956 | AX18: 28318956 | AY18: 28318956 | AZ18: 28318956 | BA18: 28318956 | BB18: 28318956 | BC18: 30628977 | BD18: 30628977 | BE18: 30628977 | BF18: 30628977 | BG18: 30628977 | BH18: 30628977 | BI18: 30628977 | BJ18: 30628977 | BK18: 30628977 | BL18: 30628977 | BM18: 30628977 | BN18: 30628977 | BO18: 30628977 | BP18: 25030745 | BQ18: 25030745 | BR18: 25030745 | BS18: 25030745 | BT18: 25030745 | BU18: 25030745 | BV18: 25030745 | BW18: 25030745 | BX18: 25030745 | BY18: 25030745 | BZ18: 25030745 | CA18: 25030745 | CB18: 25030745
B19: SERVIU Ñuble | C19: 17998490 | D19: 17998490 | E19: 17998490 | F19: 17998490 | G19: 17998490 | H19: 17998490 | I19: 17998490 | J19: 17998490 | K19: 17998490 | L19: 17998490 | M19: 17998490 | N19: 17998490 | O19: 17998490 | P19: 36920320 | Q19: 36920320 | R19: 36920320 | S19: 36920320 | T19: 36920320 | U19: 36920320 | V19: 36920320 | W19: 36920320 | X19: 36920320 | Y19: 36920320 | Z19: 36920320 | AA19: 36920320 | AB19: 36920320 | AC19: 23700733 | AD19: 23700733 | AE19: 23700733 | AF19: 23700733 | AG19: 23700733 | AH19: 23700733 | AI19: 23700733 | AJ19: 23700733 | AK19: 23700733 | AL19: 23700733 | AM19: 23700733 | AN19: 23700733 | AO19: 23700733 | AP19: 23113535 | AQ19: 23113535 | AR19: 23113535 | AS19: 23113535 | AT19: 23113535 | AU19: 23113535 | AV19: 23113535 | AW19: 23113535 | AX19: 23113535 | AY19: 23113535 | AZ19: 23113535 | BA19: 23113535 | BB19: 23113535 | BC19: 22079448 | BD19: 22079448 | BE19: 22079448 | BF19: 22079448 | BG19: 22079448 | BH19: 22079448 | BI19: 22079448 | BJ19: 22079448 | BK19: 22079448 | BL19: 22079448 | BM19: 22079448 | BN19: 22079448 | BO19: 22079448 | BP19: 24086756 | BQ19: 24086756 | BR19: 24086756 | BS19: 24086756 | BT19: 24086756 | BU19: 24086756 | BV19: 24086756 | BW19: 24086756 | BX19: 24086756 | BY19: 24086756 | BZ19: 24086756 | CA19: 24086756 | CB19: 24086756
... B25: SERVIU Magallanes | C25: 9782662 | D25: 9782662 | E25: 9782662 | F25: 9782662 | G25: 9782662 | H25: 9782662 | I25: 9782662 | J25: 9782662 | K25: 9782662 | L25: 9782662 | M25: 9782662 | N25: 9782662 | O25: 9782662 | P25: 14902342 | Q25: 14902342 | R25: 14902342 | S25: 14902342 | T25: 14902342 | U25: 14902342 | V25: 14902342 | W25: 14902342 | X25: 14902342 | Y25: 14902342 | Z25: 14902342 | AA25: 14902342 | AB25: 14902342 | AC25: 22127832 | AD25: 22127832 | AE25: 22127832 | AF25: 22127832 | AG25: 22127832 | AH25: 22127832 | AI25: 22127832 | AJ25: 22127832 | AK25: 22127832 | AL25: 22127832 | AM25: 22127832 | AN25: 22127832 | AO25: 22127832 | AP25: 22256093 | AQ25: 22256093 | AR25: 22256093 | AS25: 22256093 | AT25: 22256093 | AU25: 22256093 | AV25: 22256093 | AW25: 22256093 | AX25: 22256093 | AY25: 22256093 | AZ25: 22256093 | BA25: 22256093 | BB25: 22256093 | BC25: 21184028 | BD25: 21184028 | BE25: 21184028 | BF25: 21184028 | BG25: 21184028 | BH25: 21184028 | BI25: 21184028 | BJ25: 21184028 | BK25: 21184028 | BL25: 21184028 | BM25: 21184028 | BN25: 21184028 | BO25: 21184028 | BP25: 24770394 | BQ25: 24770394 | BR25: 24770394 | BS25: 24770394 | BT25: 24770394 | BU25: 24770394 | BV25: 24770394 | BW25: 24770394 | BX25: 24770394 | BY25: 24770394 | BZ25: 24770394 | CA25: 24770394 | CB25: 24770394
B26: Total Presupuesto Ley (Subtítulo 31) | C26: =SUM(C8:C25) -> 469564689 | D26: =SUM(D8:D25) -> 469564689 | E26: =SUM(E8:E25) -> 469564689 | F26: =SUM(F8:F25) -> 469564689 | G26: =SUM(G8:G25) -> 469564689 | H26: =SUM(H8:H25) -> 469564689 | I26: =SUM(I8:I25) -> 469564689 | J26: =SUM(J8:J25) -> 469564689 | ... CB26: =SUM(CB8:CB25) -> 465461219
B27: Presupuesto Vigente (Subtítulo 31)
C28: 2021 | P28: 2022 | AC28: 2023 | AP28: 2024 | BC28: 2025 | BP28: 2026
B29: Programa / Entidad | C29: Ene | D29: Feb | E29: Mar | F29: Abr | G29: May | H29: Jun | I29: Jul | J29: Ago | K29: Sep | L29: Oct | M29: Nov | N29: Dic | O29: Total 2021 | P29: Ene | Q29: Feb | R29: Mar | S29: Abr | T29: May | U29: Jun | V29: Jul | W29: Ago | X29: Sep | Y29: Oct | Z29: Nov | AA29: Dic | AB29: Total 2022 | AC29: Ene | AD29: Feb | AE29: Mar | AF29: Abr | AG29: May | AH29: Jun | AI29: Jul | AJ29: Ago | AK29: Sep | AL29: Oct | AM29: Nov | AN29: Dic | AO29: Total 2023 | AP29: Ene | AQ29: Feb | AR29: Mar | AS29: Abr | AT29: May | AU29: Jun | AV29: Jul | AW29: Ago | AX29: Sep | AY29: Oct | AZ29: Nov | BA29: Dic | BB29: Total 2024 | BC29: Ene | BD29: Feb | BE29: Mar | BF29: Abr | BG29: May | BH29: Jun | BI29: Jul | BJ29: Ago | BK29: Sep | BL29: Oct | BM29: Nov | BN29: Dic | BO29: Total 2025 | BP29: Ene | BQ29: Feb | BR29: Mar | BS29: Abr | BT29: May | BU29: Jun | BV29: Jul | BW29: Ago | BX29: Sep | BY29: Oct | BZ29: Nov | CA29: Dic | CB29: Total 2026
B30: Subsecretaría y Programas Centrales | C30: 35339308 | D30: 34095082 | E30: 30900763 | F30: 30000165 | G30: 28431391 | H30: 28482712 | I30: 28482712 | J30: 28482712 | K30: 28482712 | L30: 26544090 | M30: 27401071 | N30: 26558777 | O30: 26558777 | P30: 22751821 | Q30: 14162616 | R30: 14162616 | S30: 14162616 | T30: 14094265 | U30: 14094265 | V30: 13994333 | W30: 14199833 | X30: 14199833 | Y30: 14215569 | Z30: 13257545 | AA30: 11513633 | AB30: 11513633 | AC30: 22326757 | AD30: 12413948 | AE30: 12413948 | AF30: 12169459 | AG30: 11694537 | AH30: 11453537 | AI30: 11207907 | AJ30: 11175513 | AK30: 11175513 | AL30: 11175513 | AM30: 3304471 | AN30: 2258817 | AO30: 2258817 | AP30: 65885700 | AQ30: 65885700 | AR30: 40863396 | AS30: 40863396 | AT30: 40441434 | AU30: 40130157 | AV30: 40110894 | AW30: 35322619 | AX30: 31954975 | AY30: 31882527 | AZ30: 19631668 | BA30: 1858597 | BB30: 1858597 | BC30: 31496963 | BD30: 21938918 | BE30: 17774772 | BF30: 17594772 | BG30: 17439772 | BH30: 16908124 | BI30: 10908124 | BJ30: 10908124 | BK30: 10908124 | BL30: 4377527 | BM30: 4377527 | BN30: 2042428 | BO30: 2042428 | BP30: 15772873 | BQ30: 15772873 | BR30: 15772873 | BS30: 15772873 | BT30: 3763881 | BU30: 3874066 | BV30: 2591940 | BW30: 2591940 | BX30: 2591940 | BY30: 2591940 | BZ30: 2591940 | CA30: 2591940 | CB30: 2591940
B31: Parque Metropolitano (PARQUEMET) | C31: 28313204 | D31: 30808704 | E31: 30808704 | F31: 30808704 | G31: 30808704 | H31: 30808704 | I31: 30808704 | J31: 30808704 | K31: 30808704 | L31: 30808704 | M31: 30808704 | N31: 30377501 | O31: 30377501 | P31: 26279513 | Q31: 26279513 | R31: 26279513 | S31: 26279513 | T31: 26279513 | U31: 26279513 | V31: 26279513 | W31: 26279513 | X31: 26279513 | Y31: 26279513 | Z31: 23402444 | AA31: 23403944 | AB31: 23403944 | AC31: 23921092 | AD31: 23921092 | AE31: 23921092 | AF31: 23921092 | AG31: 23921092 | AH31: 23921092 | AI31: 23998690 | AJ31: 23998690 | AK31: 23998690 | AL31: 23998690 | AM31: 23228459 | AN31: 22242755 | AO31: 22242755 | AP31: 32623118 | AQ31: 32623118 | AR31: 32623118 | AS31: 32623118 | AT31: 32623118 | AU31: 32623118 | AV31: 32623118 | AW31: 32388971 | AX31: 31969868 | AY31: 31969868 | AZ31: 28971461 | BA31: 27933416 | BB31: 27933416 | BC31: 31388552 | BD31: 31388552 | BE31: 31388552 | BF31: 31388552 | BG31: 31388552 | BH31: 31388552 | BI31: 31388552 | BJ31: 31388552 | BK31: 31388552 | BL31: 31049772 | BM31: 31049772 | BN31: 30251792 | BO31: 30251792 | BP31: 32099544 | BQ31: 32099544 | BR31: 32099544 | BS31: 32099544 | BT31: 32099544 | BU31: 32099544 | BV31: 32099544 | BW31: 32099544 | BX31: 32099544 | BY31: 32099544 | BZ31: 32099544 | CA31: 32099544 | CB31: 32099544
B32: SERVIU Arica y Parinacota | C32: 10293909 | D32: 10084346 | E32: 10084346 | F32: 10084346 | G32: 9752272 | H32: 9660314 | I32: 10182785 | J32: 10182785 | K32: 10182785 | L32: 10341874 | M32: 9584765 | N32: 8277587 | O32: 8277587 | P32: 8027524 | Q32: 8983763 | R32: 8983763 | S32: 8983763 | T32: 8983763 | U32: 8983763 | V32: 8402412 | W32: 8402412 | X32: 8402412 | Y32: 8402412 | Z32: 7108557 | AA32: 6707203 | AB32: 6707203 | AC32: 9623696 | AD32: 9643166 | AE32: 9643166 | AF32: 9643166 | AG32: 9643166 | AH32: 9643166 | AI32: 9643166 | AJ32: 6911926 | AK32: 6911926 | AL32: 6911926 | AM32: 5346460 | AN32: 5348904 | AO32: 5348904 | AP32: 7002032 | AQ32: 7002032 | AR32: 7171646 | AS32: 7171646 | AT32: 6646025 | AU32: 6646025 | AV32: 6646025 | AW32: 6646025 | AX32: 6646025 | AY32: 6646025 | AZ32: 6646025 | BA32: 4403210 | BB32: 4403210 | BC32: 7819491 | BD32: 8230260 | BE32: 10011051 | BF32: 10424875 | BG32: 10424875 | BH32: 10424875 | BI32: 10424875 | BJ32: 10424875 | BK32: 10424875 | BL32: 10350160 | BM32: 10350160 | BN32: 9544096 | BO32: 9544096 | BP32: 2323330 | BQ32: 2323330 | BR32: 2323330 | BS32: 2323330 | BT32: 2764330 | BU32: 3209529 | BV32: 3209529 | BW32: 3209529 | BX32: 3209529 | BY32: 3209529 | BZ32: 3209529 | CA32: 3209529 | CB32: 3209529
B33: SERVIU Tarapacá | C33: 10606403 | D33: 10981562 | E33: 10981562 | F33: 10981562 | G33: 9508988 | H33: 10027957 | I33: 9376062 | J33: 9426062 | K33: 9426062 | L33: 9426062 | M33: 8375529 | N33: 5044955 | O33: 5044955 | P33: 4659283 | Q33: 8287823 | R33: 8287823 | S33: 8287823 | T33: 8088031 | U33: 9085876 | V33: 8230787 | W33: 9146287 | X33: 9160548 | Y33: 9229516 | Z33: 8217063 | AA33: 5987379 | AB33: 5987379 | AC33: 9013306 | AD33: 9013306 | AE33: 9013306 | AF33: 9013306 | AG33: 9013306 | AH33: 9013306 | AI33: 9013306 | AJ33: 9013306 | AK33: 9013306 | AL33: 9013306 | AM33: 8829146 | AN33: 6845802 | AO33: 6845802 | AP33: 11846836 | AQ33: 11846836 | AR33: 13988953 | AS33: 13988953 | AT33: 14532621 | AU33: 15344415 | AV33: 15354765 | AW33: 15354765 | AX33: 15735185 | AY33: 15735185 | AZ33: 15739683 | BA33: 8998445 | BB33: 8998445 | BC33: 9956278 | BD33: 9956278 | BE33: 11346159 | BF33: 11346159 | BG33: 11346159 | BH33: 11544512 | BI33: 11544512 | BJ33: 11544512 | BK33: 11544512 | BL33: 11559267 | BM33: 11166267 | BN33: 10095312 | BO33: 10095312 | BP33: 8706346 | BQ33: 8706346 | BR33: 8811028 | BS33: 8811028 | BT33: 9302509 | BU33: 9302509 | BV33: 9302509 | BW33: 9302509 | BX33: 9302509 | BY33: 9302509 | BZ33: 9302509 | CA33: 9302509 | CB33: 9302509
B34: SERVIU Antofagasta | C34: 41468112 | D34: 36245332 | E34: 36663632 | F34: 36698206 | G34: 36732779 | H34: 36266351 | I34: 35758811 | J34: 35758811 | K34: 35758811 | L34: 35859421 | M34: 34878248 | N34: 29916675 | O34: 29916675 | P34: 35548395 | Q34: 41225450 | R34: 41757245 | S34: 41757245 | T34: 41771744 | U34: 41771744 | V34: 41815242 | W34: 40323711 | X34: 32895617 | Y34: 32895617 | Z34: 28719484 | AA34: 26431429 | AB34: 26431429 | AC34: 30263070 | AD34: 31368555 | AE34: 31368555 | AF34: 31368555 | AG34: 31368555 | AH34: 31368555 | AI34: 31368555 | AJ34: 31368555 | AK34: 31368555 | AL34: 31368555 | AM34: 24948049 | AN34: 17979056 | AO34: 17979056 | AP34: 10878804 | AQ34: 10878804 | AR34: 17648371 | AS34: 17845366 | AT34: 17871737 | AU34: 19717940 | AV34: 19717940 | AW34: 19717940 | AX34: 19480742 | AY34: 19480742 | AZ34: 18903775 | BA34: 15465604 | BB34: 15465604 | BC34: 13585888 | BD34: 14789146 | BE34: 15123006 | BF34: 15123006 | BG34: 15123006 | BH34: 15123006 | BI34: 15123006 | BJ34: 15123006 | BK34: 15123006 | BL34: 14248096 | BM34: 14248096 | BN34: 12638840 | BO34: 12638840 | BP34: 13197867 | BQ34: 12480252 | BR34: 12480252 | BS34: 12480252 | BT34: 14209379 | BU34: 14209379 | BV34: 14209379 | BW34: 14209379 | BX34: 14209379 | BY34: 14209379 | BZ34: 14209379 | CA34: 14209379 | CB34: 14209379
B35: SERVIU Atacama | C35: 21129078 | D35: 22568239 | E35: 22568239 | F35: 22774239 | G35: 22814239 | H35: 22814239 | I35: 22814239 | J35: 23235030 | K35: 23235030 | L35: 23235030 | M35: 18518157 | N35: 15731773 | O35: 15731773 | P35: 24875325 | Q35: 31089481 | R35: 27688501 | S35: 27688501 | T35: 27688501 | U35: 27688501 | V35: 25851245 | W35: 25851245 | X35: 25846245 | Y35: 25846245 | Z35: 19964707 | AA35: 18388246 | AB35: 18388246 | AC35: 21315123 | AD35: 21455123 | AE35: 21455123 | AF35: 21455123 | AG35: 22632742 | AH35: 22632742 | AI35: 22688742 | AJ35: 22688742 | AK35: 22688742 | AL35: 22688742 | AM35: 23118118 | AN35: 24322778 | AO35: 24322778 | AP35: 21518444 | AQ35: 21518444 | AR35: 17812520 | AS35: 17812520 | AT35: 17812520 | AU35: 17812520 | AV35: 17812520 | AW35: 17812520 | AX35: 17188321 | AY35: 17188321 | AZ35: 17188321 | BA35: 8570431 | BB35: 8570431 | BC35: 24183340 | BD35: 24535980 | BE35: 24535980 | BF35: 24535980 | BG35: 24535980 | BH35: 23536162 | BI35: 20536162 | BJ35: 20536162 | BK35: 20536162 | BL35: 20589662 | BM35: 20589662 | BN35: 15483238 | BO35: 15483238 | BP35: 9416801 | BQ35: 5916801 | BR35: 5916801 | BS35: 5916801 | BT35: 5916801 | BU35: 9175869 | BV35: 9175869 | BW35: 9175869 | BX35: 9175869 | BY35: 9175869 | BZ35: 9175869 | CA35: 9175869 | CB35: 9175869
B36: SERVIU Coquimbo | C36: 22488189 | D36: 20626973 | E36: 18390489 | F36: 18727330 | G36: 19034787 | H36: 19143744 | I36: 19143744 | J36: 19143744 | K36: 19561023 | L36: 19561023 | M36: 19550402 | N36: 12602298 | O36: 12602298 | P36: 29291800 | Q36: 34195489 | R36: 34195489 | S36: 34195489 | T36: 34245489 | U36: 34245489 | V36: 34245489 | W36: 34245489 | X36: 34062778 | Y36: 33922765 | Z36: 25336066 | AA36: 12697850 | AB36: 12697850 | AC36: 36352142 | AD36: 36370290 | AE36: 36370290 | AF36: 36370290 | AG36: 36370290 | AH36: 36361716 | AI36: 36391716 | AJ36: 36391716 | AK36: 36391716 | AL36: 36391716 | AM36: 35187465 | AN36: 21098315 | AO36: 21098315 | AP36: 38254690 | AQ36: 38254690 | AR36: 38299930 | AS36: 38299930 | AT36: 37058319 | AU36: 31127009 | AV36: 31127009 | AW36: 31127009 | AX36: 30852784 | AY36: 31053963 | AZ36: 27696869 | BA36: 18466482 | BB36: 18466482 | BC36: 27966487 | BD36: 27966487 | BE36: 27966487 | BF36: 27966487 | BG36: 27966487 | BH36: 27958887 | BI36: 27958887 | BJ36: 27958887 | BK36: 27958887 | BL36: 24576889 | BM36: 24265859 | BN36: 18613719 | BO36: 18613719 | BP36: 30615904 | BQ36: 26615904 | BR36: 26615904 | BS36: 26615904 | BT36: 26615904 | BU36: 24556836 | BV36: 24556836 | BW36: 24556836 | BX36: 24556836 | BY36: 24556836 | BZ36: 24556836 | CA36: 24556836 | CB36: 24556836
B37: SERVIU Valparaíso | C37: 62699377 | D37: 59024248 | E37: 60396733 | F37: 61299623 | G37: 61366769 | H37: 63349580 | I37: 63349580 | J37: 63259012 | K37: 62320472 | L37: 55598596 | M37: 55550496 | N37: 41461609 | O37: 41461609 | P37: 43170852 | Q37: 52549754 | R37: 52549754 | S37: 52549754 | T37: 52549754 | U37: 52549754 | V37: 52549754 | W37: 51105545 | X37: 38395230 | Y37: 38337494 | Z37: 36725387 | AA37: 35464491 | AB37: 35464491 | AC37: 40478579 | AD37: 42614131 | AE37: 42614131 | AF37: 42858620 | AG37: 42976422 | AH37: 43076422 | AI37: 43076422 | AJ37: 44994598 | AK37: 44994598 | AL37: 44994598 | AM37: 46728628 | AN37: 45394938 | AO37: 45394938 | AP37: 44262543 | AQ37: 44262543 | AR37: 48159048 | AS37: 48159048 | AT37: 48260848 | AU37: 48260848 | AV37: 48260848 | AW37: 52963275 | AX37: 54672379 | AY37: 54187315 | AZ37: 52019214 | BA37: 37750186 | BB37: 37750186 | BC37: 42009797 | BD37: 52978932 | BE37: 54382452 | BF37: 56213503 | BG37: 56213503 | BH37: 56953012 | BI37: 56953012 | BJ37: 56953012 | BK37: 56953012 | BL37: 57115499 | BM37: 57115499 | BN37: 58076198 | BO37: 58076198 | BP37: 55214851 | BQ37: 55906268 | BR37: 56878200 | BS37: 56878200 | BT37: 59441918 | BU37: 59526130 | BV37: 59526130 | BW37: 59526130 | BX37: 59526130 | BY37: 59526130 | BZ37: 59526130 | CA37: 59526130 | CB37: 59526130
B38: SERVIU Metropolitano | C38: 121451476 | D38: 129722304 | E38: 126707424 | F38: 126938685 | G38: 132323787 | H38: 128389149 | I38: 125484432 | J38: 125153718 | K38: 123524150 | L38: 122714026 | M38: 109967510 | N38: 95169709 | O38: 95169709 | P38: 100098472 | Q38: 121303403 | R38: 121303403 | S38: 120570587 | T38: 120556703 | U38: 119765730 | V38: 120443102 | W38: 118390115 | X38: 118390115 | Y38: 115077894 | Z38: 101166870 | AA38: 94520917 | AB38: 94520917 | AC38: 105488522 | AD38: 108633999 | AE38: 108633999 | AF38: 108633999 | AG38: 108633999 | AH38: 108774999 | AI38: 108897149 | AJ38: 108897149 | AK38: 108897149 | AL38: 108897149 | AM38: 92376604 | AN38: 73346177 | AO38: 73346177 | AP38: 87253576 | AQ38: 87253576 | AR38: 93927139 | AS38: 93927139 | AT38: 94027910 | AU38: 94051385 | AV38: 96196920 | AW38: 101535195 | AX38: 101582093 | AY38: 101562510 | AZ38: 100432485 | BA38: 86087430 | BB38: 86087430 | BC38: 74587862 | BD38: 76570114 | BE38: 76595114 | BF38: 76595114 | BG38: 76595114 | BH38: 80153860 | BI38: 80153860 | BJ38: 80153860 | BK38: 80153860 | BL38: 80236491 | BM38: 80236491 | BN38: 81413921 | BO38: 81413921 | BP38: 90590002 | BQ38: 90590002 | BR38: 90590002 | BS38: 90590002 | BT38: 92970431 | BU38: 92970431 | BV38: 93624803 | BW38: 93624803 | BX38: 93624803 | BY38: 93624803 | BZ38: 93624803 | CA38: 93624803 | CB38: 93624803
B39: SERVIU O'Higgins | C39: 14249499 | D39: 10546312 | E39: 12796312 | F39: 15015842 | G39: 15685395 | H39: 15785389 | I39: 15787719 | J39: 15831289 | K39: 16583631 | L39: 16483631 | M39: 13839062 | N39: 9678227 | O39: 9678227 | P39: 11870060 | Q39: 13917678 | R39: 14847860 | S39: 14847860 | T39: 14847860 | U39: 15300817 | V39: 15300817 | W39: 16297538 | X39: 16297538 | Y39: 16297538 | Z39: 11021810 | AA39: 7220234 | AB39: 7220234 | AC39: 16473882 | AD39: 16473882 | AE39: 16473882 | AF39: 16473882 | AG39: 16473882 | AH39: 16649669 | AI39: 16649669 | AJ39: 16649669 | AK39: 16649669 | AL39: 16649669 | AM39: 16911235 | AN39: 9607053 | AO39: 9607053 | AP39: 16690085 | AQ39: 16690085 | AR39: 16690085 | AS39: 16556501 | AT39: 14974879 | AU39: 14803771 | AV39: 12925518 | AW39: 12925518 | AX39: 11911329 | AY39: 12498650 | AZ39: 12535400 | BA39: 5515173 | BB39: 5515173 | BC39: 17865780 | BD39: 17865780 | BE39: 17865780 | BF39: 17865780 | BG39: 17865780 | BH39: 17865780 | BI39: 17865780 | BJ39: 17865780 | BK39: 17865780 | BL39: 16353696 | BM39: 14508227 | BN39: 9555042 | BO39: 9555042 | BP39: 14196992 | BQ39: 14196992 | BR39: 14196992 | BS39: 14196992 | BT39: 14196992 | BU39: 14707834 | BV39: 15769553 | BW39: 15769553 | BX39: 15769553 | BY39: 15769553 | BZ39: 15769553 | CA39: 15769553 | CB39: 15769553
B40: SERVIU Maule | C40: 38209083 | D40: 41100597 | E40: 41100597 | F40: 39600597 | G40: 39025073 | H40: 37516423 | I40: 37516423 | J40: 37460264 | K40: 38573604 | L40: 37732094 | M40: 32604846 | N40: 24635036 | O40: 24635036 | P40: 41575245 | Q40: 44644684 | R40: 44911603 | S40: 44911603 | T40: 44911603 | U40: 44911603 | V40: 44911603 | W40: 44911603 | X40: 37982134 | Y40: 39377760 | Z40: 27569422 | AA40: 20988334 | AB40: 20988334 | AC40: 34076619 | AD40: 34076619 | AE40: 34076619 | AF40: 34076619 | AG40: 34076619 | AH40: 34076619 | AI40: 34076619 | AJ40: 34076619 | AK40: 34076619 | AL40: 34076619 | AM40: 26897358 | AN40: 16700770 | AO40: 16700770 | AP40: 28318956 | AQ40: 28318956 | AR40: 28318956 | AS40: 28318956 | AT40: 28007698 | AU40: 28007698 | AV40: 26950239 | AW40: 26950239 | AX40: 26321544 | AY40: 26321544 | AZ40: 26138228 | BA40: 20053849 | BB40: 20053849 | BC40: 30628977 | BD40: 30628977 | BE40: 30628977 | BF40: 30628977 | BG40: 30628977 | BH40: 30628977 | BI40: 27628977 | BJ40: 27628977 | BK40: 27628977 | BL40: 24859588 | BM40: 24859588 | BN40: 17628176 | BO40: 17628176 | BP40: 25030745 | BQ40: 25030745 | BR40: 25030745 | BS40: 25030745 | BT40: 25030745 | BU40: 24845745 | BV40: 24845745 | BW40: 24845745 | BX40: 24845745 | BY40: 24845745 | BZ40: 24845745 | CA40: 24845745 | CB40: 24845745
B41: SERVIU Ñuble | C41: 26096695 | D41: 30290020 | E41: 30290020 | F41: 29448401 | G41: 31148401 | H41: 30456420 | I41: 30468420 | J41: 30456420 | K41: 30456420 | L41: 30456420 | M41: 27581404 | N41: 24250403 | O41: 24250403 | P41: 36920320 | Q41: 39555349 | R41: 39555349 | S41: 40193554 | T41: 40193554 | U41: 39518691 | V41: 37297808 | W41: 37247808 | X41: 31996367 | Y41: 31996367 | Z41: 21418055 | AA41: 20235644 | AB41: 20235644 | AC41: 23700733 | AD41: 23700733 | AE41: 23700733 | AF41: 24725452 | AG41: 24923952 | AH41: 24923952 | AI41: 24923952 | AJ41: 24923952 | AK41: 24923952 | AL41: 24923952 | AM41: 25399952 | AN41: 23943054 | AO41: 23943054 | AP41: 23113535 | AQ41: 23113535 | AR41: 23113535 | AS41: 23113535 | AT41: 23113535 | AU41: 25829486 | AV41: 26688903 | AW41: 26688903 | AX41: 25705903 | AY41: 25705903 | AZ41: 25705903 | BA41: 19120001 | BB41: 19120001 | BC41: 22079448 | BD41: 22079448 | BE41: 22079448 | BF41: 22079448 | BG41: 22234448 | BH41: 22234448 | BI41: 22234448 | BJ41: 22234448 | BK41: 22234448 | BL41: 21553827 | BM41: 21553827 | BN41: 21538828 | BO41: 21538828 | BP41: 24086756 | BQ41: 21586756 | BR41: 21586756 | BS41: 21586756 | BT41: 21586756 | BU41: 21586756 | BV41: 20525037 | BW41: 20525037 | BX41: 20525037 | BY41: 20525037 | BZ41: 20525037 | CA41: 20525037 | CB41: 20525037
... B47: SERVIU Magallanes | C47: 11914112 | D47: 11776677 | E47: 11776677 | F47: 11777475 | G47: 11777475 | H47: 13201459 | I47: 13201459 | J47: 13201459 | K47: 13201459 | L47: 14214829 | M47: 12939967 | N47: 10741343 | O47: 10741343 | P47: 14902342 | Q47: 19316051 | R47: 19316051 | S47: 19316051 | T47: 19244386 | U47: 19174386 | V47: 16328330 | W47: 16328330 | X47: 16328330 | Y47: 16328330 | Z47: 12234667 | AA47: 9450641 | AB47: 9450641 | AC47: 22127832 | AD47: 22959758 | AE47: 22959758 | AF47: 22959758 | AG47: 24837247 | AH47: 24837247 | AI47: 24837247 | AJ47: 24837247 | AK47: 24837247 | AL47: 24837247 | AM47: 24074302 | AN47: 13086048 | AO47: 13086048 | AP47: 22256093 | AQ47: 22256093 | AR47: 22256093 | AS47: 22256093 | AT47: 22356143 | AU47: 23540375 | AV47: 23790875 | AW47: 23790875 | AX47: 22870441 | AY47: 22870441 | AZ47: 20253560 | BA47: 17985481 | BB47: 17985481 | BC47: 21184028 | BD47: 21881248 | BE47: 21881248 | BF47: 21881248 | BG47: 21881248 | BH47: 14331165 | BI47: 14331165 | BJ47: 14331165 | BK47: 14331165 | BL47: 14275594 | BM47: 14275594 | BN47: 14465044 | BO47: 14465044 | BP47: 24770394 | BQ47: 24770394 | BR47: 24770394 | BS47: 24770394 | BT47: 25550699 | BU47: 25550699 | BV47: 26178453 | BW47: 26178453 | BX47: 26178453 | BY47: 26178453 | BZ47: 26178453 | CA47: 26178453 | CB47: 26178453
B48: Total Presupuesto Vigente (Subtítulo 31) | C48: =SUM(C30:C47) -> 600298724 | D48: =SUM(D30:D47) -> 607271724 | E48: =SUM(E30:E47) -> 609033724 | F48: =SUM(F30:F47) -> 609033724 | G48: =SUM(G30:G47) -> 608005946 | H48: =SUM(H30:H47) -> 608005946 | I48: =SUM(I30:I47) -> 608005946 | J48: =SUM(J30:J47) -> 608005946 | ... CB48: =SUM(CB30:CB47) -> 466611123
B49: Ejecución Acumulada (Subtítulo 31)
C50: 2021 | P50: 2022 | AC50: 2023 | AP50: 2024 | BC50: 2025 | BP50: 2026
B51: Programa / Entidad | C51: Ene | D51: Feb | E51: Mar | F51: Abr | G51: May | H51: Jun | I51: Jul | J51: Ago | K51: Sep | L51: Oct | M51: Nov | N51: Dic | O51: Total 2021 | P51: Ene | Q51: Feb | R51: Mar | S51: Abr | T51: May | U51: Jun | V51: Jul | W51: Ago | X51: Sep | Y51: Oct | Z51: Nov | AA51: Dic | AB51: Total 2022 | AC51: Ene | AD51: Feb | AE51: Mar | AF51: Abr | AG51: May | AH51: Jun | AI51: Jul | AJ51: Ago | AK51: Sep | AL51: Oct | AM51: Nov | AN51: Dic | AO51: Total 2023 | AP51: Ene | AQ51: Feb | AR51: Mar | AS51: Abr | AT51: May | AU51: Jun | AV51: Jul | AW51: Ago | AX51: Sep | AY51: Oct | AZ51: Nov | BA51: Dic | BB51: Total 2024 | BC51: Ene | BD51: Feb | BE51: Mar | BF51: Abr | BG51: May | BH51: Jun | BI51: Jul | BJ51: Ago | BK51: Sep | BL51: Oct | BM51: Nov | BN51: Dic | BO51: Total 2025 | BP51: Ene | BQ51: Feb | BR51: Mar | BS51: Abr | BT51: May | BU51: Jun | BV51: Jul | BW51: Ago | BX51: Sep | BY51: Oct | BZ51: Nov | CA51: Dic | CB51: Total 2026
B52: Subsecretaría y Programas Centrales | C52: 0 | D52: 0 | E52: 7994378 | F52: 10551196 | G52: 12133475 | H52: 13900836 | I52: 15529648 | J52: 18642687 | K52: 20263881 | L52: 21873659 | M52: 22125896 | N52: 26495705 | O52: 26495705 | P52: 0 | Q52: 2975466 | R52: 6036009 | S52: 7664334 | T52: 7756822 | U52: 10134446 | V52: 10176894 | W52: 10261274 | X52: 10365403 | Y52: 10441208 | Z52: 10657419 | AA52: 11364777 | AB52: 11364777 | AC52: 0 | AD52: 0 | AE52: 114234 | AF52: 147709 | AG52: 159046 | AH52: 295667 | AI52: 389978 | AJ52: 1558507 | AK52: 1630507 | AL52: 1760374 | AM52: 1835548 | AN52: 2230114 | AO52: 2230114 | AP52: 0 | AQ52: 0 | AR52: 32400 | AS52: 125776 | AT52: 162026 | AU52: 240908 | AV52: 382321 | AW52: 420077 | AX52: 584298 | AY52: 593996 | AZ52: 846439 | BA52: 1765056 | BB52: 1765056 | BC52: 0 | BD52: 61271 | BE52: 185603 | BF52: 372200 | BG52: 416377 | BH52: 504460 | BI52: 639487 | BJ52: 752002 | BK52: 889001 | BL52: 1218727 | BM52: 1379310 | BN52: 1735258 | BO52: 1735258 | BP52: 0 | BQ52: 0 | BR52: 50564 | BS52: 218816 | BT52: 272078 | BU52: 533936 | BV52: 570336 | BW52: 570336 | BX52: 570336 | BY52: 570336 | BZ52: 570336 | CA52: 570336 | CB52: 570336
B53: Parque Metropolitano (PARQUEMET) | C53: 0 | D53: 1171112 | E53: 3667892 | F53: 5314023 | G53: 8604717 | H53: 11006803 | I53: 13224909 | J53: 15113085 | K53: 17014277 | L53: 19236566 | M53: 22205739 | N53: 30104947 | O53: 30104947 | P53: 0 | Q53: 0 | R53: 2366484 | S53: 5158610 | T53: 7079239 | U53: 8514428 | V53: 9937938 | W53: 11990153 | X53: 13116671 | Y53: 15670225 | Z53: 17891169 | AA53: 23304021 | AB53: 23304021 | AC53: 0 | AD53: 0 | AE53: 1192161 | AF53: 4184056 | AG53: 6014243 | AH53: 7137880 | AI53: 8238265 | AJ53: 10234742 | AK53: 11434458 | AL53: 13391619 | AM53: 15333330 | AN53: 22175040 | AO53: 22175040 | AP53: 0 | AQ53: 0 | AR53: 1896344 | AS53: 5284077 | AT53: 6718012 | AU53: 8302842 | AV53: 10078805 | AW53: 11841574 | AX53: 13163862 | AY53: 14887407 | AZ53: 17657413 | BA53: 27847917 | BB53: 27847917 | BC53: 0 | BD53: 635911 | BE53: 3406026 | BF53: 5878280 | BG53: 8481842 | BH53: 10476165 | BI53: 14140348 | BJ53: 17057587 | BK53: 18562941 | BL53: 23005910 | BM53: 25814003 | BN53: 30105231 | BO53: 30105231 | BP53: 0 | BQ53: 583993 | BR53: 2544487 | BS53: 5629990 | BT53: 7573202 | BU53: 9508871 | BV53: 13263584 | BW53: 13263584 | BX53: 13263584 | BY53: 13263584 | BZ53: 13263584 | CA53: 13263584 | CB53: 13263584
B54: SERVIU Arica y Parinacota | C54: 0 | D54: 648709 | E54: 1904633 | F54: 2846329 | G54: 3270884 | H54: 4160146 | I54: 4815337 | J54: 5273290 | K54: 5549560 | L54: 6236240 | M54: 6513380 | N54: 7993792 | O54: 7993792 | P54: 0 | Q54: 632251 | R54: 1548551 | S54: 2026879 | T54: 2399749 | U54: 2698831 | V54: 3287207 | W54: 3824985 | X54: 4204982 | Y54: 4737024 | Z54: 5184329 | AA54: 6402442 | AB54: 6402442 | AC54: 0 | AD54: 88825 | AE54: 1327201 | AF54: 1567274 | AG54: 1930397 | AH54: 2366313 | AI54: 2511593 | AJ54: 2832413 | AK54: 3220149 | AL54: 3379453 | AM54: 4297388 | AN54: 5234499 | AO54: 5234499 | AP54: 0 | AQ54: 79682 | AR54: 767871 | AS54: 942590 | AT54: 1175782 | AU54: 1342359 | AV54: 1467982 | AW54: 1523593 | AX54: 1893335 | AY54: 2491130 | AZ54: 3050438 | BA54: 4379123 | BB54: 4379123 | BC54: 0 | BD54: 1989837 | BE54: 3034140 | BF54: 5235453 | BG54: 5730916 | BH54: 6001353 | BI54: 6911060 | BJ54: 7598644 | BK54: 7724711 | BL54: 8136264 | BM54: 8334765 | BN54: 9523479 | BO54: 9523479 | BP54: 0 | BQ54: 6644 | BR54: 965714 | BS54: 1538483 | BT54: 1829965 | BU54: 1854335 | BV54: 1907383 | BW54: 1907383 | BX54: 1907383 | BY54: 1907383 | BZ54: 1907383 | CA54: 1907383 | CB54: 1907383
B55: SERVIU Tarapacá | C55: 0 | D55: 0 | E55: 497211 | F55: 740154 | G55: 1022513 | H55: 1350754 | I55: 1501503 | J55: 2076982 | K55: 2565253 | L55: 3107965 | M55: 3314790 | N55: 4616710 | O55: 4616710 | P55: 0 | Q55: 126651 | R55: 635432 | S55: 988815 | T55: 1291329 | U55: 1736798 | V55: 2011354 | W55: 2365717 | X55: 2608012 | Y55: 3139535 | Z55: 3632940 | AA55: 4718148 | AB55: 4718148 | AC55: 0 | AD55: 496962 | AE55: 1030597 | AF55: 1804022 | AG55: 2547494 | AH55: 3426246 | AI55: 3822719 | AJ55: 3998759 | AK55: 4365688 | AL55: 4761521 | AM55: 5296665 | AN55: 6454032 | AO55: 6454032 | AP55: 0 | AQ55: 278257 | AR55: 1460212 | AS55: 2026544 | AT55: 3382381 | AU55: 4039571 | AV55: 4959096 | AW55: 5548527 | AX55: 5996201 | AY55: 6527522 | AZ55: 6840220 | BA55: 8453266 | BB55: 8453266 | BC55: 0 | BD55: 0 | BE55: 832107 | BF55: 2407636 | BG55: 3152766 | BH55: 4520387 | BI55: 5101149 | BJ55: 5717562 | BK55: 6966959 | BL55: 7736069 | BM55: 8038749 | BN55: 9624301 | BO55: 9624301 | BP55: 0 | BQ55: 541326 | BR55: 1114843 | BS55: 1568397 | BT55: 1765260 | BU55: 2038550 | BV55: 2625513 | BW55: 2625513 | BX55: 2625513 | BY55: 2625513 | BZ55: 2625513 | CA55: 2625513 | CB55: 2625513
B56: SERVIU Antofagasta | C56: 0 | D56: 0 | E56: 2499943 | F56: 4318568 | G56: 6254394 | H56: 7571113 | I56: 9318475 | J56: 10622011 | K56: 13964985 | L56: 17055081 | M56: 20311131 | N56: 28537218 | O56: 28537218 | P56: 0 | Q56: 1414267 | R56: 4639959 | S56: 7376742 | T56: 10550320 | U56: 12910552 | V56: 15794687 | W56: 17723139 | X56: 20220438 | Y56: 21146568 | Z56: 22839279 | AA56: 25969095 | AB56: 25969095 | AC56: 0 | AD56: 0 | AE56: 0 | AF56: 435496 | AG56: 2956834 | AH56: 5460342 | AI56: 6519105 | AJ56: 7562017 | AK56: 9330345 | AL56: 9842292 | AM56: 11078284 | AN56: 15477344 | AO56: 15477344 | AP56: 0 | AQ56: 505204 | AR56: 1560549 | AS56: 4524550 | AT56: 5126981 | AU56: 6324528 | AV56: 7622316 | AW56: 9015359 | AX56: 9506130 | AY56: 10219951 | AZ56: 10681549 | BA56: 14221677 | BB56: 14221677 | BC56: 0 | BD56: 15654 | BE56: 1221981 | BF56: 2116938 | BG56: 3506670 | BH56: 4366354 | BI56: 5588134 | BJ56: 6509294 | BK56: 7740606 | BL56: 8339500 | BM56: 9479079 | BN56: 12476694 | BO56: 12476694 | BP56: 0 | BQ56: 0 | BR56: 2568599 | BS56: 3613313 | BT56: 4523333 | BU56: 5273951 | BV56: 5934564 | BW56: 5934564 | BX56: 5934564 | BY56: 5934564 | BZ56: 5934564 | CA56: 5934564 | CB56: 5934564
B57: SERVIU Atacama | C57: 0 | D57: 87292 | E57: 793272 | F57: 1556347 | G57: 2282348 | H57: 2893680 | I57: 3632116 | J57: 4938968 | K57: 6587924 | L57: 8294837 | M57: 10043378 | N57: 15656119 | O57: 15656119 | P57: 0 | Q57: 86461 | R57: 1016727 | S57: 1570665 | T57: 2318130 | U57: 5012601 | V57: 5637478 | W57: 6210424 | X57: 7549082 | Y57: 8799496 | Z57: 10623552 | AA57: 17848435 | AB57: 17848435 | AC57: 0 | AD57: 0 | AE57: 2793263 | AF57: 4637349 | AG57: 6800955 | AH57: 9305411 | AI57: 11608286 | AJ57: 13058895 | AK57: 15088967 | AL57: 15598733 | AM57: 17616851 | AN57: 22912881 | AO57: 22912881 | AP57: 0 | AQ57: 91311 | AR57: 1543145 | AS57: 1812150 | AT57: 2866970 | AU57: 3198071 | AV57: 3550823 | AW57: 3879032 | AX57: 4224296 | AY57: 4965161 | AZ57: 5497696 | BA57: 8070989 | BB57: 8070989 | BC57: 0 | BD57: 0 | BE57: 782785 | BF57: 3521623 | BG57: 5392411 | BH57: 7003168 | BI57: 8794735 | BJ57: 9187072 | BK57: 9707571 | BL57: 11078757 | BM57: 11801848 | BN57: 13299232 | BO57: 13299232 | BP57: 0 | BQ57: 0 | BR57: 671571 | BS57: 947529 | BT57: 1212531 | BU57: 3074751 | BV57: 4493515 | BW57: 4493515 | BX57: 4493515 | BY57: 4493515 | BZ57: 4493515 | CA57: 4493515 | CB57: 4493515
B58: SERVIU Coquimbo | C58: 0 | D58: 145074 | E58: 1058879 | F58: 2039763 | G58: 2953907 | H58: 3778375 | I58: 4390330 | J58: 4988153 | K58: 6096186 | L58: 7319317 | M58: 8210062 | N58: 11722421 | O58: 11722421 | P58: 0 | Q58: 0 | R58: 2242990 | S58: 2913694 | T58: 3475710 | U58: 4563044 | V58: 5503722 | W58: 5982265 | X58: 7324275 | Y58: 8473012 | Z58: 9570289 | AA58: 12299225 | AB58: 12299225 | AC58: 0 | AD58: 184861 | AE58: 2550024 | AF58: 3335427 | AG58: 3954033 | AH58: 5137967 | AI58: 6515902 | AJ58: 9869211 | AK58: 11282350 | AL58: 14137020 | AM58: 16461275 | AN58: 20087982 | AO58: 20087982 | AP58: 0 | AQ58: 0 | AR58: 2563142 | AS58: 4937234 | AT58: 6455476 | AU58: 7874182 | AV58: 9537233 | AW58: 10627246 | AX58: 11749652 | AY58: 12736164 | AZ58: 14354886 | BA58: 18304746 | BB58: 18304746 | BC58: 0 | BD58: 0 | BE58: 537044 | BF58: 4624082 | BG58: 6663050 | BH58: 7372366 | BI58: 8896020 | BJ58: 10874834 | BK58: 11736753 | BL58: 13073544 | BM58: 14605811 | BN58: 17113896 | BO58: 17113896 | BP58: 0 | BQ58: 1214485 | BR58: 1998311 | BS58: 3214367 | BT58: 6370940 | BU58: 7328213 | BV58: 8973928 | BW58: 8973928 | BX58: 8973928 | BY58: 8973928 | BZ58: 8973928 | CA58: 8973928 | CB58: 8973928
B59: SERVIU Valparaíso | C59: 0 | D59: 2423327 | E59: 6782736 | F59: 15251668 | G59: 16748720 | H59: 18415304 | I59: 21339663 | J59: 23380013 | K59: 25383530 | L59: 31015191 | M59: 34807108 | N59: 41047311 | O59: 41047311 | P59: 0 | Q59: 1954310 | R59: 5437246 | S59: 9074366 | T59: 11564328 | U59: 13457755 | V59: 16052872 | W59: 18591175 | X59: 21394133 | Y59: 24741056 | Z59: 27312162 | AA59: 34255389 | AB59: 34255389 | AC59: 0 | AD59: 1073661 | AE59: 6482752 | AF59: 11046429 | AG59: 14774156 | AH59: 17141463 | AI59: 19176471 | AJ59: 22477672 | AK59: 24576750 | AL59: 28005939 | AM59: 30917189 | AN59: 43303337 | AO59: 43303337 | AP59: 0 | AQ59: 817026 | AR59: 7211294 | AS59: 10269338 | AT59: 13142557 | AU59: 16019024 | AV59: 17552175 | AW59: 20571069 | AX59: 23134677 | AY59: 25245587 | AZ59: 28348834 | BA59: 35664606 | BB59: 35664606 | BC59: 0 | BD59: 0 | BE59: 6894377 | BF59: 14671995 | BG59: 18775808 | BH59: 23907660 | BI59: 29396833 | BJ59: 33730948 | BK59: 37737801 | BL59: 42029251 | BM59: 45580303 | BN59: 55696292 | BO59: 55696292 | BP59: 0 | BQ59: 575811 | BR59: 5659243 | BS59: 9197930 | BT59: 13083654 | BU59: 16463966 | BV59: 18166057 | BW59: 18166057 | BX59: 18166057 | BY59: 18166057 | BZ59: 18166057 | CA59: 18166057 | CB59: 18166057
B60: SERVIU Metropolitano | C60: 0 | D60: 0 | E60: 9171371 | F60: 20167605 | G60: 26768507 | H60: 34468225 | I60: 41087061 | J60: 49548059 | K60: 57425159 | L60: 66050722 | M60: 74504640 | N60: 93248356 | O60: 93248356 | P60: 0 | Q60: 20 | R60: 7814847 | S60: 14488934 | T60: 20550387 | U60: 25905467 | V60: 31180285 | W60: 35454583 | X60: 43316522 | Y60: 50229978 | Z60: 60493790 | AA60: 91204741 | AB60: 91204741 | AC60: 0 | AD60: 0 | AE60: 7743578 | AF60: 12770777 | AG60: 22600345 | AH60: 29409607 | AI60: 34855974 | AJ60: 38558182 | AK60: 39905006 | AL60: 43685225 | AM60: 48485518 | AN60: 69805257 | AO60: 69805257 | AP60: 0 | AQ60: 0 | AR60: 5802062 | AS60: 26606325 | AT60: 37830174 | AU60: 47455810 | AV60: 52375257 | AW60: 56860092 | AX60: 60181952 | AY60: 63436734 | AZ60: 69842295 | BA60: 84329419 | BB60: 84329419 | BC60: 0 | BD60: 0 | BE60: 12132484 | BF60: 17263226 | BG60: 25244869 | BH60: 31340839 | BI60: 39240658 | BJ60: 41627865 | BK60: 45007011 | BL60: 56559786 | BM60: 61325912 | BN60: 79219999 | BO60: 79219999 | BP60: 0 | BQ60: 8700230 | BR60: 16017382 | BS60: 19225220 | BT60: 23499085 | BU60: 28587732 | BV60: 32956485 | BW60: 32956485 | BX60: 32956485 | BY60: 32956485 | BZ60: 32956485 | CA60: 32956485 | CB60: 32956485
B61: SERVIU O'Higgins | C61: 1000 | D61: 99098 | E61: 415702 | F61: 1181604 | G61: 2061999 | H61: 2518382 | I61: 3449968 | J61: 3878692 | K61: 6374836 | L61: 6949560 | M61: 7815000 | N61: 9473969 | O61: 9473969 | P61: 0 | Q61: 577978 | R61: 1236819 | S61: 1977797 | T61: 2357232 | U61: 2969508 | V61: 3318916 | W61: 3995498 | X61: 4545865 | Y61: 4876192 | Z61: 5746022 | AA61: 6861203 | AB61: 6861203 | AC61: 0 | AD61: 492390 | AE61: 1774370 | AF61: 2626789 | AG61: 3586562 | AH61: 4109229 | AI61: 4791193 | AJ61: 4985805 | AK61: 5467268 | AL61: 5861823 | AM61: 6425422 | AN61: 8992823 | AO61: 8992823 | AP61: 0 | AQ61: 276844 | AR61: 1164884 | AS61: 1445217 | AT61: 1635928 | AU61: 1791794 | AV61: 1875060 | AW61: 2301121 | AX61: 2703028 | AY61: 3355875 | AZ61: 4056976 | BA61: 5186229 | BB61: 5186229 | BC61: 0 | BD61: 454298 | BE61: 1364864 | BF61: 2152908 | BG61: 3067456 | BH61: 3591831 | BI61: 4024502 | BJ61: 4758598 | BK61: 6018242 | BL61: 6553969 | BM61: 7179799 | BN61: 8275294 | BO61: 8275294 | BP61: 204442 | BQ61: 1444145 | BR61: 3179839 | BS61: 3866613 | BT61: 4135039 | BU61: 4729235 | BV61: 5630349 | BW61: 5630349 | BX61: 5630349 | BY61: 5630349 | BZ61: 5630349 | CA61: 5630349 | CB61: 5630349
B62: SERVIU Maule | C62: 230063 | D62: 2679421 | E62: 4420753 | F62: 5625485 | G62: 8547030 | H62: 10394218 | I62: 12259307 | J62: 13792087 | K62: 14859039 | L62: 15945761 | M62: 16872512 | N62: 21863438 | O62: 21863438 | P62: 0 | Q62: 922651 | R62: 2516611 | S62: 4242046 | T62: 5842634 | U62: 7701318 | V62: 8879148 | W62: 10547577 | X62: 11329010 | Y62: 12221517 | Z62: 14355204 | AA62: 17959345 | AB62: 17959345 | AC62: 0 | AD62: 139737 | AE62: 1933892 | AF62: 2566443 | AG62: 4806556 | AH62: 5940484 | AI62: 6960232 | AJ62: 8468944 | AK62: 9342327 | AL62: 10407121 | AM62: 10942387 | AN62: 14585744 | AO62: 14585744 | AP62: 0 | AQ62: 754193 | AR62: 3484262 | AS62: 4899524 | AT62: 6887240 | AU62: 7953500 | AV62: 9188042 | AW62: 10190994 | AX62: 15388503 | AY62: 17047081 | AZ62: 18216853 | BA62: 19302172 | BB62: 19302172 | BC62: 0 | BD62: 2936145 | BE62: 3840604 | BF62: 5205000 | BG62: 7087387 | BH62: 8761945 | BI62: 9648079 | BJ62: 11529540 | BK62: 12156420 | BL62: 13138327 | BM62: 14104360 | BN62: 16237313 | BO62: 16237313 | BP62: 0 | BQ62: 977735 | BR62: 1877551 | BS62: 2945279 | BT62: 3540409 | BU62: 4135011 | BV62: 4717171 | BW62: 4717171 | BX62: 4717171 | BY62: 4717171 | BZ62: 4717171 | CA62: 4717171 | CB62: 4717171
B63: SERVIU Ñuble | C63: 0 | D63: 1238171 | E63: 2085725 | F63: 3009570 | G63: 4344721 | H63: 6181413 | I63: 7481590 | J63: 8923223 | K63: 9969186 | L63: 12042447 | M63: 14316036 | N63: 21083177 | O63: 21083177 | P63: 0 | Q63: 6363 | R63: 1963636 | S63: 3158663 | T63: 4714179 | U63: 6147258 | V63: 8342380 | W63: 9944276 | X63: 11786997 | Y63: 13492671 | Z63: 15132338 | AA63: 19561462 | AB63: 19561462 | AC63: 0 | AD63: 1480106 | AE63: 5251198 | AF63: 8060203 | AG63: 9695784 | AH63: 11307082 | AI63: 12618163 | AJ63: 14357900 | AK63: 16141680 | AL63: 17787508 | AM63: 19945314 | AN63: 22005775 | AO63: 22005775 | AP63: 0 | AQ63: 825335 | AR63: 3513803 | AS63: 4931246 | AT63: 7350891 | AU63: 8756033 | AV63: 9821988 | AW63: 11470086 | AX63: 12805474 | AY63: 14287326 | AZ63: 15540449 | BA63: 17950052 | BB63: 17950052 | BC63: 0 | BD63: 148253 | BE63: 3292884 | BF63: 4257053 | BG63: 7062054 | BH63: 9495200 | BI63: 11760026 | BJ63: 12709417 | BK63: 14311689 | BL63: 16551275 | BM63: 17380835 | BN63: 21033526 | BO63: 21033526 | BP63: 0 | BQ63: 3262841 | BR63: 4333743 | BS63: 5206806 | BT63: 5938083 | BU63: 6532085 | BV63: 6546839 | BW63: 6546839 | BX63: 6546839 | BY63: 6546839 | BZ63: 6546839 | CA63: 6546839 | CB63: 6546839
... B69: SERVIU Magallanes | C69: 0 | D69: 780964 | E69: 2329121 | F69: 2781402 | G69: 3961113 | H69: 4999318 | I69: 5729292 | J69: 6450230 | K69: 7246756 | L69: 8083876 | M69: 9157163 | N69: 10738590 | O69: 10738590 | P69: 0 | Q69: 531868 | R69: 979900 | S69: 1668995 | T69: 2067161 | U69: 2495250 | V69: 2833549 | W69: 3310447 | X69: 4180470 | Y69: 5410940 | Z69: 6546938 | AA69: 9221232 | AB69: 9221232 | AC69: 0 | AD69: 242363 | AE69: 2468853 | AF69: 3552694 | AG69: 4986547 | AH69: 6240668 | AI69: 7483453 | AJ69: 8011980 | AK69: 9004344 | AL69: 10464944 | AM69: 11221564 | AN69: 12894724 | AO69: 12894724 | AP69: 0 | AQ69: 0 | AR69: 3256958 | AS69: 5254963 | AT69: 7343946 | AU69: 8984252 | AV69: 11604334 | AW69: 12582118 | AX69: 13958919 | AY69: 15014924 | AZ69: 16146052 | BA69: 17938143 | BB69: 17938143 | BC69: 0 | BD69: 656162 | BE69: 1462430 | BF69: 2617816 | BG69: 3672318 | BH69: 4549506 | BI69: 5755024 | BJ69: 6518863 | BK69: 8081693 | BL69: 9963180 | BM69: 11073504 | BN69: 14403339 | BO69: 14403339 | BP69: 0 | BQ69: 2033211 | BR69: 4073385 | BS69: 5482094 | BT69: 6965527 | BU69: 10120647 | BV69: 11843248 | BW69: 11843248 | BX69: 11843248 | BY69: 11843248 | BZ69: 11843248 | CA69: 11843248 | CB69: 11843248
B70: Total Ejecución Acumulada (Subtítulo 31) | C70: =SUM(C52:C69) -> 1227550 | D70: =SUM(D52:D69) -> 23205600 | E70: =SUM(E52:E69) -> 70585804 | F70: =SUM(F52:F69) -> 116596570 | G70: =SUM(G52:G69) -> 147285990 | H70: =SUM(H52:H69) -> 178003787 | I70: =SUM(I52:I69) -> 208095844 | J70: =SUM(J52:J69) -> 240830600 | ... CB70: =SUM(CB52:CB69) -> 155690398
B73: SUBTÍTULO 29 – ADQUISICIÓN DE ACTIVOS NO FINANCIEROS
B74: Presupuesto Ley (Subtítulo 29)
C75: 2021 | P75: 2022 | AC75: 2023 | AP75: 2024 | BC75: 2025 | BP75: 2026
B76: Programa / Entidad | C76: Ene | D76: Feb | E76: Mar | F76: Abr | G76: May | H76: Jun | I76: Jul | J76: Ago | K76: Sep | L76: Oct | M76: Nov | N76: Dic | O76: Total 2021 | P76: Ene | Q76: Feb | R76: Mar | S76: Abr | T76: May | U76: Jun | V76: Jul | W76: Ago | X76: Sep | Y76: Oct | Z76: Nov | AA76: Dic | AB76: Total 2022 | AC76: Ene | AD76: Feb | AE76: Mar | AF76: Abr | AG76: May | AH76: Jun | AI76: Jul | AJ76: Ago | AK76: Sep | AL76: Oct | AM76: Nov | AN76: Dic | AO76: Total 2023 | AP76: Ene | AQ76: Feb | AR76: Mar | AS76: Abr | AT76: May | AU76: Jun | AV76: Jul | AW76: Ago | AX76: Sep | AY76: Oct | AZ76: Nov | BA76: Dic | BB76: Total 2024 | BC76: Ene | BD76: Feb | BE76: Mar | BF76: Abr | BG76: May | BH76: Jun | BI76: Jul | BJ76: Ago | BK76: Sep | BL76: Oct | BM76: Nov | BN76: Dic | BO76: Total 2025 | BP76: Ene | BQ76: Feb | BR76: Mar | BS76: Abr | BT76: May | BU76: Jun | BV76: Jul | BW76: Ago | BX76: Sep | BY76: Oct | BZ76: Nov | CA76: Dic | CB76: Total 2026
B77: Subsecretaría y Programas Centrales | C77: 3879109 | D77: 3879109 | E77: 3879109 | F77: 3879109 | G77: 3879109 | H77: 3879109 | I77: 3879109 | J77: 3879109 | K77: 3879109 | L77: 3879109 | M77: 3879109 | N77: 3879109 | O77: 3879109 | P77: 3677484 | Q77: 3677484 | R77: 3677484 | S77: 3677484 | T77: 3677484 | U77: 3677484 | V77: 3677484 | W77: 3677484 | X77: 3677484 | Y77: 3677484 | Z77: 3677484 | AA77: 3677484 | AB77: 3677484 | AC77: 4127526 | AD77: 4127526 | AE77: 4127526 | AF77: 4127526 | AG77: 4127526 | AH77: 4127526 | AI77: 4127526 | AJ77: 4127526 | AK77: 4127526 | AL77: 4127526 | AM77: 4127526 | AN77: 4127526 | AO77: 4127526 | AP77: 30674754 | AQ77: 30674754 | AR77: 30674754 | AS77: 30674754 | AT77: 30674754 | AU77: 30674754 | AV77: 30674754 | AW77: 30674754 | AX77: 30674754 | AY77: 30674754 | AZ77: 30674754 | BA77: 30674754 | BB77: 30674754 | BC77: 4669285 | BD77: 4669285 | BE77: 4669285 | BF77: 4669285 | BG77: 4669285 | BH77: 4669285 | BI77: 4669285 | BJ77: 4669285 | BK77: 4669285 | BL77: 4669285 | BM77: 4669285 | BN77: 4669285 | BO77: 4669285 | BP77: 4182704 | BQ77: 4182704 | BR77: 4182704 | BS77: 4182704 | BT77: 4182704 | BU77: 4182704 | BV77: 4182704 | BW77: 4182704 | BX77: 4182704 | BY77: 4182704 | BZ77: 4182704 | CA77: 4182704 | CB77: 4182704
B78: Parque Metropolitano (PARQUEMET) | C78: 71111 | D78: 71111 | E78: 71111 | F78: 71111 | G78: 71111 | H78: 71111 | I78: 71111 | J78: 71111 | K78: 71111 | L78: 71111 | M78: 71111 | N78: 71111 | O78: 71111 | P78: 33328 | Q78: 33328 | R78: 33328 | S78: 33328 | T78: 33328 | U78: 33328 | V78: 33328 | W78: 33328 | X78: 33328 | Y78: 33328 | Z78: 33328 | AA78: 33328 | AB78: 33328 | AC78: 0 | AD78: 0 | AE78: 0 | AF78: 0 | AG78: 0 | AH78: 0 | AI78: 0 | AJ78: 0 | AK78: 0 | AL78: 0 | AM78: 0 | AN78: 0 | AO78: 0 | AP78: 0 | AQ78: 0 | AR78: 0 | AS78: 0 | AT78: 0 | AU78: 0 | AV78: 0 | AW78: 0 | AX78: 0 | AY78: 0 | AZ78: 0 | BA78: 0 | BB78: 0 | BC78: 7294 | BD78: 7294 | BE78: 7294 | BF78: 7294 | BG78: 7294 | BH78: 7294 | BI78: 7294 | BJ78: 7294 | BK78: 7294 | BL78: 7294 | BM78: 7294 | BN78: 7294 | BO78: 7294 | BP78: 0 | BQ78: 0 | BR78: 0 | BS78: 0 | BT78: 0 | BU78: 0 | BV78: 0 | BW78: 0 | BX78: 0 | BY78: 0 | BZ78: 0 | CA78: 0 | CB78: 0
B79: SERVIU Arica y Parinacota | C79: 8967 | D79: 8967 | E79: 8967 | F79: 8967 | G79: 8967 | H79: 8967 | I79: 8967 | J79: 8967 | K79: 8967 | L79: 8967 | M79: 8967 | N79: 8967 | O79: 8967 | P79: 0 | Q79: 0 | R79: 0 | S79: 0 | T79: 0 | U79: 0 | V79: 0 | W79: 0 | X79: 0 | Y79: 0 | Z79: 0 | AA79: 0 | AB79: 0 | AC79: 0 | AD79: 0 | AE79: 0 | AF79: 0 | AG79: 0 | AH79: 0 | AI79: 0 | AJ79: 0 | AK79: 0 | AL79: 0 | AM79: 0 | AN79: 0 | AO79: 0 | AP79: 0 | AQ79: 0 | AR79: 0 | AS79: 0 | AT79: 0 | AU79: 0 | AV79: 0 | AW79: 0 | AX79: 0 | AY79: 0 | AZ79: 0 | BA79: 0 | BB79: 0 | BC79: 3126 | BD79: 3126 | BE79: 3126 | BF79: 3126 | BG79: 3126 | BH79: 3126 | BI79: 3126 | BJ79: 3126 | BK79: 3126 | BL79: 3126 | BM79: 3126 | BN79: 3126 | BO79: 3126 | BP79: 10 | BQ79: 10 | BR79: 10 | BS79: 10 | BT79: 10 | BU79: 10 | BV79: 10 | BW79: 10 | BX79: 10 | BY79: 10 | BZ79: 10 | CA79: 10 | CB79: 10
B80: SERVIU Tarapacá | C80: 13147 | D80: 13147 | E80: 13147 | F80: 13147 | G80: 13147 | H80: 13147 | I80: 13147 | J80: 13147 | K80: 13147 | L80: 13147 | M80: 13147 | N80: 13147 | O80: 13147 | P80: 0 | Q80: 0 | R80: 0 | S80: 0 | T80: 0 | U80: 0 | V80: 0 | W80: 0 | X80: 0 | Y80: 0 | Z80: 0 | AA80: 0 | AB80: 0 | AC80: 0 | AD80: 0 | AE80: 0 | AF80: 0 | AG80: 0 | AH80: 0 | AI80: 0 | AJ80: 0 | AK80: 0 | AL80: 0 | AM80: 0 | AN80: 0 | AO80: 0 | AP80: 0 | AQ80: 0 | AR80: 0 | AS80: 0 | AT80: 0 | AU80: 0 | AV80: 0 | AW80: 0 | AX80: 0 | AY80: 0 | AZ80: 0 | BA80: 0 | BB80: 0 | BC80: 6172 | BD80: 6172 | BE80: 6172 | BF80: 6172 | BG80: 6172 | BH80: 6172 | BI80: 6172 | BJ80: 6172 | BK80: 6172 | BL80: 6172 | BM80: 6172 | BN80: 6172 | BO80: 6172 | BP80: 10 | BQ80: 10 | BR80: 10 | BS80: 10 | BT80: 10 | BU80: 10 | BV80: 10 | BW80: 10 | BX80: 10 | BY80: 10 | BZ80: 10 | CA80: 10 | CB80: 10
B81: SERVIU Antofagasta | C81: 1616 | D81: 1616 | E81: 1616 | F81: 1616 | G81: 1616 | H81: 1616 | I81: 1616 | J81: 1616 | K81: 1616 | L81: 1616 | M81: 1616 | N81: 1616 | O81: 1616 | P81: 0 | Q81: 0 | R81: 0 | S81: 0 | T81: 0 | U81: 0 | V81: 0 | W81: 0 | X81: 0 | Y81: 0 | Z81: 0 | AA81: 0 | AB81: 0 | AC81: 0 | AD81: 0 | AE81: 0 | AF81: 0 | AG81: 0 | AH81: 0 | AI81: 0 | AJ81: 0 | AK81: 0 | AL81: 0 | AM81: 0 | AN81: 0 | AO81: 0 | AP81: 0 | AQ81: 0 | AR81: 0 | AS81: 0 | AT81: 0 | AU81: 0 | AV81: 0 | AW81: 0 | AX81: 0 | AY81: 0 | AZ81: 0 | BA81: 0 | BB81: 0 | BC81: 747 | BD81: 747 | BE81: 747 | BF81: 747 | BG81: 747 | BH81: 747 | BI81: 747 | BJ81: 747 | BK81: 747 | BL81: 747 | BM81: 747 | BN81: 747 | BO81: 747 | BP81: 10 | BQ81: 10 | BR81: 10 | BS81: 10 | BT81: 10 | BU81: 10 | BV81: 10 | BW81: 10 | BX81: 10 | BY81: 10 | BZ81: 10 | CA81: 10 | CB81: 10
B82: SERVIU Atacama | C82: 7771 | D82: 7771 | E82: 7771 | F82: 7771 | G82: 7771 | H82: 7771 | I82: 7771 | J82: 7771 | K82: 7771 | L82: 7771 | M82: 7771 | N82: 7771 | O82: 7771 | P82: 0 | Q82: 0 | R82: 0 | S82: 0 | T82: 0 | U82: 0 | V82: 0 | W82: 0 | X82: 0 | Y82: 0 | Z82: 0 | AA82: 0 | AB82: 0 | AC82: 0 | AD82: 0 | AE82: 0 | AF82: 0 | AG82: 0 | AH82: 0 | AI82: 0 | AJ82: 0 | AK82: 0 | AL82: 0 | AM82: 0 | AN82: 0 | AO82: 0 | AP82: 0 | AQ82: 0 | AR82: 0 | AS82: 0 | AT82: 0 | AU82: 0 | AV82: 0 | AW82: 0 | AX82: 0 | AY82: 0 | AZ82: 0 | BA82: 0 | BB82: 0 | BC82: 6884 | BD82: 6884 | BE82: 6884 | BF82: 6884 | BG82: 6884 | BH82: 6884 | BI82: 6884 | BJ82: 6884 | BK82: 6884 | BL82: 6884 | BM82: 6884 | BN82: 6884 | BO82: 6884 | BP82: 10 | BQ82: 10 | BR82: 10 | BS82: 10 | BT82: 10 | BU82: 10 | BV82: 10 | BW82: 10 | BX82: 10 | BY82: 10 | BZ82: 10 | CA82: 10 | CB82: 10
B83: SERVIU Coquimbo | C83: 9458 | D83: 9458 | E83: 9458 | F83: 9458 | G83: 9458 | H83: 9458 | I83: 9458 | J83: 9458 | K83: 9458 | L83: 9458 | M83: 9458 | N83: 9458 | O83: 9458 | P83: 0 | Q83: 0 | R83: 0 | S83: 0 | T83: 0 | U83: 0 | V83: 0 | W83: 0 | X83: 0 | Y83: 0 | Z83: 0 | AA83: 0 | AB83: 0 | AC83: 0 | AD83: 0 | AE83: 0 | AF83: 0 | AG83: 0 | AH83: 0 | AI83: 0 | AJ83: 0 | AK83: 0 | AL83: 0 | AM83: 0 | AN83: 0 | AO83: 0 | AP83: 0 | AQ83: 0 | AR83: 0 | AS83: 0 | AT83: 0 | AU83: 0 | AV83: 0 | AW83: 0 | AX83: 0 | AY83: 0 | AZ83: 0 | BA83: 0 | BB83: 0 | BC83: 6351 | BD83: 6351 | BE83: 6351 | BF83: 6351 | BG83: 6351 | BH83: 6351 | BI83: 6351 | BJ83: 6351 | BK83: 6351 | BL83: 6351 | BM83: 6351 | BN83: 6351 | BO83: 6351 | BP83: 10 | BQ83: 10 | BR83: 10 | BS83: 10 | BT83: 10 | BU83: 10 | BV83: 10 | BW83: 10 | BX83: 10 | BY83: 10 | BZ83: 10 | CA83: 10 | CB83: 10
B84: SERVIU Valparaíso | C84: 16432 | D84: 16432 | E84: 16432 | F84: 16432 | G84: 16432 | H84: 16432 | I84: 16432 | J84: 16432 | K84: 16432 | L84: 16432 | M84: 16432 | N84: 16432 | O84: 16432 | P84: 0 | Q84: 0 | R84: 0 | S84: 0 | T84: 0 | U84: 0 | V84: 0 | W84: 0 | X84: 0 | Y84: 0 | Z84: 0 | AA84: 0 | AB84: 0 | AC84: 3986250 | AD84: 3986250 | AE84: 3986250 | AF84: 3986250 | AG84: 3986250 | AH84: 3986250 | AI84: 3986250 | AJ84: 3986250 | AK84: 3986250 | AL84: 3986250 | AM84: 3986250 | AN84: 3986250 | AO84: 3986250 | AP84: 0 | AQ84: 0 | AR84: 0 | AS84: 0 | AT84: 0 | AU84: 0 | AV84: 0 | AW84: 0 | AX84: 0 | AY84: 0 | AZ84: 0 | BA84: 0 | BB84: 0 | BC84: 7515 | BD84: 7515 | BE84: 7515 | BF84: 7515 | BG84: 7515 | BH84: 7515 | BI84: 7515 | BJ84: 7515 | BK84: 7515 | BL84: 7515 | BM84: 7515 | BN84: 7515 | BO84: 7515 | BP84: 10 | BQ84: 10 | BR84: 10 | BS84: 10 | BT84: 10 | BU84: 10 | BV84: 10 | BW84: 10 | BX84: 10 | BY84: 10 | BZ84: 10 | CA84: 10 | CB84: 10
B85: SERVIU Metropolitano | C85: 45774 | D85: 45774 | E85: 45774 | F85: 45774 | G85: 45774 | H85: 45774 | I85: 45774 | J85: 45774 | K85: 45774 | L85: 45774 | M85: 45774 | N85: 45774 | O85: 45774 | P85: 0 | Q85: 0 | R85: 0 | S85: 0 | T85: 0 | U85: 0 | V85: 0 | W85: 0 | X85: 0 | Y85: 0 | Z85: 0 | AA85: 0 | AB85: 0 | AC85: 9301250 | AD85: 9301250 | AE85: 9301250 | AF85: 9301250 | AG85: 9301250 | AH85: 9301250 | AI85: 9301250 | AJ85: 9301250 | AK85: 9301250 | AL85: 9301250 | AM85: 9301250 | AN85: 9301250 | AO85: 9301250 | AP85: 0 | AQ85: 0 | AR85: 0 | AS85: 0 | AT85: 0 | AU85: 0 | AV85: 0 | AW85: 0 | AX85: 0 | AY85: 0 | AZ85: 0 | BA85: 0 | BB85: 0 | BC85: 18756 | BD85: 18756 | BE85: 18756 | BF85: 18756 | BG85: 18756 | BH85: 18756 | BI85: 18756 | BJ85: 18756 | BK85: 18756 | BL85: 18756 | BM85: 18756 | BN85: 18756 | BO85: 18756 | BP85: 10 | BQ85: 10 | BR85: 10 | BS85: 10 | BT85: 10 | BU85: 10 | BV85: 10 | BW85: 10 | BX85: 10 | BY85: 10 | BZ85: 10 | CA85: 10 | CB85: 10
B86: SERVIU O'Higgins | C86: 11095 | D86: 11095 | E86: 11095 | F86: 11095 | G86: 11095 | H86: 11095 | I86: 11095 | J86: 11095 | K86: 11095 | L86: 11095 | M86: 11095 | N86: 11095 | O86: 11095 | P86: 0 | Q86: 0 | R86: 0 | S86: 0 | T86: 0 | U86: 0 | V86: 0 | W86: 0 | X86: 0 | Y86: 0 | Z86: 0 | AA86: 0 | AB86: 0 | AC86: 0 | AD86: 0 | AE86: 0 | AF86: 0 | AG86: 0 | AH86: 0 | AI86: 0 | AJ86: 0 | AK86: 0 | AL86: 0 | AM86: 0 | AN86: 0 | AO86: 0 | AP86: 0 | AQ86: 0 | AR86: 0 | AS86: 0 | AT86: 0 | AU86: 0 | AV86: 0 | AW86: 0 | AX86: 0 | AY86: 0 | AZ86: 0 | BA86: 0 | BB86: 0 | BC86: 7815 | BD86: 7815 | BE86: 7815 | BF86: 7815 | BG86: 7815 | BH86: 7815 | BI86: 7815 | BJ86: 7815 | BK86: 7815 | BL86: 7815 | BM86: 7815 | BN86: 7815 | BO86: 7815 | BP86: 10 | BQ86: 10 | BR86: 10 | BS86: 10 | BT86: 10 | BU86: 10 | BV86: 10 | BW86: 10 | BX86: 10 | BY86: 10 | BZ86: 10 | CA86: 10 | CB86: 10
B87: SERVIU Maule | C87: 7055 | D87: 7055 | E87: 7055 | F87: 7055 | G87: 7055 | H87: 7055 | I87: 7055 | J87: 7055 | K87: 7055 | L87: 7055 | M87: 7055 | N87: 7055 | O87: 7055 | P87: 0 | Q87: 0 | R87: 0 | S87: 0 | T87: 0 | U87: 0 | V87: 0 | W87: 0 | X87: 0 | Y87: 0 | Z87: 0 | AA87: 0 | AB87: 0 | AC87: 0 | AD87: 0 | AE87: 0 | AF87: 0 | AG87: 0 | AH87: 0 | AI87: 0 | AJ87: 0 | AK87: 0 | AL87: 0 | AM87: 0 | AN87: 0 | AO87: 0 | AP87: 0 | AQ87: 0 | AR87: 0 | AS87: 0 | AT87: 0 | AU87: 0 | AV87: 0 | AW87: 0 | AX87: 0 | AY87: 0 | AZ87: 0 | BA87: 0 | BB87: 0 | BC87: 3126 | BD87: 3126 | BE87: 3126 | BF87: 3126 | BG87: 3126 | BH87: 3126 | BI87: 3126 | BJ87: 3126 | BK87: 3126 | BL87: 3126 | BM87: 3126 | BN87: 3126 | BO87: 3126 | BP87: 10 | BQ87: 10 | BR87: 10 | BS87: 10 | BT87: 10 | BU87: 10 | BV87: 10 | BW87: 10 | BX87: 10 | BY87: 10 | BZ87: 10 | CA87: 10 | CB87: 10
B88: SERVIU Ñuble | C88: 15569 | D88: 15569 | E88: 15569 | F88: 15569 | G88: 15569 | H88: 15569 | I88: 15569 | J88: 15569 | K88: 15569 | L88: 15569 | M88: 15569 | N88: 15569 | O88: 15569 | P88: 0 | Q88: 0 | R88: 0 | S88: 0 | T88: 0 | U88: 0 | V88: 0 | W88: 0 | X88: 0 | Y88: 0 | Z88: 0 | AA88: 0 | AB88: 0 | AC88: 3986250 | AD88: 3986250 | AE88: 3986250 | AF88: 3986250 | AG88: 3986250 | AH88: 3986250 | AI88: 3986250 | AJ88: 3986250 | AK88: 3986250 | AL88: 3986250 | AM88: 3986250 | AN88: 3986250 | AO88: 3986250 | AP88: 0 | AQ88: 0 | AR88: 0 | AS88: 0 | AT88: 0 | AU88: 0 | AV88: 0 | AW88: 0 | AX88: 0 | AY88: 0 | AZ88: 0 | BA88: 0 | BB88: 0 | BC88: 9378 | BD88: 9378 | BE88: 9378 | BF88: 9378 | BG88: 9378 | BH88: 9378 | BI88: 9378 | BJ88: 9378 | BK88: 9378 | BL88: 9378 | BM88: 9378 | BN88: 9378 | BO88: 9378 | BP88: 10 | BQ88: 10 | BR88: 10 | BS88: 10 | BT88: 10 | BU88: 10 | BV88: 10 | BW88: 10 | BX88: 10 | BY88: 10 | BZ88: 10 | CA88: 10 | CB88: 10
... B94: SERVIU Magallanes | C94: 8750 | D94: 8750 | E94: 8750 | F94: 8750 | G94: 8750 | H94: 8750 | I94: 8750 | J94: 8750 | K94: 8750 | L94: 8750 | M94: 8750 | N94: 8750 | O94: 8750 | P94: 0 | Q94: 0 | R94: 0 | S94: 0 | T94: 0 | U94: 0 | V94: 0 | W94: 0 | X94: 0 | Y94: 0 | Z94: 0 | AA94: 0 | AB94: 0 | AC94: 0 | AD94: 0 | AE94: 0 | AF94: 0 | AG94: 0 | AH94: 0 | AI94: 0 | AJ94: 0 | AK94: 0 | AL94: 0 | AM94: 0 | AN94: 0 | AO94: 0 | AP94: 0 | AQ94: 0 | AR94: 0 | AS94: 0 | AT94: 0 | AU94: 0 | AV94: 0 | AW94: 0 | AX94: 0 | AY94: 0 | AZ94: 0 | BA94: 0 | BB94: 0 | BC94: 4168 | BD94: 4168 | BE94: 4168 | BF94: 4168 | BG94: 4168 | BH94: 4168 | BI94: 4168 | BJ94: 4168 | BK94: 4168 | BL94: 4168 | BM94: 4168 | BN94: 4168 | BO94: 4168 | BP94: 10 | BQ94: 10 | BR94: 10 | BS94: 10 | BT94: 10 | BU94: 10 | BV94: 10 | BW94: 10 | BX94: 10 | BY94: 10 | BZ94: 10 | CA94: 10 | CB94: 10
B95: Total Presupuesto Ley (Subtítulo 29) | C95: =SUM(C77:C94) -> 4157090 | D95: =SUM(D77:D94) -> 4157090 | E95: =SUM(E77:E94) -> 4157090 | F95: =SUM(F77:F94) -> 4157090 | G95: =SUM(G77:G94) -> 4157090 | H95: =SUM(H77:H94) -> 4157090 | I95: =SUM(I77:I94) -> 4157090 | J95: =SUM(J77:J94) -> 4157090 | ... CB95: =SUM(CB77:CB94) -> 4182864
B96: Presupuesto Vigente (Subtítulo 29)
C97: 2021 | P97: 2022 | AC97: 2023 | AP97: 2024 | BC97: 2025 | BP97: 2026
B98: Programa / Entidad | C98: Ene | D98: Feb | E98: Mar | F98: Abr | G98: May | H98: Jun | I98: Jul | J98: Ago | K98: Sep | L98: Oct | M98: Nov | N98: Dic | O98: Total 2021 | P98: Ene | Q98: Feb | R98: Mar | S98: Abr | T98: May | U98: Jun | V98: Jul | W98: Ago | X98: Sep | Y98: Oct | Z98: Nov | AA98: Dic | AB98: Total 2022 | AC98: Ene | AD98: Feb | AE98: Mar | AF98: Abr | AG98: May | AH98: Jun | AI98: Jul | AJ98: Ago | AK98: Sep | AL98: Oct | AM98: Nov | AN98: Dic | AO98: Total 2023 | AP98: Ene | AQ98: Feb | AR98: Mar | AS98: Abr | AT98: May | AU98: Jun | AV98: Jul | AW98: Ago | AX98: Sep | AY98: Oct | AZ98: Nov | BA98: Dic | BB98: Total 2024 | BC98: Ene | BD98: Feb | BE98: Mar | BF98: Abr | BG98: May | BH98: Jun | BI98: Jul | BJ98: Ago | BK98: Sep | BL98: Oct | BM98: Nov | BN98: Dic | BO98: Total 2025 | BP98: Ene | BQ98: Feb | BR98: Mar | BS98: Abr | BT98: May | BU98: Jun | BV98: Jul | BW98: Ago | BX98: Sep | BY98: Oct | BZ98: Nov | CA98: Dic | CB98: Total 2026
B99: Subsecretaría y Programas Centrales | C99: 3949109 | D99: 3949109 | E99: 3949109 | F99: 3949109 | G99: 3949109 | H99: 3938465 | I99: 3938465 | J99: 3938465 | K99: 3938465 | L99: 3938465 | M99: 3928965 | N99: 3199280 | O99: 3199280 | P99: 3677484 | Q99: 3677484 | R99: 3677484 | S99: 3677484 | T99: 3771152 | U99: 3841152 | V99: 3841152 | W99: 3841152 | X99: 3841152 | Y99: 3928152 | Z99: 3928152 | AA99: 3784939 | AB99: 3784939 | AC99: 4127526 | AD99: 4127526 | AE99: 4127526 | AF99: 4127526 | AG99: 4127526 | AH99: 4127526 | AI99: 4127526 | AJ99: 4127526 | AK99: 4127526 | AL99: 4127526 | AM99: 4127526 | AN99: 3999809 | AO99: 3999809 | AP99: 30674754 | AQ99: 30674754 | AR99: 30674754 | AS99: 30674754 | AT99: 30710139 | AU99: 27678180 | AV99: 27678180 | AW99: 27678180 | AX99: 27678180 | AY99: 27641880 | AZ99: 3168714 | BA99: 3168714 | BB99: 3168714 | BC99: 4435821 | BD99: 4435821 | BE99: 4435821 | BF99: 4435821 | BG99: 4435821 | BH99: 4435821 | BI99: 4435821 | BJ99: 4435821 | BK99: 4435821 | BL99: 4435821 | BM99: 4435821 | BN99: 4435821 | BO99: 4435821 | BP99: 4182704 | BQ99: 4182704 | BR99: 4182704 | BS99: 4182704 | BT99: 4182704 | BU99: 4182704 | BV99: 4182704 | BW99: 4182704 | BX99: 4182704 | BY99: 4182704 | BZ99: 4182704 | CA99: 4182704 | CB99: 4182704
B100: Parque Metropolitano (PARQUEMET) | C100: 71111 | D100: 71111 | E100: 71111 | F100: 71111 | G100: 71111 | H100: 71111 | I100: 71111 | J100: 71111 | K100: 71111 | L100: 71111 | M100: 80111 | N100: 80111 | O100: 80111 | P100: 33328 | Q100: 33328 | R100: 33328 | S100: 33328 | T100: 33328 | U100: 33328 | V100: 33328 | W100: 33328 | X100: 33328 | Y100: 33328 | Z100: 33328 | AA100: 33328 | AB100: 33328 | AC100: 0 | AD100: 0 | AE100: 0 | AF100: 0 | AG100: 0 | AH100: 0 | AI100: 0 | AJ100: 0 | AK100: 0 | AL100: 0 | AM100: 0 | AN100: 0 | AO100: 0 | AP100: 0 | AQ100: 0 | AR100: 0 | AS100: 0 | AT100: 6773 | AU100: 6773 | AV100: 6773 | AW100: 240920 | AX100: 240920 | AY100: 240920 | AZ100: 240920 | BA100: 240920 | BB100: 240920 | BC100: 6929 | BD100: 6929 | BE100: 6929 | BF100: 6929 | BG100: 6929 | BH100: 6929 | BI100: 6929 | BJ100: 6929 | BK100: 6929 | BL100: 6929 | BM100: 6929 | BN100: 6929 | BO100: 6929 | BP100: 0 | BQ100: 0 | BR100: 0 | BS100: 0 | BT100: 0 | BU100: 0 | BV100: 0 | BW100: 0 | BX100: 0 | BY100: 0 | BZ100: 0 | CA100: 0 | CB100: 0
B101: SERVIU Arica y Parinacota | C101: 8967 | D101: 8967 | E101: 8967 | F101: 8967 | G101: 8967 | H101: 8967 | I101: 8967 | J101: 8967 | K101: 8967 | L101: 8967 | M101: 6258817 | N101: 6258817 | O101: 6258817 | P101: 0 | Q101: 0 | R101: 0 | S101: 0 | T101: 0 | U101: 0 | V101: 0 | W101: 0 | X101: 7943900 | Y101: 7943900 | Z101: 9744243 | AA101: 9744243 | AB101: 9744243 | AC101: 0 | AD101: 0 | AE101: 0 | AF101: 0 | AG101: 0 | AH101: 0 | AI101: 0 | AJ101: 0 | AK101: 0 | AL101: 0 | AM101: 0 | AN101: 0 | AO101: 0 | AP101: 0 | AQ101: 0 | AR101: 0 | AS101: 0 | AT101: 5926 | AU101: 5926 | AV101: 5926 | AW101: 5926 | AX101: 5926 | AY101: 7496 | AZ101: 7496 | BA101: 7496 | BB101: 7496 | BC101: 2970 | BD101: 2970 | BE101: 2970 | BF101: 2970 | BG101: 2970 | BH101: 2970 | BI101: 2970 | BJ101: 2970 | BK101: 2970 | BL101: 2970 | BM101: 2970 | BN101: 2970 | BO101: 2970 | BP101: 10 | BQ101: 10 | BR101: 10 | BS101: 10 | BT101: 10 | BU101: 10 | BV101: 10 | BW101: 10 | BX101: 10 | BY101: 10 | BZ101: 10 | CA101: 10 | CB101: 10
B102: SERVIU Tarapacá | C102: 13147 | D102: 13147 | E102: 13147 | F102: 13147 | G102: 13147 | H102: 13147 | I102: 13147 | J102: 13147 | K102: 77908 | L102: 77908 | M102: 78408 | N102: 78408 | O102: 78408 | P102: 0 | Q102: 0 | R102: 0 | S102: 0 | T102: 0 | U102: 0 | V102: 0 | W102: 0 | X102: 0 | Y102: 0 | Z102: 0 | AA102: 0 | AB102: 0 | AC102: 0 | AD102: 3978246 | AE102: 3978246 | AF102: 3978246 | AG102: 3978246 | AH102: 3978246 | AI102: 3978246 | AJ102: 3978246 | AK102: 3978246 | AL102: 3978246 | AM102: 3978246 | AN102: 3978246 | AO102: 3978246 | AP102: 0 | AQ102: 0 | AR102: 0 | AS102: 0 | AT102: 1694 | AU102: 1694 | AV102: 1694 | AW102: 1694 | AX102: 1694 | AY102: 3479 | AZ102: 3479 | BA102: 3479 | BB102: 3479 | BC102: 5863 | BD102: 5863 | BE102: 5863 | BF102: 5863 | BG102: 5863 | BH102: 5863 | BI102: 5863 | BJ102: 5863 | BK102: 5863 | BL102: 5863 | BM102: 5863 | BN102: 5863 | BO102: 5863 | BP102: 10 | BQ102: 10 | BR102: 10 | BS102: 10 | BT102: 10 | BU102: 10 | BV102: 10 | BW102: 10 | BX102: 10 | BY102: 10 | BZ102: 10 | CA102: 10 | CB102: 10
B103: SERVIU Antofagasta | C103: 1616 | D103: 1616 | E103: 1616 | F103: 1616 | G103: 1616 | H103: 1926 | I103: 1926 | J103: 1926 | K103: 1926 | L103: 1926 | M103: 1926 | N103: 1926 | O103: 1926 | P103: 0 | Q103: 0 | R103: 0 | S103: 0 | T103: 0 | U103: 0 | V103: 0 | W103: 0 | X103: 0 | Y103: 0 | Z103: 5960113 | AA103: 5960113 | AB103: 5960113 | AC103: 0 | AD103: 0 | AE103: 0 | AF103: 0 | AG103: 0 | AH103: 0 | AI103: 0 | AJ103: 0 | AK103: 0 | AL103: 0 | AM103: 0 | AN103: 0 | AO103: 0 | AP103: 0 | AQ103: 0 | AR103: 0 | AS103: 0 | AT103: 5080 | AU103: 5080 | AV103: 5080 | AW103: 5080 | AX103: 5080 | AY103: 6270 | AZ103: 6270 | BA103: 6270 | BB103: 6270 | BC103: 710 | BD103: 710 | BE103: 710 | BF103: 710 | BG103: 710 | BH103: 710 | BI103: 710 | BJ103: 710 | BK103: 710 | BL103: 710 | BM103: 710 | BN103: 710 | BO103: 710 | BP103: 10 | BQ103: 10 | BR103: 10 | BS103: 10 | BT103: 10 | BU103: 10 | BV103: 10 | BW103: 10 | BX103: 10 | BY103: 10 | BZ103: 10 | CA103: 10 | CB103: 10
B104: SERVIU Atacama | C104: 7771 | D104: 7771 | E104: 7771 | F104: 7771 | G104: 7771 | H104: 7771 | I104: 7771 | J104: 7771 | K104: 7771 | L104: 7771 | M104: 7771 | N104: 7771 | O104: 7771 | P104: 0 | Q104: 0 | R104: 0 | S104: 0 | T104: 0 | U104: 0 | V104: 0 | W104: 0 | X104: 0 | Y104: 0 | Z104: 8335525 | AA104: 8335525 | AB104: 8335525 | AC104: 0 | AD104: 0 | AE104: 0 | AF104: 0 | AG104: 0 | AH104: 0 | AI104: 0 | AJ104: 0 | AK104: 0 | AL104: 0 | AM104: 0 | AN104: 329064 | AO104: 329064 | AP104: 0 | AQ104: 0 | AR104: 0 | AS104: 0 | AT104: 5926 | AU104: 5926 | AV104: 5926 | AW104: 5926 | AX104: 5926 | AY104: 6646 | AZ104: 6646 | BA104: 6646 | BB104: 6646 | BC104: 6540 | BD104: 6540 | BE104: 6540 | BF104: 6540 | BG104: 6540 | BH104: 6540 | BI104: 6540 | BJ104: 6540 | BK104: 6540 | BL104: 6540 | BM104: 6540 | BN104: 6540 | BO104: 6540 | BP104: 10 | BQ104: 10 | BR104: 10 | BS104: 10 | BT104: 10 | BU104: 10 | BV104: 10 | BW104: 10 | BX104: 10 | BY104: 10 | BZ104: 10 | CA104: 10 | CB104: 10
B105: SERVIU Coquimbo | C105: 9458 | D105: 9458 | E105: 9458 | F105: 9458 | G105: 1661590 | H105: 1662157 | I105: 1662157 | J105: 1662157 | K105: 1662157 | L105: 1662778 | M105: 1662778 | N105: 1662778 | O105: 1662778 | P105: 0 | Q105: 0 | R105: 0 | S105: 0 | T105: 0 | U105: 0 | V105: 0 | W105: 0 | X105: 0 | Y105: 0 | Z105: 5385954 | AA105: 25574386 | AB105: 25574386 | AC105: 0 | AD105: 0 | AE105: 0 | AF105: 0 | AG105: 0 | AH105: 0 | AI105: 0 | AJ105: 0 | AK105: 0 | AL105: 0 | AM105: 0 | AN105: 115827 | AO105: 115827 | AP105: 0 | AQ105: 0 | AR105: 0 | AS105: 0 | AT105: 8466 | AU105: 6091623 | AV105: 6091623 | AW105: 6091623 | AX105: 6091623 | AY105: 6092813 | AZ105: 6092813 | BA105: 6092813 | BB105: 6092813 | BC105: 6033 | BD105: 6033 | BE105: 6033 | BF105: 6033 | BG105: 6033 | BH105: 6033 | BI105: 6033 | BJ105: 6033 | BK105: 6033 | BL105: 6033 | BM105: 6033 | BN105: 6033 | BO105: 6033 | BP105: 10 | BQ105: 10 | BR105: 10 | BS105: 10 | BT105: 10 | BU105: 10 | BV105: 10 | BW105: 10 | BX105: 10 | BY105: 10 | BZ105: 10 | CA105: 10 | CB105: 10
B106: SERVIU Valparaíso | C106: 16432 | D106: 16432 | E106: 16432 | F106: 16432 | G106: 16432 | H106: 16432 | I106: 16432 | J106: 1463147 | K106: 1463147 | L106: 1463147 | M106: 1463147 | N106: 1985593 | O106: 1985593 | P106: 0 | Q106: 0 | R106: 0 | S106: 0 | T106: 4326119 | U106: 4326119 | V106: 4326119 | W106: 4326119 | X106: 4645716 | Y106: 4645716 | Z106: 16485804 | AA106: 17202625 | AB106: 17202625 | AC106: 3986250 | AD106: 3986250 | AE106: 3986250 | AF106: 3986250 | AG106: 3986250 | AH106: 3986250 | AI106: 3986250 | AJ106: 3986250 | AK106: 3986250 | AL106: 3986250 | AM106: 3986250 | AN106: 3986250 | AO106: 3986250 | AP106: 0 | AQ106: 0 | AR106: 0 | AS106: 0 | AT106: 20317 | AU106: 20317 | AV106: 20317 | AW106: 20317 | AX106: 20317 | AY106: 21887 | AZ106: 21887 | BA106: 21887 | BB106: 21887 | BC106: 7139 | BD106: 7139 | BE106: 7139 | BF106: 7139 | BG106: 7139 | BH106: 7139 | BI106: 7139 | BJ106: 7139 | BK106: 7139 | BL106: 7139 | BM106: 7139 | BN106: 10998043 | BO106: 10998043 | BP106: 10 | BQ106: 10 | BR106: 10 | BS106: 10 | BT106: 10 | BU106: 10 | BV106: 10 | BW106: 10 | BX106: 10 | BY106: 10 | BZ106: 10 | CA106: 10 | CB106: 10
B107: SERVIU Metropolitano | C107: 45774 | D107: 45774 | E107: 45774 | F107: 45774 | G107: 10722943 | H107: 10722943 | I107: 10722943 | J107: 10722943 | K107: 10722943 | L107: 10722943 | M107: 10722943 | N107: 11741384 | O107: 11741384 | P107: 0 | Q107: 0 | R107: 0 | S107: 2514515 | T107: 6983585 | U107: 6983585 | V107: 6983585 | W107: 6983585 | X107: 6983585 | Y107: 51902800 | Z107: 80310595 | AA107: 78492160 | AB107: 78492160 | AC107: 9301250 | AD107: 9301250 | AE107: 9301250 | AF107: 9301250 | AG107: 9301250 | AH107: 9301250 | AI107: 9301250 | AJ107: 9301250 | AK107: 9301250 | AL107: 9301250 | AM107: 9301250 | AN107: 9462117 | AO107: 9462117 | AP107: 0 | AQ107: 0 | AR107: 0 | AS107: 0 | AT107: 32168 | AU107: 32168 | AV107: 32168 | AW107: 32168 | AX107: 32168 | AY107: 44560 | AZ107: 44560 | BA107: 44560 | BB107: 44560 | BC107: 17818 | BD107: 17818 | BE107: 17818 | BF107: 17818 | BG107: 17818 | BH107: 17818 | BI107: 17818 | BJ107: 17818 | BK107: 17818 | BL107: 17818 | BM107: 17818 | BN107: 17818 | BO107: 17818 | BP107: 10 | BQ107: 10 | BR107: 10 | BS107: 10 | BT107: 10 | BU107: 10 | BV107: 10 | BW107: 10 | BX107: 10 | BY107: 10 | BZ107: 10 | CA107: 10 | CB107: 10
B108: SERVIU O'Higgins | C108: 11095 | D108: 11095 | E108: 11095 | F108: 11095 | G108: 11095 | H108: 11095 | I108: 11095 | J108: 11095 | K108: 11095 | L108: 5116931 | M108: 5116931 | N108: 5116931 | O108: 5116931 | P108: 0 | Q108: 0 | R108: 1089715 | S108: 1089715 | T108: 1089715 | U108: 1089715 | V108: 1089715 | W108: 1089715 | X108: 1089715 | Y108: 1089715 | Z108: 7899193 | AA108: 7899193 | AB108: 7899193 | AC108: 0 | AD108: 0 | AE108: 0 | AF108: 0 | AG108: 0 | AH108: 0 | AI108: 0 | AJ108: 0 | AK108: 0 | AL108: 0 | AM108: 0 | AN108: 0 | AO108: 0 | AP108: 0 | AQ108: 0 | AR108: 0 | AS108: 0 | AT108: 10159 | AU108: 10159 | AV108: 10159 | AW108: 10159 | AX108: 10159 | AY108: 12541 | AZ108: 431652 | BA108: 300457 | BB108: 300457 | BC108: 7424 | BD108: 7424 | BE108: 7424 | BF108: 7424 | BG108: 7424 | BH108: 7424 | BI108: 7424 | BJ108: 7424 | BK108: 7424 | BL108: 7424 | BM108: 7424 | BN108: 7424 | BO108: 7424 | BP108: 10 | BQ108: 10 | BR108: 10 | BS108: 10 | BT108: 10 | BU108: 10 | BV108: 10 | BW108: 10 | BX108: 10 | BY108: 10 | BZ108: 10 | CA108: 10 | CB108: 10
B109: SERVIU Maule | C109: 7055 | D109: 7055 | E109: 7055 | F109: 7055 | G109: 250007 | H109: 250007 | I109: 266968 | J109: 266968 | K109: 266968 | L109: 266968 | M109: 266968 | N109: 266968 | O109: 266968 | P109: 0 | Q109: 0 | R109: 0 | S109: 0 | T109: 33826 | U109: 33826 | V109: 33826 | W109: 33826 | X109: 33826 | Y109: 3346047 | Z109: 6440875 | AA109: 8582147 | AB109: 8582147 | AC109: 0 | AD109: 0 | AE109: 0 | AF109: 0 | AG109: 0 | AH109: 0 | AI109: 0 | AJ109: 0 | AK109: 0 | AL109: 0 | AM109: 0 | AN109: 0 | AO109: 0 | AP109: 0 | AQ109: 0 | AR109: 0 | AS109: 0 | AT109: 5080 | AU109: 5080 | AV109: 5080 | AW109: 5080 | AX109: 5080 | AY109: 6865 | AZ109: 6865 | BA109: 6865 | BB109: 6865 | BC109: 2970 | BD109: 2970 | BE109: 2970 | BF109: 2970 | BG109: 2970 | BH109: 2970 | BI109: 2970 | BJ109: 2970 | BK109: 2970 | BL109: 2970 | BM109: 2970 | BN109: 2970 | BO109: 2970 | BP109: 10 | BQ109: 10 | BR109: 10 | BS109: 10 | BT109: 10 | BU109: 10 | BV109: 10 | BW109: 10 | BX109: 10 | BY109: 10 | BZ109: 10 | CA109: 10 | CB109: 10
B110: SERVIU Ñuble | C110: 15569 | D110: 15569 | E110: 15569 | F110: 15569 | G110: 15569 | H110: 19306 | I110: 19306 | J110: 19306 | K110: 19306 | L110: 19306 | M110: 19306 | N110: 2042437 | O110: 2042437 | P110: 0 | Q110: 0 | R110: 0 | S110: 0 | T110: 0 | U110: 0 | V110: 0 | W110: 0 | X110: 0 | Y110: 0 | Z110: 1603019 | AA110: 1603019 | AB110: 1603019 | AC110: 3986250 | AD110: 3986250 | AE110: 3986250 | AF110: 3986250 | AG110: 3986250 | AH110: 3986250 | AI110: 3986250 | AJ110: 3986250 | AK110: 3986250 | AL110: 3986250 | AM110: 3986250 | AN110: 4033097 | AO110: 4033097 | AP110: 0 | AQ110: 0 | AR110: 0 | AS110: 0 | AT110: 5080 | AU110: 5080 | AV110: 5080 | AW110: 5080 | AX110: 5080 | AY110: 6270 | AZ110: 6270 | BA110: 6270 | BB110: 6270 | BC110: 8909 | BD110: 8909 | BE110: 8909 | BF110: 8909 | BG110: 8909 | BH110: 8909 | BI110: 8909 | BJ110: 8909 | BK110: 8909 | BL110: 8909 | BM110: 8909 | BN110: 8909 | BO110: 8909 | BP110: 10 | BQ110: 10 | BR110: 10 | BS110: 10 | BT110: 10 | BU110: 10 | BV110: 10 | BW110: 10 | BX110: 10 | BY110: 10 | BZ110: 10 | CA110: 10 | CB110: 10
... B116: SERVIU Magallanes | C116: 8750 | D116: 8750 | E116: 8750 | F116: 8750 | G116: 8750 | H116: 13550 | I116: 13550 | J116: 13550 | K116: 13550 | L116: 13550 | M116: 13550 | N116: 13550 | O116: 13550 | P116: 0 | Q116: 0 | R116: 0 | S116: 0 | T116: 0 | U116: 0 | V116: 0 | W116: 0 | X116: 0 | Y116: 0 | Z116: 0 | AA116: 0 | AB116: 0 | AC116: 0 | AD116: 0 | AE116: 0 | AF116: 0 | AG116: 0 | AH116: 0 | AI116: 0 | AJ116: 0 | AK116: 0 | AL116: 0 | AM116: 0 | AN116: 0 | AO116: 0 | AP116: 0 | AQ116: 0 | AR116: 0 | AS116: 0 | AT116: 6773 | AU116: 6773 | AV116: 6773 | AW116: 6773 | AX116: 6773 | AY116: 8343 | AZ116: 8343 | BA116: 8343 | BB116: 8343 | BC116: 3960 | BD116: 3960 | BE116: 3960 | BF116: 3960 | BG116: 3960 | BH116: 3960 | BI116: 3960 | BJ116: 3960 | BK116: 3960 | BL116: 11799960 | BM116: 21799960 | BN116: 21799960 | BO116: 21799960 | BP116: 10 | BQ116: 10 | BR116: 10 | BS116: 10 | BT116: 10 | BU116: 10 | BV116: 10 | BW116: 10 | BX116: 10 | BY116: 10 | BZ116: 10 | CA116: 10 | CB116: 10
B117: Total Presupuesto Vigente (Subtítulo 29) | C117: =SUM(C99:C116) -> 4227090 | D117: =SUM(D99:D116) -> 4227090 | E117: =SUM(E99:E116) -> 4227090 | F117: =SUM(F99:F116) -> 4991320 | G117: =SUM(G99:G116) -> 19462393 | H117: =SUM(H99:H116) -> 19462393 | I117: =SUM(I99:I116) -> 19479354 | J117: =SUM(J99:J116) -> 20926069 | ... CB117: =SUM(CB99:CB116) -> 4182864
B118: Ejecución Acumulada (Subtítulo 29)
C119: 2021 | P119: 2022 | AC119: 2023 | AP119: 2024 | BC119: 2025 | BP119: 2026
B120: Programa / Entidad | C120: Ene | D120: Feb | E120: Mar | F120: Abr | G120: May | H120: Jun | I120: Jul | J120: Ago | K120: Sep | L120: Oct | M120: Nov | N120: Dic | O120: Total 2021 | P120: Ene | Q120: Feb | R120: Mar | S120: Abr | T120: May | U120: Jun | V120: Jul | W120: Ago | X120: Sep | Y120: Oct | Z120: Nov | AA120: Dic | AB120: Total 2022 | AC120: Ene | AD120: Feb | AE120: Mar | AF120: Abr | AG120: May | AH120: Jun | AI120: Jul | AJ120: Ago | AK120: Sep | AL120: Oct | AM120: Nov | AN120: Dic | AO120: Total 2023 | AP120: Ene | AQ120: Feb | AR120: Mar | AS120: Abr | AT120: May | AU120: Jun | AV120: Jul | AW120: Ago | AX120: Sep | AY120: Oct | AZ120: Nov | BA120: Dic | BB120: Total 2024 | BC120: Ene | BD120: Feb | BE120: Mar | BF120: Abr | BG120: May | BH120: Jun | BI120: Jul | BJ120: Ago | BK120: Sep | BL120: Oct | BM120: Nov | BN120: Dic | BO120: Total 2025 | BP120: Ene | BQ120: Feb | BR120: Mar | BS120: Abr | BT120: May | BU120: Jun | BV120: Jul | BW120: Ago | BX120: Sep | BY120: Oct | BZ120: Nov | CA120: Dic | CB120: Total 2026
B121: Subsecretaría y Programas Centrales | C121: 26183 | D121: 376776 | E121: 378279 | F121: 446136 | G121: 453034 | H121: 1329874 | I121: 1345317 | J121: 1387391 | K121: 1462746 | L121: 1495877 | M121: 1511001 | N121: 2707796 | O121: 2707796 | P121: 68886 | Q121: 69186 | R121: 207582 | S121: 359767 | T121: 366917 | U121: 388085 | V121: 395549 | W121: 1813710 | X121: 1901113 | Y121: 1998202 | Z121: 2514049 | AA121: 3505429 | AB121: 3505429 | AC121: 1250846 | AD121: 1392713 | AE121: 1433256 | AF121: 1483029 | AG121: 1517815 | AH121: 1680447 | AI121: 1709872 | AJ121: 1904712 | AK121: 1943485 | AL121: 2116599 | AM121: 2749373 | AN121: 3241192 | AO121: 3241192 | AP121: 1473303 | AQ121: 1473303 | AR121: 1611277 | AS121: 1631762 | AT121: 1747004 | AU121: 1751284 | AV121: 1863427 | AW121: 2013570 | AX121: 2045198 | AY121: 2070666 | AZ121: 2651552 | BA121: 3071041 | BB121: 3071041 | BC121: 0 | BD121: 757870 | BE121: 826766 | BF121: 839136 | BG121: 878206 | BH121: 887434 | BI121: 948168 | BJ121: 2168256 | BK121: 2230134 | BL121: 2896737 | BM121: 3126309 | BN121: 4077223 | BO121: 4077223 | BP121: 1719166 | BQ121: 1719166 | BR121: 1866021 | BS121: 1873924 | BT121: 1910136 | BU121: 1978750 | BV121: 1989460 | BW121: 1989460 | BX121: 1989460 | BY121: 1989460 | BZ121: 1989460 | CA121: 1989460 | CB121: 1989460
B122: Parque Metropolitano (PARQUEMET) | C122: 0 | D122: 1597 | E122: 4453 | F122: 17905 | G122: 21835 | H122: 29163 | I122: 31462 | J122: 38083 | K122: 43795 | L122: 47640 | M122: 53369 | N122: 74077 | O122: 74077 | P122: 0 | Q122: 0 | R122: 0 | S122: 59 | T122: 1565 | U122: 2140 | V122: 4991 | W122: 5415 | X122: 7518 | Y122: 16518 | Z122: 26888 | AA122: 33214 | AB122: 33214 | AC122: 0 | AD122: 0 | AE122: 0 | AF122: 0 | AG122: 0 | AH122: 0 | AI122: 0 | AJ122: 0 | AK122: 0 | AL122: 0 | AM122: 0 | AN122: 0 | AO122: 0 | AP122: 0 | AQ122: 0 | AR122: 0 | AS122: 0 | AT122: 0 | AU122: 0 | AV122: 0 | AW122: 0 | AX122: 0 | AY122: 56899 | AZ122: 103913 | BA122: 240208 | BB122: 240208 | BC122: 0 | BD122: 0 | BE122: 144 | BF122: 144 | BG122: 144 | BH122: 144 | BI122: 144 | BJ122: 144 | BK122: 144 | BL122: 6463 | BM122: 6723 | BN122: 6723 | BO122: 6723 | BP122: 0 | BQ122: 0 | BR122: 0 | BS122: 0 | BT122: 0 | BU122: 0 | BV122: 0 | BW122: 0 | BX122: 0 | BY122: 0 | BZ122: 0 | CA122: 0 | CB122: 0
B123: SERVIU Arica y Parinacota | C123: 0 | D123: 0 | E123: 0 | F123: 0 | G123: 0 | H123: 0 | I123: 1263 | J123: 1263 | K123: 1263 | L123: 1263 | M123: 3499 | N123: 6240429 | O123: 6240429 | P123: 0 | Q123: 0 | R123: 0 | S123: 0 | T123: 0 | U123: 0 | V123: 0 | W123: 0 | X123: 0 | Y123: 0 | Z123: 0 | AA123: 9315642 | AB123: 9315642 | AC123: 0 | AD123: 0 | AE123: 0 | AF123: 0 | AG123: 0 | AH123: 0 | AI123: 0 | AJ123: 0 | AK123: 0 | AL123: 0 | AM123: 0 | AN123: 0 | AO123: 0 | AP123: 0 | AQ123: 0 | AR123: 0 | AS123: 0 | AT123: 0 | AU123: 0 | AV123: 0 | AW123: 0 | AX123: 0 | AY123: 5390 | AZ123: 5390 | BA123: 7431 | BB123: 7431 | BC123: 0 | BD123: 0 | BE123: 0 | BF123: 0 | BG123: 0 | BH123: 0 | BI123: 2970 | BJ123: 2970 | BK123: 2970 | BL123: 2970 | BM123: 2970 | BN123: 2970 | BO123: 2970 | BP123: 0 | BQ123: 0 | BR123: 0 | BS123: 0 | BT123: 0 | BU123: 0 | BV123: 0 | BW123: 0 | BX123: 0 | BY123: 0 | BZ123: 0 | CA123: 0 | CB123: 0
B124: SERVIU Tarapacá | C124: 2885 | D124: 2885 | E124: 2885 | F124: 4426 | G124: 4426 | H124: 4755 | I124: 10184 | J124: 10184 | K124: 11576 | L124: 11576 | M124: 37314 | N124: 76373 | O124: 76373 | P124: 0 | Q124: 0 | R124: 0 | S124: 0 | T124: 0 | U124: 0 | V124: 0 | W124: 0 | X124: 0 | Y124: 0 | Z124: 0 | AA124: 0 | AB124: 0 | AC124: 0 | AD124: 0 | AE124: 0 | AF124: 0 | AG124: 0 | AH124: 0 | AI124: 0 | AJ124: 0 | AK124: 0 | AL124: 0 | AM124: 0 | AN124: 3978246 | AO124: 3978246 | AP124: 0 | AQ124: 0 | AR124: 0 | AS124: 0 | AT124: 0 | AU124: 0 | AV124: 655 | AW124: 1663 | AX124: 1663 | AY124: 1663 | AZ124: 1663 | BA124: 3340 | BB124: 3340 | BC124: 0 | BD124: 0 | BE124: 365 | BF124: 365 | BG124: 365 | BH124: 5357 | BI124: 5837 | BJ124: 5837 | BK124: 5837 | BL124: 5837 | BM124: 5837 | BN124: 5837 | BO124: 5837 | BP124: 0 | BQ124: 0 | BR124: 0 | BS124: 0 | BT124: 0 | BU124: 0 | BV124: 0 | BW124: 0 | BX124: 0 | BY124: 0 | BZ124: 0 | CA124: 0 | CB124: 0
B125: SERVIU Antofagasta | C125: 0 | D125: 0 | E125: 0 | F125: 0 | G125: 0 | H125: 0 | I125: 0 | J125: 0 | K125: 0 | L125: 0 | M125: 0 | N125: 967 | O125: 967 | P125: 0 | Q125: 0 | R125: 0 | S125: 0 | T125: 0 | U125: 0 | V125: 0 | W125: 0 | X125: 0 | Y125: 0 | Z125: 0 | AA125: 5708036 | AB125: 5708036 | AC125: 0 | AD125: 0 | AE125: 0 | AF125: 0 | AG125: 0 | AH125: 0 | AI125: 0 | AJ125: 0 | AK125: 0 | AL125: 0 | AM125: 0 | AN125: 0 | AO125: 0 | AP125: 0 | AQ125: 0 | AR125: 0 | AS125: 0 | AT125: 0 | AU125: 0 | AV125: 0 | AW125: 0 | AX125: 0 | AY125: 0 | AZ125: 0 | BA125: 4665 | BB125: 4665 | BC125: 0 | BD125: 0 | BE125: 0 | BF125: 0 | BG125: 0 | BH125: 601 | BI125: 601 | BJ125: 601 | BK125: 601 | BL125: 601 | BM125: 707 | BN125: 707 | BO125: 707 | BP125: 0 | BQ125: 0 | BR125: 0 | BS125: 0 | BT125: 0 | BU125: 0 | BV125: 0 | BW125: 0 | BX125: 0 | BY125: 0 | BZ125: 0 | CA125: 0 | CB125: 0
B126: SERVIU Atacama | C126: 0 | D126: 0 | E126: 1109 | F126: 1109 | G126: 1109 | H126: 3164 | I126: 3709 | J126: 4709 | K126: 4709 | L126: 4709 | M126: 5491 | N126: 7698 | O126: 7698 | P126: 0 | Q126: 0 | R126: 0 | S126: 0 | T126: 0 | U126: 0 | V126: 0 | W126: 0 | X126: 0 | Y126: 0 | Z126: 0 | AA126: 8320478 | AB126: 8320478 | AC126: 0 | AD126: 0 | AE126: 0 | AF126: 0 | AG126: 0 | AH126: 0 | AI126: 0 | AJ126: 0 | AK126: 0 | AL126: 0 | AM126: 0 | AN126: 328520 | AO126: 328520 | AP126: 0 | AQ126: 0 | AR126: 0 | AS126: 0 | AT126: 0 | AU126: 0 | AV126: 5262 | AW126: 5262 | AX126: 5917 | AY126: 5917 | AZ126: 6099 | BA126: 6646 | BB126: 6646 | BC126: 0 | BD126: 0 | BE126: 0 | BF126: 5114 | BG126: 5114 | BH126: 5114 | BI126: 5114 | BJ126: 6540 | BK126: 6540 | BL126: 6540 | BM126: 6540 | BN126: 6540 | BO126: 6540 | BP126: 0 | BQ126: 0 | BR126: 0 | BS126: 0 | BT126: 0 | BU126: 0 | BV126: 0 | BW126: 0 | BX126: 0 | BY126: 0 | BZ126: 0 | CA126: 0 | CB126: 0
B127: SERVIU Coquimbo | C127: 0 | D127: 0 | E127: 0 | F127: 0 | G127: 0 | H127: 736 | I127: 736 | J127: 1630685 | K127: 1635209 | L127: 1635209 | M127: 1635209 | N127: 1662728 | O127: 1662728 | P127: 0 | Q127: 0 | R127: 0 | S127: 0 | T127: 0 | U127: 0 | V127: 0 | W127: 0 | X127: 0 | Y127: 0 | Z127: 0 | AA127: 25569663 | AB127: 25569663 | AC127: 0 | AD127: 0 | AE127: 0 | AF127: 0 | AG127: 0 | AH127: 0 | AI127: 0 | AJ127: 0 | AK127: 0 | AL127: 0 | AM127: 0 | AN127: 0 | AO127: 0 | AP127: 0 | AQ127: 0 | AR127: 0 | AS127: 0 | AT127: 0 | AU127: 0 | AV127: 6055707 | AW127: 6055707 | AX127: 6062238 | AY127: 6062238 | AZ127: 6065142 | BA127: 6065343 | BB127: 6065343 | BC127: 0 | BD127: 0 | BE127: 0 | BF127: 0 | BG127: 0 | BH127: 0 | BI127: 0 | BJ127: 4873 | BK127: 4873 | BL127: 4873 | BM127: 5880 | BN127: 6023 | BO127: 6023 | BP127: 0 | BQ127: 0 | BR127: 0 | BS127: 0 | BT127: 0 | BU127: 0 | BV127: 0 | BW127: 0 | BX127: 0 | BY127: 0 | BZ127: 0 | CA127: 0 | CB127: 0
B128: SERVIU Valparaíso | C128: 0 | D128: 0 | E128: 356 | F128: 356 | G128: 356 | H128: 1252 | I128: 2012 | J128: 2012 | K128: 10731 | L128: 10805 | M128: 11093 | N128: 1985450 | O128: 1985450 | P128: 0 | Q128: 0 | R128: 0 | S128: 0 | T128: 0 | U128: 0 | V128: 0 | W128: 0 | X128: 0 | Y128: 0 | Z128: 0 | AA128: 16845167 | AB128: 16845167 | AC128: 0 | AD128: 0 | AE128: 0 | AF128: 0 | AG128: 0 | AH128: 0 | AI128: 0 | AJ128: 0 | AK128: 0 | AL128: 0 | AM128: 0 | AN128: 3984477 | AO128: 3984477 | AP128: 0 | AQ128: 0 | AR128: 0 | AS128: 0 | AT128: 0 | AU128: 0 | AV128: 0 | AW128: 15805 | AX128: 16757 | AY128: 18403 | AZ128: 20037 | BA128: 21833 | BB128: 21833 | BC128: 0 | BD128: 0 | BE128: 2894 | BF128: 2894 | BG128: 2894 | BH128: 6167 | BI128: 6167 | BJ128: 6167 | BK128: 7132 | BL128: 7132 | BM128: 7132 | BN128: 10998036 | BO128: 10998036 | BP128: 0 | BQ128: 0 | BR128: 0 | BS128: 0 | BT128: 0 | BU128: 0 | BV128: 0 | BW128: 0 | BX128: 0 | BY128: 0 | BZ128: 0 | CA128: 0 | CB128: 0
...
