Workbook

Sheet Dashboard
B2: MINISTERIO DE OBRAS PÚBLICAS — DASHBOARD DE INVERSIÓN Y EJECUCIÓN PRESUPUESTARIA
B3: Visualizador Analítico Interactivo Tabla a Tabla | Subtítulos 31, 29, 33 y Consolidado Total | Cifras en miles de pesos ($)
B4: AÑO SELECCIONADO: | C4: 2024 | D4: COBERTURA TEMPORAL: | F4: 2021 - 2026 (Ene - Dic) | H4: UNIDAD MONETARIA: | J4: Miles de $ Corrientes (DIPRES)
B6: PRESUPUESTO LEY (INICIAL) | D6: PRESUPUESTO VIGENTE | F6: EJECUCIÓN ACUMULADA | H6: % CUMPLIMIENTO PRESUPUESTARIO | J6: SALDO POR EJECUTAR
B7: =D17 -> 2942161253 | D7: =E17 -> 2330868371 | F7: =F17 -> 2321713289 | H7: =H17 -> 0.99607224 | J7: =G17 -> 9155082
B9: Aprobado Ley de Presupuesto | D9: Presupuesto anual actualizado | F9: Total devengado en el ejercicio | H9: Ejecución devengada / Presupuesto vigente | J9: Monto disponible no devengado
B11: TABLA 1: RESUMEN CONSOLIDADO POR SUBTÍTULO PRESUPUESTARIO
B13: Subtítulo Presupuestario | C13: Cód. | D13: Presupuesto Ley | E13: Presupuesto Vigente | F13: Ejecución Acumulada | G13: Saldo por Ejecutar | H13: % Ejecución | I13: % Participación
B14: Subtítulo 31 – Iniciativas de Inversión | C14: 31 | D14: =INDEX(MOP_Mes_Corriente!$1:$161, 14, 3 + ($C$4 - 2021)*13 + 12) -> 2933512941 | E14: =INDEX(MOP_Mes_Corriente!$1:$161, 26, 3 + ($C$4 - 2021)*13 + 12) -> 2323820848 | F14: =INDEX(MOP_Mes_Corriente!$1:$161, 38, 3 + ($C$4 - 2021)*13 + 12) -> 2314939413 | G14: =E14 - F14 -> 8881435 | H14: =IF(E14>0, F14/E14, 0) -> 0.99617809 | I14: =IF($E$17>0, E14/$E$17, 0) -> 0.99697644
B15: Subtítulo 29 – Activos No Financieros | C15: 29 | D15: =INDEX(MOP_Mes_Corriente!$1:$161, 53, 3 + ($C$4 - 2021)*13 + 12) -> 8648312 | E15: =INDEX(MOP_Mes_Corriente!$1:$161, 65, 3 + ($C$4 - 2021)*13 + 12) -> 7047523 | F15: =INDEX(MOP_Mes_Corriente!$1:$161, 77, 3 + ($C$4 - 2021)*13 + 12) -> 6773876 | G15: =E15 - F15 -> 273647 | H15: =IF(E15>0, F15/E15, 0) -> 0.96117118 | I15: =IF($E$17>0, E15/$E$17, 0) -> 0.0030235611
B16: Subtítulo 33 – Transferencias de Capital | C16: 33 | D16: =INDEX(MOP_Mes_Corriente!$1:$161, 92, 3 + ($C$4 - 2021)*13 + 12) -> 0 | E16: =INDEX(MOP_Mes_Corriente!$1:$161, 104, 3 + ($C$4 - 2021)*13 + 12) -> 0 | F16: =INDEX(MOP_Mes_Corriente!$1:$161, 116, 3 + ($C$4 - 2021)*13 + 12) -> 0 | G16: =E16 - F16 -> 0 | H16: =IF(E16>0, F16/E16, 0) -> 0 | I16: =IF($E$17>0, E16/$E$17, 0) -> 0
B17: TOTAL INVERSIÓN MOP (31 + 29 + 33) | C17: TOTAL | D17: =SUM(D14:D16) -> 2942161253 | E17: =SUM(E14:E16) -> 2330868371 | F17: =SUM(F14:F16) -> 2321713289 | G17: =E17 - F17 -> 9155082 | H17: =IF(E17>0, F17/E17, 0) -> 0.99607224 | I17: =SUM(I14:I16) -> 1
B19: TABLA 2: DESGLOSE COMPLETO POR PROGRAMA / DIRECCIÓN (AÑO SELECCIONADO)
B21: Dirección / Programa | C21: Subt. 31 Vigente | D21: Subt. 31 Ejecución | E21: Subt. 29 Vigente | F21: Subt. 29 Ejecución | G21: Subt. 33 Vigente | H21: Subt. 33 Ejecución | I21: Total Vigente | J21: Total Ejecución | K21: Saldo | L21: % Ejecución | M21: % Part. MOP
B22: Dirección de Vialidad | C22: =INDEX(MOP_Mes_Corriente!$1:$161, 20, 3 + ($C$4 - 2021)*13 + 12) -> 1608652526 | D22: =INDEX(MOP_Mes_Corriente!$1:$161, 32, 3 + ($C$4 - 2021)*13 + 12) -> 1603559540 | E22: =INDEX(MOP_Mes_Corriente!$1:$161, 59, 3 + ($C$4 - 2021)*13 + 12) -> 1135861 | F22: =INDEX(MOP_Mes_Corriente!$1:$161, 71, 3 + ($C$4 - 2021)*13 + 12) -> 1123525 | G22: =INDEX(MOP_Mes_Corriente!$1:$161, 98, 3 + ($C$4 - 2021)*13 + 12) -> 0 | H22: =INDEX(MOP_Mes_Corriente!$1:$161, 110, 3 + ($C$4 - 2021)*13 + 12) -> 0 | I22: =C22 + E22 + G22 -> 1609788387 | J22: =D22 + F22 + H22 -> 1604683065 | K22: =I22 - J22 -> 5105322 | L22: =IF(I22>0, J22/I22, 0) -> 0.99682858 | M22: =IF($I$28>0, I22/$I$28, 0) -> 0.69063891
B23: Dirección de Obras Hidráulicas | C23: =INDEX(MOP_Mes_Corriente!$1:$161, 21, 3 + ($C$4 - 2021)*13 + 12) -> 244313644 | D23: =INDEX(MOP_Mes_Corriente!$1:$161, 33, 3 + ($C$4 - 2021)*13 + 12) -> 243896208 | E23: =INDEX(MOP_Mes_Corriente!$1:$161, 60, 3 + ($C$4 - 2021)*13 + 12) -> 913626 | F23: =INDEX(MOP_Mes_Corriente!$1:$161, 72, 3 + ($C$4 - 2021)*13 + 12) -> 899916 | G23: =INDEX(MOP_Mes_Corriente!$1:$161, 99, 3 + ($C$4 - 2021)*13 + 12) -> 0 | H23: =INDEX(MOP_Mes_Corriente!$1:$161, 111, 3 + ($C$4 - 2021)*13 + 12) -> 0 | I23: =C23 + E23 + G23 -> 245227270 | J23: =D23 + F23 + H23 -> 244796124 | K23: =I23 - J23 -> 431146 | L23: =IF(I23>0, J23/I23, 0) -> 0.99824185 | M23: =IF($I$28>0, I23/$I$28, 0) -> 0.10520855
B24: Subdirección de APR | C24: =INDEX(MOP_Mes_Corriente!$1:$161, 22, 3 + ($C$4 - 2021)*13 + 12) -> 192186387 | D24: =INDEX(MOP_Mes_Corriente!$1:$161, 34, 3 + ($C$4 - 2021)*13 + 12) -> 189747396 | E24: =INDEX(MOP_Mes_Corriente!$1:$161, 61, 3 + ($C$4 - 2021)*13 + 12) -> 636104 | F24: =INDEX(MOP_Mes_Corriente!$1:$161, 73, 3 + ($C$4 - 2021)*13 + 12) -> 612897 | G24: =INDEX(MOP_Mes_Corriente!$1:$161, 100, 3 + ($C$4 - 2021)*13 + 12) -> 0 | H24: =INDEX(MOP_Mes_Corriente!$1:$161, 112, 3 + ($C$4 - 2021)*13 + 12) -> 0 | I24: =C24 + E24 + G24 -> 192822491 | J24: =D24 + F24 + H24 -> 190360293 | K24: =I24 - J24 -> 2462198 | L24: =IF(I24>0, J24/I24, 0) -> 0.98723075 | M24: =IF($I$28>0, I24/$I$28, 0) -> 0.082725603
B25: Dirección de Obras Portuarias | C25: =INDEX(MOP_Mes_Corriente!$1:$161, 23, 3 + ($C$4 - 2021)*13 + 12) -> 123682417 | D25: =INDEX(MOP_Mes_Corriente!$1:$161, 35, 3 + ($C$4 - 2021)*13 + 12) -> 122976500 | E25: =INDEX(MOP_Mes_Corriente!$1:$161, 62, 3 + ($C$4 - 2021)*13 + 12) -> 1731272 | F25: =INDEX(MOP_Mes_Corriente!$1:$161, 74, 3 + ($C$4 - 2021)*13 + 12) -> 1508486 | G25: =INDEX(MOP_Mes_Corriente!$1:$161, 101, 3 + ($C$4 - 2021)*13 + 12) -> 0 | H25: =INDEX(MOP_Mes_Corriente!$1:$161, 113, 3 + ($C$4 - 2021)*13 + 12) -> 0 | I25: =C25 + E25 + G25 -> 125413689 | J25: =D25 + F25 + H25 -> 124484986 | K25: =I25 - J25 -> 928703 | L25: =IF(I25>0, J25/I25, 0) -> 0.99259488 | M25: =IF($I$28>0, I25/$I$28, 0) -> 0.053805565
B26: Dirección de Aeropuertos | C26: =INDEX(MOP_Mes_Corriente!$1:$161, 24, 3 + ($C$4 - 2021)*13 + 12) -> 121300022 | D26: =INDEX(MOP_Mes_Corriente!$1:$161, 36, 3 + ($C$4 - 2021)*13 + 12) -> 121236421 | E26: =INDEX(MOP_Mes_Corriente!$1:$161, 63, 3 + ($C$4 - 2021)*13 + 12) -> 1998403 | F26: =INDEX(MOP_Mes_Corriente!$1:$161, 75, 3 + ($C$4 - 2021)*13 + 12) -> 1997225 | G26: =INDEX(MOP_Mes_Corriente!$1:$161, 102, 3 + ($C$4 - 2021)*13 + 12) -> 0 | H26: =INDEX(MOP_Mes_Corriente!$1:$161, 114, 3 + ($C$4 - 2021)*13 + 12) -> 0 | I26: =C26 + E26 + G26 -> 123298425 | J26: =D26 + F26 + H26 -> 123233646 | K26: =I26 - J26 -> 64779 | L26: =IF(I26>0, J26/I26, 0) -> 0.99947462 | M26: =IF($I$28>0, I26/$I$28, 0) -> 0.052898064
B27: Dirección de Arquitectura | C27: =INDEX(MOP_Mes_Corriente!$1:$161, 25, 3 + ($C$4 - 2021)*13 + 12) -> 33685852 | D27: =INDEX(MOP_Mes_Corriente!$1:$161, 37, 3 + ($C$4 - 2021)*13 + 12) -> 33523348 | E27: =INDEX(MOP_Mes_Corriente!$1:$161, 64, 3 + ($C$4 - 2021)*13 + 12) -> 632257 | F27: =INDEX(MOP_Mes_Corriente!$1:$161, 76, 3 + ($C$4 - 2021)*13 + 12) -> 631827 | G27: =INDEX(MOP_Mes_Corriente!$1:$161, 103, 3 + ($C$4 - 2021)*13 + 12) -> 0 | H27: =INDEX(MOP_Mes_Corriente!$1:$161, 115, 3 + ($C$4 - 2021)*13 + 12) -> 0 | I27: =C27 + E27 + G27 -> 34318109 | J27: =D27 + F27 + H27 -> 34155175 | K27: =I27 - J27 -> 162934 | L27: =IF(I27>0, J27/I27, 0) -> 0.99525224 | M27: =IF($I$28>0, I27/$I$28, 0) -> 0.014723315
B28: TOTAL MOP | C28: =SUM(C22:C27) -> 2323820848 | D28: =SUM(D22:D27) -> 2314939413 | E28: =SUM(E22:E27) -> 7047523 | F28: =SUM(F22:F27) -> 6773876 | G28: =SUM(G22:G27) -> 0 | H28: =SUM(H22:H27) -> 0 | I28: =SUM(I22:I27) -> 2330868371 | J28: =SUM(J22:J27) -> 2321713289 | K28: =SUM(K22:K27) -> 9155082 | L28: =IF(I28>0, J28/I28, 0) -> 0.99607224 | M28: =SUM(M22:M27) -> 1
B30: TABLA 3: EVOLUCIÓN MENSUAL DEL AÑO SELECCIONADO (ENERO A DICIEMBRE)
B32: Concepto / Mes | C32: Ene | D32: Feb | E32: Mar | F32: Abr | G32: May | H32: Jun | I32: Jul | J32: Ago | K32: Sep | L32: Oct | M32: Nov | N32: Dic | O32: Cierre Total
B33: Presupuesto Ley | C33: =INDEX(MOP_Mes_Corriente!$1:$161, 14, 3 + ($C$4 - 2021)*13 + 0) + INDEX(MOP_Mes_Corriente!$1:$161, 53, 3 + ($C$4 - 2021)*13 + 0) + INDEX(MOP_Mes_Corriente!$1:$161, 92, 3 + ($C$4 - 2021)*13 + 0) -> 2942161253 | D33: =INDEX(MOP_Mes_Corriente!$1:$161, 14, 3 + ($C$4 - 2021)*13 + 1) + INDEX(MOP_Mes_Corriente!$1:$161, 53, 3 + ($C$4 - 2021)*13 + 1) + INDEX(MOP_Mes_Corriente!$1:$161, 92, 3 + ($C$4 - 2021)*13 + 1) -> 2942161253 | E33: =INDEX(MOP_Mes_Corriente!$1:$161, 14, 3 + ($C$4 - 2021)*13 + 2) + INDEX(MOP_Mes_Corriente!$1:$161, 53, 3 + ($C$4 - 2021)*13 + 2) + INDEX(MOP_Mes_Corriente!$1:$161, 92, 3 + ($C$4 - 2021)*13 + 2) -> 2942161253 | F33: =INDEX(MOP_Mes_Corriente!$1:$161, 14, 3 + ($C$4 - 2021)*13 + 3) + INDEX(MOP_Mes_Corriente!$1:$161, 53, 3 + ($C$4 - 2021)*13 + 3) + INDEX(MOP_Mes_Corriente!$1:$161, 92, 3 + ($C$4 - 2021)*13 + 3) -> 2942161253 | G33: =INDEX(MOP_Mes_Corriente!$1:$161, 14, 3 + ($C$4 - 2021)*13 + 4) + INDEX(MOP_Mes_Corriente!$1:$161, 53, 3 + ($C$4 - 2021)*13 + 4) + INDEX(MOP_Mes_Corriente!$1:$161, 92, 3 + ($C$4 - 2021)*13 + 4) -> 2942161253 | H33: =INDEX(MOP_Mes_Corriente!$1:$161, 14, 3 + ($C$4 - 2021)*13 + 5) + INDEX(MOP_Mes_Corriente!$1:$161, 53, 3 + ($C$4 - 2021)*13 + 5) + INDEX(MOP_Mes_Corriente!$1:$161, 92, 3 + ($C$4 - 2021)*13 + 5) -> 2942161253 | I33: =INDEX(MOP_Mes_Corriente!$1:$161, 14, 3 + ($C$4 - 2021)*13 + 6) + INDEX(MOP_Mes_Corriente!$1:$161, 53, 3 + ($C$4 - 2021)*13 + 6) + INDEX(MOP_Mes_Corriente!$1:$161, 92, 3 + ($C$4 - 2021)*13 + 6) -> 2942161253 | J33: =INDEX(MOP_Mes_Corriente!$1:$161, 14, 3 + ($C$4 - 2021)*13 + 7) + INDEX(MOP_Mes_Corriente!$1:$161, 53, 3 + ($C$4 - 2021)*13 + 7) + INDEX(MOP_Mes_Corriente!$1:$161, 92, 3 + ($C$4 - 2021)*13 + 7) -> 2942161253 | K33: =INDEX(MOP_Mes_Corriente!$1:$161, 14, 3 + ($C$4 - 2021)*13 + 8) + INDEX(MOP_Mes_Corriente!$1:$161, 53, 3 + ($C$4 - 2021)*13 + 8) + INDEX(MOP_Mes_Corriente!$1:$161, 92, 3 + ($C$4 - 2021)*13 + 8) -> 2942161253 | L33: =INDEX(MOP_Mes_Corriente!$1:$161, 14, 3 + ($C$4 - 2021)*13 + 9) + INDEX(MOP_Mes_Corriente!$1:$161, 53, 3 + ($C$4 - 2021)*13 + 9) + INDEX(MOP_Mes_Corriente!$1:$161, 92, 3 + ($C$4 - 2021)*13 + 9) -> 2942161253 | M33: =INDEX(MOP_Mes_Corriente!$1:$161, 14, 3 + ($C$4 - 2021)*13 + 10) + INDEX(MOP_Mes_Corriente!$1:$161, 53, 3 + ($C$4 - 2021)*13 + 10) + INDEX(MOP_Mes_Corriente!$1:$161, 92, 3 + ($C$4 - 2021)*13 + 10) -> 2942161253 | N33: =INDEX(MOP_Mes_Corriente!$1:$161, 14, 3 + ($C$4 - 2021)*13 + 11) + INDEX(MOP_Mes_Corriente!$1:$161, 53, 3 + ($C$4 - 2021)*13 + 11) + INDEX(MOP_Mes_Corriente!$1:$161, 92, 3 + ($C$4 - 2021)*13 + 11) -> 2942161253 | O33: =INDEX(MOP_Mes_Corriente!$1:$161, 14, 3 + ($C$4 - 2021)*13 + 12) + INDEX(MOP_Mes_Corriente!$1:$161, 53, 3 + ($C$4 - 2021)*13 + 12) + INDEX(MOP_Mes_Corriente!$1:$161, 92, 3 + ($C$4 - 2021)*13 + 12) -> 2942161253
B34: Presupuesto Vigente | C34: =INDEX(MOP_Mes_Corriente!$1:$161, 26, 3 + ($C$4 - 2021)*13 + 0) + INDEX(MOP_Mes_Corriente!$1:$161, 65, 3 + ($C$4 - 2021)*13 + 0) + INDEX(MOP_Mes_Corriente!$1:$161, 104, 3 + ($C$4 - 2021)*13 + 0) -> 2942161253 | D34: =INDEX(MOP_Mes_Corriente!$1:$161, 26, 3 + ($C$4 - 2021)*13 + 1) + INDEX(MOP_Mes_Corriente!$1:$161, 65, 3 + ($C$4 - 2021)*13 + 1) + INDEX(MOP_Mes_Corriente!$1:$161, 104, 3 + ($C$4 - 2021)*13 + 1) -> 2942161253 | E34: =INDEX(MOP_Mes_Corriente!$1:$161, 26, 3 + ($C$4 - 2021)*13 + 2) + INDEX(MOP_Mes_Corriente!$1:$161, 65, 3 + ($C$4 - 2021)*13 + 2) + INDEX(MOP_Mes_Corriente!$1:$161, 104, 3 + ($C$4 - 2021)*13 + 2) -> 2872224418 | F34: =INDEX(MOP_Mes_Corriente!$1:$161, 26, 3 + ($C$4 - 2021)*13 + 3) + INDEX(MOP_Mes_Corriente!$1:$161, 65, 3 + ($C$4 - 2021)*13 + 3) + INDEX(MOP_Mes_Corriente!$1:$161, 104, 3 + ($C$4 - 2021)*13 + 3) -> 2789233638 | G34: =INDEX(MOP_Mes_Corriente!$1:$161, 26, 3 + ($C$4 - 2021)*13 + 4) + INDEX(MOP_Mes_Corriente!$1:$161, 65, 3 + ($C$4 - 2021)*13 + 4) + INDEX(MOP_Mes_Corriente!$1:$161, 104, 3 + ($C$4 - 2021)*13 + 4) -> 2788989293 | H34: =INDEX(MOP_Mes_Corriente!$1:$161, 26, 3 + ($C$4 - 2021)*13 + 5) + INDEX(MOP_Mes_Corriente!$1:$161, 65, 3 + ($C$4 - 2021)*13 + 5) + INDEX(MOP_Mes_Corriente!$1:$161, 104, 3 + ($C$4 - 2021)*13 + 5) -> 2768911293 | I34: =INDEX(MOP_Mes_Corriente!$1:$161, 26, 3 + ($C$4 - 2021)*13 + 6) + INDEX(MOP_Mes_Corriente!$1:$161, 65, 3 + ($C$4 - 2021)*13 + 6) + INDEX(MOP_Mes_Corriente!$1:$161, 104, 3 + ($C$4 - 2021)*13 + 6) -> 2768911293 | J34: =INDEX(MOP_Mes_Corriente!$1:$161, 26, 3 + ($C$4 - 2021)*13 + 7) + INDEX(MOP_Mes_Corriente!$1:$161, 65, 3 + ($C$4 - 2021)*13 + 7) + INDEX(MOP_Mes_Corriente!$1:$161, 104, 3 + ($C$4 - 2021)*13 + 7) -> 2765121527 | K34: =INDEX(MOP_Mes_Corriente!$1:$161, 26, 3 + ($C$4 - 2021)*13 + 8) + INDEX(MOP_Mes_Corriente!$1:$161, 65, 3 + ($C$4 - 2021)*13 + 8) + INDEX(MOP_Mes_Corriente!$1:$161, 104, 3 + ($C$4 - 2021)*13 + 8) -> 2763486063 | L34: =INDEX(MOP_Mes_Corriente!$1:$161, 26, 3 + ($C$4 - 2021)*13 + 9) + INDEX(MOP_Mes_Corriente!$1:$161, 65, 3 + ($C$4 - 2021)*13 + 9) + INDEX(MOP_Mes_Corriente!$1:$161, 104, 3 + ($C$4 - 2021)*13 + 9) -> 2757523660 | M34: =INDEX(MOP_Mes_Corriente!$1:$161, 26, 3 + ($C$4 - 2021)*13 + 10) + INDEX(MOP_Mes_Corriente!$1:$161, 65, 3 + ($C$4 - 2021)*13 + 10) + INDEX(MOP_Mes_Corriente!$1:$161, 104, 3 + ($C$4 - 2021)*13 + 10) -> 2716453128 | N34: =INDEX(MOP_Mes_Corriente!$1:$161, 26, 3 + ($C$4 - 2021)*13 + 11) + INDEX(MOP_Mes_Corriente!$1:$161, 65, 3 + ($C$4 - 2021)*13 + 11) + INDEX(MOP_Mes_Corriente!$1:$161, 104, 3 + ($C$4 - 2021)*13 + 11) -> 2330868371 | O34: =INDEX(MOP_Mes_Corriente!$1:$161, 26, 3 + ($C$4 - 2021)*13 + 12) + INDEX(MOP_Mes_Corriente!$1:$161, 65, 3 + ($C$4 - 2021)*13 + 12) + INDEX(MOP_Mes_Corriente!$1:$161, 104, 3 + ($C$4 - 2021)*13 + 12) -> 2330868371
B35: Ejecución Acumulada | C35: =INDEX(MOP_Mes_Corriente!$1:$161, 38, 3 + ($C$4 - 2021)*13 + 0) + INDEX(MOP_Mes_Corriente!$1:$161, 77, 3 + ($C$4 - 2021)*13 + 0) + INDEX(MOP_Mes_Corriente!$1:$161, 116, 3 + ($C$4 - 2021)*13 + 0) -> 10076 | D35: =INDEX(MOP_Mes_Corriente!$1:$161, 38, 3 + ($C$4 - 2021)*13 + 1) + INDEX(MOP_Mes_Corriente!$1:$161, 77, 3 + ($C$4 - 2021)*13 + 1) + INDEX(MOP_Mes_Corriente!$1:$161, 116, 3 + ($C$4 - 2021)*13 + 1) -> 158901130 | E35: =INDEX(MOP_Mes_Corriente!$1:$161, 38, 3 + ($C$4 - 2021)*13 + 2) + INDEX(MOP_Mes_Corriente!$1:$161, 77, 3 + ($C$4 - 2021)*13 + 2) + INDEX(MOP_Mes_Corriente!$1:$161, 116, 3 + ($C$4 - 2021)*13 + 2) -> 342245752 | F35: =INDEX(MOP_Mes_Corriente!$1:$161, 38, 3 + ($C$4 - 2021)*13 + 3) + INDEX(MOP_Mes_Corriente!$1:$161, 77, 3 + ($C$4 - 2021)*13 + 3) + INDEX(MOP_Mes_Corriente!$1:$161, 116, 3 + ($C$4 - 2021)*13 + 3) -> 535933925 | G35: =INDEX(MOP_Mes_Corriente!$1:$161, 38, 3 + ($C$4 - 2021)*13 + 4) + INDEX(MOP_Mes_Corriente!$1:$161, 77, 3 + ($C$4 - 2021)*13 + 4) + INDEX(MOP_Mes_Corriente!$1:$161, 116, 3 + ($C$4 - 2021)*13 + 4) -> 735766967 | H35: =INDEX(MOP_Mes_Corriente!$1:$161, 38, 3 + ($C$4 - 2021)*13 + 5) + INDEX(MOP_Mes_Corriente!$1:$161, 77, 3 + ($C$4 - 2021)*13 + 5) + INDEX(MOP_Mes_Corriente!$1:$161, 116, 3 + ($C$4 - 2021)*13 + 5) -> 1103900218 | I35: =INDEX(MOP_Mes_Corriente!$1:$161, 38, 3 + ($C$4 - 2021)*13 + 6) + INDEX(MOP_Mes_Corriente!$1:$161, 77, 3 + ($C$4 - 2021)*13 + 6) + INDEX(MOP_Mes_Corriente!$1:$161, 116, 3 + ($C$4 - 2021)*13 + 6) -> 1232252883 | J35: =INDEX(MOP_Mes_Corriente!$1:$161, 38, 3 + ($C$4 - 2021)*13 + 7) + INDEX(MOP_Mes_Corriente!$1:$161, 77, 3 + ($C$4 - 2021)*13 + 7) + INDEX(MOP_Mes_Corriente!$1:$161, 116, 3 + ($C$4 - 2021)*13 + 7) -> 1374995854 | K35: =INDEX(MOP_Mes_Corriente!$1:$161, 38, 3 + ($C$4 - 2021)*13 + 8) + INDEX(MOP_Mes_Corriente!$1:$161, 77, 3 + ($C$4 - 2021)*13 + 8) + INDEX(MOP_Mes_Corriente!$1:$161, 116, 3 + ($C$4 - 2021)*13 + 8) -> 1567303306 | L35: =INDEX(MOP_Mes_Corriente!$1:$161, 38, 3 + ($C$4 - 2021)*13 + 9) + INDEX(MOP_Mes_Corriente!$1:$161, 77, 3 + ($C$4 - 2021)*13 + 9) + INDEX(MOP_Mes_Corriente!$1:$161, 116, 3 + ($C$4 - 2021)*13 + 9) -> 1765889793 | M35: =INDEX(MOP_Mes_Corriente!$1:$161, 38, 3 + ($C$4 - 2021)*13 + 10) + INDEX(MOP_Mes_Corriente!$1:$161, 77, 3 + ($C$4 - 2021)*13 + 10) + INDEX(MOP_Mes_Corriente!$1:$161, 116, 3 + ($C$4 - 2021)*13 + 10) -> 2025828192 | N35: =INDEX(MOP_Mes_Corriente!$1:$161, 38, 3 + ($C$4 - 2021)*13 + 11) + INDEX(MOP_Mes_Corriente!$1:$161, 77, 3 + ($C$4 - 2021)*13 + 11) + INDEX(MOP_Mes_Corriente!$1:$161, 116, 3 + ($C$4 - 2021)*13 + 11) -> 2321713289 | O35: =INDEX(MOP_Mes_Corriente!$1:$161, 38, 3 + ($C$4 - 2021)*13 + 12) + INDEX(MOP_Mes_Corriente!$1:$161, 77, 3 + ($C$4 - 2021)*13 + 12) + INDEX(MOP_Mes_Corriente!$1:$161, 116, 3 + ($C$4 - 2021)*13 + 12) -> 2321713289
B36: % Avance Ejecución | C36: =IF(C34>0, C35/C34, 0) -> 3.4246933e-06 | D36: =IF(D34>0, D35/D34, 0) -> 0.054008301 | E36: =IF(E34>0, E35/E34, 0) -> 0.11915704 | F36: =IF(F34>0, F35/F34, 0) -> 0.19214379 | G36: =IF(G34>0, G35/G34, 0) -> 0.26381133 | H36: =IF(H34>0, H35/H34, 0) -> 0.39867663 | I36: =IF(I34>0, I35/I34, 0) -> 0.44503155 | J36: =IF(J34>0, J35/J34, 0) -> 0.49726417 | ... O36: =IF(O34>0, O35/O34, 0) -> 0.99607224
B38: TABLA 4: COMPARATIVA HISTÓRICA MULTIANUAL (2021 - 2026)
B40: Año | C40: Presupuesto Ley | D40: Presupuesto Vigente | E40: Ejecución Acumulada | F40: Saldo por Ejecutar | G40: % Ejecución | H40: Crec. Vigente (YoY) | I40: Crec. Ejecución (YoY)
B41: 2021 | C41: =MOP_Mes_Corriente!O14 + MOP_Mes_Corriente!O53 + MOP_Mes_Corriente!O92 -> 2326773489 | D41: =MOP_Mes_Corriente!O26 + MOP_Mes_Corriente!O65 + MOP_Mes_Corriente!O104 -> 1577529365 | E41: =MOP_Mes_Corriente!O38 + MOP_Mes_Corriente!O77 + MOP_Mes_Corriente!O116 -> 1391673062 | F41: =D41 - E41 -> 185856303 | G41: =IF(D41>0, E41/D41, 0) -> 0.8821852 | H41: - | I41: -
B42: 2022 | C42: =MOP_Mes_Corriente!AB14 + MOP_Mes_Corriente!AB53 + MOP_Mes_Corriente!AB92 -> 2620025909 | D42: =MOP_Mes_Corriente!AB26 + MOP_Mes_Corriente!AB65 + MOP_Mes_Corriente!AB104 -> 1358582828 | E42: =MOP_Mes_Corriente!AB38 + MOP_Mes_Corriente!AB77 + MOP_Mes_Corriente!AB116 -> 1340723690 | F42: =D42 - E42 -> 17859138 | G42: =IF(D42>0, E42/D42, 0) -> 0.98685458 | H42: =IF(D41>0, (D42-D41)/D41, 0) -> -0.13879078 | I42: =IF(E41>0, (E42-E41)/E41, 0) -> -0.036610159
B43: 2023 | C43: =MOP_Mes_Corriente!AO14 + MOP_Mes_Corriente!AO53 + MOP_Mes_Corriente!AO92 -> 2835156480 | D43: =MOP_Mes_Corriente!AO26 + MOP_Mes_Corriente!AO65 + MOP_Mes_Corriente!AO104 -> 2132837420 | E43: =MOP_Mes_Corriente!AO38 + MOP_Mes_Corriente!AO77 + MOP_Mes_Corriente!AO116 -> 2106371463 | F43: =D43 - E43 -> 26465957 | G43: =IF(D43>0, E43/D43, 0) -> 0.9875912 | H43: =IF(D42>0, (D43-D42)/D42, 0) -> 0.5698987 | I43: =IF(E42>0, (E43-E42)/E42, 0) -> 0.57107052
B44: 2024 | C44: =MOP_Mes_Corriente!BB14 + MOP_Mes_Corriente!BB53 + MOP_Mes_Corriente!BB92 -> 2942161253 | D44: =MOP_Mes_Corriente!BB26 + MOP_Mes_Corriente!BB65 + MOP_Mes_Corriente!BB104 -> 2330868371 | E44: =MOP_Mes_Corriente!BB38 + MOP_Mes_Corriente!BB77 + MOP_Mes_Corriente!BB116 -> 2321713289 | F44: =D44 - E44 -> 9155082 | G44: =IF(D44>0, E44/D44, 0) -> 0.99607224 | H44: =IF(D43>0, (D44-D43)/D43, 0) -> 0.092848592 | I44: =IF(E43>0, (E44-E43)/E43, 0) -> 0.10223355
B45: 2025 | C45: =MOP_Mes_Corriente!BO14 + MOP_Mes_Corriente!BO53 + MOP_Mes_Corriente!BO92 -> 3058423954 | D45: =MOP_Mes_Corriente!BO26 + MOP_Mes_Corriente!BO65 + MOP_Mes_Corriente!BO104 -> 2814546937 | E45: =MOP_Mes_Corriente!BO38 + MOP_Mes_Corriente!BO77 + MOP_Mes_Corriente!BO116 -> 2769768945 | F45: =D45 - E45 -> 44777992 | G45: =IF(D45>0, E45/D45, 0) -> 0.98409052 | H45: =IF(D44>0, (D45-D44)/D44, 0) -> 0.20751003 | I45: =IF(E44>0, (E45-E44)/E44, 0) -> 0.19298492
B46: 2026 | C46: =MOP_Mes_Corriente!CB14 + MOP_Mes_Corriente!CB53 + MOP_Mes_Corriente!CB92 -> 2710709303 | D46: =MOP_Mes_Corriente!CB26 + MOP_Mes_Corriente!CB65 + MOP_Mes_Corriente!CB104 -> 2542855698 | E46: =MOP_Mes_Corriente!CB38 + MOP_Mes_Corriente!CB77 + MOP_Mes_Corriente!CB116 -> 1238260857 | F46: =D46 - E46 -> 1304594841 | G46: =IF(D46>0, E46/D46, 0) -> 0.48695679 | H46: =IF(D45>0, (D46-D45)/D45, 0) -> -0.096531074 | I46: =IF(E45>0, (E46-E45)/E45, 0) -> -0.55293713

Sheet MOP_Mes_Corriente
B1: Ministerio de Obras Públicas · Partida 12
B2: Miles de pesos · moneda corriente · montos devengados
B3: Subtítulo 31 — Iniciativas de Inversión
B5: Presupuesto Ley de Inversión en Infraestructura Pública del Ministerio de Obras Públicas, 2021-2026 (Subtítulo 31 — Iniciativas de Inversión, miles de pesos)
C6: 2021(1) | P6: 2022(1) | AC6: 2023 | AP6: 2024 | BC6: 2025 | BP6: 2026
B7: Programa | C7: Ene | D7: Feb | E7: Mar | F7: Abr | G7: May | H7: Jun | I7: Jul | J7: Ago | K7: Sep | L7: Oct | M7: Nov | N7: Dic | O7: Total 2021 | P7: Ene | Q7: Feb | R7: Mar | S7: Abr | T7: May | U7: Jun | V7: Jul | W7: Ago | X7: Sep | Y7: Oct | Z7: Nov | AA7: Dic | AB7: Total 2022 | AC7: Ene | AD7: Feb | AE7: Mar | AF7: Abr | AG7: May | AH7: Jun | AI7: Jul | AJ7: Ago | AK7: Sep | AL7: Oct | AM7: Nov | AN7: Dic | AO7: Total 2023 | AP7: Ene | AQ7: Feb | AR7: Mar | AS7: Abr | AT7: May | AU7: Jun | AV7: Jul | AW7: Ago | AX7: Sep | AY7: Oct | AZ7: Nov | BA7: Dic | BB7: Total 2024 | BC7: Ene | BD7: Feb | BE7: Mar | BF7: Abr | BG7: May | BH7: Jun | BI7: Jul | BJ7: Ago | BK7: Sep | BL7: Oct | BM7: Nov | BN7: Dic | BO7: Total 2025 | BP7: Ene | BQ7: Feb | BR7: Mar | BS7: Abr | BT7: May | BU7: Jun | BV7: Jul | BW7: Ago | BX7: Sep | BY7: Oct | BZ7: Nov | CA7: Dic | CB7: Total 2026
B8: Dirección de Vialidad | C8: =1224421462+380805877 -> 1605227339 | D8: =1224421462+380805877 -> 1605227339 | E8: =1224421462+380805877 -> 1605227339 | F8: =1224421462+380805877 -> 1605227339 | G8: =1224421462+380805877 -> 1605227339 | H8: =1224421462+380805877 -> 1605227339 | I8: =1224421462+380805877 -> 1605227339 | J8: =1224421462+380805877 -> 1605227339 | ... N8: =1224421462+380805877 -> 1605227339 | O8: =N8 -> 1605227339 | P8: =1220635546+581829225 -> 1802464771 | Q8: =1220635546+581829225 -> 1802464771 | R8: =1220635546+581829225 -> 1802464771 | S8: =1220635546+581829225 -> 1802464771 | T8: =1220635546+581829225 -> 1802464771 | U8: =1220635546+581829225 -> 1802464771 | V8: =1220635546+581829225 -> 1802464771 | W8: =1220635546+581829225 -> 1802464771 | ... AA8: =1220635546+581829225 -> 1802464771 | AB8: =AA8 -> 1802464771 | AC8: 1913855137 | AD8: 1913855137 | AE8: 1913855137 | AF8: 1913855137 | AG8: 1913855137 | AH8: 1913855137 | AI8: 1913855137 | AJ8: 1913855137 | AK8: 1913855137 | AL8: 1913855137 | AM8: 1913855137 | AN8: 1913855137 | AO8: =AN8 -> 1913855137 | AP8: 2012684680 | AQ8: 2012684680 | AR8: 2012684680 | AS8: 2012684680 | AT8: 2012684680 | AU8: 2012684680 | AV8: 2012684680 | AW8: 2012684680 | AX8: 2012684680 | AY8: 2012684680 | AZ8: 2012684680 | BA8: 2012684680 | BB8: =BA8 -> 2012684680 | BC8: 2083103023 | BD8: 2083103023 | BE8: 2083103023 | BF8: 2083103023 | BG8: 2083103023 | BH8: 2083103023 | BI8: 2083103023 | BJ8: 2083103023 | BK8: 2083103023 | BL8: 2083103023 | BM8: 2083103023 | BN8: 2083103023 | BO8: =BN8 -> 2083103023 | BP8: 1951485600 | BQ8: 1951485600 | BR8: 1951485600 | BS8: 1951485600 | BT8: 1951485600 | BU8: 1951485600 | BV8: 1951485600 | CB8: =BV8 -> 1951485600
B9: Dirección de Obras Hidráulicas | C9: =140801596+100700947 -> 241502543 | D9: =140801596+100700947 -> 241502543 | E9: =140801596+100700947 -> 241502543 | F9: =140801596+100700947 -> 241502543 | G9: =140801596+100700947 -> 241502543 | H9: =140801596+100700947 -> 241502543 | I9: =140801596+100700947 -> 241502543 | J9: =140801596+100700947 -> 241502543 | ... N9: =140801596+100700947 -> 241502543 | O9: =N9 -> 241502543 | P9: =147022684+130812721 -> 277835405 | Q9: =147022684+130812721 -> 277835405 | R9: =147022684+130812721 -> 277835405 | S9: =147022684+130812721 -> 277835405 | T9: =147022684+130812721 -> 277835405 | U9: =147022684+130812721 -> 277835405 | V9: =147022684+130812721 -> 277835405 | W9: =147022684+130812721 -> 277835405 | ... AA9: =147022684+130812721 -> 277835405 | AB9: =AA9 -> 277835405 | AC9: 293591805 | AD9: 293591805 | AE9: 293591805 | AF9: 293591805 | AG9: 293591805 | AH9: 293591805 | AI9: 293591805 | AJ9: 293591805 | AK9: 293591805 | AL9: 293591805 | AM9: 293591805 | AN9: 293591805 | AO9: =AN9 -> 293591805 | AP9: 295701947 | AQ9: 295701947 | AR9: 295701947 | AS9: 295701947 | AT9: 295701947 | AU9: 295701947 | AV9: 295701947 | AW9: 295701947 | AX9: 295701947 | AY9: 295701947 | AZ9: 295701947 | BA9: 295701947 | BB9: =BA9 -> 295701947 | BC9: 308121429 | BD9: 308121429 | BE9: 308121429 | BF9: 308121429 | BG9: 308121429 | BH9: 308121429 | BI9: 308121429 | BJ9: 308121429 | BK9: 308121429 | BL9: 308121429 | BM9: 308121429 | BN9: 308121429 | BO9: =BN9 -> 308121429 | BP9: 195906100 | BQ9: 195906100 | BR9: 195906100 | BS9: 195906100 | BT9: 195906100 | BU9: 195906100 | BV9: 195906100 | CB9: =BV9 -> 195906100
B10: Subdirección de APR | C10: =142048072+104543895 -> 246591967 | D10: =142048072+104543895 -> 246591967 | E10: =142048072+104543895 -> 246591967 | F10: =142048072+104543895 -> 246591967 | G10: =142048072+104543895 -> 246591967 | H10: =142048072+104543895 -> 246591967 | I10: =142048072+104543895 -> 246591967 | J10: =142048072+104543895 -> 246591967 | ... N10: =142048072+104543895 -> 246591967 | O10: =N10 -> 246591967 | P10: =148440561+129907392 -> 278347953 | Q10: =148440561+129907392 -> 278347953 | R10: =148440561+129907392 -> 278347953 | S10: =148440561+129907392 -> 278347953 | T10: =148440561+129907392 -> 278347953 | U10: =148440561+129907392 -> 278347953 | V10: =148440561+129907392 -> 278347953 | W10: =148440561+129907392 -> 278347953 | ... AA10: =148440561+129907392 -> 278347953 | AB10: =AA10 -> 278347953 | AC10: 295780655 | AD10: 295780655 | AE10: 295780655 | AF10: 295780655 | AG10: 295780655 | AH10: 295780655 | AI10: 295780655 | AJ10: 295780655 | AK10: 295780655 | AL10: 295780655 | AM10: 295780655 | AN10: 295780655 | AO10: =AN10 -> 295780655 | AP10: 315696642 | AQ10: 315696642 | AR10: 315696642 | AS10: 315696642 | AT10: 315696642 | AU10: 315696642 | AV10: 315696642 | AW10: 315696642 | AX10: 315696642 | AY10: 315696642 | AZ10: 315696642 | BA10: 315696642 | BB10: =BA10 -> 315696642 | BC10: 329603442 | BD10: 329603442 | BE10: 329603442 | BF10: 329603442 | BG10: 329603442 | BH10: 329603442 | BI10: 329603442 | BJ10: 329603442 | BK10: 329603442 | BL10: 329603442 | BM10: 329603442 | BN10: 329603442 | BO10: =BN10 -> 329603442 | BP10: 290113797 | BQ10: 290113797 | BR10: 290113797 | BS10: 290113797 | BT10: 290113797 | BU10: 290113797 | BV10: 290113797 | CB10: =BV10 -> 290113797
B11: Dirección de Obras Portuarias | C11: =73670723+10507533 -> 84178256 | D11: =73670723+10507533 -> 84178256 | E11: =73670723+10507533 -> 84178256 | F11: =73670723+10507533 -> 84178256 | G11: =73670723+10507533 -> 84178256 | H11: =73670723+10507533 -> 84178256 | I11: =73670723+10507533 -> 84178256 | J11: =73670723+10507533 -> 84178256 | ... N11: =73670723+10507533 -> 84178256 | O11: =N11 -> 84178256 | P11: =76882481+23172423 -> 100054904 | Q11: =76882481+23172423 -> 100054904 | R11: =76882481+23172423 -> 100054904 | S11: =76882481+23172423 -> 100054904 | T11: =76882481+23172423 -> 100054904 | U11: =76882481+23172423 -> 100054904 | V11: =76882481+23172423 -> 100054904 | W11: =76882481+23172423 -> 100054904 | ... AA11: =76882481+23172423 -> 100054904 | AB11: =AA11 -> 100054904 | AC11: 115171552 | AD11: 115171552 | AE11: 115171552 | AF11: 115171552 | AG11: 115171552 | AH11: 115171552 | AI11: 115171552 | AJ11: 115171552 | AK11: 115171552 | AL11: 115171552 | AM11: 115171552 | AN11: 115171552 | AO11: =AN11 -> 115171552 | AP11: 127117895 | AQ11: 127117895 | AR11: 127117895 | AS11: 127117895 | AT11: 127117895 | AU11: 127117895 | AV11: 127117895 | AW11: 127117895 | AX11: 127117895 | AY11: 127117895 | AZ11: 127117895 | BA11: 127117895 | BB11: =BA11 -> 127117895 | BC11: 125417585 | BD11: 125417585 | BE11: 125417585 | BF11: 125417585 | BG11: 125417585 | BH11: 125417585 | BI11: 125417585 | BJ11: 125417585 | BK11: 125417585 | BL11: 125417585 | BM11: 125417585 | BN11: 125417585 | BO11: =BN11 -> 125417585 | BP11: 109909690 | BQ11: 109909690 | BR11: 109909690 | BS11: 109909690 | BT11: 109909690 | BU11: 109909690 | BV11: 109909690 | CB11: =BV11 -> 109909690
B12: Dirección de Aeropuertos | C12: =60144148+46830346 -> 106974494 | D12: =60144148+46830346 -> 106974494 | E12: =60144148+46830346 -> 106974494 | F12: =60144148+46830346 -> 106974494 | G12: =60144148+46830346 -> 106974494 | H12: =60144148+46830346 -> 106974494 | I12: =60144148+46830346 -> 106974494 | J12: =60144148+46830346 -> 106974494 | ... N12: =60144148+46830346 -> 106974494 | O12: =N12 -> 106974494 | P12: =62797413+55033938 -> 117831351 | Q12: =62797413+55033938 -> 117831351 | R12: =62797413+55033938 -> 117831351 | S12: =62797413+55033938 -> 117831351 | T12: =62797413+55033938 -> 117831351 | U12: =62797413+55033938 -> 117831351 | V12: =62797413+55033938 -> 117831351 | W12: =62797413+55033938 -> 117831351 | ... AA12: =62797413+55033938 -> 117831351 | AB12: =AA12 -> 117831351 | AC12: 135318267 | AD12: 135318267 | AE12: 135318267 | AF12: 135318267 | AG12: 135318267 | AH12: 135318267 | AI12: 135318267 | AJ12: 135318267 | AK12: 135318267 | AL12: 135318267 | AM12: 135318267 | AN12: 135318267 | AO12: =AN12 -> 135318267 | AP12: 137741639 | AQ12: 137741639 | AR12: 137741639 | AS12: 137741639 | AT12: 137741639 | AU12: 137741639 | AV12: 137741639 | AW12: 137741639 | AX12: 137741639 | AY12: 137741639 | AZ12: 137741639 | BA12: 137741639 | BB12: =BA12 -> 137741639 | BC12: 141825431 | BD12: 141825431 | BE12: 141825431 | BF12: 141825431 | BG12: 141825431 | BH12: 141825431 | BI12: 141825431 | BJ12: 141825431 | BK12: 141825431 | BL12: 141825431 | BM12: 141825431 | BN12: 141825431 | BO12: =BN12 -> 141825431 | BP12: 127610750 | BQ12: 127610750 | BR12: 127610750 | BS12: 127610750 | BT12: 127610750 | BU12: 127610750 | BV12: 127610750 | CB12: =BV12 -> 127610750
B13: Dirección de Arquitectura | C13: =11904427+25061381 -> 36965808 | D13: =11904427+25061381 -> 36965808 | E13: =11904427+25061381 -> 36965808 | F13: =11904427+25061381 -> 36965808 | G13: =11904427+25061381 -> 36965808 | H13: =11904427+25061381 -> 36965808 | I13: =11904427+25061381 -> 36965808 | J13: =11904427+25061381 -> 36965808 | ... N13: =11904427+25061381 -> 36965808 | O13: =N13 -> 36965808 | P13: =8974172+32064677 -> 41038849 | Q13: =8974172+32064677 -> 41038849 | R13: =8974172+32064677 -> 41038849 | S13: =8974172+32064677 -> 41038849 | T13: =8974172+32064677 -> 41038849 | U13: =8974172+32064677 -> 41038849 | V13: =8974172+32064677 -> 41038849 | W13: =8974172+32064677 -> 41038849 | ... AA13: =8974172+32064677 -> 41038849 | AB13: =AA13 -> 41038849 | AC13: 37590026 | AD13: 37590026 | AE13: 37590026 | AF13: 37590026 | AG13: 37590026 | AH13: 37590026 | AI13: 37590026 | AJ13: 37590026 | AK13: 37590026 | AL13: 37590026 | AM13: 37590026 | AN13: 37590026 | AO13: =AN13 -> 37590026 | AP13: 44570138 | AQ13: 44570138 | AR13: 44570138 | AS13: 44570138 | AT13: 44570138 | AU13: 44570138 | AV13: 44570138 | AW13: 44570138 | AX13: 44570138 | AY13: 44570138 | AZ13: 44570138 | BA13: 44570138 | BB13: =BA13 -> 44570138 | BC13: 57109595 | BD13: 57109595 | BE13: 57109595 | BF13: 57109595 | BG13: 57109595 | BH13: 57109595 | BI13: 57109595 | BJ13: 57109595 | BK13: 57109595 | BL13: 57109595 | BM13: 57109595 | BN13: 57109595 | BO13: =BN13 -> 57109595 | BP13: 30479549 | BQ13: 30479549 | BR13: 30479549 | BS13: 30479549 | BT13: 30479549 | BU13: 30479549 | BV13: 30479549 | CB13: =BV13 -> 30479549
B14: Total | C14: =SUM(C8:C13) -> 2321440407 | D14: =SUM(D8:D13) -> 2321440407 | E14: =SUM(E8:E13) -> 2321440407 | F14: =SUM(F8:F13) -> 2321440407 | G14: =SUM(G8:G13) -> 2321440407 | H14: =SUM(H8:H13) -> 2321440407 | I14: =SUM(I8:I13) -> 2321440407 | J14: =SUM(J8:J13) -> 2321440407 | ... CB14: =SUM(CB8:CB13) -> 2705505486
B15: (1) Los años 2021 y 2022 incluyen el Presupuesto Ley del Subtítulo 30, Ítem 10. Fuente: elaboración propia, Dipres.
B17: Presupuesto Vigente de Inversión en Infraestructura Pública del Ministerio de Obras Públicas, 2021-2026 (Subtítulo 31 — Iniciativas de Inversión, miles de pesos)
C18: 2021(1) | P18: 2022(1) | AC18: 2023 | AP18: 2024 | BC18: 2025 | BP18: 2026
B19: Programa | C19: Ene | D19: Feb | E19: Mar | F19: Abr | G19: May | H19: Jun | I19: Jul | J19: Ago | K19: Sep | L19: Oct | M19: Nov | N19: Dic | O19: Total 2021 | P19: Ene | Q19: Feb | R19: Mar | S19: Abr | T19: May | U19: Jun | V19: Jul | W19: Ago | X19: Sep | Y19: Oct | Z19: Nov | AA19: Dic | AB19: Total 2022 | AC19: Ene | AD19: Feb | AE19: Mar | AF19: Abr | AG19: May | AH19: Jun | AI19: Jul | AJ19: Ago | AK19: Sep | AL19: Oct | AM19: Nov | AN19: Dic | AO19: Total 2023 | AP19: Ene | AQ19: Feb | AR19: Mar | AS19: Abr | AT19: May | AU19: Jun | AV19: Jul | AW19: Ago | AX19: Sep | AY19: Oct | AZ19: Nov | BA19: Dic | BB19: Total 2024 | BC19: Ene | BD19: Feb | BE19: Mar | BF19: Abr | BG19: May | BH19: Jun | BI19: Jul | BJ19: Ago | BK19: Sep | BL19: Oct | BM19: Nov | BN19: Dic | BO19: Total 2025 | BP19: Ene | BQ19: Feb | BR19: Mar | BS19: Abr | BT19: May | BU19: Jun | BV19: Jul | BW19: Ago | BX19: Sep | BY19: Oct | BZ19: Nov | CA19: Dic | CB19: Total 2026
B20: Dirección de Vialidad | C20: 1224421462 | D20: 1224421462 | E20: 1139453884 | F20: 1067186833 | G20: 1048239333 | H20: 1048217333 | I20: 1048217333 | J20: 1048116163 | K20: 1048116163 | L20: 1035718353 | M20: 1035625353 | N20: =991797481+130932798 -> 1122730279 | O20: =N20 -> 1122730279 | P20: 1220635546 | Q20: 1220635546 | R20: 1220279119 | S20: 1220279119 | T20: 1218682119 | U20: 1218249119 | V20: 1092879968 | W20: 1092879968 | X20: 1082339533 | Y20: 1082339533 | Z20: 1081913803 | AA20: 967670999 | AB20: =AA20 -> 967670999 | AC20: 1913855137 | AD20: 1913855137 | AE20: 1913855137 | AF20: 1893896951 | AG20: 1850161211 | AH20: 1774161211 | AI20: 1774161211 | AJ20: 1623406641 | AK20: 1620225968 | AL20: 1542961468 | AM20: 1542961468 | AN20: 1427470479 | AO20: =AN20 -> 1427470479 | AP20: 2012684680 | AQ20: 2012684680 | AR20: 1959842560 | AS20: 1959842560 | AT20: 1959505267 | AU20: 1939427267 | AV20: 1939427267 | AW20: 1938757501 | AX20: 1937457501 | AY20: 1929646738 | AZ20: 1891922336 | BA20: 1608652526 | BB20: =BA20 -> 1608652526 | BC20: 2083103023 | BD20: 2083103023 | BE20: 2068572694 | BF20: 2068438694 | BG20: 2067139640 | BH20: 1962984489 | BI20: 1968056577 | BJ20: 1968056577 | BK20: 1968056577 | BL20: 1968056577 | BM20: 1968056577 | BN20: 1976677470 | BO20: =BN20 -> 1976677470 | BP20: 1951485600 | BQ20: 1951485600 | BR20: 1905464563 | BS20: 1905464563 | BT20: 1817932962 | BU20: 1801311962 | BV20: 1801311962 | CB20: =BV20 -> 1801311962
B21: Dirección de Obras Hidráulicas | C21: 140801596 | D21: 140801596 | E21: 140801596 | F21: 140801596 | G21: 133918279 | H21: 133918279 | I21: 133918279 | J21: 133918279 | K21: 133918279 | L21: 133918279 | M21: 133918279 | N21: =131504761+8520124 -> 140024885 | O21: =N21 -> 140024885 | P21: 147022684 | Q21: 147022684 | R21: 147022684 | S21: 147022684 | T21: 147022684 | U21: 147022684 | V21: 147022684 | W21: 146848818 | X21: 144824178 | Y21: 130697780 | Z21: 130518293 | AA21: 129672445 | AB21: =AA21 -> 129672445 | AC21: 293591805 | AD21: 293591805 | AE21: 293591805 | AF21: 293591805 | AG21: 293591805 | AH21: 255048822 | AI21: 219099761 | AJ21: 212099761 | AK21: 212099761 | AL21: 212099761 | AM21: 212099761 | AN21: 198709088 | AO21: =AN21 -> 198709088 | AP21: 295701947 | AQ21: 295701947 | AR21: 278607232 | AS21: 278607232 | AT21: 278543079 | AU21: 278543079 | AV21: 278543079 | AW21: 282942267 | AX21: 282942267 | AY21: 282942267 | AZ21: 282942267 | BA21: 244313644 | BB21: =BA21 -> 244313644 | BC21: 308121429 | BD21: 308121429 | BE21: 308121429 | BF21: 308121429 | BG21: 308121429 | BH21: 288121429 | BI21: 288121429 | BJ21: 288121429 | BK21: 288121429 | BL21: 284126983 | BM21: 284126983 | BN21: 255720965 | BO21: =BN21 -> 255720965 | BP21: 195906100 | BQ21: 195906100 | BR21: 192119100 | BS21: 192119100 | BT21: 186241917 | BU21: 202307917 | BV21: 202307917 | CB21: =BV21 -> 202307917
B22: Subdirección de APR | C22: 142048072 | D22: 142048072 | E22: 142048072 | F22: 142048072 | G22: 160995572 | H22: 160995572 | I22: 160995572 | J22: 160995572 | K22: 160995572 | L22: 160995572 | M22: 160995572 | N22: =142300803+21041416 -> 163342219 | O22: =N22 -> 163342219 | P22: 148440561 | Q22: 148440561 | R22: 148440561 | S22: 148440561 | T22: 148440561 | U22: 148440561 | V22: 148440561 | W22: 148440561 | X22: 148440561 | Y22: 141404870 | Z22: 141404870 | AA22: 110932143 | AB22: =AA22 -> 110932143 | AC22: 295780655 | AD22: 295780655 | AE22: 295780655 | AF22: 295780655 | AG22: 295780655 | AH22: 275780655 | AI22: 309887671 | AJ22: 309887671 | AK22: 309887671 | AL22: 299857312 | AM22: 265750296 | AN22: 249472319 | AO22: =AN22 -> 249472319 | AP22: 315696642 | AQ22: 315696642 | AR22: 315696642 | AS22: 232705862 | AT22: 232705862 | AU22: 232705862 | AV22: 232705862 | AW22: 227906674 | AX22: 227906674 | AY22: 227906674 | AZ22: 227906674 | BA22: 192186387 | BB22: =BA22 -> 192186387 | BC22: 329603442 | BD22: 329603442 | BE22: 307603442 | BF22: 307603442 | BG22: 307603442 | BH22: 284751010 | BI22: 284751010 | BJ22: 284751010 | BK22: 284751010 | BL22: 273184204 | BM22: 273184204 | BN22: 234336066 | BO22: =BN22 -> 234336066 | BP22: 290113797 | BQ22: 290113797 | BR22: 282113797 | BS22: 282113797 | BT22: 273410383 | BU22: 273410383 | BV22: 273410383 | CB22: =BV22 -> 273410383
B23: Dirección de Obras Portuarias | C23: 73670723 | D23: 73670723 | E23: 73670723 | F23: 73670723 | G23: 73670723 | H23: 73670723 | I23: 73670723 | J23: 73670723 | K23: 73670723 | L23: 73670723 | M23: 73670723 | N23: =73116242+62000 -> 73178242 | O23: =N23 -> 73178242 | P23: 76882481 | Q23: 76882481 | R23: 76882481 | S23: 76882481 | T23: 76882481 | U23: 76882481 | V23: 76882481 | W23: 76882481 | X23: 76882481 | Y23: 76882481 | Z23: 76882481 | AA23: 64614673 | AB23: =AA23 -> 64614673 | AC23: 115171552 | AD23: 115171552 | AE23: 115171552 | AF23: 115171552 | AG23: 115171552 | AH23: 115171552 | AI23: 115171552 | AJ23: 115171552 | AK23: 115171552 | AL23: 108472329 | AM23: 108472329 | AN23: 104861138 | AO23: =AN23 -> 104861138 | AP23: 127117895 | AQ23: 127117895 | AR23: 127117895 | AS23: 127117895 | AT23: 127117895 | AU23: 127117895 | AV23: 127117895 | AW23: 127117895 | AX23: 127117895 | AY23: 127117895 | AZ23: 127117895 | BA23: 123682417 | BB23: =BA23 -> 123682417 | BC23: 125417585 | BD23: 125417585 | BE23: 139947914 | BF23: 139947914 | BG23: 139947914 | BH23: 139947914 | BI23: 145917564 | BJ23: 145917564 | BK23: 145917564 | BL23: 151478816 | BM23: 151478816 | BN23: 143006856 | BO23: =BN23 -> 143006856 | BP23: 109909690 | BQ23: 109909690 | BR23: 109909690 | BS23: 109909690 | BT23: 106612399 | BU23: 106612399 | BV23: 106612399 | CB23: =BV23 -> 106612399
B24: Dirección de Aeropuertos | C24: 60144148 | D24: 60144148 | E24: 60144148 | F24: 60144148 | G24: 60144148 | H24: 60144148 | I24: 60144148 | J24: 60144148 | K24: 60144148 | L24: 60144148 | M24: 60144148 | N24: =57087148+74000 -> 57161148 | O24: =N24 -> 57161148 | P24: 62797413 | Q24: 62797413 | R24: 62797413 | S24: 62797413 | T24: 62712374 | U24: 62712374 | V24: 62487413 | W24: 62487413 | X24: 62487413 | Y24: 62487413 | Z24: 62487413 | AA24: 66143610 | AB24: =AA24 -> 66143610 | AC24: 135318267 | AD24: 135318267 | AE24: 135318267 | AF24: 135318267 | AG24: 135318267 | AH24: 135318267 | AI24: 135318267 | AJ24: 135318267 | AK24: 135318267 | AL24: 131318267 | AM24: 131318267 | AN24: 123846968 | AO24: =AN24 -> 123846968 | AP24: 137741639 | AQ24: 137741639 | AR24: 137741639 | AS24: 135914151 | AT24: 135885801 | AU24: 135885801 | AV24: 135885801 | AW24: 135885801 | AX24: 135885801 | AY24: 137734161 | AZ24: 137734161 | BA24: 121300022 | BB24: =BA24 -> 121300022 | BC24: 141825431 | BD24: 141825431 | BE24: 141825431 | BF24: 141825431 | BG24: 141825431 | BH24: 141825431 | BI24: 141825431 | BJ24: 141825431 | BK24: 141825431 | BL24: 141825431 | BM24: 141825431 | BN24: 143001334 | BO24: =BN24 -> 143001334 | BP24: 127610750 | BQ24: 127610750 | BR24: 127610750 | BS24: 127610750 | BT24: 124345173 | BU24: 124345173 | BV24: 124345173 | CB24: =BV24 -> 124345173
B25: Dirección de Arquitectura | C25: =11904427+3610789 -> 15515216 | D25: =11904427+5306607 -> 17211034 | E25: =11904427+5306607 -> 17211034 | F25: =11904427+5306607 -> 17211034 | G25: =11904427+5306607 -> 17211034 | H25: =11904427+4045033 -> 15949460 | I25: =11904427+4045033 -> 15949460 | J25: =11904427+4045033 -> 15949460 | K25: =11904427+3610416 -> 15514843 | L25: =11904427+3610416 -> 15514843 | M25: =11904427+3610416 -> 15514843 | N25: =7205919+7501242 -> 14707161 | O25: =N25 -> 14707161 | P25: =8974172+22634181 -> 31608353 | Q25: =8974172+22634181 -> 31608353 | R25: =8974172+10297833 -> 19272005 | S25: =8974172+10297833 -> 19272005 | T25: =8974172+10297833 -> 19272005 | U25: =8974172+9873845 -> 18848017 | V25: 8974172 | W25: 8890172 | X25: 8890172 | Y25: 8663807 | Z25: 7863807 | AA25: 7392258 | AB25: =AA25 -> 7392258 | AC25: 37590026 | AD25: 36790026 | AE25: 36790026 | AF25: 36790026 | AG25: 36790026 | AH25: 32790026 | AI25: 32790026 | AJ25: 32707536 | AK25: 32707536 | AL25: 31426536 | AM25: 8720551 | AN25: 8559879 | AO25: =AN25 -> 8559879 | AP25: 44570138 | AQ25: 44570138 | AR25: 44570138 | AS25: 44570138 | AT25: 44670138 | AU25: 44670138 | AV25: 44670138 | AW25: 41933638 | AX25: 41744274 | AY25: 41744274 | AZ25: 41673300 | BA25: 33685852 | BB25: =BA25 -> 33685852 | BC25: 57109595 | BD25: 57109595 | BE25: 84609595 | BF25: 84609595 | BG25: 77572649 | BH25: 77572649 | BI25: 77594122 | BJ25: 77456003 | BK25: 77456003 | BL25: 77456003 | BM25: 77456003 | BN25: 55621639 | BO25: =BN25 -> 55621639 | BP25: 30479549 | BQ25: 30479549 | BR25: 30479549 | BS25: 30479549 | BT25: 29565163 | BU25: 29565163 | BV25: 29565163 | CB25: =BV25 -> 29565163
B26: Total | C26: =SUM(C20:C25) -> 1656601217 | D26: =SUM(D20:D25) -> 1658297035 | E26: =SUM(E20:E25) -> 1573329457 | F26: =SUM(F20:F25) -> 1501062406 | G26: =SUM(G20:G25) -> 1494179089 | H26: =SUM(H20:H25) -> 1492895515 | I26: =SUM(I20:I25) -> 1492895515 | J26: =SUM(J20:J25) -> 1492794345 | ... CB26: =SUM(CB20:CB25) -> 2537552997
B27: (1) Los años 2021 y 2022 incluyen el Presupuesto Vigente del Subtítulo 30, Ítem 10. Fuente: elaboración propia, Dipres.
B29: Ejecución de Inversión en Infraestructura Pública del Ministerio de Obras Públicas, 2021-2026 (Subtítulo 31 — Iniciativas de Inversión, miles de pesos)
C30: 2021(1) | P30: 2022(1) | AC30: 2023 | AP30: 2024 | BC30: 2025 | BP30: 2026
B31: Programa | C31: Ene | D31: Feb | E31: Mar | F31: Abr | G31: May | H31: Jun | I31: Jul | J31: Ago | K31: Sep | L31: Oct | M31: Nov | N31: Dic | O31: Total 2021 | P31: Ene | Q31: Feb | R31: Mar | S31: Abr | T31: May | U31: Jun | V31: Jul | W31: Ago | X31: Sep | Y31: Oct | Z31: Nov | AA31: Dic | AB31: Total 2022 | AC31: Ene | AD31: Feb | AE31: Mar | AF31: Abr | AG31: May | AH31: Jun | AI31: Jul | AJ31: Ago | AK31: Sep | AL31: Oct | AM31: Nov | AN31: Dic | AO31: Total 2023 | AP31: Ene | AQ31: Feb | AR31: Mar | AS31: Abr | AT31: May | AU31: Jun | AV31: Jul | AW31: Ago | AX31: Sep | AY31: Oct | AZ31: Nov | BA31: Dic | BB31: Total 2024 | BC31: Ene | BD31: Feb | BE31: Mar | BF31: Abr | BG31: May | BH31: Jun | BI31: Jul | BJ31: Ago | BK31: Sep | BL31: Oct | BM31: Nov | BN31: Dic | BO31: Total 2025 | BP31: Ene | BQ31: Feb | BR31: Mar | BS31: Abr | BT31: May | BU31: Jun | BV31: Jul | BW31: Ago | BX31: Sep | BY31: Oct | BZ31: Nov | CA31: Dic | CB31: Total 2026
B32: Dirección de Vialidad | C32: 0 | D32: 101383549 | E32: 198441247 | F32: 284324137 | G32: 358590676 | H32: 433048907 | I32: 503354400 | J32: 586218042 | K32: 653892258 | L32: 714435373 | M32: 802149786 | N32: 979979167 | O32: =N32 -> 979979167 | P32: 0 | Q32: 58153045 | R32: 139608998 | S32: 206666427 | T32: 283374746 | U32: 345265825 | V32: 405594742 | W32: 472550892 | X32: 616595780 | Y32: 680714110 | Z32: 760339461 | AA32: 955760345 | AB32: =AA32 -> 955760345 | AC32: 0 | AD32: 18205266 | AE32: 138456688 | AF32: 309745351 | AG32: 436281161 | AH32: 544941612 | AI32: 643572937 | AJ32: 731872328 | AK32: 824719400 | AL32: 940512329 | AM32: 1088998456 | AN32: 1417380025 | AO32: =AN32 -> 1417380025 | AP32: 0 | AQ32: 115017803 | AR32: 245067556 | AS32: 379975864 | AT32: 521874015 | AU32: 774852600 | AV32: 856290603 | AW32: 943020316 | AX32: 1073272838 | AY32: 1212620083 | AZ32: 1411133522 | BA32: 1603559540 | BB32: =BA32 -> 1603559540 | BC32: 1418928 | BD32: 262166719 | BE32: 478250448 | BF32: 666185288 | BG32: 837833362 | BH32: 982362882 | BI32: 1108324387 | BJ32: 1217723031 | BK32: 1369623467 | BL32: 1492337572 | BM32: 1632445535 | BN32: 1947648753 | BO32: =BN32 -> 1947648753 | BP32: 0 | BQ32: 162224034 | BR32: 321332158 | BS32: 469566556 | BT32: 614978745 | BU32: 776558972 | BV32: 909487841 | CB32: =BV32 -> 909487841
B33: Dirección de Obras Hidráulicas | C33: 0 | D33: 9524739 | E33: 18778382 | F33: 27058037 | G33: 38359267 | H33: 46029534 | I33: 54019806 | J33: 63431000 | K33: 74898419 | L33: 87833845 | M33: 101123468 | N33: 129806818 | O33: =N33 -> 129806818 | P33: 0 | Q33: 2161172 | R33: 9902695 | S33: 17446259 | T33: 23088738 | U33: 30830389 | V33: 40520841 | W33: 46926966 | X33: 55522281 | Y33: 68952930 | Z33: 83462172 | AA33: 128495787 | AB33: =AA33 -> 128495787 | AC33: 0 | AD33: 6431623 | AE33: 21339974 | AF33: 32945027 | AG33: 47577177 | AH33: 63593303 | AI33: 79376685 | AJ33: 92813663 | AK33: 104125697 | AL33: 112739918 | AM33: 129397461 | AN33: 195957467 | AO33: =AN33 -> 195957467 | AP33: 0 | AQ33: 6377090 | AR33: 23890040 | AS33: 39902005 | AT33: 58620170 | AU33: 119341758 | AV33: 136670909 | AW33: 157100022 | AX33: 175138873 | AY33: 193499950 | AZ33: 211590153 | BA33: 243896208 | BB33: =BA33 -> 243896208 | BC33: 2068692 | BD33: 14027617 | BE33: 36168803 | BF33: 53822571 | BG33: 71880596 | BH33: 92473645 | BI33: 108898696 | BJ33: 131234326 | BK33: 152827107 | BL33: 173770614 | BM33: 201417551 | BN33: 252789386 | BO33: =BN33 -> 252789386 | BP33: 0 | BQ33: 9585447 | BR33: 24838996 | BS33: 36118123 | BT33: 47381569 | BU33: 59374806 | BV33: 73650703 | CB33: =BV33 -> 73650703
B34: Subdirección de APR | C34: 0 | D34: 6666332 | E34: 21867716 | F34: 35651365 | G34: 47287710 | H34: 58269490 | I34: 67196224 | J34: 76194121 | K34: 86850665 | L34: 100525220 | M34: 114625930 | N34: 138846156 | O34: =N34 -> 138846156 | P34: 0 | Q34: 0 | R34: 7252609 | S34: 18124947 | T34: 26400403 | U34: 33265233 | V34: 41025465 | W34: 48098388 | X34: 56515227 | Y34: 64874125 | Z34: 77789880 | AA34: 108974292 | AB34: =AA34 -> 108974292 | AC34: 0 | AD34: 2303161 | AE34: 29583551 | AF34: 49465414 | AG34: 68683761 | AH34: 84807286 | AI34: 102765834 | AJ34: 120298096 | AK34: 135987986 | AL34: 156018552 | AM34: 183226741 | AN34: 244037387 | AO34: =AN34 -> 244037387 | AP34: 0 | AQ34: 11025007 | AR34: 25342159 | AS34: 43422173 | AT34: 59731566 | AU34: 80871277 | AV34: 90939725 | AW34: 104887838 | AX34: 121545898 | AY34: 134718420 | AZ34: 150454729 | BA34: 189747396 | BB34: =BA34 -> 189747396 | BC34: 2010108 | BD34: 18132777 | BE34: 36591973 | BF34: 55560502 | BG34: 73627660 | BH34: 93134581 | BI34: 109996503 | BJ34: 127458124 | BK34: 147026821 | BL34: 167611651 | BM34: 186253362 | BN34: 231742834 | BO34: =BN34 -> 231742834 | BP34: 0 | BQ34: 19469514 | BR34: 40366706 | BS34: 60258504 | BT34: 79539794 | BU34: 99543928 | BV34: 119758712 | CB34: =BV34 -> 119758712
B35: Dirección de Obras Portuarias | C35: 3825181 | D35: 8964985 | E35: 15055911 | F35: 20048280 | G35: 26317106 | H35: 31688072 | I35: 36444446 | J35: 42554997 | K35: 48413592 | L35: 53825635 | M35: 60943515 | N35: 72860066 | O35: =N35 -> 72860066 | P35: 0 | Q35: 6831369 | R35: 12735359 | S35: 17744111 | T35: 21871504 | U35: 26590987 | V35: 29792299 | W35: 33545628 | X35: 38180759 | Y35: 44900676 | Z35: 49875536 | AA35: 63389831 | AB35: =AA35 -> 63389831 | AC35: 0 | AD35: 9852119 | AE35: 18996634 | AF35: 27251266 | AG35: 35013028 | AH35: 43003795 | AI35: 50751095 | AJ35: 58156520 | AK35: 66259094 | AL35: 74165411 | AM35: 86349973 | AN35: 104365673 | AO35: =AN35 -> 104365673 | AP35: 0 | AQ35: 14355305 | AR35: 24004310 | AS35: 34981155 | AT35: 44329314 | AU35: 57184018 | AV35: 67266994 | AW35: 77238997 | AX35: 87016951 | AY35: 98032816 | AZ35: 108856624 | BA35: 122976500 | BB35: =BA35 -> 122976500 | BC35: 11343929 | BD35: 22880886 | BE35: 31954442 | BF35: 40743206 | BG35: 50003253 | BH35: 61155170 | BI35: 73000387 | BJ35: 82403582 | BK35: 91424463 | BL35: 102261627 | BM35: 115278067 | BN35: 140810158 | BO35: =BN35 -> 140810158 | BP35: 5334724 | BQ35: 18823694 | BR35: 29721986 | BS35: 39558533 | BT35: 50252046 | BU35: 57851838 | BV35: 65221155 | CB35: =BV35 -> 65221155
B36: Dirección de Aeropuertos | C36: 5238741 | D36: 10943486 | E36: 18457428 | F36: 27356255 | G36: 33912011 | H36: 39164650 | I36: 41928107 | J36: 45570244 | K36: 48624248 | L36: 50023582 | M36: 51847218 | N36: 56686190 | O36: =N36 -> 56686190 | P36: 839540 | Q36: 1930275 | R36: 5065401 | S36: 7642514 | T36: 8217159 | U36: 9505928 | V36: 12107075 | W36: 14547935 | X36: 17494128 | Y36: 27673768 | Z36: 40027308 | AA36: 65439532 | AB36: =AA36 -> 65439532 | AC36: 0 | AD36: 13210998 | AE36: 26801255 | AF36: 34566510 | AG36: 40280060 | AH36: 46287111 | AI36: 50590434 | AJ36: 60655017 | AK36: 67496353 | AL36: 74862435 | AM36: 89687930 | AN36: 122803224 | AO36: =AN36 -> 122803224 | AP36: 0 | AQ36: 10801902 | AR36: 21691356 | AS36: 33317068 | AT36: 44122345 | AU36: 59135603 | AV36: 66601938 | AW36: 74752243 | AX36: 86852892 | AY36: 99348688 | AZ36: 111690617 | BA36: 121236421 | BB36: =BA36 -> 121236421 | BC36: 5480453 | BD36: 18789767 | BE36: 33876924 | BF36: 51049771 | BG36: 63060218 | BH36: 70081917 | BI36: 74458174 | BJ36: 78656297 | BK36: 86517922 | BL36: 100099974 | BM36: 112429460 | BN36: 142638019 | BO36: =BN36 -> 142638019 | BP36: 8605874 | BQ36: 22342962 | BR36: 30219385 | BS36: 33540799 | BT36: 36963751 | BU36: 51185776 | BV36: 55356746 | CB36: =BV36 -> 55356746
B37: Dirección de Arquitectura | C37: 0 | D37: 185308 | E37: 472311 | F37: 867432 | G37: 1160606 | H37: 1516702 | I37: 2083480 | J37: 2750574 | K37: 3861743 | L37: 4604946 | M37: 5590277 | N37: 7136830 | O37: =N37 -> 7136830 | P37: 0 | Q37: 0 | R37: 112783 | S37: 865235 | T37: 1090968 | U37: 1329914 | V37: 1964401 | W37: 2518748 | X37: 3753691 | Y37: 4505699 | Z37: 5158128 | AA37: 6961523 | AB37: =AA37 -> 6961523 | AC37: 0 | AD37: 14295 | AE37: 519418 | AF37: 818017 | AG37: 1410647 | AH37: 2049207 | AI37: 2506834 | AJ37: 3618243 | AK37: 4988476 | AL37: 5883654 | AM37: 7168509 | AN37: 8421473 | AO37: =AN37 -> 8421473 | AP37: 0 | AQ37: 1265774 | AR37: 2147162 | AS37: 4222816 | AT37: 6702483 | AU37: 11199330 | AV37: 13041635 | AW37: 16175866 | AX37: 20074880 | AY37: 23775698 | AZ37: 27727701 | BA37: 33523348 | BB37: =BA37 -> 33523348 | BC37: 1010340 | BD37: 5400393 | BE37: 9140892 | BF37: 13609867 | BG37: 16763840 | BH37: 19193589 | BI37: 22131755 | BJ37: 27614100 | BK37: 31105744 | BL37: 35933608 | BM37: 40868830 | BN37: 48235342 | BO37: =BN37 -> 48235342 | BP37: 506557 | BQ37: 3068948 | BR37: 4760248 | BS37: 6527517 | BT37: 9351673 | BU37: 11151630 | BV37: 13543806 | CB37: =BV37 -> 13543806
B38: Total | C38: =SUM(C32:C37) -> 9063922 | D38: =SUM(D32:D37) -> 137668399 | E38: =SUM(E32:E37) -> 273072995 | F38: =SUM(F32:F37) -> 395305506 | G38: =SUM(G32:G37) -> 505627376 | H38: =SUM(H32:H37) -> 609717355 | I38: =SUM(I32:I37) -> 705026463 | J38: =SUM(J32:J37) -> 816718978 | ... CB38: =SUM(CB32:CB37) -> 1237018963
B39: Fuente: elaboración propia, Dipres.
B42: Subtítulo 29 — Adquisición de Activos No Financieros
B44: Presupuesto Ley de Inversión en Infraestructura Pública del Ministerio de Obras Públicas, 2021-2026 (Subtítulo 29 — Adquisición de Activos No Financieros, miles de pesos)
C45: 2021 | P45: 2022 | AC45: 2023 | AP45: 2024 | BC45: 2025 | BP45: 2026
B46: Programa | C46: Ene | D46: Feb | E46: Mar | F46: Abr | G46: May | H46: Jun | I46: Jul | J46: Ago | K46: Sep | L46: Oct | M46: Nov | N46: Dic | O46: Total 2021 | P46: Ene | Q46: Feb | R46: Mar | S46: Abr | T46: May | U46: Jun | V46: Jul | W46: Ago | X46: Sep | Y46: Oct | Z46: Nov | AA46: Dic | AB46: Total 2022 | AC46: Ene | AD46: Feb | AE46: Mar | AF46: Abr | AG46: May | AH46: Jun | AI46: Jul | AJ46: Ago | AK46: Sep | AL46: Oct | AM46: Nov | AN46: Dic | AO46: Total 2023 | AP46: Ene | AQ46: Feb | AR46: Mar | AS46: Abr | AT46: May | AU46: Jun | AV46: Jul | AW46: Ago | AX46: Sep | AY46: Oct | AZ46: Nov | BA46: Dic | BB46: Total 2024 | BC46: Ene | BD46: Feb | BE46: Mar | BF46: Abr | BG46: May | BH46: Jun | BI46: Jul | BJ46: Ago | BK46: Sep | BL46: Oct | BM46: Nov | BN46: Dic | BO46: Total 2025 | BP46: Ene | BQ46: Feb | BR46: Mar | BS46: Abr | BT46: May | BU46: Jun | BV46: Jul | BW46: Ago | BX46: Sep | BY46: Oct | BZ46: Nov | CA46: Dic | CB46: Total 2026
B47: Dirección de Vialidad | C47: 1930914 | D47: 1930914 | E47: 1930914 | F47: 1930914 | G47: 1930914 | H47: 1930914 | I47: 1930914 | J47: 1930914 | K47: 1930914 | L47: 1930914 | M47: 1930914 | N47: 1930914 | O47: =N47 -> 1930914 | P47: 298233 | Q47: 298233 | R47: 298233 | S47: 298233 | T47: 298233 | U47: 298233 | V47: 298233 | W47: 298233 | X47: 298233 | Y47: 298233 | Z47: 298233 | AA47: 298233 | AB47: =AA47 -> 298233 | AC47: 22089448 | AD47: 22089448 | AE47: 22089448 | AF47: 22089448 | AG47: 22089448 | AH47: 22089448 | AI47: 22089448 | AJ47: 22089448 | AK47: 22089448 | AL47: 22089448 | AM47: 22089448 | AN47: 22089448 | AO47: =AN47 -> 22089448 | AP47: 1135861 | AQ47: 1135861 | AR47: 1135861 | AS47: 1135861 | AT47: 1135861 | AU47: 1135861 | AV47: 1135861 | AW47: 1135861 | AX47: 1135861 | AY47: 1135861 | AZ47: 1135861 | BA47: 1135861 | BB47: =BA47 -> 1135861 | BC47: 6540884 | BD47: 6540884 | BE47: 6540884 | BF47: 6540884 | BG47: 6540884 | BH47: 6540884 | BI47: 6540884 | BJ47: 6540884 | BK47: 6540884 | BL47: 6540884 | BM47: 6540884 | BN47: 6540884 | BO47: =BN47 -> 6540884 | BP47: 1062955 | BQ47: 1062955 | BR47: 1062955 | BS47: 1062955 | BT47: 1062955 | BU47: 1062955 | BV47: 1062955 | CB47: =BV47 -> 1062955
B48: Dirección de Obras Hidráulicas | C48: 128859 | D48: 128859 | E48: 128859 | F48: 128859 | G48: 128859 | H48: 128859 | I48: 128859 | J48: 128859 | K48: 128859 | L48: 128859 | M48: 128859 | N48: 128859 | O48: =N48 -> 128859 | P48: 130362 | Q48: 130362 | R48: 130362 | S48: 130362 | T48: 130362 | U48: 130362 | V48: 130362 | W48: 130362 | X48: 130362 | Y48: 130362 | Z48: 130362 | AA48: 130362 | AB48: =AA48 -> 130362 | AC48: 647086 | AD48: 647086 | AE48: 647086 | AF48: 647086 | AG48: 647086 | AH48: 647086 | AI48: 647086 | AJ48: 647086 | AK48: 647086 | AL48: 647086 | AM48: 647086 | AN48: 647086 | AO48: =AN48 -> 647086 | AP48: 856525 | AQ48: 856525 | AR48: 856525 | AS48: 856525 | AT48: 856525 | AU48: 856525 | AV48: 856525 | AW48: 856525 | AX48: 856525 | AY48: 856525 | AZ48: 856525 | BA48: 856525 | BB48: =BA48 -> 856525 | BC48: 1233864 | BD48: 1233864 | BE48: 1233864 | BF48: 1233864 | BG48: 1233864 | BH48: 1233864 | BI48: 1233864 | BJ48: 1233864 | BK48: 1233864 | BL48: 1233864 | BM48: 1233864 | BN48: 1233864 | BO48: =BN48 -> 1233864 | BP48: 651088 | BQ48: 651088 | BR48: 651088 | BS48: 651088 | BT48: 651088 | BU48: 651088 | BV48: 651088 | CB48: =BV48 -> 651088
B49: Subdirección de APR | C49: 160447 | D49: 160447 | E49: 160447 | F49: 160447 | G49: 160447 | H49: 160447 | I49: 160447 | J49: 160447 | K49: 160447 | L49: 160447 | M49: 160447 | N49: 160447 | O49: =N49 -> 160447 | P49: 455326 | Q49: 455326 | R49: 455326 | S49: 455326 | T49: 455326 | U49: 455326 | V49: 455326 | W49: 455326 | X49: 455326 | Y49: 455326 | Z49: 455326 | AA49: 455326 | AB49: =AA49 -> 455326 | AC49: 622609 | AD49: 622609 | AE49: 622609 | AF49: 622609 | AG49: 622609 | AH49: 622609 | AI49: 622609 | AJ49: 622609 | AK49: 622609 | AL49: 622609 | AM49: 622609 | AN49: 622609 | AO49: =AN49 -> 622609 | AP49: 636104 | AQ49: 636104 | AR49: 636104 | AS49: 636104 | AT49: 636104 | AU49: 636104 | AV49: 636104 | AW49: 636104 | AX49: 636104 | AY49: 636104 | AZ49: 636104 | BA49: 636104 | BB49: =BA49 -> 636104 | BC49: 1352415 | BD49: 1352415 | BE49: 1352415 | BF49: 1352415 | BG49: 1352415 | BH49: 1352415 | BI49: 1352415 | BJ49: 1352415 | BK49: 1352415 | BL49: 1352415 | BM49: 1352415 | BN49: 1352415 | BO49: =BN49 -> 1352415 | BP49: 667445 | BQ49: 667445 | BR49: 667445 | BS49: 667445 | BT49: 667445 | BU49: 667445 | BV49: 667445 | CB49: =BV49 -> 667445
B50: Dirección de Obras Portuarias | C50: 2902086 | D50: 2902086 | E50: 2902086 | F50: 2902086 | G50: 2902086 | H50: 2902086 | I50: 2902086 | J50: 2902086 | K50: 2902086 | L50: 2902086 | M50: 2902086 | N50: 2902086 | O50: =N50 -> 2902086 | P50: 1322297 | Q50: 1322297 | R50: 1322297 | S50: 1322297 | T50: 1322297 | U50: 1322297 | V50: 1322297 | W50: 1322297 | X50: 1322297 | Y50: 1322297 | Z50: 1322297 | AA50: 1322297 | AB50: =AA50 -> 1322297 | AC50: 1814843 | AD50: 1814843 | AE50: 1814843 | AF50: 1814843 | AG50: 1814843 | AH50: 1814843 | AI50: 1814843 | AJ50: 1814843 | AK50: 1814843 | AL50: 1814843 | AM50: 1814843 | AN50: 1814843 | AO50: =AN50 -> 1814843 | AP50: 5152528 | AQ50: 5152528 | AR50: 5152528 | AS50: 5152528 | AT50: 5152528 | AU50: 5152528 | AV50: 5152528 | AW50: 5152528 | AX50: 5152528 | AY50: 5152528 | AZ50: 5152528 | BA50: 5152528 | BB50: =BA50 -> 5152528 | BC50: 2635679 | BD50: 2635679 | BE50: 2635679 | BF50: 2635679 | BG50: 2635679 | BH50: 2635679 | BI50: 2635679 | BJ50: 2635679 | BK50: 2635679 | BL50: 2635679 | BM50: 2635679 | BN50: 2635679 | BO50: =BN50 -> 2635679 | BP50: 2135157 | BQ50: 2135157 | BR50: 2135157 | BS50: 2135157 | BT50: 2135157 | BU50: 2135157 | BV50: 2135157 | CB50: =BV50 -> 2135157
B51: Dirección de Aeropuertos | C51: 103404 | D51: 103404 | E51: 103404 | F51: 103404 | G51: 103404 | H51: 103404 | I51: 103404 | J51: 103404 | K51: 103404 | L51: 103404 | M51: 103404 | N51: 103404 | O51: =N51 -> 103404 | P51: 76973 | Q51: 76973 | R51: 76973 | S51: 76973 | T51: 76973 | U51: 76973 | V51: 76973 | W51: 76973 | X51: 76973 | Y51: 76973 | Z51: 76973 | AA51: 76973 | AB51: =AA51 -> 76973 | AC51: 240323 | AD51: 240323 | AE51: 240323 | AF51: 240323 | AG51: 240323 | AH51: 240323 | AI51: 240323 | AJ51: 240323 | AK51: 240323 | AL51: 240323 | AM51: 240323 | AN51: 240323 | AO51: =AN51 -> 240323 | AP51: 251537 | AQ51: 251537 | AR51: 251537 | AS51: 251537 | AT51: 251537 | AU51: 251537 | AV51: 251537 | AW51: 251537 | AX51: 251537 | AY51: 251537 | AZ51: 251537 | BA51: 251537 | BB51: =BA51 -> 251537 | BC51: 924967 | BD51: 924967 | BE51: 924967 | BF51: 924967 | BG51: 924967 | BH51: 924967 | BI51: 924967 | BJ51: 924967 | BK51: 924967 | BL51: 924967 | BM51: 924967 | BN51: 924967 | BO51: =BN51 -> 924967 | BP51: 294239 | BQ51: 294239 | BR51: 294239 | BS51: 294239 | BT51: 294239 | BU51: 294239 | BV51: 294239 | CB51: =BV51 -> 294239
B52: Dirección de Arquitectura | C52: 107372 | D52: 107372 | E52: 107372 | F52: 107372 | G52: 107372 | H52: 107372 | I52: 107372 | J52: 107372 | K52: 107372 | L52: 107372 | M52: 107372 | N52: 107372 | O52: =N52 -> 107372 | P52: 169485 | Q52: 169485 | R52: 169485 | S52: 169485 | T52: 169485 | U52: 169485 | V52: 169485 | W52: 169485 | X52: 169485 | Y52: 169485 | Z52: 169485 | AA52: 169485 | AB52: =AA52 -> 169485 | AC52: 556957 | AD52: 556957 | AE52: 556957 | AF52: 556957 | AG52: 556957 | AH52: 556957 | AI52: 556957 | AJ52: 556957 | AK52: 556957 | AL52: 556957 | AM52: 556957 | AN52: 556957 | AO52: =AN52 -> 556957 | AP52: 615757 | AQ52: 615757 | AR52: 615757 | AS52: 615757 | AT52: 615757 | AU52: 615757 | AV52: 615757 | AW52: 615757 | AX52: 615757 | AY52: 615757 | AZ52: 615757 | BA52: 615757 | BB52: =BA52 -> 615757 | BC52: 555640 | BD52: 555640 | BE52: 555640 | BF52: 555640 | BG52: 555640 | BH52: 555640 | BI52: 555640 | BJ52: 555640 | BK52: 555640 | BL52: 555640 | BM52: 555640 | BN52: 555640 | BO52: =BN52 -> 555640 | BP52: 392933 | BQ52: 392933 | BR52: 392933 | BS52: 392933 | BT52: 392933 | BU52: 392933 | BV52: 392933 | CB52: =BV52 -> 392933
B53: Total | C53: =SUM(C47:C52) -> 5333082 | D53: =SUM(D47:D52) -> 5333082 | E53: =SUM(E47:E52) -> 5333082 | F53: =SUM(F47:F52) -> 5333082 | G53: =SUM(G47:G52) -> 5333082 | H53: =SUM(H47:H52) -> 5333082 | I53: =SUM(I47:I52) -> 5333082 | J53: =SUM(J47:J52) -> 5333082 | ... CB53: =SUM(CB47:CB52) -> 5203817
B54: Fuente: elaboración propia, Dipres.
B56: Presupuesto Vigente de Inversión en Infraestructura Pública del Ministerio de Obras Públicas, 2021-2026 (Subtítulo 29 — Adquisición de Activos No Financieros, miles de pesos)
C57: 2021 | P57: 2022 | AC57: 2023 | AP57: 2024 | BC57: 2025 | BP57: 2026
B58: Programa | C58: Ene | D58: Feb | E58: Mar | F58: Abr | G58: May | H58: Jun | I58: Jul | J58: Ago | K58: Sep | L58: Oct | M58: Nov | N58: Dic | O58: Total 2021 | P58: Ene | Q58: Feb | R58: Mar | S58: Abr | T58: May | U58: Jun | V58: Jul | W58: Ago | X58: Sep | Y58: Oct | Z58: Nov | AA58: Dic | AB58: Total 2022 | AC58: Ene | AD58: Feb | AE58: Mar | AF58: Abr | AG58: May | AH58: Jun | AI58: Jul | AJ58: Ago | AK58: Sep | AL58: Oct | AM58: Nov | AN58: Dic | AO58: Total 2023 | AP58: Ene | AQ58: Feb | AR58: Mar | AS58: Abr | AT58: May | AU58: Jun | AV58: Jul | AW58: Ago | AX58: Sep | AY58: Oct | AZ58: Nov | BA58: Dic | BB58: Total 2024 | BC58: Ene | BD58: Feb | BE58: Mar | BF58: Abr | BG58: May | BH58: Jun | BI58: Jul | BJ58: Ago | BK58: Sep | BL58: Oct | BM58: Nov | BN58: Dic | BO58: Total 2025 | BP58: Ene | BQ58: Feb | BR58: Mar | BS58: Abr | BT58: May | BU58: Jun | BV58: Jul | BW58: Ago | BX58: Sep | BY58: Oct | BZ58: Nov | CA58: Dic | CB58: Total 2026
B59: Dirección de Vialidad | C59: 1930914 | D59: 1930914 | E59: 3898492 | F59: 4709492 | G59: 4709492 | H59: 4731492 | I59: 4731492 | J59: 4832662 | K59: 4832662 | L59: 4832662 | M59: 4925662 | N59: 4819159 | O59: =N59 -> 4819159 | P59: 298233 | Q59: 298233 | R59: 298233 | S59: 298233 | T59: 1895233 | U59: 1895233 | V59: 1895233 | W59: 1895233 | X59: 11893879 | Y59: 11893879 | Z59: 11893879 | AA59: 8468149 | AB59: =AA59 -> 8468149 | AC59: 22089448 | AD59: 22089448 | AE59: 22089448 | AF59: 42047634 | AG59: 42281504 | AH59: 42281504 | AI59: 42281504 | AJ59: 42281504 | AK59: 44698344 | AL59: 44698344 | AM59: 44698344 | AN59: 7233990 | AO59: =AN59 -> 7233990 | AP59: 1135861 | AQ59: 1135861 | AR59: 1135861 | AS59: 1135861 | AT59: 1135861 | AU59: 1135861 | AV59: 1135861 | AW59: 1135861 | AX59: 1135861 | AY59: 1135861 | AZ59: 1135861 | BA59: 1135861 | BB59: =BA59 -> 1135861 | BC59: 6213840 | BD59: 6213840 | BE59: 6213840 | BF59: 6347840 | BG59: 6347840 | BH59: 6347840 | BI59: 6347840 | BJ59: 6347840 | BK59: 4559840 | BL59: 4559840 | BM59: 4559840 | BN59: 2245535 | BO59: =BN59 -> 2245535 | BP59: 1062955 | BQ59: 1062955 | BR59: 1582955 | BS59: 1582955 | BT59: 1551066 | BU59: 1551066 | BV59: 1551066 | CB59: =BV59 -> 1551066
B60: Dirección de Obras Hidráulicas | C60: 128859 | D60: 128859 | E60: 128859 | F60: 128859 | G60: 128859 | H60: 128859 | I60: 128859 | J60: 128859 | K60: 128859 | L60: 128859 | M60: 128859 | N60: 708689 | O60: =N60 -> 708689 | P60: 130362 | Q60: 130362 | R60: 130362 | S60: 130362 | T60: 130362 | U60: 130362 | V60: 130362 | W60: 130362 | X60: 1013888 | Y60: 1013888 | Z60: 1193375 | AA60: 1193375 | AB60: =AA60 -> 1193375 | AC60: 647086 | AD60: 647086 | AE60: 647086 | AF60: 647086 | AG60: 647086 | AH60: 647086 | AI60: 647086 | AJ60: 647086 | AK60: 647086 | AL60: 647086 | AM60: 647086 | AN60: 647086 | AO60: =AN60 -> 647086 | AP60: 856525 | AQ60: 856525 | AR60: 856525 | AS60: 856525 | AT60: 913626 | AU60: 913626 | AV60: 913626 | AW60: 913626 | AX60: 913626 | AY60: 913626 | AZ60: 913626 | BA60: 913626 | BB60: =BA60 -> 913626 | BC60: 1172171 | BD60: 1172171 | BE60: 1172171 | BF60: 1172171 | BG60: 1172171 | BH60: 1172171 | BI60: 1172171 | BJ60: 1172171 | BK60: 1172171 | BL60: 1172171 | BM60: 1172171 | BN60: 992552 | BO60: =BN60 -> 992552 | BP60: 651088 | BQ60: 651088 | BR60: 651088 | BS60: 651088 | BT60: 517480 | BU60: 517480 | BV60: 517480 | CB60: =BV60 -> 517480
B61: Subdirección de APR | C61: 160447 | D61: 160447 | E61: 160447 | F61: 160447 | G61: 160447 | H61: 160447 | I61: 160447 | J61: 160447 | K61: 160447 | L61: 160447 | M61: 160447 | N61: 160447 | O61: =N61 -> 160447 | P61: 455326 | Q61: 455326 | R61: 455326 | S61: 455326 | T61: 455326 | U61: 455326 | V61: 455326 | W61: 455326 | X61: 455326 | Y61: 979017 | Z61: 979017 | AA61: 979017 | AB61: =AA61 -> 979017 | AC61: 622609 | AD61: 622609 | AE61: 622609 | AF61: 622609 | AG61: 622609 | AH61: 622609 | AI61: 622609 | AJ61: 622609 | AK61: 622609 | AL61: 622609 | AM61: 622609 | AN61: 428444 | AO61: =AN61 -> 428444 | AP61: 636104 | AQ61: 636104 | AR61: 636104 | AS61: 636104 | AT61: 636104 | AU61: 636104 | AV61: 636104 | AW61: 636104 | AX61: 636104 | AY61: 636104 | AZ61: 636104 | BA61: 636104 | BB61: =BA61 -> 636104 | BC61: 1284794 | BD61: 1284794 | BE61: 1284794 | BF61: 1284794 | BG61: 1284794 | BH61: 1284794 | BI61: 1284794 | BJ61: 1284794 | BK61: 1284794 | BL61: 1284794 | BM61: 1284794 | BN61: 1212027 | BO61: =BN61 -> 1212027 | BP61: 667445 | BQ61: 667445 | BR61: 667445 | BS61: 667445 | BT61: 488932 | BU61: 488932 | BV61: 488932 | CB61: =BV61 -> 488932
B62: Dirección de Obras Portuarias | C62: 2902086 | D62: 2902086 | E62: 2902086 | F62: 2902086 | G62: 2902086 | H62: 2902086 | I62: 2902086 | J62: 2902086 | K62: 2902086 | L62: 2902086 | M62: 2902086 | N62: 486360 | O62: =N62 -> 486360 | P62: 1322297 | Q62: 1322297 | R62: 1322297 | S62: 1322297 | T62: 1322297 | U62: 1322297 | V62: 1322297 | W62: 1322297 | X62: 1322297 | Y62: 1322297 | Z62: 1322297 | AA62: 958297 | AB62: =AA62 -> 958297 | AC62: 1814843 | AD62: 1814843 | AE62: 1814843 | AF62: 1814843 | AG62: 1814843 | AH62: 1814843 | AI62: 1814843 | AJ62: 1814843 | AK62: 1814843 | AL62: 1814843 | AM62: 1814843 | AN62: 687226 | AO62: =AN62 -> 687226 | AP62: 5152528 | AQ62: 5152528 | AR62: 5152528 | AS62: 5152528 | AT62: 5152528 | AU62: 5152528 | AV62: 5152528 | AW62: 5152528 | AX62: 5006428 | AY62: 5006428 | AZ62: 1731272 | BA62: 1731272 | BB62: =BA62 -> 1731272 | BC62: 2503895 | BD62: 2503895 | BE62: 2503895 | BF62: 2503895 | BG62: 2503895 | BH62: 2503895 | BI62: 2503895 | BJ62: 2503895 | BK62: 2503895 | BL62: 2503895 | BM62: 2503895 | BN62: 391705 | BO62: =BN62 -> 391705 | BP62: 2135157 | BQ62: 2135157 | BR62: 2135157 | BS62: 2135157 | BT62: 2071102 | BU62: 2071102 | BV62: 2071102 | CB62: =BV62 -> 2071102
B63: Dirección de Aeropuertos | C63: 103404 | D63: 103404 | E63: 103404 | F63: 103404 | G63: 103404 | H63: 103404 | I63: 103404 | J63: 103404 | K63: 103404 | L63: 103404 | M63: 103404 | N63: 103404 | O63: =N63 -> 103404 | P63: 76973 | Q63: 76973 | R63: 76973 | S63: 76973 | T63: 162012 | U63: 162012 | V63: 162012 | W63: 162012 | X63: 162012 | Y63: 162012 | Z63: 162012 | AA63: 162012 | AB63: =AA63 -> 162012 | AC63: 240323 | AD63: 240323 | AE63: 240323 | AF63: 240323 | AG63: 240323 | AH63: 240323 | AI63: 240323 | AJ63: 240323 | AK63: 240323 | AL63: 240323 | AM63: 240323 | AN63: 240323 | AO63: =AN63 -> 240323 | AP63: 251537 | AQ63: 251537 | AR63: 251537 | AS63: 2079025 | AT63: 2107375 | AU63: 2107375 | AV63: 2107375 | AW63: 2107375 | AX63: 2107375 | AY63: 2107375 | AZ63: 2107375 | BA63: 1998403 | BB63: =BA63 -> 1998403 | BC63: 878719 | BD63: 878719 | BE63: 878719 | BF63: 878719 | BG63: 878719 | BH63: 878719 | BI63: 878719 | BJ63: 878719 | BK63: 878719 | BL63: 878719 | BM63: 878719 | BN63: 812930 | BO63: =BN63 -> 812930 | BP63: 294239 | BQ63: 294239 | BR63: 294239 | BS63: 294239 | BT63: 292976 | BU63: 292976 | BV63: 292976 | CB63: =BV63 -> 292976
B64: Dirección de Arquitectura | C64: 107372 | D64: 107372 | E64: 107372 | F64: 107372 | G64: 107372 | H64: 107372 | I64: 107372 | J64: 107372 | K64: 107372 | L64: 107372 | M64: 107372 | N64: 107372 | O64: =N64 -> 107372 | P64: 169485 | Q64: 169485 | R64: 169485 | S64: 169485 | T64: 169485 | U64: 169485 | V64: 169485 | W64: 169485 | X64: 169485 | Y64: 395850 | Z64: 395850 | AA64: 395850 | AB64: =AA64 -> 395850 | AC64: 556957 | AD64: 556957 | AE64: 556957 | AF64: 556957 | AG64: 556957 | AH64: 556957 | AI64: 556957 | AJ64: 556957 | AK64: 556957 | AL64: 556957 | AM64: 556957 | AN64: 556957 | AO64: =AN64 -> 556957 | AP64: 615757 | AQ64: 615757 | AR64: 615757 | AS64: 615757 | AT64: 615757 | AU64: 615757 | AV64: 615757 | AW64: 632257 | AX64: 632257 | AY64: 632257 | AZ64: 632257 | BA64: 632257 | BB64: =BA64 -> 632257 | BC64: 527858 | BD64: 527858 | BE64: 527858 | BF64: 527858 | BG64: 527858 | BH64: 527858 | BI64: 527858 | BJ64: 527858 | BK64: 527858 | BL64: 527858 | BM64: 527858 | BN64: 527858 | BO64: =BN64 -> 527858 | BP64: 392933 | BQ64: 392933 | BR64: 392933 | BS64: 392933 | BT64: 381145 | BU64: 381145 | BV64: 381145 | CB64: =BV64 -> 381145
B65: Total | C65: =SUM(C59:C64) -> 5333082 | D65: =SUM(D59:D64) -> 5333082 | E65: =SUM(E59:E64) -> 7300660 | F65: =SUM(F59:F64) -> 8111660 | G65: =SUM(G59:G64) -> 8111660 | H65: =SUM(H59:H64) -> 8133660 | I65: =SUM(I59:I64) -> 8133660 | J65: =SUM(J59:J64) -> 8234830 | ... CB65: =SUM(CB59:CB64) -> 5302701
B66: Fuente: elaboración propia, Dipres.
B68: Ejecución de Inversión en Infraestructura Pública del Ministerio de Obras Públicas, 2021-2026 (Subtítulo 29 — Adquisición de Activos No Financieros, miles de pesos)
C69: 2021 | P69: 2022 | AC69: 2023 | AP69: 2024 | BC69: 2025 | BP69: 2026
B70: Programa | C70: Ene | D70: Feb | E70: Mar | F70: Abr | G70: May | H70: Jun | I70: Jul | J70: Ago | K70: Sep | L70: Oct | M70: Nov | N70: Dic | O70: Total 2021 | P70: Ene | Q70: Feb | R70: Mar | S70: Abr | T70: May | U70: Jun | V70: Jul | W70: Ago | X70: Sep | Y70: Oct | Z70: Nov | AA70: Dic | AB70: Total 2022 | AC70: Ene | AD70: Feb | AE70: Mar | AF70: Abr | AG70: May | AH70: Jun | AI70: Jul | AJ70: Ago | AK70: Sep | AL70: Oct | AM70: Nov | AN70: Dic | AO70: Total 2023 | AP70: Ene | AQ70: Feb | AR70: Mar | AS70: Abr | AT70: May | AU70: Jun | AV70: Jul | AW70: Ago | AX70: Sep | AY70: Oct | AZ70: Nov | BA70: Dic | BB70: Total 2024 | BC70: Ene | BD70: Feb | BE70: Mar | BF70: Abr | BG70: May | BH70: Jun | BI70: Jul | BJ70: Ago | BK70: Sep | BL70: Oct | BM70: Nov | BN70: Dic | BO70: Total 2025 | BP70: Ene | BQ70: Feb | BR70: Mar | BS70: Abr | BT70: May | BU70: Jun | BV70: Jul | BW70: Ago | BX70: Sep | BY70: Oct | BZ70: Nov | CA70: Dic | CB70: Total 2026
B71: Dirección de Vialidad | C71: 0 | D71: 425938 | E71: 1462761 | F71: 1465974 | G71: 1481099 | H71: 1512434 | I71: 2183844 | J71: 2347779 | K71: 2386510 | L71: 2529946 | M71: 3094655 | N71: 4799532 | O71: =N71 -> 4799532 | P71: 0 | Q71: 0 | R71: 0 | S71: 0 | T71: 109962 | U71: 110961 | V71: 111701 | W71: 117198 | X71: 205350 | Y71: 218231 | Z71: 306659 | AA71: 8421395 | AB71: =AA71 -> 8421395 | AC71: 0 | AD71: 0 | AE71: 2948 | AF71: 4062 | AG71: 190131 | AH71: 222054 | AI71: 245430 | AJ71: 275973 | AK71: 456665 | AL71: 720929 | AM71: 963668 | AN71: 7135336 | AO71: =AN71 -> 7135336 | AP71: 0 | AQ71: 0 | AR71: 0 | AS71: 0 | AT71: 1714 | AU71: 3731 | AV71: 3731 | AW71: 53443 | AX71: 187144 | AY71: 187248 | AZ71: 221037 | BA71: 1123525 | BB71: =BA71 -> 1123525 | BC71: 0 | BD71: 0 | BE71: 0 | BF71: 3488 | BG71: 3488 | BH71: 6802 | BI71: 6802 | BJ71: 205085 | BK71: 215026 | BL71: 319809 | BM71: 541271 | BN71: 2174604 | BO71: =BN71 -> 2174604 | BP71: 0 | BQ71: 0 | BR71: 0 | BS71: 1547 | BT71: 1547 | BU71: 4001 | BV71: 4001 | CB71: =BV71 -> 4001
B72: Dirección de Obras Hidráulicas | C72: 0 | D72: 0 | E72: 0 | F72: 690 | G72: 690 | H72: 890 | I72: 890 | J72: 890 | K72: 26583 | L72: 37934 | M72: 117361 | N72: 703694 | O72: =N72 -> 703694 | P72: 0 | Q72: 0 | R72: 397 | S72: 397 | T72: 892 | U72: 20063 | V72: 21996 | W72: 21996 | X72: 75465 | Y72: 107933 | Z72: 907010 | AA72: 1149989 | AB72: =AA72 -> 1149989 | AC72: 0 | AD72: 0 | AE72: 30519 | AF72: 34103 | AG72: 58501 | AH72: 58501 | AI72: 103636 | AJ72: 103700 | AK72: 192664 | AL72: 195641 | AM72: 499753 | AN72: 628857 | AO72: =AN72 -> 628857 | AP72: 0 | AQ72: 0 | AR72: 563 | AS72: 2527 | AT72: 3420 | AU72: 355096 | AV72: 359380 | AW72: 402900 | AX72: 466045 | AY72: 466045 | AZ72: 466045 | BA72: 899916 | BB72: =BA72 -> 899916 | BC72: 0 | BD72: 0 | BE72: 0 | BF72: 2009 | BG72: 37835 | BH72: 73615 | BI72: 253012 | BJ72: 572413 | BK72: 586562 | BL72: 603974 | BM72: 818043 | BN72: 963962 | BO72: =BN72 -> 963962 | BP72: 0 | BQ72: 0 | BR72: 0 | BS72: 1508 | BT72: 129364 | BU72: 434033 | BV72: 452929 | CB72: =BV72 -> 452929
B73: Subdirección de APR | C73: 0 | D73: 0 | E73: 8167 | F73: 8833 | G73: 8833 | H73: 8833 | I73: 8833 | J73: 12555 | K73: 61123 | L73: 70203 | M73: 155639 | N73: 160231 | O73: =N73 -> 160231 | P73: 0 | Q73: 0 | R73: 0 | S73: 0 | T73: 0 | U73: 10407 | V73: 16277 | W73: 16277 | X73: 101440 | Y73: 232681 | Z73: 571170 | AA73: 709579 | AB73: =AA73 -> 709579 | AC73: 20554 | AD73: 20554 | AE73: 20857 | AF73: 41459 | AG73: 41551 | AH73: 41551 | AI73: 163019 | AJ73: 163019 | AK73: 209557 | AL73: 209557 | AM73: 236874 | AN73: 366748 | AO73: =AN73 -> 366748 | AP73: 10076 | AQ73: 10269 | AR73: 10269 | AS73: 10269 | AT73: 13954 | AU73: 337449 | AV73: 337449 | AW73: 444295 | AX73: 461458 | AY73: 470252 | AZ73: 470252 | BA73: 612897 | BB73: =BA73 -> 612897 | BC73: 0 | BD73: 160 | BE73: 160 | BF73: 160 | BG73: 4515 | BH73: 13374 | BI73: 133195 | BJ73: 499807 | BK73: 541550 | BL73: 568299 | BM73: 873723 | BN73: 1203592 | BO73: =BN73 -> 1203592 | BP73: 0 | BQ73: 0 | BR73: 0 | BS73: 13239 | BT73: 126731 | BU73: 371354 | BV73: 409008 | CB73: =BV73 -> 409008
B74: Dirección de Obras Portuarias | C74: 0 | D74: 20 | E74: 20 | F74: 40 | G74: 40 | H74: 263823 | I74: 439678 | J74: 439678 | K74: 444855 | L74: 444855 | M74: 458920 | N74: 485917 | O74: =N74 -> 485917 | P74: 0 | Q74: 0 | R74: 0 | S74: 22 | T74: 22 | U74: 22 | V74: 22 | W74: 22 | X74: 21191 | Y74: 82685 | Z74: 447234 | AA74: 865046 | AB74: =AA74 -> 865046 | AC74: 0 | AD74: 6359 | AE74: 7689 | AF74: 49168 | AG74: 90437 | AH74: 151090 | AI74: 151090 | AJ74: 152637 | AK74: 367133 | AL74: 367430 | AM74: 409162 | AN74: 620613 | AO74: =AN74 -> 620613 | AP74: 0 | AQ74: 0 | AR74: 0 | AS74: 1891 | AT74: 25269 | AU74: 68307 | AV74: 92369 | AW74: 255657 | AX74: 297429 | AY74: 650218 | AZ74: 722119 | BA74: 1508486 | BB74: =BA74 -> 1508486 | BC74: 0 | BD74: 0 | BE74: 0 | BF74: 5944 | BG74: 41309 | BH74: 91749 | BI74: 93532 | BJ74: 93532 | BK74: 96960 | BL74: 112867 | BM74: 143043 | BN74: 248096 | BO74: =BN74 -> 248096 | BP74: 70510 | BQ74: 70510 | BR74: 77071 | BS74: 91088 | BT74: 155966 | BU74: 155966 | BV74: 161164 | CB74: =BV74 -> 161164
B75: Dirección de Aeropuertos | C75: 0 | D75: 0 | E75: 0 | F75: 0 | G75: 375 | H75: 375 | I75: 375 | J75: 375 | K75: 16453 | L75: 16738 | M75: 59581 | N75: 101089 | O75: =N75 -> 101089 | P75: 0 | Q75: 0 | R75: 0 | S75: 43 | T75: 43 | U75: 638 | V75: 3960 | W75: 60216 | X75: 61185 | Y75: 67106 | Z75: 95932 | AA75: 160797 | AB75: =AA75 -> 160797 | AC75: 0 | AD75: 0 | AE75: 0 | AF75: 0 | AG75: 3085 | AH75: 82381 | AI75: 125991 | AJ75: 140950 | AK75: 158342 | AL75: 163795 | AM75: 191564 | AN75: 237804 | AO75: =AN75 -> 237804 | AP75: 0 | AQ75: 0 | AR75: 0 | AS75: 2262 | AT75: 74380 | AU75: 161068 | AV75: 226500 | AW75: 235972 | AX75: 1485698 | AY75: 1613690 | AZ75: 1931498 | BA75: 1997225 | BB75: =BA75 -> 1997225 | BC75: 0 | BD75: 97469 | BE75: 97751 | BF75: 98001 | BG75: 170182 | BH75: 170245 | BI75: 421065 | BJ75: 428624 | BK75: 444757 | BL75: 610730 | BM75: 614072 | BN75: 809633 | BO75: =BN75 -> 809633 | BP75: 0 | BQ75: 0 | BR75: 0 | BS75: 0 | BT75: 0 | BU75: 64950 | BV75: 127454 | CB75: =BV75 -> 127454
B76: Dirección de Arquitectura | C76: 0 | D76: 0 | E76: 0 | F76: 0 | G76: 0 | H76: 0 | I76: 0 | J76: 0 | K76: 0 | L76: 0 | M76: 38499 | N76: 107372 | O76: =N76 -> 107372 | P76: 0 | Q76: 0 | R76: 0 | S76: 0 | T76: 0 | U76: 0 | V76: 1222 | W76: 9602 | X76: 92334 | Y76: 96189 | Z76: 319595 | AA76: 395574 | AB76: =AA76 -> 395574 | AC76: 0 | AD76: 333 | AE76: 581 | AF76: 17754 | AG76: 70246 | AH76: 92472 | AI76: 321438 | AJ76: 325356 | AK76: 420771 | AL76: 450435 | AM76: 501604 | AN76: 554997 | AO76: =AN76 -> 554997 | AP76: 0 | AQ76: 47980 | AR76: 92337 | AS76: 95895 | AT76: 268337 | AU76: 389981 | AV76: 421650 | AW76: 428305 | AX76: 503200 | AY76: 506685 | AZ76: 563895 | BA76: 631827 | BB76: =BA76 -> 631827 | BC76: 0 | BD76: 33966 | BE76: 39677 | BF76: 68547 | BG76: 184933 | BH76: 316527 | BI76: 324773 | BJ76: 324773 | BK76: 329257 | BL76: 333451 | BM76: 436896 | BN76: 504566 | BO76: =BN76 -> 504566 | BP76: 0 | BQ76: 0 | BR76: 59187 | BS76: 68554 | BT76: 87338 | BU76: 87338 | BV76: 87338 | CB76: =BV76 -> 87338
B77: Total | C77: =SUM(C71:C76) -> 0 | D77: =SUM(D71:D76) -> 425958 | E77: =SUM(E71:E76) -> 1470948 | F77: =SUM(F71:F76) -> 1475537 | G77: =SUM(G71:G76) -> 1491037 | H77: =SUM(H71:H76) -> 1786355 | I77: =SUM(I71:I76) -> 2633620 | J77: =SUM(J71:J76) -> 2801277 | ... CB77: =SUM(CB71:CB76) -> 1241894
B78: Fuente: elaboración propia, Dipres.
B81: Subtítulo 33 — Transferencias de Capital
B83: Presupuesto Ley de Inversión en Infraestructura Pública del Ministerio de Obras Públicas, 2021-2026 (Subtítulo 33 — Transferencias de Capital, miles de pesos)
C84: 2021 | P84: 2022 | AC84: 2023 | AP84: 2024 | BC84: 2025 | BP84: 2026
B85: Programa | C85: Ene | D85: Feb | E85: Mar | F85: Abr | G85: May | H85: Jun | I85: Jul | J85: Ago | K85: Sep | L85: Oct | M85: Nov | N85: Dic | O85: Total 2021 | P85: Ene | Q85: Feb | R85: Mar | S85: Abr | T85: May | U85: Jun | V85: Jul | W85: Ago | X85: Sep | Y85: Oct | Z85: Nov | AA85: Dic | AB85: Total 2022 | AC85: Ene | AD85: Feb | AE85: Mar | AF85: Abr | AG85: May | AH85: Jun | AI85: Jul | AJ85: Ago | AK85: Sep | AL85: Oct | AM85: Nov | AN85: Dic | AO85: Total 2023 | AP85: Ene | AQ85: Feb | AR85: Mar | AS85: Abr | AT85: May | AU85: Jun | AV85: Jul | AW85: Ago | AX85: Sep | AY85: Oct | AZ85: Nov | BA85: Dic | BB85: Total 2024 | BC85: Ene | BD85: Feb | BE85: Mar | BF85: Abr | BG85: May | BH85: Jun | BI85: Jul | BJ85: Ago | BK85: Sep | BL85: Oct | BM85: Nov | BN85: Dic | BO85: Total 2025 | BP85: Ene | BQ85: Feb | BR85: Mar | BS85: Abr | BT85: May | BU85: Jun | BV85: Jul | BW85: Ago | BX85: Sep | BY85: Oct | BZ85: Nov | CA85: Dic | CB85: Total 2026
B86: Dirección de Vialidad | O86: =N86 -> 0 | AB86: =AA86 -> 0 | AO86: =AN86 -> 0 | AP86: 0 | AQ86: 0 | AR86: 0 | AS86: 0 | AT86: 0 | AU86: 0 | AV86: 0 | AW86: 0 | AX86: 0 | AY86: 0 | AZ86: 0 | BA86: 0 | BB86: =BA86 -> 0 | BC86: 0 | BD86: 0 | BE86: 0 | BF86: 0 | BG86: 0 | BH86: 0 | BI86: 0 | BJ86: 0 | BK86: 0 | BL86: 0 | BM86: 0 | BN86: 0 | BO86: =BN86 -> 0 | BP86: 0 | BQ86: 0 | BR86: 0 | BS86: 0 | BT86: 0 | BU86: 0 | BV86: 0 | CB86: =BV86 -> 0
B87: Dirección de Obras Hidráulicas | O87: =N87 -> 0 | AB87: =AA87 -> 0 | AO87: =AN87 -> 0 | AP87: 0 | AQ87: 0 | AR87: 0 | AS87: 0 | AT87: 0 | AU87: 0 | AV87: 0 | AW87: 0 | AX87: 0 | AY87: 0 | AZ87: 0 | BA87: 0 | BB87: =BA87 -> 0 | BC87: 0 | BD87: 0 | BE87: 0 | BF87: 0 | BG87: 0 | BH87: 0 | BI87: 0 | BJ87: 0 | BK87: 0 | BL87: 0 | BM87: 0 | BN87: 0 | BO87: =BN87 -> 0 | BP87: 0 | BQ87: 0 | BR87: 0 | BS87: 0 | BT87: 0 | BU87: 0 | BV87: 0 | CB87: =BV87 -> 0
B88: Subdirección de APR | O88: =N88 -> 0 | AB88: =AA88 -> 0 | AC88: 17877772 | AD88: 17877772 | AE88: 17877772 | AF88: 17877772 | AG88: 17877772 | AH88: 17877772 | AI88: 17877772 | AJ88: 17877772 | AK88: 17877772 | AL88: 17877772 | AM88: 17877772 | AN88: 17877772 | AO88: =AN88 -> 17877772 | AP88: 0 | AQ88: 0 | AR88: 0 | AS88: 0 | AT88: 0 | AU88: 0 | AV88: 0 | AW88: 0 | AX88: 0 | AY88: 0 | AZ88: 0 | BA88: 0 | BB88: =BA88 -> 0 | BC88: 0 | BD88: 0 | BE88: 0 | BF88: 0 | BG88: 0 | BH88: 0 | BI88: 0 | BJ88: 0 | BK88: 0 | BL88: 0 | BM88: 0 | BN88: 0 | BO88: =BN88 -> 0 | BP88: 0 | BQ88: 0 | BR88: 0 | BS88: 0 | BT88: 0 | BU88: 0 | BV88: 0 | CB88: =BV88 -> 0
B89: Dirección de Obras Portuarias | O89: =N89 -> 0 | AB89: =AA89 -> 0 | AO89: =AN89 -> 0 | AP89: 0 | AQ89: 0 | AR89: 0 | AS89: 0 | AT89: 0 | AU89: 0 | AV89: 0 | AW89: 0 | AX89: 0 | AY89: 0 | AZ89: 0 | BA89: 0 | BB89: =BA89 -> 0 | BC89: 0 | BD89: 0 | BE89: 0 | BF89: 0 | BG89: 0 | BH89: 0 | BI89: 0 | BJ89: 0 | BK89: 0 | BL89: 0 | BM89: 0 | BN89: 0 | BO89: =BN89 -> 0 | BP89: 0 | BQ89: 0 | BR89: 0 | BS89: 0 | BT89: 0 | BU89: 0 | BV89: 0 | CB89: =BV89 -> 0
B90: Dirección de Aeropuertos | O90: =N90 -> 0 | AB90: =AA90 -> 0 | AO90: =AN90 -> 0 | AP90: 0 | AQ90: 0 | AR90: 0 | AS90: 0 | AT90: 0 | AU90: 0 | AV90: 0 | AW90: 0 | AX90: 0 | AY90: 0 | AZ90: 0 | BA90: 0 | BB90: =BA90 -> 0 | BC90: 0 | BD90: 0 | BE90: 0 | BF90: 0 | BG90: 0 | BH90: 0 | BI90: 0 | BJ90: 0 | BK90: 0 | BL90: 0 | BM90: 0 | BN90: 0 | BO90: =BN90 -> 0 | BP90: 0 | BQ90: 0 | BR90: 0 | BS90: 0 | BT90: 0 | BU90: 0 | BV90: 0 | CB90: =BV90 -> 0
B91: Dirección de Arquitectura | O91: =N91 -> 0 | AB91: =AA91 -> 0 | AO91: =AN91 -> 0 | AP91: 0 | AQ91: 0 | AR91: 0 | AS91: 0 | AT91: 0 | AU91: 0 | AV91: 0 | AW91: 0 | AX91: 0 | AY91: 0 | AZ91: 0 | BA91: 0 | BB91: =BA91 -> 0 | BC91: 0 | BD91: 0 | BE91: 0 | BF91: 0 | BG91: 0 | BH91: 0 | BI91: 0 | BJ91: 0 | BK91: 0 | BL91: 0 | BM91: 0 | BN91: 0 | BO91: =BN91 -> 0 | BP91: 0 | BQ91: 0 | BR91: 0 | BS91: 0 | BT91: 0 | BU91: 0 | BV91: 0 | CB91: =BV91 -> 0
B92: Total | C92: =SUM(C86:C91) -> 0 | D92: =SUM(D86:D91) -> 0 | E92: =SUM(E86:E91) -> 0 | F92: =SUM(F86:F91) -> 0 | G92: =SUM(G86:G91) -> 0 | H92: =SUM(H86:H91) -> 0 | I92: =SUM(I86:I91) -> 0 | J92: =SUM(J86:J91) -> 0 | ... CB92: =SUM(CB86:CB91) -> 0
B93: El Subtítulo 33 solo aparece en APR, desde 2023. En los demás Programas y años no está en los informes de ejecución. Fuente: elaboración propia, Dipres.
B95: Presupuesto Vigente de Inversión en Infraestructura Pública del Ministerio de Obras Públicas, 2021-2026 (Subtítulo 33 — Transferencias de Capital, miles de pesos)
C96: 2021 | P96: 2022 | AC96: 2023 | AP96: 2024 | BC96: 2025 | BP96: 2026
B97: Programa | C97: Ene | D97: Feb | E97: Mar | F97: Abr | G97: May | H97: Jun | I97: Jul | J97: Ago | K97: Sep | L97: Oct | M97: Nov | N97: Dic | O97: Total 2021 | P97: Ene | Q97: Feb | R97: Mar | S97: Abr | T97: May | U97: Jun | V97: Jul | W97: Ago | X97: Sep | Y97: Oct | Z97: Nov | AA97: Dic | AB97: Total 2022 | AC97: Ene | AD97: Feb | AE97: Mar | AF97: Abr | AG97: May | AH97: Jun | AI97: Jul | AJ97: Ago | AK97: Sep | AL97: Oct | AM97: Nov | AN97: Dic | AO97: Total 2023 | AP97: Ene | AQ97: Feb | AR97: Mar | AS97: Abr | AT97: May | AU97: Jun | AV97: Jul | AW97: Ago | AX97: Sep | AY97: Oct | AZ97: Nov | BA97: Dic | BB97: Total 2024 | BC97: Ene | BD97: Feb | BE97: Mar | BF97: Abr | BG97: May | BH97: Jun | BI97: Jul | BJ97: Ago | BK97: Sep | BL97: Oct | BM97: Nov | BN97: Dic | BO97: Total 2025 | BP97: Ene | BQ97: Feb | BR97: Mar | BS97: Abr | BT97: May | BU97: Jun | BV97: Jul | BW97: Ago | BX97: Sep | BY97: Oct | BZ97: Nov | CA97: Dic | CB97: Total 2026
B98: Dirección de Vialidad | O98: =N98 -> 0 | AB98: =AA98 -> 0 | AO98: =AN98 -> 0 | AP98: 0 | AQ98: 0 | AR98: 0 | AS98: 0 | AT98: 0 | AU98: 0 | AV98: 0 | AW98: 0 | AX98: 0 | AY98: 0 | AZ98: 0 | BA98: 0 | BB98: =BA98 -> 0 | BC98: 0 | BD98: 0 | BE98: 0 | BF98: 0 | BG98: 0 | BH98: 0 | BI98: 0 | BJ98: 0 | BK98: 0 | BL98: 0 | BM98: 0 | BN98: 0 | BO98: =BN98 -> 0 | BP98: 0 | BQ98: 0 | BR98: 0 | BS98: 0 | BT98: 0 | BU98: 0 | BV98: 0 | CB98: =BV98 -> 0
B99: Dirección de Obras Hidráulicas | O99: =N99 -> 0 | AB99: =AA99 -> 0 | AO99: =AN99 -> 0 | AP99: 0 | AQ99: 0 | AR99: 0 | AS99: 0 | AT99: 0 | AU99: 0 | AV99: 0 | AW99: 0 | AX99: 0 | AY99: 0 | AZ99: 0 | BA99: 0 | BB99: =BA99 -> 0 | BC99: 0 | BD99: 0 | BE99: 0 | BF99: 0 | BG99: 0 | BH99: 0 | BI99: 0 | BJ99: 0 | BK99: 0 | BL99: 0 | BM99: 0 | BN99: 0 | BO99: =BN99 -> 0 | BP99: 0 | BQ99: 0 | BR99: 0 | BS99: 0 | BT99: 0 | BU99: 0 | BV99: 0 | CB99: =BV99 -> 0
B100: Subdirección de APR | O100: =N100 -> 0 | AB100: =AA100 -> 0 | AC100: 17877772 | AD100: 17877772 | AE100: 17877772 | AF100: 17877772 | AG100: 17877772 | AH100: 17877772 | AI100: 17877772 | AJ100: 17772523 | AK100: 17772523 | AL100: 17772523 | AM100: 10123523 | AN100: 10123523 | AO100: =AN100 -> 10123523 | AP100: 0 | AQ100: 0 | AR100: 0 | AS100: 0 | AT100: 0 | AU100: 0 | AV100: 0 | AW100: 0 | AX100: 0 | AY100: 0 | AZ100: 0 | BA100: 0 | BB100: =BA100 -> 0 | BC100: 0 | BD100: 0 | BE100: 0 | BF100: 0 | BG100: 0 | BH100: 0 | BI100: 0 | BJ100: 0 | BK100: 0 | BL100: 0 | BM100: 0 | BN100: 0 | BO100: =BN100 -> 0 | BP100: 0 | BQ100: 0 | BR100: 0 | BS100: 0 | BT100: 0 | BU100: 0 | BV100: 0 | CB100: =BV100 -> 0
B101: Dirección de Obras Portuarias | O101: =N101 -> 0 | AB101: =AA101 -> 0 | AO101: =AN101 -> 0 | AP101: 0 | AQ101: 0 | AR101: 0 | AS101: 0 | AT101: 0 | AU101: 0 | AV101: 0 | AW101: 0 | AX101: 0 | AY101: 0 | AZ101: 0 | BA101: 0 | BB101: =BA101 -> 0 | BC101: 0 | BD101: 0 | BE101: 0 | BF101: 0 | BG101: 0 | BH101: 0 | BI101: 0 | BJ101: 0 | BK101: 0 | BL101: 0 | BM101: 0 | BN101: 0 | BO101: =BN101 -> 0 | BP101: 0 | BQ101: 0 | BR101: 0 | BS101: 0 | BT101: 0 | BU101: 0 | BV101: 0 | CB101: =BV101 -> 0
B102: Dirección de Aeropuertos | O102: =N102 -> 0 | AB102: =AA102 -> 0 | AO102: =AN102 -> 0 | AP102: 0 | AQ102: 0 | AR102: 0 | AS102: 0 | AT102: 0 | AU102: 0 | AV102: 0 | AW102: 0 | AX102: 0 | AY102: 0 | AZ102: 0 | BA102: 0 | BB102: =BA102 -> 0 | BC102: 0 | BD102: 0 | BE102: 0 | BF102: 0 | BG102: 0 | BH102: 0 | BI102: 0 | BJ102: 0 | BK102: 0 | BL102: 0 | BM102: 0 | BN102: 0 | BO102: =BN102 -> 0 | BP102: 0 | BQ102: 0 | BR102: 0 | BS102: 0 | BT102: 0 | BU102: 0 | BV102: 0 | CB102: =BV102 -> 0
B103: Dirección de Arquitectura | O103: =N103 -> 0 | AB103: =AA103 -> 0 | AO103: =AN103 -> 0 | AP103: 0 | AQ103: 0 | AR103: 0 | AS103: 0 | AT103: 0 | AU103: 0 | AV103: 0 | AW103: 0 | AX103: 0 | AY103: 0 | AZ103: 0 | BA103: 0 | BB103: =BA103 -> 0 | BC103: 0 | BD103: 0 | BE103: 0 | BF103: 0 | BG103: 0 | BH103: 0 | BI103: 0 | BJ103: 0 | BK103: 0 | BL103: 0 | BM103: 0 | BN103: 0 | BO103: =BN103 -> 0 | BP103: 0 | BQ103: 0 | BR103: 0 | BS103: 0 | BT103: 0 | BU103: 0 | BV103: 0 | CB103: =BV103 -> 0
B104: Total | C104: =SUM(C98:C103) -> 0 | D104: =SUM(D98:D103) -> 0 | E104: =SUM(E98:E103) -> 0 | F104: =SUM(F98:F103) -> 0 | G104: =SUM(G98:G103) -> 0 | H104: =SUM(H98:H103) -> 0 | I104: =SUM(I98:I103) -> 0 | J104: =SUM(J98:J103) -> 0 | ... CB104: =SUM(CB98:CB103) -> 0
B105: El Subtítulo 33 solo aparece en APR, desde 2023. En los demás Programas y años no está en los informes de ejecución. Fuente: elaboración propia, Dipres.
B107: Ejecución de Inversión en Infraestructura Pública del Ministerio de Obras Públicas, 2021-2026 (Subtítulo 33 — Transferencias de Capital, miles de pesos)
C108: 2021 | P108: 2022 | AC108: 2023 | AP108: 2024 | BC108: 2025 | BP108: 2026
B109: Programa | C109: Ene | D109: Feb | E109: Mar | F109: Abr | G109: May | H109: Jun | I109: Jul | J109: Ago | K109: Sep | L109: Oct | M109: Nov | N109: Dic | O109: Total 2021 | P109: Ene | Q109: Feb | R109: Mar | S109: Abr | T109: May | U109: Jun | V109: Jul | W109: Ago | X109: Sep | Y109: Oct | Z109: Nov | AA109: Dic | AB109: Total 2022 | AC109: Ene | AD109: Feb | AE109: Mar | AF109: Abr | AG109: May | AH109: Jun | AI109: Jul | AJ109: Ago | AK109: Sep | AL109: Oct | AM109: Nov | AN109: Dic | AO109: Total 2023 | AP109: Ene | AQ109: Feb | AR109: Mar | AS109: Abr | AT109: May | AU109: Jun | AV109: Jul | AW109: Ago | AX109: Sep | AY109: Oct | AZ109: Nov | BA109: Dic | BB109: Total 2024 | BC109: Ene | BD109: Feb | BE109: Mar | BF109: Abr | BG109: May | BH109: Jun | BI109: Jul | BJ109: Ago | BK109: Sep | BL109: Oct | BM109: Nov | BN109: Dic | BO109: Total 2025 | BP109: Ene | BQ109: Feb | BR109: Mar | BS109: Abr | BT109: May | BU109: Jun | BV109: Jul | BW109: Ago | BX109: Sep | BY109: Oct | BZ109: Nov | CA109: Dic | CB109: Total 2026
B110: Dirección de Vialidad | O110: =N110 -> 0 | AB110: =AA110 -> 0 | AO110: =AN110 -> 0 | AP110: 0 | AQ110: 0 | AR110: 0 | AS110: 0 | AT110: 0 | AU110: 0 | AV110: 0 | AW110: 0 | AX110: 0 | AY110: 0 | AZ110: 0 | BA110: 0 | BB110: =BA110 -> 0 | BC110: 0 | BD110: 0 | BE110: 0 | BF110: 0 | BG110: 0 | BH110: 0 | BI110: 0 | BJ110: 0 | BK110: 0 | BL110: 0 | BM110: 0 | BN110: 0 | BO110: =BN110 -> 0 | BP110: 0 | BQ110: 0 | BR110: 0 | BS110: 0 | BT110: 0 | BU110: 0 | BV110: 0 | CB110: =BV110 -> 0
B111: Dirección de Obras Hidráulicas | O111: =N111 -> 0 | AB111: =AA111 -> 0 | AO111: =AN111 -> 0 | AP111: 0 | AQ111: 0 | AR111: 0 | AS111: 0 | AT111: 0 | AU111: 0 | AV111: 0 | AW111: 0 | AX111: 0 | AY111: 0 | AZ111: 0 | BA111: 0 | BB111: =BA111 -> 0 | BC111: 0 | BD111: 0 | BE111: 0 | BF111: 0 | BG111: 0 | BH111: 0 | BI111: 0 | BJ111: 0 | BK111: 0 | BL111: 0 | BM111: 0 | BN111: 0 | BO111: =BN111 -> 0 | BP111: 0 | BQ111: 0 | BR111: 0 | BS111: 0 | BT111: 0 | BU111: 0 | BV111: 0 | CB111: =BV111 -> 0
B112: Subdirección de APR | O112: =N112 -> 0 | AB112: =AA112 -> 0 | AC112: 0 | AD112: 0 | AE112: 0 | AF112: 0 | AG112: 0 | AH112: 0 | AI112: 1050 | AJ112: 1050 | AK112: 37795 | AL112: 169483 | AM112: 843033 | AN112: 3861859 | AO112: =AN112 -> 3861859 | AP112: 0 | AQ112: 0 | AR112: 0 | AS112: 0 | AT112: 0 | AU112: 0 | AV112: 0 | AW112: 0 | AX112: 0 | AY112: 0 | AZ112: 0 | BA112: 0 | BB112: =BA112 -> 0 | BC112: 0 | BD112: 0 | BE112: 0 | BF112: 0 | BG112: 0 | BH112: 0 | BI112: 0 | BJ112: 0 | BK112: 0 | BL112: 0 | BM112: 0 | BN112: 0 | BO112: =BN112 -> 0 | BP112: 0 | BQ112: 0 | BR112: 0 | BS112: 0 | BT112: 0 | BU112: 0 | BV112: 0 | CB112: =BV112 -> 0
B113: Dirección de Obras Portuarias | O113: =N113 -> 0 | AB113: =AA113 -> 0 | AO113: =AN113 -> 0 | AP113: 0 | AQ113: 0 | AR113: 0 | AS113: 0 | AT113: 0 | AU113: 0 | AV113: 0 | AW113: 0 | AX113: 0 | AY113: 0 | AZ113: 0 | BA113: 0 | BB113: =BA113 -> 0 | BC113: 0 | BD113: 0 | BE113: 0 | BF113: 0 | BG113: 0 | BH113: 0 | BI113: 0 | BJ113: 0 | BK113: 0 | BL113: 0 | BM113: 0 | BN113: 0 | BO113: =BN113 -> 0 | BP113: 0 | BQ113: 0 | BR113: 0 | BS113: 0 | BT113: 0 | BU113: 0 | BV113: 0 | CB113: =BV113 -> 0
...
