Workbook

Sheet Dashboard
B2: MINISTERIO DE OBRAS PÚBLICAS — DASHBOARD DE INVERSIÓN Y EJECUCIÓN PRESUPUESTARIA
B3: Visualizador Analítico Interactivo Tabla a Tabla | Subtítulos 31, 29, 33 y Consolidado Total | Cifras en miles de pesos ($)
B4: AÑO SELECCIONADO: | C4: 2024 | D4: COBERTURA TEMPORAL: | F4: 2014 - 2026 (Ene - Dic) | H4: UNIDAD MONETARIA: | J4: Miles de $ Corrientes (DIPRES)
B6: PRESUPUESTO LEY (INICIAL) | D6: PRESUPUESTO VIGENTE | F6: EJECUCIÓN ACUMULADA | H6: % CUMPLIMIENTO PRESUPUESTARIO | J6: SALDO POR EJECUTAR
B7: =D17 -> 2942161253 | D7: =E17 -> 2330868371 | F7: =F17 -> 2321713289 | H7: =H17 -> 0.99607224 | J7: =G17 -> 9155082
B9: Aprobado Ley de Presupuesto | D9: Presupuesto anual actualizado | F9: Total devengado en el ejercicio | H9: Ejecución devengada / Presupuesto vigente | J9: Monto disponible no devengado
B11: TABLA 1: RESUMEN CONSOLIDADO POR SUBTÍTULO PRESUPUESTARIO
B13: Subtítulo Presupuestario | C13: Cód. | D13: Presupuesto Ley | E13: Presupuesto Vigente | F13: Ejecución Acumulada | G13: Saldo por Ejecutar | H13: % Ejecución | I13: % Participación
B14: Subtítulo 31 – Iniciativas de Inversión | C14: 31 | D14: =INDEX(MOP_Mes_Corriente!$1:$161, 14, 3 + ($C$4 - 2014)*13 + 12) -> 2933512941 | E14: =INDEX(MOP_Mes_Corriente!$1:$161, 26, 3 + ($C$4 - 2014)*13 + 12) -> 2323820848 | F14: =INDEX(MOP_Mes_Corriente!$1:$161, 38, 3 + ($C$4 - 2014)*13 + 12) -> 2314939413 | G14: =E14 - F14 -> 8881435 | H14: =IF(E14>0, F14/E14, 0) -> 0.99617809 | I14: =IF($E$17>0, E14/$E$17, 0) -> 0.99697644
B15: Subtítulo 29 – Activos No Financieros | C15: 29 | D15: =INDEX(MOP_Mes_Corriente!$1:$161, 53, 3 + ($C$4 - 2014)*13 + 12) -> 8648312 | E15: =INDEX(MOP_Mes_Corriente!$1:$161, 65, 3 + ($C$4 - 2014)*13 + 12) -> 7047523 | F15: =INDEX(MOP_Mes_Corriente!$1:$161, 77, 3 + ($C$4 - 2014)*13 + 12) -> 6773876 | G15: =E15 - F15 -> 273647 | H15: =IF(E15>0, F15/E15, 0) -> 0.96117118 | I15: =IF($E$17>0, E15/$E$17, 0) -> 0.0030235611
B16: Subtítulo 33 – Transferencias de Capital | C16: 33 | D16: =INDEX(MOP_Mes_Corriente!$1:$161, 92, 3 + ($C$4 - 2014)*13 + 12) -> 0 | E16: =INDEX(MOP_Mes_Corriente!$1:$161, 104, 3 + ($C$4 - 2014)*13 + 12) -> 0 | F16: =INDEX(MOP_Mes_Corriente!$1:$161, 116, 3 + ($C$4 - 2014)*13 + 12) -> 0 | G16: =E16 - F16 -> 0 | H16: =IF(E16>0, F16/E16, 0) -> 0 | I16: =IF($E$17>0, E16/$E$17, 0) -> 0
B17: TOTAL INVERSIÓN MOP (31 + 29 + 33) | C17: TOTAL | D17: =SUM(D14:D16) -> 2942161253 | E17: =SUM(E14:E16) -> 2330868371 | F17: =SUM(F14:F16) -> 2321713289 | G17: =E17 - F17 -> 9155082 | H17: =IF(E17>0, F17/E17, 0) -> 0.99607224 | I17: =SUM(I14:I16) -> 1
B19: TABLA 2: DESGLOSE COMPLETO POR PROGRAMA / DIRECCIÓN (AÑO SELECCIONADO)
B21: Dirección / Programa | C21: Subt. 31 Vigente | D21: Subt. 31 Ejecución | E21: Subt. 29 Vigente | F21: Subt. 29 Ejecución | G21: Subt. 33 Vigente | H21: Subt. 33 Ejecución | I21: Total Vigente | J21: Total Ejecución | K21: Saldo | L21: % Ejecución | M21: % Part. MOP
B22: Dirección de Vialidad | C22: =INDEX(MOP_Mes_Corriente!$1:$161, 20, 3 + ($C$4 - 2014)*13 + 12) -> 1608652526 | D22: =INDEX(MOP_Mes_Corriente!$1:$161, 32, 3 + ($C$4 - 2014)*13 + 12) -> 1603559540 | E22: =INDEX(MOP_Mes_Corriente!$1:$161, 59, 3 + ($C$4 - 2014)*13 + 12) -> 1135861 | F22: =INDEX(MOP_Mes_Corriente!$1:$161, 71, 3 + ($C$4 - 2014)*13 + 12) -> 1123525 | G22: =INDEX(MOP_Mes_Corriente!$1:$161, 98, 3 + ($C$4 - 2014)*13 + 12) -> 0 | H22: =INDEX(MOP_Mes_Corriente!$1:$161, 110, 3 + ($C$4 - 2014)*13 + 12) -> 0 | I22: =C22 + E22 + G22 -> 1609788387 | J22: =D22 + F22 + H22 -> 1604683065 | K22: =I22 - J22 -> 5105322 | L22: =IF(I22>0, J22/I22, 0) -> 0.99682858 | M22: =IF($I$28>0, I22/$I$28, 0) -> 0.69063891
B23: Dirección de Obras Hidráulicas | C23: =INDEX(MOP_Mes_Corriente!$1:$161, 21, 3 + ($C$4 - 2014)*13 + 12) -> 244313644 | D23: =INDEX(MOP_Mes_Corriente!$1:$161, 33, 3 + ($C$4 - 2014)*13 + 12) -> 243896208 | E23: =INDEX(MOP_Mes_Corriente!$1:$161, 60, 3 + ($C$4 - 2014)*13 + 12) -> 913626 | F23: =INDEX(MOP_Mes_Corriente!$1:$161, 72, 3 + ($C$4 - 2014)*13 + 12) -> 899916 | G23: =INDEX(MOP_Mes_Corriente!$1:$161, 99, 3 + ($C$4 - 2014)*13 + 12) -> 0 | H23: =INDEX(MOP_Mes_Corriente!$1:$161, 111, 3 + ($C$4 - 2014)*13 + 12) -> 0 | I23: =C23 + E23 + G23 -> 245227270 | J23: =D23 + F23 + H23 -> 244796124 | K23: =I23 - J23 -> 431146 | L23: =IF(I23>0, J23/I23, 0) -> 0.99824185 | M23: =IF($I$28>0, I23/$I$28, 0) -> 0.10520855
B24: Subdirección de APR | C24: =INDEX(MOP_Mes_Corriente!$1:$161, 22, 3 + ($C$4 - 2014)*13 + 12) -> 192186387 | D24: =INDEX(MOP_Mes_Corriente!$1:$161, 34, 3 + ($C$4 - 2014)*13 + 12) -> 189747396 | E24: =INDEX(MOP_Mes_Corriente!$1:$161, 61, 3 + ($C$4 - 2014)*13 + 12) -> 636104 | F24: =INDEX(MOP_Mes_Corriente!$1:$161, 73, 3 + ($C$4 - 2014)*13 + 12) -> 612897 | G24: =INDEX(MOP_Mes_Corriente!$1:$161, 100, 3 + ($C$4 - 2014)*13 + 12) -> 0 | H24: =INDEX(MOP_Mes_Corriente!$1:$161, 112, 3 + ($C$4 - 2014)*13 + 12) -> 0 | I24: =C24 + E24 + G24 -> 192822491 | J24: =D24 + F24 + H24 -> 190360293 | K24: =I24 - J24 -> 2462198 | L24: =IF(I24>0, J24/I24, 0) -> 0.98723075 | M24: =IF($I$28>0, I24/$I$28, 0) -> 0.082725603
B25: Dirección de Obras Portuarias | C25: =INDEX(MOP_Mes_Corriente!$1:$161, 23, 3 + ($C$4 - 2014)*13 + 12) -> 123682417 | D25: =INDEX(MOP_Mes_Corriente!$1:$161, 35, 3 + ($C$4 - 2014)*13 + 12) -> 122976500 | E25: =INDEX(MOP_Mes_Corriente!$1:$161, 62, 3 + ($C$4 - 2014)*13 + 12) -> 1731272 | F25: =INDEX(MOP_Mes_Corriente!$1:$161, 74, 3 + ($C$4 - 2014)*13 + 12) -> 1508486 | G25: =INDEX(MOP_Mes_Corriente!$1:$161, 101, 3 + ($C$4 - 2014)*13 + 12) -> 0 | H25: =INDEX(MOP_Mes_Corriente!$1:$161, 113, 3 + ($C$4 - 2014)*13 + 12) -> 0 | I25: =C25 + E25 + G25 -> 125413689 | J25: =D25 + F25 + H25 -> 124484986 | K25: =I25 - J25 -> 928703 | L25: =IF(I25>0, J25/I25, 0) -> 0.99259488 | M25: =IF($I$28>0, I25/$I$28, 0) -> 0.053805565
B26: Dirección de Aeropuertos | C26: =INDEX(MOP_Mes_Corriente!$1:$161, 24, 3 + ($C$4 - 2014)*13 + 12) -> 121300022 | D26: =INDEX(MOP_Mes_Corriente!$1:$161, 36, 3 + ($C$4 - 2014)*13 + 12) -> 121236421 | E26: =INDEX(MOP_Mes_Corriente!$1:$161, 63, 3 + ($C$4 - 2014)*13 + 12) -> 1998403 | F26: =INDEX(MOP_Mes_Corriente!$1:$161, 75, 3 + ($C$4 - 2014)*13 + 12) -> 1997225 | G26: =INDEX(MOP_Mes_Corriente!$1:$161, 102, 3 + ($C$4 - 2014)*13 + 12) -> 0 | H26: =INDEX(MOP_Mes_Corriente!$1:$161, 114, 3 + ($C$4 - 2014)*13 + 12) -> 0 | I26: =C26 + E26 + G26 -> 123298425 | J26: =D26 + F26 + H26 -> 123233646 | K26: =I26 - J26 -> 64779 | L26: =IF(I26>0, J26/I26, 0) -> 0.99947462 | M26: =IF($I$28>0, I26/$I$28, 0) -> 0.052898064
B27: Dirección de Arquitectura | C27: =INDEX(MOP_Mes_Corriente!$1:$161, 25, 3 + ($C$4 - 2014)*13 + 12) -> 33685852 | D27: =INDEX(MOP_Mes_Corriente!$1:$161, 37, 3 + ($C$4 - 2014)*13 + 12) -> 33523348 | E27: =INDEX(MOP_Mes_Corriente!$1:$161, 64, 3 + ($C$4 - 2014)*13 + 12) -> 632257 | F27: =INDEX(MOP_Mes_Corriente!$1:$161, 76, 3 + ($C$4 - 2014)*13 + 12) -> 631827 | G27: =INDEX(MOP_Mes_Corriente!$1:$161, 103, 3 + ($C$4 - 2014)*13 + 12) -> 0 | H27: =INDEX(MOP_Mes_Corriente!$1:$161, 115, 3 + ($C$4 - 2014)*13 + 12) -> 0 | I27: =C27 + E27 + G27 -> 34318109 | J27: =D27 + F27 + H27 -> 34155175 | K27: =I27 - J27 -> 162934 | L27: =IF(I27>0, J27/I27, 0) -> 0.99525224 | M27: =IF($I$28>0, I27/$I$28, 0) -> 0.014723315
B28: TOTAL MOP | C28: =SUM(C22:C27) -> 2323820848 | D28: =SUM(D22:D27) -> 2314939413 | E28: =SUM(E22:E27) -> 7047523 | F28: =SUM(F22:F27) -> 6773876 | G28: =SUM(G22:G27) -> 0 | H28: =SUM(H22:H27) -> 0 | I28: =SUM(I22:I27) -> 2330868371 | J28: =SUM(J22:J27) -> 2321713289 | K28: =SUM(K22:K27) -> 9155082 | L28: =IF(I28>0, J28/I28, 0) -> 0.99607224 | M28: =SUM(M22:M27) -> 1
B30: TABLA 3: EVOLUCIÓN MENSUAL DEL AÑO SELECCIONADO (ENERO A DICIEMBRE)
B32: Concepto / Mes | C32: Ene | D32: Feb | E32: Mar | F32: Abr | G32: May | H32: Jun | I32: Jul | J32: Ago | K32: Sep | L32: Oct | M32: Nov | N32: Dic | O32: Cierre Total
B33: Presupuesto Ley | C33: =INDEX(MOP_Mes_Corriente!$1:$161, 14, 3 + ($C$4 - 2014)*13 + 0) + INDEX(MOP_Mes_Corriente!$1:$161, 53, 3 + ($C$4 - 2014)*13 + 0) + INDEX(MOP_Mes_Corriente!$1:$161, 92, 3 + ($C$4 - 2014)*13 + 0) -> 2942161253 | D33: =INDEX(MOP_Mes_Corriente!$1:$161, 14, 3 + ($C$4 - 2014)*13 + 1) + INDEX(MOP_Mes_Corriente!$1:$161, 53, 3 + ($C$4 - 2014)*13 + 1) + INDEX(MOP_Mes_Corriente!$1:$161, 92, 3 + ($C$4 - 2014)*13 + 1) -> 2942161253 | E33: =INDEX(MOP_Mes_Corriente!$1:$161, 14, 3 + ($C$4 - 2014)*13 + 2) + INDEX(MOP_Mes_Corriente!$1:$161, 53, 3 + ($C$4 - 2014)*13 + 2) + INDEX(MOP_Mes_Corriente!$1:$161, 92, 3 + ($C$4 - 2014)*13 + 2) -> 2942161253 | F33: =INDEX(MOP_Mes_Corriente!$1:$161, 14, 3 + ($C$4 - 2014)*13 + 3) + INDEX(MOP_Mes_Corriente!$1:$161, 53, 3 + ($C$4 - 2014)*13 + 3) + INDEX(MOP_Mes_Corriente!$1:$161, 92, 3 + ($C$4 - 2014)*13 + 3) -> 2942161253 | G33: =INDEX(MOP_Mes_Corriente!$1:$161, 14, 3 + ($C$4 - 2014)*13 + 4) + INDEX(MOP_Mes_Corriente!$1:$161, 53, 3 + ($C$4 - 2014)*13 + 4) + INDEX(MOP_Mes_Corriente!$1:$161, 92, 3 + ($C$4 - 2014)*13 + 4) -> 2942161253 | H33: =INDEX(MOP_Mes_Corriente!$1:$161, 14, 3 + ($C$4 - 2014)*13 + 5) + INDEX(MOP_Mes_Corriente!$1:$161, 53, 3 + ($C$4 - 2014)*13 + 5) + INDEX(MOP_Mes_Corriente!$1:$161, 92, 3 + ($C$4 - 2014)*13 + 5) -> 2942161253 | I33: =INDEX(MOP_Mes_Corriente!$1:$161, 14, 3 + ($C$4 - 2014)*13 + 6) + INDEX(MOP_Mes_Corriente!$1:$161, 53, 3 + ($C$4 - 2014)*13 + 6) + INDEX(MOP_Mes_Corriente!$1:$161, 92, 3 + ($C$4 - 2014)*13 + 6) -> 2942161253 | J33: =INDEX(MOP_Mes_Corriente!$1:$161, 14, 3 + ($C$4 - 2014)*13 + 7) + INDEX(MOP_Mes_Corriente!$1:$161, 53, 3 + ($C$4 - 2014)*13 + 7) + INDEX(MOP_Mes_Corriente!$1:$161, 92, 3 + ($C$4 - 2014)*13 + 7) -> 2942161253 | K33: =INDEX(MOP_Mes_Corriente!$1:$161, 14, 3 + ($C$4 - 2014)*13 + 8) + INDEX(MOP_Mes_Corriente!$1:$161, 53, 3 + ($C$4 - 2014)*13 + 8) + INDEX(MOP_Mes_Corriente!$1:$161, 92, 3 + ($C$4 - 2014)*13 + 8) -> 2942161253 | L33: =INDEX(MOP_Mes_Corriente!$1:$161, 14, 3 + ($C$4 - 2014)*13 + 9) + INDEX(MOP_Mes_Corriente!$1:$161, 53, 3 + ($C$4 - 2014)*13 + 9) + INDEX(MOP_Mes_Corriente!$1:$161, 92, 3 + ($C$4 - 2014)*13 + 9) -> 2942161253 | M33: =INDEX(MOP_Mes_Corriente!$1:$161, 14, 3 + ($C$4 - 2014)*13 + 10) + INDEX(MOP_Mes_Corriente!$1:$161, 53, 3 + ($C$4 - 2014)*13 + 10) + INDEX(MOP_Mes_Corriente!$1:$161, 92, 3 + ($C$4 - 2014)*13 + 10) -> 2942161253 | N33: =INDEX(MOP_Mes_Corriente!$1:$161, 14, 3 + ($C$4 - 2014)*13 + 11) + INDEX(MOP_Mes_Corriente!$1:$161, 53, 3 + ($C$4 - 2014)*13 + 11) + INDEX(MOP_Mes_Corriente!$1:$161, 92, 3 + ($C$4 - 2014)*13 + 11) -> 2942161253 | O33: =INDEX(MOP_Mes_Corriente!$1:$161, 14, 3 + ($C$4 - 2014)*13 + 12) + INDEX(MOP_Mes_Corriente!$1:$161, 53, 3 + ($C$4 - 2014)*13 + 12) + INDEX(MOP_Mes_Corriente!$1:$161, 92, 3 + ($C$4 - 2014)*13 + 12) -> 2942161253
B34: Presupuesto Vigente | C34: =INDEX(MOP_Mes_Corriente!$1:$161, 26, 3 + ($C$4 - 2014)*13 + 0) + INDEX(MOP_Mes_Corriente!$1:$161, 65, 3 + ($C$4 - 2014)*13 + 0) + INDEX(MOP_Mes_Corriente!$1:$161, 104, 3 + ($C$4 - 2014)*13 + 0) -> 2942161253 | D34: =INDEX(MOP_Mes_Corriente!$1:$161, 26, 3 + ($C$4 - 2014)*13 + 1) + INDEX(MOP_Mes_Corriente!$1:$161, 65, 3 + ($C$4 - 2014)*13 + 1) + INDEX(MOP_Mes_Corriente!$1:$161, 104, 3 + ($C$4 - 2014)*13 + 1) -> 2942161253 | E34: =INDEX(MOP_Mes_Corriente!$1:$161, 26, 3 + ($C$4 - 2014)*13 + 2) + INDEX(MOP_Mes_Corriente!$1:$161, 65, 3 + ($C$4 - 2014)*13 + 2) + INDEX(MOP_Mes_Corriente!$1:$161, 104, 3 + ($C$4 - 2014)*13 + 2) -> 2872224418 | F34: =INDEX(MOP_Mes_Corriente!$1:$161, 26, 3 + ($C$4 - 2014)*13 + 3) + INDEX(MOP_Mes_Corriente!$1:$161, 65, 3 + ($C$4 - 2014)*13 + 3) + INDEX(MOP_Mes_Corriente!$1:$161, 104, 3 + ($C$4 - 2014)*13 + 3) -> 2789233638 | G34: =INDEX(MOP_Mes_Corriente!$1:$161, 26, 3 + ($C$4 - 2014)*13 + 4) + INDEX(MOP_Mes_Corriente!$1:$161, 65, 3 + ($C$4 - 2014)*13 + 4) + INDEX(MOP_Mes_Corriente!$1:$161, 104, 3 + ($C$4 - 2014)*13 + 4) -> 2788989293 | H34: =INDEX(MOP_Mes_Corriente!$1:$161, 26, 3 + ($C$4 - 2014)*13 + 5) + INDEX(MOP_Mes_Corriente!$1:$161, 65, 3 + ($C$4 - 2014)*13 + 5) + INDEX(MOP_Mes_Corriente!$1:$161, 104, 3 + ($C$4 - 2014)*13 + 5) -> 2768911293 | I34: =INDEX(MOP_Mes_Corriente!$1:$161, 26, 3 + ($C$4 - 2014)*13 + 6) + INDEX(MOP_Mes_Corriente!$1:$161, 65, 3 + ($C$4 - 2014)*13 + 6) + INDEX(MOP_Mes_Corriente!$1:$161, 104, 3 + ($C$4 - 2014)*13 + 6) -> 2768911293 | J34: =INDEX(MOP_Mes_Corriente!$1:$161, 26, 3 + ($C$4 - 2014)*13 + 7) + INDEX(MOP_Mes_Corriente!$1:$161, 65, 3 + ($C$4 - 2014)*13 + 7) + INDEX(MOP_Mes_Corriente!$1:$161, 104, 3 + ($C$4 - 2014)*13 + 7) -> 2765121527 | K34: =INDEX(MOP_Mes_Corriente!$1:$161, 26, 3 + ($C$4 - 2014)*13 + 8) + INDEX(MOP_Mes_Corriente!$1:$161, 65, 3 + ($C$4 - 2014)*13 + 8) + INDEX(MOP_Mes_Corriente!$1:$161, 104, 3 + ($C$4 - 2014)*13 + 8) -> 2763486063 | L34: =INDEX(MOP_Mes_Corriente!$1:$161, 26, 3 + ($C$4 - 2014)*13 + 9) + INDEX(MOP_Mes_Corriente!$1:$161, 65, 3 + ($C$4 - 2014)*13 + 9) + INDEX(MOP_Mes_Corriente!$1:$161, 104, 3 + ($C$4 - 2014)*13 + 9) -> 2757523660 | M34: =INDEX(MOP_Mes_Corriente!$1:$161, 26, 3 + ($C$4 - 2014)*13 + 10) + INDEX(MOP_Mes_Corriente!$1:$161, 65, 3 + ($C$4 - 2014)*13 + 10) + INDEX(MOP_Mes_Corriente!$1:$161, 104, 3 + ($C$4 - 2014)*13 + 10) -> 2716453128 | N34: =INDEX(MOP_Mes_Corriente!$1:$161, 26, 3 + ($C$4 - 2014)*13 + 11) + INDEX(MOP_Mes_Corriente!$1:$161, 65, 3 + ($C$4 - 2014)*13 + 11) + INDEX(MOP_Mes_Corriente!$1:$161, 104, 3 + ($C$4 - 2014)*13 + 11) -> 2330868371 | O34: =INDEX(MOP_Mes_Corriente!$1:$161, 26, 3 + ($C$4 - 2014)*13 + 12) + INDEX(MOP_Mes_Corriente!$1:$161, 65, 3 + ($C$4 - 2014)*13 + 12) + INDEX(MOP_Mes_Corriente!$1:$161, 104, 3 + ($C$4 - 2014)*13 + 12) -> 2330868371
B35: Ejecución Acumulada | C35: =INDEX(MOP_Mes_Corriente!$1:$161, 38, 3 + ($C$4 - 2014)*13 + 0) + INDEX(MOP_Mes_Corriente!$1:$161, 77, 3 + ($C$4 - 2014)*13 + 0) + INDEX(MOP_Mes_Corriente!$1:$161, 116, 3 + ($C$4 - 2014)*13 + 0) -> 10076 | D35: =INDEX(MOP_Mes_Corriente!$1:$161, 38, 3 + ($C$4 - 2014)*13 + 1) + INDEX(MOP_Mes_Corriente!$1:$161, 77, 3 + ($C$4 - 2014)*13 + 1) + INDEX(MOP_Mes_Corriente!$1:$161, 116, 3 + ($C$4 - 2014)*13 + 1) -> 158901130 | E35: =INDEX(MOP_Mes_Corriente!$1:$161, 38, 3 + ($C$4 - 2014)*13 + 2) + INDEX(MOP_Mes_Corriente!$1:$161, 77, 3 + ($C$4 - 2014)*13 + 2) + INDEX(MOP_Mes_Corriente!$1:$161, 116, 3 + ($C$4 - 2014)*13 + 2) -> 342245752 | F35: =INDEX(MOP_Mes_Corriente!$1:$161, 38, 3 + ($C$4 - 2014)*13 + 3) + INDEX(MOP_Mes_Corriente!$1:$161, 77, 3 + ($C$4 - 2014)*13 + 3) + INDEX(MOP_Mes_Corriente!$1:$161, 116, 3 + ($C$4 - 2014)*13 + 3) -> 535933925 | G35: =INDEX(MOP_Mes_Corriente!$1:$161, 38, 3 + ($C$4 - 2014)*13 + 4) + INDEX(MOP_Mes_Corriente!$1:$161, 77, 3 + ($C$4 - 2014)*13 + 4) + INDEX(MOP_Mes_Corriente!$1:$161, 116, 3 + ($C$4 - 2014)*13 + 4) -> 735766967 | H35: =INDEX(MOP_Mes_Corriente!$1:$161, 38, 3 + ($C$4 - 2014)*13 + 5) + INDEX(MOP_Mes_Corriente!$1:$161, 77, 3 + ($C$4 - 2014)*13 + 5) + INDEX(MOP_Mes_Corriente!$1:$161, 116, 3 + ($C$4 - 2014)*13 + 5) -> 1103900218 | I35: =INDEX(MOP_Mes_Corriente!$1:$161, 38, 3 + ($C$4 - 2014)*13 + 6) + INDEX(MOP_Mes_Corriente!$1:$161, 77, 3 + ($C$4 - 2014)*13 + 6) + INDEX(MOP_Mes_Corriente!$1:$161, 116, 3 + ($C$4 - 2014)*13 + 6) -> 1232252883 | J35: =INDEX(MOP_Mes_Corriente!$1:$161, 38, 3 + ($C$4 - 2014)*13 + 7) + INDEX(MOP_Mes_Corriente!$1:$161, 77, 3 + ($C$4 - 2014)*13 + 7) + INDEX(MOP_Mes_Corriente!$1:$161, 116, 3 + ($C$4 - 2014)*13 + 7) -> 1374995854 | K35: =INDEX(MOP_Mes_Corriente!$1:$161, 38, 3 + ($C$4 - 2014)*13 + 8) + INDEX(MOP_Mes_Corriente!$1:$161, 77, 3 + ($C$4 - 2014)*13 + 8) + INDEX(MOP_Mes_Corriente!$1:$161, 116, 3 + ($C$4 - 2014)*13 + 8) -> 1567303306 | L35: =INDEX(MOP_Mes_Corriente!$1:$161, 38, 3 + ($C$4 - 2014)*13 + 9) + INDEX(MOP_Mes_Corriente!$1:$161, 77, 3 + ($C$4 - 2014)*13 + 9) + INDEX(MOP_Mes_Corriente!$1:$161, 116, 3 + ($C$4 - 2014)*13 + 9) -> 1765889793 | M35: =INDEX(MOP_Mes_Corriente!$1:$161, 38, 3 + ($C$4 - 2014)*13 + 10) + INDEX(MOP_Mes_Corriente!$1:$161, 77, 3 + ($C$4 - 2014)*13 + 10) + INDEX(MOP_Mes_Corriente!$1:$161, 116, 3 + ($C$4 - 2014)*13 + 10) -> 2025828192 | N35: =INDEX(MOP_Mes_Corriente!$1:$161, 38, 3 + ($C$4 - 2014)*13 + 11) + INDEX(MOP_Mes_Corriente!$1:$161, 77, 3 + ($C$4 - 2014)*13 + 11) + INDEX(MOP_Mes_Corriente!$1:$161, 116, 3 + ($C$4 - 2014)*13 + 11) -> 2321713289 | O35: =INDEX(MOP_Mes_Corriente!$1:$161, 38, 3 + ($C$4 - 2014)*13 + 12) + INDEX(MOP_Mes_Corriente!$1:$161, 77, 3 + ($C$4 - 2014)*13 + 12) + INDEX(MOP_Mes_Corriente!$1:$161, 116, 3 + ($C$4 - 2014)*13 + 12) -> 2321713289
B36: % Avance Ejecución | C36: =IF(C34>0, C35/C34, 0) -> 3.4246933e-06 | D36: =IF(D34>0, D35/D34, 0) -> 0.054008301 | E36: =IF(E34>0, E35/E34, 0) -> 0.11915704 | F36: =IF(F34>0, F35/F34, 0) -> 0.19214379 | G36: =IF(G34>0, G35/G34, 0) -> 0.26381133 | H36: =IF(H34>0, H35/H34, 0) -> 0.39867663 | I36: =IF(I34>0, I35/I34, 0) -> 0.44503155 | J36: =IF(J34>0, J35/J34, 0) -> 0.49726417 | ... O36: =IF(O34>0, O35/O34, 0) -> 0.99607224
B38: TABLA 4: COMPARATIVA HISTÓRICA MULTIANUAL (2014 - 2026)
B40: Año | C40: Presupuesto Ley | D40: Presupuesto Vigente | E40: Ejecución Acumulada | F40: Saldo por Ejecutar | G40: % Ejecución | H40: Crec. Vigente (YoY) | I40: Crec. Ejecución (YoY)
B41: 2014 | C41: =MOP_Mes_Corriente!O14 + MOP_Mes_Corriente!O53 + MOP_Mes_Corriente!O92 -> 1084025889 | D41: =MOP_Mes_Corriente!O26 + MOP_Mes_Corriente!O65 + MOP_Mes_Corriente!O104 -> 1166387752 | E41: =MOP_Mes_Corriente!O38 + MOP_Mes_Corriente!O77 + MOP_Mes_Corriente!O116 -> 1164341987 | F41: =D41 - E41 -> 2045765 | G41: =IF(D41>0, E41/D41, 0) -> 0.99824607 | H41: - | I41: -
B42: 2015 | C42: =MOP_Mes_Corriente!AB14 + MOP_Mes_Corriente!AB53 + MOP_Mes_Corriente!AB92 -> 1280988401 | D42: =MOP_Mes_Corriente!AB26 + MOP_Mes_Corriente!AB65 + MOP_Mes_Corriente!AB104 -> 1327989832 | E42: =MOP_Mes_Corriente!AB38 + MOP_Mes_Corriente!AB77 + MOP_Mes_Corriente!AB116 -> 1325414832 | F42: =D42 - E42 -> 2575000 | G42: =IF(D42>0, E42/D42, 0) -> 0.99806098 | H42: =IF(D41>0, (D42-D41)/D41, 0) -> 0.13854919 | I42: =IF(E41>0, (E42-E41)/E41, 0) -> 0.13833809
B43: 2016 | C43: =MOP_Mes_Corriente!AO14 + MOP_Mes_Corriente!AO53 + MOP_Mes_Corriente!AO92 -> 1280211801 | D43: =MOP_Mes_Corriente!AO26 + MOP_Mes_Corriente!AO65 + MOP_Mes_Corriente!AO104 -> 1282280297 | E43: =MOP_Mes_Corriente!AO38 + MOP_Mes_Corriente!AO77 + MOP_Mes_Corriente!AO116 -> 1279809174 | F43: =D43 - E43 -> 2471123 | G43: =IF(D43>0, E43/D43, 0) -> 0.99807287 | H43: =IF(D42>0, (D43-D42)/D42, 0) -> -0.034420094 | I43: =IF(E42>0, (E43-E42)/E42, 0) -> -0.034408592
B44: 2017 | C44: =MOP_Mes_Corriente!BB14 + MOP_Mes_Corriente!BB53 + MOP_Mes_Corriente!BB92 -> 1341993281 | D44: =MOP_Mes_Corriente!BB26 + MOP_Mes_Corriente!BB65 + MOP_Mes_Corriente!BB104 -> 1319688378 | E44: =MOP_Mes_Corriente!BB38 + MOP_Mes_Corriente!BB77 + MOP_Mes_Corriente!BB116 -> 1316094896 | F44: =D44 - E44 -> 3593482 | G44: =IF(D44>0, E44/D44, 0) -> 0.99727702 | H44: =IF(D43>0, (D44-D43)/D43, 0) -> 0.029173092 | I44: =IF(E43>0, (E44-E43)/E43, 0) -> 0.028352447
B45: 2018 | C45: =MOP_Mes_Corriente!BO14 + MOP_Mes_Corriente!BO53 + MOP_Mes_Corriente!BO92 -> 1360411524 | D45: =MOP_Mes_Corriente!BO26 + MOP_Mes_Corriente!BO65 + MOP_Mes_Corriente!BO104 -> 1257040244 | E45: =MOP_Mes_Corriente!BO38 + MOP_Mes_Corriente!BO77 + MOP_Mes_Corriente!BO116 -> 1252583084 | F45: =D45 - E45 -> 4457160 | G45: =IF(D45>0, E45/D45, 0) -> 0.99645424 | H45: =IF(D44>0, (D45-D44)/D44, 0) -> -0.047471915 | I45: =IF(E44>0, (E45-E44)/E44, 0) -> -0.048257775
B46: 2019 | C46: =MOP_Mes_Corriente!CB14 + MOP_Mes_Corriente!CB53 + MOP_Mes_Corriente!CB92 -> 1453655213 | D46: =MOP_Mes_Corriente!CB26 + MOP_Mes_Corriente!CB65 + MOP_Mes_Corriente!CB104 -> 1476564275 | E46: =MOP_Mes_Corriente!CB38 + MOP_Mes_Corriente!CB77 + MOP_Mes_Corriente!CB116 -> 1462473656 | F46: =D46 - E46 -> 14090619 | G46: =IF(D46>0, E46/D46, 0) -> 0.99045716 | H46: =IF(D45>0, (D46-D45)/D45, 0) -> 0.17463564 | I46: =IF(E45>0, (E46-E45)/E45, 0) -> 0.16756619
B47: 2020 | C47: =MOP_Mes_Corriente!CO14 + MOP_Mes_Corriente!CO53 + MOP_Mes_Corriente!CO92 -> 1578601711 | D47: =MOP_Mes_Corriente!CO26 + MOP_Mes_Corriente!CO65 + MOP_Mes_Corriente!CO104 -> 1397548041 | E47: =MOP_Mes_Corriente!CO38 + MOP_Mes_Corriente!CO77 + MOP_Mes_Corriente!CO116 -> 1373767417 | F47: =D47 - E47 -> 23780624 | G47: =IF(D47>0, E47/D47, 0) -> 0.98298404 | H47: =IF(D46>0, (D47-D46)/D46, 0) -> -0.053513576 | I47: =IF(E46>0, (E47-E46)/E46, 0) -> -0.060654931
B48: 2021 | C48: =MOP_Mes_Corriente!DB14 + MOP_Mes_Corriente!DB53 + MOP_Mes_Corriente!DB92 -> 2326773489 | D48: =MOP_Mes_Corriente!DB26 + MOP_Mes_Corriente!DB65 + MOP_Mes_Corriente!DB104 -> 1577529365 | E48: =MOP_Mes_Corriente!DB38 + MOP_Mes_Corriente!DB77 + MOP_Mes_Corriente!DB116 -> 1391673062 | F48: =D48 - E48 -> 185856303 | G48: =IF(D48>0, E48/D48, 0) -> 0.8821852 | H48: =IF(D47>0, (D48-D47)/D47, 0) -> 0.12878364 | I48: =IF(E47>0, (E48-E47)/E47, 0) -> 0.013033971
B49: 2022 | C49: =MOP_Mes_Corriente!DO14 + MOP_Mes_Corriente!DO53 + MOP_Mes_Corriente!DO92 -> 2620025909 | D49: =MOP_Mes_Corriente!DO26 + MOP_Mes_Corriente!DO65 + MOP_Mes_Corriente!DO104 -> 1358582828 | E49: =MOP_Mes_Corriente!DO38 + MOP_Mes_Corriente!DO77 + MOP_Mes_Corriente!DO116 -> 1340723690 | F49: =D49 - E49 -> 17859138 | G49: =IF(D49>0, E49/D49, 0) -> 0.98685458 | H49: =IF(D48>0, (D49-D48)/D48, 0) -> -0.13879078 | I49: =IF(E48>0, (E49-E48)/E48, 0) -> -0.036610159
B50: 2023 | C50: =MOP_Mes_Corriente!EB14 + MOP_Mes_Corriente!EB53 + MOP_Mes_Corriente!EB92 -> 2835156480 | D50: =MOP_Mes_Corriente!EB26 + MOP_Mes_Corriente!EB65 + MOP_Mes_Corriente!EB104 -> 2132837420 | E50: =MOP_Mes_Corriente!EB38 + MOP_Mes_Corriente!EB77 + MOP_Mes_Corriente!EB116 -> 2106371463 | F50: =D50 - E50 -> 26465957 | G50: =IF(D50>0, E50/D50, 0) -> 0.9875912 | H50: =IF(D49>0, (D50-D49)/D49, 0) -> 0.5698987 | I50: =IF(E49>0, (E50-E49)/E49, 0) -> 0.57107052
B51: 2024 | C51: =MOP_Mes_Corriente!EO14 + MOP_Mes_Corriente!EO53 + MOP_Mes_Corriente!EO92 -> 2942161253 | D51: =MOP_Mes_Corriente!EO26 + MOP_Mes_Corriente!EO65 + MOP_Mes_Corriente!EO104 -> 2330868371 | E51: =MOP_Mes_Corriente!EO38 + MOP_Mes_Corriente!EO77 + MOP_Mes_Corriente!EO116 -> 2321713289 | F51: =D51 - E51 -> 9155082 | G51: =IF(D51>0, E51/D51, 0) -> 0.99607224 | H51: =IF(D50>0, (D51-D50)/D50, 0) -> 0.092848592 | I51: =IF(E50>0, (E51-E50)/E50, 0) -> 0.10223355
B52: 2025 | C52: =MOP_Mes_Corriente!FB14 + MOP_Mes_Corriente!FB53 + MOP_Mes_Corriente!FB92 -> 3058423954 | D52: =MOP_Mes_Corriente!FB26 + MOP_Mes_Corriente!FB65 + MOP_Mes_Corriente!FB104 -> 2814546937 | E52: =MOP_Mes_Corriente!FB38 + MOP_Mes_Corriente!FB77 + MOP_Mes_Corriente!FB116 -> 2769768945 | F52: =D52 - E52 -> 44777992 | G52: =IF(D52>0, E52/D52, 0) -> 0.98409052 | H52: =IF(D51>0, (D52-D51)/D51, 0) -> 0.20751003 | I52: =IF(E51>0, (E52-E51)/E51, 0) -> 0.19298492
B53: 2026 | C53: =MOP_Mes_Corriente!FO14 + MOP_Mes_Corriente!FO53 + MOP_Mes_Corriente!FO92 -> 2710709303 | D53: =MOP_Mes_Corriente!FO26 + MOP_Mes_Corriente!FO65 + MOP_Mes_Corriente!FO104 -> 2542855698 | E53: =MOP_Mes_Corriente!FO38 + MOP_Mes_Corriente!FO77 + MOP_Mes_Corriente!FO116 -> 1238260857 | F53: =D53 - E53 -> 1304594841 | G53: =IF(D53>0, E53/D53, 0) -> 0.48695679 | H53: =IF(D52>0, (D53-D52)/D52, 0) -> -0.096531074 | I53: =IF(E52>0, (E53-E52)/E52, 0) -> -0.55293713

Sheet MOP_Mes_Corriente
B1: Ministerio de Obras Públicas – Partida 12
B2: Miles de pesos – moneda corriente – montos devengados
B3: Subtítulo 31 – Iniciativas de Inversión
B5: Presupuesto Ley de Inversión en Infraestructura Pública del Ministerio de Obras Públicas, 2014-2026 (Subtítulo 31 – Iniciativas de Inversión, miles de pesos)
C6: 2014 | P6: 2015 | AC6: 2016 | AP6: 2017 | BC6: 2018 | BP6: 2019 | CC6: 2020 | CP6: 2021(1) | DC6: 2022(1) | DP6: 2023 | EC6: 2024 | EP6: 2025 | FC6: 2026
B7: Programa | C7: Ene | D7: Feb | E7: Mar | F7: Abr | G7: May | H7: Jun | I7: Jul | J7: Ago | K7: Sep | L7: Oct | M7: Nov | N7: Dic | O7: Total 2014 | P7: Ene | Q7: Feb | R7: Mar | S7: Abr | T7: May | U7: Jun | V7: Jul | W7: Ago | X7: Sep | Y7: Oct | Z7: Nov | AA7: Dic | AB7: Total 2015 | AC7: Ene | AD7: Feb | AE7: Mar | AF7: Abr | AG7: May | AH7: Jun | AI7: Jul | AJ7: Ago | AK7: Sep | AL7: Oct | AM7: Nov | AN7: Dic | AO7: Total 2016 | AP7: Ene | AQ7: Feb | AR7: Mar | AS7: Abr | AT7: May | AU7: Jun | AV7: Jul | AW7: Ago | AX7: Sep | AY7: Oct | AZ7: Nov | BA7: Dic | BB7: Total 2017 | BC7: Ene | BD7: Feb | BE7: Mar | BF7: Abr | BG7: May | BH7: Jun | BI7: Jul | BJ7: Ago | BK7: Sep | BL7: Oct | BM7: Nov | BN7: Dic | BO7: Total 2018 | BP7: Ene | BQ7: Feb | BR7: Mar | BS7: Abr | BT7: May | BU7: Jun | BV7: Jul | BW7: Ago | BX7: Sep | BY7: Oct | BZ7: Nov | CA7: Dic | CB7: Total 2019 | CC7: Ene | CD7: Feb | CE7: Mar | CF7: Abr | CG7: May | CH7: Jun | CI7: Jul | CJ7: Ago | CK7: Sep | CL7: Oct | CM7: Nov | CN7: Dic | CO7: Total 2020 | CP7: Ene | CQ7: Feb | CR7: Mar | CS7: Abr | CT7: May | CU7: Jun | CV7: Jul | CW7: Ago | CX7: Sep | CY7: Oct | CZ7: Nov | DA7: Dic | DB7: Total 2021 | DC7: Ene | DD7: Feb | DE7: Mar | DF7: Abr | DG7: May | DH7: Jun | DI7: Jul | DJ7: Ago | DK7: Sep | DL7: Oct | DM7: Nov | DN7: Dic | DO7: Total 2022 | DP7: Ene | DQ7: Feb | DR7: Mar | DS7: Abr | DT7: May | DU7: Jun | DV7: Jul | DW7: Ago | DX7: Sep | DY7: Oct | DZ7: Nov | EA7: Dic | EB7: Total 2023 | EC7: Ene | ED7: Feb | EE7: Mar | EF7: Abr | EG7: May | EH7: Jun | EI7: Jul | EJ7: Ago | EK7: Sep | EL7: Oct | EM7: Nov | EN7: Dic | EO7: Total 2024 | EP7: Ene | EQ7: Feb | ER7: Mar | ES7: Abr | ET7: May | EU7: Jun | EV7: Jul | EW7: Ago | EX7: Sep | EY7: Oct | EZ7: Nov | FA7: Dic | FB7: Total 2025 | FC7: Ene | FD7: Feb | FE7: Mar | FF7: Abr | FG7: May | FH7: Jun | FI7: Jul | FJ7: Ago | FK7: Sep | FL7: Oct | FM7: Nov | FN7: Dic | FO7: Total 2026
B8: Dirección de Vialidad | C8: 806907228 | D8: 806907228 | E8: 806907228 | F8: 806907228 | G8: 806907228 | H8: 806907228 | I8: 806907228 | J8: 806907228 | K8: 806907228 | L8: 806907228 | M8: 806907228 | N8: 806907228 | O8: =N8 -> 806907228 | P8: 957407656 | Q8: 957407656 | R8: 957407656 | S8: 957407656 | T8: 957407656 | U8: 957407656 | V8: 957407656 | W8: 957407656 | X8: 957407656 | Y8: 957407656 | Z8: 957407656 | AA8: 957407656 | AB8: =AA8 -> 957407656 | AC8: 937156766 | AD8: 937156766 | AE8: 937156766 | AF8: 937156766 | AG8: 937156766 | AH8: 937156766 | AI8: 937156766 | AJ8: 937156766 | AK8: 937156766 | AL8: 937156766 | AM8: 937156766 | AN8: 937156766 | AO8: =AN8 -> 937156766 | AP8: 982538421 | AQ8: 982538421 | AR8: 982538421 | AS8: 982538421 | AT8: 982538421 | AU8: 982538421 | AV8: 982538421 | AW8: 982538421 | AX8: 982538421 | AY8: 982538421 | AZ8: 982538421 | BA8: 982538421 | BB8: =BA8 -> 982538421 | BC8: 998447263 | BD8: 998447263 | BE8: 998447263 | BF8: 998447263 | BG8: 998447263 | BH8: 998447263 | BI8: 998447263 | BJ8: 998447263 | BK8: 998447263 | BL8: 998447263 | BM8: 998447263 | BN8: 998447263 | BO8: =BN8 -> 998447263 | BP8: 1056398949 | BQ8: 1056398949 | BR8: 1056398949 | BS8: 1056398949 | BT8: 1056398949 | BU8: 1056398949 | BV8: 1056398949 | BW8: 1056398949 | BX8: 1056398949 | BY8: 1056398949 | BZ8: 1056398949 | CA8: 1056398949 | CB8: =CA8 -> 1056398949 | CC8: 1148358839 | CD8: 1148358839 | CE8: 1148358839 | CF8: 1148358839 | CG8: 1148358839 | CH8: 1148358839 | CI8: 1148358839 | CJ8: 1148358839 | CK8: 1148358839 | CL8: 1148358839 | CM8: 1148358839 | CN8: 1148358839 | CO8: =CN8 -> 1148358839 | CP8: =1224421462+380805877 -> 1605227339 | CQ8: =1224421462+380805877 -> 1605227339 | CR8: =1224421462+380805877 -> 1605227339 | CS8: =1224421462+380805877 -> 1605227339 | CT8: =1224421462+380805877 -> 1605227339 | CU8: =1224421462+380805877 -> 1605227339 | CV8: =1224421462+380805877 -> 1605227339 | CW8: =1224421462+380805877 -> 1605227339 | ... DA8: =1224421462+380805877 -> 1605227339 | DB8: =DA8 -> 1605227339 | DC8: =1220635546+581829225 -> 1802464771 | DD8: =1220635546+581829225 -> 1802464771 | DE8: =1220635546+581829225 -> 1802464771 | DF8: =1220635546+581829225 -> 1802464771 | DG8: =1220635546+581829225 -> 1802464771 | DH8: =1220635546+581829225 -> 1802464771 | DI8: =1220635546+581829225 -> 1802464771 | DJ8: =1220635546+581829225 -> 1802464771 | ... DN8: =1220635546+581829225 -> 1802464771 | DO8: =DN8 -> 1802464771 | DP8: 1913855137 | DQ8: 1913855137 | DR8: 1913855137 | DS8: 1913855137 | DT8: 1913855137 | DU8: 1913855137 | DV8: 1913855137 | DW8: 1913855137 | DX8: 1913855137 | DY8: 1913855137 | DZ8: 1913855137 | EA8: 1913855137 | EB8: =EA8 -> 1913855137 | EC8: 2012684680 | ED8: 2012684680 | EE8: 2012684680 | EF8: 2012684680 | EG8: 2012684680 | EH8: 2012684680 | EI8: 2012684680 | EJ8: 2012684680 | EK8: 2012684680 | EL8: 2012684680 | EM8: 2012684680 | EN8: 2012684680 | EO8: =EN8 -> 2012684680 | EP8: 2083103023 | EQ8: 2083103023 | ER8: 2083103023 | ES8: 2083103023 | ET8: 2083103023 | EU8: 2083103023 | EV8: 2083103023 | EW8: 2083103023 | EX8: 2083103023 | EY8: 2083103023 | EZ8: 2083103023 | FA8: 2083103023 | FB8: =FA8 -> 2083103023 | FC8: 1951485600 | FD8: 1951485600 | FE8: 1951485600 | FF8: 1951485600 | FG8: 1951485600 | FH8: 1951485600 | FI8: 1951485600 | FO8: =FI8 -> 1951485600
B9: Dirección de Obras Hidráulicas | C9: 101236706 | D9: 101236706 | E9: 101236706 | F9: 101236706 | G9: 101236706 | H9: 101236706 | I9: 101236706 | J9: 101236706 | K9: 101236706 | L9: 101236706 | M9: 101236706 | N9: 101236706 | O9: =N9 -> 101236706 | P9: 117398169 | Q9: 117398169 | R9: 117398169 | S9: 117398169 | T9: 117398169 | U9: 117398169 | V9: 117398169 | W9: 117398169 | X9: 117398169 | Y9: 117398169 | Z9: 117398169 | AA9: 117398169 | AB9: =AA9 -> 117398169 | AC9: 127292924 | AD9: 127292924 | AE9: 127292924 | AF9: 127292924 | AG9: 127292924 | AH9: 127292924 | AI9: 127292924 | AJ9: 127292924 | AK9: 127292924 | AL9: 127292924 | AM9: 127292924 | AN9: 127292924 | AO9: =AN9 -> 127292924 | AP9: 121635713 | AQ9: 121635713 | AR9: 121635713 | AS9: 121635713 | AT9: 121635713 | AU9: 121635713 | AV9: 121635713 | AW9: 121635713 | AX9: 121635713 | AY9: 121635713 | AZ9: 121635713 | BA9: 121635713 | BB9: =BA9 -> 121635713 | BC9: 119785354 | BD9: 119785354 | BE9: 119785354 | BF9: 119785354 | BG9: 119785354 | BH9: 119785354 | BI9: 119785354 | BJ9: 119785354 | BK9: 119785354 | BL9: 119785354 | BM9: 119785354 | BN9: 119785354 | BO9: =BN9 -> 119785354 | BP9: 129182602 | BQ9: 129182602 | BR9: 129182602 | BS9: 129182602 | BT9: 129182602 | BU9: 129182602 | BV9: 129182602 | BW9: 129182602 | BX9: 129182602 | BY9: 129182602 | BZ9: 129182602 | CA9: 129182602 | CB9: =CA9 -> 129182602 | CC9: 137671350 | CD9: 137671350 | CE9: 137671350 | CF9: 137671350 | CG9: 137671350 | CH9: 137671350 | CI9: 137671350 | CJ9: 137671350 | CK9: 137671350 | CL9: 137671350 | CM9: 137671350 | CN9: 137671350 | CO9: =CN9 -> 137671350 | CP9: =140801596+100700947 -> 241502543 | CQ9: =140801596+100700947 -> 241502543 | CR9: =140801596+100700947 -> 241502543 | CS9: =140801596+100700947 -> 241502543 | CT9: =140801596+100700947 -> 241502543 | CU9: =140801596+100700947 -> 241502543 | CV9: =140801596+100700947 -> 241502543 | CW9: =140801596+100700947 -> 241502543 | ... DA9: =140801596+100700947 -> 241502543 | DB9: =DA9 -> 241502543 | DC9: =147022684+130812721 -> 277835405 | DD9: =147022684+130812721 -> 277835405 | DE9: =147022684+130812721 -> 277835405 | DF9: =147022684+130812721 -> 277835405 | DG9: =147022684+130812721 -> 277835405 | DH9: =147022684+130812721 -> 277835405 | DI9: =147022684+130812721 -> 277835405 | DJ9: =147022684+130812721 -> 277835405 | ... DN9: =147022684+130812721 -> 277835405 | DO9: =DN9 -> 277835405 | DP9: 293591805 | DQ9: 293591805 | DR9: 293591805 | DS9: 293591805 | DT9: 293591805 | DU9: 293591805 | DV9: 293591805 | DW9: 293591805 | DX9: 293591805 | DY9: 293591805 | DZ9: 293591805 | EA9: 293591805 | EB9: =EA9 -> 293591805 | EC9: 295701947 | ED9: 295701947 | EE9: 295701947 | EF9: 295701947 | EG9: 295701947 | EH9: 295701947 | EI9: 295701947 | EJ9: 295701947 | EK9: 295701947 | EL9: 295701947 | EM9: 295701947 | EN9: 295701947 | EO9: =EN9 -> 295701947 | EP9: 308121429 | EQ9: 308121429 | ER9: 308121429 | ES9: 308121429 | ET9: 308121429 | EU9: 308121429 | EV9: 308121429 | EW9: 308121429 | EX9: 308121429 | EY9: 308121429 | EZ9: 308121429 | FA9: 308121429 | FB9: =FA9 -> 308121429 | FC9: 195906100 | FD9: 195906100 | FE9: 195906100 | FF9: 195906100 | FG9: 195906100 | FH9: 195906100 | FI9: 195906100 | FO9: =FI9 -> 195906100
B10: Subdirección de APR | C10: 49407947 | D10: 49407947 | E10: 49407947 | F10: 49407947 | G10: 49407947 | H10: 49407947 | I10: 49407947 | J10: 49407947 | K10: 49407947 | L10: 49407947 | M10: 49407947 | N10: 49407947 | O10: =N10 -> 49407947 | P10: 68884752 | Q10: 68884752 | R10: 68884752 | S10: 68884752 | T10: 68884752 | U10: 68884752 | V10: 68884752 | W10: 68884752 | X10: 68884752 | Y10: 68884752 | Z10: 68884752 | AA10: 68884752 | AB10: =AA10 -> 68884752 | AC10: 71502372 | AD10: 71502372 | AE10: 71502372 | AF10: 71502372 | AG10: 71502372 | AH10: 71502372 | AI10: 71502372 | AJ10: 71502372 | AK10: 71502372 | AL10: 71502372 | AM10: 71502372 | AN10: 71502372 | AO10: =AN10 -> 71502372 | AP10: 89991483 | AQ10: 89991483 | AR10: 89991483 | AS10: 89991483 | AT10: 89991483 | AU10: 89991483 | AV10: 89991483 | AW10: 89991483 | AX10: 89991483 | AY10: 89991483 | AZ10: 89991483 | BA10: 89991483 | BB10: =BA10 -> 89991483 | BC10: 102433801 | BD10: 102433801 | BE10: 102433801 | BF10: 102433801 | BG10: 102433801 | BH10: 102433801 | BI10: 102433801 | BJ10: 102433801 | BK10: 102433801 | BL10: 102433801 | BM10: 102433801 | BN10: 102433801 | BO10: =BN10 -> 102433801 | BP10: 114691671 | BQ10: 114691671 | BR10: 114691671 | BS10: 114691671 | BT10: 114691671 | BU10: 114691671 | BV10: 114691671 | BW10: 114691671 | BX10: 114691671 | BY10: 114691671 | BZ10: 114691671 | CA10: 114691671 | CB10: =CA10 -> 114691671 | CC10: 135338654 | CD10: 135338654 | CE10: 135338654 | CF10: 135338654 | CG10: 135338654 | CH10: 135338654 | CI10: 135338654 | CJ10: 135338654 | CK10: 135338654 | CL10: 135338654 | CM10: 135338654 | CN10: 135338654 | CO10: =CN10 -> 135338654 | CP10: =142048072+104543895 -> 246591967 | CQ10: =142048072+104543895 -> 246591967 | CR10: =142048072+104543895 -> 246591967 | CS10: =142048072+104543895 -> 246591967 | CT10: =142048072+104543895 -> 246591967 | CU10: =142048072+104543895 -> 246591967 | CV10: =142048072+104543895 -> 246591967 | CW10: =142048072+104543895 -> 246591967 | ... DA10: =142048072+104543895 -> 246591967 | DB10: =DA10 -> 246591967 | DC10: =148440561+129907392 -> 278347953 | DD10: =148440561+129907392 -> 278347953 | DE10: =148440561+129907392 -> 278347953 | DF10: =148440561+129907392 -> 278347953 | DG10: =148440561+129907392 -> 278347953 | DH10: =148440561+129907392 -> 278347953 | DI10: =148440561+129907392 -> 278347953 | DJ10: =148440561+129907392 -> 278347953 | ... DN10: =148440561+129907392 -> 278347953 | DO10: =DN10 -> 278347953 | DP10: 295780655 | DQ10: 295780655 | DR10: 295780655 | DS10: 295780655 | DT10: 295780655 | DU10: 295780655 | DV10: 295780655 | DW10: 295780655 | DX10: 295780655 | DY10: 295780655 | DZ10: 295780655 | EA10: 295780655 | EB10: =EA10 -> 295780655 | EC10: 315696642 | ED10: 315696642 | EE10: 315696642 | EF10: 315696642 | EG10: 315696642 | EH10: 315696642 | EI10: 315696642 | EJ10: 315696642 | EK10: 315696642 | EL10: 315696642 | EM10: 315696642 | EN10: 315696642 | EO10: =EN10 -> 315696642 | EP10: 329603442 | EQ10: 329603442 | ER10: 329603442 | ES10: 329603442 | ET10: 329603442 | EU10: 329603442 | EV10: 329603442 | EW10: 329603442 | EX10: 329603442 | EY10: 329603442 | EZ10: 329603442 | FA10: 329603442 | FB10: =FA10 -> 329603442 | FC10: 290113797 | FD10: 290113797 | FE10: 290113797 | FF10: 290113797 | FG10: 290113797 | FH10: 290113797 | FI10: 290113797 | FO10: =FI10 -> 290113797
B11: Dirección de Obras Portuarias | C11: 55038550 | D11: 55038550 | E11: 55038550 | F11: 55038550 | G11: 55038550 | H11: 55038550 | I11: 55038550 | J11: 55038550 | K11: 55038550 | L11: 55038550 | M11: 55038550 | N11: 55038550 | O11: =N11 -> 55038550 | P11: 63737311 | Q11: 63737311 | R11: 63737311 | S11: 63737311 | T11: 63737311 | U11: 63737311 | V11: 63737311 | W11: 63737311 | X11: 63737311 | Y11: 63737311 | Z11: 63737311 | AA11: 63737311 | AB11: =AA11 -> 63737311 | AC11: 66005341 | AD11: 66005341 | AE11: 66005341 | AF11: 66005341 | AG11: 66005341 | AH11: 66005341 | AI11: 66005341 | AJ11: 66005341 | AK11: 66005341 | AL11: 66005341 | AM11: 66005341 | AN11: 66005341 | AO11: =AN11 -> 66005341 | AP11: 68152361 | AQ11: 68152361 | AR11: 68152361 | AS11: 68152361 | AT11: 68152361 | AU11: 68152361 | AV11: 68152361 | AW11: 68152361 | AX11: 68152361 | AY11: 68152361 | AZ11: 68152361 | BA11: 68152361 | BB11: =BA11 -> 68152361 | BC11: 69097793 | BD11: 69097793 | BE11: 69097793 | BF11: 69097793 | BG11: 69097793 | BH11: 69097793 | BI11: 69097793 | BJ11: 69097793 | BK11: 69097793 | BL11: 69097793 | BM11: 69097793 | BN11: 69097793 | BO11: =BN11 -> 69097793 | BP11: 69888575 | BQ11: 69888575 | BR11: 69888575 | BS11: 69888575 | BT11: 69888575 | BU11: 69888575 | BV11: 69888575 | BW11: 69888575 | BX11: 69888575 | BY11: 69888575 | BZ11: 69888575 | CA11: 69888575 | CB11: =CA11 -> 69888575 | CC11: 71705676 | CD11: 71705676 | CE11: 71705676 | CF11: 71705676 | CG11: 71705676 | CH11: 71705676 | CI11: 71705676 | CJ11: 71705676 | CK11: 71705676 | CL11: 71705676 | CM11: 71705676 | CN11: 71705676 | CO11: =CN11 -> 71705676 | CP11: =73670723+10507533 -> 84178256 | CQ11: =73670723+10507533 -> 84178256 | CR11: =73670723+10507533 -> 84178256 | CS11: =73670723+10507533 -> 84178256 | CT11: =73670723+10507533 -> 84178256 | CU11: =73670723+10507533 -> 84178256 | CV11: =73670723+10507533 -> 84178256 | CW11: =73670723+10507533 -> 84178256 | ... DA11: =73670723+10507533 -> 84178256 | DB11: =DA11 -> 84178256 | DC11: =76882481+23172423 -> 100054904 | DD11: =76882481+23172423 -> 100054904 | DE11: =76882481+23172423 -> 100054904 | DF11: =76882481+23172423 -> 100054904 | DG11: =76882481+23172423 -> 100054904 | DH11: =76882481+23172423 -> 100054904 | DI11: =76882481+23172423 -> 100054904 | DJ11: =76882481+23172423 -> 100054904 | ... DN11: =76882481+23172423 -> 100054904 | DO11: =DN11 -> 100054904 | DP11: 115171552 | DQ11: 115171552 | DR11: 115171552 | DS11: 115171552 | DT11: 115171552 | DU11: 115171552 | DV11: 115171552 | DW11: 115171552 | DX11: 115171552 | DY11: 115171552 | DZ11: 115171552 | EA11: 115171552 | EB11: =EA11 -> 115171552 | EC11: 127117895 | ED11: 127117895 | EE11: 127117895 | EF11: 127117895 | EG11: 127117895 | EH11: 127117895 | EI11: 127117895 | EJ11: 127117895 | EK11: 127117895 | EL11: 127117895 | EM11: 127117895 | EN11: 127117895 | EO11: =EN11 -> 127117895 | EP11: 125417585 | EQ11: 125417585 | ER11: 125417585 | ES11: 125417585 | ET11: 125417585 | EU11: 125417585 | EV11: 125417585 | EW11: 125417585 | EX11: 125417585 | EY11: 125417585 | EZ11: 125417585 | FA11: 125417585 | FB11: =FA11 -> 125417585 | FC11: 109909690 | FD11: 109909690 | FE11: 109909690 | FF11: 109909690 | FG11: 109909690 | FH11: 109909690 | FI11: 109909690 | FO11: =FI11 -> 109909690
B12: Dirección de Aeropuertos | C12: 41285665 | D12: 41285665 | E12: 41285665 | F12: 41285665 | G12: 41285665 | H12: 41285665 | I12: 41285665 | J12: 41285665 | K12: 41285665 | L12: 41285665 | M12: 41285665 | N12: 41285665 | O12: =N12 -> 41285665 | P12: 41009608 | Q12: 41009608 | R12: 41009608 | S12: 41009608 | T12: 41009608 | U12: 41009608 | V12: 41009608 | W12: 41009608 | X12: 41009608 | Y12: 41009608 | Z12: 41009608 | AA12: 41009608 | AB12: =AA12 -> 41009608 | AC12: 43953347 | AD12: 43953347 | AE12: 43953347 | AF12: 43953347 | AG12: 43953347 | AH12: 43953347 | AI12: 43953347 | AJ12: 43953347 | AK12: 43953347 | AL12: 43953347 | AM12: 43953347 | AN12: 43953347 | AO12: =AN12 -> 43953347 | AP12: 45271947 | AQ12: 45271947 | AR12: 45271947 | AS12: 45271947 | AT12: 45271947 | AU12: 45271947 | AV12: 45271947 | AW12: 45271947 | AX12: 45271947 | AY12: 45271947 | AZ12: 45271947 | BA12: 45271947 | BB12: =BA12 -> 45271947 | BC12: 35602336 | BD12: 35602336 | BE12: 35602336 | BF12: 35602336 | BG12: 35602336 | BH12: 35602336 | BI12: 35602336 | BJ12: 35602336 | BK12: 35602336 | BL12: 35602336 | BM12: 35602336 | BN12: 35602336 | BO12: =BN12 -> 35602336 | BP12: 53068499 | BQ12: 53068499 | BR12: 53068499 | BS12: 53068499 | BT12: 53068499 | BU12: 53068499 | BV12: 53068499 | BW12: 53068499 | BX12: 53068499 | BY12: 53068499 | BZ12: 53068499 | CA12: 53068499 | CB12: =CA12 -> 53068499 | CC12: 58584599 | CD12: 58584599 | CE12: 58584599 | CF12: 58584599 | CG12: 58584599 | CH12: 58584599 | CI12: 58584599 | CJ12: 58584599 | CK12: 58584599 | CL12: 58584599 | CM12: 58584599 | CN12: 58584599 | CO12: =CN12 -> 58584599 | CP12: =60144148+46830346 -> 106974494 | CQ12: =60144148+46830346 -> 106974494 | CR12: =60144148+46830346 -> 106974494 | CS12: =60144148+46830346 -> 106974494 | CT12: =60144148+46830346 -> 106974494 | CU12: =60144148+46830346 -> 106974494 | CV12: =60144148+46830346 -> 106974494 | CW12: =60144148+46830346 -> 106974494 | ... DA12: =60144148+46830346 -> 106974494 | DB12: =DA12 -> 106974494 | DC12: =62797413+55033938 -> 117831351 | DD12: =62797413+55033938 -> 117831351 | DE12: =62797413+55033938 -> 117831351 | DF12: =62797413+55033938 -> 117831351 | DG12: =62797413+55033938 -> 117831351 | DH12: =62797413+55033938 -> 117831351 | DI12: =62797413+55033938 -> 117831351 | DJ12: =62797413+55033938 -> 117831351 | ... DN12: =62797413+55033938 -> 117831351 | DO12: =DN12 -> 117831351 | DP12: 135318267 | DQ12: 135318267 | DR12: 135318267 | DS12: 135318267 | DT12: 135318267 | DU12: 135318267 | DV12: 135318267 | DW12: 135318267 | DX12: 135318267 | DY12: 135318267 | DZ12: 135318267 | EA12: 135318267 | EB12: =EA12 -> 135318267 | EC12: 137741639 | ED12: 137741639 | EE12: 137741639 | EF12: 137741639 | EG12: 137741639 | EH12: 137741639 | EI12: 137741639 | EJ12: 137741639 | EK12: 137741639 | EL12: 137741639 | EM12: 137741639 | EN12: 137741639 | EO12: =EN12 -> 137741639 | EP12: 141825431 | EQ12: 141825431 | ER12: 141825431 | ES12: 141825431 | ET12: 141825431 | EU12: 141825431 | EV12: 141825431 | EW12: 141825431 | EX12: 141825431 | EY12: 141825431 | EZ12: 141825431 | FA12: 141825431 | FB12: =FA12 -> 141825431 | FC12: 127610750 | FD12: 127610750 | FE12: 127610750 | FF12: 127610750 | FG12: 127610750 | FH12: 127610750 | FI12: 127610750 | FO12: =FI12 -> 127610750
B13: Dirección de Arquitectura | C13: 26272563 | D13: 26272563 | E13: 26272563 | F13: 26272563 | G13: 26272563 | H13: 26272563 | I13: 26272563 | J13: 26272563 | K13: 26272563 | L13: 26272563 | M13: 26272563 | N13: 26272563 | O13: =N13 -> 26272563 | P13: 28203580 | Q13: 28203580 | R13: 28203580 | S13: 28203580 | T13: 28203580 | U13: 28203580 | V13: 28203580 | W13: 28203580 | X13: 28203580 | Y13: 28203580 | Z13: 28203580 | AA13: 28203580 | AB13: =AA13 -> 28203580 | AC13: 25719874 | AD13: 25719874 | AE13: 25719874 | AF13: 25719874 | AG13: 25719874 | AH13: 25719874 | AI13: 25719874 | AJ13: 25719874 | AK13: 25719874 | AL13: 25719874 | AM13: 25719874 | AN13: 25719874 | AO13: =AN13 -> 25719874 | AP13: 28283754 | AQ13: 28283754 | AR13: 28283754 | AS13: 28283754 | AT13: 28283754 | AU13: 28283754 | AV13: 28283754 | AW13: 28283754 | AX13: 28283754 | AY13: 28283754 | AZ13: 28283754 | BA13: 28283754 | BB13: =BA13 -> 28283754 | BC13: 30504194 | BD13: 30504194 | BE13: 30504194 | BF13: 30504194 | BG13: 30504194 | BH13: 30504194 | BI13: 30504194 | BJ13: 30504194 | BK13: 30504194 | BL13: 30504194 | BM13: 30504194 | BN13: 30504194 | BO13: =BN13 -> 30504194 | BP13: 25853361 | BQ13: 25853361 | BR13: 25853361 | BS13: 25853361 | BT13: 25853361 | BU13: 25853361 | BV13: 25853361 | BW13: 25853361 | BX13: 25853361 | BY13: 25853361 | BZ13: 25853361 | CA13: 25853361 | CB13: =CA13 -> 25853361 | CC13: 22096777 | CD13: 22096777 | CE13: 22096777 | CF13: 22096777 | CG13: 22096777 | CH13: 22096777 | CI13: 22096777 | CJ13: 22096777 | CK13: 22096777 | CL13: 22096777 | CM13: 22096777 | CN13: 22096777 | CO13: =CN13 -> 22096777 | CP13: =11904427+25061381 -> 36965808 | CQ13: =11904427+25061381 -> 36965808 | CR13: =11904427+25061381 -> 36965808 | CS13: =11904427+25061381 -> 36965808 | CT13: =11904427+25061381 -> 36965808 | CU13: =11904427+25061381 -> 36965808 | CV13: =11904427+25061381 -> 36965808 | CW13: =11904427+25061381 -> 36965808 | ... DA13: =11904427+25061381 -> 36965808 | DB13: =DA13 -> 36965808 | DC13: =8974172+32064677 -> 41038849 | DD13: =8974172+32064677 -> 41038849 | DE13: =8974172+32064677 -> 41038849 | DF13: =8974172+32064677 -> 41038849 | DG13: =8974172+32064677 -> 41038849 | DH13: =8974172+32064677 -> 41038849 | DI13: =8974172+32064677 -> 41038849 | DJ13: =8974172+32064677 -> 41038849 | ... DN13: =8974172+32064677 -> 41038849 | DO13: =DN13 -> 41038849 | DP13: 37590026 | DQ13: 37590026 | DR13: 37590026 | DS13: 37590026 | DT13: 37590026 | DU13: 37590026 | DV13: 37590026 | DW13: 37590026 | DX13: 37590026 | DY13: 37590026 | DZ13: 37590026 | EA13: 37590026 | EB13: =EA13 -> 37590026 | EC13: 44570138 | ED13: 44570138 | EE13: 44570138 | EF13: 44570138 | EG13: 44570138 | EH13: 44570138 | EI13: 44570138 | EJ13: 44570138 | EK13: 44570138 | EL13: 44570138 | EM13: 44570138 | EN13: 44570138 | EO13: =EN13 -> 44570138 | EP13: 57109595 | EQ13: 57109595 | ER13: 57109595 | ES13: 57109595 | ET13: 57109595 | EU13: 57109595 | EV13: 57109595 | EW13: 57109595 | EX13: 57109595 | EY13: 57109595 | EZ13: 57109595 | FA13: 57109595 | FB13: =FA13 -> 57109595 | FC13: 30479549 | FD13: 30479549 | FE13: 30479549 | FF13: 30479549 | FG13: 30479549 | FH13: 30479549 | FI13: 30479549 | FO13: =FI13 -> 30479549
B14: Total | C14: =SUM(C8:C13) -> 1080148659 | D14: =SUM(D8:D13) -> 1080148659 | E14: =SUM(E8:E13) -> 1080148659 | F14: =SUM(F8:F13) -> 1080148659 | G14: =SUM(G8:G13) -> 1080148659 | H14: =SUM(H8:H13) -> 1080148659 | I14: =SUM(I8:I13) -> 1080148659 | J14: =SUM(J8:J13) -> 1080148659 | ... FO14: =SUM(FO8:FO13) -> 2705505486
B15: (1) Los años 2021 y 2022 incluyen el Presupuesto Ley del Subtítulo 30, Ítem 10. Fuente: elaboración propia, Dipres.
B17: Presupuesto Vigente de Inversión en Infraestructura Pública del Ministerio de Obras Públicas, 2014-2026 (Subtítulo 31 – Iniciativas de Inversión, miles de pesos)
C18: 2014 | P18: 2015 | AC18: 2016 | AP18: 2017 | BC18: 2018 | BP18: 2019 | CC18: 2020 | CP18: 2021(1) | DC18: 2022(1) | DP18: 2023 | EC18: 2024 | EP18: 2025 | FC18: 2026
B19: Programa | C19: Ene | D19: Feb | E19: Mar | F19: Abr | G19: May | H19: Jun | I19: Jul | J19: Ago | K19: Sep | L19: Oct | M19: Nov | N19: Dic | O19: Total 2014 | P19: Ene | Q19: Feb | R19: Mar | S19: Abr | T19: May | U19: Jun | V19: Jul | W19: Ago | X19: Sep | Y19: Oct | Z19: Nov | AA19: Dic | AB19: Total 2015 | AC19: Ene | AD19: Feb | AE19: Mar | AF19: Abr | AG19: May | AH19: Jun | AI19: Jul | AJ19: Ago | AK19: Sep | AL19: Oct | AM19: Nov | AN19: Dic | AO19: Total 2016 | AP19: Ene | AQ19: Feb | AR19: Mar | AS19: Abr | AT19: May | AU19: Jun | AV19: Jul | AW19: Ago | AX19: Sep | AY19: Oct | AZ19: Nov | BA19: Dic | BB19: Total 2017 | BC19: Ene | BD19: Feb | BE19: Mar | BF19: Abr | BG19: May | BH19: Jun | BI19: Jul | BJ19: Ago | BK19: Sep | BL19: Oct | BM19: Nov | BN19: Dic | BO19: Total 2018 | BP19: Ene | BQ19: Feb | BR19: Mar | BS19: Abr | BT19: May | BU19: Jun | BV19: Jul | BW19: Ago | BX19: Sep | BY19: Oct | BZ19: Nov | CA19: Dic | CB19: Total 2019 | CC19: Ene | CD19: Feb | CE19: Mar | CF19: Abr | CG19: May | CH19: Jun | CI19: Jul | CJ19: Ago | CK19: Sep | CL19: Oct | CM19: Nov | CN19: Dic | CO19: Total 2020 | CP19: Ene | CQ19: Feb | CR19: Mar | CS19: Abr | CT19: May | CU19: Jun | CV19: Jul | CW19: Ago | CX19: Sep | CY19: Oct | CZ19: Nov | DA19: Dic | DB19: Total 2021 | DC19: Ene | DD19: Feb | DE19: Mar | DF19: Abr | DG19: May | DH19: Jun | DI19: Jul | DJ19: Ago | DK19: Sep | DL19: Oct | DM19: Nov | DN19: Dic | DO19: Total 2022 | DP19: Ene | DQ19: Feb | DR19: Mar | DS19: Abr | DT19: May | DU19: Jun | DV19: Jul | DW19: Ago | DX19: Sep | DY19: Oct | DZ19: Nov | EA19: Dic | EB19: Total 2023 | EC19: Ene | ED19: Feb | EE19: Mar | EF19: Abr | EG19: May | EH19: Jun | EI19: Jul | EJ19: Ago | EK19: Sep | EL19: Oct | EM19: Nov | EN19: Dic | EO19: Total 2024 | EP19: Ene | EQ19: Feb | ER19: Mar | ES19: Abr | ET19: May | EU19: Jun | EV19: Jul | EW19: Ago | EX19: Sep | EY19: Oct | EZ19: Nov | FA19: Dic | FB19: Total 2025 | FC19: Ene | FD19: Feb | FE19: Mar | FF19: Abr | FG19: May | FH19: Jun | FI19: Jul | FJ19: Ago | FK19: Sep | FL19: Oct | FM19: Nov | FN19: Dic | FO19: Total 2026
B20: Dirección de Vialidad | C20: 806907228 | D20: 806907228 | E20: 797207228 | F20: 797207228 | G20: 799193228 | H20: 801043262 | I20: 797883262 | J20: 817043262 | K20: 818043262 | L20: 842704970 | M20: 843143806 | N20: 853032416 | O20: =N20 -> 853032416 | P20: 957407656 | Q20: 958801347 | R20: 952446725 | S20: 944486725 | T20: 948962726 | U20: 949105726 | V20: 949005726 | W20: 949071698 | X20: 949071698 | Y20: 949071698 | Z20: 978416698 | AA20: 978378698 | AB20: =AA20 -> 978378698 | AC20: 937156766 | AD20: 930976766 | AE20: 939666557 | AF20: 937705385 | AG20: 937705385 | AH20: 937166385 | AI20: 937166385 | AJ20: 937166385 | AK20: 937166385 | AL20: 937166385 | AM20: 937073385 | AN20: 940884842 | AO20: =AN20 -> 940884842 | AP20: 982538421 | AQ20: 982538421 | AR20: 982260421 | AS20: 982260421 | AT20: 982060421 | AU20: 963745421 | AV20: 963304221 | AW20: 951169721 | AX20: 951169721 | AY20: 934145882 | AZ20: 931388882 | BA20: 909483945 | BB20: =BA20 -> 909483945 | BC20: 998447263 | BD20: 998447263 | BE20: 992502179 | BF20: 997730439 | BG20: 997415248 | BH20: 989715248 | BI20: 987815248 | BJ20: 987280248 | BK20: 987280248 | BL20: 987265248 | BM20: 986833548 | BN20: 903724337 | BO20: =BN20 -> 903724337 | BP20: 1056398949 | BQ20: 1056398949 | BR20: 1056398949 | BS20: 1061857019 | BT20: 1066368519 | BU20: 1061536519 | BV20: 1061502269 | BW20: 1074213648 | BX20: 1085679831 | BY20: 1085679831 | BZ20: 1085679831 | CA20: 1085267877 | CB20: =CA20 -> 1085267877 | CC20: 1148358839 | CD20: 1151054581 | CE20: 1248782581 | CF20: 1248782581 | CG20: 1216917979 | CH20: 1216917979 | CI20: 1216383979 | CJ20: 1216383979 | CK20: 1216383979 | CL20: 1197726086 | CM20: 1197588086 | CN20: 961564167 | CO20: =CN20 -> 961564167 | CP20: 1224421462 | CQ20: 1224421462 | CR20: 1139453884 | CS20: 1067186833 | CT20: 1048239333 | CU20: 1048217333 | CV20: 1048217333 | CW20: 1048116163 | CX20: 1048116163 | CY20: 1035718353 | CZ20: 1035625353 | DA20: =991797481+130932798 -> 1122730279 | DB20: =DA20 -> 1122730279 | DC20: 1220635546 | DD20: 1220635546 | DE20: 1220279119 | DF20: 1220279119 | DG20: 1218682119 | DH20: 1218249119 | DI20: 1092879968 | DJ20: 1092879968 | DK20: 1082339533 | DL20: 1082339533 | DM20: 1081913803 | DN20: 967670999 | DO20: =DN20 -> 967670999 | DP20: 1913855137 | DQ20: 1913855137 | DR20: 1913855137 | DS20: 1893896951 | DT20: 1850161211 | DU20: 1774161211 | DV20: 1774161211 | DW20: 1623406641 | DX20: 1620225968 | DY20: 1542961468 | DZ20: 1542961468 | EA20: 1427470479 | EB20: =EA20 -> 1427470479 | EC20: 2012684680 | ED20: 2012684680 | EE20: 1959842560 | EF20: 1959842560 | EG20: 1959505267 | EH20: 1939427267 | EI20: 1939427267 | EJ20: 1938757501 | EK20: 1937457501 | EL20: 1929646738 | EM20: 1891922336 | EN20: 1608652526 | EO20: =EN20 -> 1608652526 | EP20: 2083103023 | EQ20: 2083103023 | ER20: 2068572694 | ES20: 2068438694 | ET20: 2067139640 | EU20: 1962984489 | EV20: 1968056577 | EW20: 1968056577 | EX20: 1968056577 | EY20: 1968056577 | EZ20: 1968056577 | FA20: 1976677470 | FB20: =FA20 -> 1976677470 | FC20: 1951485600 | FD20: 1951485600 | FE20: 1905464563 | FF20: 1905464563 | FG20: 1817932962 | FH20: 1801311962 | FI20: 1801311962 | FO20: =FI20 -> 1801311962
B21: Dirección de Obras Hidráulicas | C21: 101236706 | D21: 101236706 | E21: 101236706 | F21: 101236706 | G21: 101236706 | H21: 101236706 | I21: 101236706 | J21: 101236706 | K21: 101236706 | L21: 104448787 | M21: 104448787 | N21: 105052138 | O21: =N21 -> 105052138 | P21: 117398169 | Q21: 117398169 | R21: 117398169 | S21: 117398169 | T21: 117398169 | U21: 119398169 | V21: 119398169 | W21: 119398169 | X21: 119398169 | Y21: 126602707 | Z21: 126602707 | AA21: 127586435 | AB21: =AA21 -> 127586435 | AC21: 127292924 | AD21: 127292924 | AE21: 127292924 | AF21: 127292924 | AG21: 127292924 | AH21: 127292924 | AI21: 127292924 | AJ21: 127292924 | AK21: 127292924 | AL21: 127292924 | AM21: 127292924 | AN21: 125791938 | AO21: =AN21 -> 125791938 | AP21: 121635713 | AQ21: 121635713 | AR21: 121635713 | AS21: 121635713 | AT21: 121635713 | AU21: 129989213 | AV21: 129989213 | AW21: 141642213 | AX21: 141642213 | AY21: 147144690 | AZ21: 147144690 | BA21: 146472297 | BB21: =BA21 -> 146472297 | BC21: 119785354 | BD21: 119785354 | BE21: 119835354 | BF21: 119835354 | BG21: 119835354 | BH21: 119835354 | BI21: 119601854 | BJ21: 119601854 | BK21: 121911854 | BL21: 125699985 | BM21: 125699985 | BN21: 120161746 | BO21: =BN21 -> 120161746 | BP21: 129182602 | BQ21: 129182602 | BR21: 129182602 | BS21: 129182602 | BT21: 129182602 | BU21: 129182602 | BV21: 129182602 | BW21: 131234832 | BX21: 140899926 | BY21: 140899926 | BZ21: 140899926 | CA21: 138342165 | CB21: =CA21 -> 138342165 | CC21: 137671350 | CD21: 137671350 | CE21: 152971350 | CF21: 152971350 | CG21: 143861214 | CH21: 143861214 | CI21: 143861214 | CJ21: 143861214 | CK21: 143861214 | CL21: 143861214 | CM21: 143861214 | CN21: 141821958 | CO21: =CN21 -> 141821958 | CP21: 140801596 | CQ21: 140801596 | CR21: 140801596 | CS21: 140801596 | CT21: 133918279 | CU21: 133918279 | CV21: 133918279 | CW21: 133918279 | CX21: 133918279 | CY21: 133918279 | CZ21: 133918279 | DA21: =131504761+8520124 -> 140024885 | DB21: =DA21 -> 140024885 | DC21: 147022684 | DD21: 147022684 | DE21: 147022684 | DF21: 147022684 | DG21: 147022684 | DH21: 147022684 | DI21: 147022684 | DJ21: 146848818 | DK21: 144824178 | DL21: 130697780 | DM21: 130518293 | DN21: 129672445 | DO21: =DN21 -> 129672445 | DP21: 293591805 | DQ21: 293591805 | DR21: 293591805 | DS21: 293591805 | DT21: 293591805 | DU21: 255048822 | DV21: 219099761 | DW21: 212099761 | DX21: 212099761 | DY21: 212099761 | DZ21: 212099761 | EA21: 198709088 | EB21: =EA21 -> 198709088 | EC21: 295701947 | ED21: 295701947 | EE21: 278607232 | EF21: 278607232 | EG21: 278543079 | EH21: 278543079 | EI21: 278543079 | EJ21: 282942267 | EK21: 282942267 | EL21: 282942267 | EM21: 282942267 | EN21: 244313644 | EO21: =EN21 -> 244313644 | EP21: 308121429 | EQ21: 308121429 | ER21: 308121429 | ES21: 308121429 | ET21: 308121429 | EU21: 288121429 | EV21: 288121429 | EW21: 288121429 | EX21: 288121429 | EY21: 284126983 | EZ21: 284126983 | FA21: 255720965 | FB21: =FA21 -> 255720965 | FC21: 195906100 | FD21: 195906100 | FE21: 192119100 | FF21: 192119100 | FG21: 186241917 | FH21: 202307917 | FI21: 202307917 | FO21: =FI21 -> 202307917
B22: Subdirección de APR | C22: 49407947 | D22: 49407947 | E22: 49407947 | F22: 49407947 | G22: 49407947 | H22: 55507947 | I22: 55507947 | J22: 60507947 | K22: 60507947 | L22: 65278980 | M22: 65278980 | N22: 67579947 | O22: =N22 -> 67579947 | P22: 68884752 | Q22: 68884752 | R22: 68884752 | S22: 68884752 | T22: 68884752 | U22: 85940845 | V22: 85940845 | W22: 87740845 | X22: 87740845 | Y22: 88355845 | Z22: 93717760 | AA22: 93689760 | AB22: =AA22 -> 93689760 | AC22: 71502372 | AD22: 71502372 | AE22: 71502372 | AF22: 71502372 | AG22: 71502372 | AH22: 71502372 | AI22: 71502372 | AJ22: 75002372 | AK22: 75002372 | AL22: 75002372 | AM22: 79147193 | AN22: 80579039 | AO22: =AN22 -> 80579039 | AP22: 89991483 | AQ22: 89991483 | AR22: 89991483 | AS22: 89991483 | AT22: 89991483 | AU22: 92696068 | AV22: 92696068 | AW22: 92696068 | AX22: 92696068 | AY22: 98217166 | AZ22: 98217166 | BA22: 100477231 | BB22: =BA22 -> 100477231 | BC22: 102433801 | BD22: 102433801 | BE22: 102433801 | BF22: 102433801 | BG22: 102433801 | BH22: 102433801 | BI22: 102433801 | BJ22: 102433801 | BK22: 102433801 | BL22: 106891813 | BM22: 106891813 | BN22: 102680557 | BO22: =BN22 -> 102680557 | BP22: 114691671 | BQ22: 114691671 | BR22: 114691671 | BS22: 114691671 | BT22: 114691671 | BU22: 114691671 | BV22: 114691671 | BW22: 123071862 | BX22: 118010898 | BY22: 118010898 | BZ22: 118010898 | CA22: 112674850 | CB22: =CA22 -> 112674850 | CC22: 135338654 | CD22: 135338654 | CE22: 135338654 | CF22: 158338654 | CG22: 155319586 | CH22: 155319586 | CI22: 155319586 | CJ22: 155319586 | CK22: 155319586 | CL22: 155319586 | CM22: 155319586 | CN22: 148506367 | CO22: =CN22 -> 148506367 | CP22: 142048072 | CQ22: 142048072 | CR22: 142048072 | CS22: 142048072 | CT22: 160995572 | CU22: 160995572 | CV22: 160995572 | CW22: 160995572 | CX22: 160995572 | CY22: 160995572 | CZ22: 160995572 | DA22: =142300803+21041416 -> 163342219 | DB22: =DA22 -> 163342219 | DC22: 148440561 | DD22: 148440561 | DE22: 148440561 | DF22: 148440561 | DG22: 148440561 | DH22: 148440561 | DI22: 148440561 | DJ22: 148440561 | DK22: 148440561 | DL22: 141404870 | DM22: 141404870 | DN22: 110932143 | DO22: =DN22 -> 110932143 | DP22: 295780655 | DQ22: 295780655 | DR22: 295780655 | DS22: 295780655 | DT22: 295780655 | DU22: 275780655 | DV22: 309887671 | DW22: 309887671 | DX22: 309887671 | DY22: 299857312 | DZ22: 265750296 | EA22: 249472319 | EB22: =EA22 -> 249472319 | EC22: 315696642 | ED22: 315696642 | EE22: 315696642 | EF22: 232705862 | EG22: 232705862 | EH22: 232705862 | EI22: 232705862 | EJ22: 227906674 | EK22: 227906674 | EL22: 227906674 | EM22: 227906674 | EN22: 192186387 | EO22: =EN22 -> 192186387 | EP22: 329603442 | EQ22: 329603442 | ER22: 307603442 | ES22: 307603442 | ET22: 307603442 | EU22: 284751010 | EV22: 284751010 | EW22: 284751010 | EX22: 284751010 | EY22: 273184204 | EZ22: 273184204 | FA22: 234336066 | FB22: =FA22 -> 234336066 | FC22: 290113797 | FD22: 290113797 | FE22: 282113797 | FF22: 282113797 | FG22: 273410383 | FH22: 273410383 | FI22: 273410383 | FO22: =FI22 -> 273410383
B23: Dirección de Obras Portuarias | C23: 55038550 | D23: 55038550 | E23: 55038550 | F23: 55038550 | G23: 55038550 | H23: 55038550 | I23: 56087343 | J23: 56087343 | K23: 56087343 | L23: 56087343 | M23: 56087343 | N23: 55967642 | O23: =N23 -> 55967642 | P23: 63737311 | Q23: 63737311 | R23: 63737311 | S23: 63737311 | T23: 63737311 | U23: 63737311 | V23: 63737311 | W23: 63737311 | X23: 63737311 | Y23: 60537311 | Z23: 66537311 | AA23: 66227311 | AB23: =AA23 -> 66227311 | AC23: 66005341 | AD23: 66005341 | AE23: 66005341 | AF23: 66005341 | AG23: 66005341 | AH23: 66005341 | AI23: 66005341 | AJ23: 66005341 | AK23: 66005341 | AL23: 66005341 | AM23: 66005341 | AN23: 66601585 | AO23: =AN23 -> 66601585 | AP23: 68152361 | AQ23: 68152361 | AR23: 68152361 | AS23: 68152361 | AT23: 68152361 | AU23: 68152361 | AV23: 68152361 | AW23: 68152361 | AX23: 68152361 | AY23: 68292361 | AZ23: 70792361 | BA23: 72233361 | BB23: =BA23 -> 72233361 | BC23: 69097793 | BD23: 69097793 | BE23: 69097793 | BF23: 69097793 | BG23: 69097793 | BH23: 69097793 | BI23: 68963100 | BJ23: 68963100 | BK23: 66653100 | BL23: 64364969 | BM23: 64332418 | BN23: 60805995 | BO23: =BN23 -> 60805995 | BP23: 69888575 | BQ23: 69888575 | BR23: 69888575 | BS23: 69888575 | BT23: 69888575 | BU23: 69888575 | BV23: 69888575 | BW23: 69888575 | BX23: 68888575 | BY23: 68888575 | BZ23: 68888575 | CA23: 62099040 | CB23: =CA23 -> 62099040 | CC23: 71705676 | CD23: 71705676 | CE23: 80110666 | CF23: 80110666 | CG23: 79796573 | CH23: 79796573 | CI23: 74160268 | CJ23: 74160268 | CK23: 74160268 | CL23: 74160268 | CM23: 73045737 | CN23: 71705970 | CO23: =CN23 -> 71705970 | CP23: 73670723 | CQ23: 73670723 | CR23: 73670723 | CS23: 73670723 | CT23: 73670723 | CU23: 73670723 | CV23: 73670723 | CW23: 73670723 | CX23: 73670723 | CY23: 73670723 | CZ23: 73670723 | DA23: =73116242+62000 -> 73178242 | DB23: =DA23 -> 73178242 | DC23: 76882481 | DD23: 76882481 | DE23: 76882481 | DF23: 76882481 | DG23: 76882481 | DH23: 76882481 | DI23: 76882481 | DJ23: 76882481 | DK23: 76882481 | DL23: 76882481 | DM23: 76882481 | DN23: 64614673 | DO23: =DN23 -> 64614673 | DP23: 115171552 | DQ23: 115171552 | DR23: 115171552 | DS23: 115171552 | DT23: 115171552 | DU23: 115171552 | DV23: 115171552 | DW23: 115171552 | DX23: 115171552 | DY23: 108472329 | DZ23: 108472329 | EA23: 104861138 | EB23: =EA23 -> 104861138 | EC23: 127117895 | ED23: 127117895 | EE23: 127117895 | EF23: 127117895 | EG23: 127117895 | EH23: 127117895 | EI23: 127117895 | EJ23: 127117895 | EK23: 127117895 | EL23: 127117895 | EM23: 127117895 | EN23: 123682417 | EO23: =EN23 -> 123682417 | EP23: 125417585 | EQ23: 125417585 | ER23: 139947914 | ES23: 139947914 | ET23: 139947914 | EU23: 139947914 | EV23: 145917564 | EW23: 145917564 | EX23: 145917564 | EY23: 151478816 | EZ23: 151478816 | FA23: 143006856 | FB23: =FA23 -> 143006856 | FC23: 109909690 | FD23: 109909690 | FE23: 109909690 | FF23: 109909690 | FG23: 106612399 | FH23: 106612399 | FI23: 106612399 | FO23: =FI23 -> 106612399
B24: Dirección de Aeropuertos | C24: 41285665 | D24: 41285665 | E24: 41285665 | F24: 41285665 | G24: 41769665 | H24: 41769665 | I24: 41769665 | J24: 43790807 | K24: 43790807 | L24: 44708207 | M24: 44708207 | N24: 45507263 | O24: =N24 -> 45507263 | P24: 41009608 | Q24: 41009608 | R24: 41009608 | S24: 41009608 | T24: 41009608 | U24: 41009608 | V24: 41009608 | W24: 39209608 | X24: 39209608 | Y24: 39209608 | Z24: 38038808 | AA24: 34834080 | AB24: =AA24 -> 34834080 | AC24: 43953347 | AD24: 43953347 | AE24: 43953347 | AF24: 43633347 | AG24: 43633347 | AH24: 43633347 | AI24: 43633347 | AJ24: 43633347 | AK24: 43633347 | AL24: 43171347 | AM24: 43171347 | AN24: 43860342 | AO24: =AN24 -> 43860342 | AP24: 45271947 | AQ24: 45271947 | AR24: 45271947 | AS24: 45271947 | AT24: 45271947 | AU24: 45271947 | AV24: 45271947 | AW24: 45271947 | AX24: 45271947 | AY24: 46889947 | AZ24: 46889947 | BA24: 49070760 | BB24: =BA24 -> 49070760 | BC24: 35602336 | BD24: 35602336 | BE24: 35602336 | BF24: 35602336 | BG24: 35602336 | BH24: 43302336 | BI24: 43302336 | BJ24: 43802336 | BK24: 43802336 | BL24: 43802336 | BM24: 43802336 | BN24: 34299269 | BO24: =BN24 -> 34299269 | BP24: 53068499 | BQ24: 53068499 | BR24: 53068499 | BS24: 53068499 | BT24: 53068499 | BU24: 53068499 | BV24: 53068499 | BW24: 55300713 | BX24: 55300713 | BY24: 55300713 | BZ24: 55300713 | CA24: 54338642 | CB24: =CA24 -> 54338642 | CC24: 58584599 | CD24: 58584599 | CE24: 58584599 | CF24: 66247946 | CG24: 66247946 | CH24: 66247946 | CI24: 66147946 | CJ24: 64991732 | CK24: 64991732 | CL24: 64570095 | CM24: 64570095 | CN24: 58584599 | CO24: =CN24 -> 58584599 | CP24: 60144148 | CQ24: 60144148 | CR24: 60144148 | CS24: 60144148 | CT24: 60144148 | CU24: 60144148 | CV24: 60144148 | CW24: 60144148 | CX24: 60144148 | CY24: 60144148 | CZ24: 60144148 | DA24: =57087148+74000 -> 57161148 | DB24: =DA24 -> 57161148 | DC24: 62797413 | DD24: 62797413 | DE24: 62797413 | DF24: 62797413 | DG24: 62712374 | DH24: 62712374 | DI24: 62487413 | DJ24: 62487413 | DK24: 62487413 | DL24: 62487413 | DM24: 62487413 | DN24: 66143610 | DO24: =DN24 -> 66143610 | DP24: 135318267 | DQ24: 135318267 | DR24: 135318267 | DS24: 135318267 | DT24: 135318267 | DU24: 135318267 | DV24: 135318267 | DW24: 135318267 | DX24: 135318267 | DY24: 131318267 | DZ24: 131318267 | EA24: 123846968 | EB24: =EA24 -> 123846968 | EC24: 137741639 | ED24: 137741639 | EE24: 137741639 | EF24: 135914151 | EG24: 135885801 | EH24: 135885801 | EI24: 135885801 | EJ24: 135885801 | EK24: 135885801 | EL24: 137734161 | EM24: 137734161 | EN24: 121300022 | EO24: =EN24 -> 121300022 | EP24: 141825431 | EQ24: 141825431 | ER24: 141825431 | ES24: 141825431 | ET24: 141825431 | EU24: 141825431 | EV24: 141825431 | EW24: 141825431 | EX24: 141825431 | EY24: 141825431 | EZ24: 141825431 | FA24: 143001334 | FB24: =FA24 -> 143001334 | FC24: 127610750 | FD24: 127610750 | FE24: 127610750 | FF24: 127610750 | FG24: 124345173 | FH24: 124345173 | FI24: 124345173 | FO24: =FI24 -> 124345173
B25: Dirección de Arquitectura | C25: 26272563 | D25: 26272563 | E25: 26955763 | F25: 26955763 | G25: 26955763 | H25: 26955763 | I25: 26955763 | J25: 27252763 | K25: 27252763 | L25: 27252763 | M25: 27558870 | N25: 25516525 | O25: =N25 -> 25516525 | P25: 28203580 | Q25: 28203580 | R25: 28176903 | S25: 28176903 | T25: 28176903 | U25: 22493729 | V25: 22493729 | W25: 22477989 | X25: 22277989 | Y25: 17658451 | Z25: 14124507 | AA25: 12055801 | AB25: =AA25 -> 12055801 | AC25: 25719874 | AD25: 25719874 | AE25: 25719874 | AF25: 25719874 | AG25: 25719874 | AH25: 25684874 | AI25: 25684874 | AJ25: 22184874 | AK25: 19898360 | AL25: 19898360 | AM25: 19898360 | AN25: 16279503 | AO25: =AN25 -> 16279503 | AP25: 28283754 | AQ25: 28283754 | AR25: 28283754 | AS25: 28283754 | AT25: 28283754 | AU25: 28260646 | AV25: 28337248 | AW25: 28337248 | AX25: 28337248 | AY25: 31399972 | AZ25: 31399972 | BA25: 21498175 | BB25: =BA25 -> 21498175 | BC25: 30504194 | BD25: 30504194 | BE25: 30504194 | BF25: 30504194 | BG25: 30445086 | BH25: 30445086 | BI25: 30385624 | BJ25: 30385624 | BK25: 30385624 | BL25: 24302238 | BM25: 24302238 | BN25: 20961721 | BO25: =BN25 -> 20961721 | BP25: 25853361 | BQ25: 25853361 | BR25: 25853361 | BS25: 25853361 | BT25: 25853361 | BU25: 25853361 | BV25: 25853361 | BW25: 21612552 | BX25: 17506566 | BY25: 17506566 | BZ25: 17506566 | CA25: 15189077 | CB25: =CA25 -> 15189077 | CC25: 22096777 | CD25: 22096777 | CE25: 22096777 | CF25: 22096777 | CG25: 8619318 | CH25: 8619318 | CI25: 8619318 | CJ25: 8619318 | CK25: 8619318 | CL25: 8619318 | CM25: 5194154 | CN25: 5194154 | CO25: =CN25 -> 5194154 | CP25: 15515216 | CQ25: 17211034 | CR25: 17211034 | CS25: 17211034 | CT25: 17211034 | CU25: 15949460 | CV25: 15949460 | CW25: 15949460 | CX25: 15514843 | CY25: 15514843 | CZ25: 15514843 | DA25: =7205919+7501242 -> 14707161 | DB25: =DA25 -> 14707161 | DC25: 31608353 | DD25: 31608353 | DE25: 19272005 | DF25: 19272005 | DG25: 19272005 | DH25: 18848017 | DI25: 8974172 | DJ25: 8890172 | DK25: 8890172 | DL25: 8663807 | DM25: 7863807 | DN25: 7392258 | DO25: =DN25 -> 7392258 | DP25: 37590026 | DQ25: 36790026 | DR25: 36790026 | DS25: 36790026 | DT25: 36790026 | DU25: 32790026 | DV25: 32790026 | DW25: 32707536 | DX25: 32707536 | DY25: 31426536 | DZ25: 8720551 | EA25: 8559879 | EB25: =EA25 -> 8559879 | EC25: 44570138 | ED25: 44570138 | EE25: 44570138 | EF25: 44570138 | EG25: 44670138 | EH25: 44670138 | EI25: 44670138 | EJ25: 41933638 | EK25: 41744274 | EL25: 41744274 | EM25: 41673300 | EN25: 33685852 | EO25: =EN25 -> 33685852 | EP25: 57109595 | EQ25: 57109595 | ER25: 84609595 | ES25: 84609595 | ET25: 77572649 | EU25: 77572649 | EV25: 77594122 | EW25: 77456003 | EX25: 77456003 | EY25: 77456003 | EZ25: 77456003 | FA25: 55621639 | FB25: =FA25 -> 55621639 | FC25: 30479549 | FD25: 30479549 | FE25: 30479549 | FF25: 30479549 | FG25: 29565163 | FH25: 29565163 | FI25: 29565163 | FO25: =FI25 -> 29565163
B26: Total | C26: =SUM(C20:C25) -> 1080148659 | D26: =SUM(D20:D25) -> 1080148659 | E26: =SUM(E20:E25) -> 1071131859 | F26: =SUM(F20:F25) -> 1071131859 | G26: =SUM(G20:G25) -> 1073601859 | H26: =SUM(H20:H25) -> 1081551893 | I26: =SUM(I20:I25) -> 1079440686 | J26: =SUM(J20:J25) -> 1105918828 | ... FO26: =SUM(FO20:FO25) -> 2537552997
B27: (1) Los años 2021 y 2022 incluyen el Presupuesto Vigente del Subtítulo 30, Ítem 10. Fuente: elaboración propia, Dipres.
B29: Ejecución de Inversión en Infraestructura Pública del Ministerio de Obras Públicas, 2014-2026 (Subtítulo 31 – Iniciativas de Inversión, miles de pesos)
C30: 2014 | P30: 2015 | AC30: 2016 | AP30: 2017 | BC30: 2018 | BP30: 2019 | CC30: 2020 | CP30: 2021(1) | DC30: 2022(1) | DP30: 2023 | EC30: 2024 | EP30: 2025 | FC30: 2026
B31: Programa | C31: Ene | D31: Feb | E31: Mar | F31: Abr | G31: May | H31: Jun | I31: Jul | J31: Ago | K31: Sep | L31: Oct | M31: Nov | N31: Dic | O31: Total 2014 | P31: Ene | Q31: Feb | R31: Mar | S31: Abr | T31: May | U31: Jun | V31: Jul | W31: Ago | X31: Sep | Y31: Oct | Z31: Nov | AA31: Dic | AB31: Total 2015 | AC31: Ene | AD31: Feb | AE31: Mar | AF31: Abr | AG31: May | AH31: Jun | AI31: Jul | AJ31: Ago | AK31: Sep | AL31: Oct | AM31: Nov | AN31: Dic | AO31: Total 2016 | AP31: Ene | AQ31: Feb | AR31: Mar | AS31: Abr | AT31: May | AU31: Jun | AV31: Jul | AW31: Ago | AX31: Sep | AY31: Oct | AZ31: Nov | BA31: Dic | BB31: Total 2017 | BC31: Ene | BD31: Feb | BE31: Mar | BF31: Abr | BG31: May | BH31: Jun | BI31: Jul | BJ31: Ago | BK31: Sep | BL31: Oct | BM31: Nov | BN31: Dic | BO31: Total 2018 | BP31: Ene | BQ31: Feb | BR31: Mar | BS31: Abr | BT31: May | BU31: Jun | BV31: Jul | BW31: Ago | BX31: Sep | BY31: Oct | BZ31: Nov | CA31: Dic | CB31: Total 2019 | CC31: Ene | CD31: Feb | CE31: Mar | CF31: Abr | CG31: May | CH31: Jun | CI31: Jul | CJ31: Ago | CK31: Sep | CL31: Oct | CM31: Nov | CN31: Dic | CO31: Total 2020 | CP31: Ene | CQ31: Feb | CR31: Mar | CS31: Abr | CT31: May | CU31: Jun | CV31: Jul | CW31: Ago | CX31: Sep | CY31: Oct | CZ31: Nov | DA31: Dic | DB31: Total 2021 | DC31: Ene | DD31: Feb | DE31: Mar | DF31: Abr | DG31: May | DH31: Jun | DI31: Jul | DJ31: Ago | DK31: Sep | DL31: Oct | DM31: Nov | DN31: Dic | DO31: Total 2022 | DP31: Ene | DQ31: Feb | DR31: Mar | DS31: Abr | DT31: May | DU31: Jun | DV31: Jul | DW31: Ago | DX31: Sep | DY31: Oct | DZ31: Nov | EA31: Dic | EB31: Total 2023 | EC31: Ene | ED31: Feb | EE31: Mar | EF31: Abr | EG31: May | EH31: Jun | EI31: Jul | EJ31: Ago | EK31: Sep | EL31: Oct | EM31: Nov | EN31: Dic | EO31: Total 2024 | EP31: Ene | EQ31: Feb | ER31: Mar | ES31: Abr | ET31: May | EU31: Jun | EV31: Jul | EW31: Ago | EX31: Sep | EY31: Oct | EZ31: Nov | FA31: Dic | FB31: Total 2025 | FC31: Ene | FD31: Feb | FE31: Mar | FF31: Abr | FG31: May | FH31: Jun | FI31: Jul | FJ31: Ago | FK31: Sep | FL31: Oct | FM31: Nov | FN31: Dic | FO31: Total 2026
B32: Dirección de Vialidad | C32: 0 | D32: 109495507 | E32: 187847739 | F32: 265238101 | G32: 332568897 | H32: 394278543 | I32: 446664037 | J32: 504805550 | K32: 557993422 | L32: 619454289 | M32: 701289585 | N32: 852007357 | O32: =N32 -> 852007357 | P32: 35691957 | Q32: 115879618 | R32: 210457678 | S32: 292947200 | T32: 361894458 | U32: 419786083 | V32: 476513994 | W32: 546526929 | X32: 608703218 | Y32: 688327936 | Z32: 772280679 | AA32: 976840711 | AB32: =AA32 -> 976840711 | AC32: 40005015 | AD32: 118158110 | AE32: 206609169 | AF32: 287881130 | AG32: 358249243 | AH32: 428512091 | AI32: 493195502 | AJ32: 565430649 | AK32: 635240221 | AL32: 720114806 | AM32: 799381459 | AN32: 939632633 | AO32: =AN32 -> 939632633 | AP32: 40701104 | AQ32: 108107750 | AR32: 184856578 | AS32: 252856020 | AT32: 319104639 | AU32: 374972572 | AV32: 431914072 | AW32: 497890053 | AX32: 572274603 | AY32: 640444837 | AZ32: 725045158 | BA32: 907408172 | BB32: =BA32 -> 907408172 | BC32: 0 | BD32: 80673042 | BE32: 168539648 | BF32: 237340393 | BG32: 309376504 | BH32: 379148992 | BI32: 442209871 | BJ32: 504027341 | BK32: 570803171 | BL32: 654884646 | BM32: 732454087 | BN32: 901443445 | BO32: =BN32 -> 901443445 | BP32: 0 | BQ32: 102696407 | BR32: 193837202 | BS32: 287563262 | BT32: 363596898 | BU32: 432817167 | BV32: 525171083 | BW32: 613755849 | BX32: 681368937 | BY32: 768886920 | BZ32: 859787144 | CA32: 1081677766 | CB32: =CA32 -> 1081677766 | CC32: 0 | CD32: 96871169 | CE32: 193870511 | CF32: 272631717 | CG32: 327561887 | CH32: 418295604 | CI32: 502258190 | CJ32: 574520045 | CK32: 633600171 | CL32: 713927353 | CM32: 800349975 | CN32: 945847843 | CO32: =CN32 -> 945847843 | CP32: 0 | CQ32: 101383549 | CR32: 198441247 | CS32: 284324137 | CT32: 358590676 | CU32: 433048907 | CV32: 503354400 | CW32: 586218042 | CX32: 653892258 | CY32: 714435373 | CZ32: 802149786 | DA32: 979979167 | DB32: =DA32 -> 979979167 | DC32: 0 | DD32: 58153045 | DE32: 139608998 | DF32: 206666427 | DG32: 283374746 | DH32: 345265825 | DI32: 405594742 | DJ32: 472550892 | DK32: 616595780 | DL32: 680714110 | DM32: 760339461 | DN32: 955760345 | DO32: =DN32 -> 955760345 | DP32: 0 | DQ32: 18205266 | DR32: 138456688 | DS32: 309745351 | DT32: 436281161 | DU32: 544941612 | DV32: 643572937 | DW32: 731872328 | DX32: 824719400 | DY32: 940512329 | DZ32: 1088998456 | EA32: 1417380025 | EB32: =EA32 -> 1417380025 | EC32: 0 | ED32: 115017803 | EE32: 245067556 | EF32: 379975864 | EG32: 521874015 | EH32: 774852600 | EI32: 856290603 | EJ32: 943020316 | EK32: 1073272838 | EL32: 1212620083 | EM32: 1411133522 | EN32: 1603559540 | EO32: =EN32 -> 1603559540 | EP32: 1418928 | EQ32: 262166719 | ER32: 478250448 | ES32: 666185288 | ET32: 837833362 | EU32: 982362882 | EV32: 1108324387 | EW32: 1217723031 | EX32: 1369623467 | EY32: 1492337572 | EZ32: 1632445535 | FA32: 1947648753 | FB32: =FA32 -> 1947648753 | FC32: 0 | FD32: 162224034 | FE32: 321332158 | FF32: 469566556 | FG32: 614978745 | FH32: 776558972 | FI32: 909487841 | FO32: =FI32 -> 909487841
B33: Dirección de Obras Hidráulicas | C33: 0 | D33: 0 | E33: 0 | F33: 12849023 | G33: 18502602 | H33: 24001975 | I33: 28200302 | J33: 35581648 | K33: 44712998 | L33: 54749457 | M33: 68221191 | N33: 104714724 | O33: =N33 -> 104714724 | P33: 4135149 | Q33: 12016222 | R33: 22838957 | S33: 31173658 | T33: 38126481 | U33: 48008563 | V33: 54996009 | W33: 62015391 | X33: 73214656 | Y33: 81368537 | Z33: 95966048 | AA33: 127205691 | AB33: =AA33 -> 127205691 | AC33: 1644472 | AD33: 6760437 | AE33: 14482109 | AF33: 20055802 | AG33: 26700349 | AH33: 38755843 | AI33: 45496469 | AJ33: 52480551 | AK33: 60402105 | AL33: 68110654 | AM33: 84499774 | AN33: 125549909 | AO33: =AN33 -> 125549909 | AP33: 1269137 | AQ33: 5677714 | AR33: 11079172 | AS33: 19699660 | AT33: 26881172 | AU33: 36009564 | AV33: 43753678 | AW33: 54111195 | AX33: 65957670 | AY33: 79535288 | AZ33: 98614598 | BA33: 145867704 | BB33: =BA33 -> 145867704 | BC33: 0 | BD33: 8476734 | BE33: 15590064 | BF33: 22689725 | BG33: 31479542 | BH33: 41016085 | BI33: 50471408 | BJ33: 56335889 | BK33: 65509002 | BL33: 73476914 | BM33: 84787919 | BN33: 119645504 | BO33: =BN33 -> 119645504 | BP33: 0 | BQ33: 0 | BR33: 0 | BS33: 14799182 | BT33: 20928761 | BU33: 27050471 | BV33: 36175836 | BW33: 44639401 | BX33: 52882663 | BY33: 68082147 | BZ33: 91945190 | CA33: 132633546 | CB33: =CA33 -> 132633546 | CC33: 0 | CD33: 0 | CE33: 15933925 | CF33: 27347698 | CG33: 34970453 | CH33: 42227599 | CI33: 50004801 | CJ33: 60357141 | CK33: 71496670 | CL33: 87043293 | CM33: 108285783 | CN33: 139288956 | CO33: =CN33 -> 139288956 | CP33: 0 | CQ33: 9524739 | CR33: 18778382 | CS33: 27058037 | CT33: 38359267 | CU33: 46029534 | CV33: 54019806 | CW33: 63431000 | CX33: 74898419 | CY33: 87833845 | CZ33: 101123468 | DA33: 129806818 | DB33: =DA33 -> 129806818 | DC33: 0 | DD33: 2161172 | DE33: 9902695 | DF33: 17446259 | DG33: 23088738 | DH33: 30830389 | DI33: 40520841 | DJ33: 46926966 | DK33: 55522281 | DL33: 68952930 | DM33: 83462172 | DN33: 128495787 | DO33: =DN33 -> 128495787 | DP33: 0 | DQ33: 6431623 | DR33: 21339974 | DS33: 32945027 | DT33: 47577177 | DU33: 63593303 | DV33: 79376685 | DW33: 92813663 | DX33: 104125697 | DY33: 112739918 | DZ33: 129397461 | EA33: 195957467 | EB33: =EA33 -> 195957467 | EC33: 0 | ED33: 6377090 | EE33: 23890040 | EF33: 39902005 | EG33: 58620170 | EH33: 119341758 | EI33: 136670909 | EJ33: 157100022 | EK33: 175138873 | EL33: 193499950 | EM33: 211590153 | EN33: 243896208 | EO33: =EN33 -> 243896208 | EP33: 2068692 | EQ33: 14027617 | ER33: 36168803 | ES33: 53822571 | ET33: 71880596 | EU33: 92473645 | EV33: 108898696 | EW33: 131234326 | EX33: 152827107 | EY33: 173770614 | EZ33: 201417551 | FA33: 252789386 | FB33: =FA33 -> 252789386 | FC33: 0 | FD33: 9585447 | FE33: 24838996 | FF33: 36118123 | FG33: 47381569 | FH33: 59374806 | FI33: 73650703 | FO33: =FI33 -> 73650703
B34: Subdirección de APR | C34: 0 | D34: 0 | E34: 2123137 | F34: 11318242 | G34: 16412231 | H34: 21503320 | I34: 26571960 | J34: 31336635 | K34: 36845348 | L34: 42847765 | M34: 49413111 | N34: 67417598 | O34: =N34 -> 67417598 | P34: 3681645 | Q34: 8539463 | R34: 18555701 | S34: 26344808 | T34: 33283091 | U34: 38882927 | V34: 45906320 | W34: 51669887 | X34: 58317963 | Y34: 63943837 | Z34: 72706421 | AA34: 93526873 | AB34: =AA34 -> 93526873 | AC34: 0 | AD34: 7489256 | AE34: 14608985 | AF34: 20077326 | AG34: 25109701 | AH34: 31740697 | AI34: 36595708 | AJ34: 43957889 | AK34: 48847708 | AL34: 53992956 | AM34: 60335109 | AN34: 80271976 | AO34: =AN34 -> 80271976 | AP34: 0 | AQ34: 7437942 | AR34: 15597962 | AS34: 22904045 | AT34: 29421513 | AU34: 37145004 | AV34: 44696488 | AW34: 52727926 | AX34: 60463520 | AY34: 67026822 | AZ34: 76122310 | BA34: 100202686 | BB34: =BA34 -> 100202686 | BC34: 0 | BD34: 1539829 | BE34: 9980097 | BF34: 15990396 | BG34: 26512540 | BH34: 32634743 | BI34: 38873532 | BJ34: 44503197 | BK34: 51124646 | BL34: 58962002 | BM34: 71960162 | BN34: 101837360 | BO34: =BN34 -> 101837360 | BP34: 0 | BQ34: 8543845 | BR34: 16492779 | BS34: 25420378 | BT34: 33246158 | BU34: 39464017 | BV34: 45418356 | BW34: 54819773 | BX34: 62481533 | BY34: 71071550 | BZ34: 80774307 | CA34: 109754082 | CB34: =CA34 -> 109754082 | CC34: 0 | CD34: 0 | CE34: 14046798 | CF34: 23975486 | CG34: 32933206 | CH34: 44476459 | CI34: 54767019 | CJ34: 64603134 | CK34: 75187064 | CL34: 91643647 | CM34: 112911790 | CN34: 145498589 | CO34: =CN34 -> 145498589 | CP34: 0 | CQ34: 6666332 | CR34: 21867716 | CS34: 35651365 | CT34: 47287710 | CU34: 58269490 | CV34: 67196224 | CW34: 76194121 | CX34: 86850665 | CY34: 100525220 | CZ34: 114625930 | DA34: 138846156 | DB34: =DA34 -> 138846156 | DC34: 0 | DD34: 0 | DE34: 7252609 | DF34: 18124947 | DG34: 26400403 | DH34: 33265233 | DI34: 41025465 | DJ34: 48098388 | DK34: 56515227 | DL34: 64874125 | DM34: 77789880 | DN34: 108974292 | DO34: =DN34 -> 108974292 | DP34: 0 | DQ34: 2303161 | DR34: 29583551 | DS34: 49465414 | DT34: 68683761 | DU34: 84807286 | DV34: 102765834 | DW34: 120298096 | DX34: 135987986 | DY34: 156018552 | DZ34: 183226741 | EA34: 244037387 | EB34: =EA34 -> 244037387 | EC34: 0 | ED34: 11025007 | EE34: 25342159 | EF34: 43422173 | EG34: 59731566 | EH34: 80871277 | EI34: 90939725 | EJ34: 104887838 | EK34: 121545898 | EL34: 134718420 | EM34: 150454729 | EN34: 189747396 | EO34: =EN34 -> 189747396 | EP34: 2010108 | EQ34: 18132777 | ER34: 36591973 | ES34: 55560502 | ET34: 73627660 | EU34: 93134581 | EV34: 109996503 | EW34: 127458124 | EX34: 147026821 | EY34: 167611651 | EZ34: 186253362 | FA34: 231742834 | FB34: =FA34 -> 231742834 | FC34: 0 | FD34: 19469514 | FE34: 40366706 | FF34: 60258504 | FG34: 79539794 | FH34: 99543928 | FI34: 119758712 | FO34: =FI34 -> 119758712
B35: Dirección de Obras Portuarias | C35: 0 | D35: 7450429 | E35: 13193802 | F35: 18293446 | G35: 22626920 | H35: 26415122 | I35: 30372078 | J35: 34891139 | K35: 39425450 | L35: 44372578 | M35: 49575185 | N35: 55862229 | O35: =N35 -> 55862229 | P35: 2407710 | Q35: 5910699 | R35: 9882174 | S35: 13108974 | T35: 15732284 | U35: 19553181 | V35: 24349229 | W35: 30187369 | X35: 35622534 | Y35: 42257897 | Z35: 50178950 | AA35: 66160697 | AB35: =AA35 -> 66160697 | AC35: 5244325 | AD35: 10266262 | AE35: 16219822 | AF35: 21648618 | AG35: 27387993 | AH35: 33761936 | AI35: 38844614 | AJ35: 43222678 | AK35: 47526334 | AL35: 53352145 | AM35: 57473232 | AN35: 66424573 | AO35: =AN35 -> 66424573 | AP35: 5239069 | AQ35: 9634272 | AR35: 14245421 | AS35: 19009524 | AT35: 23475477 | AU35: 27885034 | AV35: 32415133 | AW35: 37252785 | AX35: 41640505 | AY35: 48309815 | AZ35: 56401587 | BA35: 72170849 | BB35: =BA35 -> 72170849 | BC35: 3794605 | BD35: 8887650 | BE35: 13076526 | BF35: 16300776 | BG35: 19258274 | BH35: 22907994 | BI35: 26103926 | BJ35: 29804745 | BK35: 33918911 | BL35: 41523749 | BM35: 48730813 | BN35: 60699920 | BO35: =BN35 -> 60699920 | BP35: 0 | BQ35: 4959518 | BR35: 8623561 | BS35: 12610274 | BT35: 15677706 | BU35: 18815030 | BV35: 21774664 | BW35: 25278290 | BX35: 30144344 | BY35: 37764237 | BZ35: 48335683 | CA35: 61662087 | CB35: =CA35 -> 61662087 | CC35: 2667250 | CD35: 10044327 | CE35: 16258240 | CF35: 20216983 | CG35: 23232514 | CH35: 27197118 | CI35: 32144233 | CJ35: 38307654 | CK35: 44833503 | CL35: 52317209 | CM35: 59444391 | CN35: 71411475 | CO35: =CN35 -> 71411475 | CP35: 3825181 | CQ35: 8964985 | CR35: 15055911 | CS35: 20048280 | CT35: 26317106 | CU35: 31688072 | CV35: 36444446 | CW35: 42554997 | CX35: 48413592 | CY35: 53825635 | CZ35: 60943515 | DA35: 72860066 | DB35: =DA35 -> 72860066 | DC35: 0 | DD35: 6831369 | DE35: 12735359 | DF35: 17744111 | DG35: 21871504 | DH35: 26590987 | DI35: 29792299 | DJ35: 33545628 | DK35: 38180759 | DL35: 44900676 | DM35: 49875536 | DN35: 63389831 | DO35: =DN35 -> 63389831 | DP35: 0 | DQ35: 9852119 | DR35: 18996634 | DS35: 27251266 | DT35: 35013028 | DU35: 43003795 | DV35: 50751095 | DW35: 58156520 | DX35: 66259094 | DY35: 74165411 | DZ35: 86349973 | EA35: 104365673 | EB35: =EA35 -> 104365673 | EC35: 0 | ED35: 14355305 | EE35: 24004310 | EF35: 34981155 | EG35: 44329314 | EH35: 57184018 | EI35: 67266994 | EJ35: 77238997 | EK35: 87016951 | EL35: 98032816 | EM35: 108856624 | EN35: 122976500 | EO35: =EN35 -> 122976500 | EP35: 11343929 | EQ35: 22880886 | ER35: 31954442 | ES35: 40743206 | ET35: 50003253 | EU35: 61155170 | EV35: 73000387 | EW35: 82403582 | EX35: 91424463 | EY35: 102261627 | EZ35: 115278067 | FA35: 140810158 | FB35: =FA35 -> 140810158 | FC35: 5334724 | FD35: 18823694 | FE35: 29721986 | FF35: 39558533 | FG35: 50252046 | FH35: 57851838 | FI35: 65221155 | FO35: =FI35 -> 65221155
B36: Dirección de Aeropuertos | C36: 0 | D36: 3153629 | E36: 6333205 | F36: 10206572 | G36: 13380354 | H36: 15204069 | I36: 18935291 | J36: 22710901 | K36: 27092685 | L36: 30577580 | M36: 35648923 | N36: 45255795 | O36: =N36 -> 45255795 | P36: 2264225 | Q36: 4541595 | R36: 8911305 | S36: 11084249 | T36: 12623921 | U36: 14560264 | V36: 16520085 | W36: 18590642 | X36: 20057752 | Y36: 21728752 | Z36: 25609920 | AA36: 34520713 | AB36: =AA36 -> 34520713 | AC36: 1294891 | AD36: 3230391 | AE36: 6707771 | AF36: 9854285 | AG36: 12462996 | AH36: 14578473 | AI36: 18444600 | AJ36: 21445778 | AK36: 24594268 | AL36: 28879386 | AM36: 34953390 | AN36: 43649710 | AO36: =AN36 -> 43649710 | AP36: 1701148 | AQ36: 4989185 | AR36: 8908051 | AS36: 11712516 | AT36: 15151391 | AU36: 18220822 | AV36: 21901116 | AW36: 24950352 | AX36: 28607785 | AY36: 32972810 | AZ36: 38268304 | BA36: 48861397 | BB36: =BA36 -> 48861397 | BC36: 2321145 | BD36: 7642086 | BE36: 9990190 | BF36: 11333440 | BG36: 13219960 | BH36: 14644250 | BI36: 17565409 | BJ36: 19503920 | BK36: 21067209 | BL36: 23658290 | BM36: 27309272 | BN36: 34089377 | BO36: =BN36 -> 34089377 | BP36: 0 | BQ36: 2918777 | BR36: 8655533 | BS36: 12471449 | BT36: 15294277 | BU36: 17720411 | BV36: 19806946 | BW36: 21796811 | BX36: 24959259 | BY36: 30963792 | BZ36: 38358537 | CA36: 53939967 | CB36: =CA36 -> 53939967 | CC36: 303665 | CD36: 4282732 | CE36: 8015041 | CF36: 10962085 | CG36: 13797288 | CH36: 16103675 | CI36: 17499070 | CJ36: 18841178 | CK36: 20956225 | CL36: 26897713 | CM36: 39607854 | CN36: 58248413 | CO36: =CN36 -> 58248413 | CP36: 5238741 | CQ36: 10943486 | CR36: 18457428 | CS36: 27356255 | CT36: 33912011 | CU36: 39164650 | CV36: 41928107 | CW36: 45570244 | CX36: 48624248 | CY36: 50023582 | CZ36: 51847218 | DA36: 56686190 | DB36: =DA36 -> 56686190 | DC36: 839540 | DD36: 1930275 | DE36: 5065401 | DF36: 7642514 | DG36: 8217159 | DH36: 9505928 | DI36: 12107075 | DJ36: 14547935 | DK36: 17494128 | DL36: 27673768 | DM36: 40027308 | DN36: 65439532 | DO36: =DN36 -> 65439532 | DP36: 0 | DQ36: 13210998 | DR36: 26801255 | DS36: 34566510 | DT36: 40280060 | DU36: 46287111 | DV36: 50590434 | DW36: 60655017 | DX36: 67496353 | DY36: 74862435 | DZ36: 89687930 | EA36: 122803224 | EB36: =EA36 -> 122803224 | EC36: 0 | ED36: 10801902 | EE36: 21691356 | EF36: 33317068 | EG36: 44122345 | EH36: 59135603 | EI36: 66601938 | EJ36: 74752243 | EK36: 86852892 | EL36: 99348688 | EM36: 111690617 | EN36: 121236421 | EO36: =EN36 -> 121236421 | EP36: 5480453 | EQ36: 18789767 | ER36: 33876924 | ES36: 51049771 | ET36: 63060218 | EU36: 70081917 | EV36: 74458174 | EW36: 78656297 | EX36: 86517922 | EY36: 100099974 | EZ36: 112429460 | FA36: 142638019 | FB36: =FA36 -> 142638019 | FC36: 8605874 | FD36: 22342962 | FE36: 30219385 | FF36: 33540799 | FG36: 36963751 | FH36: 51185776 | FI36: 55356746 | FO36: =FI36 -> 55356746
B37: Dirección de Arquitectura | C37: 0 | D37: 57591 | E37: 2904221 | F37: 4181638 | G37: 8599963 | H37: 17353835 | I37: 19639160 | J37: 20130486 | K37: 20287005 | L37: 20566868 | M37: 23635450 | N37: 25363607 | O37: =N37 -> 25363607 | P37: 298118 | Q37: 929191 | R37: 1348993 | S37: 1710614 | T37: 1997677 | U37: 2275739 | V37: 3467099 | W37: 4389984 | X37: 5606304 | Y37: 7175069 | Z37: 9072251 | AA37: 11974051 | AB37: =AA37 -> 11974051 | AC37: 0 | AD37: 1722584 | AE37: 2423350 | AF37: 4116924 | AG37: 5773095 | AH37: 7187484 | AI37: 8310819 | AJ37: 8643566 | AK37: 10276104 | AL37: 11991317 | AM37: 13830342 | AN37: 16091959 | AO37: =AN37 -> 16091959 | AP37: 0 | AQ37: 1930720 | AR37: 3039686 | AS37: 4280290 | AT37: 5593090 | AU37: 8744083 | AV37: 10181331 | AW37: 11686410 | AX37: 13119459 | AY37: 14292697 | AZ37: 15490579 | BA37: 21241804 | BB37: =BA37 -> 21241804 | BC37: 0 | BD37: 5886400 | BE37: 7481295 | BF37: 8719920 | BG37: 11153942 | BH37: 12155230 | BI37: 13134856 | BJ37: 14455606 | BK37: 16064457 | BL37: 17132589 | BM37: 17904381 | BN37: 20784765 | BO37: =BN37 -> 20784765 | BP37: 0 | BQ37: 1041613 | BR37: 1825993 | BS37: 2954492 | BT37: 3961108 | BU37: 4263265 | BV37: 5067001 | BW37: 5568722 | BX37: 6156946 | BY37: 7114240 | BZ37: 12100538 | CA37: 14179880 | CB37: =CA37 -> 14179880 | CC37: 0 | CD37: 30830 | CE37: 126373 | CF37: 260932 | CG37: 271532 | CH37: 391694 | CI37: 448090 | CJ37: 1130221 | CK37: 1726167 | CL37: 2486239 | CM37: 3563594 | CN37: 4911613 | CO37: =CN37 -> 4911613 | CP37: 0 | CQ37: 185308 | CR37: 472311 | CS37: 867432 | CT37: 1160606 | CU37: 1516702 | CV37: 2083480 | CW37: 2750574 | CX37: 3861743 | CY37: 4604946 | CZ37: 5590277 | DA37: 7136830 | DB37: =DA37 -> 7136830 | DC37: 0 | DD37: 0 | DE37: 112783 | DF37: 865235 | DG37: 1090968 | DH37: 1329914 | DI37: 1964401 | DJ37: 2518748 | DK37: 3753691 | DL37: 4505699 | DM37: 5158128 | DN37: 6961523 | DO37: =DN37 -> 6961523 | DP37: 0 | DQ37: 14295 | DR37: 519418 | DS37: 818017 | DT37: 1410647 | DU37: 2049207 | DV37: 2506834 | DW37: 3618243 | DX37: 4988476 | DY37: 5883654 | DZ37: 7168509 | EA37: 8421473 | EB37: =EA37 -> 8421473 | EC37: 0 | ED37: 1265774 | EE37: 2147162 | EF37: 4222816 | EG37: 6702483 | EH37: 11199330 | EI37: 13041635 | EJ37: 16175866 | EK37: 20074880 | EL37: 23775698 | EM37: 27727701 | EN37: 33523348 | EO37: =EN37 -> 33523348 | EP37: 1010340 | EQ37: 5400393 | ER37: 9140892 | ES37: 13609867 | ET37: 16763840 | EU37: 19193589 | EV37: 22131755 | EW37: 27614100 | EX37: 31105744 | EY37: 35933608 | EZ37: 40868830 | FA37: 48235342 | FB37: =FA37 -> 48235342 | FC37: 506557 | FD37: 3068948 | FE37: 4760248 | FF37: 6527517 | FG37: 9351673 | FH37: 11151630 | FI37: 13543806 | FO37: =FI37 -> 13543806
B38: Total | C38: =SUM(C32:C37) -> 0 | D38: =SUM(D32:D37) -> 120157156 | E38: =SUM(E32:E37) -> 212402104 | F38: =SUM(F32:F37) -> 322087022 | G38: =SUM(G32:G37) -> 412090967 | H38: =SUM(H32:H37) -> 498756864 | I38: =SUM(I32:I37) -> 570382828 | J38: =SUM(J32:J37) -> 649456359 | ... FO38: =SUM(FO32:FO37) -> 1237018963
B39: Fuente: elaboración propia, Dipres.
B42: Subtítulo 29 – Adquisición de Activos No Financieros
B44: Presupuesto Ley de Inversión en Infraestructura Pública del Ministerio de Obras Públicas, 2014-2026 (Subtítulo 29 – Adquisición de Activos No Financieros, miles de pesos)
C45: 2014 | P45: 2015 | AC45: 2016 | AP45: 2017 | BC45: 2018 | BP45: 2019 | CC45: 2020 | CP45: 2021 | DC45: 2022 | DP45: 2023 | EC45: 2024 | EP45: 2025 | FC45: 2026
B46: Programa | C46: Ene | D46: Feb | E46: Mar | F46: Abr | G46: May | H46: Jun | I46: Jul | J46: Ago | K46: Sep | L46: Oct | M46: Nov | N46: Dic | O46: Total 2014 | P46: Ene | Q46: Feb | R46: Mar | S46: Abr | T46: May | U46: Jun | V46: Jul | W46: Ago | X46: Sep | Y46: Oct | Z46: Nov | AA46: Dic | AB46: Total 2015 | AC46: Ene | AD46: Feb | AE46: Mar | AF46: Abr | AG46: May | AH46: Jun | AI46: Jul | AJ46: Ago | AK46: Sep | AL46: Oct | AM46: Nov | AN46: Dic | AO46: Total 2016 | AP46: Ene | AQ46: Feb | AR46: Mar | AS46: Abr | AT46: May | AU46: Jun | AV46: Jul | AW46: Ago | AX46: Sep | AY46: Oct | AZ46: Nov | BA46: Dic | BB46: Total 2017 | BC46: Ene | BD46: Feb | BE46: Mar | BF46: Abr | BG46: May | BH46: Jun | BI46: Jul | BJ46: Ago | BK46: Sep | BL46: Oct | BM46: Nov | BN46: Dic | BO46: Total 2018 | BP46: Ene | BQ46: Feb | BR46: Mar | BS46: Abr | BT46: May | BU46: Jun | BV46: Jul | BW46: Ago | BX46: Sep | BY46: Oct | BZ46: Nov | CA46: Dic | CB46: Total 2019 | CC46: Ene | CD46: Feb | CE46: Mar | CF46: Abr | CG46: May | CH46: Jun | CI46: Jul | CJ46: Ago | CK46: Sep | CL46: Oct | CM46: Nov | CN46: Dic | CO46: Total 2020 | CP46: Ene | CQ46: Feb | CR46: Mar | CS46: Abr | CT46: May | CU46: Jun | CV46: Jul | CW46: Ago | CX46: Sep | CY46: Oct | CZ46: Nov | DA46: Dic | DB46: Total 2021 | DC46: Ene | DD46: Feb | DE46: Mar | DF46: Abr | DG46: May | DH46: Jun | DI46: Jul | DJ46: Ago | DK46: Sep | DL46: Oct | DM46: Nov | DN46: Dic | DO46: Total 2022 | DP46: Ene | DQ46: Feb | DR46: Mar | DS46: Abr | DT46: May | DU46: Jun | DV46: Jul | DW46: Ago | DX46: Sep | DY46: Oct | DZ46: Nov | EA46: Dic | EB46: Total 2023 | EC46: Ene | ED46: Feb | EE46: Mar | EF46: Abr | EG46: May | EH46: Jun | EI46: Jul | EJ46: Ago | EK46: Sep | EL46: Oct | EM46: Nov | EN46: Dic | EO46: Total 2024 | EP46: Ene | EQ46: Feb | ER46: Mar | ES46: Abr | ET46: May | EU46: Jun | EV46: Jul | EW46: Ago | EX46: Sep | EY46: Oct | EZ46: Nov | FA46: Dic | FB46: Total 2025 | FC46: Ene | FD46: Feb | FE46: Mar | FF46: Abr | FG46: May | FH46: Jun | FI46: Jul | FJ46: Ago | FK46: Sep | FL46: Oct | FM46: Nov | FN46: Dic | FO46: Total 2026
B47: Dirección de Vialidad | C47: 2953248 | D47: 2953248 | E47: 2953248 | F47: 2953248 | G47: 2953248 | H47: 2953248 | I47: 2953248 | J47: 2953248 | K47: 2953248 | L47: 2953248 | M47: 2953248 | N47: 2953248 | O47: =N47 -> 2953248 | P47: 1753030 | Q47: 1753030 | R47: 1753030 | S47: 1753030 | T47: 1753030 | U47: 1753030 | V47: 1753030 | W47: 1753030 | X47: 1753030 | Y47: 1753030 | Z47: 1753030 | AA47: 1753030 | AB47: =AA47 -> 1753030 | AC47: 1791359 | AD47: 1791359 | AE47: 1791359 | AF47: 1791359 | AG47: 1791359 | AH47: 1791359 | AI47: 1791359 | AJ47: 1791359 | AK47: 1791359 | AL47: 1791359 | AM47: 1791359 | AN47: 1791359 | AO47: =AN47 -> 1791359 | AP47: 1779405 | AQ47: 1779405 | AR47: 1779405 | AS47: 1779405 | AT47: 1779405 | AU47: 1779405 | AV47: 1779405 | AW47: 1779405 | AX47: 1779405 | AY47: 1779405 | AZ47: 1779405 | BA47: 1779405 | BB47: =BA47 -> 1779405 | BC47: 1606877 | BD47: 1606877 | BE47: 1606877 | BF47: 1606877 | BG47: 1606877 | BH47: 1606877 | BI47: 1606877 | BJ47: 1606877 | BK47: 1606877 | BL47: 1606877 | BM47: 1606877 | BN47: 1606877 | BO47: =BN47 -> 1606877 | BP47: 1639746 | BQ47: 1639746 | BR47: 1639746 | BS47: 1639746 | BT47: 1639746 | BU47: 1639746 | BV47: 1639746 | BW47: 1639746 | BX47: 1639746 | BY47: 1639746 | BZ47: 1639746 | CA47: 1639746 | CB47: =CA47 -> 1639746 | CC47: 1704539 | CD47: 1704539 | CE47: 1704539 | CF47: 1704539 | CG47: 1704539 | CH47: 1704539 | CI47: 1704539 | CJ47: 1704539 | CK47: 1704539 | CL47: 1704539 | CM47: 1704539 | CN47: 1704539 | CO47: =CN47 -> 1704539 | CP47: 1930914 | CQ47: 1930914 | CR47: 1930914 | CS47: 1930914 | CT47: 1930914 | CU47: 1930914 | CV47: 1930914 | CW47: 1930914 | CX47: 1930914 | CY47: 1930914 | CZ47: 1930914 | DA47: 1930914 | DB47: =DA47 -> 1930914 | DC47: 298233 | DD47: 298233 | DE47: 298233 | DF47: 298233 | DG47: 298233 | DH47: 298233 | DI47: 298233 | DJ47: 298233 | DK47: 298233 | DL47: 298233 | DM47: 298233 | DN47: 298233 | DO47: =DN47 -> 298233 | DP47: 22089448 | DQ47: 22089448 | DR47: 22089448 | DS47: 22089448 | DT47: 22089448 | DU47: 22089448 | DV47: 22089448 | DW47: 22089448 | DX47: 22089448 | DY47: 22089448 | DZ47: 22089448 | EA47: 22089448 | EB47: =EA47 -> 22089448 | EC47: 1135861 | ED47: 1135861 | EE47: 1135861 | EF47: 1135861 | EG47: 1135861 | EH47: 1135861 | EI47: 1135861 | EJ47: 1135861 | EK47: 1135861 | EL47: 1135861 | EM47: 1135861 | EN47: 1135861 | EO47: =EN47 -> 1135861 | EP47: 6540884 | EQ47: 6540884 | ER47: 6540884 | ES47: 6540884 | ET47: 6540884 | EU47: 6540884 | EV47: 6540884 | EW47: 6540884 | EX47: 6540884 | EY47: 6540884 | EZ47: 6540884 | FA47: 6540884 | FB47: =FA47 -> 6540884 | FC47: 1062955 | FD47: 1062955 | FE47: 1062955 | FF47: 1062955 | FG47: 1062955 | FH47: 1062955 | FI47: 1062955 | FO47: =FI47 -> 1062955
B48: Dirección de Obras Hidráulicas | C48: 381750 | D48: 381750 | E48: 381750 | F48: 381750 | G48: 381750 | H48: 381750 | I48: 381750 | J48: 381750 | K48: 381750 | L48: 381750 | M48: 381750 | N48: 381750 | O48: =N48 -> 381750 | P48: 362280 | Q48: 362280 | R48: 362280 | S48: 362280 | T48: 362280 | U48: 362280 | V48: 362280 | W48: 362280 | X48: 362280 | Y48: 362280 | Z48: 362280 | AA48: 362280 | AB48: =AA48 -> 362280 | AC48: 327142 | AD48: 327142 | AE48: 327142 | AF48: 327142 | AG48: 327142 | AH48: 327142 | AI48: 327142 | AJ48: 327142 | AK48: 327142 | AL48: 327142 | AM48: 327142 | AN48: 327142 | AO48: =AN48 -> 327142 | AP48: 174624 | AQ48: 174624 | AR48: 174624 | AS48: 174624 | AT48: 174624 | AU48: 174624 | AV48: 174624 | AW48: 174624 | AX48: 174624 | AY48: 174624 | AZ48: 174624 | BA48: 174624 | BB48: =BA48 -> 174624 | BC48: 139517 | BD48: 139517 | BE48: 139517 | BF48: 139517 | BG48: 139517 | BH48: 139517 | BI48: 139517 | BJ48: 139517 | BK48: 139517 | BL48: 139517 | BM48: 139517 | BN48: 139517 | BO48: =BN48 -> 139517 | BP48: 115465 | BQ48: 115465 | BR48: 115465 | BS48: 115465 | BT48: 115465 | BU48: 115465 | BV48: 115465 | BW48: 115465 | BX48: 115465 | BY48: 115465 | BZ48: 115465 | CA48: 115465 | CB48: =CA48 -> 115465 | CC48: 188388 | CD48: 188388 | CE48: 188388 | CF48: 188388 | CG48: 188388 | CH48: 188388 | CI48: 188388 | CJ48: 188388 | CK48: 188388 | CL48: 188388 | CM48: 188388 | CN48: 188388 | CO48: =CN48 -> 188388 | CP48: 128859 | CQ48: 128859 | CR48: 128859 | CS48: 128859 | CT48: 128859 | CU48: 128859 | CV48: 128859 | CW48: 128859 | CX48: 128859 | CY48: 128859 | CZ48: 128859 | DA48: 128859 | DB48: =DA48 -> 128859 | DC48: 130362 | DD48: 130362 | DE48: 130362 | DF48: 130362 | DG48: 130362 | DH48: 130362 | DI48: 130362 | DJ48: 130362 | DK48: 130362 | DL48: 130362 | DM48: 130362 | DN48: 130362 | DO48: =DN48 -> 130362 | DP48: 647086 | DQ48: 647086 | DR48: 647086 | DS48: 647086 | DT48: 647086 | DU48: 647086 | DV48: 647086 | DW48: 647086 | DX48: 647086 | DY48: 647086 | DZ48: 647086 | EA48: 647086 | EB48: =EA48 -> 647086 | EC48: 856525 | ED48: 856525 | EE48: 856525 | EF48: 856525 | EG48: 856525 | EH48: 856525 | EI48: 856525 | EJ48: 856525 | EK48: 856525 | EL48: 856525 | EM48: 856525 | EN48: 856525 | EO48: =EN48 -> 856525 | EP48: 1233864 | EQ48: 1233864 | ER48: 1233864 | ES48: 1233864 | ET48: 1233864 | EU48: 1233864 | EV48: 1233864 | EW48: 1233864 | EX48: 1233864 | EY48: 1233864 | EZ48: 1233864 | FA48: 1233864 | FB48: =FA48 -> 1233864 | FC48: 651088 | FD48: 651088 | FE48: 651088 | FF48: 651088 | FG48: 651088 | FH48: 651088 | FI48: 651088 | FO48: =FI48 -> 651088
B49: Subdirección de APR | C49: 40007 | D49: 40007 | E49: 40007 | F49: 40007 | G49: 40007 | H49: 40007 | I49: 40007 | J49: 40007 | K49: 40007 | L49: 40007 | M49: 40007 | N49: 40007 | O49: =N49 -> 40007 | P49: 78467 | Q49: 78467 | R49: 78467 | S49: 78467 | T49: 78467 | U49: 78467 | V49: 78467 | W49: 78467 | X49: 78467 | Y49: 78467 | Z49: 78467 | AA49: 78467 | AB49: =AA49 -> 78467 | AC49: 62947 | AD49: 62947 | AE49: 62947 | AF49: 62947 | AG49: 62947 | AH49: 62947 | AI49: 62947 | AJ49: 62947 | AK49: 62947 | AL49: 62947 | AM49: 62947 | AN49: 62947 | AO49: =AN49 -> 62947 | AP49: 49257 | AQ49: 49257 | AR49: 49257 | AS49: 49257 | AT49: 49257 | AU49: 49257 | AV49: 49257 | AW49: 49257 | AX49: 49257 | AY49: 49257 | AZ49: 49257 | BA49: 49257 | BB49: =BA49 -> 49257 | BC49: 610722 | BD49: 610722 | BE49: 610722 | BF49: 610722 | BG49: 610722 | BH49: 610722 | BI49: 610722 | BJ49: 610722 | BK49: 610722 | BL49: 610722 | BM49: 610722 | BN49: 610722 | BO49: =BN49 -> 610722 | BP49: 166534 | BQ49: 166534 | BR49: 166534 | BS49: 166534 | BT49: 166534 | BU49: 166534 | BV49: 166534 | BW49: 166534 | BX49: 166534 | BY49: 166534 | BZ49: 166534 | CA49: 166534 | CB49: =CA49 -> 166534 | CC49: 206665 | CD49: 206665 | CE49: 206665 | CF49: 206665 | CG49: 206665 | CH49: 206665 | CI49: 206665 | CJ49: 206665 | CK49: 206665 | CL49: 206665 | CM49: 206665 | CN49: 206665 | CO49: =CN49 -> 206665 | CP49: 160447 | CQ49: 160447 | CR49: 160447 | CS49: 160447 | CT49: 160447 | CU49: 160447 | CV49: 160447 | CW49: 160447 | CX49: 160447 | CY49: 160447 | CZ49: 160447 | DA49: 160447 | DB49: =DA49 -> 160447 | DC49: 455326 | DD49: 455326 | DE49: 455326 | DF49: 455326 | DG49: 455326 | DH49: 455326 | DI49: 455326 | DJ49: 455326 | DK49: 455326 | DL49: 455326 | DM49: 455326 | DN49: 455326 | DO49: =DN49 -> 455326 | DP49: 622609 | DQ49: 622609 | DR49: 622609 | DS49: 622609 | DT49: 622609 | DU49: 622609 | DV49: 622609 | DW49: 622609 | DX49: 622609 | DY49: 622609 | DZ49: 622609 | EA49: 622609 | EB49: =EA49 -> 622609 | EC49: 636104 | ED49: 636104 | EE49: 636104 | EF49: 636104 | EG49: 636104 | EH49: 636104 | EI49: 636104 | EJ49: 636104 | EK49: 636104 | EL49: 636104 | EM49: 636104 | EN49: 636104 | EO49: =EN49 -> 636104 | EP49: 1352415 | EQ49: 1352415 | ER49: 1352415 | ES49: 1352415 | ET49: 1352415 | EU49: 1352415 | EV49: 1352415 | EW49: 1352415 | EX49: 1352415 | EY49: 1352415 | EZ49: 1352415 | FA49: 1352415 | FB49: =FA49 -> 1352415 | FC49: 667445 | FD49: 667445 | FE49: 667445 | FF49: 667445 | FG49: 667445 | FH49: 667445 | FI49: 667445 | FO49: =FI49 -> 667445
B50: Dirección de Obras Portuarias | C50: 166373 | D50: 166373 | E50: 166373 | F50: 166373 | G50: 166373 | H50: 166373 | I50: 166373 | J50: 166373 | K50: 166373 | L50: 166373 | M50: 166373 | N50: 166373 | O50: =N50 -> 166373 | P50: 1590037 | Q50: 1590037 | R50: 1590037 | S50: 1590037 | T50: 1590037 | U50: 1590037 | V50: 1590037 | W50: 1590037 | X50: 1590037 | Y50: 1590037 | Z50: 1590037 | AA50: 1590037 | AB50: =AA50 -> 1590037 | AC50: 6130543 | AD50: 6130543 | AE50: 6130543 | AF50: 6130543 | AG50: 6130543 | AH50: 6130543 | AI50: 6130543 | AJ50: 6130543 | AK50: 6130543 | AL50: 6130543 | AM50: 6130543 | AN50: 6130543 | AO50: =AN50 -> 6130543 | AP50: 3892493 | AQ50: 3892493 | AR50: 3892493 | AS50: 3892493 | AT50: 3892493 | AU50: 3892493 | AV50: 3892493 | AW50: 3892493 | AX50: 3892493 | AY50: 3892493 | AZ50: 3892493 | BA50: 3892493 | BB50: =BA50 -> 3892493 | BC50: 1987092 | BD50: 1987092 | BE50: 1987092 | BF50: 1987092 | BG50: 1987092 | BH50: 1987092 | BI50: 1987092 | BJ50: 1987092 | BK50: 1987092 | BL50: 1987092 | BM50: 1987092 | BN50: 1987092 | BO50: =BN50 -> 1987092 | BP50: 2440271 | BQ50: 2440271 | BR50: 2440271 | BS50: 2440271 | BT50: 2440271 | BU50: 2440271 | BV50: 2440271 | BW50: 2440271 | BX50: 2440271 | BY50: 2440271 | BZ50: 2440271 | CA50: 2440271 | CB50: =CA50 -> 2440271 | CC50: 2488259 | CD50: 2488259 | CE50: 2488259 | CF50: 2488259 | CG50: 2488259 | CH50: 2488259 | CI50: 2488259 | CJ50: 2488259 | CK50: 2488259 | CL50: 2488259 | CM50: 2488259 | CN50: 2488259 | CO50: =CN50 -> 2488259 | CP50: 2902086 | CQ50: 2902086 | CR50: 2902086 | CS50: 2902086 | CT50: 2902086 | CU50: 2902086 | CV50: 2902086 | CW50: 2902086 | CX50: 2902086 | CY50: 2902086 | CZ50: 2902086 | DA50: 2902086 | DB50: =DA50 -> 2902086 | DC50: 1322297 | DD50: 1322297 | DE50: 1322297 | DF50: 1322297 | DG50: 1322297 | DH50: 1322297 | DI50: 1322297 | DJ50: 1322297 | DK50: 1322297 | DL50: 1322297 | DM50: 1322297 | DN50: 1322297 | DO50: =DN50 -> 1322297 | DP50: 1814843 | DQ50: 1814843 | DR50: 1814843 | DS50: 1814843 | DT50: 1814843 | DU50: 1814843 | DV50: 1814843 | DW50: 1814843 | DX50: 1814843 | DY50: 1814843 | DZ50: 1814843 | EA50: 1814843 | EB50: =EA50 -> 1814843 | EC50: 5152528 | ED50: 5152528 | EE50: 5152528 | EF50: 5152528 | EG50: 5152528 | EH50: 5152528 | EI50: 5152528 | EJ50: 5152528 | EK50: 5152528 | EL50: 5152528 | EM50: 5152528 | EN50: 5152528 | EO50: =EN50 -> 5152528 | EP50: 2635679 | EQ50: 2635679 | ER50: 2635679 | ES50: 2635679 | ET50: 2635679 | EU50: 2635679 | EV50: 2635679 | EW50: 2635679 | EX50: 2635679 | EY50: 2635679 | EZ50: 2635679 | FA50: 2635679 | FB50: =FA50 -> 2635679 | FC50: 2135157 | FD50: 2135157 | FE50: 2135157 | FF50: 2135157 | FG50: 2135157 | FH50: 2135157 | FI50: 2135157 | FO50: =FI50 -> 2135157
B51: Dirección de Aeropuertos | C51: 231070 | D51: 231070 | E51: 231070 | F51: 231070 | G51: 231070 | H51: 231070 | I51: 231070 | J51: 231070 | K51: 231070 | L51: 231070 | M51: 231070 | N51: 231070 | O51: =N51 -> 231070 | P51: 467863 | Q51: 467863 | R51: 467863 | S51: 467863 | T51: 467863 | U51: 467863 | V51: 467863 | W51: 467863 | X51: 467863 | Y51: 467863 | Z51: 467863 | AA51: 467863 | AB51: =AA51 -> 467863 | AC51: 173175 | AD51: 173175 | AE51: 173175 | AF51: 173175 | AG51: 173175 | AH51: 173175 | AI51: 173175 | AJ51: 173175 | AK51: 173175 | AL51: 173175 | AM51: 173175 | AN51: 173175 | AO51: =AN51 -> 173175 | AP51: 100131 | AQ51: 100131 | AR51: 100131 | AS51: 100131 | AT51: 100131 | AU51: 100131 | AV51: 100131 | AW51: 100131 | AX51: 100131 | AY51: 100131 | AZ51: 100131 | BA51: 100131 | BB51: =BA51 -> 100131 | BC51: 95500 | BD51: 95500 | BE51: 95500 | BF51: 95500 | BG51: 95500 | BH51: 95500 | BI51: 95500 | BJ51: 95500 | BK51: 95500 | BL51: 95500 | BM51: 95500 | BN51: 95500 | BO51: =BN51 -> 95500 | BP51: 97653 | BQ51: 97653 | BR51: 97653 | BS51: 97653 | BT51: 97653 | BU51: 97653 | BV51: 97653 | BW51: 97653 | BX51: 97653 | BY51: 97653 | BZ51: 97653 | CA51: 97653 | CB51: =CA51 -> 97653 | CC51: 72183 | CD51: 72183 | CE51: 72183 | CF51: 72183 | CG51: 72183 | CH51: 72183 | CI51: 72183 | CJ51: 72183 | CK51: 72183 | CL51: 72183 | CM51: 72183 | CN51: 72183 | CO51: =CN51 -> 72183 | CP51: 103404 | CQ51: 103404 | CR51: 103404 | CS51: 103404 | CT51: 103404 | CU51: 103404 | CV51: 103404 | CW51: 103404 | CX51: 103404 | CY51: 103404 | CZ51: 103404 | DA51: 103404 | DB51: =DA51 -> 103404 | DC51: 76973 | DD51: 76973 | DE51: 76973 | DF51: 76973 | DG51: 76973 | DH51: 76973 | DI51: 76973 | DJ51: 76973 | DK51: 76973 | DL51: 76973 | DM51: 76973 | DN51: 76973 | DO51: =DN51 -> 76973 | DP51: 240323 | DQ51: 240323 | DR51: 240323 | DS51: 240323 | DT51: 240323 | DU51: 240323 | DV51: 240323 | DW51: 240323 | DX51: 240323 | DY51: 240323 | DZ51: 240323 | EA51: 240323 | EB51: =EA51 -> 240323 | EC51: 251537 | ED51: 251537 | EE51: 251537 | EF51: 251537 | EG51: 251537 | EH51: 251537 | EI51: 251537 | EJ51: 251537 | EK51: 251537 | EL51: 251537 | EM51: 251537 | EN51: 251537 | EO51: =EN51 -> 251537 | EP51: 924967 | EQ51: 924967 | ER51: 924967 | ES51: 924967 | ET51: 924967 | EU51: 924967 | EV51: 924967 | EW51: 924967 | EX51: 924967 | EY51: 924967 | EZ51: 924967 | FA51: 924967 | FB51: =FA51 -> 924967 | FC51: 294239 | FD51: 294239 | FE51: 294239 | FF51: 294239 | FG51: 294239 | FH51: 294239 | FI51: 294239 | FO51: =FI51 -> 294239
B52: Dirección de Arquitectura | C52: 104782 | D52: 104782 | E52: 104782 | F52: 104782 | G52: 104782 | H52: 104782 | I52: 104782 | J52: 104782 | K52: 104782 | L52: 104782 | M52: 104782 | N52: 104782 | O52: =N52 -> 104782 | P52: 95648 | Q52: 95648 | R52: 95648 | S52: 95648 | T52: 95648 | U52: 95648 | V52: 95648 | W52: 95648 | X52: 95648 | Y52: 95648 | Z52: 95648 | AA52: 95648 | AB52: =AA52 -> 95648 | AC52: 96011 | AD52: 96011 | AE52: 96011 | AF52: 96011 | AG52: 96011 | AH52: 96011 | AI52: 96011 | AJ52: 96011 | AK52: 96011 | AL52: 96011 | AM52: 96011 | AN52: 96011 | AO52: =AN52 -> 96011 | AP52: 123692 | AQ52: 123692 | AR52: 123692 | AS52: 123692 | AT52: 123692 | AU52: 123692 | AV52: 123692 | AW52: 123692 | AX52: 123692 | AY52: 123692 | AZ52: 123692 | BA52: 123692 | BB52: =BA52 -> 123692 | BC52: 101075 | BD52: 101075 | BE52: 101075 | BF52: 101075 | BG52: 101075 | BH52: 101075 | BI52: 101075 | BJ52: 101075 | BK52: 101075 | BL52: 101075 | BM52: 101075 | BN52: 101075 | BO52: =BN52 -> 101075 | BP52: 111887 | BQ52: 111887 | BR52: 111887 | BS52: 111887 | BT52: 111887 | BU52: 111887 | BV52: 111887 | BW52: 111887 | BX52: 111887 | BY52: 111887 | BZ52: 111887 | CA52: 111887 | CB52: =CA52 -> 111887 | CC52: 185782 | CD52: 185782 | CE52: 185782 | CF52: 185782 | CG52: 185782 | CH52: 185782 | CI52: 185782 | CJ52: 185782 | CK52: 185782 | CL52: 185782 | CM52: 185782 | CN52: 185782 | CO52: =CN52 -> 185782 | CP52: 107372 | CQ52: 107372 | CR52: 107372 | CS52: 107372 | CT52: 107372 | CU52: 107372 | CV52: 107372 | CW52: 107372 | CX52: 107372 | CY52: 107372 | CZ52: 107372 | DA52: 107372 | DB52: =DA52 -> 107372 | DC52: 169485 | DD52: 169485 | DE52: 169485 | DF52: 169485 | DG52: 169485 | DH52: 169485 | DI52: 169485 | DJ52: 169485 | DK52: 169485 | DL52: 169485 | DM52: 169485 | DN52: 169485 | DO52: =DN52 -> 169485 | DP52: 556957 | DQ52: 556957 | DR52: 556957 | DS52: 556957 | DT52: 556957 | DU52: 556957 | DV52: 556957 | DW52: 556957 | DX52: 556957 | DY52: 556957 | DZ52: 556957 | EA52: 556957 | EB52: =EA52 -> 556957 | EC52: 615757 | ED52: 615757 | EE52: 615757 | EF52: 615757 | EG52: 615757 | EH52: 615757 | EI52: 615757 | EJ52: 615757 | EK52: 615757 | EL52: 615757 | EM52: 615757 | EN52: 615757 | EO52: =EN52 -> 615757 | EP52: 555640 | EQ52: 555640 | ER52: 555640 | ES52: 555640 | ET52: 555640 | EU52: 555640 | EV52: 555640 | EW52: 555640 | EX52: 555640 | EY52: 555640 | EZ52: 555640 | FA52: 555640 | FB52: =FA52 -> 555640 | FC52: 392933 | FD52: 392933 | FE52: 392933 | FF52: 392933 | FG52: 392933 | FH52: 392933 | FI52: 392933 | FO52: =FI52 -> 392933
B53: Total | C53: =SUM(C47:C52) -> 3877230 | D53: =SUM(D47:D52) -> 3877230 | E53: =SUM(E47:E52) -> 3877230 | F53: =SUM(F47:F52) -> 3877230 | G53: =SUM(G47:G52) -> 3877230 | H53: =SUM(H47:H52) -> 3877230 | I53: =SUM(I47:I52) -> 3877230 | J53: =SUM(J47:J52) -> 3877230 | ... FO53: =SUM(FO47:FO52) -> 5203817
B54: Fuente: elaboración propia, Dipres.
B56: Presupuesto Vigente de Inversión en Infraestructura Pública del Ministerio de Obras Públicas, 2014-2026 (Subtítulo 29 – Adquisición de Activos No Financieros, miles de pesos)
C57: 2014 | P57: 2015 | AC57: 2016 | AP57: 2017 | BC57: 2018 | BP57: 2019 | CC57: 2020 | CP57: 2021 | DC57: 2022 | DP57: 2023 | EC57: 2024 | EP57: 2025 | FC57: 2026
B58: Programa | C58: Ene | D58: Feb | E58: Mar | F58: Abr | G58: May | H58: Jun | I58: Jul | J58: Ago | K58: Sep | L58: Oct | M58: Nov | N58: Dic | O58: Total 2014 | P58: Ene | Q58: Feb | R58: Mar | S58: Abr | T58: May | U58: Jun | V58: Jul | W58: Ago | X58: Sep | Y58: Oct | Z58: Nov | AA58: Dic | AB58: Total 2015 | AC58: Ene | AD58: Feb | AE58: Mar | AF58: Abr | AG58: May | AH58: Jun | AI58: Jul | AJ58: Ago | AK58: Sep | AL58: Oct | AM58: Nov | AN58: Dic | AO58: Total 2016 | AP58: Ene | AQ58: Feb | AR58: Mar | AS58: Abr | AT58: May | AU58: Jun | AV58: Jul | AW58: Ago | AX58: Sep | AY58: Oct | AZ58: Nov | BA58: Dic | BB58: Total 2017 | BC58: Ene | BD58: Feb | BE58: Mar | BF58: Abr | BG58: May | BH58: Jun | BI58: Jul | BJ58: Ago | BK58: Sep | BL58: Oct | BM58: Nov | BN58: Dic | BO58: Total 2018 | BP58: Ene | BQ58: Feb | BR58: Mar | BS58: Abr | BT58: May | BU58: Jun | BV58: Jul | BW58: Ago | BX58: Sep | BY58: Oct | BZ58: Nov | CA58: Dic | CB58: Total 2019 | CC58: Ene | CD58: Feb | CE58: Mar | CF58: Abr | CG58: May | CH58: Jun | CI58: Jul | CJ58: Ago | CK58: Sep | CL58: Oct | CM58: Nov | CN58: Dic | CO58: Total 2020 | CP58: Ene | CQ58: Feb | CR58: Mar | CS58: Abr | CT58: May | CU58: Jun | CV58: Jul | CW58: Ago | CX58: Sep | CY58: Oct | CZ58: Nov | DA58: Dic | DB58: Total 2021 | DC58: Ene | DD58: Feb | DE58: Mar | DF58: Abr | DG58: May | DH58: Jun | DI58: Jul | DJ58: Ago | DK58: Sep | DL58: Oct | DM58: Nov | DN58: Dic | DO58: Total 2022 | DP58: Ene | DQ58: Feb | DR58: Mar | DS58: Abr | DT58: May | DU58: Jun | DV58: Jul | DW58: Ago | DX58: Sep | DY58: Oct | DZ58: Nov | EA58: Dic | EB58: Total 2023 | EC58: Ene | ED58: Feb | EE58: Mar | EF58: Abr | EG58: May | EH58: Jun | EI58: Jul | EJ58: Ago | EK58: Sep | EL58: Oct | EM58: Nov | EN58: Dic | EO58: Total 2024 | EP58: Ene | EQ58: Feb | ER58: Mar | ES58: Abr | ET58: May | EU58: Jun | EV58: Jul | EW58: Ago | EX58: Sep | EY58: Oct | EZ58: Nov | FA58: Dic | FB58: Total 2025 | FC58: Ene | FD58: Feb | FE58: Mar | FF58: Abr | FG58: May | FH58: Jun | FI58: Jul | FJ58: Ago | FK58: Sep | FL58: Oct | FM58: Nov | FN58: Dic | FO58: Total 2026
B59: Dirección de Vialidad | C59: 2953248 | D59: 2953248 | E59: 2953248 | F59: 2953248 | G59: 2967248 | H59: 13617214 | I59: 16777214 | J59: 16777214 | K59: 16777214 | L59: 18277214 | M59: 18638378 | N59: 12770620 | O59: =N59 -> 12770620 | P59: 1753030 | Q59: 1753030 | R59: 8107652 | S59: 8107652 | T59: 8642652 | U59: 8642652 | V59: 8742652 | W59: 8742652 | X59: 8742652 | Y59: 8742652 | Z59: 11742652 | AA59: 11742652 | AB59: =AA59 -> 11742652 | AC59: 1791359 | AD59: 1791359 | AE59: 1791359 | AF59: 1721359 | AG59: 1721359 | AH59: 2260359 | AI59: 2260359 | AJ59: 2260359 | AK59: 2260359 | AL59: 2260359 | AM59: 2353359 | AN59: 2665605 | AO59: =AN59 -> 2665605 | AP59: 1779405 | AQ59: 1779405 | AR59: 2057405 | AS59: 2057405 | AT59: 2257405 | AU59: 18725105 | AV59: 18941005 | AW59: 19075505 | AX59: 19084105 | AY59: 19084105 | AZ59: 19100105 | BA59: 14280017 | BB59: =BA59 -> 14280017 | BC59: 1606877 | BD59: 1606877 | BE59: 7551961 | BF59: 7551961 | BG59: 7867152 | BH59: 7867152 | BI59: 7603828 | BJ59: 7641450 | BK59: 7641450 | BL59: 7656450 | BM59: 8088150 | BN59: 8261850 | BO59: =BN59 -> 8261850 | BP59: 1639746 | BQ59: 1639746 | BR59: 1639746 | BS59: 1708546 | BT59: 1708546 | BU59: 6540546 | BV59: 6574796 | BW59: 6624796 | BX59: 6624796 | BY59: 6624796 | BZ59: 6624796 | CA59: 6641796 | CB59: =CA59 -> 6641796 | CC59: 1704539 | CD59: 1704539 | CE59: 1704539 | CF59: 1155557 | CG59: 803695 | CH59: 803695 | CI59: 1337695 | CJ59: 1337695 | CK59: 1337695 | CL59: 8003088 | CM59: 8003088 | CN59: 7435088 | CO59: =CN59 -> 7435088 | CP59: 1930914 | CQ59: 1930914 | CR59: 3898492 | CS59: 4709492 | CT59: 4709492 | CU59: 4731492 | CV59: 4731492 | CW59: 4832662 | CX59: 4832662 | CY59: 4832662 | CZ59: 4925662 | DA59: 4819159 | DB59: =DA59 -> 4819159 | DC59: 298233 | DD59: 298233 | DE59: 298233 | DF59: 298233 | DG59: 1895233 | DH59: 1895233 | DI59: 1895233 | DJ59: 1895233 | DK59: 11893879 | DL59: 11893879 | DM59: 11893879 | DN59: 8468149 | DO59: =DN59 -> 8468149 | DP59: 22089448 | DQ59: 22089448 | DR59: 22089448 | DS59: 42047634 | DT59: 42281504 | DU59: 42281504 | DV59: 42281504 | DW59: 42281504 | DX59: 44698344 | DY59: 44698344 | DZ59: 44698344 | EA59: 7233990 | EB59: =EA59 -> 7233990 | EC59: 1135861 | ED59: 1135861 | EE59: 1135861 | EF59: 1135861 | EG59: 1135861 | EH59: 1135861 | EI59: 1135861 | EJ59: 1135861 | EK59: 1135861 | EL59: 1135861 | EM59: 1135861 | EN59: 1135861 | EO59: =EN59 -> 1135861 | EP59: 6213840 | EQ59: 6213840 | ER59: 6213840 | ES59: 6347840 | ET59: 6347840 | EU59: 6347840 | EV59: 6347840 | EW59: 6347840 | EX59: 4559840 | EY59: 4559840 | EZ59: 4559840 | FA59: 2245535 | FB59: =FA59 -> 2245535 | FC59: 1062955 | FD59: 1062955 | FE59: 1582955 | FF59: 1582955 | FG59: 1551066 | FH59: 1551066 | FI59: 1551066 | FO59: =FI59 -> 1551066
B60: Dirección de Obras Hidráulicas | C60: 381750 | D60: 381750 | E60: 381750 | F60: 381750 | G60: 381750 | H60: 381750 | I60: 381750 | J60: 381750 | K60: 381750 | L60: 381750 | M60: 381750 | N60: 381750 | O60: =N60 -> 381750 | P60: 362280 | Q60: 362280 | R60: 362280 | S60: 362280 | T60: 362280 | U60: 362280 | V60: 362280 | W60: 362280 | X60: 362280 | Y60: 362280 | Z60: 362280 | AA60: 362280 | AB60: =AA60 -> 362280 | AC60: 327142 | AD60: 327142 | AE60: 327142 | AF60: 258142 | AG60: 258142 | AH60: 258142 | AI60: 258142 | AJ60: 258142 | AK60: 258142 | AL60: 258142 | AM60: 258142 | AN60: 258142 | AO60: =AN60 -> 258142 | AP60: 174624 | AQ60: 174624 | AR60: 174624 | AS60: 174624 | AT60: 174624 | AU60: 174624 | AV60: 174624 | AW60: 521624 | AX60: 521624 | AY60: 521624 | AZ60: 521624 | BA60: 546624 | BB60: =BA60 -> 546624 | BC60: 139517 | BD60: 139517 | BE60: 139517 | BF60: 139517 | BG60: 139517 | BH60: 139517 | BI60: 131028 | BJ60: 138040 | BK60: 138040 | BL60: 138040 | BM60: 138040 | BN60: 3231423 | BO60: =BN60 -> 3231423 | BP60: 115465 | BQ60: 115465 | BR60: 115465 | BS60: 115465 | BT60: 115465 | BU60: 115465 | BV60: 115465 | BW60: 162235 | BX60: 162235 | BY60: 162235 | BZ60: 162235 | CA60: 754307 | CB60: =CA60 -> 754307 | CC60: 188388 | CD60: 188388 | CE60: 188388 | CF60: 173698 | CG60: 94575 | CH60: 94575 | CI60: 94575 | CJ60: 94575 | CK60: 94575 | CL60: 92075 | CM60: 92075 | CN60: 112017 | CO60: =CN60 -> 112017 | CP60: 128859 | CQ60: 128859 | CR60: 128859 | CS60: 128859 | CT60: 128859 | CU60: 128859 | CV60: 128859 | CW60: 128859 | CX60: 128859 | CY60: 128859 | CZ60: 128859 | DA60: 708689 | DB60: =DA60 -> 708689 | DC60: 130362 | DD60: 130362 | DE60: 130362 | DF60: 130362 | DG60: 130362 | DH60: 130362 | DI60: 130362 | DJ60: 130362 | DK60: 1013888 | DL60: 1013888 | DM60: 1193375 | DN60: 1193375 | DO60: =DN60 -> 1193375 | DP60: 647086 | DQ60: 647086 | DR60: 647086 | DS60: 647086 | DT60: 647086 | DU60: 647086 | DV60: 647086 | DW60: 647086 | DX60: 647086 | DY60: 647086 | DZ60: 647086 | EA60: 647086 | EB60: =EA60 -> 647086 | EC60: 856525 | ED60: 856525 | EE60: 856525 | EF60: 856525 | EG60: 913626 | EH60: 913626 | EI60: 913626 | EJ60: 913626 | EK60: 913626 | EL60: 913626 | EM60: 913626 | EN60: 913626 | EO60: =EN60 -> 913626 | EP60: 1172171 | EQ60: 1172171 | ER60: 1172171 | ES60: 1172171 | ET60: 1172171 | EU60: 1172171 | EV60: 1172171 | EW60: 1172171 | EX60: 1172171 | EY60: 1172171 | EZ60: 1172171 | FA60: 992552 | FB60: =FA60 -> 992552 | FC60: 651088 | FD60: 651088 | FE60: 651088 | FF60: 651088 | FG60: 517480 | FH60: 517480 | FI60: 517480 | FO60: =FI60 -> 517480
B61: Subdirección de APR | C61: 40007 | D61: 40007 | E61: 40007 | F61: 40007 | G61: 40007 | H61: 40007 | I61: 40007 | J61: 40007 | K61: 40007 | L61: 40007 | M61: 40007 | N61: 40007 | O61: =N61 -> 40007 | P61: 78467 | Q61: 78467 | R61: 78467 | S61: 78467 | T61: 78467 | U61: 78467 | V61: 78467 | W61: 78467 | X61: 78467 | Y61: 78467 | Z61: 78467 | AA61: 78467 | AB61: =AA61 -> 78467 | AC61: 62947 | AD61: 62947 | AE61: 62947 | AF61: 62947 | AG61: 62947 | AH61: 62947 | AI61: 62947 | AJ61: 62947 | AK61: 62947 | AL61: 62947 | AM61: 62947 | AN61: 62947 | AO61: =AN61 -> 62947 | AP61: 49257 | AQ61: 49257 | AR61: 49257 | AS61: 49257 | AT61: 49257 | AU61: 49257 | AV61: 49257 | AW61: 49257 | AX61: 49257 | AY61: 49257 | AZ61: 49257 | BA61: 49257 | BB61: =BA61 -> 49257 | BC61: 610722 | BD61: 610722 | BE61: 610722 | BF61: 610722 | BG61: 610722 | BH61: 610722 | BI61: 566060 | BJ61: 566060 | BK61: 566060 | BL61: 566060 | BM61: 566060 | BN61: 566060 | BO61: =BN61 -> 566060 | BP61: 166534 | BQ61: 166534 | BR61: 166534 | BS61: 166534 | BT61: 166534 | BU61: 166534 | BV61: 177586 | BW61: 177586 | BX61: 177586 | BY61: 177586 | BZ61: 177586 | CA61: 177586 | CB61: =CA61 -> 177586 | CC61: 206665 | CD61: 206665 | CE61: 206665 | CF61: 182934 | CG61: 182934 | CH61: 182934 | CI61: 182934 | CJ61: 182934 | CK61: 182934 | CL61: 182934 | CM61: 182934 | CN61: 183383 | CO61: =CN61 -> 183383 | CP61: 160447 | CQ61: 160447 | CR61: 160447 | CS61: 160447 | CT61: 160447 | CU61: 160447 | CV61: 160447 | CW61: 160447 | CX61: 160447 | CY61: 160447 | CZ61: 160447 | DA61: 160447 | DB61: =DA61 -> 160447 | DC61: 455326 | DD61: 455326 | DE61: 455326 | DF61: 455326 | DG61: 455326 | DH61: 455326 | DI61: 455326 | DJ61: 455326 | DK61: 455326 | DL61: 979017 | DM61: 979017 | DN61: 979017 | DO61: =DN61 -> 979017 | DP61: 622609 | DQ61: 622609 | DR61: 622609 | DS61: 622609 | DT61: 622609 | DU61: 622609 | DV61: 622609 | DW61: 622609 | DX61: 622609 | DY61: 622609 | DZ61: 622609 | EA61: 428444 | EB61: =EA61 -> 428444 | EC61: 636104 | ED61: 636104 | EE61: 636104 | EF61: 636104 | EG61: 636104 | EH61: 636104 | EI61: 636104 | EJ61: 636104 | EK61: 636104 | EL61: 636104 | EM61: 636104 | EN61: 636104 | EO61: =EN61 -> 636104 | EP61: 1284794 | EQ61: 1284794 | ER61: 1284794 | ES61: 1284794 | ET61: 1284794 | EU61: 1284794 | EV61: 1284794 | EW61: 1284794 | EX61: 1284794 | EY61: 1284794 | EZ61: 1284794 | FA61: 1212027 | FB61: =FA61 -> 1212027 | FC61: 667445 | FD61: 667445 | FE61: 667445 | FF61: 667445 | FG61: 488932 | FH61: 488932 | FI61: 488932 | FO61: =FI61 -> 488932
B62: Dirección de Obras Portuarias | C62: 166373 | D62: 166373 | E62: 166373 | F62: 166373 | G62: 166373 | H62: 166373 | I62: 166373 | J62: 166373 | K62: 166373 | L62: 166373 | M62: 166373 | N62: 166373 | O62: =N62 -> 166373 | P62: 1590037 | Q62: 1590037 | R62: 1590037 | S62: 1590037 | T62: 1590037 | U62: 1590037 | V62: 1590037 | W62: 1590037 | X62: 1590037 | Y62: 1590037 | Z62: 1590037 | AA62: 1900037 | AB62: =AA62 -> 1900037 | AC62: 6130543 | AD62: 6130543 | AE62: 6130543 | AF62: 6108543 | AG62: 6108543 | AH62: 6108543 | AI62: 6108543 | AJ62: 6108543 | AK62: 6108543 | AL62: 6108543 | AM62: 6108543 | AN62: 4530168 | AO62: =AN62 -> 4530168 | AP62: 3892493 | AQ62: 3892493 | AR62: 3892493 | AS62: 3892493 | AT62: 3892493 | AU62: 3892493 | AV62: 3892493 | AW62: 3892493 | AX62: 3892493 | AY62: 3718873 | AZ62: 3718873 | BA62: 3718873 | BB62: =BA62 -> 3718873 | BC62: 1987092 | BD62: 1987092 | BE62: 1987092 | BF62: 1987092 | BG62: 1987092 | BH62: 1987092 | BI62: 1594960 | BJ62: 1594960 | BK62: 1594960 | BL62: 1594960 | BM62: 1627511 | BN62: 353432 | BO62: =BN62 -> 353432 | BP62: 2440271 | BQ62: 2440271 | BR62: 2390271 | BS62: 2390271 | BT62: 2390271 | BU62: 2390271 | BV62: 2379219 | BW62: 2379219 | BX62: 2379219 | BY62: 2379219 | BZ62: 2379219 | CA62: 869395 | CB62: =CA62 -> 869395 | CC62: 2488259 | CD62: 2488259 | CE62: 2488259 | CF62: 1571869 | CG62: 1541383 | CH62: 1541383 | CI62: 1541383 | CJ62: 1541383 | CK62: 1541383 | CL62: 1538683 | CM62: 2653214 | CN62: 1949794 | CO62: =CN62 -> 1949794 | CP62: 2902086 | CQ62: 2902086 | CR62: 2902086 | CS62: 2902086 | CT62: 2902086 | CU62: 2902086 | CV62: 2902086 | CW62: 2902086 | CX62: 2902086 | CY62: 2902086 | CZ62: 2902086 | DA62: 486360 | DB62: =DA62 -> 486360 | DC62: 1322297 | DD62: 1322297 | DE62: 1322297 | DF62: 1322297 | DG62: 1322297 | DH62: 1322297 | DI62: 1322297 | DJ62: 1322297 | DK62: 1322297 | DL62: 1322297 | DM62: 1322297 | DN62: 958297 | DO62: =DN62 -> 958297 | DP62: 1814843 | DQ62: 1814843 | DR62: 1814843 | DS62: 1814843 | DT62: 1814843 | DU62: 1814843 | DV62: 1814843 | DW62: 1814843 | DX62: 1814843 | DY62: 1814843 | DZ62: 1814843 | EA62: 687226 | EB62: =EA62 -> 687226 | EC62: 5152528 | ED62: 5152528 | EE62: 5152528 | EF62: 5152528 | EG62: 5152528 | EH62: 5152528 | EI62: 5152528 | EJ62: 5152528 | EK62: 5006428 | EL62: 5006428 | EM62: 1731272 | EN62: 1731272 | EO62: =EN62 -> 1731272 | EP62: 2503895 | EQ62: 2503895 | ER62: 2503895 | ES62: 2503895 | ET62: 2503895 | EU62: 2503895 | EV62: 2503895 | EW62: 2503895 | EX62: 2503895 | EY62: 2503895 | EZ62: 2503895 | FA62: 391705 | FB62: =FA62 -> 391705 | FC62: 2135157 | FD62: 2135157 | FE62: 2135157 | FF62: 2135157 | FG62: 2071102 | FH62: 2071102 | FI62: 2071102 | FO62: =FI62 -> 2071102
B63: Dirección de Aeropuertos | C63: 231070 | D63: 231070 | E63: 231070 | F63: 231070 | G63: 231070 | H63: 231070 | I63: 231070 | J63: 231070 | K63: 231070 | L63: 231070 | M63: 231070 | N63: 231070 | O63: =N63 -> 231070 | P63: 467863 | Q63: 467863 | R63: 467863 | S63: 467863 | T63: 467863 | U63: 467863 | V63: 467863 | W63: 467863 | X63: 467863 | Y63: 467863 | Z63: 838663 | AA63: 838663 | AB63: =AA63 -> 838663 | AC63: 173175 | AD63: 173175 | AE63: 173175 | AF63: 173175 | AG63: 173175 | AH63: 173175 | AI63: 173175 | AJ63: 173175 | AK63: 173175 | AL63: 635175 | AM63: 635175 | AN63: 635175 | AO63: =AN63 -> 635175 | AP63: 100131 | AQ63: 100131 | AR63: 100131 | AS63: 100131 | AT63: 100131 | AU63: 100131 | AV63: 100131 | AW63: 100131 | AX63: 100131 | AY63: 1082131 | AZ63: 1082131 | BA63: 1762131 | BB63: =BA63 -> 1762131 | BC63: 95500 | BD63: 95500 | BE63: 95500 | BF63: 95500 | BG63: 95500 | BH63: 95500 | BI63: 85076 | BJ63: 85076 | BK63: 85076 | BL63: 85076 | BM63: 85076 | BN63: 1689211 | BO63: =BN63 -> 1689211 | BP63: 97653 | BQ63: 97653 | BR63: 97653 | BS63: 97653 | BT63: 97653 | BU63: 97653 | BV63: 97653 | BW63: 97653 | BX63: 97653 | BY63: 97653 | BZ63: 97653 | CA63: 97653 | CB63: =CA63 -> 97653 | CC63: 72183 | CD63: 72183 | CE63: 72183 | CF63: 58992 | CG63: 41722 | CH63: 41722 | CI63: 41722 | CJ63: 41722 | CK63: 41722 | CL63: 383162 | CM63: 383162 | CN63: 383162 | CO63: =CN63 -> 383162 | CP63: 103404 | CQ63: 103404 | CR63: 103404 | CS63: 103404 | CT63: 103404 | CU63: 103404 | CV63: 103404 | CW63: 103404 | CX63: 103404 | CY63: 103404 | CZ63: 103404 | DA63: 103404 | DB63: =DA63 -> 103404 | DC63: 76973 | DD63: 76973 | DE63: 76973 | DF63: 76973 | DG63: 162012 | DH63: 162012 | DI63: 162012 | DJ63: 162012 | DK63: 162012 | DL63: 162012 | DM63: 162012 | DN63: 162012 | DO63: =DN63 -> 162012 | DP63: 240323 | DQ63: 240323 | DR63: 240323 | DS63: 240323 | DT63: 240323 | DU63: 240323 | DV63: 240323 | DW63: 240323 | DX63: 240323 | DY63: 240323 | DZ63: 240323 | EA63: 240323 | EB63: =EA63 -> 240323 | EC63: 251537 | ED63: 251537 | EE63: 251537 | EF63: 2079025 | EG63: 2107375 | EH63: 2107375 | EI63: 2107375 | EJ63: 2107375 | EK63: 2107375 | EL63: 2107375 | EM63: 2107375 | EN63: 1998403 | EO63: =EN63 -> 1998403 | EP63: 878719 | EQ63: 878719 | ER63: 878719 | ES63: 878719 | ET63: 878719 | EU63: 878719 | EV63: 878719 | EW63: 878719 | EX63: 878719 | EY63: 878719 | EZ63: 878719 | FA63: 812930 | FB63: =FA63 -> 812930 | FC63: 294239 | FD63: 294239 | FE63: 294239 | FF63: 294239 | FG63: 292976 | FH63: 292976 | FI63: 292976 | FO63: =FI63 -> 292976
B64: Dirección de Arquitectura | C64: 104782 | D64: 104782 | E64: 104782 | F64: 104782 | G64: 142001 | H64: 142001 | I64: 142001 | J64: 142001 | K64: 142001 | L64: 142001 | M64: 142001 | N64: 142001 | O64: =N64 -> 142001 | P64: 95648 | Q64: 95648 | R64: 95648 | S64: 95648 | T64: 95648 | U64: 95648 | V64: 95648 | W64: 95648 | X64: 295648 | Y64: 295648 | Z64: 295648 | AA64: 295648 | AB64: =AA64 -> 295648 | AC64: 96011 | AD64: 96011 | AE64: 96011 | AF64: 96011 | AG64: 96011 | AH64: 131011 | AI64: 131011 | AJ64: 131011 | AK64: 131011 | AL64: 131011 | AM64: 131011 | AN64: 131011 | AO64: =AN64 -> 131011 | AP64: 123692 | AQ64: 123692 | AR64: 131707 | AS64: 131707 | AT64: 131707 | AU64: 154815 | AV64: 154815 | AW64: 154815 | AX64: 154815 | AY64: 154815 | AZ64: 154815 | BA64: 95707 | BB64: =BA64 -> 95707 | BC64: 101075 | BD64: 101075 | BE64: 101075 | BF64: 101075 | BG64: 160183 | BH64: 160183 | BI64: 145935 | BJ64: 165021 | BK64: 165021 | BL64: 290395 | BM64: 290395 | BN64: 304643 | BO64: =BN64 -> 304643 | BP64: 111887 | BQ64: 111887 | BR64: 111887 | BS64: 111887 | BT64: 111887 | BU64: 111887 | BV64: 111887 | BW64: 111887 | BX64: 111887 | BY64: 111887 | BZ64: 111887 | CA64: 111887 | CB64: =CA64 -> 111887 | CC64: 185782 | CD64: 185782 | CE64: 185782 | CF64: 159768 | CG64: 107382 | CH64: 107382 | CI64: 107382 | CJ64: 107382 | CK64: 107382 | CL64: 107382 | CM64: 107382 | CN64: 107382 | CO64: =CN64 -> 107382 | CP64: 107372 | CQ64: 107372 | CR64: 107372 | CS64: 107372 | CT64: 107372 | CU64: 107372 | CV64: 107372 | CW64: 107372 | CX64: 107372 | CY64: 107372 | CZ64: 107372 | DA64: 107372 | DB64: =DA64 -> 107372 | DC64: 169485 | DD64: 169485 | DE64: 169485 | DF64: 169485 | DG64: 169485 | DH64: 169485 | DI64: 169485 | DJ64: 169485 | DK64: 169485 | DL64: 395850 | DM64: 395850 | DN64: 395850 | DO64: =DN64 -> 395850 | DP64: 556957 | DQ64: 556957 | DR64: 556957 | DS64: 556957 | DT64: 556957 | DU64: 556957 | DV64: 556957 | DW64: 556957 | DX64: 556957 | DY64: 556957 | DZ64: 556957 | EA64: 556957 | EB64: =EA64 -> 556957 | EC64: 615757 | ED64: 615757 | EE64: 615757 | EF64: 615757 | EG64: 615757 | EH64: 615757 | EI64: 615757 | EJ64: 632257 | EK64: 632257 | EL64: 632257 | EM64: 632257 | EN64: 632257 | EO64: =EN64 -> 632257 | EP64: 527858 | EQ64: 527858 | ER64: 527858 | ES64: 527858 | ET64: 527858 | EU64: 527858 | EV64: 527858 | EW64: 527858 | EX64: 527858 | EY64: 527858 | EZ64: 527858 | FA64: 527858 | FB64: =FA64 -> 527858 | FC64: 392933 | FD64: 392933 | FE64: 392933 | FF64: 392933 | FG64: 381145 | FH64: 381145 | FI64: 381145 | FO64: =FI64 -> 381145
B65: Total | C65: =SUM(C59:C64) -> 3877230 | D65: =SUM(D59:D64) -> 3877230 | E65: =SUM(E59:E64) -> 3877230 | F65: =SUM(F59:F64) -> 3877230 | G65: =SUM(G59:G64) -> 3928449 | H65: =SUM(H59:H64) -> 14578415 | I65: =SUM(I59:I64) -> 17738415 | J65: =SUM(J59:J64) -> 17738415 | ... FO65: =SUM(FO59:FO64) -> 5302701
B66: Fuente: elaboración propia, Dipres.
B68: Ejecución de Inversión en Infraestructura Pública del Ministerio de Obras Públicas, 2014-2026 (Subtítulo 29 – Adquisición de Activos No Financieros, miles de pesos)
C69: 2014 | P69: 2015 | AC69: 2016 | AP69: 2017 | BC69: 2018 | BP69: 2019 | CC69: 2020 | CP69: 2021 | DC69: 2022 | DP69: 2023 | EC69: 2024 | EP69: 2025 | FC69: 2026
B70: Programa | C70: Ene | D70: Feb | E70: Mar | F70: Abr | G70: May | H70: Jun | I70: Jul | J70: Ago | K70: Sep | L70: Oct | M70: Nov | N70: Dic | O70: Total 2014 | P70: Ene | Q70: Feb | R70: Mar | S70: Abr | T70: May | U70: Jun | V70: Jul | W70: Ago | X70: Sep | Y70: Oct | Z70: Nov | AA70: Dic | AB70: Total 2015 | AC70: Ene | AD70: Feb | AE70: Mar | AF70: Abr | AG70: May | AH70: Jun | AI70: Jul | AJ70: Ago | AK70: Sep | AL70: Oct | AM70: Nov | AN70: Dic | AO70: Total 2016 | AP70: Ene | AQ70: Feb | AR70: Mar | AS70: Abr | AT70: May | AU70: Jun | AV70: Jul | AW70: Ago | AX70: Sep | AY70: Oct | AZ70: Nov | BA70: Dic | BB70: Total 2017 | BC70: Ene | BD70: Feb | BE70: Mar | BF70: Abr | BG70: May | BH70: Jun | BI70: Jul | BJ70: Ago | BK70: Sep | BL70: Oct | BM70: Nov | BN70: Dic | BO70: Total 2018 | BP70: Ene | BQ70: Feb | BR70: Mar | BS70: Abr | BT70: May | BU70: Jun | BV70: Jul | BW70: Ago | BX70: Sep | BY70: Oct | BZ70: Nov | CA70: Dic | CB70: Total 2019 | CC70: Ene | CD70: Feb | CE70: Mar | CF70: Abr | CG70: May | CH70: Jun | CI70: Jul | CJ70: Ago | CK70: Sep | CL70: Oct | CM70: Nov | CN70: Dic | CO70: Total 2020 | CP70: Ene | CQ70: Feb | CR70: Mar | CS70: Abr | CT70: May | CU70: Jun | CV70: Jul | CW70: Ago | CX70: Sep | CY70: Oct | CZ70: Nov | DA70: Dic | DB70: Total 2021 | DC70: Ene | DD70: Feb | DE70: Mar | DF70: Abr | DG70: May | DH70: Jun | DI70: Jul | DJ70: Ago | DK70: Sep | DL70: Oct | DM70: Nov | DN70: Dic | DO70: Total 2022 | DP70: Ene | DQ70: Feb | DR70: Mar | DS70: Abr | DT70: May | DU70: Jun | DV70: Jul | DW70: Ago | DX70: Sep | DY70: Oct | DZ70: Nov | EA70: Dic | EB70: Total 2023 | EC70: Ene | ED70: Feb | EE70: Mar | EF70: Abr | EG70: May | EH70: Jun | EI70: Jul | EJ70: Ago | EK70: Sep | EL70: Oct | EM70: Nov | EN70: Dic | EO70: Total 2024 | EP70: Ene | EQ70: Feb | ER70: Mar | ES70: Abr | ET70: May | EU70: Jun | EV70: Jul | EW70: Ago | EX70: Sep | EY70: Oct | EZ70: Nov | FA70: Dic | FB70: Total 2025 | FC70: Ene | FD70: Feb | FE70: Mar | FF70: Abr | FG70: May | FH70: Jun | FI70: Jul | FJ70: Ago | FK70: Sep | FL70: Oct | FM70: Nov | FN70: Dic | FO70: Total 2026
B71: Dirección de Vialidad | C71: 0 | D71: 3363 | E71: 89766 | F71: 177873 | G71: 347371 | H71: 768455 | I71: 1122871 | J71: 1568088 | K71: 2263223 | L71: 3127503 | M71: 3633055 | N71: 12762763 | O71: =N71 -> 12762763 | P71: 0 | Q71: 2870 | R71: 6339 | S71: 61172 | T71: 711583 | U71: 1495390 | V71: 1891893 | W71: 5438346 | X71: 6548037 | Y71: 6819195 | Z71: 7620746 | AA71: 11724749 | AB71: =AA71 -> 11724749 | AC71: 109 | AD71: 109 | AE71: 251411 | AF71: 311698 | AG71: 338921 | AH71: 351062 | AI71: 353892 | AJ71: 600284 | AK71: 745907 | AL71: 1013149 | AM71: 1394994 | AN71: 2658727 | AO71: =AN71 -> 2658727 | AP71: 309 | AQ71: 845 | AR71: 11077 | AS71: 123120 | AT71: 196933 | AU71: 285370 | AV71: 547537 | AW71: 1009460 | AX71: 1211237 | AY71: 1293769 | AZ71: 1785704 | BA71: 14200656 | BB71: =BA71 -> 14200656 | BC71: 0 | BD71: 0 | BE71: 724 | BF71: 1893231 | BG71: 2311385 | BH71: 4280160 | BI71: 4296433 | BJ71: 4363606 | BK71: 4486603 | BL71: 5980395 | BM71: 6124209 | BN71: 8256058 | BO71: =BN71 -> 8256058 | BP71: 48 | BQ71: 1255 | BR71: 3121 | BS71: 11999 | BT71: 16209 | BU71: 43534 | BV71: 168962 | BW71: 238287 | BX71: 426172 | BY71: 469766 | BZ71: 1120608 | CA71: 6641118 | CB71: =CA71 -> 6641118 | CC71: 0 | CD71: 585 | CE71: 52513 | CF71: 57523 | CG71: 76947 | CH71: 149037 | CI71: 167768 | CJ71: 176713 | CK71: 779715 | CL71: 783383 | CM71: 1097528 | CN71: 5843319 | CO71: =CN71 -> 5843319 | CP71: 0 | CQ71: 425938 | CR71: 1462761 | CS71: 1465974 | CT71: 1481099 | CU71: 1512434 | CV71: 2183844 | CW71: 2347779 | CX71: 2386510 | CY71: 2529946 | CZ71: 3094655 | DA71: 4799532 | DB71: =DA71 -> 4799532 | DC71: 0 | DD71: 0 | DE71: 0 | DF71: 0 | DG71: 109962 | DH71: 110961 | DI71: 111701 | DJ71: 117198 | DK71: 205350 | DL71: 218231 | DM71: 306659 | DN71: 8421395 | DO71: =DN71 -> 8421395 | DP71: 0 | DQ71: 0 | DR71: 2948 | DS71: 4062 | DT71: 190131 | DU71: 222054 | DV71: 245430 | DW71: 275973 | DX71: 456665 | DY71: 720929 | DZ71: 963668 | EA71: 7135336 | EB71: =EA71 -> 7135336 | EC71: 0 | ED71: 0 | EE71: 0 | EF71: 0 | EG71: 1714 | EH71: 3731 | EI71: 3731 | EJ71: 53443 | EK71: 187144 | EL71: 187248 | EM71: 221037 | EN71: 1123525 | EO71: =EN71 -> 1123525 | EP71: 0 | EQ71: 0 | ER71: 0 | ES71: 3488 | ET71: 3488 | EU71: 6802 | EV71: 6802 | EW71: 205085 | EX71: 215026 | EY71: 319809 | EZ71: 541271 | FA71: 2174604 | FB71: =FA71 -> 2174604 | FC71: 0 | FD71: 0 | FE71: 0 | FF71: 1547 | FG71: 1547 | FH71: 4001 | FI71: 4001 | FO71: =FI71 -> 4001
B72: Dirección de Obras Hidráulicas | C72: 1034 | D72: 1034 | E72: 54953 | F72: 56185 | G72: 56766 | H72: 58287 | I72: 81035 | J72: 124589 | K72: 127877 | L72: 227166 | M72: 271989 | N72: 381174 | O72: =N72 -> 381174 | P72: 0 | Q72: 600 | R72: 2848 | S72: 35886 | T72: 37141 | U72: 46047 | V72: 56945 | W72: 89534 | X72: 202171 | Y72: 217407 | Z72: 234284 | AA72: 362008 | AB72: =AA72 -> 362008 | AC72: 81 | AD72: 6200 | AE72: 42765 | AF72: 67427 | AG72: 221926 | AH72: 224260 | AI72: 226362 | AJ72: 229974 | AK72: 231250 | AL72: 232453 | AM72: 234657 | AN72: 257788 | AO72: =AN72 -> 257788 | AP72: 883 | AQ72: 883 | AR72: 883 | AS72: 883 | AT72: 1928 | AU72: 15652 | AV72: 23980 | AW72: 46130 | AX72: 130300 | AY72: 484366 | AZ72: 489621 | BA72: 521394 | BB72: =BA72 -> 521394 | BC72: 0 | BD72: 0 | BE72: 68075 | BF72: 70711 | BG72: 70737 | BH72: 71042 | BI72: 72990 | BJ72: 75523 | BK72: 76055 | BL72: 76160 | BM72: 82646 | BN72: 3222076 | BO72: =BN72 -> 3222076 | BP72: 0 | BQ72: 8598 | BR72: 8707 | BS72: 9293 | BT72: 18342 | BU72: 19070 | BV72: 23140 | BW72: 58242 | BX72: 74817 | BY72: 83298 | BZ72: 90462 | CA72: 735491 | CB72: =CA72 -> 735491 | CC72: 94 | CD72: 586 | CE72: 2824 | CF72: 2824 | CG72: 2903 | CH72: 4098 | CI72: 4690 | CJ72: 16234 | CK72: 16234 | CL72: 21529 | CM72: 21819 | CN72: 106457 | CO72: =CN72 -> 106457 | CP72: 0 | CQ72: 0 | CR72: 0 | CS72: 690 | CT72: 690 | CU72: 890 | CV72: 890 | CW72: 890 | CX72: 26583 | CY72: 37934 | CZ72: 117361 | DA72: 703694 | DB72: =DA72 -> 703694 | DC72: 0 | DD72: 0 | DE72: 397 | DF72: 397 | DG72: 892 | DH72: 20063 | DI72: 21996 | DJ72: 21996 | DK72: 75465 | DL72: 107933 | DM72: 907010 | DN72: 1149989 | DO72: =DN72 -> 1149989 | DP72: 0 | DQ72: 0 | DR72: 30519 | DS72: 34103 | DT72: 58501 | DU72: 58501 | DV72: 103636 | DW72: 103700 | DX72: 192664 | DY72: 195641 | DZ72: 499753 | EA72: 628857 | EB72: =EA72 -> 628857 | EC72: 0 | ED72: 0 | EE72: 563 | EF72: 2527 | EG72: 3420 | EH72: 355096 | EI72: 359380 | EJ72: 402900 | EK72: 466045 | EL72: 466045 | EM72: 466045 | EN72: 899916 | EO72: =EN72 -> 899916 | EP72: 0 | EQ72: 0 | ER72: 0 | ES72: 2009 | ET72: 37835 | EU72: 73615 | EV72: 253012 | EW72: 572413 | EX72: 586562 | EY72: 603974 | EZ72: 818043 | FA72: 963962 | FB72: =FA72 -> 963962 | FC72: 0 | FD72: 0 | FE72: 0 | FF72: 1508 | FG72: 129364 | FH72: 434033 | FI72: 452929 | FO72: =FI72 -> 452929
B73: Subdirección de APR | C73: 0 | D73: 0 | E73: 0 | F73: 158 | G73: 158 | H73: 2851 | I73: 3091 | J73: 4209 | K73: 4548 | L73: 19543 | M73: 20114 | N73: 39562 | O73: =N73 -> 39562 | P73: 0 | Q73: 0 | R73: 0 | S73: 0 | T73: 50 | U73: 219 | V73: 3752 | W73: 4034 | X73: 15970 | Y73: 48323 | Z73: 48523 | AA73: 78328 | AB73: =AA73 -> 78328 | AC73: 0 | AD73: 0 | AE73: 18172 | AF73: 18172 | AG73: 18909 | AH73: 33441 | AI73: 47973 | AJ73: 47973 | AK73: 47973 | AL73: 47973 | AM73: 47973 | AN73: 62859 | AO73: =AN73 -> 62859 | AP73: 0 | AQ73: 0 | AR73: 0 | AS73: 4582 | AT73: 4582 | AU73: 4910 | AV73: 4910 | AW73: 19278 | AX73: 39213 | AY73: 40363 | AZ73: 43648 | BA73: 48831 | BB73: =BA73 -> 48831 | BC73: 0 | BD73: 0 | BE73: 192566 | BF73: 338581 | BG73: 338766 | BH73: 338897 | BI73: 339144 | BJ73: 340166 | BK73: 352012 | BL73: 354410 | BM73: 359566 | BN73: 371308 | BO73: =BN73 -> 371308 | BP73: 0 | BQ73: 0 | BR73: 6370 | BS73: 28886 | BT73: 28886 | BU73: 32938 | BV73: 33031 | BW73: 113263 | BX73: 129421 | BY73: 134520 | BZ73: 152937 | CA73: 176605 | CB73: =CA73 -> 176605 | CC73: 0 | CD73: 96 | CE73: 5191 | CF73: 5191 | CG73: 5191 | CH73: 6386 | CI73: 6923 | CJ73: 22582 | CK73: 33560 | CL73: 46486 | CM73: 49066 | CN73: 172891 | CO73: =CN73 -> 172891 | CP73: 0 | CQ73: 0 | CR73: 8167 | CS73: 8833 | CT73: 8833 | CU73: 8833 | CV73: 8833 | CW73: 12555 | CX73: 61123 | CY73: 70203 | CZ73: 155639 | DA73: 160231 | DB73: =DA73 -> 160231 | DC73: 0 | DD73: 0 | DE73: 0 | DF73: 0 | DG73: 0 | DH73: 10407 | DI73: 16277 | DJ73: 16277 | DK73: 101440 | DL73: 232681 | DM73: 571170 | DN73: 709579 | DO73: =DN73 -> 709579 | DP73: 20554 | DQ73: 20554 | DR73: 20857 | DS73: 41459 | DT73: 41551 | DU73: 41551 | DV73: 163019 | DW73: 163019 | DX73: 209557 | DY73: 209557 | DZ73: 236874 | EA73: 366748 | EB73: =EA73 -> 366748 | EC73: 10076 | ED73: 10269 | EE73: 10269 | EF73: 10269 | EG73: 13954 | EH73: 337449 | EI73: 337449 | EJ73: 444295 | EK73: 461458 | EL73: 470252 | EM73: 470252 | EN73: 612897 | EO73: =EN73 -> 612897 | EP73: 0 | EQ73: 160 | ER73: 160 | ES73: 160 | ET73: 4515 | EU73: 13374 | EV73: 133195 | EW73: 499807 | EX73: 541550 | EY73: 568299 | EZ73: 873723 | FA73: 1203592 | FB73: =FA73 -> 1203592 | FC73: 0 | FD73: 0 | FE73: 0 | FF73: 13239 | FG73: 126731 | FH73: 371354 | FI73: 409008 | FO73: =FI73 -> 409008
B74: Dirección de Obras Portuarias | C74: 28 | D74: 1653 | E74: 2688 | F74: 4655 | G74: 12025 | H74: 62826 | I74: 63775 | J74: 95480 | K74: 126024 | L74: 127041 | M74: 138557 | N74: 164578 | O74: =N74 -> 164578 | P74: 0 | Q74: 0 | R74: 8688 | S74: 76594 | T74: 147628 | U74: 148375 | V74: 148375 | W74: 180831 | X74: 299063 | Y74: 831232 | Z74: 841681 | AA74: 1887067 | AB74: =AA74 -> 1887067 | AC74: 0 | AD74: 0 | AE74: 3725 | AF74: 21787 | AG74: 600528 | AH74: 600638 | AI74: 1677304 | AJ74: 2766835 | AK74: 3300940 | AL74: 4100106 | AM74: 4283586 | AN74: 4478644 | AO74: =AN74 -> 4478644 | AP74: 42 | AQ74: 799133 | AR74: 799559 | AS74: 815806 | AT74: 928261 | AU74: 932834 | AV74: 949476 | AW74: 1550892 | AX74: 2352528 | AY74: 2352966 | AZ74: 3418204 | BA74: 3716927 | BB74: =BA74 -> 3716927 | BC74: 0 | BD74: 1961 | BE74: 3246 | BF74: 3246 | BG74: 5694 | BH74: 28528 | BI74: 41565 | BJ74: 41622 | BK74: 41622 | BL74: 42767 | BM74: 83821 | BN74: 330448 | BO74: =BN74 -> 330448 | BP74: 29 | BQ74: 29 | BR74: 29 | BS74: 116 | BT74: 208 | BU74: 399 | BV74: 399 | BW74: 399 | BX74: 1919 | BY74: 3160 | BZ74: 299768 | CA74: 863900 | CB74: =CA74 -> 863900 | CC74: 0 | CD74: 176042 | CE74: 176719 | CF74: 176794 | CG74: 441735 | CH74: 442125 | CI74: 443658 | CJ74: 735258 | CK74: 735258 | CL74: 1044245 | CM74: 1483899 | CN74: 1947994 | CO74: =CN74 -> 1947994 | CP74: 0 | CQ74: 20 | CR74: 20 | CS74: 40 | CT74: 40 | CU74: 263823 | CV74: 439678 | CW74: 439678 | CX74: 444855 | CY74: 444855 | CZ74: 458920 | DA74: 485917 | DB74: =DA74 -> 485917 | DC74: 0 | DD74: 0 | DE74: 0 | DF74: 22 | DG74: 22 | DH74: 22 | DI74: 22 | DJ74: 22 | DK74: 21191 | DL74: 82685 | DM74: 447234 | DN74: 865046 | DO74: =DN74 -> 865046 | DP74: 0 | DQ74: 6359 | DR74: 7689 | DS74: 49168 | DT74: 90437 | DU74: 151090 | DV74: 151090 | DW74: 152637 | DX74: 367133 | DY74: 367430 | DZ74: 409162 | EA74: 620613 | EB74: =EA74 -> 620613 | EC74: 0 | ED74: 0 | EE74: 0 | EF74: 1891 | EG74: 25269 | EH74: 68307 | EI74: 92369 | EJ74: 255657 | EK74: 297429 | EL74: 650218 | EM74: 722119 | EN74: 1508486 | EO74: =EN74 -> 1508486 | EP74: 0 | EQ74: 0 | ER74: 0 | ES74: 5944 | ET74: 41309 | EU74: 91749 | EV74: 93532 | EW74: 93532 | EX74: 96960 | EY74: 112867 | EZ74: 143043 | FA74: 248096 | FB74: =FA74 -> 248096 | FC74: 70510 | FD74: 70510 | FE74: 77071 | FF74: 91088 | FG74: 155966 | FH74: 155966 | FI74: 161164 | FO74: =FI74 -> 161164
B75: Dirección de Aeropuertos | C75: 169 | D75: 435 | E75: 39580 | F75: 54505 | G75: 56186 | H75: 57808 | I75: 69634 | J75: 114793 | K75: 128678 | L75: 129341 | M75: 205814 | N75: 230680 | O75: =N75 -> 230680 | P75: 98 | Q75: 907 | R75: 1747 | S75: 39102 | T75: 50749 | U75: 52117 | V75: 53586 | W75: 55733 | X75: 63697 | Y75: 82932 | Z75: 158015 | AA75: 838373 | AB75: =AA75 -> 838373 | AC75: 0 | AD75: 17902 | AE75: 25945 | AF75: 51062 | AG75: 54469 | AH75: 55416 | AI75: 56875 | AJ75: 60356 | AK75: 64353 | AL75: 74033 | AM75: 75711 | AN75: 634425 | AO75: =AN75 -> 634425 | AP75: 0 | AQ75: 269 | AR75: 269 | AS75: 22119 | AT75: 22119 | AU75: 22695 | AV75: 46097 | AW75: 48260 | AX75: 48861 | AY75: 61420 | AZ75: 74200 | BA75: 1758867 | BB75: =BA75 -> 1758867 | BC75: 198 | BD75: 1102 | BE75: 5726 | BF75: 28536 | BG75: 48499 | BH75: 53855 | BI75: 60520 | BJ75: 69445 | BK75: 70064 | BL75: 73093 | BM75: 73356 | BN75: 1605443 | BO75: =BN75 -> 1605443 | BP75: 147 | BQ75: 229 | BR75: 344 | BS75: 3873 | BT75: 25548 | BU75: 41488 | BV75: 43633 | BW75: 48371 | BX75: 69965 | BY75: 76233 | BZ75: 80516 | CA75: 97338 | CB75: =CA75 -> 97338 | CC75: 607 | CD75: 1736 | CE75: 2472 | CF75: 2472 | CG75: 18311 | CH75: 18311 | CI75: 18985 | CJ75: 18985 | CK75: 21184 | CL75: 31168 | CM75: 33157 | CN75: 382693 | CO75: =CN75 -> 382693 | CP75: 0 | CQ75: 0 | CR75: 0 | CS75: 0 | CT75: 375 | CU75: 375 | CV75: 375 | CW75: 375 | CX75: 16453 | CY75: 16738 | CZ75: 59581 | DA75: 101089 | DB75: =DA75 -> 101089 | DC75: 0 | DD75: 0 | DE75: 0 | DF75: 43 | DG75: 43 | DH75: 638 | DI75: 3960 | DJ75: 60216 | DK75: 61185 | DL75: 67106 | DM75: 95932 | DN75: 160797 | DO75: =DN75 -> 160797 | DP75: 0 | DQ75: 0 | DR75: 0 | DS75: 0 | DT75: 3085 | DU75: 82381 | DV75: 125991 | DW75: 140950 | DX75: 158342 | DY75: 163795 | DZ75: 191564 | EA75: 237804 | EB75: =EA75 -> 237804 | EC75: 0 | ED75: 0 | EE75: 0 | EF75: 2262 | EG75: 74380 | EH75: 161068 | EI75: 226500 | EJ75: 235972 | EK75: 1485698 | EL75: 1613690 | EM75: 1931498 | EN75: 1997225 | EO75: =EN75 -> 1997225 | EP75: 0 | EQ75: 97469 | ER75: 97751 | ES75: 98001 | ET75: 170182 | EU75: 170245 | EV75: 421065 | EW75: 428624 | EX75: 444757 | EY75: 610730 | EZ75: 614072 | FA75: 809633 | FB75: =FA75 -> 809633 | FC75: 0 | FD75: 0 | FE75: 0 | FF75: 0 | FG75: 0 | FH75: 64950 | FI75: 127454 | FO75: =FI75 -> 127454
B76: Dirección de Arquitectura | C76: 140 | D76: 8109 | E76: 8109 | F76: 8613 | G76: 84253 | H76: 84548 | I76: 86349 | J76: 86349 | K76: 86399 | L76: 98968 | M76: 117677 | N76: 141920 | O76: =N76 -> 141920 | P76: 0 | Q76: 60 | R76: 60 | S76: 2161 | T76: 36520 | U76: 61061 | V76: 74560 | W76: 75213 | X76: 75636 | Y76: 79205 | Z76: 177440 | AA76: 295571 | AB76: =AA76 -> 295571 | AC76: 0 | AD76: 19653 | AE76: 32728 | AF76: 33680 | AG76: 35995 | AH76: 38174 | AI76: 38528 | AJ76: 39517 | AK76: 41442 | AL76: 42876 | AM76: 54418 | AN76: 95971 | AO76: =AN76 -> 95971 | AP76: 0 | AQ76: 1007 | AR76: 1387 | AS76: 4088 | AT76: 18570 | AU76: 18846 | AV76: 38317 | AW76: 42381 | AX76: 45866 | AY76: 54771 | AZ76: 81489 | BA76: 95609 | BB76: =BA76 -> 95609 | BC76: 0 | BD76: 3271 | BE76: 3271 | BF76: 3389 | BG76: 4357 | BH76: 10454 | BI76: 14421 | BJ76: 18234 | BK76: 59217 | BL76: 60033 | BM76: 68642 | BN76: 297380 | BO76: =BN76 -> 297380 | BP76: 693 | BQ76: 15530 | BR76: 15631 | BS76: 20846 | BT76: 65721 | BU76: 89898 | BV76: 92591 | BW76: 100668 | BX76: 100991 | BY76: 103952 | BZ76: 109621 | CA76: 111876 | CB76: =CA76 -> 111876 | CC76: 0 | CD76: 1098 | CE76: 3137 | CF76: 17987 | CG76: 22135 | CH76: 22135 | CI76: 29972 | CJ76: 79295 | CK76: 84364 | CL76: 87854 | CM76: 95431 | CN76: 107174 | CO76: =CN76 -> 107174 | CP76: 0 | CQ76: 0 | CR76: 0 | CS76: 0 | CT76: 0 | CU76: 0 | CV76: 0 | CW76: 0 | CX76: 0 | CY76: 0 | CZ76: 38499 | DA76: 107372 | DB76: =DA76 -> 107372 | DC76: 0 | DD76: 0 | DE76: 0 | DF76: 0 | DG76: 0 | DH76: 0 | DI76: 1222 | DJ76: 9602 | DK76: 92334 | DL76: 96189 | DM76: 319595 | DN76: 395574 | DO76: =DN76 -> 395574 | DP76: 0 | DQ76: 333 | DR76: 581 | DS76: 17754 | DT76: 70246 | DU76: 92472 | DV76: 321438 | DW76: 325356 | DX76: 420771 | DY76: 450435 | DZ76: 501604 | EA76: 554997 | EB76: =EA76 -> 554997 | EC76: 0 | ED76: 47980 | EE76: 92337 | EF76: 95895 | EG76: 268337 | EH76: 389981 | EI76: 421650 | EJ76: 428305 | EK76: 503200 | EL76: 506685 | EM76: 563895 | EN76: 631827 | EO76: =EN76 -> 631827 | EP76: 0 | EQ76: 33966 | ER76: 39677 | ES76: 68547 | ET76: 184933 | EU76: 316527 | EV76: 324773 | EW76: 324773 | EX76: 329257 | EY76: 333451 | EZ76: 436896 | FA76: 504566 | FB76: =FA76 -> 504566 | FC76: 0 | FD76: 0 | FE76: 59187 | FF76: 68554 | FG76: 87338 | FH76: 87338 | FI76: 87338 | FO76: =FI76 -> 87338
B77: Total | C77: =SUM(C71:C76) -> 1371 | D77: =SUM(D71:D76) -> 14594 | E77: =SUM(E71:E76) -> 195096 | F77: =SUM(F71:F76) -> 301989 | G77: =SUM(G71:G76) -> 556759 | H77: =SUM(H71:H76) -> 1034775 | I77: =SUM(I71:I76) -> 1426755 | J77: =SUM(J71:J76) -> 1993508 | ... FO77: =SUM(FO71:FO76) -> 1241894
B78: Fuente: elaboración propia, Dipres.
B81: Subtítulo 33 – Transferencias de Capital
B83: Presupuesto Ley de Inversión en Infraestructura Pública del Ministerio de Obras Públicas, 2014-2026 (Subtítulo 33 – Transferencias de Capital, miles de pesos)
C84: 2014 | P84: 2015 | AC84: 2016 | AP84: 2017 | BC84: 2018 | BP84: 2019 | CC84: 2020 | CP84: 2021 | DC84: 2022 | DP84: 2023 | EC84: 2024 | EP84: 2025 | FC84: 2026
B85: Programa | C85: Ene | D85: Feb | E85: Mar | F85: Abr | G85: May | H85: Jun | I85: Jul | J85: Ago | K85: Sep | L85: Oct | M85: Nov | N85: Dic | O85: Total 2014 | P85: Ene | Q85: Feb | R85: Mar | S85: Abr | T85: May | U85: Jun | V85: Jul | W85: Ago | X85: Sep | Y85: Oct | Z85: Nov | AA85: Dic | AB85: Total 2015 | AC85: Ene | AD85: Feb | AE85: Mar | AF85: Abr | AG85: May | AH85: Jun | AI85: Jul | AJ85: Ago | AK85: Sep | AL85: Oct | AM85: Nov | AN85: Dic | AO85: Total 2016 | AP85: Ene | AQ85: Feb | AR85: Mar | AS85: Abr | AT85: May | AU85: Jun | AV85: Jul | AW85: Ago | AX85: Sep | AY85: Oct | AZ85: Nov | BA85: Dic | BB85: Total 2017 | BC85: Ene | BD85: Feb | BE85: Mar | BF85: Abr | BG85: May | BH85: Jun | BI85: Jul | BJ85: Ago | BK85: Sep | BL85: Oct | BM85: Nov | BN85: Dic | BO85: Total 2018 | BP85: Ene | BQ85: Feb | BR85: Mar | BS85: Abr | BT85: May | BU85: Jun | BV85: Jul | BW85: Ago | BX85: Sep | BY85: Oct | BZ85: Nov | CA85: Dic | CB85: Total 2019 | CC85: Ene | CD85: Feb | CE85: Mar | CF85: Abr | CG85: May | CH85: Jun | CI85: Jul | CJ85: Ago | CK85: Sep | CL85: Oct | CM85: Nov | CN85: Dic | CO85: Total 2020 | CP85: Ene | CQ85: Feb | CR85: Mar | CS85: Abr | CT85: May | CU85: Jun | CV85: Jul | CW85: Ago | CX85: Sep | CY85: Oct | CZ85: Nov | DA85: Dic | DB85: Total 2021 | DC85: Ene | DD85: Feb | DE85: Mar | DF85: Abr | DG85: May | DH85: Jun | DI85: Jul | DJ85: Ago | DK85: Sep | DL85: Oct | DM85: Nov | DN85: Dic | DO85: Total 2022 | DP85: Ene | DQ85: Feb | DR85: Mar | DS85: Abr | DT85: May | DU85: Jun | DV85: Jul | DW85: Ago | DX85: Sep | DY85: Oct | DZ85: Nov | EA85: Dic | EB85: Total 2023 | EC85: Ene | ED85: Feb | EE85: Mar | EF85: Abr | EG85: May | EH85: Jun | EI85: Jul | EJ85: Ago | EK85: Sep | EL85: Oct | EM85: Nov | EN85: Dic | EO85: Total 2024 | EP85: Ene | EQ85: Feb | ER85: Mar | ES85: Abr | ET85: May | EU85: Jun | EV85: Jul | EW85: Ago | EX85: Sep | EY85: Oct | EZ85: Nov | FA85: Dic | FB85: Total 2025 | FC85: Ene | FD85: Feb | FE85: Mar | FF85: Abr | FG85: May | FH85: Jun | FI85: Jul | FJ85: Ago | FK85: Sep | FL85: Oct | FM85: Nov | FN85: Dic | FO85: Total 2026
B86: Dirección de Vialidad | C86: 0 | D86: 0 | E86: 0 | F86: 0 | G86: 0 | H86: 0 | I86: 0 | J86: 0 | K86: 0 | L86: 0 | M86: 0 | N86: 0 | O86: =N86 -> 0 | P86: 0 | Q86: 0 | R86: 0 | S86: 0 | T86: 0 | U86: 0 | V86: 0 | W86: 0 | X86: 0 | Y86: 0 | Z86: 0 | AA86: 0 | AB86: =AA86 -> 0 | AC86: 0 | AD86: 0 | AE86: 0 | AF86: 0 | AG86: 0 | AH86: 0 | AI86: 0 | AJ86: 0 | AK86: 0 | AL86: 0 | AM86: 0 | AN86: 0 | AO86: =AN86 -> 0 | AP86: 0 | AQ86: 0 | AR86: 0 | AS86: 0 | AT86: 0 | AU86: 0 | AV86: 0 | AW86: 0 | AX86: 0 | AY86: 0 | AZ86: 0 | BA86: 0 | BB86: =BA86 -> 0 | BC86: 0 | BD86: 0 | BE86: 0 | BF86: 0 | BG86: 0 | BH86: 0 | BI86: 0 | BJ86: 0 | BK86: 0 | BL86: 0 | BM86: 0 | BN86: 0 | BO86: =BN86 -> 0 | BP86: 0 | BQ86: 0 | BR86: 0 | BS86: 0 | BT86: 0 | BU86: 0 | BV86: 0 | BW86: 0 | BX86: 0 | BY86: 0 | BZ86: 0 | CA86: 0 | CB86: =CA86 -> 0 | CC86: 0 | CD86: 0 | CE86: 0 | CF86: 0 | CG86: 0 | CH86: 0 | CI86: 0 | CJ86: 0 | CK86: 0 | CL86: 0 | CM86: 0 | CN86: 0 | CO86: =CN86 -> 0 | CP86: 0 | CQ86: 0 | CR86: 0 | CS86: 0 | CT86: 0 | CU86: 0 | CV86: 0 | CW86: 0 | CX86: 0 | CY86: 0 | CZ86: 0 | DA86: 0 | DB86: =DA86 -> 0 | DC86: 0 | DD86: 0 | DE86: 0 | DF86: 0 | DG86: 0 | DH86: 0 | DI86: 0 | DJ86: 0 | DK86: 0 | DL86: 0 | DM86: 0 | DN86: 0 | DO86: =DN86 -> 0 | DP86: 0 | DQ86: 0 | DR86: 0 | DS86: 0 | DT86: 0 | DU86: 0 | DV86: 0 | DW86: 0 | DX86: 0 | DY86: 0 | DZ86: 0 | EA86: 0 | EB86: =EA86 -> 0 | EC86: 0 | ED86: 0 | EE86: 0 | EF86: 0 | EG86: 0 | EH86: 0 | EI86: 0 | EJ86: 0 | EK86: 0 | EL86: 0 | EM86: 0 | EN86: 0 | EO86: =EN86 -> 0 | EP86: 0 | EQ86: 0 | ER86: 0 | ES86: 0 | ET86: 0 | EU86: 0 | EV86: 0 | EW86: 0 | EX86: 0 | EY86: 0 | EZ86: 0 | FA86: 0 | FB86: =FA86 -> 0 | FC86: 0 | FD86: 0 | FE86: 0 | FF86: 0 | FG86: 0 | FH86: 0 | FI86: 0 | FO86: =FI86 -> 0
B87: Dirección de Obras Hidráulicas | C87: 0 | D87: 0 | E87: 0 | F87: 0 | G87: 0 | H87: 0 | I87: 0 | J87: 0 | K87: 0 | L87: 0 | M87: 0 | N87: 0 | O87: =N87 -> 0 | P87: 0 | Q87: 0 | R87: 0 | S87: 0 | T87: 0 | U87: 0 | V87: 0 | W87: 0 | X87: 0 | Y87: 0 | Z87: 0 | AA87: 0 | AB87: =AA87 -> 0 | AC87: 0 | AD87: 0 | AE87: 0 | AF87: 0 | AG87: 0 | AH87: 0 | AI87: 0 | AJ87: 0 | AK87: 0 | AL87: 0 | AM87: 0 | AN87: 0 | AO87: =AN87 -> 0 | AP87: 0 | AQ87: 0 | AR87: 0 | AS87: 0 | AT87: 0 | AU87: 0 | AV87: 0 | AW87: 0 | AX87: 0 | AY87: 0 | AZ87: 0 | BA87: 0 | BB87: =BA87 -> 0 | BC87: 0 | BD87: 0 | BE87: 0 | BF87: 0 | BG87: 0 | BH87: 0 | BI87: 0 | BJ87: 0 | BK87: 0 | BL87: 0 | BM87: 0 | BN87: 0 | BO87: =BN87 -> 0 | BP87: 0 | BQ87: 0 | BR87: 0 | BS87: 0 | BT87: 0 | BU87: 0 | BV87: 0 | BW87: 0 | BX87: 0 | BY87: 0 | BZ87: 0 | CA87: 0 | CB87: =CA87 -> 0 | CC87: 0 | CD87: 0 | CE87: 0 | CF87: 0 | CG87: 0 | CH87: 0 | CI87: 0 | CJ87: 0 | CK87: 0 | CL87: 0 | CM87: 0 | CN87: 0 | CO87: =CN87 -> 0 | CP87: 0 | CQ87: 0 | CR87: 0 | CS87: 0 | CT87: 0 | CU87: 0 | CV87: 0 | CW87: 0 | CX87: 0 | CY87: 0 | CZ87: 0 | DA87: 0 | DB87: =DA87 -> 0 | DC87: 0 | DD87: 0 | DE87: 0 | DF87: 0 | DG87: 0 | DH87: 0 | DI87: 0 | DJ87: 0 | DK87: 0 | DL87: 0 | DM87: 0 | DN87: 0 | DO87: =DN87 -> 0 | DP87: 0 | DQ87: 0 | DR87: 0 | DS87: 0 | DT87: 0 | DU87: 0 | DV87: 0 | DW87: 0 | DX87: 0 | DY87: 0 | DZ87: 0 | EA87: 0 | EB87: =EA87 -> 0 | EC87: 0 | ED87: 0 | EE87: 0 | EF87: 0 | EG87: 0 | EH87: 0 | EI87: 0 | EJ87: 0 | EK87: 0 | EL87: 0 | EM87: 0 | EN87: 0 | EO87: =EN87 -> 0 | EP87: 0 | EQ87: 0 | ER87: 0 | ES87: 0 | ET87: 0 | EU87: 0 | EV87: 0 | EW87: 0 | EX87: 0 | EY87: 0 | EZ87: 0 | FA87: 0 | FB87: =FA87 -> 0 | FC87: 0 | FD87: 0 | FE87: 0 | FF87: 0 | FG87: 0 | FH87: 0 | FI87: 0 | FO87: =FI87 -> 0
B88: Subdirección de APR | C88: 0 | D88: 0 | E88: 0 | F88: 0 | G88: 0 | H88: 0 | I88: 0 | J88: 0 | K88: 0 | L88: 0 | M88: 0 | N88: 0 | O88: =N88 -> 0 | P88: 0 | Q88: 0 | R88: 0 | S88: 0 | T88: 0 | U88: 0 | V88: 0 | W88: 0 | X88: 0 | Y88: 0 | Z88: 0 | AA88: 0 | AB88: =AA88 -> 0 | AC88: 0 | AD88: 0 | AE88: 0 | AF88: 0 | AG88: 0 | AH88: 0 | AI88: 0 | AJ88: 0 | AK88: 0 | AL88: 0 | AM88: 0 | AN88: 0 | AO88: =AN88 -> 0 | AP88: 0 | AQ88: 0 | AR88: 0 | AS88: 0 | AT88: 0 | AU88: 0 | AV88: 0 | AW88: 0 | AX88: 0 | AY88: 0 | AZ88: 0 | BA88: 0 | BB88: =BA88 -> 0 | BC88: 0 | BD88: 0 | BE88: 0 | BF88: 0 | BG88: 0 | BH88: 0 | BI88: 0 | BJ88: 0 | BK88: 0 | BL88: 0 | BM88: 0 | BN88: 0 | BO88: =BN88 -> 0 | BP88: 0 | BQ88: 0 | BR88: 0 | BS88: 0 | BT88: 0 | BU88: 0 | BV88: 0 | BW88: 0 | BX88: 0 | BY88: 0 | BZ88: 0 | CA88: 0 | CB88: =CA88 -> 0 | CC88: 0 | CD88: 0 | CE88: 0 | CF88: 0 | CG88: 0 | CH88: 0 | CI88: 0 | CJ88: 0 | CK88: 0 | CL88: 0 | CM88: 0 | CN88: 0 | CO88: =CN88 -> 0 | CP88: 0 | CQ88: 0 | CR88: 0 | CS88: 0 | CT88: 0 | CU88: 0 | CV88: 0 | CW88: 0 | CX88: 0 | CY88: 0 | CZ88: 0 | DA88: 0 | DB88: =DA88 -> 0 | DC88: 0 | DD88: 0 | DE88: 0 | DF88: 0 | DG88: 0 | DH88: 0 | DI88: 0 | DJ88: 0 | DK88: 0 | DL88: 0 | DM88: 0 | DN88: 0 | DO88: =DN88 -> 0 | DP88: 17877772 | DQ88: 17877772 | DR88: 17877772 | DS88: 17877772 | DT88: 17877772 | DU88: 17877772 | DV88: 17877772 | DW88: 17877772 | DX88: 17877772 | DY88: 17877772 | DZ88: 17877772 | EA88: 17877772 | EB88: =EA88 -> 17877772 | EC88: 0 | ED88: 0 | EE88: 0 | EF88: 0 | EG88: 0 | EH88: 0 | EI88: 0 | EJ88: 0 | EK88: 0 | EL88: 0 | EM88: 0 | EN88: 0 | EO88: =EN88 -> 0 | EP88: 0 | EQ88: 0 | ER88: 0 | ES88: 0 | ET88: 0 | EU88: 0 | EV88: 0 | EW88: 0 | EX88: 0 | EY88: 0 | EZ88: 0 | FA88: 0 | FB88: =FA88 -> 0 | FC88: 0 | FD88: 0 | FE88: 0 | FF88: 0 | FG88: 0 | FH88: 0 | FI88: 0 | FO88: =FI88 -> 0
B89: Dirección de Obras Portuarias | C89: 0 | D89: 0 | E89: 0 | F89: 0 | G89: 0 | H89: 0 | I89: 0 | J89: 0 | K89: 0 | L89: 0 | M89: 0 | N89: 0 | O89: =N89 -> 0 | P89: 0 | Q89: 0 | R89: 0 | S89: 0 | T89: 0 | U89: 0 | V89: 0 | W89: 0 | X89: 0 | Y89: 0 | Z89: 0 | AA89: 0 | AB89: =AA89 -> 0 | AC89: 0 | AD89: 0 | AE89: 0 | AF89: 0 | AG89: 0 | AH89: 0 | AI89: 0 | AJ89: 0 | AK89: 0 | AL89: 0 | AM89: 0 | AN89: 0 | AO89: =AN89 -> 0 | AP89: 0 | AQ89: 0 | AR89: 0 | AS89: 0 | AT89: 0 | AU89: 0 | AV89: 0 | AW89: 0 | AX89: 0 | AY89: 0 | AZ89: 0 | BA89: 0 | BB89: =BA89 -> 0 | BC89: 0 | BD89: 0 | BE89: 0 | BF89: 0 | BG89: 0 | BH89: 0 | BI89: 0 | BJ89: 0 | BK89: 0 | BL89: 0 | BM89: 0 | BN89: 0 | BO89: =BN89 -> 0 | BP89: 0 | BQ89: 0 | BR89: 0 | BS89: 0 | BT89: 0 | BU89: 0 | BV89: 0 | BW89: 0 | BX89: 0 | BY89: 0 | BZ89: 0 | CA89: 0 | CB89: =CA89 -> 0 | CC89: 0 | CD89: 0 | CE89: 0 | CF89: 0 | CG89: 0 | CH89: 0 | CI89: 0 | CJ89: 0 | CK89: 0 | CL89: 0 | CM89: 0 | CN89: 0 | CO89: =CN89 -> 0 | CP89: 0 | CQ89: 0 | CR89: 0 | CS89: 0 | CT89: 0 | CU89: 0 | CV89: 0 | CW89: 0 | CX89: 0 | CY89: 0 | CZ89: 0 | DA89: 0 | DB89: =DA89 -> 0 | DC89: 0 | DD89: 0 | DE89: 0 | DF89: 0 | DG89: 0 | DH89: 0 | DI89: 0 | DJ89: 0 | DK89: 0 | DL89: 0 | DM89: 0 | DN89: 0 | DO89: =DN89 -> 0 | DP89: 0 | DQ89: 0 | DR89: 0 | DS89: 0 | DT89: 0 | DU89: 0 | DV89: 0 | DW89: 0 | DX89: 0 | DY89: 0 | DZ89: 0 | EA89: 0 | EB89: =EA89 -> 0 | EC89: 0 | ED89: 0 | EE89: 0 | EF89: 0 | EG89: 0 | EH89: 0 | EI89: 0 | EJ89: 0 | EK89: 0 | EL89: 0 | EM89: 0 | EN89: 0 | EO89: =EN89 -> 0 | EP89: 0 | EQ89: 0 | ER89: 0 | ES89: 0 | ET89: 0 | EU89: 0 | EV89: 0 | EW89: 0 | EX89: 0 | EY89: 0 | EZ89: 0 | FA89: 0 | FB89: =FA89 -> 0 | FC89: 0 | FD89: 0 | FE89: 0 | FF89: 0 | FG89: 0 | FH89: 0 | FI89: 0 | FO89: =FI89 -> 0
B90: Dirección de Aeropuertos | C90: 0 | D90: 0 | E90: 0 | F90: 0 | G90: 0 | H90: 0 | I90: 0 | J90: 0 | K90: 0 | L90: 0 | M90: 0 | N90: 0 | O90: =N90 -> 0 | P90: 0 | Q90: 0 | R90: 0 | S90: 0 | T90: 0 | U90: 0 | V90: 0 | W90: 0 | X90: 0 | Y90: 0 | Z90: 0 | AA90: 0 | AB90: =AA90 -> 0 | AC90: 0 | AD90: 0 | AE90: 0 | AF90: 0 | AG90: 0 | AH90: 0 | AI90: 0 | AJ90: 0 | AK90: 0 | AL90: 0 | AM90: 0 | AN90: 0 | AO90: =AN90 -> 0 | AP90: 0 | AQ90: 0 | AR90: 0 | AS90: 0 | AT90: 0 | AU90: 0 | AV90: 0 | AW90: 0 | AX90: 0 | AY90: 0 | AZ90: 0 | BA90: 0 | BB90: =BA90 -> 0 | BC90: 0 | BD90: 0 | BE90: 0 | BF90: 0 | BG90: 0 | BH90: 0 | BI90: 0 | BJ90: 0 | BK90: 0 | BL90: 0 | BM90: 0 | BN90: 0 | BO90: =BN90 -> 0 | BP90: 0 | BQ90: 0 | BR90: 0 | BS90: 0 | BT90: 0 | BU90: 0 | BV90: 0 | BW90: 0 | BX90: 0 | BY90: 0 | BZ90: 0 | CA90: 0 | CB90: =CA90 -> 0 | CC90: 0 | CD90: 0 | CE90: 0 | CF90: 0 | CG90: 0 | CH90: 0 | CI90: 0 | CJ90: 0 | CK90: 0 | CL90: 0 | CM90: 0 | CN90: 0 | CO90: =CN90 -> 0 | CP90: 0 | CQ90: 0 | CR90: 0 | CS90: 0 | CT90: 0 | CU90: 0 | CV90: 0 | CW90: 0 | CX90: 0 | CY90: 0 | CZ90: 0 | DA90: 0 | DB90: =DA90 -> 0 | DC90: 0 | DD90: 0 | DE90: 0 | DF90: 0 | DG90: 0 | DH90: 0 | DI90: 0 | DJ90: 0 | DK90: 0 | DL90: 0 | DM90: 0 | DN90: 0 | DO90: =DN90 -> 0 | DP90: 0 | DQ90: 0 | DR90: 0 | DS90: 0 | DT90: 0 | DU90: 0 | DV90: 0 | DW90: 0 | DX90: 0 | DY90: 0 | DZ90: 0 | EA90: 0 | EB90: =EA90 -> 0 | EC90: 0 | ED90: 0 | EE90: 0 | EF90: 0 | EG90: 0 | EH90: 0 | EI90: 0 | EJ90: 0 | EK90: 0 | EL90: 0 | EM90: 0 | EN90: 0 | EO90: =EN90 -> 0 | EP90: 0 | EQ90: 0 | ER90: 0 | ES90: 0 | ET90: 0 | EU90: 0 | EV90: 0 | EW90: 0 | EX90: 0 | EY90: 0 | EZ90: 0 | FA90: 0 | FB90: =FA90 -> 0 | FC90: 0 | FD90: 0 | FE90: 0 | FF90: 0 | FG90: 0 | FH90: 0 | FI90: 0 | FO90: =FI90 -> 0
B91: Dirección de Arquitectura | C91: 0 | D91: 0 | E91: 0 | F91: 0 | G91: 0 | H91: 0 | I91: 0 | J91: 0 | K91: 0 | L91: 0 | M91: 0 | N91: 0 | O91: =N91 -> 0 | P91: 0 | Q91: 0 | R91: 0 | S91: 0 | T91: 0 | U91: 0 | V91: 0 | W91: 0 | X91: 0 | Y91: 0 | Z91: 0 | AA91: 0 | AB91: =AA91 -> 0 | AC91: 0 | AD91: 0 | AE91: 0 | AF91: 0 | AG91: 0 | AH91: 0 | AI91: 0 | AJ91: 0 | AK91: 0 | AL91: 0 | AM91: 0 | AN91: 0 | AO91: =AN91 -> 0 | AP91: 0 | AQ91: 0 | AR91: 0 | AS91: 0 | AT91: 0 | AU91: 0 | AV91: 0 | AW91: 0 | AX91: 0 | AY91: 0 | AZ91: 0 | BA91: 0 | BB91: =BA91 -> 0 | BC91: 0 | BD91: 0 | BE91: 0 | BF91: 0 | BG91: 0 | BH91: 0 | BI91: 0 | BJ91: 0 | BK91: 0 | BL91: 0 | BM91: 0 | BN91: 0 | BO91: =BN91 -> 0 | BP91: 0 | BQ91: 0 | BR91: 0 | BS91: 0 | BT91: 0 | BU91: 0 | BV91: 0 | BW91: 0 | BX91: 0 | BY91: 0 | BZ91: 0 | CA91: 0 | CB91: =CA91 -> 0 | CC91: 0 | CD91: 0 | CE91: 0 | CF91: 0 | CG91: 0 | CH91: 0 | CI91: 0 | CJ91: 0 | CK91: 0 | CL91: 0 | CM91: 0 | CN91: 0 | CO91: =CN91 -> 0 | CP91: 0 | CQ91: 0 | CR91: 0 | CS91: 0 | CT91: 0 | CU91: 0 | CV91: 0 | CW91: 0 | CX91: 0 | CY91: 0 | CZ91: 0 | DA91: 0 | DB91: =DA91 -> 0 | DC91: 0 | DD91: 0 | DE91: 0 | DF91: 0 | DG91: 0 | DH91: 0 | DI91: 0 | DJ91: 0 | DK91: 0 | DL91: 0 | DM91: 0 | DN91: 0 | DO91: =DN91 -> 0 | DP91: 0 | DQ91: 0 | DR91: 0 | DS91: 0 | DT91: 0 | DU91: 0 | DV91: 0 | DW91: 0 | DX91: 0 | DY91: 0 | DZ91: 0 | EA91: 0 | EB91: =EA91 -> 0 | EC91: 0 | ED91: 0 | EE91: 0 | EF91: 0 | EG91: 0 | EH91: 0 | EI91: 0 | EJ91: 0 | EK91: 0 | EL91: 0 | EM91: 0 | EN91: 0 | EO91: =EN91 -> 0 | EP91: 0 | EQ91: 0 | ER91: 0 | ES91: 0 | ET91: 0 | EU91: 0 | EV91: 0 | EW91: 0 | EX91: 0 | EY91: 0 | EZ91: 0 | FA91: 0 | FB91: =FA91 -> 0 | FC91: 0 | FD91: 0 | FE91: 0 | FF91: 0 | FG91: 0 | FH91: 0 | FI91: 0 | FO91: =FI91 -> 0
B92: Total | C92: =SUM(C86:C91) -> 0 | D92: =SUM(D86:D91) -> 0 | E92: =SUM(E86:E91) -> 0 | F92: =SUM(F86:F91) -> 0 | G92: =SUM(G86:G91) -> 0 | H92: =SUM(H86:H91) -> 0 | I92: =SUM(I86:I91) -> 0 | J92: =SUM(J86:J91) -> 0 | ... FO92: =SUM(FO86:FO91) -> 0
B93: El Subtítulo 33 solo aparece en APR, desde 2023. En los demás Programas y años no está en los informes de ejecución. Fuente: elaboración propia, Dipres.
B95: Presupuesto Vigente de Inversión en Infraestructura Pública del Ministerio de Obras Públicas, 2014-2026 (Subtítulo 33 – Transferencias de Capital, miles de pesos)
C96: 2014 | P96: 2015 | AC96: 2016 | AP96: 2017 | BC96: 2018 | BP96: 2019 | CC96: 2020 | CP96: 2021 | DC96: 2022 | DP96: 2023 | EC96: 2024 | EP96: 2025 | FC96: 2026
B97: Programa | C97: Ene | D97: Feb | E97: Mar | F97: Abr | G97: May | H97: Jun | I97: Jul | J97: Ago | K97: Sep | L97: Oct | M97: Nov | N97: Dic | O97: Total 2014 | P97: Ene | Q97: Feb | R97: Mar | S97: Abr | T97: May | U97: Jun | V97: Jul | W97: Ago | X97: Sep | Y97: Oct | Z97: Nov | AA97: Dic | AB97: Total 2015 | AC97: Ene | AD97: Feb | AE97: Mar | AF97: Abr | AG97: May | AH97: Jun | AI97: Jul | AJ97: Ago | AK97: Sep | AL97: Oct | AM97: Nov | AN97: Dic | AO97: Total 2016 | AP97: Ene | AQ97: Feb | AR97: Mar | AS97: Abr | AT97: May | AU97: Jun | AV97: Jul | AW97: Ago | AX97: Sep | AY97: Oct | AZ97: Nov | BA97: Dic | BB97: Total 2017 | BC97: Ene | BD97: Feb | BE97: Mar | BF97: Abr | BG97: May | BH97: Jun | BI97: Jul | BJ97: Ago | BK97: Sep | BL97: Oct | BM97: Nov | BN97: Dic | BO97: Total 2018 | BP97: Ene | BQ97: Feb | BR97: Mar | BS97: Abr | BT97: May | BU97: Jun | BV97: Jul | BW97: Ago | BX97: Sep | BY97: Oct | BZ97: Nov | CA97: Dic | CB97: Total 2019 | CC97: Ene | CD97: Feb | CE97: Mar | CF97: Abr | CG97: May | CH97: Jun | CI97: Jul | CJ97: Ago | CK97: Sep | CL97: Oct | CM97: Nov | CN97: Dic | CO97: Total 2020 | CP97: Ene | CQ97: Feb | CR97: Mar | CS97: Abr | CT97: May | CU97: Jun | CV97: Jul | CW97: Ago | CX97: Sep | CY97: Oct | CZ97: Nov | DA97: Dic | DB97: Total 2021 | DC97: Ene | DD97: Feb | DE97: Mar | DF97: Abr | DG97: May | DH97: Jun | DI97: Jul | DJ97: Ago | DK97: Sep | DL97: Oct | DM97: Nov | DN97: Dic | DO97: Total 2022 | DP97: Ene | DQ97: Feb | DR97: Mar | DS97: Abr | DT97: May | DU97: Jun | DV97: Jul | DW97: Ago | DX97: Sep | DY97: Oct | DZ97: Nov | EA97: Dic | EB97: Total 2023 | EC97: Ene | ED97: Feb | EE97: Mar | EF97: Abr | EG97: May | EH97: Jun | EI97: Jul | EJ97: Ago | EK97: Sep | EL97: Oct | EM97: Nov | EN97: Dic | EO97: Total 2024 | EP97: Ene | EQ97: Feb | ER97: Mar | ES97: Abr | ET97: May | EU97: Jun | EV97: Jul | EW97: Ago | EX97: Sep | EY97: Oct | EZ97: Nov | FA97: Dic | FB97: Total 2025 | FC97: Ene | FD97: Feb | FE97: Mar | FF97: Abr | FG97: May | FH97: Jun | FI97: Jul | FJ97: Ago | FK97: Sep | FL97: Oct | FM97: Nov | FN97: Dic | FO97: Total 2026
B98: Dirección de Vialidad | C98: 0 | D98: 0 | E98: 0 | F98: 0 | G98: 0 | H98: 0 | I98: 0 | J98: 0 | K98: 0 | L98: 0 | M98: 0 | N98: 0 | O98: =N98 -> 0 | P98: 0 | Q98: 0 | R98: 0 | S98: 0 | T98: 0 | U98: 0 | V98: 0 | W98: 0 | X98: 0 | Y98: 0 | Z98: 0 | AA98: 0 | AB98: =AA98 -> 0 | AC98: 0 | AD98: 0 | AE98: 0 | AF98: 0 | AG98: 0 | AH98: 0 | AI98: 0 | AJ98: 0 | AK98: 0 | AL98: 0 | AM98: 0 | AN98: 0 | AO98: =AN98 -> 0 | AP98: 0 | AQ98: 0 | AR98: 0 | AS98: 0 | AT98: 0 | AU98: 0 | AV98: 0 | AW98: 0 | AX98: 0 | AY98: 0 | AZ98: 0 | BA98: 0 | BB98: =BA98 -> 0 | BC98: 0 | BD98: 0 | BE98: 0 | BF98: 0 | BG98: 0 | BH98: 0 | BI98: 0 | BJ98: 0 | BK98: 0 | BL98: 0 | BM98: 0 | BN98: 0 | BO98: =BN98 -> 0 | BP98: 0 | BQ98: 0 | BR98: 0 | BS98: 0 | BT98: 0 | BU98: 0 | BV98: 0 | BW98: 0 | BX98: 0 | BY98: 0 | BZ98: 0 | CA98: 0 | CB98: =CA98 -> 0 | CC98: 0 | CD98: 0 | CE98: 0 | CF98: 0 | CG98: 0 | CH98: 0 | CI98: 0 | CJ98: 0 | CK98: 0 | CL98: 0 | CM98: 0 | CN98: 0 | CO98: =CN98 -> 0 | CP98: 0 | CQ98: 0 | CR98: 0 | CS98: 0 | CT98: 0 | CU98: 0 | CV98: 0 | CW98: 0 | CX98: 0 | CY98: 0 | CZ98: 0 | DA98: 0 | DB98: =DA98 -> 0 | DC98: 0 | DD98: 0 | DE98: 0 | DF98: 0 | DG98: 0 | DH98: 0 | DI98: 0 | DJ98: 0 | DK98: 0 | DL98: 0 | DM98: 0 | DN98: 0 | DO98: =DN98 -> 0 | DP98: 0 | DQ98: 0 | DR98: 0 | DS98: 0 | DT98: 0 | DU98: 0 | DV98: 0 | DW98: 0 | DX98: 0 | DY98: 0 | DZ98: 0 | EA98: 0 | EB98: =EA98 -> 0 | EC98: 0 | ED98: 0 | EE98: 0 | EF98: 0 | EG98: 0 | EH98: 0 | EI98: 0 | EJ98: 0 | EK98: 0 | EL98: 0 | EM98: 0 | EN98: 0 | EO98: =EN98 -> 0 | EP98: 0 | EQ98: 0 | ER98: 0 | ES98: 0 | ET98: 0 | EU98: 0 | EV98: 0 | EW98: 0 | EX98: 0 | EY98: 0 | EZ98: 0 | FA98: 0 | FB98: =FA98 -> 0 | FC98: 0 | FD98: 0 | FE98: 0 | FF98: 0 | FG98: 0 | FH98: 0 | FI98: 0 | FO98: =FI98 -> 0
B99: Dirección de Obras Hidráulicas | C99: 0 | D99: 0 | E99: 0 | F99: 0 | G99: 0 | H99: 0 | I99: 0 | J99: 0 | K99: 0 | L99: 0 | M99: 0 | N99: 0 | O99: =N99 -> 0 | P99: 0 | Q99: 0 | R99: 0 | S99: 0 | T99: 0 | U99: 0 | V99: 0 | W99: 0 | X99: 0 | Y99: 0 | Z99: 0 | AA99: 0 | AB99: =AA99 -> 0 | AC99: 0 | AD99: 0 | AE99: 0 | AF99: 0 | AG99: 0 | AH99: 0 | AI99: 0 | AJ99: 0 | AK99: 0 | AL99: 0 | AM99: 0 | AN99: 0 | AO99: =AN99 -> 0 | AP99: 0 | AQ99: 0 | AR99: 0 | AS99: 0 | AT99: 0 | AU99: 0 | AV99: 0 | AW99: 0 | AX99: 0 | AY99: 0 | AZ99: 0 | BA99: 0 | BB99: =BA99 -> 0 | BC99: 0 | BD99: 0 | BE99: 0 | BF99: 0 | BG99: 0 | BH99: 0 | BI99: 0 | BJ99: 0 | BK99: 0 | BL99: 0 | BM99: 0 | BN99: 0 | BO99: =BN99 -> 0 | BP99: 0 | BQ99: 0 | BR99: 0 | BS99: 0 | BT99: 0 | BU99: 0 | BV99: 0 | BW99: 0 | BX99: 0 | BY99: 0 | BZ99: 0 | CA99: 0 | CB99: =CA99 -> 0 | CC99: 0 | CD99: 0 | CE99: 0 | CF99: 0 | CG99: 0 | CH99: 0 | CI99: 0 | CJ99: 0 | CK99: 0 | CL99: 0 | CM99: 0 | CN99: 0 | CO99: =CN99 -> 0 | CP99: 0 | CQ99: 0 | CR99: 0 | CS99: 0 | CT99: 0 | CU99: 0 | CV99: 0 | CW99: 0 | CX99: 0 | CY99: 0 | CZ99: 0 | DA99: 0 | DB99: =DA99 -> 0 | DC99: 0 | DD99: 0 | DE99: 0 | DF99: 0 | DG99: 0 | DH99: 0 | DI99: 0 | DJ99: 0 | DK99: 0 | DL99: 0 | DM99: 0 | DN99: 0 | DO99: =DN99 -> 0 | DP99: 0 | DQ99: 0 | DR99: 0 | DS99: 0 | DT99: 0 | DU99: 0 | DV99: 0 | DW99: 0 | DX99: 0 | DY99: 0 | DZ99: 0 | EA99: 0 | EB99: =EA99 -> 0 | EC99: 0 | ED99: 0 | EE99: 0 | EF99: 0 | EG99: 0 | EH99: 0 | EI99: 0 | EJ99: 0 | EK99: 0 | EL99: 0 | EM99: 0 | EN99: 0 | EO99: =EN99 -> 0 | EP99: 0 | EQ99: 0 | ER99: 0 | ES99: 0 | ET99: 0 | EU99: 0 | EV99: 0 | EW99: 0 | EX99: 0 | EY99: 0 | EZ99: 0 | FA99: 0 | FB99: =FA99 -> 0 | FC99: 0 | FD99: 0 | FE99: 0 | FF99: 0 | FG99: 0 | FH99: 0 | FI99: 0 | FO99: =FI99 -> 0
B100: Subdirección de APR | C100: 0 | D100: 0 | E100: 0 | F100: 0 | G100: 0 | H100: 0 | I100: 0 | J100: 0 | K100: 0 | L100: 0 | M100: 0 | N100: 0 | O100: =N100 -> 0 | P100: 0 | Q100: 0 | R100: 0 | S100: 0 | T100: 0 | U100: 0 | V100: 0 | W100: 0 | X100: 0 | Y100: 0 | Z100: 0 | AA100: 0 | AB100: =AA100 -> 0 | AC100: 0 | AD100: 0 | AE100: 0 | AF100: 0 | AG100: 0 | AH100: 0 | AI100: 0 | AJ100: 0 | AK100: 0 | AL100: 0 | AM100: 0 | AN100: 0 | AO100: =AN100 -> 0 | AP100: 0 | AQ100: 0 | AR100: 0 | AS100: 0 | AT100: 0 | AU100: 0 | AV100: 0 | AW100: 0 | AX100: 0 | AY100: 0 | AZ100: 0 | BA100: 0 | BB100: =BA100 -> 0 | BC100: 0 | BD100: 0 | BE100: 0 | BF100: 0 | BG100: 0 | BH100: 0 | BI100: 0 | BJ100: 0 | BK100: 0 | BL100: 0 | BM100: 0 | BN100: 0 | BO100: =BN100 -> 0 | BP100: 0 | BQ100: 0 | BR100: 0 | BS100: 0 | BT100: 0 | BU100: 0 | BV100: 0 | BW100: 0 | BX100: 0 | BY100: 0 | BZ100: 0 | CA100: 0 | CB100: =CA100 -> 0 | CC100: 0 | CD100: 0 | CE100: 0 | CF100: 0 | CG100: 0 | CH100: 0 | CI100: 0 | CJ100: 0 | CK100: 0 | CL100: 0 | CM100: 0 | CN100: 0 | CO100: =CN100 -> 0 | CP100: 0 | CQ100: 0 | CR100: 0 | CS100: 0 | CT100: 0 | CU100: 0 | CV100: 0 | CW100: 0 | CX100: 0 | CY100: 0 | CZ100: 0 | DA100: 0 | DB100: =DA100 -> 0 | DC100: 0 | DD100: 0 | DE100: 0 | DF100: 0 | DG100: 0 | DH100: 0 | DI100: 0 | DJ100: 0 | DK100: 0 | DL100: 0 | DM100: 0 | DN100: 0 | DO100: =DN100 -> 0 | DP100: 17877772 | DQ100: 17877772 | DR100: 17877772 | DS100: 17877772 | DT100: 17877772 | DU100: 17877772 | DV100: 17877772 | DW100: 17772523 | DX100: 17772523 | DY100: 17772523 | DZ100: 10123523 | EA100: 10123523 | EB100: =EA100 -> 10123523 | EC100: 0 | ED100: 0 | EE100: 0 | EF100: 0 | EG100: 0 | EH100: 0 | EI100: 0 | EJ100: 0 | EK100: 0 | EL100: 0 | EM100: 0 | EN100: 0 | EO100: =EN100 -> 0 | EP100: 0 | EQ100: 0 | ER100: 0 | ES100: 0 | ET100: 0 | EU100: 0 | EV100: 0 | EW100: 0 | EX100: 0 | EY100: 0 | EZ100: 0 | FA100: 0 | FB100: =FA100 -> 0 | FC100: 0 | FD100: 0 | FE100: 0 | FF100: 0 | FG100: 0 | FH100: 0 | FI100: 0 | FO100: =FI100 -> 0
B101: Dirección de Obras Portuarias | C101: 0 | D101: 0 | E101: 0 | F101: 0 | G101: 0 | H101: 0 | I101: 0 | J101: 0 | K101: 0 | L101: 0 | M101: 0 | N101: 0 | O101: =N101 -> 0 | P101: 0 | Q101: 0 | R101: 0 | S101: 0 | T101: 0 | U101: 0 | V101: 0 | W101: 0 | X101: 0 | Y101: 0 | Z101: 0 | AA101: 0 | AB101: =AA101 -> 0 | AC101: 0 | AD101: 0 | AE101: 0 | AF101: 0 | AG101: 0 | AH101: 0 | AI101: 0 | AJ101: 0 | AK101: 0 | AL101: 0 | AM101: 0 | AN101: 0 | AO101: =AN101 -> 0 | AP101: 0 | AQ101: 0 | AR101: 0 | AS101: 0 | AT101: 0 | AU101: 0 | AV101: 0 | AW101: 0 | AX101: 0 | AY101: 0 | AZ101: 0 | BA101: 0 | BB101: =BA101 -> 0 | BC101: 0 | BD101: 0 | BE101: 0 | BF101: 0 | BG101: 0 | BH101: 0 | BI101: 0 | BJ101: 0 | BK101: 0 | BL101: 0 | BM101: 0 | BN101: 0 | BO101: =BN101 -> 0 | BP101: 0 | BQ101: 0 | BR101: 0 | BS101: 0 | BT101: 0 | BU101: 0 | BV101: 0 | BW101: 0 | BX101: 0 | BY101: 0 | BZ101: 0 | CA101: 0 | CB101: =CA101 -> 0 | CC101: 0 | CD101: 0 | CE101: 0 | CF101: 0 | CG101: 0 | CH101: 0 | CI101: 0 | CJ101: 0 | CK101: 0 | CL101: 0 | CM101: 0 | CN101: 0 | CO101: =CN101 -> 0 | CP101: 0 | CQ101: 0 | CR101: 0 | CS101: 0 | CT101: 0 | CU101: 0 | CV101: 0 | CW101: 0 | CX101: 0 | CY101: 0 | CZ101: 0 | DA101: 0 | DB101: =DA101 -> 0 | DC101: 0 | DD101: 0 | DE101: 0 | DF101: 0 | DG101: 0 | DH101: 0 | DI101: 0 | DJ101: 0 | DK101: 0 | DL101: 0 | DM101: 0 | DN101: 0 | DO101: =DN101 -> 0 | DP101: 0 | DQ101: 0 | DR101: 0 | DS101: 0 | DT101: 0 | DU101: 0 | DV101: 0 | DW101: 0 | DX101: 0 | DY101: 0 | DZ101: 0 | EA101: 0 | EB101: =EA101 -> 0 | EC101: 0 | ED101: 0 | EE101: 0 | EF101: 0 | EG101: 0 | EH101: 0 | EI101: 0 | EJ101: 0 | EK101: 0 | EL101: 0 | EM101: 0 | EN101: 0 | EO101: =EN101 -> 0 | EP101: 0 | EQ101: 0 | ER101: 0 | ES101: 0 | ET101: 0 | EU101: 0 | EV101: 0 | EW101: 0 | EX101: 0 | EY101: 0 | EZ101: 0 | FA101: 0 | FB101: =FA101 -> 0 | FC101: 0 | FD101: 0 | FE101: 0 | FF101: 0 | FG101: 0 | FH101: 0 | FI101: 0 | FO101: =FI101 -> 0
B102: Dirección de Aeropuertos | C102: 0 | D102: 0 | E102: 0 | F102: 0 | G102: 0 | H102: 0 | I102: 0 | J102: 0 | K102: 0 | L102: 0 | M102: 0 | N102: 0 | O102: =N102 -> 0 | P102: 0 | Q102: 0 | R102: 0 | S102: 0 | T102: 0 | U102: 0 | V102: 0 | W102: 0 | X102: 0 | Y102: 0 | Z102: 0 | AA102: 0 | AB102: =AA102 -> 0 | AC102: 0 | AD102: 0 | AE102: 0 | AF102: 0 | AG102: 0 | AH102: 0 | AI102: 0 | AJ102: 0 | AK102: 0 | AL102: 0 | AM102: 0 | AN102: 0 | AO102: =AN102 -> 0 | AP102: 0 | AQ102: 0 | AR102: 0 | AS102: 0 | AT102: 0 | AU102: 0 | AV102: 0 | AW102: 0 | AX102: 0 | AY102: 0 | AZ102: 0 | BA102: 0 | BB102: =BA102 -> 0 | BC102: 0 | BD102: 0 | BE102: 0 | BF102: 0 | BG102: 0 | BH102: 0 | BI102: 0 | BJ102: 0 | BK102: 0 | BL102: 0 | BM102: 0 | BN102: 0 | BO102: =BN102 -> 0 | BP102: 0 | BQ102: 0 | BR102: 0 | BS102: 0 | BT102: 0 | BU102: 0 | BV102: 0 | BW102: 0 | BX102: 0 | BY102: 0 | BZ102: 0 | CA102: 0 | CB102: =CA102 -> 0 | CC102: 0 | CD102: 0 | CE102: 0 | CF102: 0 | CG102: 0 | CH102: 0 | CI102: 0 | CJ102: 0 | CK102: 0 | CL102: 0 | CM102: 0 | CN102: 0 | CO102: =CN102 -> 0 | CP102: 0 | CQ102: 0 | CR102: 0 | CS102: 0 | CT102: 0 | CU102: 0 | CV102: 0 | CW102: 0 | CX102: 0 | CY102: 0 | CZ102: 0 | DA102: 0 | DB102: =DA102 -> 0 | DC102: 0 | DD102: 0 | DE102: 0 | DF102: 0 | DG102: 0 | DH102: 0 | DI102: 0 | DJ102: 0 | DK102: 0 | DL102: 0 | DM102: 0 | DN102: 0 | DO102: =DN102 -> 0 | DP102: 0 | DQ102: 0 | DR102: 0 | DS102: 0 | DT102: 0 | DU102: 0 | DV102: 0 | DW102: 0 | DX102: 0 | DY102: 0 | DZ102: 0 | EA102: 0 | EB102: =EA102 -> 0 | EC102: 0 | ED102: 0 | EE102: 0 | EF102: 0 | EG102: 0 | EH102: 0 | EI102: 0 | EJ102: 0 | EK102: 0 | EL102: 0 | EM102: 0 | EN102: 0 | EO102: =EN102 -> 0 | EP102: 0 | EQ102: 0 | ER102: 0 | ES102: 0 | ET102: 0 | EU102: 0 | EV102: 0 | EW102: 0 | EX102: 0 | EY102: 0 | EZ102: 0 | FA102: 0 | FB102: =FA102 -> 0 | FC102: 0 | FD102: 0 | FE102: 0 | FF102: 0 | FG102: 0 | FH102: 0 | FI102: 0 | FO102: =FI102 -> 0
B103: Dirección de Arquitectura | C103: 0 | D103: 0 | E103: 0 | F103: 0 | G103: 0 | H103: 0 | I103: 0 | J103: 0 | K103: 0 | L103: 0 | M103: 0 | N103: 0 | O103: =N103 -> 0 | P103: 0 | Q103: 0 | R103: 0 | S103: 0 | T103: 0 | U103: 0 | V103: 0 | W103: 0 | X103: 0 | Y103: 0 | Z103: 0 | AA103: 0 | AB103: =AA103 -> 0 | AC103: 0 | AD103: 0 | AE103: 0 | AF103: 0 | AG103: 0 | AH103: 0 | AI103: 0 | AJ103: 0 | AK103: 0 | AL103: 0 | AM103: 0 | AN103: 0 | AO103: =AN103 -> 0 | AP103: 0 | AQ103: 0 | AR103: 0 | AS103: 0 | AT103: 0 | AU103: 0 | AV103: 0 | AW103: 0 | AX103: 0 | AY103: 0 | AZ103: 0 | BA103: 0 | BB103: =BA103 -> 0 | BC103: 0 | BD103: 0 | BE103: 0 | BF103: 0 | BG103: 0 | BH103: 0 | BI103: 0 | BJ103: 0 | BK103: 0 | BL103: 0 | BM103: 0 | BN103: 0 | BO103: =BN103 -> 0 | BP103: 0 | BQ103: 0 | BR103: 0 | BS103: 0 | BT103: 0 | BU103: 0 | BV103: 0 | BW103: 0 | BX103: 0 | BY103: 0 | BZ103: 0 | CA103: 0 | CB103: =CA103 -> 0 | CC103: 0 | CD103: 0 | CE103: 0 | CF103: 0 | CG103: 0 | CH103: 0 | CI103: 0 | CJ103: 0 | CK103: 0 | CL103: 0 | CM103: 0 | CN103: 0 | CO103: =CN103 -> 0 | CP103: 0 | CQ103: 0 | CR103: 0 | CS103: 0 | CT103: 0 | CU103: 0 | CV103: 0 | CW103: 0 | CX103: 0 | CY103: 0 | CZ103: 0 | DA103: 0 | DB103: =DA103 -> 0 | DC103: 0 | DD103: 0 | DE103: 0 | DF103: 0 | DG103: 0 | DH103: 0 | DI103: 0 | DJ103: 0 | DK103: 0 | DL103: 0 | DM103: 0 | DN103: 0 | DO103: =DN103 -> 0 | DP103: 0 | DQ103: 0 | DR103: 0 | DS103: 0 | DT103: 0 | DU103: 0 | DV103: 0 | DW103: 0 | DX103: 0 | DY103: 0 | DZ103: 0 | EA103: 0 | EB103: =EA103 -> 0 | EC103: 0 | ED103: 0 | EE103: 0 | EF103: 0 | EG103: 0 | EH103: 0 | EI103: 0 | EJ103: 0 | EK103: 0 | EL103: 0 | EM103: 0 | EN103: 0 | EO103: =EN103 -> 0 | EP103: 0 | EQ103: 0 | ER103: 0 | ES103: 0 | ET103: 0 | EU103: 0 | EV103: 0 | EW103: 0 | EX103: 0 | EY103: 0 | EZ103: 0 | FA103: 0 | FB103: =FA103 -> 0 | FC103: 0 | FD103: 0 | FE103: 0 | FF103: 0 | FG103: 0 | FH103: 0 | FI103: 0 | FO103: =FI103 -> 0
B104: Total | C104: =SUM(C98:C103) -> 0 | D104: =SUM(D98:D103) -> 0 | E104: =SUM(E98:E103) -> 0 | F104: =SUM(F98:F103) -> 0 | G104: =SUM(G98:G103) -> 0 | H104: =SUM(H98:H103) -> 0 | I104: =SUM(I98:I103) -> 0 | J104: =SUM(J98:J103) -> 0 | ... FO104: =SUM(FO98:FO103) -> 0
B105: El Subtítulo 33 solo aparece en APR, desde 2023. En los demás Programas y años no está en los informes de ejecución. Fuente: elaboración propia, Dipres.
B107: Ejecución de Inversión en Infraestructura Pública del Ministerio de Obras Públicas, 2014-2026 (Subtítulo 33 – Transferencias de Capital, miles de pesos)
C108: 2014 | P108: 2015 | AC108: 2016 | AP108: 2017 | BC108: 2018 | BP108: 2019 | CC108: 2020 | CP108: 2021 | DC108: 2022 | DP108: 2023 | EC108: 2024 | EP108: 2025 | FC108: 2026
B109: Programa | C109: Ene | D109: Feb | E109: Mar | F109: Abr | G109: May | H109: Jun | I109: Jul | J109: Ago | K109: Sep | L109: Oct | M109: Nov | N109: Dic | O109: Total 2014 | P109: Ene | Q109: Feb | R109: Mar | S109: Abr | T109: May | U109: Jun | V109: Jul | W109: Ago | X109: Sep | Y109: Oct | Z109: Nov | AA109: Dic | AB109: Total 2015 | AC109: Ene | AD109: Feb | AE109: Mar | AF109: Abr | AG109: May | AH109: Jun | AI109: Jul | AJ109: Ago | AK109: Sep | AL109: Oct | AM109: Nov | AN109: Dic | AO109: Total 2016 | AP109: Ene | AQ109: Feb | AR109: Mar | AS109: Abr | AT109: May | AU109: Jun | AV109: Jul | AW109: Ago | AX109: Sep | AY109: Oct | AZ109: Nov | BA109: Dic | BB109: Total 2017 | BC109: Ene | BD109: Feb | BE109: Mar | BF109: Abr | BG109: May | BH109: Jun | BI109: Jul | BJ109: Ago | BK109: Sep | BL109: Oct | BM109: Nov | BN109: Dic | BO109: Total 2018 | BP109: Ene | BQ109: Feb | BR109: Mar | BS109: Abr | BT109: May | BU109: Jun | BV109: Jul | BW109: Ago | BX109: Sep | BY109: Oct | BZ109: Nov | CA109: Dic | CB109: Total 2019 | CC109: Ene | CD109: Feb | CE109: Mar | CF109: Abr | CG109: May | CH109: Jun | CI109: Jul | CJ109: Ago | CK109: Sep | CL109: Oct | CM109: Nov | CN109: Dic | CO109: Total 2020 | CP109: Ene | CQ109: Feb | CR109: Mar | CS109: Abr | CT109: May | CU109: Jun | CV109: Jul | CW109: Ago | CX109: Sep | CY109: Oct | CZ109: Nov | DA109: Dic | DB109: Total 2021 | DC109: Ene | DD109: Feb | DE109: Mar | DF109: Abr | DG109: May | DH109: Jun | DI109: Jul | DJ109: Ago | DK109: Sep | DL109: Oct | DM109: Nov | DN109: Dic | DO109: Total 2022 | DP109: Ene | DQ109: Feb | DR109: Mar | DS109: Abr | DT109: May | DU109: Jun | DV109: Jul | DW109: Ago | DX109: Sep | DY109: Oct | DZ109: Nov | EA109: Dic | EB109: Total 2023 | EC109: Ene | ED109: Feb | EE109: Mar | EF109: Abr | EG109: May | EH109: Jun | EI109: Jul | EJ109: Ago | EK109: Sep | EL109: Oct | EM109: Nov | EN109: Dic | EO109: Total 2024 | EP109: Ene | EQ109: Feb | ER109: Mar | ES109: Abr | ET109: May | EU109: Jun | EV109: Jul | EW109: Ago | EX109: Sep | EY109: Oct | EZ109: Nov | FA109: Dic | FB109: Total 2025 | FC109: Ene | FD109: Feb | FE109: Mar | FF109: Abr | FG109: May | FH109: Jun | FI109: Jul | FJ109: Ago | FK109: Sep | FL109: Oct | FM109: Nov | FN109: Dic | FO109: Total 2026
B110: Dirección de Vialidad | C110: 0 | D110: 0 | E110: 0 | F110: 0 | G110: 0 | H110: 0 | I110: 0 | J110: 0 | K110: 0 | L110: 0 | M110: 0 | N110: 0 | O110: =N110 -> 0 | P110: 0 | Q110: 0 | R110: 0 | S110: 0 | T110: 0 | U110: 0 | V110: 0 | W110: 0 | X110: 0 | Y110: 0 | Z110: 0 | AA110: 0 | AB110: =AA110 -> 0 | AC110: 0 | AD110: 0 | AE110: 0 | AF110: 0 | AG110: 0 | AH110: 0 | AI110: 0 | AJ110: 0 | AK110: 0 | AL110: 0 | AM110: 0 | AN110: 0 | AO110: =AN110 -> 0 | AP110: 0 | AQ110: 0 | AR110: 0 | AS110: 0 | AT110: 0 | AU110: 0 | AV110: 0 | AW110: 0 | AX110: 0 | AY110: 0 | AZ110: 0 | BA110: 0 | BB110: =BA110 -> 0 | BC110: 0 | BD110: 0 | BE110: 0 | BF110: 0 | BG110: 0 | BH110: 0 | BI110: 0 | BJ110: 0 | BK110: 0 | BL110: 0 | BM110: 0 | BN110: 0 | BO110: =BN110 -> 0 | BP110: 0 | BQ110: 0 | BR110: 0 | BS110: 0 | BT110: 0 | BU110: 0 | BV110: 0 | BW110: 0 | BX110: 0 | BY110: 0 | BZ110: 0 | CA110: 0 | CB110: =CA110 -> 0 | CC110: 0 | CD110: 0 | CE110: 0 | CF110: 0 | CG110: 0 | CH110: 0 | CI110: 0 | CJ110: 0 | CK110: 0 | CL110: 0 | CM110: 0 | CN110: 0 | CO110: =CN110 -> 0 | CP110: 0 | CQ110: 0 | CR110: 0 | CS110: 0 | CT110: 0 | CU110: 0 | CV110: 0 | CW110: 0 | CX110: 0 | CY110: 0 | CZ110: 0 | DA110: 0 | DB110: =DA110 -> 0 | DC110: 0 | DD110: 0 | DE110: 0 | DF110: 0 | DG110: 0 | DH110: 0 | DI110: 0 | DJ110: 0 | DK110: 0 | DL110: 0 | DM110: 0 | DN110: 0 | DO110: =DN110 -> 0 | DP110: 0 | DQ110: 0 | DR110: 0 | DS110: 0 | DT110: 0 | DU110: 0 | DV110: 0 | DW110: 0 | DX110: 0 | DY110: 0 | DZ110: 0 | EA110: 0 | EB110: =EA110 -> 0 | EC110: 0 | ED110: 0 | EE110: 0 | EF110: 0 | EG110: 0 | EH110: 0 | EI110: 0 | EJ110: 0 | EK110: 0 | EL110: 0 | EM110: 0 | EN110: 0 | EO110: =EN110 -> 0 | EP110: 0 | EQ110: 0 | ER110: 0 | ES110: 0 | ET110: 0 | EU110: 0 | EV110: 0 | EW110: 0 | EX110: 0 | EY110: 0 | EZ110: 0 | FA110: 0 | FB110: =FA110 -> 0 | FC110: 0 | FD110: 0 | FE110: 0 | FF110: 0 | FG110: 0 | FH110: 0 | FI110: 0 | FO110: =FI110 -> 0
B111: Dirección de Obras Hidráulicas | C111: 0 | D111: 0 | E111: 0 | F111: 0 | G111: 0 | H111: 0 | I111: 0 | J111: 0 | K111: 0 | L111: 0 | M111: 0 | N111: 0 | O111: =N111 -> 0 | P111: 0 | Q111: 0 | R111: 0 | S111: 0 | T111: 0 | U111: 0 | V111: 0 | W111: 0 | X111: 0 | Y111: 0 | Z111: 0 | AA111: 0 | AB111: =AA111 -> 0 | AC111: 0 | AD111: 0 | AE111: 0 | AF111: 0 | AG111: 0 | AH111: 0 | AI111: 0 | AJ111: 0 | AK111: 0 | AL111: 0 | AM111: 0 | AN111: 0 | AO111: =AN111 -> 0 | AP111: 0 | AQ111: 0 | AR111: 0 | AS111: 0 | AT111: 0 | AU111: 0 | AV111: 0 | AW111: 0 | AX111: 0 | AY111: 0 | AZ111: 0 | BA111: 0 | BB111: =BA111 -> 0 | BC111: 0 | BD111: 0 | BE111: 0 | BF111: 0 | BG111: 0 | BH111: 0 | BI111: 0 | BJ111: 0 | BK111: 0 | BL111: 0 | BM111: 0 | BN111: 0 | BO111: =BN111 -> 0 | BP111: 0 | BQ111: 0 | BR111: 0 | BS111: 0 | BT111: 0 | BU111: 0 | BV111: 0 | BW111: 0 | BX111: 0 | BY111: 0 | BZ111: 0 | CA111: 0 | CB111: =CA111 -> 0 | CC111: 0 | CD111: 0 | CE111: 0 | CF111: 0 | CG111: 0 | CH111: 0 | CI111: 0 | CJ111: 0 | CK111: 0 | CL111: 0 | CM111: 0 | CN111: 0 | CO111: =CN111 -> 0 | CP111: 0 | CQ111: 0 | CR111: 0 | CS111: 0 | CT111: 0 | CU111: 0 | CV111: 0 | CW111: 0 | CX111: 0 | CY111: 0 | CZ111: 0 | DA111: 0 | DB111: =DA111 -> 0 | DC111: 0 | DD111: 0 | DE111: 0 | DF111: 0 | DG111: 0 | DH111: 0 | DI111: 0 | DJ111: 0 | DK111: 0 | DL111: 0 | DM111: 0 | DN111: 0 | DO111: =DN111 -> 0 | DP111: 0 | DQ111: 0 | DR111: 0 | DS111: 0 | DT111: 0 | DU111: 0 | DV111: 0 | DW111: 0 | DX111: 0 | DY111: 0 | DZ111: 0 | EA111: 0 | EB111: =EA111 -> 0 | EC111: 0 | ED111: 0 | EE111: 0 | EF111: 0 | EG111: 0 | EH111: 0 | EI111: 0 | EJ111: 0 | EK111: 0 | EL111: 0 | EM111: 0 | EN111: 0 | EO111: =EN111 -> 0 | EP111: 0 | EQ111: 0 | ER111: 0 | ES111: 0 | ET111: 0 | EU111: 0 | EV111: 0 | EW111: 0 | EX111: 0 | EY111: 0 | EZ111: 0 | FA111: 0 | FB111: =FA111 -> 0 | FC111: 0 | FD111: 0 | FE111: 0 | FF111: 0 | FG111: 0 | FH111: 0 | FI111: 0 | FO111: =FI111 -> 0
B112: Subdirección de APR | C112: 0 | D112: 0 | E112: 0 | F112: 0 | G112: 0 | H112: 0 | I112: 0 | J112: 0 | K112: 0 | L112: 0 | M112: 0 | N112: 0 | O112: =N112 -> 0 | P112: 0 | Q112: 0 | R112: 0 | S112: 0 | T112: 0 | U112: 0 | V112: 0 | W112: 0 | X112: 0 | Y112: 0 | Z112: 0 | AA112: 0 | AB112: =AA112 -> 0 | AC112: 0 | AD112: 0 | AE112: 0 | AF112: 0 | AG112: 0 | AH112: 0 | AI112: 0 | AJ112: 0 | AK112: 0 | AL112: 0 | AM112: 0 | AN112: 0 | AO112: =AN112 -> 0 | AP112: 0 | AQ112: 0 | AR112: 0 | AS112: 0 | AT112: 0 | AU112: 0 | AV112: 0 | AW112: 0 | AX112: 0 | AY112: 0 | AZ112: 0 | BA112: 0 | BB112: =BA112 -> 0 | BC112: 0 | BD112: 0 | BE112: 0 | BF112: 0 | BG112: 0 | BH112: 0 | BI112: 0 | BJ112: 0 | BK112: 0 | BL112: 0 | BM112: 0 | BN112: 0 | BO112: =BN112 -> 0 | BP112: 0 | BQ112: 0 | BR112: 0 | BS112: 0 | BT112: 0 | BU112: 0 | BV112: 0 | BW112: 0 | BX112: 0 | BY112: 0 | BZ112: 0 | CA112: 0 | CB112: =CA112 -> 0 | CC112: 0 | CD112: 0 | CE112: 0 | CF112: 0 | CG112: 0 | CH112: 0 | CI112: 0 | CJ112: 0 | CK112: 0 | CL112: 0 | CM112: 0 | CN112: 0 | CO112: =CN112 -> 0 | CP112: 0 | CQ112: 0 | CR112: 0 | CS112: 0 | CT112: 0 | CU112: 0 | CV112: 0 | CW112: 0 | CX112: 0 | CY112: 0 | CZ112: 0 | DA112: 0 | DB112: =DA112 -> 0 | DC112: 0 | DD112: 0 | DE112: 0 | DF112: 0 | DG112: 0 | DH112: 0 | DI112: 0 | DJ112: 0 | DK112: 0 | DL112: 0 | DM112: 0 | DN112: 0 | DO112: =DN112 -> 0 | DP112: 0 | DQ112: 0 | DR112: 0 | DS112: 0 | DT112: 0 | DU112: 0 | DV112: 1050 | DW112: 1050 | DX112: 37795 | DY112: 169483 | DZ112: 843033 | EA112: 3861859 | EB112: =EA112 -> 3861859 | EC112: 0 | ED112: 0 | EE112: 0 | EF112: 0 | EG112: 0 | EH112: 0 | EI112: 0 | EJ112: 0 | EK112: 0 | EL112: 0 | EM112: 0 | EN112: 0 | EO112: =EN112 -> 0 | EP112: 0 | EQ112: 0 | ER112: 0 | ES112: 0 | ET112: 0 | EU112: 0 | EV112: 0 | EW112: 0 | EX112: 0 | EY112: 0 | EZ112: 0 | FA112: 0 | FB112: =FA112 -> 0 | FC112: 0 | FD112: 0 | FE112: 0 | FF112: 0 | FG112: 0 | FH112: 0 | FI112: 0 | FO112: =FI112 -> 0
B113: Dirección de Obras Portuarias | C113: 0 | D113: 0 | E113: 0 | F113: 0 | G113: 0 | H113: 0 | I113: 0 | J113: 0 | K113: 0 | L113: 0 | M113: 0 | N113: 0 | O113: =N113 -> 0 | P113: 0 | Q113: 0 | R113: 0 | S113: 0 | T113: 0 | U113: 0 | V113: 0 | W113: 0 | X113: 0 | Y113: 0 | Z113: 0 | AA113: 0 | AB113: =AA113 -> 0 | AC113: 0 | AD113: 0 | AE113: 0 | AF113: 0 | AG113: 0 | AH113: 0 | AI113: 0 | AJ113: 0 | AK113: 0 | AL113: 0 | AM113: 0 | AN113: 0 | AO113: =AN113 -> 0 | AP113: 0 | AQ113: 0 | AR113: 0 | AS113: 0 | AT113: 0 | AU113: 0 | AV113: 0 | AW113: 0 | AX113: 0 | AY113: 0 | AZ113: 0 | BA113: 0 | BB113: =BA113 -> 0 | BC113: 0 | BD113: 0 | BE113: 0 | BF113: 0 | BG113: 0 | BH113: 0 | BI113: 0 | BJ113: 0 | BK113: 0 | BL113: 0 | BM113: 0 | BN113: 0 | BO113: =BN113 -> 0 | BP113: 0 | BQ113: 0 | BR113: 0 | BS113: 0 | BT113: 0 | BU113: 0 | BV113: 0 | BW113: 0 | BX113: 0 | BY113: 0 | BZ113: 0 | CA113: 0 | CB113: =CA113 -> 0 | CC113: 0 | CD113: 0 | CE113: 0 | CF113: 0 | CG113: 0 | CH113: 0 | CI113: 0 | CJ113: 0 | CK113: 0 | CL113: 0 | CM113: 0 | CN113: 0 | CO113: =CN113 -> 0 | CP113: 0 | CQ113: 0 | CR113: 0 | CS113: 0 | CT113: 0 | CU113: 0 | CV113: 0 | CW113: 0 | CX113: 0 | CY113: 0 | CZ113: 0 | DA113: 0 | DB113: =DA113 -> 0 | DC113: 0 | DD113: 0 | DE113: 0 | DF113: 0 | DG113: 0 | DH113: 0 | DI113: 0 | DJ113: 0 | DK113: 0 | DL113: 0 | DM113: 0 | DN113: 0 | DO113: =DN113 -> 0 | DP113: 0 | DQ113: 0 | DR113: 0 | DS113: 0 | DT113: 0 | DU113: 0 | DV113: 0 | DW113: 0 | DX113: 0 | DY113: 0 | DZ113: 0 | EA113: 0 | EB113: =EA113 -> 0 | EC113: 0 | ED113: 0 | EE113: 0 | EF113: 0 | EG113: 0 | EH113: 0 | EI113: 0 | EJ113: 0 | EK113: 0 | EL113: 0 | EM113: 0 | EN113: 0 | EO113: =EN113 -> 0 | EP113: 0 | EQ113: 0 | ER113: 0 | ES113: 0 | ET113: 0 | EU113: 0 | EV113: 0 | EW113: 0 | EX113: 0 | EY113: 0 | EZ113: 0 | FA113: 0 | FB113: =FA113 -> 0 | FC113: 0 | FD113: 0 | FE113: 0 | FF113: 0 | FG113: 0 | FH113: 0 | FI113: 0 | FO113: =FI113 -> 0
...
