Workbook

Sheet Dashboard
B2: MINISTERIO DE VIVIENDA Y URBANISMO — DASHBOARD DE INVERSIÓN Y EJECUCIÓN PRESUPUESTARIA
B3: Visualizador Analítico Interactivo Tabla a Tabla | Subtítulos 33 (Subsidios/Capital), 31 (Inversión Directa), 29 (Activos) y Consolidado | Cifras en miles de pesos ($)
B4: AÑO SELECCIONADO: | C4: 2024 | D4: COBERTURA TEMPORAL: | F4: 2014 - 2026 (Ene - Dic) | H4: UNIDAD MONETARIA: | J4: Miles de $ Corrientes (DIPRES)
B6: PRESUPUESTO LEY (INICIAL) | D6: PRESUPUESTO VIGENTE | F6: EJECUCIÓN ACUMULADA | H6: % CUMPLIMIENTO PRESUPUESTARIO | J6: SALDO POR EJECUTAR
B7: =D17 -> 3320541734 | D7: =E17 -> 3332768183 | F7: =F17 -> 3312699040 | H7: =H17 -> 0.99397824 | J7: =G17 -> 20069143
B9: Aprobado Ley de Presupuesto | D9: Presupuesto anual actualizado | F9: Total devengado en el ejercicio | H9: Ejecución devengada / Presupuesto vigente | J9: Monto disponible no devengado
B11: TABLA 1: RESUMEN CONSOLIDADO POR SUBTÍTULO PRESUPUESTARIO
B13: Subtítulo Presupuestario | C13: Cód. | D13: Presupuesto Ley | E13: Presupuesto Vigente | F13: Ejecución Acumulada | G13: Saldo por Ejecutar | H13: % Ejecución | I13: % Participación
B14: Subtítulo 33 – Transferencias de Capital (Subsidios) | C14: 33 | D14: =INDEX(MINVU_Mes_Corriente!$1:$300, 164, 3 + ($C$4 - 2014)*13 + 12) -> 2729162964 | E14: =INDEX(MINVU_Mes_Corriente!$1:$300, 186, 3 + ($C$4 - 2014)*13 + 12) -> 2913408485 | F14: =INDEX(MINVU_Mes_Corriente!$1:$300, 208, 3 + ($C$4 - 2014)*13 + 12) -> 2904924599 | G14: =E14 - F14 -> 8483886 | H14: =IF(E14>0, F14/E14, 0) -> 0.99708799 | I14: =IF($E$17>0, E14/$E$17, 0) -> 0.87417076
B15: Subtítulo 31 – Iniciativas de Inversión | C15: 31 | D15: =INDEX(MINVU_Mes_Corriente!$1:$300, 26, 3 + ($C$4 - 2014)*13 + 12) -> 560704016 | E15: =INDEX(MINVU_Mes_Corriente!$1:$300, 48, 3 + ($C$4 - 2014)*13 + 12) -> 400142072 | F15: =INDEX(MINVU_Mes_Corriente!$1:$300, 70, 3 + ($C$4 - 2014)*13 + 12) -> 388712182 | G15: =E15 - F15 -> 11429890 | H15: =IF(E15>0, F15/E15, 0) -> 0.97143542 | I15: =IF($E$17>0, E15/$E$17, 0) -> 0.12006298
B16: Subtítulo 29 – Activos No Financieros | C16: 29 | D16: =INDEX(MINVU_Mes_Corriente!$1:$300, 95, 3 + ($C$4 - 2014)*13 + 12) -> 30674754 | E16: =INDEX(MINVU_Mes_Corriente!$1:$300, 117, 3 + ($C$4 - 2014)*13 + 12) -> 19217626 | F16: =INDEX(MINVU_Mes_Corriente!$1:$300, 139, 3 + ($C$4 - 2014)*13 + 12) -> 19062259 | G16: =E16 - F16 -> 155367 | H16: =IF(E16>0, F16/E16, 0) -> 0.99191539 | I16: =IF($E$17>0, E16/$E$17, 0) -> 0.0057662654
B17: TOTAL INVERSIÓN MINVU (33 + 31 + 29) | C17: TOTAL | D17: =SUM(D14:D16) -> 3320541734 | E17: =SUM(E14:E16) -> 3332768183 | F17: =SUM(F14:F16) -> 3312699040 | G17: =E17 - F17 -> 20069143 | H17: =IF(E17>0, F17/E17, 0) -> 0.99397824 | I17: =SUM(I14:I16) -> 1
B19: TABLA 2: DESGLOSE COMPLETO POR ENTIDAD / PROGRAMA / SERVIU (AÑO SELECCIONADO)
B21: Entidad / SERVIU Regional | C21: Subt. 33 Vigente | D21: Subt. 33 Ejecución | E21: Subt. 31 Vigente | F21: Subt. 31 Ejecución | G21: Subt. 29 Vigente | H21: Subt. 29 Ejecución | I21: Total Vigente | J21: Total Ejecución | K21: Saldo | L21: % Ejecución | M21: % Part. MINVU
B22: Subsecretaría y Programas Centrales | C22: =INDEX(MINVU_Mes_Corriente!$1:$300, 168, 3 + ($C$4 - 2014)*13 + 12) -> 253260952 | D22: =INDEX(MINVU_Mes_Corriente!$1:$300, 190, 3 + ($C$4 - 2014)*13 + 12) -> 249185192 | E22: =INDEX(MINVU_Mes_Corriente!$1:$300, 30, 3 + ($C$4 - 2014)*13 + 12) -> 1858597 | F22: =INDEX(MINVU_Mes_Corriente!$1:$300, 52, 3 + ($C$4 - 2014)*13 + 12) -> 1765056 | G22: =INDEX(MINVU_Mes_Corriente!$1:$300, 99, 3 + ($C$4 - 2014)*13 + 12) -> 3168714 | H22: =INDEX(MINVU_Mes_Corriente!$1:$300, 121, 3 + ($C$4 - 2014)*13 + 12) -> 3071041 | I22: =C22 + E22 + G22 -> 258288263 | J22: =D22 + F22 + H22 -> 254021289 | K22: =I22 - J22 -> 4266974 | L22: =IF(I22>0, J22/I22, 0) -> 0.9834798 | M22: =IF($I$40>0, I22/$I$40, 0) -> 0.077499619
B23: Parque Metropolitano (PARQUEMET) | C23: =INDEX(MINVU_Mes_Corriente!$1:$300, 169, 3 + ($C$4 - 2014)*13 + 12) -> 0 | D23: =INDEX(MINVU_Mes_Corriente!$1:$300, 191, 3 + ($C$4 - 2014)*13 + 12) -> 0 | E23: =INDEX(MINVU_Mes_Corriente!$1:$300, 31, 3 + ($C$4 - 2014)*13 + 12) -> 27933416 | F23: =INDEX(MINVU_Mes_Corriente!$1:$300, 53, 3 + ($C$4 - 2014)*13 + 12) -> 27847917 | G23: =INDEX(MINVU_Mes_Corriente!$1:$300, 100, 3 + ($C$4 - 2014)*13 + 12) -> 240920 | H23: =INDEX(MINVU_Mes_Corriente!$1:$300, 122, 3 + ($C$4 - 2014)*13 + 12) -> 240208 | I23: =C23 + E23 + G23 -> 28174336 | J23: =D23 + F23 + H23 -> 28088125 | K23: =I23 - J23 -> 86211 | L23: =IF(I23>0, J23/I23, 0) -> 0.99694009 | M23: =IF($I$40>0, I23/$I$40, 0) -> 0.0084537341
B24: SERVIU Arica y Parinacota | C24: =INDEX(MINVU_Mes_Corriente!$1:$300, 170, 3 + ($C$4 - 2014)*13 + 12) -> 83210671 | D24: =INDEX(MINVU_Mes_Corriente!$1:$300, 192, 3 + ($C$4 - 2014)*13 + 12) -> 83196155 | E24: =INDEX(MINVU_Mes_Corriente!$1:$300, 32, 3 + ($C$4 - 2014)*13 + 12) -> 4403210 | F24: =INDEX(MINVU_Mes_Corriente!$1:$300, 54, 3 + ($C$4 - 2014)*13 + 12) -> 4379123 | G24: =INDEX(MINVU_Mes_Corriente!$1:$300, 101, 3 + ($C$4 - 2014)*13 + 12) -> 7496 | H24: =INDEX(MINVU_Mes_Corriente!$1:$300, 123, 3 + ($C$4 - 2014)*13 + 12) -> 7431 | I24: =C24 + E24 + G24 -> 87621377 | J24: =D24 + F24 + H24 -> 87582709 | K24: =I24 - J24 -> 38668 | L24: =IF(I24>0, J24/I24, 0) -> 0.99955869 | M24: =IF($I$40>0, I24/$I$40, 0) -> 0.026290871
B25: SERVIU Tarapacá | C25: =INDEX(MINVU_Mes_Corriente!$1:$300, 171, 3 + ($C$4 - 2014)*13 + 12) -> 81745804 | D25: =INDEX(MINVU_Mes_Corriente!$1:$300, 193, 3 + ($C$4 - 2014)*13 + 12) -> 81667751 | E25: =INDEX(MINVU_Mes_Corriente!$1:$300, 33, 3 + ($C$4 - 2014)*13 + 12) -> 8998445 | F25: =INDEX(MINVU_Mes_Corriente!$1:$300, 55, 3 + ($C$4 - 2014)*13 + 12) -> 8453266 | G25: =INDEX(MINVU_Mes_Corriente!$1:$300, 102, 3 + ($C$4 - 2014)*13 + 12) -> 3479 | H25: =INDEX(MINVU_Mes_Corriente!$1:$300, 124, 3 + ($C$4 - 2014)*13 + 12) -> 3340 | I25: =C25 + E25 + G25 -> 90747728 | J25: =D25 + F25 + H25 -> 90124357 | K25: =I25 - J25 -> 623371 | L25: =IF(I25>0, J25/I25, 0) -> 0.99313073 | M25: =IF($I$40>0, I25/$I$40, 0) -> 0.027228935
B26: SERVIU Antofagasta | C26: =INDEX(MINVU_Mes_Corriente!$1:$300, 172, 3 + ($C$4 - 2014)*13 + 12) -> 73119497 | D26: =INDEX(MINVU_Mes_Corriente!$1:$300, 194, 3 + ($C$4 - 2014)*13 + 12) -> 73069447 | E26: =INDEX(MINVU_Mes_Corriente!$1:$300, 34, 3 + ($C$4 - 2014)*13 + 12) -> 15465604 | F26: =INDEX(MINVU_Mes_Corriente!$1:$300, 56, 3 + ($C$4 - 2014)*13 + 12) -> 14221677 | G26: =INDEX(MINVU_Mes_Corriente!$1:$300, 103, 3 + ($C$4 - 2014)*13 + 12) -> 6270 | H26: =INDEX(MINVU_Mes_Corriente!$1:$300, 125, 3 + ($C$4 - 2014)*13 + 12) -> 4665 | I26: =C26 + E26 + G26 -> 88591371 | J26: =D26 + F26 + H26 -> 87295789 | K26: =I26 - J26 -> 1295582 | L26: =IF(I26>0, J26/I26, 0) -> 0.98537575 | M26: =IF($I$40>0, I26/$I$40, 0) -> 0.026581918
B27: SERVIU Atacama | C27: =INDEX(MINVU_Mes_Corriente!$1:$300, 173, 3 + ($C$4 - 2014)*13 + 12) -> 50339570 | D27: =INDEX(MINVU_Mes_Corriente!$1:$300, 195, 3 + ($C$4 - 2014)*13 + 12) -> 50275024 | E27: =INDEX(MINVU_Mes_Corriente!$1:$300, 35, 3 + ($C$4 - 2014)*13 + 12) -> 8570431 | F27: =INDEX(MINVU_Mes_Corriente!$1:$300, 57, 3 + ($C$4 - 2014)*13 + 12) -> 8070989 | G27: =INDEX(MINVU_Mes_Corriente!$1:$300, 104, 3 + ($C$4 - 2014)*13 + 12) -> 6646 | H27: =INDEX(MINVU_Mes_Corriente!$1:$300, 126, 3 + ($C$4 - 2014)*13 + 12) -> 6646 | I27: =C27 + E27 + G27 -> 58916647 | J27: =D27 + F27 + H27 -> 58352659 | K27: =I27 - J27 -> 563988 | L27: =IF(I27>0, J27/I27, 0) -> 0.99042736 | M27: =IF($I$40>0, I27/$I$40, 0) -> 0.017677991
B28: SERVIU Coquimbo | C28: =INDEX(MINVU_Mes_Corriente!$1:$300, 174, 3 + ($C$4 - 2014)*13 + 12) -> 107360177 | D28: =INDEX(MINVU_Mes_Corriente!$1:$300, 196, 3 + ($C$4 - 2014)*13 + 12) -> 106974951 | E28: =INDEX(MINVU_Mes_Corriente!$1:$300, 36, 3 + ($C$4 - 2014)*13 + 12) -> 18466482 | F28: =INDEX(MINVU_Mes_Corriente!$1:$300, 58, 3 + ($C$4 - 2014)*13 + 12) -> 18304746 | G28: =INDEX(MINVU_Mes_Corriente!$1:$300, 105, 3 + ($C$4 - 2014)*13 + 12) -> 6092813 | H28: =INDEX(MINVU_Mes_Corriente!$1:$300, 127, 3 + ($C$4 - 2014)*13 + 12) -> 6065343 | I28: =C28 + E28 + G28 -> 131919472 | J28: =D28 + F28 + H28 -> 131345040 | K28: =I28 - J28 -> 574432 | L28: =IF(I28>0, J28/I28, 0) -> 0.99564559 | M28: =IF($I$40>0, I28/$I$40, 0) -> 0.039582553
B29: SERVIU Valparaíso | C29: =INDEX(MINVU_Mes_Corriente!$1:$300, 175, 3 + ($C$4 - 2014)*13 + 12) -> 226125474 | D29: =INDEX(MINVU_Mes_Corriente!$1:$300, 197, 3 + ($C$4 - 2014)*13 + 12) -> 225998740 | E29: =INDEX(MINVU_Mes_Corriente!$1:$300, 37, 3 + ($C$4 - 2014)*13 + 12) -> 37750186 | F29: =INDEX(MINVU_Mes_Corriente!$1:$300, 59, 3 + ($C$4 - 2014)*13 + 12) -> 35664606 | G29: =INDEX(MINVU_Mes_Corriente!$1:$300, 106, 3 + ($C$4 - 2014)*13 + 12) -> 21887 | H29: =INDEX(MINVU_Mes_Corriente!$1:$300, 128, 3 + ($C$4 - 2014)*13 + 12) -> 21833 | I29: =C29 + E29 + G29 -> 263897547 | J29: =D29 + F29 + H29 -> 261685179 | K29: =I29 - J29 -> 2212368 | L29: =IF(I29>0, J29/I29, 0) -> 0.99161656 | M29: =IF($I$40>0, I29/$I$40, 0) -> 0.079182689
B30: SERVIU Metropolitano | C30: =INDEX(MINVU_Mes_Corriente!$1:$300, 176, 3 + ($C$4 - 2014)*13 + 12) -> 536507887 | D30: =INDEX(MINVU_Mes_Corriente!$1:$300, 198, 3 + ($C$4 - 2014)*13 + 12) -> 535781681 | E30: =INDEX(MINVU_Mes_Corriente!$1:$300, 38, 3 + ($C$4 - 2014)*13 + 12) -> 86087430 | F30: =INDEX(MINVU_Mes_Corriente!$1:$300, 60, 3 + ($C$4 - 2014)*13 + 12) -> 84329419 | G30: =INDEX(MINVU_Mes_Corriente!$1:$300, 107, 3 + ($C$4 - 2014)*13 + 12) -> 44560 | H30: =INDEX(MINVU_Mes_Corriente!$1:$300, 129, 3 + ($C$4 - 2014)*13 + 12) -> 44534 | I30: =C30 + E30 + G30 -> 622639877 | J30: =D30 + F30 + H30 -> 620155634 | K30: =I30 - J30 -> 2484243 | L30: =IF(I30>0, J30/I30, 0) -> 0.99601014 | M30: =IF($I$40>0, I30/$I$40, 0) -> 0.18682364
B31: SERVIU O'Higgins | C31: =INDEX(MINVU_Mes_Corriente!$1:$300, 177, 3 + ($C$4 - 2014)*13 + 12) -> 172944682 | D31: =INDEX(MINVU_Mes_Corriente!$1:$300, 199, 3 + ($C$4 - 2014)*13 + 12) -> 172843913 | E31: =INDEX(MINVU_Mes_Corriente!$1:$300, 39, 3 + ($C$4 - 2014)*13 + 12) -> 5515173 | F31: =INDEX(MINVU_Mes_Corriente!$1:$300, 61, 3 + ($C$4 - 2014)*13 + 12) -> 5186229 | G31: =INDEX(MINVU_Mes_Corriente!$1:$300, 108, 3 + ($C$4 - 2014)*13 + 12) -> 300457 | H31: =INDEX(MINVU_Mes_Corriente!$1:$300, 130, 3 + ($C$4 - 2014)*13 + 12) -> 300441 | I31: =C31 + E31 + G31 -> 178760312 | J31: =D31 + F31 + H31 -> 178330583 | K31: =I31 - J31 -> 429729 | L31: =IF(I31>0, J31/I31, 0) -> 0.99759606 | M31: =IF($I$40>0, I31/$I$40, 0) -> 0.053637188
B32: SERVIU Maule | C32: =INDEX(MINVU_Mes_Corriente!$1:$300, 178, 3 + ($C$4 - 2014)*13 + 12) -> 213444748 | D32: =INDEX(MINVU_Mes_Corriente!$1:$300, 200, 3 + ($C$4 - 2014)*13 + 12) -> 213325058 | E32: =INDEX(MINVU_Mes_Corriente!$1:$300, 40, 3 + ($C$4 - 2014)*13 + 12) -> 20053849 | F32: =INDEX(MINVU_Mes_Corriente!$1:$300, 62, 3 + ($C$4 - 2014)*13 + 12) -> 19302172 | G32: =INDEX(MINVU_Mes_Corriente!$1:$300, 109, 3 + ($C$4 - 2014)*13 + 12) -> 6865 | H32: =INDEX(MINVU_Mes_Corriente!$1:$300, 131, 3 + ($C$4 - 2014)*13 + 12) -> 6833 | I32: =C32 + E32 + G32 -> 233505462 | J32: =D32 + F32 + H32 -> 232634063 | K32: =I32 - J32 -> 871399 | L32: =IF(I32>0, J32/I32, 0) -> 0.99626819 | M32: =IF($I$40>0, I32/$I$40, 0) -> 0.070063518
B33: SERVIU Ñuble | C33: =INDEX(MINVU_Mes_Corriente!$1:$300, 179, 3 + ($C$4 - 2014)*13 + 12) -> 154702362 | D33: =INDEX(MINVU_Mes_Corriente!$1:$300, 201, 3 + ($C$4 - 2014)*13 + 12) -> 154664738 | E33: =INDEX(MINVU_Mes_Corriente!$1:$300, 41, 3 + ($C$4 - 2014)*13 + 12) -> 19120001 | F33: =INDEX(MINVU_Mes_Corriente!$1:$300, 63, 3 + ($C$4 - 2014)*13 + 12) -> 17950052 | G33: =INDEX(MINVU_Mes_Corriente!$1:$300, 110, 3 + ($C$4 - 2014)*13 + 12) -> 6270 | H33: =INDEX(MINVU_Mes_Corriente!$1:$300, 132, 3 + ($C$4 - 2014)*13 + 12) -> 6042 | I33: =C33 + E33 + G33 -> 173828633 | J33: =D33 + F33 + H33 -> 172620832 | K33: =I33 - J33 -> 1207801 | L33: =IF(I33>0, J33/I33, 0) -> 0.99305177 | M33: =IF($I$40>0, I33/$I$40, 0) -> 0.052157433
B34: SERVIU Biobío | C34: =INDEX(MINVU_Mes_Corriente!$1:$300, 180, 3 + ($C$4 - 2014)*13 + 12) -> 303934966 | D34: =INDEX(MINVU_Mes_Corriente!$1:$300, 202, 3 + ($C$4 - 2014)*13 + 12) -> 303859023 | E34: =INDEX(MINVU_Mes_Corriente!$1:$300, 42, 3 + ($C$4 - 2014)*13 + 12) -> 52850218 | F34: =INDEX(MINVU_Mes_Corriente!$1:$300, 64, 3 + ($C$4 - 2014)*13 + 12) -> 52001305 | G34: =INDEX(MINVU_Mes_Corriente!$1:$300, 111, 3 + ($C$4 - 2014)*13 + 12) -> 12960 | H34: =INDEX(MINVU_Mes_Corriente!$1:$300, 133, 3 + ($C$4 - 2014)*13 + 12) -> 12190 | I34: =C34 + E34 + G34 -> 356798144 | J34: =D34 + F34 + H34 -> 355872518 | K34: =I34 - J34 -> 925626 | L34: =IF(I34>0, J34/I34, 0) -> 0.99740574 | M34: =IF($I$40>0, I34/$I$40, 0) -> 0.10705759
B35: SERVIU La Araucanía | C35: =INDEX(MINVU_Mes_Corriente!$1:$300, 181, 3 + ($C$4 - 2014)*13 + 12) -> 266347073 | D35: =INDEX(MINVU_Mes_Corriente!$1:$300, 203, 3 + ($C$4 - 2014)*13 + 12) -> 265754901 | E35: =INDEX(MINVU_Mes_Corriente!$1:$300, 43, 3 + ($C$4 - 2014)*13 + 12) -> 36728957 | F35: =INDEX(MINVU_Mes_Corriente!$1:$300, 65, 3 + ($C$4 - 2014)*13 + 12) -> 36426224 | G35: =INDEX(MINVU_Mes_Corriente!$1:$300, 112, 3 + ($C$4 - 2014)*13 + 12) -> 12161 | H35: =INDEX(MINVU_Mes_Corriente!$1:$300, 134, 3 + ($C$4 - 2014)*13 + 12) -> 12134 | I35: =C35 + E35 + G35 -> 303088191 | J35: =D35 + F35 + H35 -> 302193259 | K35: =I35 - J35 -> 894932 | L35: =IF(I35>0, J35/I35, 0) -> 0.99704729 | M35: =IF($I$40>0, I35/$I$40, 0) -> 0.090941876
B36: SERVIU Los Ríos | C36: =INDEX(MINVU_Mes_Corriente!$1:$300, 182, 3 + ($C$4 - 2014)*13 + 12) -> 73852164 | D36: =INDEX(MINVU_Mes_Corriente!$1:$300, 204, 3 + ($C$4 - 2014)*13 + 12) -> 72195760 | E36: =INDEX(MINVU_Mes_Corriente!$1:$300, 44, 3 + ($C$4 - 2014)*13 + 12) -> 13330524 | F36: =INDEX(MINVU_Mes_Corriente!$1:$300, 66, 3 + ($C$4 - 2014)*13 + 12) -> 12655537 | G36: =INDEX(MINVU_Mes_Corriente!$1:$300, 113, 3 + ($C$4 - 2014)*13 + 12) -> 9216 | H36: =INDEX(MINVU_Mes_Corriente!$1:$300, 135, 3 + ($C$4 - 2014)*13 + 12) -> 9209 | I36: =C36 + E36 + G36 -> 87191904 | J36: =D36 + F36 + H36 -> 84860506 | K36: =I36 - J36 -> 2331398 | L36: =IF(I36>0, J36/I36, 0) -> 0.9732613 | M36: =IF($I$40>0, I36/$I$40, 0) -> 0.026162007
B37: SERVIU Los Lagos | C37: =INDEX(MINVU_Mes_Corriente!$1:$300, 183, 3 + ($C$4 - 2014)*13 + 12) -> 209110935 | D37: =INDEX(MINVU_Mes_Corriente!$1:$300, 205, 3 + ($C$4 - 2014)*13 + 12) -> 209043392 | E37: =INDEX(MINVU_Mes_Corriente!$1:$300, 45, 3 + ($C$4 - 2014)*13 + 12) -> 17300120 | F37: =INDEX(MINVU_Mes_Corriente!$1:$300, 67, 3 + ($C$4 - 2014)*13 + 12) -> 16578842 | G37: =INDEX(MINVU_Mes_Corriente!$1:$300, 114, 3 + ($C$4 - 2014)*13 + 12) -> 9262299 | H37: =INDEX(MINVU_Mes_Corriente!$1:$300, 136, 3 + ($C$4 - 2014)*13 + 12) -> 9235856 | I37: =C37 + E37 + G37 -> 235673354 | J37: =D37 + F37 + H37 -> 234858090 | K37: =I37 - J37 -> 815264 | L37: =IF(I37>0, J37/I37, 0) -> 0.9965407 | M37: =IF($I$40>0, I37/$I$40, 0) -> 0.070713995
B38: SERVIU Aysén | C38: =INDEX(MINVU_Mes_Corriente!$1:$300, 184, 3 + ($C$4 - 2014)*13 + 12) -> 40911462 | D38: =INDEX(MINVU_Mes_Corriente!$1:$300, 206, 3 + ($C$4 - 2014)*13 + 12) -> 40629172 | E38: =INDEX(MINVU_Mes_Corriente!$1:$300, 46, 3 + ($C$4 - 2014)*13 + 12) -> 7723948 | F38: =INDEX(MINVU_Mes_Corriente!$1:$300, 68, 3 + ($C$4 - 2014)*13 + 12) -> 7636879 | G38: =INDEX(MINVU_Mes_Corriente!$1:$300, 115, 3 + ($C$4 - 2014)*13 + 12) -> 6270 | H38: =INDEX(MINVU_Mes_Corriente!$1:$300, 137, 3 + ($C$4 - 2014)*13 + 12) -> 6224 | I38: =C38 + E38 + G38 -> 48641680 | J38: =D38 + F38 + H38 -> 48272275 | K38: =I38 - J38 -> 369405 | L38: =IF(I38>0, J38/I38, 0) -> 0.99240559 | M38: =IF($I$40>0, I38/$I$40, 0) -> 0.014594979
B39: SERVIU Magallanes | C39: =INDEX(MINVU_Mes_Corriente!$1:$300, 185, 3 + ($C$4 - 2014)*13 + 12) -> 66490061 | D39: =INDEX(MINVU_Mes_Corriente!$1:$300, 207, 3 + ($C$4 - 2014)*13 + 12) -> 66459701 | E39: =INDEX(MINVU_Mes_Corriente!$1:$300, 47, 3 + ($C$4 - 2014)*13 + 12) -> 17985481 | F39: =INDEX(MINVU_Mes_Corriente!$1:$300, 69, 3 + ($C$4 - 2014)*13 + 12) -> 17938143 | G39: =INDEX(MINVU_Mes_Corriente!$1:$300, 116, 3 + ($C$4 - 2014)*13 + 12) -> 8343 | H39: =INDEX(MINVU_Mes_Corriente!$1:$300, 138, 3 + ($C$4 - 2014)*13 + 12) -> 8289 | I39: =C39 + E39 + G39 -> 84483885 | J39: =D39 + F39 + H39 -> 84406133 | K39: =I39 - J39 -> 77752 | L39: =IF(I39>0, J39/I39, 0) -> 0.99907968 | M39: =IF($I$40>0, I39/$I$40, 0) -> 0.025349463
B40: TOTAL MINVU | C40: =SUM(C22:C39) -> 2913408485 | D40: =SUM(D22:D39) -> 2904924599 | E40: =SUM(E22:E39) -> 400142072 | F40: =SUM(F22:F39) -> 388712182 | G40: =SUM(G22:G39) -> 19217626 | H40: =SUM(H22:H39) -> 19062259 | I40: =SUM(I22:I39) -> 3332768183 | J40: =SUM(J22:J39) -> 3312699040 | K40: =SUM(K22:K39) -> 20069143 | L40: =IF(I40>0, J40/I40, 0) -> 0.99397824 | M40: =SUM(M22:M39) -> 1
B42: TABLA 3: EVOLUCIÓN MENSUAL DEL AÑO SELECCIONADO (ENERO A DICIEMBRE)
B44: Concepto / Mes | C44: Ene | D44: Feb | E44: Mar | F44: Abr | G44: May | H44: Jun | I44: Jul | J44: Ago | K44: Sep | L44: Oct | M44: Nov | N44: Dic | O44: Cierre Total
B45: Presupuesto Ley | C45: =INDEX(MINVU_Mes_Corriente!$1:$300, 164, 3 + ($C$4 - 2014)*13 + 0) + INDEX(MINVU_Mes_Corriente!$1:$300, 26, 3 + ($C$4 - 2014)*13 + 0) + INDEX(MINVU_Mes_Corriente!$1:$300, 95, 3 + ($C$4 - 2014)*13 + 0) -> 3320541734 | D45: =INDEX(MINVU_Mes_Corriente!$1:$300, 164, 3 + ($C$4 - 2014)*13 + 1) + INDEX(MINVU_Mes_Corriente!$1:$300, 26, 3 + ($C$4 - 2014)*13 + 1) + INDEX(MINVU_Mes_Corriente!$1:$300, 95, 3 + ($C$4 - 2014)*13 + 1) -> 3320541734 | E45: =INDEX(MINVU_Mes_Corriente!$1:$300, 164, 3 + ($C$4 - 2014)*13 + 2) + INDEX(MINVU_Mes_Corriente!$1:$300, 26, 3 + ($C$4 - 2014)*13 + 2) + INDEX(MINVU_Mes_Corriente!$1:$300, 95, 3 + ($C$4 - 2014)*13 + 2) -> 3320541734 | F45: =INDEX(MINVU_Mes_Corriente!$1:$300, 164, 3 + ($C$4 - 2014)*13 + 3) + INDEX(MINVU_Mes_Corriente!$1:$300, 26, 3 + ($C$4 - 2014)*13 + 3) + INDEX(MINVU_Mes_Corriente!$1:$300, 95, 3 + ($C$4 - 2014)*13 + 3) -> 3320541734 | G45: =INDEX(MINVU_Mes_Corriente!$1:$300, 164, 3 + ($C$4 - 2014)*13 + 4) + INDEX(MINVU_Mes_Corriente!$1:$300, 26, 3 + ($C$4 - 2014)*13 + 4) + INDEX(MINVU_Mes_Corriente!$1:$300, 95, 3 + ($C$4 - 2014)*13 + 4) -> 3320541734 | H45: =INDEX(MINVU_Mes_Corriente!$1:$300, 164, 3 + ($C$4 - 2014)*13 + 5) + INDEX(MINVU_Mes_Corriente!$1:$300, 26, 3 + ($C$4 - 2014)*13 + 5) + INDEX(MINVU_Mes_Corriente!$1:$300, 95, 3 + ($C$4 - 2014)*13 + 5) -> 3320541734 | I45: =INDEX(MINVU_Mes_Corriente!$1:$300, 164, 3 + ($C$4 - 2014)*13 + 6) + INDEX(MINVU_Mes_Corriente!$1:$300, 26, 3 + ($C$4 - 2014)*13 + 6) + INDEX(MINVU_Mes_Corriente!$1:$300, 95, 3 + ($C$4 - 2014)*13 + 6) -> 3320541734 | J45: =INDEX(MINVU_Mes_Corriente!$1:$300, 164, 3 + ($C$4 - 2014)*13 + 7) + INDEX(MINVU_Mes_Corriente!$1:$300, 26, 3 + ($C$4 - 2014)*13 + 7) + INDEX(MINVU_Mes_Corriente!$1:$300, 95, 3 + ($C$4 - 2014)*13 + 7) -> 3320541734 | K45: =INDEX(MINVU_Mes_Corriente!$1:$300, 164, 3 + ($C$4 - 2014)*13 + 8) + INDEX(MINVU_Mes_Corriente!$1:$300, 26, 3 + ($C$4 - 2014)*13 + 8) + INDEX(MINVU_Mes_Corriente!$1:$300, 95, 3 + ($C$4 - 2014)*13 + 8) -> 3320541734 | L45: =INDEX(MINVU_Mes_Corriente!$1:$300, 164, 3 + ($C$4 - 2014)*13 + 9) + INDEX(MINVU_Mes_Corriente!$1:$300, 26, 3 + ($C$4 - 2014)*13 + 9) + INDEX(MINVU_Mes_Corriente!$1:$300, 95, 3 + ($C$4 - 2014)*13 + 9) -> 3320541734 | M45: =INDEX(MINVU_Mes_Corriente!$1:$300, 164, 3 + ($C$4 - 2014)*13 + 10) + INDEX(MINVU_Mes_Corriente!$1:$300, 26, 3 + ($C$4 - 2014)*13 + 10) + INDEX(MINVU_Mes_Corriente!$1:$300, 95, 3 + ($C$4 - 2014)*13 + 10) -> 3320541734 | N45: =INDEX(MINVU_Mes_Corriente!$1:$300, 164, 3 + ($C$4 - 2014)*13 + 11) + INDEX(MINVU_Mes_Corriente!$1:$300, 26, 3 + ($C$4 - 2014)*13 + 11) + INDEX(MINVU_Mes_Corriente!$1:$300, 95, 3 + ($C$4 - 2014)*13 + 11) -> 3320541734 | O45: =INDEX(MINVU_Mes_Corriente!$1:$300, 164, 3 + ($C$4 - 2014)*13 + 12) + INDEX(MINVU_Mes_Corriente!$1:$300, 26, 3 + ($C$4 - 2014)*13 + 12) + INDEX(MINVU_Mes_Corriente!$1:$300, 95, 3 + ($C$4 - 2014)*13 + 12) -> 3320541734
B46: Presupuesto Vigente | C46: =INDEX(MINVU_Mes_Corriente!$1:$300, 186, 3 + ($C$4 - 2014)*13 + 0) + INDEX(MINVU_Mes_Corriente!$1:$300, 48, 3 + ($C$4 - 2014)*13 + 0) + INDEX(MINVU_Mes_Corriente!$1:$300, 117, 3 + ($C$4 - 2014)*13 + 0) -> 3320541734 | D46: =INDEX(MINVU_Mes_Corriente!$1:$300, 186, 3 + ($C$4 - 2014)*13 + 1) + INDEX(MINVU_Mes_Corriente!$1:$300, 48, 3 + ($C$4 - 2014)*13 + 1) + INDEX(MINVU_Mes_Corriente!$1:$300, 117, 3 + ($C$4 - 2014)*13 + 1) -> 3320541734 | E46: =INDEX(MINVU_Mes_Corriente!$1:$300, 186, 3 + ($C$4 - 2014)*13 + 2) + INDEX(MINVU_Mes_Corriente!$1:$300, 48, 3 + ($C$4 - 2014)*13 + 2) + INDEX(MINVU_Mes_Corriente!$1:$300, 117, 3 + ($C$4 - 2014)*13 + 2) -> 3320541734 | F46: =INDEX(MINVU_Mes_Corriente!$1:$300, 186, 3 + ($C$4 - 2014)*13 + 3) + INDEX(MINVU_Mes_Corriente!$1:$300, 48, 3 + ($C$4 - 2014)*13 + 3) + INDEX(MINVU_Mes_Corriente!$1:$300, 117, 3 + ($C$4 - 2014)*13 + 3) -> 3320541734 | G46: =INDEX(MINVU_Mes_Corriente!$1:$300, 186, 3 + ($C$4 - 2014)*13 + 4) + INDEX(MINVU_Mes_Corriente!$1:$300, 48, 3 + ($C$4 - 2014)*13 + 4) + INDEX(MINVU_Mes_Corriente!$1:$300, 117, 3 + ($C$4 - 2014)*13 + 4) -> 3320643534 | H46: =INDEX(MINVU_Mes_Corriente!$1:$300, 186, 3 + ($C$4 - 2014)*13 + 5) + INDEX(MINVU_Mes_Corriente!$1:$300, 48, 3 + ($C$4 - 2014)*13 + 5) + INDEX(MINVU_Mes_Corriente!$1:$300, 117, 3 + ($C$4 - 2014)*13 + 5) -> 3320643534 | I46: =INDEX(MINVU_Mes_Corriente!$1:$300, 186, 3 + ($C$4 - 2014)*13 + 6) + INDEX(MINVU_Mes_Corriente!$1:$300, 48, 3 + ($C$4 - 2014)*13 + 6) + INDEX(MINVU_Mes_Corriente!$1:$300, 117, 3 + ($C$4 - 2014)*13 + 6) -> 3329424159 | J46: =INDEX(MINVU_Mes_Corriente!$1:$300, 186, 3 + ($C$4 - 2014)*13 + 7) + INDEX(MINVU_Mes_Corriente!$1:$300, 48, 3 + ($C$4 - 2014)*13 + 7) + INDEX(MINVU_Mes_Corriente!$1:$300, 117, 3 + ($C$4 - 2014)*13 + 7) -> 3376717372 | K46: =INDEX(MINVU_Mes_Corriente!$1:$300, 186, 3 + ($C$4 - 2014)*13 + 8) + INDEX(MINVU_Mes_Corriente!$1:$300, 48, 3 + ($C$4 - 2014)*13 + 8) + INDEX(MINVU_Mes_Corriente!$1:$300, 117, 3 + ($C$4 - 2014)*13 + 8) -> 3421717372 | L46: =INDEX(MINVU_Mes_Corriente!$1:$300, 186, 3 + ($C$4 - 2014)*13 + 9) + INDEX(MINVU_Mes_Corriente!$1:$300, 48, 3 + ($C$4 - 2014)*13 + 9) + INDEX(MINVU_Mes_Corriente!$1:$300, 117, 3 + ($C$4 - 2014)*13 + 9) -> 3491232791 | M46: =INDEX(MINVU_Mes_Corriente!$1:$300, 186, 3 + ($C$4 - 2014)*13 + 10) + INDEX(MINVU_Mes_Corriente!$1:$300, 48, 3 + ($C$4 - 2014)*13 + 10) + INDEX(MINVU_Mes_Corriente!$1:$300, 117, 3 + ($C$4 - 2014)*13 + 10) -> 3488688633 | N46: =INDEX(MINVU_Mes_Corriente!$1:$300, 186, 3 + ($C$4 - 2014)*13 + 11) + INDEX(MINVU_Mes_Corriente!$1:$300, 48, 3 + ($C$4 - 2014)*13 + 11) + INDEX(MINVU_Mes_Corriente!$1:$300, 117, 3 + ($C$4 - 2014)*13 + 11) -> 3332768183 | O46: =INDEX(MINVU_Mes_Corriente!$1:$300, 186, 3 + ($C$4 - 2014)*13 + 12) + INDEX(MINVU_Mes_Corriente!$1:$300, 48, 3 + ($C$4 - 2014)*13 + 12) + INDEX(MINVU_Mes_Corriente!$1:$300, 117, 3 + ($C$4 - 2014)*13 + 12) -> 3332768183
B47: Ejecución Acumulada | C47: =INDEX(MINVU_Mes_Corriente!$1:$300, 208, 3 + ($C$4 - 2014)*13 + 0) + INDEX(MINVU_Mes_Corriente!$1:$300, 70, 3 + ($C$4 - 2014)*13 + 0) + INDEX(MINVU_Mes_Corriente!$1:$300, 139, 3 + ($C$4 - 2014)*13 + 0) -> 144905537 | D47: =INDEX(MINVU_Mes_Corriente!$1:$300, 208, 3 + ($C$4 - 2014)*13 + 1) + INDEX(MINVU_Mes_Corriente!$1:$300, 70, 3 + ($C$4 - 2014)*13 + 1) + INDEX(MINVU_Mes_Corriente!$1:$300, 139, 3 + ($C$4 - 2014)*13 + 1) -> 392112901 | E47: =INDEX(MINVU_Mes_Corriente!$1:$300, 208, 3 + ($C$4 - 2014)*13 + 2) + INDEX(MINVU_Mes_Corriente!$1:$300, 70, 3 + ($C$4 - 2014)*13 + 2) + INDEX(MINVU_Mes_Corriente!$1:$300, 139, 3 + ($C$4 - 2014)*13 + 2) -> 734004289 | F47: =INDEX(MINVU_Mes_Corriente!$1:$300, 208, 3 + ($C$4 - 2014)*13 + 3) + INDEX(MINVU_Mes_Corriente!$1:$300, 70, 3 + ($C$4 - 2014)*13 + 3) + INDEX(MINVU_Mes_Corriente!$1:$300, 139, 3 + ($C$4 - 2014)*13 + 3) -> 1004471755 | G47: =INDEX(MINVU_Mes_Corriente!$1:$300, 208, 3 + ($C$4 - 2014)*13 + 4) + INDEX(MINVU_Mes_Corriente!$1:$300, 70, 3 + ($C$4 - 2014)*13 + 4) + INDEX(MINVU_Mes_Corriente!$1:$300, 139, 3 + ($C$4 - 2014)*13 + 4) -> 1303821878 | H47: =INDEX(MINVU_Mes_Corriente!$1:$300, 208, 3 + ($C$4 - 2014)*13 + 5) + INDEX(MINVU_Mes_Corriente!$1:$300, 70, 3 + ($C$4 - 2014)*13 + 5) + INDEX(MINVU_Mes_Corriente!$1:$300, 139, 3 + ($C$4 - 2014)*13 + 5) -> 1551877586 | I47: =INDEX(MINVU_Mes_Corriente!$1:$300, 208, 3 + ($C$4 - 2014)*13 + 6) + INDEX(MINVU_Mes_Corriente!$1:$300, 70, 3 + ($C$4 - 2014)*13 + 6) + INDEX(MINVU_Mes_Corriente!$1:$300, 139, 3 + ($C$4 - 2014)*13 + 6) -> 1800513314 | J47: =INDEX(MINVU_Mes_Corriente!$1:$300, 208, 3 + ($C$4 - 2014)*13 + 7) + INDEX(MINVU_Mes_Corriente!$1:$300, 70, 3 + ($C$4 - 2014)*13 + 7) + INDEX(MINVU_Mes_Corriente!$1:$300, 139, 3 + ($C$4 - 2014)*13 + 7) -> 2056646958 | K47: =INDEX(MINVU_Mes_Corriente!$1:$300, 208, 3 + ($C$4 - 2014)*13 + 8) + INDEX(MINVU_Mes_Corriente!$1:$300, 70, 3 + ($C$4 - 2014)*13 + 8) + INDEX(MINVU_Mes_Corriente!$1:$300, 139, 3 + ($C$4 - 2014)*13 + 8) -> 2287303377 | L47: =INDEX(MINVU_Mes_Corriente!$1:$300, 208, 3 + ($C$4 - 2014)*13 + 9) + INDEX(MINVU_Mes_Corriente!$1:$300, 70, 3 + ($C$4 - 2014)*13 + 9) + INDEX(MINVU_Mes_Corriente!$1:$300, 139, 3 + ($C$4 - 2014)*13 + 9) -> 2541084845 | M47: =INDEX(MINVU_Mes_Corriente!$1:$300, 208, 3 + ($C$4 - 2014)*13 + 10) + INDEX(MINVU_Mes_Corriente!$1:$300, 70, 3 + ($C$4 - 2014)*13 + 10) + INDEX(MINVU_Mes_Corriente!$1:$300, 139, 3 + ($C$4 - 2014)*13 + 10) -> 2810519043 | N47: =INDEX(MINVU_Mes_Corriente!$1:$300, 208, 3 + ($C$4 - 2014)*13 + 11) + INDEX(MINVU_Mes_Corriente!$1:$300, 70, 3 + ($C$4 - 2014)*13 + 11) + INDEX(MINVU_Mes_Corriente!$1:$300, 139, 3 + ($C$4 - 2014)*13 + 11) -> 3312699040 | O47: =INDEX(MINVU_Mes_Corriente!$1:$300, 208, 3 + ($C$4 - 2014)*13 + 12) + INDEX(MINVU_Mes_Corriente!$1:$300, 70, 3 + ($C$4 - 2014)*13 + 12) + INDEX(MINVU_Mes_Corriente!$1:$300, 139, 3 + ($C$4 - 2014)*13 + 12) -> 3312699040
B48: % Avance Ejecución | C48: =IF(C46>0, C47/C46, 0) -> 0.043639125 | D48: =IF(D46>0, D47/D46, 0) -> 0.11808703 | E48: =IF(E46>0, E47/E46, 0) -> 0.22104956 | F48: =IF(F46>0, F47/F46, 0) -> 0.30250237 | G48: =IF(G46>0, G47/G46, 0) -> 0.39264133 | H48: =IF(H46>0, H47/H46, 0) -> 0.46734242 | I48: =IF(I46>0, I47/I46, 0) -> 0.5407882 | J48: =IF(J46>0, J47/J46, 0) -> 0.60906695 | ... O48: =IF(O46>0, O47/O46, 0) -> 0.99397824
B50: TABLA 4: COMPARATIVA HISTÓRICA MULTIANUAL (2014 - 2026)
B52: Año | C52: Presupuesto Ley | D52: Presupuesto Vigente | E52: Ejecución Acumulada | F52: Saldo por Ejecutar | G52: % Ejecución | H52: Crec. Vigente (YoY) | I52: Crec. Ejecución (YoY)
B53: 2014 | C53: =MINVU_Mes_Corriente!O164 + MINVU_Mes_Corriente!O26 + MINVU_Mes_Corriente!O95 -> 1280389722 | D53: =MINVU_Mes_Corriente!O186 + MINVU_Mes_Corriente!O48 + MINVU_Mes_Corriente!O117 -> 1468688961 | E53: =MINVU_Mes_Corriente!O208 + MINVU_Mes_Corriente!O70 + MINVU_Mes_Corriente!O139 -> 1460922722 | F53: =D53 - E53 -> 7766239 | G53: =IF(D53>0, E53/D53, 0) -> 0.99471213 | H53: - | I53: -
B54: 2015 | C54: =MINVU_Mes_Corriente!AB164 + MINVU_Mes_Corriente!AB26 + MINVU_Mes_Corriente!AB95 -> 1563189422 | D54: =MINVU_Mes_Corriente!AB186 + MINVU_Mes_Corriente!AB48 + MINVU_Mes_Corriente!AB117 -> 1585977798 | E54: =MINVU_Mes_Corriente!AB208 + MINVU_Mes_Corriente!AB70 + MINVU_Mes_Corriente!AB139 -> 1578590760 | F54: =D54 - E54 -> 7387038 | G54: =IF(D54>0, E54/D54, 0) -> 0.99534228 | H54: =IF(D53>0, (D54-D53)/D53, 0) -> 0.079859548 | I54: =IF(E53>0, (E54-E53)/E53, 0) -> 0.080543643
B55: 2016 | C55: =MINVU_Mes_Corriente!AO164 + MINVU_Mes_Corriente!AO26 + MINVU_Mes_Corriente!AO95 -> 1713772055 | D55: =MINVU_Mes_Corriente!AO186 + MINVU_Mes_Corriente!AO48 + MINVU_Mes_Corriente!AO117 -> 1727475521 | E55: =MINVU_Mes_Corriente!AO208 + MINVU_Mes_Corriente!AO70 + MINVU_Mes_Corriente!AO139 -> 1719476578 | F55: =D55 - E55 -> 7998943 | G55: =IF(D55>0, E55/D55, 0) -> 0.99536958 | H55: =IF(D54>0, (D55-D54)/D54, 0) -> 0.089217972 | I55: =IF(E54>0, (E55-E54)/E54, 0) -> 0.089247842
B56: 2017 | C56: =MINVU_Mes_Corriente!BB164 + MINVU_Mes_Corriente!BB26 + MINVU_Mes_Corriente!BB95 -> 1738839198 | D56: =MINVU_Mes_Corriente!BB186 + MINVU_Mes_Corriente!BB48 + MINVU_Mes_Corriente!BB117 -> 1758673597 | E56: =MINVU_Mes_Corriente!BB208 + MINVU_Mes_Corriente!BB70 + MINVU_Mes_Corriente!BB139 -> 1750915720 | F56: =D56 - E56 -> 7757877 | G56: =IF(D56>0, E56/D56, 0) -> 0.99558879 | H56: =IF(D55>0, (D56-D55)/D55, 0) -> 0.018059924 | I56: =IF(E55>0, (E56-E55)/E55, 0) -> 0.018284135
B57: 2018 | C57: =MINVU_Mes_Corriente!BO164 + MINVU_Mes_Corriente!BO26 + MINVU_Mes_Corriente!BO95 -> 1745380579 | D57: =MINVU_Mes_Corriente!BO186 + MINVU_Mes_Corriente!BO48 + MINVU_Mes_Corriente!BO117 -> 1702433466 | E57: =MINVU_Mes_Corriente!BO208 + MINVU_Mes_Corriente!BO70 + MINVU_Mes_Corriente!BO139 -> 1695561038 | F57: =D57 - E57 -> 6872428 | G57: =IF(D57>0, E57/D57, 0) -> 0.99596317 | H57: =IF(D56>0, (D57-D56)/D56, 0) -> -0.03197872 | I57: =IF(E56>0, (E57-E56)/E56, 0) -> -0.031614704
B58: 2019 | C58: =MINVU_Mes_Corriente!CB164 + MINVU_Mes_Corriente!CB26 + MINVU_Mes_Corriente!CB95 -> 1889599270 | D58: =MINVU_Mes_Corriente!CB186 + MINVU_Mes_Corriente!CB48 + MINVU_Mes_Corriente!CB117 -> 2048075399 | E58: =MINVU_Mes_Corriente!CB208 + MINVU_Mes_Corriente!CB70 + MINVU_Mes_Corriente!CB139 -> 2034276707 | F58: =D58 - E58 -> 13798692 | G58: =IF(D58>0, E58/D58, 0) -> 0.99326261 | H58: =IF(D57>0, (D58-D57)/D57, 0) -> 0.20302816 | I58: =IF(E57>0, (E58-E57)/E57, 0) -> 0.19976613
B59: 2020 | C59: =MINVU_Mes_Corriente!CO164 + MINVU_Mes_Corriente!CO26 + MINVU_Mes_Corriente!CO95 -> 2009243466 | D59: =MINVU_Mes_Corriente!CO186 + MINVU_Mes_Corriente!CO48 + MINVU_Mes_Corriente!CO117 -> 2068983787 | E59: =MINVU_Mes_Corriente!CO208 + MINVU_Mes_Corriente!CO70 + MINVU_Mes_Corriente!CO139 -> 2048851634 | F59: =D59 - E59 -> 20132153 | G59: =IF(D59>0, E59/D59, 0) -> 0.99026955 | H59: =IF(D58>0, (D59-D58)/D58, 0) -> 0.010208798 | I59: =IF(E58>0, (E59-E58)/E58, 0) -> 0.0071646728
B60: 2021 | C60: =MINVU_Mes_Corriente!DB164 + MINVU_Mes_Corriente!DB26 + MINVU_Mes_Corriente!DB95 -> 2165166433 | D60: =MINVU_Mes_Corriente!DB186 + MINVU_Mes_Corriente!DB48 + MINVU_Mes_Corriente!DB117 -> 2390342927 | E60: =MINVU_Mes_Corriente!DB208 + MINVU_Mes_Corriente!DB70 + MINVU_Mes_Corriente!DB139 -> 2353204514 | F60: =D60 - E60 -> 37138413 | G60: =IF(D60>0, E60/D60, 0) -> 0.98446314 | H60: =IF(D59>0, (D60-D59)/D59, 0) -> 0.15532221 | I60: =IF(E59>0, (E60-E59)/E59, 0) -> 0.14854803
B61: 2022 | C61: =MINVU_Mes_Corriente!DO164 + MINVU_Mes_Corriente!DO26 + MINVU_Mes_Corriente!DO95 -> 2517555200 | D61: =MINVU_Mes_Corriente!DO186 + MINVU_Mes_Corriente!DO48 + MINVU_Mes_Corriente!DO117 -> 2807365504 | E61: =MINVU_Mes_Corriente!DO208 + MINVU_Mes_Corriente!DO70 + MINVU_Mes_Corriente!DO139 -> 2782762948 | F61: =D61 - E61 -> 24602556 | G61: =IF(D61>0, E61/D61, 0) -> 0.99123643 | H61: =IF(D60>0, (D61-D60)/D60, 0) -> 0.1744614 | I61: =IF(E60>0, (E61-E60)/E60, 0) -> 0.1825419
B62: 2023 | C62: =MINVU_Mes_Corriente!EB164 + MINVU_Mes_Corriente!EB26 + MINVU_Mes_Corriente!EB95 -> 2940348026 | D62: =MINVU_Mes_Corriente!EB186 + MINVU_Mes_Corriente!EB48 + MINVU_Mes_Corriente!EB117 -> 2931817014 | E62: =MINVU_Mes_Corriente!EB208 + MINVU_Mes_Corriente!EB70 + MINVU_Mes_Corriente!EB139 -> 2900163375 | F62: =D62 - E62 -> 31653639 | G62: =IF(D62>0, E62/D62, 0) -> 0.98920341 | H62: =IF(D61>0, (D62-D61)/D61, 0) -> 0.044330355 | I62: =IF(E61>0, (E62-E61)/E61, 0) -> 0.04218844
B63: 2024 | C63: =MINVU_Mes_Corriente!EO164 + MINVU_Mes_Corriente!EO26 + MINVU_Mes_Corriente!EO95 -> 3320541734 | D63: =MINVU_Mes_Corriente!EO186 + MINVU_Mes_Corriente!EO48 + MINVU_Mes_Corriente!EO117 -> 3332768183 | E63: =MINVU_Mes_Corriente!EO208 + MINVU_Mes_Corriente!EO70 + MINVU_Mes_Corriente!EO139 -> 3312699040 | F63: =D63 - E63 -> 20069143 | G63: =IF(D63>0, E63/D63, 0) -> 0.99397824 | H63: =IF(D62>0, (D63-D62)/D62, 0) -> 0.13675859 | I63: =IF(E62>0, (E63-E62)/E62, 0) -> 0.14224566
B64: 2025 | C64: =MINVU_Mes_Corriente!FB164 + MINVU_Mes_Corriente!FB26 + MINVU_Mes_Corriente!FB95 -> 3720328808 | D64: =MINVU_Mes_Corriente!FB186 + MINVU_Mes_Corriente!FB48 + MINVU_Mes_Corriente!FB117 -> 3742940536 | E64: =MINVU_Mes_Corriente!FB208 + MINVU_Mes_Corriente!FB70 + MINVU_Mes_Corriente!FB139 -> 3692492363 | F64: =D64 - E64 -> 50448173 | G64: =IF(D64>0, E64/D64, 0) -> 0.98652178 | H64: =IF(D63>0, (D64-D63)/D63, 0) -> 0.12307257 | I64: =IF(E63>0, (E64-E63)/E63, 0) -> 0.1146477
B65: 2026 | C65: =MINVU_Mes_Corriente!FO164 + MINVU_Mes_Corriente!FO26 + MINVU_Mes_Corriente!FO95 -> 4149679420 | D65: =MINVU_Mes_Corriente!FO186 + MINVU_Mes_Corriente!FO48 + MINVU_Mes_Corriente!FO117 -> 4153039902 | E65: =MINVU_Mes_Corriente!FO208 + MINVU_Mes_Corriente!FO70 + MINVU_Mes_Corriente!FO139 -> 2142379287 | F65: =D65 - E65 -> 2010660615 | G65: =IF(D65>0, E65/D65, 0) -> 0.5158581 | H65: =IF(D64>0, (D65-D64)/D64, 0) -> 0.10956609 | I65: =IF(E64>0, (E65-E64)/E64, 0) -> -0.4198013

Sheet MINVU_Mes_Corriente
B1: Ministerio de Vivienda y Urbanismo — Partida 18
B2: Miles de pesos — moneda corriente — montos devengados
B4: SUBTÍTULO 31 – INICIATIVAS DE INVERSIÓN
B5: Presupuesto Ley (Subtítulo 31)
C6: 2014 | P6: 2015 | AC6: 2016 | AP6: 2017 | BC6: 2018 | BP6: 2019 | CC6: 2020 | CP6: 2021 | DC6: 2022 | DP6: 2023 | EC6: 2024 | EP6: 2025 | FC6: 2026
B7: Programa / Entidad | C7: Ene | D7: Feb | E7: Mar | F7: Abr | G7: May | H7: Jun | I7: Jul | J7: Ago | K7: Sep | L7: Oct | M7: Nov | N7: Dic | O7: Total 2014 | P7: Ene | Q7: Feb | R7: Mar | S7: Abr | T7: May | U7: Jun | V7: Jul | W7: Ago | X7: Sep | Y7: Oct | Z7: Nov | AA7: Dic | AB7: Total 2015 | AC7: Ene | AD7: Feb | AE7: Mar | AF7: Abr | AG7: May | AH7: Jun | AI7: Jul | AJ7: Ago | AK7: Sep | AL7: Oct | AM7: Nov | AN7: Dic | AO7: Total 2016 | AP7: Ene | AQ7: Feb | AR7: Mar | AS7: Abr | AT7: May | AU7: Jun | AV7: Jul | AW7: Ago | AX7: Sep | AY7: Oct | AZ7: Nov | BA7: Dic | BB7: Total 2017 | BC7: Ene | BD7: Feb | BE7: Mar | BF7: Abr | BG7: May | BH7: Jun | BI7: Jul | BJ7: Ago | BK7: Sep | BL7: Oct | BM7: Nov | BN7: Dic | BO7: Total 2018 | BP7: Ene | BQ7: Feb | BR7: Mar | BS7: Abr | BT7: May | BU7: Jun | BV7: Jul | BW7: Ago | BX7: Sep | BY7: Oct | BZ7: Nov | CA7: Dic | CB7: Total 2019 | CC7: Ene | CD7: Feb | CE7: Mar | CF7: Abr | CG7: May | CH7: Jun | CI7: Jul | CJ7: Ago | CK7: Sep | CL7: Oct | CM7: Nov | CN7: Dic | CO7: Total 2020 | CP7: Ene | CQ7: Feb | CR7: Mar | CS7: Abr | CT7: May | CU7: Jun | CV7: Jul | CW7: Ago | CX7: Sep | CY7: Oct | CZ7: Nov | DA7: Dic | DB7: Total 2021 | DC7: Ene | DD7: Feb | DE7: Mar | DF7: Abr | DG7: May | DH7: Jun | DI7: Jul | DJ7: Ago | DK7: Sep | DL7: Oct | DM7: Nov | DN7: Dic | DO7: Total 2022 | DP7: Ene | DQ7: Feb | DR7: Mar | DS7: Abr | DT7: May | DU7: Jun | DV7: Jul | DW7: Ago | DX7: Sep | DY7: Oct | DZ7: Nov | EA7: Dic | EB7: Total 2023 | EC7: Ene | ED7: Feb | EE7: Mar | EF7: Abr | EG7: May | EH7: Jun | EI7: Jul | EJ7: Ago | EK7: Sep | EL7: Oct | EM7: Nov | EN7: Dic | EO7: Total 2024 | EP7: Ene | EQ7: Feb | ER7: Mar | ES7: Abr | ET7: May | EU7: Jun | EV7: Jul | EW7: Ago | EX7: Sep | EY7: Oct | EZ7: Nov | FA7: Dic | FB7: Total 2025 | FC7: Ene | FD7: Feb | FE7: Mar | FF7: Abr | FG7: May | FH7: Jun | FI7: Jul | FJ7: Ago | FK7: Sep | FL7: Oct | FM7: Nov | FN7: Dic | FO7: Total 2026
B8: Subsecretaría y Programas Centrales | C8: 46689781 | D8: 46689781 | E8: 47980703 | F8: 47980703 | G8: 47980703 | H8: 47980703 | I8: 47980703 | J8: 47980703 | K8: 47980703 | L8: 47980703 | M8: 47980703 | N8: 47980703 | O8: 47980703 | P8: 52447510 | Q8: 52447510 | R8: 52447510 | S8: 52447510 | T8: 52447510 | U8: 52447510 | V8: 52447510 | W8: 52447510 | X8: 52447510 | Y8: 52447510 | Z8: 52447510 | AA8: 52447510 | AB8: 52447510 | AC8: 49700606 | AD8: 49700606 | AE8: 49700606 | AF8: 49700606 | AG8: 49700606 | AH8: 49700606 | AI8: 49700606 | AJ8: 49700606 | AK8: 49700606 | AL8: 49700606 | AM8: 49700606 | AN8: 49700606 | AO8: 49700606 | AP8: 45980831 | AQ8: 45980831 | AR8: 45980831 | AS8: 45980831 | AT8: 45980831 | AU8: 45980831 | AV8: 45980831 | AW8: 45980831 | AX8: 45980831 | AY8: 45980831 | AZ8: 45980831 | BA8: 45980831 | BB8: 45980831 | BC8: 45443730 | BD8: 45443730 | BE8: 45443730 | BF8: 45443730 | BG8: 45443730 | BH8: 45443730 | BI8: 45443730 | BJ8: 45443730 | BK8: 45443730 | BL8: 45443730 | BM8: 45443730 | BN8: 45443730 | BO8: 45443730 | BP8: 51220903 | BQ8: 51220903 | BR8: 51220903 | BS8: 51220903 | BT8: 51220903 | BU8: 51220903 | BV8: 51220903 | BW8: 51220903 | BX8: 51220903 | BY8: 51220903 | BZ8: 51220903 | CA8: 51220903 | CB8: 51220903 | CC8: 51587816 | CD8: 51587816 | CE8: 51587816 | CF8: 51587816 | CG8: 51587816 | CH8: 51587816 | CI8: 51587816 | CJ8: 51587816 | CK8: 51587816 | CL8: 51587816 | CM8: 51587816 | CN8: 51587816 | CO8: 51587816 | CP8: 35339308 | CQ8: 35339308 | CR8: 35339308 | CS8: 35339308 | CT8: 35339308 | CU8: 35339308 | CV8: 35339308 | CW8: 35339308 | CX8: 35339308 | CY8: 35339308 | CZ8: 35339308 | DA8: 35339308 | DB8: 35339308 | DC8: 22751821 | DD8: 22751821 | DE8: 22751821 | DF8: 22751821 | DG8: 22751821 | DH8: 22751821 | DI8: 22751821 | DJ8: 22751821 | DK8: 22751821 | DL8: 22751821 | DM8: 22751821 | DN8: 22751821 | DO8: 22751821 | DP8: 22326757 | DQ8: 22326757 | DR8: 22326757 | DS8: 22326757 | DT8: 22326757 | DU8: 22326757 | DV8: 22326757 | DW8: 22326757 | DX8: 22326757 | DY8: 22326757 | DZ8: 22326757 | EA8: 22326757 | EB8: 22326757 | EC8: 65885700 | ED8: 65885700 | EE8: 65885700 | EF8: 65885700 | EG8: 65885700 | EH8: 65885700 | EI8: 65885700 | EJ8: 65885700 | EK8: 65885700 | EL8: 65885700 | EM8: 65885700 | EN8: 65885700 | EO8: 65885700 | EP8: 31496963 | EQ8: 31496963 | ER8: 31496963 | ES8: 31496963 | ET8: 31496963 | EU8: 31496963 | EV8: 31496963 | EW8: 31496963 | EX8: 31496963 | EY8: 31496963 | EZ8: 31496963 | FA8: 31496963 | FB8: 31496963 | FC8: 15772873 | FD8: 15772873 | FE8: 15772873 | FF8: 15772873 | FG8: 15772873 | FH8: 15772873 | FI8: 15772873 | FJ8: 15772873 | FK8: 15772873 | FL8: 15772873 | FM8: 15772873 | FN8: 15772873 | FO8: 15772873
B9: Parque Metropolitano (PARQUEMET) | C9: 11852830 | D9: 11852830 | E9: 11852830 | F9: 11852830 | G9: 11852830 | H9: 11852830 | I9: 11852830 | J9: 11852830 | K9: 11852830 | L9: 11852830 | M9: 11852830 | N9: 11852830 | O9: 11852830 | P9: 12432312 | Q9: 12432312 | R9: 12432312 | S9: 12432312 | T9: 12432312 | U9: 12432312 | V9: 12432312 | W9: 12432312 | X9: 12432312 | Y9: 12432312 | Z9: 12432312 | AA9: 12432312 | AB9: 12432312 | AC9: 15376817 | AD9: 15376817 | AE9: 15376817 | AF9: 15376817 | AG9: 15376817 | AH9: 15376817 | AI9: 15376817 | AJ9: 15376817 | AK9: 15376817 | AL9: 15376817 | AM9: 15376817 | AN9: 15376817 | AO9: 15376817 | AP9: 19125128 | AQ9: 19125128 | AR9: 19125128 | AS9: 19125128 | AT9: 19125128 | AU9: 19125128 | AV9: 19125128 | AW9: 19125128 | AX9: 19125128 | AY9: 19125128 | AZ9: 19125128 | BA9: 19125128 | BB9: 19125128 | BC9: 22875150 | BD9: 22875150 | BE9: 22875150 | BF9: 22875150 | BG9: 22875150 | BH9: 22875150 | BI9: 22875150 | BJ9: 22875150 | BK9: 22875150 | BL9: 22875150 | BM9: 22875150 | BN9: 22875150 | BO9: 22875150 | BP9: 23805335 | BQ9: 23805335 | BR9: 23805335 | BS9: 23805335 | BT9: 23805335 | BU9: 23805335 | BV9: 23805335 | BW9: 23805335 | BX9: 23805335 | BY9: 23805335 | BZ9: 23805335 | CA9: 23805335 | CB9: 23805335 | CC9: 30005711 | CD9: 30005711 | CE9: 30005711 | CF9: 30005711 | CG9: 30005711 | CH9: 30005711 | CI9: 30005711 | CJ9: 30005711 | CK9: 30005711 | CL9: 30005711 | CM9: 30005711 | CN9: 30005711 | CO9: 30005711 | CP9: 28313204 | CQ9: 28313204 | CR9: 28313204 | CS9: 28313204 | CT9: 28313204 | CU9: 28313204 | CV9: 28313204 | CW9: 28313204 | CX9: 28313204 | CY9: 28313204 | CZ9: 28313204 | DA9: 28313204 | DB9: 28313204 | DC9: 26279513 | DD9: 26279513 | DE9: 26279513 | DF9: 26279513 | DG9: 26279513 | DH9: 26279513 | DI9: 26279513 | DJ9: 26279513 | DK9: 26279513 | DL9: 26279513 | DM9: 26279513 | DN9: 26279513 | DO9: 26279513 | DP9: 23921092 | DQ9: 23921092 | DR9: 23921092 | DS9: 23921092 | DT9: 23921092 | DU9: 23921092 | DV9: 23921092 | DW9: 23921092 | DX9: 23921092 | DY9: 23921092 | DZ9: 23921092 | EA9: 23921092 | EB9: 23921092 | EC9: 32623118 | ED9: 32623118 | EE9: 32623118 | EF9: 32623118 | EG9: 32623118 | EH9: 32623118 | EI9: 32623118 | EJ9: 32623118 | EK9: 32623118 | EL9: 32623118 | EM9: 32623118 | EN9: 32623118 | EO9: 32623118 | EP9: 31388552 | EQ9: 31388552 | ER9: 31388552 | ES9: 31388552 | ET9: 31388552 | EU9: 31388552 | EV9: 31388552 | EW9: 31388552 | EX9: 31388552 | EY9: 31388552 | EZ9: 31388552 | FA9: 31388552 | FB9: 31388552 | FC9: 32099544 | FD9: 32099544 | FE9: 32099544 | FF9: 32099544 | FG9: 32099544 | FH9: 32099544 | FI9: 32099544 | FJ9: 32099544 | FK9: 32099544 | FL9: 32099544 | FM9: 32099544 | FN9: 32099544 | FO9: 32099544
B10: SERVIU Arica y Parinacota | C10: 5502314 | D10: 5502314 | E10: 5502314 | F10: 5502314 | G10: 5502314 | H10: 5502314 | I10: 5502314 | J10: 5502314 | K10: 5502314 | L10: 5502314 | M10: 5502314 | N10: 5502314 | O10: 5502314 | P10: 7116496 | Q10: 7116496 | R10: 7116496 | S10: 7116496 | T10: 7116496 | U10: 7116496 | V10: 7116496 | W10: 7116496 | X10: 7116496 | Y10: 7116496 | Z10: 7116496 | AA10: 7116496 | AB10: 7116496 | AC10: 7118243 | AD10: 7118243 | AE10: 7118243 | AF10: 7118243 | AG10: 7118243 | AH10: 7118243 | AI10: 7118243 | AJ10: 7118243 | AK10: 7118243 | AL10: 7118243 | AM10: 7118243 | AN10: 7118243 | AO10: 7118243 | AP10: 6360483 | AQ10: 6360483 | AR10: 6360483 | AS10: 6360483 | AT10: 6360483 | AU10: 6360483 | AV10: 6360483 | AW10: 6360483 | AX10: 6360483 | AY10: 6360483 | AZ10: 6360483 | BA10: 6360483 | BB10: 6360483 | BC10: 8905218 | BD10: 8905218 | BE10: 8905218 | BF10: 8905218 | BG10: 8905218 | BH10: 8905218 | BI10: 8905218 | BJ10: 8905218 | BK10: 8905218 | BL10: 8905218 | BM10: 8905218 | BN10: 8905218 | BO10: 8905218 | BP10: 5657692 | BQ10: 5657692 | BR10: 5657692 | BS10: 5657692 | BT10: 5657692 | BU10: 5657692 | BV10: 5657692 | BW10: 5657692 | BX10: 5657692 | BY10: 5657692 | BZ10: 5657692 | CA10: 5657692 | CB10: 5657692 | CC10: 8447722 | CD10: 8447722 | CE10: 8447722 | CF10: 8447722 | CG10: 8447722 | CH10: 8447722 | CI10: 8447722 | CJ10: 8447722 | CK10: 8447722 | CL10: 8447722 | CM10: 8447722 | CN10: 8447722 | CO10: 8447722 | CP10: 9734344 | CQ10: 9734344 | CR10: 9734344 | CS10: 9734344 | CT10: 9734344 | CU10: 9734344 | CV10: 9734344 | CW10: 9734344 | CX10: 9734344 | CY10: 9734344 | CZ10: 9734344 | DA10: 9734344 | DB10: 9734344 | DC10: 8027524 | DD10: 8027524 | DE10: 8027524 | DF10: 8027524 | DG10: 8027524 | DH10: 8027524 | DI10: 8027524 | DJ10: 8027524 | DK10: 8027524 | DL10: 8027524 | DM10: 8027524 | DN10: 8027524 | DO10: 8027524 | DP10: 9623696 | DQ10: 9623696 | DR10: 9623696 | DS10: 9623696 | DT10: 9623696 | DU10: 9623696 | DV10: 9623696 | DW10: 9623696 | DX10: 9623696 | DY10: 9623696 | DZ10: 9623696 | EA10: 9623696 | EB10: 9623696 | EC10: 7002032 | ED10: 7002032 | EE10: 7002032 | EF10: 7002032 | EG10: 7002032 | EH10: 7002032 | EI10: 7002032 | EJ10: 7002032 | EK10: 7002032 | EL10: 7002032 | EM10: 7002032 | EN10: 7002032 | EO10: 7002032 | EP10: 7819491 | EQ10: 7819491 | ER10: 7819491 | ES10: 7819491 | ET10: 7819491 | EU10: 7819491 | EV10: 7819491 | EW10: 7819491 | EX10: 7819491 | EY10: 7819491 | EZ10: 7819491 | FA10: 7819491 | FB10: 7819491 | FC10: 2323330 | FD10: 2323330 | FE10: 2323330 | FF10: 2323330 | FG10: 2323330 | FH10: 2323330 | FI10: 2323330 | FJ10: 2323330 | FK10: 2323330 | FL10: 2323330 | FM10: 2323330 | FN10: 2323330 | FO10: 2323330
B11: SERVIU Tarapacá | C11: 17762256 | D11: 17762256 | E11: 17762256 | F11: 17762256 | G11: 17762256 | H11: 17762256 | I11: 17762256 | J11: 17762256 | K11: 17762256 | L11: 17762256 | M11: 17762256 | N11: 17762256 | O11: 17762256 | P11: 21803885 | Q11: 21803885 | R11: 21803885 | S11: 21803885 | T11: 21803885 | U11: 21803885 | V11: 21803885 | W11: 21803885 | X11: 21803885 | Y11: 21803885 | Z11: 21803885 | AA11: 21803885 | AB11: 21803885 | AC11: 20753826 | AD11: 20753826 | AE11: 20753826 | AF11: 20753826 | AG11: 20753826 | AH11: 20753826 | AI11: 20753826 | AJ11: 20753826 | AK11: 20753826 | AL11: 20753826 | AM11: 20753826 | AN11: 20753826 | AO11: 20753826 | AP11: 19705469 | AQ11: 19705469 | AR11: 19705469 | AS11: 19705469 | AT11: 19705469 | AU11: 19705469 | AV11: 19705469 | AW11: 19705469 | AX11: 19705469 | AY11: 19705469 | AZ11: 19705469 | BA11: 19705469 | BB11: 19705469 | BC11: 20697782 | BD11: 20697782 | BE11: 20697782 | BF11: 20697782 | BG11: 20697782 | BH11: 20697782 | BI11: 20697782 | BJ11: 20697782 | BK11: 20697782 | BL11: 20697782 | BM11: 20697782 | BN11: 20697782 | BO11: 20697782 | BP11: 12609240 | BQ11: 12609240 | BR11: 12609240 | BS11: 12609240 | BT11: 12609240 | BU11: 12609240 | BV11: 12609240 | BW11: 12609240 | BX11: 12609240 | BY11: 12609240 | BZ11: 12609240 | CA11: 12609240 | CB11: 12609240 | CC11: 8704861 | CD11: 8704861 | CE11: 8704861 | CF11: 8704861 | CG11: 8704861 | CH11: 8704861 | CI11: 8704861 | CJ11: 8704861 | CK11: 8704861 | CL11: 8704861 | CM11: 8704861 | CN11: 8704861 | CO11: 8704861 | CP11: 7005376 | CQ11: 7005376 | CR11: 7005376 | CS11: 7005376 | CT11: 7005376 | CU11: 7005376 | CV11: 7005376 | CW11: 7005376 | CX11: 7005376 | CY11: 7005376 | CZ11: 7005376 | DA11: 7005376 | DB11: 7005376 | DC11: 4659283 | DD11: 4659283 | DE11: 4659283 | DF11: 4659283 | DG11: 4659283 | DH11: 4659283 | DI11: 4659283 | DJ11: 4659283 | DK11: 4659283 | DL11: 4659283 | DM11: 4659283 | DN11: 4659283 | DO11: 4659283 | DP11: 9013306 | DQ11: 9013306 | DR11: 9013306 | DS11: 9013306 | DT11: 9013306 | DU11: 9013306 | DV11: 9013306 | DW11: 9013306 | DX11: 9013306 | DY11: 9013306 | DZ11: 9013306 | EA11: 9013306 | EB11: 9013306 | EC11: 11846836 | ED11: 11846836 | EE11: 11846836 | EF11: 11846836 | EG11: 11846836 | EH11: 11846836 | EI11: 11846836 | EJ11: 11846836 | EK11: 11846836 | EL11: 11846836 | EM11: 11846836 | EN11: 11846836 | EO11: 11846836 | EP11: 9956278 | EQ11: 9956278 | ER11: 9956278 | ES11: 9956278 | ET11: 9956278 | EU11: 9956278 | EV11: 9956278 | EW11: 9956278 | EX11: 9956278 | EY11: 9956278 | EZ11: 9956278 | FA11: 9956278 | FB11: 9956278 | FC11: 8706346 | FD11: 8706346 | FE11: 8706346 | FF11: 8706346 | FG11: 8706346 | FH11: 8706346 | FI11: 8706346 | FJ11: 8706346 | FK11: 8706346 | FL11: 8706346 | FM11: 8706346 | FN11: 8706346 | FO11: 8706346
B12: SERVIU Antofagasta | C12: 8823051 | D12: 8823051 | E12: 8823051 | F12: 8823051 | G12: 8823051 | H12: 8823051 | I12: 8823051 | J12: 8823051 | K12: 8823051 | L12: 8823051 | M12: 8823051 | N12: 8823051 | O12: 8823051 | P12: 9265514 | Q12: 9265514 | R12: 9265514 | S12: 9265514 | T12: 9265514 | U12: 9265514 | V12: 9265514 | W12: 9265514 | X12: 9265514 | Y12: 9265514 | Z12: 9265514 | AA12: 9265514 | AB12: 9265514 | AC12: 17751422 | AD12: 17751422 | AE12: 17751422 | AF12: 17751422 | AG12: 17751422 | AH12: 17751422 | AI12: 17751422 | AJ12: 17751422 | AK12: 17751422 | AL12: 17751422 | AM12: 17751422 | AN12: 17751422 | AO12: 17751422 | AP12: 23414402 | AQ12: 23414402 | AR12: 23414402 | AS12: 23414402 | AT12: 23414402 | AU12: 23414402 | AV12: 23414402 | AW12: 23414402 | AX12: 23414402 | AY12: 23414402 | AZ12: 23414402 | BA12: 23414402 | BB12: 23414402 | BC12: 16518133 | BD12: 16518133 | BE12: 16518133 | BF12: 16518133 | BG12: 16518133 | BH12: 16518133 | BI12: 16518133 | BJ12: 16518133 | BK12: 16518133 | BL12: 16518133 | BM12: 16518133 | BN12: 16518133 | BO12: 16518133 | BP12: 9624594 | BQ12: 9624594 | BR12: 9624594 | BS12: 9624594 | BT12: 9624594 | BU12: 9624594 | BV12: 9624594 | BW12: 9624594 | BX12: 9624594 | BY12: 9624594 | BZ12: 9624594 | CA12: 9624594 | CB12: 9624594 | CC12: 25370209 | CD12: 25370209 | CE12: 25370209 | CF12: 25370209 | CG12: 25370209 | CH12: 25370209 | CI12: 25370209 | CJ12: 25370209 | CK12: 25370209 | CL12: 25370209 | CM12: 25370209 | CN12: 25370209 | CO12: 25370209 | CP12: 35181732 | CQ12: 35181732 | CR12: 35181732 | CS12: 35181732 | CT12: 35181732 | CU12: 35181732 | CV12: 35181732 | CW12: 35181732 | CX12: 35181732 | CY12: 35181732 | CZ12: 35181732 | DA12: 35181732 | DB12: 35181732 | DC12: 35548395 | DD12: 35548395 | DE12: 35548395 | DF12: 35548395 | DG12: 35548395 | DH12: 35548395 | DI12: 35548395 | DJ12: 35548395 | DK12: 35548395 | DL12: 35548395 | DM12: 35548395 | DN12: 35548395 | DO12: 35548395 | DP12: 30263070 | DQ12: 30263070 | DR12: 30263070 | DS12: 30263070 | DT12: 30263070 | DU12: 30263070 | DV12: 30263070 | DW12: 30263070 | DX12: 30263070 | DY12: 30263070 | DZ12: 30263070 | EA12: 30263070 | EB12: 30263070 | EC12: 10878804 | ED12: 10878804 | EE12: 10878804 | EF12: 10878804 | EG12: 10878804 | EH12: 10878804 | EI12: 10878804 | EJ12: 10878804 | EK12: 10878804 | EL12: 10878804 | EM12: 10878804 | EN12: 10878804 | EO12: 10878804 | EP12: 13585888 | EQ12: 13585888 | ER12: 13585888 | ES12: 13585888 | ET12: 13585888 | EU12: 13585888 | EV12: 13585888 | EW12: 13585888 | EX12: 13585888 | EY12: 13585888 | EZ12: 13585888 | FA12: 13585888 | FB12: 13585888 | FC12: 13197867 | FD12: 13197867 | FE12: 13197867 | FF12: 13197867 | FG12: 13197867 | FH12: 13197867 | FI12: 13197867 | FJ12: 13197867 | FK12: 13197867 | FL12: 13197867 | FM12: 13197867 | FN12: 13197867 | FO12: 13197867
B13: SERVIU Atacama | C13: 5303372 | D13: 5303372 | E13: 5303372 | F13: 5303372 | G13: 5303372 | H13: 5303372 | I13: 5303372 | J13: 5303372 | K13: 5303372 | L13: 5303372 | M13: 5303372 | N13: 5303372 | O13: 5303372 | P13: 10483676 | Q13: 10483676 | R13: 10483676 | S13: 10483676 | T13: 10483676 | U13: 10483676 | V13: 10483676 | W13: 10483676 | X13: 10483676 | Y13: 10483676 | Z13: 10483676 | AA13: 10483676 | AB13: 10483676 | AC13: 7956960 | AD13: 7956960 | AE13: 7956960 | AF13: 7956960 | AG13: 7956960 | AH13: 7956960 | AI13: 7956960 | AJ13: 7956960 | AK13: 7956960 | AL13: 7956960 | AM13: 7956960 | AN13: 7956960 | AO13: 7956960 | AP13: 22558714 | AQ13: 22558714 | AR13: 22558714 | AS13: 22558714 | AT13: 22558714 | AU13: 22558714 | AV13: 22558714 | AW13: 22558714 | AX13: 22558714 | AY13: 22558714 | AZ13: 22558714 | BA13: 22558714 | BB13: 22558714 | BC13: 26064643 | BD13: 26064643 | BE13: 26064643 | BF13: 26064643 | BG13: 26064643 | BH13: 26064643 | BI13: 26064643 | BJ13: 26064643 | BK13: 26064643 | BL13: 26064643 | BM13: 26064643 | BN13: 26064643 | BO13: 26064643 | BP13: 16889432 | BQ13: 16889432 | BR13: 16889432 | BS13: 16889432 | BT13: 16889432 | BU13: 16889432 | BV13: 16889432 | BW13: 16889432 | BX13: 16889432 | BY13: 16889432 | BZ13: 16889432 | CA13: 16889432 | CB13: 16889432 | CC13: 17341145 | CD13: 17341145 | CE13: 17341145 | CF13: 17341145 | CG13: 17341145 | CH13: 17341145 | CI13: 17341145 | CJ13: 17341145 | CK13: 17341145 | CL13: 17341145 | CM13: 17341145 | CN13: 17341145 | CO13: 17341145 | CP13: 18709251 | CQ13: 18709251 | CR13: 18709251 | CS13: 18709251 | CT13: 18709251 | CU13: 18709251 | CV13: 18709251 | CW13: 18709251 | CX13: 18709251 | CY13: 18709251 | CZ13: 18709251 | DA13: 18709251 | DB13: 18709251 | DC13: 24875325 | DD13: 24875325 | DE13: 24875325 | DF13: 24875325 | DG13: 24875325 | DH13: 24875325 | DI13: 24875325 | DJ13: 24875325 | DK13: 24875325 | DL13: 24875325 | DM13: 24875325 | DN13: 24875325 | DO13: 24875325 | DP13: 21315123 | DQ13: 21315123 | DR13: 21315123 | DS13: 21315123 | DT13: 21315123 | DU13: 21315123 | DV13: 21315123 | DW13: 21315123 | DX13: 21315123 | DY13: 21315123 | DZ13: 21315123 | EA13: 21315123 | EB13: 21315123 | EC13: 21518444 | ED13: 21518444 | EE13: 21518444 | EF13: 21518444 | EG13: 21518444 | EH13: 21518444 | EI13: 21518444 | EJ13: 21518444 | EK13: 21518444 | EL13: 21518444 | EM13: 21518444 | EN13: 21518444 | EO13: 21518444 | EP13: 24183340 | EQ13: 24183340 | ER13: 24183340 | ES13: 24183340 | ET13: 24183340 | EU13: 24183340 | EV13: 24183340 | EW13: 24183340 | EX13: 24183340 | EY13: 24183340 | EZ13: 24183340 | FA13: 24183340 | FB13: 24183340 | FC13: 9416801 | FD13: 9416801 | FE13: 9416801 | FF13: 9416801 | FG13: 9416801 | FH13: 9416801 | FI13: 9416801 | FJ13: 9416801 | FK13: 9416801 | FL13: 9416801 | FM13: 9416801 | FN13: 9416801 | FO13: 9416801
B14: SERVIU Coquimbo | C14: 16064354 | D14: 16064354 | E14: 16064354 | F14: 16064354 | G14: 16064354 | H14: 16064354 | I14: 16064354 | J14: 16064354 | K14: 16064354 | L14: 16064354 | M14: 16064354 | N14: 16064354 | O14: 16064354 | P14: 19283793 | Q14: 19283793 | R14: 19283793 | S14: 19283793 | T14: 19283793 | U14: 19283793 | V14: 19283793 | W14: 19283793 | X14: 19283793 | Y14: 19283793 | Z14: 19283793 | AA14: 19283793 | AB14: 19283793 | AC14: 18570059 | AD14: 18570059 | AE14: 18570059 | AF14: 18570059 | AG14: 18570059 | AH14: 18570059 | AI14: 18570059 | AJ14: 18570059 | AK14: 18570059 | AL14: 18570059 | AM14: 18570059 | AN14: 18570059 | AO14: 18570059 | AP14: 27391856 | AQ14: 27391856 | AR14: 27391856 | AS14: 27391856 | AT14: 27391856 | AU14: 27391856 | AV14: 27391856 | AW14: 27391856 | AX14: 27391856 | AY14: 27391856 | AZ14: 27391856 | BA14: 27391856 | BB14: 27391856 | BC14: 16967208 | BD14: 16967208 | BE14: 16967208 | BF14: 16967208 | BG14: 16967208 | BH14: 16967208 | BI14: 16967208 | BJ14: 16967208 | BK14: 16967208 | BL14: 16967208 | BM14: 16967208 | BN14: 16967208 | BO14: 16967208 | BP14: 14997280 | BQ14: 14997280 | BR14: 14997280 | BS14: 14997280 | BT14: 14997280 | BU14: 14997280 | BV14: 14997280 | BW14: 14997280 | BX14: 14997280 | BY14: 14997280 | BZ14: 14997280 | CA14: 14997280 | CB14: 14997280 | CC14: 15408322 | CD14: 15408322 | CE14: 15408322 | CF14: 15408322 | CG14: 15408322 | CH14: 15408322 | CI14: 15408322 | CJ14: 15408322 | CK14: 15408322 | CL14: 15408322 | CM14: 15408322 | CN14: 15408322 | CO14: 15408322 | CP14: 16689514 | CQ14: 16689514 | CR14: 16689514 | CS14: 16689514 | CT14: 16689514 | CU14: 16689514 | CV14: 16689514 | CW14: 16689514 | CX14: 16689514 | CY14: 16689514 | CZ14: 16689514 | DA14: 16689514 | DB14: 16689514 | DC14: 29291800 | DD14: 29291800 | DE14: 29291800 | DF14: 29291800 | DG14: 29291800 | DH14: 29291800 | DI14: 29291800 | DJ14: 29291800 | DK14: 29291800 | DL14: 29291800 | DM14: 29291800 | DN14: 29291800 | DO14: 29291800 | DP14: 36352142 | DQ14: 36352142 | DR14: 36352142 | DS14: 36352142 | DT14: 36352142 | DU14: 36352142 | DV14: 36352142 | DW14: 36352142 | DX14: 36352142 | DY14: 36352142 | DZ14: 36352142 | EA14: 36352142 | EB14: 36352142 | EC14: 38254690 | ED14: 38254690 | EE14: 38254690 | EF14: 38254690 | EG14: 38254690 | EH14: 38254690 | EI14: 38254690 | EJ14: 38254690 | EK14: 38254690 | EL14: 38254690 | EM14: 38254690 | EN14: 38254690 | EO14: 38254690 | EP14: 27966487 | EQ14: 27966487 | ER14: 27966487 | ES14: 27966487 | ET14: 27966487 | EU14: 27966487 | EV14: 27966487 | EW14: 27966487 | EX14: 27966487 | EY14: 27966487 | EZ14: 27966487 | FA14: 27966487 | FB14: 27966487 | FC14: 30615904 | FD14: 30615904 | FE14: 30615904 | FF14: 30615904 | FG14: 30615904 | FH14: 30615904 | FI14: 30615904 | FJ14: 30615904 | FK14: 30615904 | FL14: 30615904 | FM14: 30615904 | FN14: 30615904 | FO14: 30615904
B15: SERVIU Valparaíso | C15: 18833256 | D15: 18833256 | E15: 18833256 | F15: 18833256 | G15: 18833256 | H15: 18833256 | I15: 18833256 | J15: 18833256 | K15: 18833256 | L15: 18833256 | M15: 18833256 | N15: 18833256 | O15: 18833256 | P15: 34473321 | Q15: 34473321 | R15: 34473321 | S15: 34473321 | T15: 34473321 | U15: 34473321 | V15: 34473321 | W15: 34473321 | X15: 34473321 | Y15: 34473321 | Z15: 34473321 | AA15: 34473321 | AB15: 34473321 | AC15: 32958542 | AD15: 32958542 | AE15: 32958542 | AF15: 32958542 | AG15: 32958542 | AH15: 32958542 | AI15: 32958542 | AJ15: 32958542 | AK15: 32958542 | AL15: 32958542 | AM15: 32958542 | AN15: 32958542 | AO15: 32958542 | AP15: 41283218 | AQ15: 41283218 | AR15: 41283218 | AS15: 41283218 | AT15: 41283218 | AU15: 41283218 | AV15: 41283218 | AW15: 41283218 | AX15: 41283218 | AY15: 41283218 | AZ15: 41283218 | BA15: 41283218 | BB15: 41283218 | BC15: 30569054 | BD15: 30569054 | BE15: 30569054 | BF15: 30569054 | BG15: 30569054 | BH15: 30569054 | BI15: 30569054 | BJ15: 30569054 | BK15: 30569054 | BL15: 30569054 | BM15: 30569054 | BN15: 30569054 | BO15: 30569054 | BP15: 28738435 | BQ15: 28738435 | BR15: 28738435 | BS15: 28738435 | BT15: 28738435 | BU15: 28738435 | BV15: 28738435 | BW15: 28738435 | BX15: 28738435 | BY15: 28738435 | BZ15: 28738435 | CA15: 28738435 | CB15: 28738435 | CC15: 33362165 | CD15: 33362165 | CE15: 33362165 | CF15: 33362165 | CG15: 33362165 | CH15: 33362165 | CI15: 33362165 | CJ15: 33362165 | CK15: 33362165 | CL15: 33362165 | CM15: 33362165 | CN15: 33362165 | CO15: 33362165 | CP15: 53755591 | CQ15: 53755591 | CR15: 53755591 | CS15: 53755591 | CT15: 53755591 | CU15: 53755591 | CV15: 53755591 | CW15: 53755591 | CX15: 53755591 | CY15: 53755591 | CZ15: 53755591 | DA15: 53755591 | DB15: 53755591 | DC15: 43170852 | DD15: 43170852 | DE15: 43170852 | DF15: 43170852 | DG15: 43170852 | DH15: 43170852 | DI15: 43170852 | DJ15: 43170852 | DK15: 43170852 | DL15: 43170852 | DM15: 43170852 | DN15: 43170852 | DO15: 43170852 | DP15: 40478579 | DQ15: 40478579 | DR15: 40478579 | DS15: 40478579 | DT15: 40478579 | DU15: 40478579 | DV15: 40478579 | DW15: 40478579 | DX15: 40478579 | DY15: 40478579 | DZ15: 40478579 | EA15: 40478579 | EB15: 40478579 | EC15: 44262543 | ED15: 44262543 | EE15: 44262543 | EF15: 44262543 | EG15: 44262543 | EH15: 44262543 | EI15: 44262543 | EJ15: 44262543 | EK15: 44262543 | EL15: 44262543 | EM15: 44262543 | EN15: 44262543 | EO15: 44262543 | EP15: 42009797 | EQ15: 42009797 | ER15: 42009797 | ES15: 42009797 | ET15: 42009797 | EU15: 42009797 | EV15: 42009797 | EW15: 42009797 | EX15: 42009797 | EY15: 42009797 | EZ15: 42009797 | FA15: 42009797 | FB15: 42009797 | FC15: 36533880 | FD15: 36533880 | FE15: 36533880 | FF15: 36533880 | FG15: 36533880 | FH15: 36533880 | FI15: 36533880 | FJ15: 36533880 | FK15: 36533880 | FL15: 36533880 | FM15: 36533880 | FN15: 36533880 | FO15: 36533880
B16: SERVIU Metropolitano | C16: 58929368 | D16: 58929368 | E16: 58929368 | F16: 58929368 | G16: 58929368 | H16: 58929368 | I16: 58929368 | J16: 58929368 | K16: 58929368 | L16: 58929368 | M16: 58929368 | N16: 58929368 | O16: 58929368 | P16: 63938761 | Q16: 63938761 | R16: 63938761 | S16: 63938761 | T16: 63938761 | U16: 63938761 | V16: 63938761 | W16: 63938761 | X16: 63938761 | Y16: 63938761 | Z16: 63938761 | AA16: 63938761 | AB16: 63938761 | AC16: 60602895 | AD16: 60602895 | AE16: 60602895 | AF16: 60602895 | AG16: 60602895 | AH16: 60602895 | AI16: 60602895 | AJ16: 60602895 | AK16: 60602895 | AL16: 60602895 | AM16: 60602895 | AN16: 60602895 | AO16: 60602895 | AP16: 56615435 | AQ16: 56615435 | AR16: 56615435 | AS16: 56615435 | AT16: 56615435 | AU16: 56615435 | AV16: 56615435 | AW16: 56615435 | AX16: 56615435 | AY16: 56615435 | AZ16: 56615435 | BA16: 56615435 | BB16: 56615435 | BC16: 45393646 | BD16: 45393646 | BE16: 45393646 | BF16: 45393646 | BG16: 45393646 | BH16: 45393646 | BI16: 45393646 | BJ16: 45393646 | BK16: 45393646 | BL16: 45393646 | BM16: 45393646 | BN16: 45393646 | BO16: 45393646 | BP16: 50282027 | BQ16: 50282027 | BR16: 50282027 | BS16: 50282027 | BT16: 50282027 | BU16: 50282027 | BV16: 50282027 | BW16: 50282027 | BX16: 50282027 | BY16: 50282027 | BZ16: 50282027 | CA16: 50282027 | CB16: 50282027 | CC16: 68935312 | CD16: 68935312 | CE16: 68935312 | CF16: 68935312 | CG16: 68935312 | CH16: 68935312 | CI16: 68935312 | CJ16: 68935312 | CK16: 68935312 | CL16: 68935312 | CM16: 68935312 | CN16: 68935312 | CO16: 68935312 | CP16: 75469606 | CQ16: 75469606 | CR16: 75469606 | CS16: 75469606 | CT16: 75469606 | CU16: 75469606 | CV16: 75469606 | CW16: 75469606 | CX16: 75469606 | CY16: 75469606 | CZ16: 75469606 | DA16: 75469606 | DB16: 75469606 | DC16: 100098472 | DD16: 100098472 | DE16: 100098472 | DF16: 100098472 | DG16: 100098472 | DH16: 100098472 | DI16: 100098472 | DJ16: 100098472 | DK16: 100098472 | DL16: 100098472 | DM16: 100098472 | DN16: 100098472 | DO16: 100098472 | DP16: 105488522 | DQ16: 105488522 | DR16: 105488522 | DS16: 105488522 | DT16: 105488522 | DU16: 105488522 | DV16: 105488522 | DW16: 105488522 | DX16: 105488522 | DY16: 105488522 | DZ16: 105488522 | EA16: 105488522 | EB16: 105488522 | EC16: 87253576 | ED16: 87253576 | EE16: 87253576 | EF16: 87253576 | EG16: 87253576 | EH16: 87253576 | EI16: 87253576 | EJ16: 87253576 | EK16: 87253576 | EL16: 87253576 | EM16: 87253576 | EN16: 87253576 | EO16: 87253576 | EP16: 74587862 | EQ16: 74587862 | ER16: 74587862 | ES16: 74587862 | ET16: 74587862 | EU16: 74587862 | EV16: 74587862 | EW16: 74587862 | EX16: 74587862 | EY16: 74587862 | EZ16: 74587862 | FA16: 74587862 | FB16: 74587862 | FC16: 90590002 | FD16: 90590002 | FE16: 90590002 | FF16: 90590002 | FG16: 90590002 | FH16: 90590002 | FI16: 90590002 | FJ16: 90590002 | FK16: 90590002 | FL16: 90590002 | FM16: 90590002 | FN16: 90590002 | FO16: 90590002
B17: SERVIU O'Higgins | C17: 26277535 | D17: 26277535 | E17: 26277535 | F17: 26277535 | G17: 26277535 | H17: 26277535 | I17: 26277535 | J17: 26277535 | K17: 26277535 | L17: 26277535 | M17: 26277535 | N17: 26277535 | O17: 26277535 | P17: 18864208 | Q17: 18864208 | R17: 18864208 | S17: 18864208 | T17: 18864208 | U17: 18864208 | V17: 18864208 | W17: 18864208 | X17: 18864208 | Y17: 18864208 | Z17: 18864208 | AA17: 18864208 | AB17: 18864208 | AC17: 16417514 | AD17: 16417514 | AE17: 16417514 | AF17: 16417514 | AG17: 16417514 | AH17: 16417514 | AI17: 16417514 | AJ17: 16417514 | AK17: 16417514 | AL17: 16417514 | AM17: 16417514 | AN17: 16417514 | AO17: 16417514 | AP17: 7822380 | AQ17: 7822380 | AR17: 7822380 | AS17: 7822380 | AT17: 7822380 | AU17: 7822380 | AV17: 7822380 | AW17: 7822380 | AX17: 7822380 | AY17: 7822380 | AZ17: 7822380 | BA17: 7822380 | BB17: 7822380 | BC17: 14195819 | BD17: 14195819 | BE17: 14195819 | BF17: 14195819 | BG17: 14195819 | BH17: 14195819 | BI17: 14195819 | BJ17: 14195819 | BK17: 14195819 | BL17: 14195819 | BM17: 14195819 | BN17: 14195819 | BO17: 14195819 | BP17: 10934837 | BQ17: 10934837 | BR17: 10934837 | BS17: 10934837 | BT17: 10934837 | BU17: 10934837 | BV17: 10934837 | BW17: 10934837 | BX17: 10934837 | BY17: 10934837 | BZ17: 10934837 | CA17: 10934837 | CB17: 10934837 | CC17: 12638831 | CD17: 12638831 | CE17: 12638831 | CF17: 12638831 | CG17: 12638831 | CH17: 12638831 | CI17: 12638831 | CJ17: 12638831 | CK17: 12638831 | CL17: 12638831 | CM17: 12638831 | CN17: 12638831 | CO17: 12638831 | CP17: 9595472 | CQ17: 9595472 | CR17: 9595472 | CS17: 9595472 | CT17: 9595472 | CU17: 9595472 | CV17: 9595472 | CW17: 9595472 | CX17: 9595472 | CY17: 9595472 | CZ17: 9595472 | DA17: 9595472 | DB17: 9595472 | DC17: 11870060 | DD17: 11870060 | DE17: 11870060 | DF17: 11870060 | DG17: 11870060 | DH17: 11870060 | DI17: 11870060 | DJ17: 11870060 | DK17: 11870060 | DL17: 11870060 | DM17: 11870060 | DN17: 11870060 | DO17: 11870060 | DP17: 16473882 | DQ17: 16473882 | DR17: 16473882 | DS17: 16473882 | DT17: 16473882 | DU17: 16473882 | DV17: 16473882 | DW17: 16473882 | DX17: 16473882 | DY17: 16473882 | DZ17: 16473882 | EA17: 16473882 | EB17: 16473882 | EC17: 16690085 | ED17: 16690085 | EE17: 16690085 | EF17: 16690085 | EG17: 16690085 | EH17: 16690085 | EI17: 16690085 | EJ17: 16690085 | EK17: 16690085 | EL17: 16690085 | EM17: 16690085 | EN17: 16690085 | EO17: 16690085 | EP17: 17865780 | EQ17: 17865780 | ER17: 17865780 | ES17: 17865780 | ET17: 17865780 | EU17: 17865780 | EV17: 17865780 | EW17: 17865780 | EX17: 17865780 | EY17: 17865780 | EZ17: 17865780 | FA17: 17865780 | FB17: 17865780 | FC17: 14196992 | FD17: 14196992 | FE17: 14196992 | FF17: 14196992 | FG17: 14196992 | FH17: 14196992 | FI17: 14196992 | FJ17: 14196992 | FK17: 14196992 | FL17: 14196992 | FM17: 14196992 | FN17: 14196992 | FO17: 14196992
B18: SERVIU Maule | C18: 18959297 | D18: 18959297 | E18: 18959297 | F18: 18959297 | G18: 18959297 | H18: 18959297 | I18: 18959297 | J18: 18959297 | K18: 18959297 | L18: 18959297 | M18: 18959297 | N18: 18959297 | O18: 18959297 | P18: 28078883 | Q18: 28078883 | R18: 28078883 | S18: 28078883 | T18: 28078883 | U18: 28078883 | V18: 28078883 | W18: 28078883 | X18: 28078883 | Y18: 28078883 | Z18: 28078883 | AA18: 28078883 | AB18: 28078883 | AC18: 27091258 | AD18: 27091258 | AE18: 27091258 | AF18: 27091258 | AG18: 27091258 | AH18: 27091258 | AI18: 27091258 | AJ18: 27091258 | AK18: 27091258 | AL18: 27091258 | AM18: 27091258 | AN18: 27091258 | AO18: 27091258 | AP18: 41060039 | AQ18: 41060039 | AR18: 41060039 | AS18: 41060039 | AT18: 41060039 | AU18: 41060039 | AV18: 41060039 | AW18: 41060039 | AX18: 41060039 | AY18: 41060039 | AZ18: 41060039 | BA18: 41060039 | BB18: 41060039 | BC18: 44459639 | BD18: 44459639 | BE18: 44459639 | BF18: 44459639 | BG18: 44459639 | BH18: 44459639 | BI18: 44459639 | BJ18: 44459639 | BK18: 44459639 | BL18: 44459639 | BM18: 44459639 | BN18: 44459639 | BO18: 44459639 | BP18: 36664986 | BQ18: 36664986 | BR18: 36664986 | BS18: 36664986 | BT18: 36664986 | BU18: 36664986 | BV18: 36664986 | BW18: 36664986 | BX18: 36664986 | BY18: 36664986 | BZ18: 36664986 | CA18: 36664986 | CB18: 36664986 | CC18: 28819307 | CD18: 28819307 | CE18: 28819307 | CF18: 28819307 | CG18: 28819307 | CH18: 28819307 | CI18: 28819307 | CJ18: 28819307 | CK18: 28819307 | CL18: 28819307 | CM18: 28819307 | CN18: 28819307 | CO18: 28819307 | CP18: 32317785 | CQ18: 32317785 | CR18: 32317785 | CS18: 32317785 | CT18: 32317785 | CU18: 32317785 | CV18: 32317785 | CW18: 32317785 | CX18: 32317785 | CY18: 32317785 | CZ18: 32317785 | DA18: 32317785 | DB18: 32317785 | DC18: 41575245 | DD18: 41575245 | DE18: 41575245 | DF18: 41575245 | DG18: 41575245 | DH18: 41575245 | DI18: 41575245 | DJ18: 41575245 | DK18: 41575245 | DL18: 41575245 | DM18: 41575245 | DN18: 41575245 | DO18: 41575245 | DP18: 34076619 | DQ18: 34076619 | DR18: 34076619 | DS18: 34076619 | DT18: 34076619 | DU18: 34076619 | DV18: 34076619 | DW18: 34076619 | DX18: 34076619 | DY18: 34076619 | DZ18: 34076619 | EA18: 34076619 | EB18: 34076619 | EC18: 28318956 | ED18: 28318956 | EE18: 28318956 | EF18: 28318956 | EG18: 28318956 | EH18: 28318956 | EI18: 28318956 | EJ18: 28318956 | EK18: 28318956 | EL18: 28318956 | EM18: 28318956 | EN18: 28318956 | EO18: 28318956 | EP18: 30628977 | EQ18: 30628977 | ER18: 30628977 | ES18: 30628977 | ET18: 30628977 | EU18: 30628977 | EV18: 30628977 | EW18: 30628977 | EX18: 30628977 | EY18: 30628977 | EZ18: 30628977 | FA18: 30628977 | FB18: 30628977 | FC18: 25030745 | FD18: 25030745 | FE18: 25030745 | FF18: 25030745 | FG18: 25030745 | FH18: 25030745 | FI18: 25030745 | FJ18: 25030745 | FK18: 25030745 | FL18: 25030745 | FM18: 25030745 | FN18: 25030745 | FO18: 25030745
B19: SERVIU Ñuble | C19: 0 | D19: 0 | E19: 0 | F19: 0 | G19: 0 | H19: 0 | I19: 0 | J19: 0 | K19: 0 | L19: 0 | M19: 0 | N19: 0 | O19: 0 | P19: 0 | Q19: 0 | R19: 0 | S19: 0 | T19: 0 | U19: 0 | V19: 0 | W19: 0 | X19: 0 | Y19: 0 | Z19: 0 | AA19: 0 | AB19: 0 | AC19: 0 | AD19: 0 | AE19: 0 | AF19: 0 | AG19: 0 | AH19: 0 | AI19: 0 | AJ19: 0 | AK19: 0 | AL19: 0 | AM19: 0 | AN19: 0 | AO19: 0 | AP19: 0 | AQ19: 0 | AR19: 0 | AS19: 0 | AT19: 0 | AU19: 0 | AV19: 0 | AW19: 0 | AX19: 0 | AY19: 0 | AZ19: 0 | BA19: 0 | BB19: 0 | BC19: 0 | BD19: 0 | BE19: 0 | BF19: 0 | BG19: 0 | BH19: 0 | BI19: 0 | BJ19: 0 | BK19: 0 | BL19: 0 | BM19: 0 | BN19: 0 | BO19: 0 | BP19: 3063155 | BQ19: 3063155 | BR19: 3063155 | BS19: 3063155 | BT19: 3063155 | BU19: 3063155 | BV19: 3063155 | BW19: 3063155 | BX19: 3063155 | BY19: 3063155 | BZ19: 3063155 | CA19: 3063155 | CB19: 3063155 | CC19: 7620030 | CD19: 7620030 | CE19: 7620030 | CF19: 7620030 | CG19: 7620030 | CH19: 7620030 | CI19: 7620030 | CJ19: 7620030 | CK19: 7620030 | CL19: 7620030 | CM19: 7620030 | CN19: 7620030 | CO19: 7620030 | CP19: 17998490 | CQ19: 17998490 | CR19: 17998490 | CS19: 17998490 | CT19: 17998490 | CU19: 17998490 | CV19: 17998490 | CW19: 17998490 | CX19: 17998490 | CY19: 17998490 | CZ19: 17998490 | DA19: 17998490 | DB19: 17998490 | DC19: 36920320 | DD19: 36920320 | DE19: 36920320 | DF19: 36920320 | DG19: 36920320 | DH19: 36920320 | DI19: 36920320 | DJ19: 36920320 | DK19: 36920320 | DL19: 36920320 | DM19: 36920320 | DN19: 36920320 | DO19: 36920320 | DP19: 23700733 | DQ19: 23700733 | DR19: 23700733 | DS19: 23700733 | DT19: 23700733 | DU19: 23700733 | DV19: 23700733 | DW19: 23700733 | DX19: 23700733 | DY19: 23700733 | DZ19: 23700733 | EA19: 23700733 | EB19: 23700733 | EC19: 23113535 | ED19: 23113535 | EE19: 23113535 | EF19: 23113535 | EG19: 23113535 | EH19: 23113535 | EI19: 23113535 | EJ19: 23113535 | EK19: 23113535 | EL19: 23113535 | EM19: 23113535 | EN19: 23113535 | EO19: 23113535 | EP19: 22079448 | EQ19: 22079448 | ER19: 22079448 | ES19: 22079448 | ET19: 22079448 | EU19: 22079448 | EV19: 22079448 | EW19: 22079448 | EX19: 22079448 | EY19: 22079448 | EZ19: 22079448 | FA19: 22079448 | FB19: 22079448 | FC19: 24086756 | FD19: 24086756 | FE19: 24086756 | FF19: 24086756 | FG19: 24086756 | FH19: 24086756 | FI19: 24086756 | FJ19: 24086756 | FK19: 24086756 | FL19: 24086756 | FM19: 24086756 | FN19: 24086756 | FO19: 24086756
... B25: SERVIU Magallanes | C25: 11406728 | D25: 11406728 | E25: 11406728 | F25: 11406728 | G25: 11406728 | H25: 11406728 | I25: 11406728 | J25: 11406728 | K25: 11406728 | L25: 11406728 | M25: 11406728 | N25: 11406728 | O25: 11406728 | P25: 8619188 | Q25: 8619188 | R25: 8619188 | S25: 8619188 | T25: 8619188 | U25: 8619188 | V25: 8619188 | W25: 8619188 | X25: 8619188 | Y25: 8619188 | Z25: 8619188 | AA25: 8619188 | AB25: 8619188 | AC25: 8177486 | AD25: 8177486 | AE25: 8177486 | AF25: 8177486 | AG25: 8177486 | AH25: 8177486 | AI25: 8177486 | AJ25: 8177486 | AK25: 8177486 | AL25: 8177486 | AM25: 8177486 | AN25: 8177486 | AO25: 8177486 | AP25: 10756255 | AQ25: 10756255 | AR25: 10756255 | AS25: 10756255 | AT25: 10756255 | AU25: 10756255 | AV25: 10756255 | AW25: 10756255 | AX25: 10756255 | AY25: 10756255 | AZ25: 10756255 | BA25: 10756255 | BB25: 10756255 | BC25: 11496808 | BD25: 11496808 | BE25: 11496808 | BF25: 11496808 | BG25: 11496808 | BH25: 11496808 | BI25: 11496808 | BJ25: 11496808 | BK25: 11496808 | BL25: 11496808 | BM25: 11496808 | BN25: 11496808 | BO25: 11496808 | BP25: 15389832 | BQ25: 15389832 | BR25: 15389832 | BS25: 15389832 | BT25: 15389832 | BU25: 15389832 | BV25: 15389832 | BW25: 15389832 | BX25: 15389832 | BY25: 15389832 | BZ25: 15389832 | CA25: 15389832 | CB25: 15389832 | CC25: 12031468 | CD25: 12031468 | CE25: 12031468 | CF25: 12031468 | CG25: 12031468 | CH25: 12031468 | CI25: 12031468 | CJ25: 12031468 | CK25: 12031468 | CL25: 12031468 | CM25: 12031468 | CN25: 12031468 | CO25: 12031468 | CP25: 9782662 | CQ25: 9782662 | CR25: 9782662 | CS25: 9782662 | CT25: 9782662 | CU25: 9782662 | CV25: 9782662 | CW25: 9782662 | CX25: 9782662 | CY25: 9782662 | CZ25: 9782662 | DA25: 9782662 | DB25: 9782662 | DC25: 14902342 | DD25: 14902342 | DE25: 14902342 | DF25: 14902342 | DG25: 14902342 | DH25: 14902342 | DI25: 14902342 | DJ25: 14902342 | DK25: 14902342 | DL25: 14902342 | DM25: 14902342 | DN25: 14902342 | DO25: 14902342 | DP25: 22127832 | DQ25: 22127832 | DR25: 22127832 | DS25: 22127832 | DT25: 22127832 | DU25: 22127832 | DV25: 22127832 | DW25: 22127832 | DX25: 22127832 | DY25: 22127832 | DZ25: 22127832 | EA25: 22127832 | EB25: 22127832 | EC25: 22256093 | ED25: 22256093 | EE25: 22256093 | EF25: 22256093 | EG25: 22256093 | EH25: 22256093 | EI25: 22256093 | EJ25: 22256093 | EK25: 22256093 | EL25: 22256093 | EM25: 22256093 | EN25: 22256093 | EO25: 22256093 | EP25: 21184028 | EQ25: 21184028 | ER25: 21184028 | ES25: 21184028 | ET25: 21184028 | EU25: 21184028 | EV25: 21184028 | EW25: 21184028 | EX25: 21184028 | EY25: 21184028 | EZ25: 21184028 | FA25: 21184028 | FB25: 21184028 | FC25: 24770394 | FD25: 24770394 | FE25: 24770394 | FF25: 24770394 | FG25: 24770394 | FH25: 24770394 | FI25: 24770394 | FJ25: 24770394 | FK25: 24770394 | FL25: 24770394 | FM25: 24770394 | FN25: 24770394 | FO25: 24770394
B26: Total Presupuesto Ley (Subtítulo 31) | C26: =SUM(C8:C25) -> 350781874 | D26: =SUM(D8:D25) -> 350781874 | E26: =SUM(E8:E25) -> 352072796 | F26: =SUM(F8:F25) -> 352072796 | G26: =SUM(G8:G25) -> 352072796 | H26: =SUM(H8:H25) -> 352072796 | I26: =SUM(I8:I25) -> 352072796 | J26: =SUM(J8:J25) -> 352072796 | ... FO26: =SUM(FO8:FO25) -> 465461219
B27: Presupuesto Vigente (Subtítulo 31)
C28: 2014 | P28: 2015 | AC28: 2016 | AP28: 2017 | BC28: 2018 | BP28: 2019 | CC28: 2020 | CP28: 2021 | DC28: 2022 | DP28: 2023 | EC28: 2024 | EP28: 2025 | FC28: 2026
B29: Programa / Entidad | C29: Ene | D29: Feb | E29: Mar | F29: Abr | G29: May | H29: Jun | I29: Jul | J29: Ago | K29: Sep | L29: Oct | M29: Nov | N29: Dic | O29: Total 2014 | P29: Ene | Q29: Feb | R29: Mar | S29: Abr | T29: May | U29: Jun | V29: Jul | W29: Ago | X29: Sep | Y29: Oct | Z29: Nov | AA29: Dic | AB29: Total 2015 | AC29: Ene | AD29: Feb | AE29: Mar | AF29: Abr | AG29: May | AH29: Jun | AI29: Jul | AJ29: Ago | AK29: Sep | AL29: Oct | AM29: Nov | AN29: Dic | AO29: Total 2016 | AP29: Ene | AQ29: Feb | AR29: Mar | AS29: Abr | AT29: May | AU29: Jun | AV29: Jul | AW29: Ago | AX29: Sep | AY29: Oct | AZ29: Nov | BA29: Dic | BB29: Total 2017 | BC29: Ene | BD29: Feb | BE29: Mar | BF29: Abr | BG29: May | BH29: Jun | BI29: Jul | BJ29: Ago | BK29: Sep | BL29: Oct | BM29: Nov | BN29: Dic | BO29: Total 2018 | BP29: Ene | BQ29: Feb | BR29: Mar | BS29: Abr | BT29: May | BU29: Jun | BV29: Jul | BW29: Ago | BX29: Sep | BY29: Oct | BZ29: Nov | CA29: Dic | CB29: Total 2019 | CC29: Ene | CD29: Feb | CE29: Mar | CF29: Abr | CG29: May | CH29: Jun | CI29: Jul | CJ29: Ago | CK29: Sep | CL29: Oct | CM29: Nov | CN29: Dic | CO29: Total 2020 | CP29: Ene | CQ29: Feb | CR29: Mar | CS29: Abr | CT29: May | CU29: Jun | CV29: Jul | CW29: Ago | CX29: Sep | CY29: Oct | CZ29: Nov | DA29: Dic | DB29: Total 2021 | DC29: Ene | DD29: Feb | DE29: Mar | DF29: Abr | DG29: May | DH29: Jun | DI29: Jul | DJ29: Ago | DK29: Sep | DL29: Oct | DM29: Nov | DN29: Dic | DO29: Total 2022 | DP29: Ene | DQ29: Feb | DR29: Mar | DS29: Abr | DT29: May | DU29: Jun | DV29: Jul | DW29: Ago | DX29: Sep | DY29: Oct | DZ29: Nov | EA29: Dic | EB29: Total 2023 | EC29: Ene | ED29: Feb | EE29: Mar | EF29: Abr | EG29: May | EH29: Jun | EI29: Jul | EJ29: Ago | EK29: Sep | EL29: Oct | EM29: Nov | EN29: Dic | EO29: Total 2024 | EP29: Ene | EQ29: Feb | ER29: Mar | ES29: Abr | ET29: May | EU29: Jun | EV29: Jul | EW29: Ago | EX29: Sep | EY29: Oct | EZ29: Nov | FA29: Dic | FB29: Total 2025 | FC29: Ene | FD29: Feb | FE29: Mar | FF29: Abr | FG29: May | FH29: Jun | FI29: Jul | FJ29: Ago | FK29: Sep | FL29: Oct | FM29: Nov | FN29: Dic | FO29: Total 2026
B30: Subsecretaría y Programas Centrales | C30: 46689781 | D30: 46689781 | E30: 36108344 | F30: 36108344 | G30: 35108344 | H30: 35051835 | I30: 35051835 | J30: 30460971 | K30: 27254831 | L30: 27083752 | M30: 26230314 | N30: 25082082 | O30: 25082082 | P30: 52447510 | Q30: 34707828 | R30: 34637698 | S30: 34637698 | T30: 34577698 | U30: 34213379 | V30: 33826803 | W30: 33964676 | X30: 34237560 | Y30: 31614904 | Z30: 31384850 | AA30: 27202285 | AB30: 27202285 | AC30: 49700606 | AD30: 29051988 | AE30: 28882887 | AF30: 28882887 | AG30: 28814489 | AH30: 28814489 | AI30: 28739993 | AJ30: 28639393 | AK30: 28639393 | AL30: 28573867 | AM30: 28561967 | AN30: 27769919 | AO30: 27769919 | AP30: 45980831 | AQ30: 29828531 | AR30: 29828531 | AS30: 29785271 | AT30: 29785271 | AU30: 29837531 | AV30: 29837531 | AW30: 29703072 | AX30: 29703072 | AY30: 29738991 | AZ30: 29239385 | BA30: 29123116 | BB30: 29123116 | BC30: 45443730 | BD30: 32561425 | BE30: 32561425 | BF30: 32561425 | BG30: 32561425 | BH30: 32561425 | BI30: 32504329 | BJ30: 32732984 | BK30: 32732984 | BL30: 31962688 | BM30: 31506727 | BN30: 30554750 | BO30: 30554750 | BP30: 51220903 | BQ30: 51220903 | BR30: 36026667 | BS30: 36026667 | BT30: 36026667 | BU30: 36026667 | BV30: 34946790 | BW30: 34745372 | BX30: 36026667 | BY30: 51220903 | BZ30: 51220903 | CA30: 38081494 | CB30: 38081494 | CC30: 51587816 | CD30: 51587816 | CE30: 51587816 | CF30: 45777900 | CG30: 45777900 | CH30: 45919780 | CI30: 46321227 | CJ30: 46321227 | CK30: 36664247 | CL30: 36102413 | CM30: 36087871 | CN30: 35129581 | CO30: 35129581 | CP30: 35339308 | CQ30: 34095082 | CR30: 30900763 | CS30: 30000165 | CT30: 28431391 | CU30: 28482712 | CV30: 28482712 | CW30: 28482712 | CX30: 28482712 | CY30: 26544090 | CZ30: 27401071 | DA30: 26558777 | DB30: 26558777 | DC30: 22751821 | DD30: 14162616 | DE30: 14162616 | DF30: 14162616 | DG30: 14094265 | DH30: 14094265 | DI30: 13994333 | DJ30: 14199833 | DK30: 14199833 | DL30: 14215569 | DM30: 13257545 | DN30: 11513633 | DO30: 11513633 | DP30: 22326757 | DQ30: 12413948 | DR30: 12413948 | DS30: 12169459 | DT30: 11694537 | DU30: 11453537 | DV30: 11207907 | DW30: 11175513 | DX30: 11175513 | DY30: 11175513 | DZ30: 3304471 | EA30: 2258817 | EB30: 2258817 | EC30: 65885700 | ED30: 65885700 | EE30: 40863396 | EF30: 40863396 | EG30: 40441434 | EH30: 40130157 | EI30: 40110894 | EJ30: 35322619 | EK30: 31954975 | EL30: 31882527 | EM30: 19631668 | EN30: 1858597 | EO30: 1858597 | EP30: 31496963 | EQ30: 21938918 | ER30: 17774772 | ES30: 17594772 | ET30: 17439772 | EU30: 16908124 | EV30: 10908124 | EW30: 10908124 | EX30: 10908124 | EY30: 4377527 | EZ30: 4377527 | FA30: 2042428 | FB30: 2042428 | FC30: 15772873 | FD30: 15772873 | FE30: 15772873 | FF30: 15772873 | FG30: 3763881 | FH30: 3874066 | FI30: 2591940 | FJ30: 2591940 | FK30: 2591940 | FL30: 2591940 | FM30: 2591940 | FN30: 2591940 | FO30: 2591940
B31: Parque Metropolitano (PARQUEMET) | C31: 11852830 | D31: 11852830 | E31: 11852830 | F31: 11852830 | G31: 11852830 | H31: 11852830 | I31: 11852830 | J31: 11852830 | K31: 11852830 | L31: 11852830 | M31: 11852830 | N31: 11623749 | O31: 11623749 | P31: 12432312 | Q31: 15452289 | R31: 15452289 | S31: 15452289 | T31: 15452289 | U31: 15452289 | V31: 15452289 | W31: 15463341 | X31: 15463341 | Y31: 15653813 | Z31: 15653813 | AA31: 15653813 | AB31: 15653813 | AC31: 15376817 | AD31: 15376817 | AE31: 15545918 | AF31: 15545918 | AG31: 15545918 | AH31: 15545918 | AI31: 15545918 | AJ31: 16102418 | AK31: 16102418 | AL31: 16102418 | AM31: 16102418 | AN31: 16102418 | AO31: 16102418 | AP31: 19125128 | AQ31: 19125128 | AR31: 19125128 | AS31: 19125128 | AT31: 19125128 | AU31: 19125128 | AV31: 19125128 | AW31: 19125128 | AX31: 19125128 | AY31: 19125128 | AZ31: 19125128 | BA31: 19125128 | BB31: 19125128 | BC31: 22875150 | BD31: 22875150 | BE31: 22875150 | BF31: 22875150 | BG31: 22875150 | BH31: 22875150 | BI31: 22875150 | BJ31: 22875150 | BK31: 22875150 | BL31: 22875150 | BM31: 22875150 | BN31: 20559175 | BO31: 20559175 | BP31: 23805335 | BQ31: 23805335 | BR31: 23805335 | BS31: 23805335 | BT31: 23805335 | BU31: 23805335 | BV31: 23805335 | BW31: 23805335 | BX31: 24082775 | BY31: 24082775 | BZ31: 24082775 | CA31: 23199865 | CB31: 23199865 | CC31: 30005711 | CD31: 30005711 | CE31: 30005711 | CF31: 30005711 | CG31: 30005711 | CH31: 30005711 | CI31: 30005711 | CJ31: 30005711 | CK31: 24363947 | CL31: 24363947 | CM31: 24363947 | CN31: 23514290 | CO31: 23514290 | CP31: 28313204 | CQ31: 30808704 | CR31: 30808704 | CS31: 30808704 | CT31: 30808704 | CU31: 30808704 | CV31: 30808704 | CW31: 30808704 | CX31: 30808704 | CY31: 30808704 | CZ31: 30808704 | DA31: 30377501 | DB31: 30377501 | DC31: 26279513 | DD31: 26279513 | DE31: 26279513 | DF31: 26279513 | DG31: 26279513 | DH31: 26279513 | DI31: 26279513 | DJ31: 26279513 | DK31: 26279513 | DL31: 26279513 | DM31: 23402444 | DN31: 23403944 | DO31: 23403944 | DP31: 23921092 | DQ31: 23921092 | DR31: 23921092 | DS31: 23921092 | DT31: 23921092 | DU31: 23921092 | DV31: 23998690 | DW31: 23998690 | DX31: 23998690 | DY31: 23998690 | DZ31: 23228459 | EA31: 22242755 | EB31: 22242755 | EC31: 32623118 | ED31: 32623118 | EE31: 32623118 | EF31: 32623118 | EG31: 32623118 | EH31: 32623118 | EI31: 32623118 | EJ31: 32388971 | EK31: 31969868 | EL31: 31969868 | EM31: 28971461 | EN31: 27933416 | EO31: 27933416 | EP31: 31388552 | EQ31: 31388552 | ER31: 31388552 | ES31: 31388552 | ET31: 31388552 | EU31: 31388552 | EV31: 31388552 | EW31: 31388552 | EX31: 31388552 | EY31: 31049772 | EZ31: 31049772 | FA31: 30251792 | FB31: 30251792 | FC31: 32099544 | FD31: 32099544 | FE31: 32099544 | FF31: 32099544 | FG31: 32099544 | FH31: 32099544 | FI31: 32099544 | FJ31: 32099544 | FK31: 32099544 | FL31: 32099544 | FM31: 32099544 | FN31: 32099544 | FO31: 32099544
B32: SERVIU Arica y Parinacota | C32: 5502314 | D32: 5502314 | E32: 5975273 | F32: 5975273 | G32: 5975273 | H32: 5975273 | I32: 5975273 | J32: 6076123 | K32: 6081001 | L32: 6070217 | M32: 6070217 | N32: 5726238 | O32: 5726238 | P32: 7116496 | Q32: 7918169 | R32: 7918169 | S32: 7918169 | T32: 8068747 | U32: 8068747 | V32: 8068747 | W32: 8521337 | X32: 8521337 | Y32: 8741191 | Z32: 8741191 | AA32: 8051916 | AB32: 8051916 | AC32: 7118243 | AD32: 8303389 | AE32: 9807240 | AF32: 9807240 | AG32: 9807240 | AH32: 9807240 | AI32: 10530390 | AJ32: 10530390 | AK32: 10530390 | AL32: 10530390 | AM32: 9994370 | AN32: 9419196 | AO32: 9419196 | AP32: 6360483 | AQ32: 7408519 | AR32: 7408519 | AS32: 7408519 | AT32: 7408519 | AU32: 7542057 | AV32: 7685652 | AW32: 7685652 | AX32: 8741294 | AY32: 9731912 | AZ32: 9712114 | BA32: 9325032 | BB32: 9325032 | BC32: 8905218 | BD32: 9754722 | BE32: 9754722 | BF32: 9754722 | BG32: 9754722 | BH32: 9754722 | BI32: 9725723 | BJ32: 8926953 | BK32: 8926953 | BL32: 7126953 | BM32: 7126953 | BN32: 5732079 | BO32: 5732079 | BP32: 5657692 | BQ32: 5657692 | BR32: 6371024 | BS32: 6371024 | BT32: 6220569 | BU32: 5955169 | BV32: 5955169 | BW32: 5256757 | BX32: 5256757 | BY32: 5256757 | BZ32: 5256757 | CA32: 3514334 | CB32: 3514334 | CC32: 8447722 | CD32: 8447722 | CE32: 8447722 | CF32: 7952427 | CG32: 7952427 | CH32: 7952427 | CI32: 7952427 | CJ32: 7952427 | CK32: 7952427 | CL32: 7867785 | CM32: 7867785 | CN32: 5737629 | CO32: 5737629 | CP32: 10293909 | CQ32: 10084346 | CR32: 10084346 | CS32: 10084346 | CT32: 9752272 | CU32: 9660314 | CV32: 10182785 | CW32: 10182785 | CX32: 10182785 | CY32: 10341874 | CZ32: 9584765 | DA32: 8277587 | DB32: 8277587 | DC32: 8027524 | DD32: 8983763 | DE32: 8983763 | DF32: 8983763 | DG32: 8983763 | DH32: 8983763 | DI32: 8402412 | DJ32: 8402412 | DK32: 8402412 | DL32: 8402412 | DM32: 7108557 | DN32: 6707203 | DO32: 6707203 | DP32: 9623696 | DQ32: 9643166 | DR32: 9643166 | DS32: 9643166 | DT32: 9643166 | DU32: 9643166 | DV32: 9643166 | DW32: 6911926 | DX32: 6911926 | DY32: 6911926 | DZ32: 5346460 | EA32: 5348904 | EB32: 5348904 | EC32: 7002032 | ED32: 7002032 | EE32: 7171646 | EF32: 7171646 | EG32: 6646025 | EH32: 6646025 | EI32: 6646025 | EJ32: 6646025 | EK32: 6646025 | EL32: 6646025 | EM32: 6646025 | EN32: 4403210 | EO32: 4403210 | EP32: 7819491 | EQ32: 8230260 | ER32: 10011051 | ES32: 10424875 | ET32: 10424875 | EU32: 10424875 | EV32: 10424875 | EW32: 10424875 | EX32: 10424875 | EY32: 10350160 | EZ32: 10350160 | FA32: 9544096 | FB32: 9544096 | FC32: 2323330 | FD32: 2323330 | FE32: 2323330 | FF32: 2323330 | FG32: 2764330 | FH32: 3209529 | FI32: 3209529 | FJ32: 3209529 | FK32: 3209529 | FL32: 3209529 | FM32: 3209529 | FN32: 3209529 | FO32: 3209529
B33: SERVIU Tarapacá | C33: 17762256 | D33: 17762256 | E33: 16843046 | F33: 15777268 | G33: 15328807 | H33: 15328807 | I33: 15328807 | J33: 14379335 | K33: 15106156 | L33: 12897017 | M33: 11231074 | N33: 10238076 | O33: 10238076 | P33: 21803885 | Q33: 22132341 | R33: 24937185 | S33: 25576034 | T33: 25728577 | U33: 25728577 | V33: 25905683 | W33: 25905683 | X33: 25905683 | Y33: 25735021 | Z33: 23856857 | AA33: 21579945 | AB33: 21579945 | AC33: 20753826 | AD33: 21247771 | AE33: 21247771 | AF33: 21247771 | AG33: 23956472 | AH33: 23956472 | AI33: 23956472 | AJ33: 23956472 | AK33: 23956472 | AL33: 23956472 | AM33: 22883013 | AN33: 21082046 | AO33: 21082046 | AP33: 19705469 | AQ33: 20496863 | AR33: 20496863 | AS33: 20496863 | AT33: 18696863 | AU33: 18438053 | AV33: 18192873 | AW33: 18242873 | AX33: 15496860 | AY33: 15917562 | AZ33: 14889946 | BA33: 13127480 | BB33: 13127480 | BC33: 20697782 | BD33: 21356232 | BE33: 21356232 | BF33: 21356232 | BG33: 21356232 | BH33: 21356232 | BI33: 21356232 | BJ33: 22033428 | BK33: 22033428 | BL33: 17880851 | BM33: 17880851 | BN33: 12103850 | BO33: 12103850 | BP33: 12609240 | BQ33: 13569680 | BR33: 13633063 | BS33: 13836663 | BT33: 13916153 | BU33: 14370533 | BV33: 15029835 | BW33: 15029835 | BX33: 15029835 | BY33: 15029835 | BZ33: 15029835 | CA33: 12459105 | CB33: 12459105 | CC33: 8704861 | CD33: 8704861 | CE33: 8704861 | CF33: 10539515 | CG33: 10539515 | CH33: 10539515 | CI33: 10539515 | CJ33: 10539515 | CK33: 10539515 | CL33: 11158228 | CM33: 11158228 | CN33: 10127399 | CO33: 10127399 | CP33: 10606403 | CQ33: 10981562 | CR33: 10981562 | CS33: 10981562 | CT33: 9508988 | CU33: 10027957 | CV33: 9376062 | CW33: 9426062 | CX33: 9426062 | CY33: 9426062 | CZ33: 8375529 | DA33: 5044955 | DB33: 5044955 | DC33: 4659283 | DD33: 8287823 | DE33: 8287823 | DF33: 8287823 | DG33: 8088031 | DH33: 9085876 | DI33: 8230787 | DJ33: 9146287 | DK33: 9160548 | DL33: 9229516 | DM33: 8217063 | DN33: 5987379 | DO33: 5987379 | DP33: 9013306 | DQ33: 9013306 | DR33: 9013306 | DS33: 9013306 | DT33: 9013306 | DU33: 9013306 | DV33: 9013306 | DW33: 9013306 | DX33: 9013306 | DY33: 9013306 | DZ33: 8829146 | EA33: 6845802 | EB33: 6845802 | EC33: 11846836 | ED33: 11846836 | EE33: 13988953 | EF33: 13988953 | EG33: 14532621 | EH33: 15344415 | EI33: 15354765 | EJ33: 15354765 | EK33: 15735185 | EL33: 15735185 | EM33: 15739683 | EN33: 8998445 | EO33: 8998445 | EP33: 9956278 | EQ33: 9956278 | ER33: 11346159 | ES33: 11346159 | ET33: 11346159 | EU33: 11544512 | EV33: 11544512 | EW33: 11544512 | EX33: 11544512 | EY33: 11559267 | EZ33: 11166267 | FA33: 10095312 | FB33: 10095312 | FC33: 8706346 | FD33: 8706346 | FE33: 8811028 | FF33: 8811028 | FG33: 9302509 | FH33: 9302509 | FI33: 9302509 | FJ33: 9302509 | FK33: 9302509 | FL33: 9302509 | FM33: 9302509 | FN33: 9302509 | FO33: 9302509
B34: SERVIU Antofagasta | C34: 8823051 | D34: 8823051 | E34: 9505842 | F34: 9505842 | G34: 9505842 | H34: 9505842 | I34: 9616562 | J34: 10028392 | K34: 10028392 | L34: 10048392 | M34: 10085392 | N34: 7373739 | O34: 7373739 | P34: 9265514 | Q34: 15060572 | R34: 19686983 | S34: 19686983 | T34: 16002928 | U34: 16002928 | V34: 16002928 | W34: 16002928 | X34: 16002928 | Y34: 16020518 | Z34: 16020518 | AA34: 15294380 | AB34: 15294380 | AC34: 17751422 | AD34: 27457900 | AE34: 27457900 | AF34: 27457900 | AG34: 27457900 | AH34: 27457900 | AI34: 26307220 | AJ34: 26307220 | AK34: 26307220 | AL34: 26209950 | AM34: 24799962 | AN34: 24193416 | AO34: 24193416 | AP34: 23414402 | AQ34: 24408861 | AR34: 23962611 | AS34: 23341783 | AT34: 23341783 | AU34: 22408598 | AV34: 18990965 | AW34: 18639711 | AX34: 17502371 | AY34: 17107364 | AZ34: 17068751 | BA34: 16553142 | BB34: 16553142 | BC34: 16518133 | BD34: 17451307 | BE34: 17451307 | BF34: 17451307 | BG34: 17451307 | BH34: 17451307 | BI34: 17451307 | BJ34: 17451307 | BK34: 17438995 | BL34: 16741821 | BM34: 16741821 | BN34: 14566468 | BO34: 14566468 | BP34: 9624594 | BQ34: 9624594 | BR34: 10797605 | BS34: 10797605 | BT34: 11006605 | BU34: 12295984 | BV34: 15844488 | BW34: 15883036 | BX34: 15408225 | BY34: 15408225 | BZ34: 15408225 | CA34: 14279469 | CB34: 14279469 | CC34: 25370209 | CD34: 25370209 | CE34: 33570209 | CF34: 25324968 | CG34: 25324968 | CH34: 25324968 | CI34: 20467573 | CJ34: 20467573 | CK34: 21469756 | CL34: 21524754 | CM34: 21431831 | CN34: 17737601 | CO34: 17737601 | CP34: 41468112 | CQ34: 36245332 | CR34: 36663632 | CS34: 36698206 | CT34: 36732779 | CU34: 36266351 | CV34: 35758811 | CW34: 35758811 | CX34: 35758811 | CY34: 35859421 | CZ34: 34878248 | DA34: 29916675 | DB34: 29916675 | DC34: 35548395 | DD34: 41225450 | DE34: 41757245 | DF34: 41757245 | DG34: 41771744 | DH34: 41771744 | DI34: 41815242 | DJ34: 40323711 | DK34: 32895617 | DL34: 32895617 | DM34: 28719484 | DN34: 26431429 | DO34: 26431429 | DP34: 30263070 | DQ34: 31368555 | DR34: 31368555 | DS34: 31368555 | DT34: 31368555 | DU34: 31368555 | DV34: 31368555 | DW34: 31368555 | DX34: 31368555 | DY34: 31368555 | DZ34: 24948049 | EA34: 17979056 | EB34: 17979056 | EC34: 10878804 | ED34: 10878804 | EE34: 17648371 | EF34: 17845366 | EG34: 17871737 | EH34: 19717940 | EI34: 19717940 | EJ34: 19717940 | EK34: 19480742 | EL34: 19480742 | EM34: 18903775 | EN34: 15465604 | EO34: 15465604 | EP34: 13585888 | EQ34: 14789146 | ER34: 15123006 | ES34: 15123006 | ET34: 15123006 | EU34: 15123006 | EV34: 15123006 | EW34: 15123006 | EX34: 15123006 | EY34: 14248096 | EZ34: 14248096 | FA34: 12638840 | FB34: 12638840 | FC34: 13197867 | FD34: 12480252 | FE34: 12480252 | FF34: 12480252 | FG34: 14209379 | FH34: 14209379 | FI34: 14209379 | FJ34: 14209379 | FK34: 14209379 | FL34: 14209379 | FM34: 14209379 | FN34: 14209379 | FO34: 14209379
B35: SERVIU Atacama | C35: 5303372 | D35: 5303372 | E35: 6632621 | F35: 7095200 | G35: 8383749 | H35: 8383749 | I35: 8383749 | J35: 11541278 | K35: 11554154 | L35: 11554154 | M35: 11593154 | N35: 9346642 | O35: 9346642 | P35: 10483676 | Q35: 11262255 | R35: 11262255 | S35: 11262255 | T35: 11262255 | U35: 11262255 | V35: 11262255 | W35: 11036169 | X35: 11036169 | Y35: 11036169 | Z35: 10916856 | AA35: 4089941 | AB35: 4089941 | AC35: 7956960 | AD35: 9020805 | AE35: 10052277 | AF35: 10052277 | AG35: 10154821 | AH35: 10154821 | AI35: 10220130 | AJ35: 14581092 | AK35: 14581092 | AL35: 14581092 | AM35: 14581092 | AN35: 14433260 | AO35: 14433260 | AP35: 22558714 | AQ35: 23324716 | AR35: 23324716 | AS35: 23324716 | AT35: 27372752 | AU35: 24657172 | AV35: 24657172 | AW35: 24721802 | AX35: 24721802 | AY35: 24737302 | AZ35: 24615368 | BA35: 19553460 | BB35: 19553460 | BC35: 26064643 | BD35: 26628701 | BE35: 26536361 | BF35: 23620186 | BG35: 23620186 | BH35: 20766385 | BI35: 19983496 | BJ35: 18871332 | BK35: 18871332 | BL35: 17871332 | BM35: 17688332 | BN35: 15072183 | BO35: 15072183 | BP35: 16889432 | BQ35: 16889432 | BR35: 17238420 | BS35: 17238420 | BT35: 15942666 | BU35: 14567498 | BV35: 14533639 | BW35: 14542725 | BX35: 14294652 | BY35: 14294652 | BZ35: 14294652 | CA35: 14082606 | CB35: 14082606 | CC35: 17341145 | CD35: 17341145 | CE35: 17341145 | CF35: 18075017 | CG35: 18075017 | CH35: 18075017 | CI35: 18042642 | CJ35: 18042642 | CK35: 16389750 | CL35: 16389750 | CM35: 19659750 | CN35: 12812259 | CO35: 12812259 | CP35: 21129078 | CQ35: 22568239 | CR35: 22568239 | CS35: 22774239 | CT35: 22814239 | CU35: 22814239 | CV35: 22814239 | CW35: 23235030 | CX35: 23235030 | CY35: 23235030 | CZ35: 18518157 | DA35: 15731773 | DB35: 15731773 | DC35: 24875325 | DD35: 31089481 | DE35: 27688501 | DF35: 27688501 | DG35: 27688501 | DH35: 27688501 | DI35: 25851245 | DJ35: 25851245 | DK35: 25846245 | DL35: 25846245 | DM35: 19964707 | DN35: 18388246 | DO35: 18388246 | DP35: 21315123 | DQ35: 21455123 | DR35: 21455123 | DS35: 21455123 | DT35: 22632742 | DU35: 22632742 | DV35: 22688742 | DW35: 22688742 | DX35: 22688742 | DY35: 22688742 | DZ35: 23118118 | EA35: 24322778 | EB35: 24322778 | EC35: 21518444 | ED35: 21518444 | EE35: 17812520 | EF35: 17812520 | EG35: 17812520 | EH35: 17812520 | EI35: 17812520 | EJ35: 17812520 | EK35: 17188321 | EL35: 17188321 | EM35: 17188321 | EN35: 8570431 | EO35: 8570431 | EP35: 24183340 | EQ35: 24535980 | ER35: 24535980 | ES35: 24535980 | ET35: 24535980 | EU35: 23536162 | EV35: 20536162 | EW35: 20536162 | EX35: 20536162 | EY35: 20589662 | EZ35: 20589662 | FA35: 15483238 | FB35: 15483238 | FC35: 9416801 | FD35: 5916801 | FE35: 5916801 | FF35: 5916801 | FG35: 5916801 | FH35: 9175869 | FI35: 9175869 | FJ35: 9175869 | FK35: 9175869 | FL35: 9175869 | FM35: 9175869 | FN35: 9175869 | FO35: 9175869
B36: SERVIU Coquimbo | C36: 16064354 | D36: 16064354 | E36: 16064354 | F36: 16064354 | G36: 14464354 | H36: 14438110 | I36: 14199670 | J36: 13832426 | K36: 14068983 | L36: 14068983 | M36: 14068983 | N36: 15762470 | O36: 15762470 | P36: 19283793 | Q36: 19861023 | R36: 19863023 | S36: 19930814 | T36: 21712910 | U36: 21712910 | V36: 21836318 | W36: 16295088 | X36: 16277488 | Y36: 16228128 | Z36: 16228128 | AA36: 13034803 | AB36: 13034803 | AC36: 18570059 | AD36: 18623459 | AE36: 18623459 | AF36: 18700786 | AG36: 18988098 | AH36: 18988098 | AI36: 19620339 | AJ36: 19149477 | AK36: 19149477 | AL36: 19158377 | AM36: 18658871 | AN36: 18073209 | AO36: 18073209 | AP36: 27391856 | AQ36: 27433256 | AR36: 27433256 | AS36: 26321074 | AT36: 22321074 | AU36: 20513352 | AV36: 21017110 | AW36: 21017110 | AX36: 21113163 | AY36: 21230101 | AZ36: 20389893 | BA36: 20127284 | BB36: 20127284 | BC36: 16967208 | BD36: 17005608 | BE36: 17005608 | BF36: 17005608 | BG36: 17005608 | BH36: 20812835 | BI36: 20864674 | BJ36: 20948585 | BK36: 20948585 | BL36: 20927435 | BM36: 20927435 | BN36: 16701870 | BO36: 16701870 | BP36: 14997280 | BQ36: 14997280 | BR36: 15034080 | BS36: 15034080 | BT36: 15034080 | BU36: 15034080 | BV36: 14052695 | BW36: 14059646 | BX36: 14106446 | BY36: 14106446 | BZ36: 14106446 | CA36: 11002790 | CB36: 11002790 | CC36: 15408322 | CD36: 15408322 | CE36: 15408322 | CF36: 14908322 | CG36: 14908322 | CH36: 14908322 | CI36: 15293629 | CJ36: 15293629 | CK36: 15385629 | CL36: 15390229 | CM36: 15390229 | CN36: 11446802 | CO36: 11446802 | CP36: 22488189 | CQ36: 20626973 | CR36: 18390489 | CS36: 18727330 | CT36: 19034787 | CU36: 19143744 | CV36: 19143744 | CW36: 19143744 | CX36: 19561023 | CY36: 19561023 | CZ36: 19550402 | DA36: 12602298 | DB36: 12602298 | DC36: 29291800 | DD36: 34195489 | DE36: 34195489 | DF36: 34195489 | DG36: 34245489 | DH36: 34245489 | DI36: 34245489 | DJ36: 34245489 | DK36: 34062778 | DL36: 33922765 | DM36: 25336066 | DN36: 12697850 | DO36: 12697850 | DP36: 36352142 | DQ36: 36370290 | DR36: 36370290 | DS36: 36370290 | DT36: 36370290 | DU36: 36361716 | DV36: 36391716 | DW36: 36391716 | DX36: 36391716 | DY36: 36391716 | DZ36: 35187465 | EA36: 21098315 | EB36: 21098315 | EC36: 38254690 | ED36: 38254690 | EE36: 38299930 | EF36: 38299930 | EG36: 37058319 | EH36: 31127009 | EI36: 31127009 | EJ36: 31127009 | EK36: 30852784 | EL36: 31053963 | EM36: 27696869 | EN36: 18466482 | EO36: 18466482 | EP36: 27966487 | EQ36: 27966487 | ER36: 27966487 | ES36: 27966487 | ET36: 27966487 | EU36: 27958887 | EV36: 27958887 | EW36: 27958887 | EX36: 27958887 | EY36: 24576889 | EZ36: 24265859 | FA36: 18613719 | FB36: 18613719 | FC36: 30615904 | FD36: 26615904 | FE36: 26615904 | FF36: 26615904 | FG36: 26615904 | FH36: 24556836 | FI36: 24556836 | FJ36: 24556836 | FK36: 24556836 | FL36: 24556836 | FM36: 24556836 | FN36: 24556836 | FO36: 24556836
B37: SERVIU Valparaíso | C37: 18833256 | D37: 18833256 | E37: 23731558 | F37: 23731558 | G37: 25990242 | H37: 26046751 | I37: 26046751 | J37: 27425407 | K37: 27959179 | L37: 29929355 | M37: 29929355 | N37: 26931572 | O37: 26931572 | P37: 34473321 | Q37: 38317295 | R37: 38317295 | S37: 38317295 | T37: 38317295 | U37: 38495890 | V37: 38495890 | W37: 38495890 | X37: 38495890 | Y37: 37978006 | Z37: 38164607 | AA37: 35142226 | AB37: 35142226 | AC37: 32958542 | AD37: 37919651 | AE37: 37919651 | AF37: 37919651 | AG37: 38074183 | AH37: 38074183 | AI37: 34426571 | AJ37: 34544571 | AK37: 34544571 | AL37: 31386419 | AM37: 31411870 | AN37: 30142222 | AO37: 30142222 | AP37: 41283218 | AQ37: 46964338 | AR37: 46589212 | AS37: 46589212 | AT37: 44014691 | AU37: 44463135 | AV37: 45427885 | AW37: 44378695 | AX37: 44387659 | AY37: 44297659 | AZ37: 41556873 | BA37: 38915790 | BB37: 38915790 | BC37: 30569054 | BD37: 33820152 | BE37: 33820152 | BF37: 33820152 | BG37: 33820152 | BH37: 33820152 | BI37: 33758144 | BJ37: 33477644 | BK37: 33130707 | BL37: 31630707 | BM37: 31606728 | BN37: 27912775 | BO37: 27912775 | BP37: 28738435 | BQ37: 28738435 | BR37: 32660016 | BS37: 32660016 | BT37: 32660016 | BU37: 32660016 | BV37: 32278214 | BW37: 32282208 | BX37: 32453284 | BY37: 32453284 | BZ37: 32453284 | CA37: 32820875 | CB37: 32820875 | CC37: 33362165 | CD37: 33362165 | CE37: 33362165 | CF37: 34938757 | CG37: 34938757 | CH37: 35708483 | CI37: 35948235 | CJ37: 35948235 | CK37: 35948235 | CL37: 37738172 | CM37: 35365279 | CN37: 34255045 | CO37: 34255045 | CP37: 62699377 | CQ37: 59024248 | CR37: 60396733 | CS37: 61299623 | CT37: 61366769 | CU37: 63349580 | CV37: 63349580 | CW37: 63259012 | CX37: 62320472 | CY37: 55598596 | CZ37: 55550496 | DA37: 41461609 | DB37: 41461609 | DC37: 43170852 | DD37: 52549754 | DE37: 52549754 | DF37: 52549754 | DG37: 52549754 | DH37: 52549754 | DI37: 52549754 | DJ37: 51105545 | DK37: 38395230 | DL37: 38337494 | DM37: 36725387 | DN37: 35464491 | DO37: 35464491 | DP37: 40478579 | DQ37: 42614131 | DR37: 42614131 | DS37: 42858620 | DT37: 42976422 | DU37: 43076422 | DV37: 43076422 | DW37: 44994598 | DX37: 44994598 | DY37: 44994598 | DZ37: 46728628 | EA37: 45394938 | EB37: 45394938 | EC37: 44262543 | ED37: 44262543 | EE37: 48159048 | EF37: 48159048 | EG37: 48260848 | EH37: 48260848 | EI37: 48260848 | EJ37: 52963275 | EK37: 54672379 | EL37: 54187315 | EM37: 52019214 | EN37: 37750186 | EO37: 37750186 | EP37: 42009797 | EQ37: 52978932 | ER37: 54382452 | ES37: 56213503 | ET37: 56213503 | EU37: 56953012 | EV37: 56953012 | EW37: 56953012 | EX37: 56953012 | EY37: 57115499 | EZ37: 57115499 | FA37: 58076198 | FB37: 58076198 | FC37: 55214851 | FD37: 55906268 | FE37: 56878200 | FF37: 56878200 | FG37: 59441918 | FH37: 59526130 | FI37: 59526130 | FJ37: 59526130 | FK37: 59526130 | FL37: 59526130 | FM37: 59526130 | FN37: 59526130 | FO37: 59526130
B38: SERVIU Metropolitano | C38: 58929368 | D38: 58929368 | E38: 61299428 | F38: 61299428 | G38: 61035428 | H38: 68835428 | I38: 68835428 | J38: 68835428 | K38: 66996084 | L38: 66996084 | M38: 64608849 | N38: 58609167 | O38: 58609167 | P38: 63938761 | Q38: 66340139 | R38: 66340139 | S38: 66340139 | T38: 69049481 | U38: 69091853 | V38: 69091853 | W38: 69100103 | X38: 69375103 | Y38: 75090311 | Z38: 78353961 | AA38: 78751322 | AB38: 78751322 | AC38: 60602895 | AD38: 63153473 | AE38: 63153473 | AF38: 63153473 | AG38: 64307218 | AH38: 64307218 | AI38: 64178967 | AJ38: 64060967 | AK38: 64060967 | AL38: 63775967 | AM38: 63749839 | AN38: 62651641 | AO38: 62651641 | AP38: 56615435 | AQ38: 62385158 | AR38: 62385158 | AS38: 62385158 | AT38: 67437677 | AU38: 68574813 | AV38: 68574813 | AW38: 68596763 | AX38: 69045256 | AY38: 68724707 | AZ38: 68359363 | BA38: 66642401 | BB38: 66642401 | BC38: 45393646 | BD38: 48998646 | BE38: 48998646 | BF38: 51246966 | BG38: 51246966 | BH38: 55888503 | BI38: 56119392 | BJ38: 56287885 | BK38: 56578626 | BL38: 60353589 | BM38: 60242577 | BN38: 58209053 | BO38: 58209053 | BP38: 50282027 | BQ38: 50282027 | BR38: 53009671 | BS38: 53009671 | BT38: 53009671 | BU38: 57977327 | BV38: 58340687 | BW38: 58388581 | BX38: 58458181 | BY38: 58458181 | BZ38: 58084101 | CA38: 51683997 | CB38: 51683997 | CC38: 68935312 | CD38: 68935312 | CE38: 68935312 | CF38: 75620186 | CG38: 75620186 | CH38: 75844049 | CI38: 80679015 | CJ38: 80679015 | CK38: 80774930 | CL38: 79030699 | CM38: 77186172 | CN38: 64493832 | CO38: 64493832 | CP38: 121451476 | CQ38: 129722304 | CR38: 126707424 | CS38: 126938685 | CT38: 132323787 | CU38: 128389149 | CV38: 125484432 | CW38: 125153718 | CX38: 123524150 | CY38: 122714026 | CZ38: 109967510 | DA38: 95169709 | DB38: 95169709 | DC38: 100098472 | DD38: 121303403 | DE38: 121303403 | DF38: 120570587 | DG38: 120556703 | DH38: 119765730 | DI38: 120443102 | DJ38: 118390115 | DK38: 118390115 | DL38: 115077894 | DM38: 101166870 | DN38: 94520917 | DO38: 94520917 | DP38: 105488522 | DQ38: 108633999 | DR38: 108633999 | DS38: 108633999 | DT38: 108633999 | DU38: 108774999 | DV38: 108897149 | DW38: 108897149 | DX38: 108897149 | DY38: 108897149 | DZ38: 92376604 | EA38: 73346177 | EB38: 73346177 | EC38: 87253576 | ED38: 87253576 | EE38: 93927139 | EF38: 93927139 | EG38: 94027910 | EH38: 94051385 | EI38: 96196920 | EJ38: 101535195 | EK38: 101582093 | EL38: 101562510 | EM38: 100432485 | EN38: 86087430 | EO38: 86087430 | EP38: 74587862 | EQ38: 76570114 | ER38: 76595114 | ES38: 76595114 | ET38: 76595114 | EU38: 80153860 | EV38: 80153860 | EW38: 80153860 | EX38: 80153860 | EY38: 80236491 | EZ38: 80236491 | FA38: 81413921 | FB38: 81413921 | FC38: 90590002 | FD38: 90590002 | FE38: 90590002 | FF38: 90590002 | FG38: 92970431 | FH38: 92970431 | FI38: 93624803 | FJ38: 93624803 | FK38: 93624803 | FL38: 93624803 | FM38: 93624803 | FN38: 93624803 | FO38: 93624803
B39: SERVIU O'Higgins | C39: 26277535 | D39: 26277535 | E39: 26748312 | F39: 26748312 | G39: 26748312 | H39: 26748312 | I39: 26748312 | J39: 26726738 | K39: 26292618 | L39: 26329678 | M39: 26998781 | N39: 24040927 | O39: 24040927 | P39: 18864208 | Q39: 19338496 | R39: 19338496 | S39: 19338496 | T39: 19338496 | U39: 19524220 | V39: 19524220 | W39: 19839063 | X39: 19845063 | Y39: 19607579 | Z39: 19607579 | AA39: 17888887 | AB39: 17888887 | AC39: 16417514 | AD39: 16997144 | AE39: 16997144 | AF39: 16997144 | AG39: 17037144 | AH39: 17037144 | AI39: 16028382 | AJ39: 16028382 | AK39: 16028382 | AL39: 16175789 | AM39: 16038369 | AN39: 13977385 | AO39: 13977385 | AP39: 7822380 | AQ39: 10397259 | AR39: 11033081 | AS39: 11363963 | AT39: 12077458 | AU39: 13068971 | AV39: 12819084 | AW39: 12819084 | AX39: 13047301 | AY39: 12557081 | AZ39: 12476081 | BA39: 12055519 | BB39: 12055519 | BC39: 14195819 | BD39: 14956513 | BE39: 14956513 | BF39: 14956513 | BG39: 14956513 | BH39: 14956513 | BI39: 15542566 | BJ39: 15677746 | BK39: 15677746 | BL39: 15677746 | BM39: 15677746 | BN39: 14104034 | BO39: 14104034 | BP39: 10934837 | BQ39: 10934837 | BR39: 11287404 | BS39: 11287404 | BT39: 11287404 | BU39: 9987404 | BV39: 9197242 | BW39: 12512242 | BX39: 12589806 | BY39: 12589806 | BZ39: 12589806 | CA39: 12717694 | CB39: 12717694 | CC39: 12638831 | CD39: 12638831 | CE39: 14888831 | CF39: 15345095 | CG39: 15345095 | CH39: 15345095 | CI39: 15345095 | CJ39: 15345095 | CK39: 15345095 | CL39: 16871832 | CM39: 16871832 | CN39: 14102964 | CO39: 14102964 | CP39: 14249499 | CQ39: 10546312 | CR39: 12796312 | CS39: 15015842 | CT39: 15685395 | CU39: 15785389 | CV39: 15787719 | CW39: 15831289 | CX39: 16583631 | CY39: 16483631 | CZ39: 13839062 | DA39: 9678227 | DB39: 9678227 | DC39: 11870060 | DD39: 13917678 | DE39: 14847860 | DF39: 14847860 | DG39: 14847860 | DH39: 15300817 | DI39: 15300817 | DJ39: 16297538 | DK39: 16297538 | DL39: 16297538 | DM39: 11021810 | DN39: 7220234 | DO39: 7220234 | DP39: 16473882 | DQ39: 16473882 | DR39: 16473882 | DS39: 16473882 | DT39: 16473882 | DU39: 16649669 | DV39: 16649669 | DW39: 16649669 | DX39: 16649669 | DY39: 16649669 | DZ39: 16911235 | EA39: 9607053 | EB39: 9607053 | EC39: 16690085 | ED39: 16690085 | EE39: 16690085 | EF39: 16556501 | EG39: 14974879 | EH39: 14803771 | EI39: 12925518 | EJ39: 12925518 | EK39: 11911329 | EL39: 12498650 | EM39: 12535400 | EN39: 5515173 | EO39: 5515173 | EP39: 17865780 | EQ39: 17865780 | ER39: 17865780 | ES39: 17865780 | ET39: 17865780 | EU39: 17865780 | EV39: 17865780 | EW39: 17865780 | EX39: 17865780 | EY39: 16353696 | EZ39: 14508227 | FA39: 9555042 | FB39: 9555042 | FC39: 14196992 | FD39: 14196992 | FE39: 14196992 | FF39: 14196992 | FG39: 14196992 | FH39: 14707834 | FI39: 15769553 | FJ39: 15769553 | FK39: 15769553 | FL39: 15769553 | FM39: 15769553 | FN39: 15769553 | FO39: 15769553
B40: SERVIU Maule | C40: 18959297 | D40: 18959297 | E40: 19317682 | F40: 19317682 | G40: 19317682 | H40: 19317682 | I40: 19317682 | J40: 17427743 | K40: 14211891 | L40: 14221791 | M40: 11511175 | N40: 11912008 | O40: 11912008 | P40: 28078883 | Q40: 27662312 | R40: 24925916 | S40: 23490672 | T40: 23490672 | U40: 23701391 | V40: 24524439 | W40: 24586738 | X40: 24586738 | Y40: 24586738 | Z40: 24583209 | AA40: 22379587 | AB40: 22379587 | AC40: 27091258 | AD40: 27371836 | AE40: 27371836 | AF40: 27371836 | AG40: 24871836 | AH40: 24871836 | AI40: 25203264 | AJ40: 25203264 | AK40: 25203264 | AL40: 25363764 | AM40: 25363764 | AN40: 25497404 | AO40: 25497404 | AP40: 41060039 | AQ40: 41469511 | AR40: 41469511 | AS40: 41469511 | AT40: 36763321 | AU40: 38373607 | AV40: 37223431 | AW40: 33725901 | AX40: 33390089 | AY40: 32241794 | AZ40: 32210326 | BA40: 26016012 | BB40: 26016012 | BC40: 44459639 | BD40: 44483207 | BE40: 44483207 | BF40: 44483207 | BG40: 44483207 | BH40: 44483207 | BI40: 44459639 | BJ40: 44459639 | BK40: 44459639 | BL40: 41459639 | BM40: 41459639 | BN40: 29944592 | BO40: 29944592 | BP40: 36664986 | BQ40: 35704546 | BR40: 35704546 | BS40: 35704546 | BT40: 35704546 | BU40: 34871320 | BV40: 33717390 | BW40: 34207244 | BX40: 33707244 | BY40: 33707244 | BZ40: 33617481 | CA40: 30614544 | CB40: 30614544 | CC40: 28819307 | CD40: 28819307 | CE40: 28819307 | CF40: 29046589 | CG40: 29046589 | CH40: 29046589 | CI40: 29046589 | CJ40: 29046589 | CK40: 29447160 | CL40: 29447160 | CM40: 29374095 | CN40: 23515061 | CO40: 23515061 | CP40: 38209083 | CQ40: 41100597 | CR40: 41100597 | CS40: 39600597 | CT40: 39025073 | CU40: 37516423 | CV40: 37516423 | CW40: 37460264 | CX40: 38573604 | CY40: 37732094 | CZ40: 32604846 | DA40: 24635036 | DB40: 24635036 | DC40: 41575245 | DD40: 44644684 | DE40: 44911603 | DF40: 44911603 | DG40: 44911603 | DH40: 44911603 | DI40: 44911603 | DJ40: 44911603 | DK40: 37982134 | DL40: 39377760 | DM40: 27569422 | DN40: 20988334 | DO40: 20988334 | DP40: 34076619 | DQ40: 34076619 | DR40: 34076619 | DS40: 34076619 | DT40: 34076619 | DU40: 34076619 | DV40: 34076619 | DW40: 34076619 | DX40: 34076619 | DY40: 34076619 | DZ40: 26897358 | EA40: 16700770 | EB40: 16700770 | EC40: 28318956 | ED40: 28318956 | EE40: 28318956 | EF40: 28318956 | EG40: 28007698 | EH40: 28007698 | EI40: 26950239 | EJ40: 26950239 | EK40: 26321544 | EL40: 26321544 | EM40: 26138228 | EN40: 20053849 | EO40: 20053849 | EP40: 30628977 | EQ40: 30628977 | ER40: 30628977 | ES40: 30628977 | ET40: 30628977 | EU40: 30628977 | EV40: 27628977 | EW40: 27628977 | EX40: 27628977 | EY40: 24859588 | EZ40: 24859588 | FA40: 17628176 | FB40: 17628176 | FC40: 25030745 | FD40: 25030745 | FE40: 25030745 | FF40: 25030745 | FG40: 25030745 | FH40: 24845745 | FI40: 24845745 | FJ40: 24845745 | FK40: 24845745 | FL40: 24845745 | FM40: 24845745 | FN40: 24845745 | FO40: 24845745
B41: SERVIU Ñuble | C41: 0 | D41: 0 | E41: 0 | F41: 0 | G41: 0 | H41: 0 | I41: 0 | J41: 0 | K41: 0 | L41: 0 | M41: 0 | N41: 0 | O41: 0 | P41: 0 | Q41: 0 | R41: 0 | S41: 0 | T41: 0 | U41: 0 | V41: 0 | W41: 0 | X41: 0 | Y41: 0 | Z41: 0 | AA41: 0 | AB41: 0 | AC41: 0 | AD41: 0 | AE41: 0 | AF41: 0 | AG41: 0 | AH41: 0 | AI41: 0 | AJ41: 0 | AK41: 0 | AL41: 0 | AM41: 0 | AN41: 0 | AO41: 0 | AP41: 0 | AQ41: 0 | AR41: 0 | AS41: 0 | AT41: 0 | AU41: 0 | AV41: 0 | AW41: 0 | AX41: 0 | AY41: 0 | AZ41: 0 | BA41: 0 | BB41: 0 | BC41: 0 | BD41: 0 | BE41: 0 | BF41: 0 | BG41: 0 | BH41: 0 | BI41: 0 | BJ41: 0 | BK41: 0 | BL41: 0 | BM41: 0 | BN41: 0 | BO41: 0 | BP41: 3063155 | BQ41: 3063155 | BR41: 3063155 | BS41: 3063155 | BT41: 3063155 | BU41: 3063155 | BV41: 3063155 | BW41: 3018835 | BX41: 2944526 | BY41: 2944526 | BZ41: 2944526 | CA41: 1577035 | CB41: 1577035 | CC41: 7620030 | CD41: 7620030 | CE41: 7620030 | CF41: 7620030 | CG41: 7620030 | CH41: 7620030 | CI41: 9971216 | CJ41: 9971216 | CK41: 10446130 | CL41: 10481188 | CM41: 10481188 | CN41: 8072817 | CO41: 8072817 | CP41: 26096695 | CQ41: 30290020 | CR41: 30290020 | CS41: 29448401 | CT41: 31148401 | CU41: 30456420 | CV41: 30468420 | CW41: 30456420 | CX41: 30456420 | CY41: 30456420 | CZ41: 27581404 | DA41: 24250403 | DB41: 24250403 | DC41: 36920320 | DD41: 39555349 | DE41: 39555349 | DF41: 40193554 | DG41: 40193554 | DH41: 39518691 | DI41: 37297808 | DJ41: 37247808 | DK41: 31996367 | DL41: 31996367 | DM41: 21418055 | DN41: 20235644 | DO41: 20235644 | DP41: 23700733 | DQ41: 23700733 | DR41: 23700733 | DS41: 24725452 | DT41: 24923952 | DU41: 24923952 | DV41: 24923952 | DW41: 24923952 | DX41: 24923952 | DY41: 24923952 | DZ41: 25399952 | EA41: 23943054 | EB41: 23943054 | EC41: 23113535 | ED41: 23113535 | EE41: 23113535 | EF41: 23113535 | EG41: 23113535 | EH41: 25829486 | EI41: 26688903 | EJ41: 26688903 | EK41: 25705903 | EL41: 25705903 | EM41: 25705903 | EN41: 19120001 | EO41: 19120001 | EP41: 22079448 | EQ41: 22079448 | ER41: 22079448 | ES41: 22079448 | ET41: 22234448 | EU41: 22234448 | EV41: 22234448 | EW41: 22234448 | EX41: 22234448 | EY41: 21553827 | EZ41: 21553827 | FA41: 21538828 | FB41: 21538828 | FC41: 24086756 | FD41: 21586756 | FE41: 21586756 | FF41: 21586756 | FG41: 21586756 | FH41: 21586756 | FI41: 20525037 | FJ41: 20525037 | FK41: 20525037 | FL41: 20525037 | FM41: 20525037 | FN41: 20525037 | FO41: 20525037
... B47: SERVIU Magallanes | C47: 11406728 | D47: 11406728 | E47: 11596054 | F47: 11596054 | G47: 10709092 | H47: 10709092 | I47: 10709092 | J47: 9709092 | K47: 10655843 | L47: 9272796 | M47: 9608738 | N47: 10205658 | O47: 10205658 | P47: 8619188 | Q47: 8726852 | R47: 8726852 | S47: 8071780 | T47: 7220648 | U47: 6876938 | V47: 6876938 | W47: 6876938 | X47: 6876938 | Y47: 7319883 | Z47: 7330434 | AA47: 7353631 | AB47: 7353631 | AC47: 8177486 | AD47: 8615461 | AE47: 8615461 | AF47: 8615461 | AG47: 6799663 | AH47: 6799663 | AI47: 7307245 | AJ47: 7307245 | AK47: 7307245 | AL47: 7205749 | AM47: 7205749 | AN47: 6998201 | AO47: 6998201 | AP47: 10756255 | AQ47: 11373660 | AR47: 12022669 | AS47: 12197769 | AT47: 12911553 | AU47: 12911553 | AV47: 12911553 | AW47: 12911553 | AX47: 12921162 | AY47: 12855946 | AZ47: 12334496 | BA47: 12237771 | BB47: 12237771 | BC47: 11496808 | BD47: 11867162 | BE47: 11867162 | BF47: 11867162 | BG47: 11867162 | BH47: 11867162 | BI47: 11497185 | BJ47: 11497185 | BK47: 11497185 | BL47: 10297185 | BM47: 10066422 | BN47: 8367091 | BO47: 8367091 | BP47: 15389832 | BQ47: 15389832 | BR47: 15190745 | BS47: 14987145 | BT47: 14987145 | BU47: 13966788 | BV47: 13944098 | BW47: 13375246 | BX47: 12516314 | BY47: 12516314 | BZ47: 12516314 | CA47: 11596560 | CB47: 11596560 | CC47: 12031468 | CD47: 12031468 | CE47: 12031468 | CF47: 12837885 | CG47: 12837885 | CH47: 12837885 | CI47: 12837885 | CJ47: 12837885 | CK47: 12837885 | CL47: 11333156 | CM47: 11333156 | CN47: 9230697 | CO47: 9230697 | CP47: 11914112 | CQ47: 11776677 | CR47: 11776677 | CS47: 11777475 | CT47: 11777475 | CU47: 13201459 | CV47: 13201459 | CW47: 13201459 | CX47: 13201459 | CY47: 14214829 | CZ47: 12939967 | DA47: 10741343 | DB47: 10741343 | DC47: 14902342 | DD47: 19316051 | DE47: 19316051 | DF47: 19316051 | DG47: 19244386 | DH47: 19174386 | DI47: 16328330 | DJ47: 16328330 | DK47: 16328330 | DL47: 16328330 | DM47: 12234667 | DN47: 9450641 | DO47: 9450641 | DP47: 22127832 | DQ47: 22959758 | DR47: 22959758 | DS47: 22959758 | DT47: 24837247 | DU47: 24837247 | DV47: 24837247 | DW47: 24837247 | DX47: 24837247 | DY47: 24837247 | DZ47: 24074302 | EA47: 13086048 | EB47: 13086048 | EC47: 22256093 | ED47: 22256093 | EE47: 22256093 | EF47: 22256093 | EG47: 22356143 | EH47: 23540375 | EI47: 23790875 | EJ47: 23790875 | EK47: 22870441 | EL47: 22870441 | EM47: 20253560 | EN47: 17985481 | EO47: 17985481 | EP47: 21184028 | EQ47: 21881248 | ER47: 21881248 | ES47: 21881248 | ET47: 21881248 | EU47: 14331165 | EV47: 14331165 | EW47: 14331165 | EX47: 14331165 | EY47: 14275594 | EZ47: 14275594 | FA47: 14465044 | FB47: 14465044 | FC47: 24770394 | FD47: 24770394 | FE47: 24770394 | FF47: 24770394 | FG47: 25550699 | FH47: 25550699 | FI47: 26178453 | FJ47: 26178453 | FK47: 26178453 | FL47: 26178453 | FM47: 26178453 | FN47: 26178453 | FO47: 26178453
B48: Total Presupuesto Vigente (Subtítulo 31) | C48: =SUM(C30:C47) -> 350781874 | D48: =SUM(D30:D47) -> 350781874 | E48: =SUM(E30:E47) -> 352072796 | F48: =SUM(F30:F47) -> 352072796 | G48: =SUM(G30:G47) -> 351719524 | H48: =SUM(H30:H47) -> 359519524 | I48: =SUM(I30:I47) -> 359519524 | J48: =SUM(J30:J47) -> 355194489 | ... FO48: =SUM(FO30:FO47) -> 466611123
B49: Ejecución Acumulada (Subtítulo 31)
C50: 2014 | P50: 2015 | AC50: 2016 | AP50: 2017 | BC50: 2018 | BP50: 2019 | CC50: 2020 | CP50: 2021 | DC50: 2022 | DP50: 2023 | EC50: 2024 | EP50: 2025 | FC50: 2026
B51: Programa / Entidad | C51: Ene | D51: Feb | E51: Mar | F51: Abr | G51: May | H51: Jun | I51: Jul | J51: Ago | K51: Sep | L51: Oct | M51: Nov | N51: Dic | O51: Total 2014 | P51: Ene | Q51: Feb | R51: Mar | S51: Abr | T51: May | U51: Jun | V51: Jul | W51: Ago | X51: Sep | Y51: Oct | Z51: Nov | AA51: Dic | AB51: Total 2015 | AC51: Ene | AD51: Feb | AE51: Mar | AF51: Abr | AG51: May | AH51: Jun | AI51: Jul | AJ51: Ago | AK51: Sep | AL51: Oct | AM51: Nov | AN51: Dic | AO51: Total 2016 | AP51: Ene | AQ51: Feb | AR51: Mar | AS51: Abr | AT51: May | AU51: Jun | AV51: Jul | AW51: Ago | AX51: Sep | AY51: Oct | AZ51: Nov | BA51: Dic | BB51: Total 2017 | BC51: Ene | BD51: Feb | BE51: Mar | BF51: Abr | BG51: May | BH51: Jun | BI51: Jul | BJ51: Ago | BK51: Sep | BL51: Oct | BM51: Nov | BN51: Dic | BO51: Total 2018 | BP51: Ene | BQ51: Feb | BR51: Mar | BS51: Abr | BT51: May | BU51: Jun | BV51: Jul | BW51: Ago | BX51: Sep | BY51: Oct | BZ51: Nov | CA51: Dic | CB51: Total 2019 | CC51: Ene | CD51: Feb | CE51: Mar | CF51: Abr | CG51: May | CH51: Jun | CI51: Jul | CJ51: Ago | CK51: Sep | CL51: Oct | CM51: Nov | CN51: Dic | CO51: Total 2020 | CP51: Ene | CQ51: Feb | CR51: Mar | CS51: Abr | CT51: May | CU51: Jun | CV51: Jul | CW51: Ago | CX51: Sep | CY51: Oct | CZ51: Nov | DA51: Dic | DB51: Total 2021 | DC51: Ene | DD51: Feb | DE51: Mar | DF51: Abr | DG51: May | DH51: Jun | DI51: Jul | DJ51: Ago | DK51: Sep | DL51: Oct | DM51: Nov | DN51: Dic | DO51: Total 2022 | DP51: Ene | DQ51: Feb | DR51: Mar | DS51: Abr | DT51: May | DU51: Jun | DV51: Jul | DW51: Ago | DX51: Sep | DY51: Oct | DZ51: Nov | EA51: Dic | EB51: Total 2023 | EC51: Ene | ED51: Feb | EE51: Mar | EF51: Abr | EG51: May | EH51: Jun | EI51: Jul | EJ51: Ago | EK51: Sep | EL51: Oct | EM51: Nov | EN51: Dic | EO51: Total 2024 | EP51: Ene | EQ51: Feb | ER51: Mar | ES51: Abr | ET51: May | EU51: Jun | EV51: Jul | EW51: Ago | EX51: Sep | EY51: Oct | EZ51: Nov | FA51: Dic | FB51: Total 2025 | FC51: Ene | FD51: Feb | FE51: Mar | FF51: Abr | FG51: May | FH51: Jun | FI51: Jul | FJ51: Ago | FK51: Sep | FL51: Oct | FM51: Nov | FN51: Dic | FO51: Total 2026
B52: Subsecretaría y Programas Centrales | C52: 0 | D52: 0 | E52: 5285526 | F52: 7623650 | G52: 9325202 | H52: 12053628 | I52: 13741951 | J52: 15547865 | K52: 17642904 | L52: 20087428 | M52: 21872533 | N52: 24973612 | O52: 24973612 | P52: 0 | Q52: 1758080 | R52: 4631663 | S52: 9239327 | T52: 12855540 | U52: 13605003 | V52: 14696740 | W52: 17668687 | X52: 17774175 | Y52: 21589336 | Z52: 26515869 | AA52: 27016469 | AB52: 27016469 | AC52: 0 | AD52: 1863635 | AE52: 6804559 | AF52: 7685073 | AG52: 9596517 | AH52: 15770650 | AI52: 16662929 | AJ52: 19835636 | AK52: 22980290 | AL52: 23070304 | AM52: 23979944 | AN52: 27734905 | AO52: 27734905 | AP52: 0 | AQ52: 3138006 | AR52: 5957303 | AS52: 9592357 | AT52: 12505841 | AU52: 15864053 | AV52: 16695010 | AW52: 19238755 | AX52: 21312957 | AY52: 24223205 | AZ52: 25481206 | BA52: 29097157 | BB52: 29097157 | BC52: 0 | BD52: 0 | BE52: 4912430 | BF52: 9544573 | BG52: 11637935 | BH52: 17194468 | BI52: 17302017 | BJ52: 20698610 | BK52: 24113608 | BL52: 26282403 | BM52: 27158567 | BN52: 30353278 | BO52: 30353278 | BP52: 0 | BQ52: 0 | BR52: 4719 | BS52: 12020540 | BT52: 14213957 | BU52: 18659162 | BV52: 22278794 | BW52: 24650799 | BX52: 26091556 | BY52: 29407809 | BZ52: 29702698 | CA52: 36560931 | CB52: 36560931 | CC52: 0 | CD52: 0 | CE52: 10363502 | CF52: 10363502 | CG52: 14129290 | CH52: 16729630 | CI52: 19583264 | CJ52: 21955379 | CK52: 25977625 | CL52: 28409070 | CM52: 30885382 | CN52: 35016199 | CO52: 35016199 | CP52: 0 | CQ52: 0 | CR52: 7994378 | CS52: 10551196 | CT52: 12133475 | CU52: 13900836 | CV52: 15529648 | CW52: 18642687 | CX52: 20263881 | CY52: 21873659 | CZ52: 22125896 | DA52: 26495705 | DB52: 26495705 | DC52: 0 | DD52: 2975466 | DE52: 6036009 | DF52: 7664334 | DG52: 7756822 | DH52: 10134446 | DI52: 10176894 | DJ52: 10261274 | DK52: 10365403 | DL52: 10441208 | DM52: 10657419 | DN52: 11364777 | DO52: 11364777 | DP52: 0 | DQ52: 0 | DR52: 114234 | DS52: 147709 | DT52: 159046 | DU52: 295667 | DV52: 389978 | DW52: 1558507 | DX52: 1630507 | DY52: 1760374 | DZ52: 1835548 | EA52: 2230114 | EB52: 2230114 | EC52: 0 | ED52: 0 | EE52: 32400 | EF52: 125776 | EG52: 162026 | EH52: 240908 | EI52: 382321 | EJ52: 420077 | EK52: 584298 | EL52: 593996 | EM52: 846439 | EN52: 1765056 | EO52: 1765056 | EP52: 0 | EQ52: 61271 | ER52: 185603 | ES52: 372200 | ET52: 416377 | EU52: 504460 | EV52: 639487 | EW52: 752002 | EX52: 889001 | EY52: 1218727 | EZ52: 1379310 | FA52: 1735258 | FB52: 1735258 | FC52: 0 | FD52: 0 | FE52: 50564 | FF52: 218816 | FG52: 272078 | FH52: 533936 | FI52: 570336 | FJ52: 570336 | FK52: 570336 | FL52: 570336 | FM52: 570336 | FN52: 570336 | FO52: 570336
B53: Parque Metropolitano (PARQUEMET) | C53: 0 | D53: 0 | E53: 0 | F53: 256695 | G53: 1260954 | H53: 2618062 | I53: 3986048 | J53: 4527877 | K53: 5436701 | L53: 6976481 | M53: 8024790 | N53: 11568395 | O53: 11568395 | P53: 0 | Q53: 322765 | R53: 1378821 | S53: 2177878 | T53: 3049262 | U53: 3932935 | V53: 4839319 | W53: 5752684 | X53: 6731018 | Y53: 8443169 | Z53: 11177887 | AA53: 15633949 | AB53: 15633949 | AC53: 0 | AD53: 0 | AE53: 1397625 | AF53: 2424727 | AG53: 3828005 | AH53: 5306869 | AI53: 6332630 | AJ53: 7366283 | AK53: 8793796 | AL53: 9939273 | AM53: 11474269 | AN53: 16092199 | AO53: 16092199 | AP53: 0 | AQ53: 0 | AR53: 1927192 | AS53: 3237441 | AT53: 4580771 | AU53: 5522467 | AV53: 6487674 | AW53: 7820014 | AX53: 9206115 | AY53: 10229331 | AZ53: 11747968 | BA53: 19044894 | BB53: 19044894 | BC53: 0 | BD53: 0 | BE53: 2198748 | BF53: 3728696 | BG53: 4969587 | BH53: 6569077 | BI53: 8047191 | BJ53: 9328596 | BK53: 11149426 | BL53: 12608747 | BM53: 14925555 | BN53: 20507070 | BO53: 20507070 | BP53: 0 | BQ53: 0 | BR53: 2831657 | BS53: 4478583 | BT53: 6002880 | BU53: 7735245 | BV53: 9298872 | BW53: 11042847 | BX53: 12872551 | BY53: 14394250 | BZ53: 17896272 | CA53: 22884058 | CB53: 22884058 | CC53: 0 | CD53: 0 | CE53: 588343 | CF53: 3131622 | CG53: 4375457 | CH53: 6605418 | CI53: 7545633 | CJ53: 9498861 | CK53: 10920638 | CL53: 13645794 | CM53: 17990560 | CN53: 23419360 | CO53: 23419360 | CP53: 0 | CQ53: 1171112 | CR53: 3667892 | CS53: 5314023 | CT53: 8604717 | CU53: 11006803 | CV53: 13224909 | CW53: 15113085 | CX53: 17014277 | CY53: 19236566 | CZ53: 22205739 | DA53: 30104947 | DB53: 30104947 | DC53: 0 | DD53: 0 | DE53: 2366484 | DF53: 5158610 | DG53: 7079239 | DH53: 8514428 | DI53: 9937938 | DJ53: 11990153 | DK53: 13116671 | DL53: 15670225 | DM53: 17891169 | DN53: 23304021 | DO53: 23304021 | DP53: 0 | DQ53: 0 | DR53: 1192161 | DS53: 4184056 | DT53: 6014243 | DU53: 7137880 | DV53: 8238265 | DW53: 10234742 | DX53: 11434458 | DY53: 13391619 | DZ53: 15333330 | EA53: 22175040 | EB53: 22175040 | EC53: 0 | ED53: 0 | EE53: 1896344 | EF53: 5284077 | EG53: 6718012 | EH53: 8302842 | EI53: 10078805 | EJ53: 11841574 | EK53: 13163862 | EL53: 14887407 | EM53: 17657413 | EN53: 27847917 | EO53: 27847917 | EP53: 0 | EQ53: 635911 | ER53: 3406026 | ES53: 5878280 | ET53: 8481842 | EU53: 10476165 | EV53: 14140348 | EW53: 17057587 | EX53: 18562941 | EY53: 23005910 | EZ53: 25814003 | FA53: 30105231 | FB53: 30105231 | FC53: 0 | FD53: 583993 | FE53: 2544487 | FF53: 5629990 | FG53: 7573202 | FH53: 9508871 | FI53: 13263584 | FJ53: 13263584 | FK53: 13263584 | FL53: 13263584 | FM53: 13263584 | FN53: 13263584 | FO53: 13263584
B54: SERVIU Arica y Parinacota | C54: 0 | D54: 0 | E54: 0 | F54: 2054367 | G54: 2583263 | H54: 3408811 | I54: 3904983 | J54: 4303686 | K54: 4555363 | L54: 4745995 | M54: 5001952 | N54: 5690901 | O54: 5690901 | P54: 0 | Q54: 164128 | R54: 925595 | S54: 1634433 | T54: 1979997 | U54: 2604169 | V54: 3542420 | W54: 3737700 | X54: 4302578 | Y54: 5028608 | Z54: 5405738 | AA54: 7710266 | AB54: 7710266 | AC54: 0 | AD54: 12041 | AE54: 879163 | AF54: 1352498 | AG54: 1759936 | AH54: 2662466 | AI54: 3279563 | AJ54: 3863945 | AK54: 4905144 | AL54: 5653125 | AM54: 6903824 | AN54: 9324466 | AO54: 9324466 | AP54: 13993 | AQ54: 1002548 | AR54: 2166432 | AS54: 3083123 | AT54: 3734900 | AU54: 4470668 | AV54: 4912013 | AW54: 5367062 | AX54: 6170211 | AY54: 6590801 | AZ54: 7243620 | BA54: 9183124 | BB54: 9183124 | BC54: 0 | BD54: 36023 | BE54: 783789 | BF54: 1280499 | BG54: 1473075 | BH54: 1994179 | BI54: 2457008 | BJ54: 3092368 | BK54: 3227844 | BL54: 3635695 | BM54: 4382661 | BN54: 5515395 | BO54: 5515395 | BP54: 0 | BQ54: 0 | BR54: 537679 | BS54: 856319 | BT54: 1230631 | BU54: 1430735 | BV54: 1557881 | BW54: 1557881 | BX54: 1800915 | BY54: 2325177 | BZ54: 2510532 | CA54: 3424320 | CB54: 3424320 | CC54: 0 | CD54: 0 | CE54: 503306 | CF54: 1123937 | CG54: 1223891 | CH54: 1247901 | CI54: 1533469 | CJ54: 1716612 | CK54: 2535782 | CL54: 3034585 | CM54: 4621279 | CN54: 5604121 | CO54: 5604121 | CP54: 0 | CQ54: 648709 | CR54: 1904633 | CS54: 2846329 | CT54: 3270884 | CU54: 4160146 | CV54: 4815337 | CW54: 5273290 | CX54: 5549560 | CY54: 6236240 | CZ54: 6513380 | DA54: 7993792 | DB54: 7993792 | DC54: 0 | DD54: 632251 | DE54: 1548551 | DF54: 2026879 | DG54: 2399749 | DH54: 2698831 | DI54: 3287207 | DJ54: 3824985 | DK54: 4204982 | DL54: 4737024 | DM54: 5184329 | DN54: 6402442 | DO54: 6402442 | DP54: 0 | DQ54: 88825 | DR54: 1327201 | DS54: 1567274 | DT54: 1930397 | DU54: 2366313 | DV54: 2511593 | DW54: 2832413 | DX54: 3220149 | DY54: 3379453 | DZ54: 4297388 | EA54: 5234499 | EB54: 5234499 | EC54: 0 | ED54: 79682 | EE54: 767871 | EF54: 942590 | EG54: 1175782 | EH54: 1342359 | EI54: 1467982 | EJ54: 1523593 | EK54: 1893335 | EL54: 2491130 | EM54: 3050438 | EN54: 4379123 | EO54: 4379123 | EP54: 0 | EQ54: 1989837 | ER54: 3034140 | ES54: 5235453 | ET54: 5730916 | EU54: 6001353 | EV54: 6911060 | EW54: 7598644 | EX54: 7724711 | EY54: 8136264 | EZ54: 8334765 | FA54: 9523479 | FB54: 9523479 | FC54: 0 | FD54: 6644 | FE54: 965714 | FF54: 1538483 | FG54: 1829965 | FH54: 1854335 | FI54: 1907383 | FJ54: 1907383 | FK54: 1907383 | FL54: 1907383 | FM54: 1907383 | FN54: 1907383 | FO54: 1907383
B55: SERVIU Tarapacá | C55: 0 | D55: 230079 | E55: 554197 | F55: 659268 | G55: 858794 | H55: 1131237 | I55: 1614132 | J55: 2469901 | K55: 4932352 | L55: 6316133 | M55: 7642879 | N55: 10117639 | O55: 10117639 | P55: 504240 | Q55: 1393208 | R55: 2266857 | S55: 3629294 | T55: 5189123 | U55: 6863268 | V55: 9017474 | W55: 9971246 | X55: 11690181 | Y55: 14244279 | Z55: 16239113 | AA55: 21373548 | AB55: 21373548 | AC55: 0 | AD55: 1214686 | AE55: 3132055 | AF55: 4537751 | AG55: 5521781 | AH55: 7009216 | AI55: 7475480 | AJ55: 8355475 | AK55: 10318775 | AL55: 11678934 | AM55: 14084565 | AN55: 20648322 | AO55: 20648322 | AP55: 0 | AQ55: 212229 | AR55: 886139 | AS55: 901022 | AT55: 1805085 | AU55: 2789351 | AV55: 4237344 | AW55: 5217585 | AX55: 5993135 | AY55: 6819502 | AZ55: 8730596 | BA55: 12987217 | BB55: 12987217 | BC55: 0 | BD55: 1055597 | BE55: 1984909 | BF55: 2799441 | BG55: 3625196 | BH55: 4438144 | BI55: 5122966 | BJ55: 5871374 | BK55: 6510876 | BL55: 7193808 | BM55: 7822921 | BN55: 10324534 | BO55: 10324534 | BP55: 0 | BQ55: 570428 | BR55: 1810034 | BS55: 2951374 | BT55: 3644448 | BU55: 4756337 | BV55: 5958119 | BW55: 6576824 | BX55: 7292191 | BY55: 8231643 | BZ55: 9805091 | CA55: 12289148 | CB55: 12289148 | CC55: 0 | CD55: 493216 | CE55: 1268021 | CF55: 2129749 | CG55: 2925614 | CH55: 4168246 | CI55: 4292186 | CJ55: 5136977 | CK55: 5171525 | CL55: 5641871 | CM55: 6171023 | CN55: 9331650 | CO55: 9331650 | CP55: 0 | CQ55: 0 | CR55: 497211 | CS55: 740154 | CT55: 1022513 | CU55: 1350754 | CV55: 1501503 | CW55: 2076982 | CX55: 2565253 | CY55: 3107965 | CZ55: 3314790 | DA55: 4616710 | DB55: 4616710 | DC55: 0 | DD55: 126651 | DE55: 635432 | DF55: 988815 | DG55: 1291329 | DH55: 1736798 | DI55: 2011354 | DJ55: 2365717 | DK55: 2608012 | DL55: 3139535 | DM55: 3632940 | DN55: 4718148 | DO55: 4718148 | DP55: 0 | DQ55: 496962 | DR55: 1030597 | DS55: 1804022 | DT55: 2547494 | DU55: 3426246 | DV55: 3822719 | DW55: 3998759 | DX55: 4365688 | DY55: 4761521 | DZ55: 5296665 | EA55: 6454032 | EB55: 6454032 | EC55: 0 | ED55: 278257 | EE55: 1460212 | EF55: 2026544 | EG55: 3382381 | EH55: 4039571 | EI55: 4959096 | EJ55: 5548527 | EK55: 5996201 | EL55: 6527522 | EM55: 6840220 | EN55: 8453266 | EO55: 8453266 | EP55: 0 | EQ55: 0 | ER55: 832107 | ES55: 2407636 | ET55: 3152766 | EU55: 4520387 | EV55: 5101149 | EW55: 5717562 | EX55: 6966959 | EY55: 7736069 | EZ55: 8038749 | FA55: 9624301 | FB55: 9624301 | FC55: 0 | FD55: 541326 | FE55: 1114843 | FF55: 1568397 | FG55: 1765260 | FH55: 2038550 | FI55: 2625513 | FJ55: 2625513 | FK55: 2625513 | FL55: 2625513 | FM55: 2625513 | FN55: 2625513 | FO55: 2625513
B56: SERVIU Antofagasta | C56: 0 | D56: 0 | E56: 782168 | F56: 1347474 | G56: 2057929 | H56: 2558180 | I56: 3023152 | J56: 3298170 | K56: 3661291 | L56: 4271463 | M56: 4852376 | N56: 6434888 | O56: 6434888 | P56: 4092 | Q56: 231030 | R56: 292954 | S56: 438063 | T56: 1150097 | U56: 2838907 | V56: 5269359 | W56: 6833676 | X56: 9619988 | Y56: 10577705 | Z56: 11526517 | AA56: 15277375 | AB56: 15277375 | AC56: 0 | AD56: 93224 | AE56: 3184391 | AF56: 5955836 | AG56: 7106655 | AH56: 8239649 | AI56: 10101551 | AJ56: 11484697 | AK56: 13222733 | AL56: 14644815 | AM56: 18321371 | AN56: 23727109 | AO56: 23727109 | AP56: 0 | AQ56: 431136 | AR56: 1409446 | AS56: 2578331 | AT56: 4041879 | AU56: 4928737 | AV56: 6001692 | AW56: 7767287 | AX56: 9432392 | AY56: 10906439 | AZ56: 12751249 | BA56: 16549920 | BB56: 16549920 | BC56: 0 | BD56: 0 | BE56: 1894797 | BF56: 4257525 | BG56: 5238310 | BH56: 6174209 | BI56: 7718160 | BJ56: 8850068 | BK56: 9750916 | BL56: 10313499 | BM56: 10907596 | BN56: 14472612 | BO56: 14472612 | BP56: 0 | BQ56: 0 | BR56: 910691 | BS56: 1409752 | BT56: 2594470 | BU56: 3418003 | BV56: 4795828 | BW56: 5858245 | BX56: 6134205 | BY56: 6963320 | BZ56: 7933750 | CA56: 13905907 | CB56: 13905907 | CC56: 0 | CD56: 0 | CE56: 1027541 | CF56: 1765767 | CG56: 2601093 | CH56: 3897536 | CI56: 5398997 | CJ56: 7404891 | CK56: 9612010 | CL56: 11450577 | CM56: 13012809 | CN56: 17324522 | CO56: 17324522 | CP56: 0 | CQ56: 0 | CR56: 2499943 | CS56: 4318568 | CT56: 6254394 | CU56: 7571113 | CV56: 9318475 | CW56: 10622011 | CX56: 13964985 | CY56: 17055081 | CZ56: 20311131 | DA56: 28537218 | DB56: 28537218 | DC56: 0 | DD56: 1414267 | DE56: 4639959 | DF56: 7376742 | DG56: 10550320 | DH56: 12910552 | DI56: 15794687 | DJ56: 17723139 | DK56: 20220438 | DL56: 21146568 | DM56: 22839279 | DN56: 25969095 | DO56: 25969095 | DP56: 0 | DQ56: 0 | DR56: 0 | DS56: 435496 | DT56: 2956834 | DU56: 5460342 | DV56: 6519105 | DW56: 7562017 | DX56: 9330345 | DY56: 9842292 | DZ56: 11078284 | EA56: 15477344 | EB56: 15477344 | EC56: 0 | ED56: 505204 | EE56: 1560549 | EF56: 4524550 | EG56: 5126981 | EH56: 6324528 | EI56: 7622316 | EJ56: 9015359 | EK56: 9506130 | EL56: 10219951 | EM56: 10681549 | EN56: 14221677 | EO56: 14221677 | EP56: 0 | EQ56: 15654 | ER56: 1221981 | ES56: 2116938 | ET56: 3506670 | EU56: 4366354 | EV56: 5588134 | EW56: 6509294 | EX56: 7740606 | EY56: 8339500 | EZ56: 9479079 | FA56: 12476694 | FB56: 12476694 | FC56: 0 | FD56: 0 | FE56: 2568599 | FF56: 3613313 | FG56: 4523333 | FH56: 5273951 | FI56: 5934564 | FJ56: 5934564 | FK56: 5934564 | FL56: 5934564 | FM56: 5934564 | FN56: 5934564 | FO56: 5934564
B57: SERVIU Atacama | C57: 0 | D57: 0 | E57: 1098458 | F57: 1933638 | G57: 3064609 | H57: 3908033 | I57: 4697968 | J57: 5347985 | K57: 5671589 | L57: 6239294 | M57: 7770834 | N57: 9209771 | O57: 9209771 | P57: 8999 | Q57: 24058 | R57: 260612 | S57: 416001 | T57: 608430 | U57: 893914 | V57: 1116618 | W57: 1237369 | X57: 1414943 | Y57: 1713679 | Z57: 1972741 | AA57: 3998755 | AB57: 3998755 | AC57: 0 | AD57: 16593 | AE57: 1339225 | AF57: 3373362 | AG57: 3855615 | AH57: 4853900 | AI57: 5238231 | AJ57: 6361005 | AK57: 8223144 | AL57: 9659890 | AM57: 11445701 | AN57: 14268540 | AO57: 14268540 | AP57: 0 | AQ57: 33046 | AR57: 4155318 | AS57: 5965870 | AT57: 6695100 | AU57: 9408018 | AV57: 10611721 | AW57: 12150340 | AX57: 13208552 | AY57: 14585443 | AZ57: 15610128 | BA57: 19456156 | BB57: 19456156 | BC57: 0 | BD57: 0 | BE57: 2580218 | BF57: 3786906 | BG57: 4949566 | BH57: 5630786 | BI57: 6368160 | BJ57: 7294318 | BK57: 8346883 | BL57: 9334347 | BM57: 11119202 | BN57: 14855118 | BO57: 14855118 | BP57: 0 | BQ57: 0 | BR57: 2753306 | BS57: 3686888 | BT57: 5052293 | BU57: 6328203 | BV57: 7082487 | BW57: 7719385 | BX57: 8461345 | BY57: 9165065 | BZ57: 10230142 | CA57: 13715523 | CB57: 13715523 | CC57: 0 | CD57: 0 | CE57: 2234308 | CF57: 3228842 | CG57: 4095520 | CH57: 4635941 | CI57: 5023185 | CJ57: 5525140 | CK57: 6027626 | CL57: 6386362 | CM57: 7230663 | CN57: 12532955 | CO57: 12532955 | CP57: 0 | CQ57: 87292 | CR57: 793272 | CS57: 1556347 | CT57: 2282348 | CU57: 2893680 | CV57: 3632116 | CW57: 4938968 | CX57: 6587924 | CY57: 8294837 | CZ57: 10043378 | DA57: 15656119 | DB57: 15656119 | DC57: 0 | DD57: 86461 | DE57: 1016727 | DF57: 1570665 | DG57: 2318130 | DH57: 5012601 | DI57: 5637478 | DJ57: 6210424 | DK57: 7549082 | DL57: 8799496 | DM57: 10623552 | DN57: 17848435 | DO57: 17848435 | DP57: 0 | DQ57: 0 | DR57: 2793263 | DS57: 4637349 | DT57: 6800955 | DU57: 9305411 | DV57: 11608286 | DW57: 13058895 | DX57: 15088967 | DY57: 15598733 | DZ57: 17616851 | EA57: 22912881 | EB57: 22912881 | EC57: 0 | ED57: 91311 | EE57: 1543145 | EF57: 1812150 | EG57: 2866970 | EH57: 3198071 | EI57: 3550823 | EJ57: 3879032 | EK57: 4224296 | EL57: 4965161 | EM57: 5497696 | EN57: 8070989 | EO57: 8070989 | EP57: 0 | EQ57: 0 | ER57: 782785 | ES57: 3521623 | ET57: 5392411 | EU57: 7003168 | EV57: 8794735 | EW57: 9187072 | EX57: 9707571 | EY57: 11078757 | EZ57: 11801848 | FA57: 13299232 | FB57: 13299232 | FC57: 0 | FD57: 0 | FE57: 671571 | FF57: 947529 | FG57: 1212531 | FH57: 3074751 | FI57: 4493515 | FJ57: 4493515 | FK57: 4493515 | FL57: 4493515 | FM57: 4493515 | FN57: 4493515 | FO57: 4493515
B58: SERVIU Coquimbo | C58: 0 | D58: 0 | E58: 2513542 | F58: 3412271 | G58: 4408845 | H58: 5186589 | I58: 5476407 | J58: 5887832 | K58: 5951399 | L58: 7183682 | M58: 11165109 | N58: 15718762 | O58: 15718762 | P58: 71110 | Q58: 454325 | R58: 1758422 | S58: 2676989 | T58: 3698079 | U58: 4404201 | V58: 5475035 | W58: 6339833 | X58: 7669044 | Y58: 9384372 | Z58: 10861151 | AA58: 12973688 | AB58: 12973688 | AC58: 0 | AD58: 4200 | AE58: 2702394 | AF58: 3616540 | AG58: 4748907 | AH58: 6165619 | AI58: 7276872 | AJ58: 8360770 | AK58: 9362544 | AL58: 10950685 | AM58: 13481793 | AN58: 17901095 | AO58: 17901095 | AP58: 0 | AQ58: 638200 | AR58: 3893999 | AS58: 5448165 | AT58: 7142382 | AU58: 9343795 | AV58: 11326679 | AW58: 13888007 | AX58: 15098925 | AY58: 16402080 | AZ58: 17685552 | BA58: 19946546 | BB58: 19946546 | BC58: 0 | BD58: 4250 | BE58: 4651436 | BF58: 5760832 | BG58: 7130498 | BH58: 8641438 | BI58: 9497124 | BJ58: 10683527 | BK58: 11657409 | BL58: 13288277 | BM58: 14093331 | BN58: 16630930 | BO58: 16630930 | BP58: 0 | BQ58: 0 | BR58: 2205084 | BS58: 2602194 | BT58: 3870748 | BU58: 5059716 | BV58: 5471563 | BW58: 5958514 | BX58: 6471586 | BY58: 7074258 | BZ58: 8670899 | CA58: 10285886 | CB58: 10285886 | CC58: 0 | CD58: 0 | CE58: 1944475 | CF58: 3245659 | CG58: 4690523 | CH58: 5474272 | CI58: 6224364 | CJ58: 6873785 | CK58: 7216001 | CL58: 7838147 | CM58: 8875527 | CN58: 10845646 | CO58: 10845646 | CP58: 0 | CQ58: 145074 | CR58: 1058879 | CS58: 2039763 | CT58: 2953907 | CU58: 3778375 | CV58: 4390330 | CW58: 4988153 | CX58: 6096186 | CY58: 7319317 | CZ58: 8210062 | DA58: 11722421 | DB58: 11722421 | DC58: 0 | DD58: 0 | DE58: 2242990 | DF58: 2913694 | DG58: 3475710 | DH58: 4563044 | DI58: 5503722 | DJ58: 5982265 | DK58: 7324275 | DL58: 8473012 | DM58: 9570289 | DN58: 12299225 | DO58: 12299225 | DP58: 0 | DQ58: 184861 | DR58: 2550024 | DS58: 3335427 | DT58: 3954033 | DU58: 5137967 | DV58: 6515902 | DW58: 9869211 | DX58: 11282350 | DY58: 14137020 | DZ58: 16461275 | EA58: 20087982 | EB58: 20087982 | EC58: 0 | ED58: 0 | EE58: 2563142 | EF58: 4937234 | EG58: 6455476 | EH58: 7874182 | EI58: 9537233 | EJ58: 10627246 | EK58: 11749652 | EL58: 12736164 | EM58: 14354886 | EN58: 18304746 | EO58: 18304746 | EP58: 0 | EQ58: 0 | ER58: 537044 | ES58: 4624082 | ET58: 6663050 | EU58: 7372366 | EV58: 8896020 | EW58: 10874834 | EX58: 11736753 | EY58: 13073544 | EZ58: 14605811 | FA58: 17113896 | FB58: 17113896 | FC58: 0 | FD58: 1214485 | FE58: 1998311 | FF58: 3214367 | FG58: 6370940 | FH58: 7328213 | FI58: 8973928 | FJ58: 8973928 | FK58: 8973928 | FL58: 8973928 | FM58: 8973928 | FN58: 8973928 | FO58: 8973928
B59: SERVIU Valparaíso | C59: 0 | D59: 0 | E59: 4682990 | F59: 6737067 | G59: 9073470 | H59: 11274580 | I59: 12685525 | J59: 14707743 | K59: 16168686 | L59: 18628188 | M59: 21627939 | N59: 26720935 | O59: 26720935 | P59: 2561068 | Q59: 4817816 | R59: 8111988 | S59: 10861654 | T59: 13586321 | U59: 15077683 | V59: 16918337 | W59: 18691777 | X59: 20724096 | Y59: 23469588 | Z59: 29168140 | AA59: 34824496 | AB59: 34824496 | AC59: 224821 | AD59: 1278603 | AE59: 2677630 | AF59: 4423969 | AG59: 5750799 | AH59: 7383615 | AI59: 8433108 | AJ59: 10145300 | AK59: 13841439 | AL59: 16493034 | AM59: 19575261 | AN59: 29886003 | AO59: 29886003 | AP59: 16506 | AQ59: 2024369 | AR59: 3960178 | AS59: 5569008 | AT59: 7250492 | AU59: 9199235 | AV59: 12117075 | AW59: 15625214 | AX59: 18786926 | AY59: 22952869 | AZ59: 28063619 | BA59: 38234943 | BB59: 38234943 | BC59: 0 | BD59: 1421348 | BE59: 4321108 | BF59: 6377758 | BG59: 8515875 | BH59: 10265173 | BI59: 12719573 | BJ59: 15004072 | BK59: 17238142 | BL59: 19728628 | BM59: 22680584 | BN59: 27714608 | BO59: 27714608 | BP59: 0 | BQ59: 0 | BR59: 4348933 | BS59: 6874858 | BT59: 9416897 | BU59: 11406050 | BV59: 14220308 | BW59: 17069752 | BX59: 19612545 | BY59: 22845584 | BZ59: 26887876 | CA59: 32568898 | CB59: 32568898 | CC59: 0 | CD59: 0 | CE59: 4568439 | CF59: 6603295 | CG59: 9300130 | CH59: 12235601 | CI59: 14526131 | CJ59: 16939219 | CK59: 19917692 | CL59: 23257211 | CM59: 26731410 | CN59: 33967325 | CO59: 33967325 | CP59: 0 | CQ59: 2423327 | CR59: 6782736 | CS59: 15251668 | CT59: 16748720 | CU59: 18415304 | CV59: 21339663 | CW59: 23380013 | CX59: 25383530 | CY59: 31015191 | CZ59: 34807108 | DA59: 41047311 | DB59: 41047311 | DC59: 0 | DD59: 1954310 | DE59: 5437246 | DF59: 9074366 | DG59: 11564328 | DH59: 13457755 | DI59: 16052872 | DJ59: 18591175 | DK59: 21394133 | DL59: 24741056 | DM59: 27312162 | DN59: 34255389 | DO59: 34255389 | DP59: 0 | DQ59: 1073661 | DR59: 6482752 | DS59: 11046429 | DT59: 14774156 | DU59: 17141463 | DV59: 19176471 | DW59: 22477672 | DX59: 24576750 | DY59: 28005939 | DZ59: 30917189 | EA59: 43303337 | EB59: 43303337 | EC59: 0 | ED59: 817026 | EE59: 7211294 | EF59: 10269338 | EG59: 13142557 | EH59: 16019024 | EI59: 17552175 | EJ59: 20571069 | EK59: 23134677 | EL59: 25245587 | EM59: 28348834 | EN59: 35664606 | EO59: 35664606 | EP59: 0 | EQ59: 0 | ER59: 6894377 | ES59: 14671995 | ET59: 18775808 | EU59: 23907660 | EV59: 29396833 | EW59: 33730948 | EX59: 37737801 | EY59: 42029251 | EZ59: 45580303 | FA59: 55696292 | FB59: 55696292 | FC59: 0 | FD59: 575811 | FE59: 5659243 | FF59: 9197930 | FG59: 13083654 | FH59: 16463966 | FI59: 18166057 | FJ59: 18166057 | FK59: 18166057 | FL59: 18166057 | FM59: 18166057 | FN59: 18166057 | FO59: 18166057
B60: SERVIU Metropolitano | C60: 0 | D60: 0 | E60: 2970460 | F60: 7075373 | G60: 11029119 | H60: 14673873 | I60: 18929628 | J60: 22297963 | K60: 25916623 | L60: 30381483 | M60: 42408242 | N60: 57410502 | O60: 57410502 | P60: 139559 | Q60: 4065998 | R60: 8108896 | S60: 13346732 | T60: 22254966 | U60: 26324505 | V60: 29649709 | W60: 33482238 | X60: 37387061 | Y60: 46286901 | Z60: 52751680 | AA60: 77458939 | AB60: 77458939 | AC60: 0 | AD60: 2881477 | AE60: 8166342 | AF60: 13544296 | AG60: 18219423 | AH60: 22352621 | AI60: 25983046 | AJ60: 30449450 | AK60: 34399039 | AL60: 39823543 | AM60: 47010366 | AN60: 61458965 | AO60: 61458965 | AP60: 0 | AQ60: 43451 | AR60: 6381762 | AS60: 11054623 | AT60: 15079476 | AU60: 18322176 | AV60: 22489207 | AW60: 26693958 | AX60: 31570624 | AY60: 37626385 | AZ60: 45141783 | BA60: 65482649 | BB60: 65482649 | BC60: 0 | BD60: 0 | BE60: 8987133 | BF60: 14119906 | BG60: 18017167 | BH60: 21413096 | BI60: 24430930 | BJ60: 27550274 | BK60: 30736201 | BL60: 35415402 | BM60: 46178819 | BN60: 57766807 | BO60: 57766807 | BP60: 0 | BQ60: 0 | BR60: 9612053 | BS60: 13818878 | BT60: 16872617 | BU60: 21351154 | BV60: 25315392 | BW60: 28294973 | BX60: 30810123 | BY60: 33442924 | BZ60: 38060457 | CA60: 51041585 | CB60: 51041585 | CC60: 0 | CD60: 0 | CE60: 6424503 | CF60: 9878571 | CG60: 13104189 | CH60: 15753019 | CI60: 19023549 | CJ60: 23239366 | CK60: 31131974 | CL60: 35551974 | CM60: 46895221 | CN60: 61574099 | CO60: 61574099 | CP60: 0 | CQ60: 0 | CR60: 9171371 | CS60: 20167605 | CT60: 26768507 | CU60: 34468225 | CV60: 41087061 | CW60: 49548059 | CX60: 57425159 | CY60: 66050722 | CZ60: 74504640 | DA60: 93248356 | DB60: 93248356 | DC60: 0 | DD60: 20 | DE60: 7814847 | DF60: 14488934 | DG60: 20550387 | DH60: 25905467 | DI60: 31180285 | DJ60: 35454583 | DK60: 43316522 | DL60: 50229978 | DM60: 60493790 | DN60: 91204741 | DO60: 91204741 | DP60: 0 | DQ60: 0 | DR60: 7743578 | DS60: 12770777 | DT60: 22600345 | DU60: 29409607 | DV60: 34855974 | DW60: 38558182 | DX60: 39905006 | DY60: 43685225 | DZ60: 48485518 | EA60: 69805257 | EB60: 69805257 | EC60: 0 | ED60: 0 | EE60: 5802062 | EF60: 26606325 | EG60: 37830174 | EH60: 47455810 | EI60: 52375257 | EJ60: 56860092 | EK60: 60181952 | EL60: 63436734 | EM60: 69842295 | EN60: 84329419 | EO60: 84329419 | EP60: 0 | EQ60: 0 | ER60: 12132484 | ES60: 17263226 | ET60: 25244869 | EU60: 31340839 | EV60: 39240658 | EW60: 41627865 | EX60: 45007011 | EY60: 56559786 | EZ60: 61325912 | FA60: 79219999 | FB60: 79219999 | FC60: 0 | FD60: 8700230 | FE60: 16017382 | FF60: 19225220 | FG60: 23499085 | FH60: 28587732 | FI60: 32956485 | FJ60: 32956485 | FK60: 32956485 | FL60: 32956485 | FM60: 32956485 | FN60: 32956485 | FO60: 32956485
B61: SERVIU O'Higgins | C61: 0 | D61: 22242 | E61: 478896 | F61: 2549912 | G61: 5167975 | H61: 6238179 | I61: 7905028 | J61: 9924768 | K61: 11965300 | L61: 15043991 | M61: 17656937 | N61: 23748761 | O61: 23748761 | P61: 1254564 | Q61: 3173445 | R61: 4991770 | S61: 6315165 | T61: 7229974 | U61: 8881782 | V61: 9995926 | W61: 11130328 | X61: 12266626 | Y61: 12938846 | Z61: 14602559 | AA61: 17797525 | AB61: 17797525 | AC61: 9176 | AD61: 1428632 | AE61: 2465590 | AF61: 3433499 | AG61: 4351308 | AH61: 5226281 | AI61: 5968589 | AJ61: 6672133 | AK61: 7390606 | AL61: 8553565 | AM61: 9986200 | AN61: 13373805 | AO61: 13373805 | AP61: 255076 | AQ61: 1188844 | AR61: 2543469 | AS61: 3286158 | AT61: 3978582 | AU61: 5322922 | AV61: 5759652 | AW61: 6814851 | AX61: 7633241 | AY61: 8233443 | AZ61: 9070756 | BA61: 11670063 | BB61: 11670063 | BC61: 0 | BD61: 568944 | BE61: 1975522 | BF61: 2922577 | BG61: 3924253 | BH61: 4839396 | BI61: 5642790 | BJ61: 6683163 | BK61: 7629648 | BL61: 8541640 | BM61: 9172530 | BN61: 13993895 | BO61: 13993895 | BP61: 0 | BQ61: 560042 | BR61: 2689600 | BS61: 2832524 | BT61: 3699337 | BU61: 4639655 | BV61: 4702977 | BW61: 5388587 | BX61: 5954537 | BY61: 6511917 | BZ61: 7937328 | CA61: 12042288 | CB61: 12042288 | CC61: 0 | CD61: 0 | CE61: 1043612 | CF61: 1649999 | CG61: 3165833 | CH61: 3614370 | CI61: 4396015 | CJ61: 4778929 | CK61: 5047595 | CL61: 6124286 | CM61: 6338278 | CN61: 10402261 | CO61: 10402261 | CP61: 1000 | CQ61: 99098 | CR61: 415702 | CS61: 1181604 | CT61: 2061999 | CU61: 2518382 | CV61: 3449968 | CW61: 3878692 | CX61: 6374836 | CY61: 6949560 | CZ61: 7815000 | DA61: 9473969 | DB61: 9473969 | DC61: 0 | DD61: 577978 | DE61: 1236819 | DF61: 1977797 | DG61: 2357232 | DH61: 2969508 | DI61: 3318916 | DJ61: 3995498 | DK61: 4545865 | DL61: 4876192 | DM61: 5746022 | DN61: 6861203 | DO61: 6861203 | DP61: 0 | DQ61: 492390 | DR61: 1774370 | DS61: 2626789 | DT61: 3586562 | DU61: 4109229 | DV61: 4791193 | DW61: 4985805 | DX61: 5467268 | DY61: 5861823 | DZ61: 6425422 | EA61: 8992823 | EB61: 8992823 | EC61: 0 | ED61: 276844 | EE61: 1164884 | EF61: 1445217 | EG61: 1635928 | EH61: 1791794 | EI61: 1875060 | EJ61: 2301121 | EK61: 2703028 | EL61: 3355875 | EM61: 4056976 | EN61: 5186229 | EO61: 5186229 | EP61: 0 | EQ61: 454298 | ER61: 1364864 | ES61: 2152908 | ET61: 3067456 | EU61: 3591831 | EV61: 4024502 | EW61: 4758598 | EX61: 6018242 | EY61: 6553969 | EZ61: 7179799 | FA61: 8275294 | FB61: 8275294 | FC61: 204442 | FD61: 1444145 | FE61: 3179839 | FF61: 3866613 | FG61: 4135039 | FH61: 4729235 | FI61: 5630349 | FJ61: 5630349 | FK61: 5630349 | FL61: 5630349 | FM61: 5630349 | FN61: 5630349 | FO61: 5630349
B62: SERVIU Maule | C62: 0 | D62: 7202 | E62: 3176200 | F62: 4006859 | G62: 4424912 | H62: 4821159 | I62: 5158438 | J62: 5423043 | K62: 6939626 | L62: 8379851 | M62: 9648365 | N62: 11692667 | O62: 11692667 | P62: 0 | Q62: 759446 | R62: 1730817 | S62: 2751576 | T62: 3194132 | U62: 4637000 | V62: 5482147 | W62: 7320179 | X62: 9906296 | Y62: 13305528 | Z62: 16063966 | AA62: 22241143 | AB62: 22241143 | AC62: 2719828 | AD62: 5948540 | AE62: 8880077 | AF62: 10394535 | AG62: 11735192 | AH62: 13862936 | AI62: 15854225 | AJ62: 17677233 | AK62: 18638802 | AL62: 19689703 | AM62: 21339509 | AN62: 24953816 | AO62: 24953816 | AP62: 0 | AQ62: 2119333 | AR62: 4260332 | AS62: 5387834 | AT62: 8197687 | AU62: 10069833 | AV62: 11455116 | AW62: 12817014 | AX62: 14074095 | AY62: 16238954 | AZ62: 19882223 | BA62: 25294991 | BB62: 25294991 | BC62: 2991337 | BD62: 5558521 | BE62: 7476713 | BF62: 10423728 | BG62: 13982342 | BH62: 15710790 | BI62: 18080520 | BJ62: 19629237 | BK62: 21227499 | BL62: 22352857 | BM62: 25934821 | BN62: 29681699 | BO62: 29681699 | BP62: 0 | BQ62: 1436174 | BR62: 4654419 | BS62: 5903657 | BT62: 8722713 | BU62: 11002949 | BV62: 12796788 | BW62: 14941827 | BX62: 16817139 | BY62: 20861092 | BZ62: 24834887 | CA62: 29748545 | CB62: 29748545 | CC62: 0 | CD62: 1421550 | CE62: 5936171 | CF62: 9196573 | CG62: 10845707 | CH62: 12720299 | CI62: 13547075 | CJ62: 13873276 | CK62: 16520877 | CL62: 17188208 | CM62: 18070270 | CN62: 22057592 | CO62: 22057592 | CP62: 230063 | CQ62: 2679421 | CR62: 4420753 | CS62: 5625485 | CT62: 8547030 | CU62: 10394218 | CV62: 12259307 | CW62: 13792087 | CX62: 14859039 | CY62: 15945761 | CZ62: 16872512 | DA62: 21863438 | DB62: 21863438 | DC62: 0 | DD62: 922651 | DE62: 2516611 | DF62: 4242046 | DG62: 5842634 | DH62: 7701318 | DI62: 8879148 | DJ62: 10547577 | DK62: 11329010 | DL62: 12221517 | DM62: 14355204 | DN62: 17959345 | DO62: 17959345 | DP62: 0 | DQ62: 139737 | DR62: 1933892 | DS62: 2566443 | DT62: 4806556 | DU62: 5940484 | DV62: 6960232 | DW62: 8468944 | DX62: 9342327 | DY62: 10407121 | DZ62: 10942387 | EA62: 14585744 | EB62: 14585744 | EC62: 0 | ED62: 754193 | EE62: 3484262 | EF62: 4899524 | EG62: 6887240 | EH62: 7953500 | EI62: 9188042 | EJ62: 10190994 | EK62: 15388503 | EL62: 17047081 | EM62: 18216853 | EN62: 19302172 | EO62: 19302172 | EP62: 0 | EQ62: 2936145 | ER62: 3840604 | ES62: 5205000 | ET62: 7087387 | EU62: 8761945 | EV62: 9648079 | EW62: 11529540 | EX62: 12156420 | EY62: 13138327 | EZ62: 14104360 | FA62: 16237313 | FB62: 16237313 | FC62: 0 | FD62: 977735 | FE62: 1877551 | FF62: 2945279 | FG62: 3540409 | FH62: 4135011 | FI62: 4717171 | FJ62: 4717171 | FK62: 4717171 | FL62: 4717171 | FM62: 4717171 | FN62: 4717171 | FO62: 4717171
B63: SERVIU Ñuble | C63: 0 | D63: 0 | E63: 0 | F63: 0 | G63: 0 | H63: 0 | I63: 0 | J63: 0 | K63: 0 | L63: 0 | M63: 0 | N63: 0 | O63: 0 | P63: 0 | Q63: 0 | R63: 0 | S63: 0 | T63: 0 | U63: 0 | V63: 0 | W63: 0 | X63: 0 | Y63: 0 | Z63: 0 | AA63: 0 | AB63: 0 | AC63: 0 | AD63: 0 | AE63: 0 | AF63: 0 | AG63: 0 | AH63: 0 | AI63: 0 | AJ63: 0 | AK63: 0 | AL63: 0 | AM63: 0 | AN63: 0 | AO63: 0 | AP63: 0 | AQ63: 0 | AR63: 0 | AS63: 0 | AT63: 0 | AU63: 0 | AV63: 0 | AW63: 0 | AX63: 0 | AY63: 0 | AZ63: 0 | BA63: 0 | BB63: 0 | BC63: 0 | BD63: 0 | BE63: 0 | BF63: 0 | BG63: 0 | BH63: 0 | BI63: 0 | BJ63: 0 | BK63: 0 | BL63: 0 | BM63: 0 | BN63: 0 | BO63: 0 | BP63: 0 | BQ63: 0 | BR63: 0 | BS63: 0 | BT63: 0 | BU63: 874 | BV63: 1049 | BW63: 1524 | BX63: 1524 | BY63: 1524 | BZ63: 467746 | CA63: 1299327 | CB63: 1299327 | CC63: 0 | CD63: 0 | CE63: 1114006 | CF63: 1584090 | CG63: 1906446 | CH63: 2183361 | CI63: 2523674 | CJ63: 2981886 | CK63: 3199263 | CL63: 3332552 | CM63: 4943147 | CN63: 7366369 | CO63: 7366369 | CP63: 0 | CQ63: 1238171 | CR63: 2085725 | CS63: 3009570 | CT63: 4344721 | CU63: 6181413 | CV63: 7481590 | CW63: 8923223 | CX63: 9969186 | CY63: 12042447 | CZ63: 14316036 | DA63: 21083177 | DB63: 21083177 | DC63: 0 | DD63: 6363 | DE63: 1963636 | DF63: 3158663 | DG63: 4714179 | DH63: 6147258 | DI63: 8342380 | DJ63: 9944276 | DK63: 11786997 | DL63: 13492671 | DM63: 15132338 | DN63: 19561462 | DO63: 19561462 | DP63: 0 | DQ63: 1480106 | DR63: 5251198 | DS63: 8060203 | DT63: 9695784 | DU63: 11307082 | DV63: 12618163 | DW63: 14357900 | DX63: 16141680 | DY63: 17787508 | DZ63: 19945314 | EA63: 22005775 | EB63: 22005775 | EC63: 0 | ED63: 825335 | EE63: 3513803 | EF63: 4931246 | EG63: 7350891 | EH63: 8756033 | EI63: 9821988 | EJ63: 11470086 | EK63: 12805474 | EL63: 14287326 | EM63: 15540449 | EN63: 17950052 | EO63: 17950052 | EP63: 0 | EQ63: 148253 | ER63: 3292884 | ES63: 4257053 | ET63: 7062054 | EU63: 9495200 | EV63: 11760026 | EW63: 12709417 | EX63: 14311689 | EY63: 16551275 | EZ63: 17380835 | FA63: 21033526 | FB63: 21033526 | FC63: 0 | FD63: 3262841 | FE63: 4333743 | FF63: 5206806 | FG63: 5938083 | FH63: 6532085 | FI63: 6546839 | FJ63: 6546839 | FK63: 6546839 | FL63: 6546839 | FM63: 6546839 | FN63: 6546839 | FO63: 6546839
... B69: SERVIU Magallanes | C69: 0 | D69: 0 | E69: 0 | F69: 0 | G69: 2236759 | H69: 2936263 | I69: 3376405 | J69: 3831284 | K69: 4373377 | L69: 5605051 | M69: 7083064 | N69: 10086654 | O69: 10086654 | P69: 0 | Q69: 1355193 | R69: 2305331 | S69: 2786520 | T69: 2927940 | U69: 3122432 | V69: 3439673 | W69: 4069347 | X69: 4682305 | Y69: 5401569 | Z69: 6287608 | AA69: 7294234 | AB69: 7294234 | AC69: 0 | AD69: 483 | AE69: 1413270 | AF69: 1980069 | AG69: 2272091 | AH69: 2491838 | AI69: 2746815 | AJ69: 3018326 | AK69: 3473818 | AL69: 3981430 | AM69: 5163052 | AN69: 6987365 | AO69: 6987365 | AP69: 0 | AQ69: 158172 | AR69: 909922 | AS69: 1390797 | AT69: 1705539 | AU69: 2153438 | AV69: 2716665 | AW69: 3592634 | AX69: 4907018 | AY69: 6713412 | AZ69: 8822110 | BA69: 12128181 | BB69: 12128181 | BC69: 0 | BD69: 0 | BE69: 1538137 | BF69: 2152907 | BG69: 2673139 | BH69: 3045374 | BI69: 3298116 | BJ69: 3687401 | BK69: 3907234 | BL69: 4735498 | BM69: 5847323 | BN69: 8358099 | BO69: 8358099 | BP69: 0 | BQ69: 0 | BR69: 2506319 | BS69: 3406649 | BT69: 4321791 | BU69: 4770627 | BV69: 5172462 | BW69: 5172462 | BX69: 6207780 | BY69: 7894979 | BZ69: 9688128 | CA69: 11296807 | CB69: 11296807 | CC69: 0 | CD69: 0 | CE69: 1868482 | CF69: 3082450 | CG69: 3421285 | CH69: 3921486 | CI69: 4631969 | CJ69: 5189973 | CK69: 5834945 | CL69: 6703659 | CM69: 7658162 | CN69: 9121098 | CO69: 9121098 | CP69: 0 | CQ69: 780964 | CR69: 2329121 | CS69: 2781402 | CT69: 3961113 | CU69: 4999318 | CV69: 5729292 | CW69: 6450230 | CX69: 7246756 | CY69: 8083876 | CZ69: 9157163 | DA69: 10738590 | DB69: 10738590 | DC69: 0 | DD69: 531868 | DE69: 979900 | DF69: 1668995 | DG69: 2067161 | DH69: 2495250 | DI69: 2833549 | DJ69: 3310447 | DK69: 4180470 | DL69: 5410940 | DM69: 6546938 | DN69: 9221232 | DO69: 9221232 | DP69: 0 | DQ69: 242363 | DR69: 2468853 | DS69: 3552694 | DT69: 4986547 | DU69: 6240668 | DV69: 7483453 | DW69: 8011980 | DX69: 9004344 | DY69: 10464944 | DZ69: 11221564 | EA69: 12894724 | EB69: 12894724 | EC69: 0 | ED69: 0 | EE69: 3256958 | EF69: 5254963 | EG69: 7343946 | EH69: 8984252 | EI69: 11604334 | EJ69: 12582118 | EK69: 13958919 | EL69: 15014924 | EM69: 16146052 | EN69: 17938143 | EO69: 17938143 | EP69: 0 | EQ69: 656162 | ER69: 1462430 | ES69: 2617816 | ET69: 3672318 | EU69: 4549506 | EV69: 5755024 | EW69: 6518863 | EX69: 8081693 | EY69: 9963180 | EZ69: 11073504 | FA69: 14403339 | FB69: 14403339 | FC69: 0 | FD69: 2033211 | FE69: 4073385 | FF69: 5482094 | FG69: 6965527 | FH69: 10120647 | FI69: 11843248 | FJ69: 11843248 | FK69: 11843248 | FL69: 11843248 | FM69: 11843248 | FN69: 11843248 | FO69: 11843248
B70: Total Ejecución Acumulada (Subtítulo 31) | C70: =SUM(C52:C69) -> 0 | D70: =SUM(D52:D69) -> 6707055 | E70: =SUM(E52:E69) -> 42771872 | F70: =SUM(F52:F69) -> 67048131 | G70: =SUM(G52:G69) -> 91643055 | H70: =SUM(H52:H69) -> 112124722 | I70: =SUM(I52:I69) -> 131413645 | J70: =SUM(J52:J69) -> 150483865 | ... FO70: =SUM(FO52:FO69) -> 155690398
B73: SUBTÍTULO 29 – ADQUISICIÓN DE ACTIVOS NO FINANCIEROS
B74: Presupuesto Ley (Subtítulo 29)
C75: 2014 | P75: 2015 | AC75: 2016 | AP75: 2017 | BC75: 2018 | BP75: 2019 | CC75: 2020 | CP75: 2021 | DC75: 2022 | DP75: 2023 | EC75: 2024 | EP75: 2025 | FC75: 2026
B76: Programa / Entidad | C76: Ene | D76: Feb | E76: Mar | F76: Abr | G76: May | H76: Jun | I76: Jul | J76: Ago | K76: Sep | L76: Oct | M76: Nov | N76: Dic | O76: Total 2014 | P76: Ene | Q76: Feb | R76: Mar | S76: Abr | T76: May | U76: Jun | V76: Jul | W76: Ago | X76: Sep | Y76: Oct | Z76: Nov | AA76: Dic | AB76: Total 2015 | AC76: Ene | AD76: Feb | AE76: Mar | AF76: Abr | AG76: May | AH76: Jun | AI76: Jul | AJ76: Ago | AK76: Sep | AL76: Oct | AM76: Nov | AN76: Dic | AO76: Total 2016 | AP76: Ene | AQ76: Feb | AR76: Mar | AS76: Abr | AT76: May | AU76: Jun | AV76: Jul | AW76: Ago | AX76: Sep | AY76: Oct | AZ76: Nov | BA76: Dic | BB76: Total 2017 | BC76: Ene | BD76: Feb | BE76: Mar | BF76: Abr | BG76: May | BH76: Jun | BI76: Jul | BJ76: Ago | BK76: Sep | BL76: Oct | BM76: Nov | BN76: Dic | BO76: Total 2018 | BP76: Ene | BQ76: Feb | BR76: Mar | BS76: Abr | BT76: May | BU76: Jun | BV76: Jul | BW76: Ago | BX76: Sep | BY76: Oct | BZ76: Nov | CA76: Dic | CB76: Total 2019 | CC76: Ene | CD76: Feb | CE76: Mar | CF76: Abr | CG76: May | CH76: Jun | CI76: Jul | CJ76: Ago | CK76: Sep | CL76: Oct | CM76: Nov | CN76: Dic | CO76: Total 2020 | CP76: Ene | CQ76: Feb | CR76: Mar | CS76: Abr | CT76: May | CU76: Jun | CV76: Jul | CW76: Ago | CX76: Sep | CY76: Oct | CZ76: Nov | DA76: Dic | DB76: Total 2021 | DC76: Ene | DD76: Feb | DE76: Mar | DF76: Abr | DG76: May | DH76: Jun | DI76: Jul | DJ76: Ago | DK76: Sep | DL76: Oct | DM76: Nov | DN76: Dic | DO76: Total 2022 | DP76: Ene | DQ76: Feb | DR76: Mar | DS76: Abr | DT76: May | DU76: Jun | DV76: Jul | DW76: Ago | DX76: Sep | DY76: Oct | DZ76: Nov | EA76: Dic | EB76: Total 2023 | EC76: Ene | ED76: Feb | EE76: Mar | EF76: Abr | EG76: May | EH76: Jun | EI76: Jul | EJ76: Ago | EK76: Sep | EL76: Oct | EM76: Nov | EN76: Dic | EO76: Total 2024 | EP76: Ene | EQ76: Feb | ER76: Mar | ES76: Abr | ET76: May | EU76: Jun | EV76: Jul | EW76: Ago | EX76: Sep | EY76: Oct | EZ76: Nov | FA76: Dic | FB76: Total 2025 | FC76: Ene | FD76: Feb | FE76: Mar | FF76: Abr | FG76: May | FH76: Jun | FI76: Jul | FJ76: Ago | FK76: Sep | FL76: Oct | FM76: Nov | FN76: Dic | FO76: Total 2026
B77: Subsecretaría y Programas Centrales | C77: 4128812 | D77: 4128812 | E77: 15897592 | F77: 15897592 | G77: 15897592 | H77: 15897592 | I77: 15897592 | J77: 15897592 | K77: 15897592 | L77: 15897592 | M77: 15897592 | N77: 15897592 | O77: 15897592 | P77: 4693552 | Q77: 4693552 | R77: 4693552 | S77: 4693552 | T77: 4693552 | U77: 4693552 | V77: 4693552 | W77: 4693552 | X77: 4693552 | Y77: 4693552 | Z77: 4693552 | AA77: 4693552 | AB77: 4693552 | AC77: 3911026 | AD77: 3911026 | AE77: 3911026 | AF77: 3911026 | AG77: 3911026 | AH77: 3911026 | AI77: 3911026 | AJ77: 3911026 | AK77: 3911026 | AL77: 3911026 | AM77: 3911026 | AN77: 3911026 | AO77: 3911026 | AP77: 4389807 | AQ77: 4389807 | AR77: 4389807 | AS77: 4389807 | AT77: 4389807 | AU77: 4389807 | AV77: 4389807 | AW77: 4389807 | AX77: 4389807 | AY77: 4389807 | AZ77: 4389807 | BA77: 4389807 | BB77: 4389807 | BC77: 4513827 | BD77: 4513827 | BE77: 4513827 | BF77: 4513827 | BG77: 4513827 | BH77: 4513827 | BI77: 4513827 | BJ77: 4513827 | BK77: 4513827 | BL77: 4513827 | BM77: 4513827 | BN77: 4513827 | BO77: 4513827 | BP77: 4195666 | BQ77: 4195666 | BR77: 4195666 | BS77: 4195666 | BT77: 4195666 | BU77: 4195666 | BV77: 4195666 | BW77: 4195666 | BX77: 4195666 | BY77: 4195666 | BZ77: 4195666 | CA77: 4195666 | CB77: 4195666 | CC77: 4783688 | CD77: 4783688 | CE77: 4783688 | CF77: 4783688 | CG77: 4783688 | CH77: 4783688 | CI77: 4783688 | CJ77: 4783688 | CK77: 4783688 | CL77: 4783688 | CM77: 4783688 | CN77: 4783688 | CO77: 4783688 | CP77: 3879109 | CQ77: 3879109 | CR77: 3879109 | CS77: 3879109 | CT77: 3879109 | CU77: 3879109 | CV77: 3879109 | CW77: 3879109 | CX77: 3879109 | CY77: 3879109 | CZ77: 3879109 | DA77: 3879109 | DB77: 3879109 | DC77: 3677484 | DD77: 3677484 | DE77: 3677484 | DF77: 3677484 | DG77: 3677484 | DH77: 3677484 | DI77: 3677484 | DJ77: 3677484 | DK77: 3677484 | DL77: 3677484 | DM77: 3677484 | DN77: 3677484 | DO77: 3677484 | DP77: 4127526 | DQ77: 4127526 | DR77: 4127526 | DS77: 4127526 | DT77: 4127526 | DU77: 4127526 | DV77: 4127526 | DW77: 4127526 | DX77: 4127526 | DY77: 4127526 | DZ77: 4127526 | EA77: 4127526 | EB77: 4127526 | EC77: 30674754 | ED77: 30674754 | EE77: 30674754 | EF77: 30674754 | EG77: 30674754 | EH77: 30674754 | EI77: 30674754 | EJ77: 30674754 | EK77: 30674754 | EL77: 30674754 | EM77: 30674754 | EN77: 30674754 | EO77: 30674754 | EP77: 4669285 | EQ77: 4669285 | ER77: 4669285 | ES77: 4669285 | ET77: 4669285 | EU77: 4669285 | EV77: 4669285 | EW77: 4669285 | EX77: 4669285 | EY77: 4669285 | EZ77: 4669285 | FA77: 4669285 | FB77: 4669285 | FC77: 4182704 | FD77: 4182704 | FE77: 4182704 | FF77: 4182704 | FG77: 4182704 | FH77: 4182704 | FI77: 4182704 | FJ77: 4182704 | FK77: 4182704 | FL77: 4182704 | FM77: 4182704 | FN77: 4182704 | FO77: 4182704
B78: Parque Metropolitano (PARQUEMET) | C78: 54576 | D78: 54576 | E78: 54576 | F78: 54576 | G78: 54576 | H78: 54576 | I78: 54576 | J78: 54576 | K78: 54576 | L78: 54576 | M78: 54576 | N78: 54576 | O78: 54576 | P78: 56213 | Q78: 56213 | R78: 56213 | S78: 56213 | T78: 56213 | U78: 56213 | V78: 56213 | W78: 56213 | X78: 56213 | Y78: 56213 | Z78: 56213 | AA78: 56213 | AB78: 56213 | AC78: 58349 | AD78: 58349 | AE78: 58349 | AF78: 58349 | AG78: 58349 | AH78: 58349 | AI78: 58349 | AJ78: 58349 | AK78: 58349 | AL78: 58349 | AM78: 58349 | AN78: 58349 | AO78: 58349 | AP78: 64890 | AQ78: 64890 | AR78: 64890 | AS78: 64890 | AT78: 64890 | AU78: 64890 | AV78: 64890 | AW78: 64890 | AX78: 64890 | AY78: 64890 | AZ78: 64890 | BA78: 64890 | BB78: 64890 | BC78: 104652 | BD78: 104652 | BE78: 104652 | BF78: 104652 | BG78: 104652 | BH78: 104652 | BI78: 104652 | BJ78: 104652 | BK78: 104652 | BL78: 104652 | BM78: 104652 | BN78: 104652 | BO78: 104652 | BP78: 141261 | BQ78: 141261 | BR78: 141261 | BS78: 141261 | BT78: 141261 | BU78: 141261 | BV78: 141261 | BW78: 141261 | BX78: 141261 | BY78: 141261 | BZ78: 141261 | CA78: 141261 | CB78: 141261 | CC78: 144934 | CD78: 144934 | CE78: 144934 | CF78: 144934 | CG78: 144934 | CH78: 144934 | CI78: 144934 | CJ78: 144934 | CK78: 144934 | CL78: 144934 | CM78: 144934 | CN78: 144934 | CO78: 144934 | CP78: 71111 | CQ78: 71111 | CR78: 71111 | CS78: 71111 | CT78: 71111 | CU78: 71111 | CV78: 71111 | CW78: 71111 | CX78: 71111 | CY78: 71111 | CZ78: 71111 | DA78: 71111 | DB78: 71111 | DC78: 33328 | DD78: 33328 | DE78: 33328 | DF78: 33328 | DG78: 33328 | DH78: 33328 | DI78: 33328 | DJ78: 33328 | DK78: 33328 | DL78: 33328 | DM78: 33328 | DN78: 33328 | DO78: 33328 | DP78: 0 | DQ78: 0 | DR78: 0 | DS78: 0 | DT78: 0 | DU78: 0 | DV78: 0 | DW78: 0 | DX78: 0 | DY78: 0 | DZ78: 0 | EA78: 0 | EB78: 0 | EC78: 0 | ED78: 0 | EE78: 0 | EF78: 0 | EG78: 0 | EH78: 0 | EI78: 0 | EJ78: 0 | EK78: 0 | EL78: 0 | EM78: 0 | EN78: 0 | EO78: 0 | EP78: 7294 | EQ78: 7294 | ER78: 7294 | ES78: 7294 | ET78: 7294 | EU78: 7294 | EV78: 7294 | EW78: 7294 | EX78: 7294 | EY78: 7294 | EZ78: 7294 | FA78: 7294 | FB78: 7294 | FC78: 0 | FD78: 0 | FE78: 0 | FF78: 0 | FG78: 0 | FH78: 0 | FI78: 0 | FJ78: 0 | FK78: 0 | FL78: 0 | FM78: 0 | FN78: 0 | FO78: 0
B79: SERVIU Arica y Parinacota | C79: 23059 | D79: 23059 | E79: 23059 | F79: 23059 | G79: 23059 | H79: 23059 | I79: 23059 | J79: 23059 | K79: 23059 | L79: 23059 | M79: 23059 | N79: 23059 | O79: 23059 | P79: 24642 | Q79: 24642 | R79: 24642 | S79: 24642 | T79: 24642 | U79: 24642 | V79: 24642 | W79: 24642 | X79: 24642 | Y79: 24642 | Z79: 24642 | AA79: 24642 | AB79: 24642 | AC79: 23431 | AD79: 23431 | AE79: 23431 | AF79: 23431 | AG79: 23431 | AH79: 23431 | AI79: 23431 | AJ79: 23431 | AK79: 23431 | AL79: 23431 | AM79: 23431 | AN79: 23431 | AO79: 23431 | AP79: 13390 | AQ79: 13390 | AR79: 13390 | AS79: 13390 | AT79: 13390 | AU79: 13390 | AV79: 13390 | AW79: 13390 | AX79: 13390 | AY79: 13390 | AZ79: 13390 | BA79: 13390 | BB79: 13390 | BC79: 18468 | BD79: 18468 | BE79: 18468 | BF79: 18468 | BG79: 18468 | BH79: 18468 | BI79: 18468 | BJ79: 18468 | BK79: 18468 | BL79: 18468 | BM79: 18468 | BN79: 18468 | BO79: 18468 | BP79: 11102 | BQ79: 11102 | BR79: 11102 | BS79: 11102 | BT79: 11102 | BU79: 11102 | BV79: 11102 | BW79: 11102 | BX79: 11102 | BY79: 11102 | BZ79: 11102 | CA79: 11102 | CB79: 11102 | CC79: 11391 | CD79: 11391 | CE79: 11391 | CF79: 11391 | CG79: 11391 | CH79: 11391 | CI79: 11391 | CJ79: 11391 | CK79: 11391 | CL79: 11391 | CM79: 11391 | CN79: 11391 | CO79: 11391 | CP79: 8967 | CQ79: 8967 | CR79: 8967 | CS79: 8967 | CT79: 8967 | CU79: 8967 | CV79: 8967 | CW79: 8967 | CX79: 8967 | CY79: 8967 | CZ79: 8967 | DA79: 8967 | DB79: 8967 | DC79: 0 | DD79: 0 | DE79: 0 | DF79: 0 | DG79: 0 | DH79: 0 | DI79: 0 | DJ79: 0 | DK79: 0 | DL79: 0 | DM79: 0 | DN79: 0 | DO79: 0 | DP79: 0 | DQ79: 0 | DR79: 0 | DS79: 0 | DT79: 0 | DU79: 0 | DV79: 0 | DW79: 0 | DX79: 0 | DY79: 0 | DZ79: 0 | EA79: 0 | EB79: 0 | EC79: 0 | ED79: 0 | EE79: 0 | EF79: 0 | EG79: 0 | EH79: 0 | EI79: 0 | EJ79: 0 | EK79: 0 | EL79: 0 | EM79: 0 | EN79: 0 | EO79: 0 | EP79: 3126 | EQ79: 3126 | ER79: 3126 | ES79: 3126 | ET79: 3126 | EU79: 3126 | EV79: 3126 | EW79: 3126 | EX79: 3126 | EY79: 3126 | EZ79: 3126 | FA79: 3126 | FB79: 3126 | FC79: 10 | FD79: 10 | FE79: 10 | FF79: 10 | FG79: 10 | FH79: 10 | FI79: 10 | FJ79: 10 | FK79: 10 | FL79: 10 | FM79: 10 | FN79: 10 | FO79: 10
B80: SERVIU Tarapacá | C80: 9750 | D80: 9750 | E80: 9750 | F80: 9750 | G80: 9750 | H80: 9750 | I80: 9750 | J80: 9750 | K80: 9750 | L80: 9750 | M80: 9750 | N80: 9750 | O80: 9750 | P80: 15091 | Q80: 15091 | R80: 15091 | S80: 15091 | T80: 15091 | U80: 15091 | V80: 15091 | W80: 15091 | X80: 15091 | Y80: 15091 | Z80: 15091 | AA80: 15091 | AB80: 15091 | AC80: 14630 | AD80: 14630 | AE80: 14630 | AF80: 14630 | AG80: 14630 | AH80: 14630 | AI80: 14630 | AJ80: 14630 | AK80: 14630 | AL80: 14630 | AM80: 14630 | AN80: 14630 | AO80: 14630 | AP80: 15965 | AQ80: 15965 | AR80: 15965 | AS80: 15965 | AT80: 15965 | AU80: 15965 | AV80: 15965 | AW80: 15965 | AX80: 15965 | AY80: 15965 | AZ80: 15965 | BA80: 15965 | BB80: 15965 | BC80: 15148 | BD80: 15148 | BE80: 15148 | BF80: 15148 | BG80: 15148 | BH80: 15148 | BI80: 15148 | BJ80: 15148 | BK80: 15148 | BL80: 15148 | BM80: 15148 | BN80: 15148 | BO80: 15148 | BP80: 17987 | BQ80: 17987 | BR80: 17987 | BS80: 17987 | BT80: 17987 | BU80: 17987 | BV80: 17987 | BW80: 17987 | BX80: 17987 | BY80: 17987 | BZ80: 17987 | CA80: 17987 | CB80: 17987 | CC80: 18455 | CD80: 18455 | CE80: 18455 | CF80: 18455 | CG80: 18455 | CH80: 18455 | CI80: 18455 | CJ80: 18455 | CK80: 18455 | CL80: 18455 | CM80: 18455 | CN80: 18455 | CO80: 18455 | CP80: 13147 | CQ80: 13147 | CR80: 13147 | CS80: 13147 | CT80: 13147 | CU80: 13147 | CV80: 13147 | CW80: 13147 | CX80: 13147 | CY80: 13147 | CZ80: 13147 | DA80: 13147 | DB80: 13147 | DC80: 0 | DD80: 0 | DE80: 0 | DF80: 0 | DG80: 0 | DH80: 0 | DI80: 0 | DJ80: 0 | DK80: 0 | DL80: 0 | DM80: 0 | DN80: 0 | DO80: 0 | DP80: 0 | DQ80: 0 | DR80: 0 | DS80: 0 | DT80: 0 | DU80: 0 | DV80: 0 | DW80: 0 | DX80: 0 | DY80: 0 | DZ80: 0 | EA80: 0 | EB80: 0 | EC80: 0 | ED80: 0 | EE80: 0 | EF80: 0 | EG80: 0 | EH80: 0 | EI80: 0 | EJ80: 0 | EK80: 0 | EL80: 0 | EM80: 0 | EN80: 0 | EO80: 0 | EP80: 6172 | EQ80: 6172 | ER80: 6172 | ES80: 6172 | ET80: 6172 | EU80: 6172 | EV80: 6172 | EW80: 6172 | EX80: 6172 | EY80: 6172 | EZ80: 6172 | FA80: 6172 | FB80: 6172 | FC80: 10 | FD80: 10 | FE80: 10 | FF80: 10 | FG80: 10 | FH80: 10 | FI80: 10 | FJ80: 10 | FK80: 10 | FL80: 10 | FM80: 10 | FN80: 10 | FO80: 10
B81: SERVIU Antofagasta | C81: 6703 | D81: 6703 | E81: 6703 | F81: 6703 | G81: 6703 | H81: 6703 | I81: 6703 | J81: 6703 | K81: 6703 | L81: 6703 | M81: 6703 | N81: 6703 | O81: 6703 | P81: 8171 | Q81: 8171 | R81: 8171 | S81: 8171 | T81: 8171 | U81: 8171 | V81: 8171 | W81: 8171 | X81: 8171 | Y81: 8171 | Z81: 8171 | AA81: 8171 | AB81: 8171 | AC81: 10165 | AD81: 10165 | AE81: 10165 | AF81: 10165 | AG81: 10165 | AH81: 10165 | AI81: 10165 | AJ81: 10165 | AK81: 10165 | AL81: 10165 | AM81: 10165 | AN81: 10165 | AO81: 10165 | AP81: 11330 | AQ81: 11330 | AR81: 11330 | AS81: 11330 | AT81: 11330 | AU81: 11330 | AV81: 11330 | AW81: 11330 | AX81: 11330 | AY81: 11330 | AZ81: 11330 | BA81: 11330 | BB81: 11330 | BC81: 1530650 | BD81: 1530650 | BE81: 1530650 | BF81: 1530650 | BG81: 1530650 | BH81: 1530650 | BI81: 1530650 | BJ81: 1530650 | BK81: 1530650 | BL81: 1530650 | BM81: 1530650 | BN81: 1530650 | BO81: 1530650 | BP81: 8728 | BQ81: 8728 | BR81: 8728 | BS81: 8728 | BT81: 8728 | BU81: 8728 | BV81: 8728 | BW81: 8728 | BX81: 8728 | BY81: 8728 | BZ81: 8728 | CA81: 8728 | CB81: 8728 | CC81: 7563 | CD81: 7563 | CE81: 7563 | CF81: 7563 | CG81: 7563 | CH81: 7563 | CI81: 7563 | CJ81: 7563 | CK81: 7563 | CL81: 7563 | CM81: 7563 | CN81: 7563 | CO81: 7563 | CP81: 1616 | CQ81: 1616 | CR81: 1616 | CS81: 1616 | CT81: 1616 | CU81: 1616 | CV81: 1616 | CW81: 1616 | CX81: 1616 | CY81: 1616 | CZ81: 1616 | DA81: 1616 | DB81: 1616 | DC81: 0 | DD81: 0 | DE81: 0 | DF81: 0 | DG81: 0 | DH81: 0 | DI81: 0 | DJ81: 0 | DK81: 0 | DL81: 0 | DM81: 0 | DN81: 0 | DO81: 0 | DP81: 0 | DQ81: 0 | DR81: 0 | DS81: 0 | DT81: 0 | DU81: 0 | DV81: 0 | DW81: 0 | DX81: 0 | DY81: 0 | DZ81: 0 | EA81: 0 | EB81: 0 | EC81: 0 | ED81: 0 | EE81: 0 | EF81: 0 | EG81: 0 | EH81: 0 | EI81: 0 | EJ81: 0 | EK81: 0 | EL81: 0 | EM81: 0 | EN81: 0 | EO81: 0 | EP81: 747 | EQ81: 747 | ER81: 747 | ES81: 747 | ET81: 747 | EU81: 747 | EV81: 747 | EW81: 747 | EX81: 747 | EY81: 747 | EZ81: 747 | FA81: 747 | FB81: 747 | FC81: 10 | FD81: 10 | FE81: 10 | FF81: 10 | FG81: 10 | FH81: 10 | FI81: 10 | FJ81: 10 | FK81: 10 | FL81: 10 | FM81: 10 | FN81: 10 | FO81: 10
B82: SERVIU Atacama | C82: 8794 | D82: 8794 | E82: 8794 | F82: 8794 | G82: 8794 | H82: 8794 | I82: 8794 | J82: 8794 | K82: 8794 | L82: 8794 | M82: 8794 | N82: 8794 | O82: 8794 | P82: 13274 | Q82: 13274 | R82: 13274 | S82: 13274 | T82: 13274 | U82: 13274 | V82: 13274 | W82: 13274 | X82: 13274 | Y82: 13274 | Z82: 13274 | AA82: 13274 | AB82: 13274 | AC82: 15315 | AD82: 15315 | AE82: 15315 | AF82: 15315 | AG82: 15315 | AH82: 15315 | AI82: 15315 | AJ82: 15315 | AK82: 15315 | AL82: 15315 | AM82: 15315 | AN82: 15315 | AO82: 15315 | AP82: 13699 | AQ82: 13699 | AR82: 13699 | AS82: 13699 | AT82: 13699 | AU82: 13699 | AV82: 13699 | AW82: 13699 | AX82: 13699 | AY82: 13699 | AZ82: 13699 | BA82: 13699 | BB82: 13699 | BC82: 18833 | BD82: 18833 | BE82: 18833 | BF82: 18833 | BG82: 18833 | BH82: 18833 | BI82: 18833 | BJ82: 18833 | BK82: 18833 | BL82: 18833 | BM82: 18833 | BN82: 18833 | BO82: 18833 | BP82: 13337 | BQ82: 13337 | BR82: 13337 | BS82: 13337 | BT82: 13337 | BU82: 13337 | BV82: 13337 | BW82: 13337 | BX82: 13337 | BY82: 13337 | BZ82: 13337 | CA82: 13337 | CB82: 13337 | CC82: 13684 | CD82: 13684 | CE82: 13684 | CF82: 13684 | CG82: 13684 | CH82: 13684 | CI82: 13684 | CJ82: 13684 | CK82: 13684 | CL82: 13684 | CM82: 13684 | CN82: 13684 | CO82: 13684 | CP82: 7771 | CQ82: 7771 | CR82: 7771 | CS82: 7771 | CT82: 7771 | CU82: 7771 | CV82: 7771 | CW82: 7771 | CX82: 7771 | CY82: 7771 | CZ82: 7771 | DA82: 7771 | DB82: 7771 | DC82: 0 | DD82: 0 | DE82: 0 | DF82: 0 | DG82: 0 | DH82: 0 | DI82: 0 | DJ82: 0 | DK82: 0 | DL82: 0 | DM82: 0 | DN82: 0 | DO82: 0 | DP82: 0 | DQ82: 0 | DR82: 0 | DS82: 0 | DT82: 0 | DU82: 0 | DV82: 0 | DW82: 0 | DX82: 0 | DY82: 0 | DZ82: 0 | EA82: 0 | EB82: 0 | EC82: 0 | ED82: 0 | EE82: 0 | EF82: 0 | EG82: 0 | EH82: 0 | EI82: 0 | EJ82: 0 | EK82: 0 | EL82: 0 | EM82: 0 | EN82: 0 | EO82: 0 | EP82: 6884 | EQ82: 6884 | ER82: 6884 | ES82: 6884 | ET82: 6884 | EU82: 6884 | EV82: 6884 | EW82: 6884 | EX82: 6884 | EY82: 6884 | EZ82: 6884 | FA82: 6884 | FB82: 6884 | FC82: 10 | FD82: 10 | FE82: 10 | FF82: 10 | FG82: 10 | FH82: 10 | FI82: 10 | FJ82: 10 | FK82: 10 | FL82: 10 | FM82: 10 | FN82: 10 | FO82: 10
B83: SERVIU Coquimbo | C83: 19164 | D83: 19164 | E83: 19164 | F83: 19164 | G83: 19164 | H83: 19164 | I83: 19164 | J83: 19164 | K83: 19164 | L83: 19164 | M83: 19164 | N83: 19164 | O83: 19164 | P83: 20898 | Q83: 20898 | R83: 20898 | S83: 20898 | T83: 20898 | U83: 20898 | V83: 20898 | W83: 20898 | X83: 20898 | Y83: 20898 | Z83: 20898 | AA83: 20898 | AB83: 20898 | AC83: 16233 | AD83: 16233 | AE83: 16233 | AF83: 16233 | AG83: 16233 | AH83: 16233 | AI83: 16233 | AJ83: 16233 | AK83: 16233 | AL83: 16233 | AM83: 16233 | AN83: 16233 | AO83: 16233 | AP83: 15038 | AQ83: 15038 | AR83: 15038 | AS83: 15038 | AT83: 15038 | AU83: 15038 | AV83: 15038 | AW83: 15038 | AX83: 15038 | AY83: 15038 | AZ83: 15038 | BA83: 15038 | BB83: 15038 | BC83: 17276 | BD83: 17276 | BE83: 17276 | BF83: 17276 | BG83: 17276 | BH83: 17276 | BI83: 17276 | BJ83: 17276 | BK83: 17276 | BL83: 17276 | BM83: 17276 | BN83: 17276 | BO83: 17276 | BP83: 11951 | BQ83: 11951 | BR83: 11951 | BS83: 11951 | BT83: 11951 | BU83: 11951 | BV83: 11951 | BW83: 11951 | BX83: 11951 | BY83: 11951 | BZ83: 11951 | CA83: 11951 | CB83: 11951 | CC83: 12262 | CD83: 12262 | CE83: 12262 | CF83: 12262 | CG83: 12262 | CH83: 12262 | CI83: 12262 | CJ83: 12262 | CK83: 12262 | CL83: 12262 | CM83: 12262 | CN83: 12262 | CO83: 12262 | CP83: 9458 | CQ83: 9458 | CR83: 9458 | CS83: 9458 | CT83: 9458 | CU83: 9458 | CV83: 9458 | CW83: 9458 | CX83: 9458 | CY83: 9458 | CZ83: 9458 | DA83: 9458 | DB83: 9458 | DC83: 0 | DD83: 0 | DE83: 0 | DF83: 0 | DG83: 0 | DH83: 0 | DI83: 0 | DJ83: 0 | DK83: 0 | DL83: 0 | DM83: 0 | DN83: 0 | DO83: 0 | DP83: 0 | DQ83: 0 | DR83: 0 | DS83: 0 | DT83: 0 | DU83: 0 | DV83: 0 | DW83: 0 | DX83: 0 | DY83: 0 | DZ83: 0 | EA83: 0 | EB83: 0 | EC83: 0 | ED83: 0 | EE83: 0 | EF83: 0 | EG83: 0 | EH83: 0 | EI83: 0 | EJ83: 0 | EK83: 0 | EL83: 0 | EM83: 0 | EN83: 0 | EO83: 0 | EP83: 6351 | EQ83: 6351 | ER83: 6351 | ES83: 6351 | ET83: 6351 | EU83: 6351 | EV83: 6351 | EW83: 6351 | EX83: 6351 | EY83: 6351 | EZ83: 6351 | FA83: 6351 | FB83: 6351 | FC83: 10 | FD83: 10 | FE83: 10 | FF83: 10 | FG83: 10 | FH83: 10 | FI83: 10 | FJ83: 10 | FK83: 10 | FL83: 10 | FM83: 10 | FN83: 10 | FO83: 10
B84: SERVIU Valparaíso | C84: 22603 | D84: 22603 | E84: 22603 | F84: 22603 | G84: 22603 | H84: 22603 | I84: 22603 | J84: 22603 | K84: 22603 | L84: 22603 | M84: 22603 | N84: 22603 | O84: 22603 | P84: 126364 | Q84: 126364 | R84: 126364 | S84: 126364 | T84: 126364 | U84: 126364 | V84: 126364 | W84: 126364 | X84: 126364 | Y84: 126364 | Z84: 126364 | AA84: 126364 | AB84: 126364 | AC84: 572264 | AD84: 572264 | AE84: 572264 | AF84: 572264 | AG84: 572264 | AH84: 572264 | AI84: 572264 | AJ84: 572264 | AK84: 572264 | AL84: 572264 | AM84: 572264 | AN84: 572264 | AO84: 572264 | AP84: 187666 | AQ84: 187666 | AR84: 187666 | AS84: 187666 | AT84: 187666 | AU84: 187666 | AV84: 187666 | AW84: 187666 | AX84: 187666 | AY84: 187666 | AZ84: 187666 | BA84: 187666 | BB84: 187666 | BC84: 29913 | BD84: 29913 | BE84: 29913 | BF84: 29913 | BG84: 29913 | BH84: 29913 | BI84: 29913 | BJ84: 29913 | BK84: 29913 | BL84: 29913 | BM84: 29913 | BN84: 29913 | BO84: 29913 | BP84: 22012 | BQ84: 22012 | BR84: 22012 | BS84: 22012 | BT84: 22012 | BU84: 22012 | BV84: 22012 | BW84: 22012 | BX84: 22012 | BY84: 22012 | BZ84: 22012 | CA84: 22012 | CB84: 22012 | CC84: 180044 | CD84: 180044 | CE84: 180044 | CF84: 180044 | CG84: 180044 | CH84: 180044 | CI84: 180044 | CJ84: 180044 | CK84: 180044 | CL84: 180044 | CM84: 180044 | CN84: 180044 | CO84: 180044 | CP84: 16432 | CQ84: 16432 | CR84: 16432 | CS84: 16432 | CT84: 16432 | CU84: 16432 | CV84: 16432 | CW84: 16432 | CX84: 16432 | CY84: 16432 | CZ84: 16432 | DA84: 16432 | DB84: 16432 | DC84: 0 | DD84: 0 | DE84: 0 | DF84: 0 | DG84: 0 | DH84: 0 | DI84: 0 | DJ84: 0 | DK84: 0 | DL84: 0 | DM84: 0 | DN84: 0 | DO84: 0 | DP84: 3986250 | DQ84: 3986250 | DR84: 3986250 | DS84: 3986250 | DT84: 3986250 | DU84: 3986250 | DV84: 3986250 | DW84: 3986250 | DX84: 3986250 | DY84: 3986250 | DZ84: 3986250 | EA84: 3986250 | EB84: 3986250 | EC84: 0 | ED84: 0 | EE84: 0 | EF84: 0 | EG84: 0 | EH84: 0 | EI84: 0 | EJ84: 0 | EK84: 0 | EL84: 0 | EM84: 0 | EN84: 0 | EO84: 0 | EP84: 7515 | EQ84: 7515 | ER84: 7515 | ES84: 7515 | ET84: 7515 | EU84: 7515 | EV84: 7515 | EW84: 7515 | EX84: 7515 | EY84: 7515 | EZ84: 7515 | FA84: 7515 | FB84: 7515 | FC84: 10 | FD84: 10 | FE84: 10 | FF84: 10 | FG84: 10 | FH84: 10 | FI84: 10 | FJ84: 10 | FK84: 10 | FL84: 10 | FM84: 10 | FN84: 10 | FO84: 10
B85: SERVIU Metropolitano | C85: 52172 | D85: 52172 | E85: 52172 | F85: 52172 | G85: 52172 | H85: 52172 | I85: 52172 | J85: 52172 | K85: 52172 | L85: 52172 | M85: 52172 | N85: 52172 | O85: 52172 | P85: 6810295 | Q85: 6810295 | R85: 6810295 | S85: 6810295 | T85: 6810295 | U85: 6810295 | V85: 6810295 | W85: 6810295 | X85: 6810295 | Y85: 6810295 | Z85: 6810295 | AA85: 6810295 | AB85: 6810295 | AC85: 106766 | AD85: 106766 | AE85: 106766 | AF85: 106766 | AG85: 106766 | AH85: 106766 | AI85: 106766 | AJ85: 106766 | AK85: 106766 | AL85: 106766 | AM85: 106766 | AN85: 106766 | AO85: 106766 | AP85: 82915 | AQ85: 82915 | AR85: 82915 | AS85: 82915 | AT85: 82915 | AU85: 82915 | AV85: 82915 | AW85: 82915 | AX85: 82915 | AY85: 82915 | AZ85: 82915 | BA85: 82915 | BB85: 82915 | BC85: 115897 | BD85: 115897 | BE85: 115897 | BF85: 115897 | BG85: 115897 | BH85: 115897 | BI85: 115897 | BJ85: 115897 | BK85: 115897 | BL85: 115897 | BM85: 115897 | BN85: 115897 | BO85: 115897 | BP85: 71643 | BQ85: 71643 | BR85: 71643 | BS85: 71643 | BT85: 71643 | BU85: 71643 | BV85: 71643 | BW85: 71643 | BX85: 71643 | BY85: 71643 | BZ85: 71643 | CA85: 71643 | CB85: 71643 | CC85: 73506 | CD85: 73506 | CE85: 73506 | CF85: 73506 | CG85: 73506 | CH85: 73506 | CI85: 73506 | CJ85: 73506 | CK85: 73506 | CL85: 73506 | CM85: 73506 | CN85: 73506 | CO85: 73506 | CP85: 45774 | CQ85: 45774 | CR85: 45774 | CS85: 45774 | CT85: 45774 | CU85: 45774 | CV85: 45774 | CW85: 45774 | CX85: 45774 | CY85: 45774 | CZ85: 45774 | DA85: 45774 | DB85: 45774 | DC85: 0 | DD85: 0 | DE85: 0 | DF85: 0 | DG85: 0 | DH85: 0 | DI85: 0 | DJ85: 0 | DK85: 0 | DL85: 0 | DM85: 0 | DN85: 0 | DO85: 0 | DP85: 9301250 | DQ85: 9301250 | DR85: 9301250 | DS85: 9301250 | DT85: 9301250 | DU85: 9301250 | DV85: 9301250 | DW85: 9301250 | DX85: 9301250 | DY85: 9301250 | DZ85: 9301250 | EA85: 9301250 | EB85: 9301250 | EC85: 0 | ED85: 0 | EE85: 0 | EF85: 0 | EG85: 0 | EH85: 0 | EI85: 0 | EJ85: 0 | EK85: 0 | EL85: 0 | EM85: 0 | EN85: 0 | EO85: 0 | EP85: 18756 | EQ85: 18756 | ER85: 18756 | ES85: 18756 | ET85: 18756 | EU85: 18756 | EV85: 18756 | EW85: 18756 | EX85: 18756 | EY85: 18756 | EZ85: 18756 | FA85: 18756 | FB85: 18756 | FC85: 10 | FD85: 10 | FE85: 10 | FF85: 10 | FG85: 10 | FH85: 10 | FI85: 10 | FJ85: 10 | FK85: 10 | FL85: 10 | FM85: 10 | FN85: 10 | FO85: 10
B86: SERVIU O'Higgins | C86: 20560 | D86: 20560 | E86: 20560 | F86: 20560 | G86: 20560 | H86: 20560 | I86: 20560 | J86: 20560 | K86: 20560 | L86: 20560 | M86: 20560 | N86: 20560 | O86: 20560 | P86: 22608 | Q86: 22608 | R86: 22608 | S86: 22608 | T86: 22608 | U86: 22608 | V86: 22608 | W86: 22608 | X86: 22608 | Y86: 22608 | Z86: 22608 | AA86: 22608 | AB86: 22608 | AC86: 945905 | AD86: 945905 | AE86: 945905 | AF86: 945905 | AG86: 945905 | AH86: 945905 | AI86: 945905 | AJ86: 945905 | AK86: 945905 | AL86: 945905 | AM86: 945905 | AN86: 945905 | AO86: 945905 | AP86: 16995 | AQ86: 16995 | AR86: 16995 | AS86: 16995 | AT86: 16995 | AU86: 16995 | AV86: 16995 | AW86: 16995 | AX86: 16995 | AY86: 16995 | AZ86: 16995 | BA86: 16995 | BB86: 16995 | BC86: 17432 | BD86: 17432 | BE86: 17432 | BF86: 17432 | BG86: 17432 | BH86: 17432 | BI86: 17432 | BJ86: 17432 | BK86: 17432 | BL86: 17432 | BM86: 17432 | BN86: 17432 | BO86: 17432 | BP86: 936647 | BQ86: 936647 | BR86: 936647 | BS86: 936647 | BT86: 936647 | BU86: 936647 | BV86: 936647 | BW86: 936647 | BX86: 936647 | BY86: 936647 | BZ86: 936647 | CA86: 936647 | CB86: 936647 | CC86: 3242677 | CD86: 3242677 | CE86: 3242677 | CF86: 3242677 | CG86: 3242677 | CH86: 3242677 | CI86: 3242677 | CJ86: 3242677 | CK86: 3242677 | CL86: 3242677 | CM86: 3242677 | CN86: 3242677 | CO86: 3242677 | CP86: 11095 | CQ86: 11095 | CR86: 11095 | CS86: 11095 | CT86: 11095 | CU86: 11095 | CV86: 11095 | CW86: 11095 | CX86: 11095 | CY86: 11095 | CZ86: 11095 | DA86: 11095 | DB86: 11095 | DC86: 0 | DD86: 0 | DE86: 0 | DF86: 0 | DG86: 0 | DH86: 0 | DI86: 0 | DJ86: 0 | DK86: 0 | DL86: 0 | DM86: 0 | DN86: 0 | DO86: 0 | DP86: 0 | DQ86: 0 | DR86: 0 | DS86: 0 | DT86: 0 | DU86: 0 | DV86: 0 | DW86: 0 | DX86: 0 | DY86: 0 | DZ86: 0 | EA86: 0 | EB86: 0 | EC86: 0 | ED86: 0 | EE86: 0 | EF86: 0 | EG86: 0 | EH86: 0 | EI86: 0 | EJ86: 0 | EK86: 0 | EL86: 0 | EM86: 0 | EN86: 0 | EO86: 0 | EP86: 7815 | EQ86: 7815 | ER86: 7815 | ES86: 7815 | ET86: 7815 | EU86: 7815 | EV86: 7815 | EW86: 7815 | EX86: 7815 | EY86: 7815 | EZ86: 7815 | FA86: 7815 | FB86: 7815 | FC86: 10 | FD86: 10 | FE86: 10 | FF86: 10 | FG86: 10 | FH86: 10 | FI86: 10 | FJ86: 10 | FK86: 10 | FL86: 10 | FM86: 10 | FN86: 10 | FO86: 10
B87: SERVIU Maule | C87: 22041 | D87: 22041 | E87: 22041 | F87: 22041 | G87: 22041 | H87: 22041 | I87: 22041 | J87: 22041 | K87: 22041 | L87: 22041 | M87: 22041 | N87: 22041 | O87: 22041 | P87: 24650 | Q87: 24650 | R87: 24650 | S87: 24650 | T87: 24650 | U87: 24650 | V87: 24650 | W87: 24650 | X87: 24650 | Y87: 24650 | Z87: 24650 | AA87: 24650 | AB87: 24650 | AC87: 25151 | AD87: 25151 | AE87: 25151 | AF87: 25151 | AG87: 25151 | AH87: 25151 | AI87: 25151 | AJ87: 25151 | AK87: 25151 | AL87: 25151 | AM87: 25151 | AN87: 25151 | AO87: 25151 | AP87: 692985 | AQ87: 692985 | AR87: 692985 | AS87: 692985 | AT87: 692985 | AU87: 692985 | AV87: 692985 | AW87: 692985 | AX87: 692985 | AY87: 692985 | AZ87: 692985 | BA87: 692985 | BB87: 692985 | BC87: 1462323 | BD87: 1462323 | BE87: 1462323 | BF87: 1462323 | BG87: 1462323 | BH87: 1462323 | BI87: 1462323 | BJ87: 1462323 | BK87: 1462323 | BL87: 1462323 | BM87: 1462323 | BN87: 1462323 | BO87: 1462323 | BP87: 563609 | BQ87: 563609 | BR87: 563609 | BS87: 563609 | BT87: 563609 | BU87: 563609 | BV87: 563609 | BW87: 563609 | BX87: 563609 | BY87: 563609 | BZ87: 563609 | CA87: 563609 | CB87: 563609 | CC87: 12650 | CD87: 12650 | CE87: 12650 | CF87: 12650 | CG87: 12650 | CH87: 12650 | CI87: 12650 | CJ87: 12650 | CK87: 12650 | CL87: 12650 | CM87: 12650 | CN87: 12650 | CO87: 12650 | CP87: 7055 | CQ87: 7055 | CR87: 7055 | CS87: 7055 | CT87: 7055 | CU87: 7055 | CV87: 7055 | CW87: 7055 | CX87: 7055 | CY87: 7055 | CZ87: 7055 | DA87: 7055 | DB87: 7055 | DC87: 0 | DD87: 0 | DE87: 0 | DF87: 0 | DG87: 0 | DH87: 0 | DI87: 0 | DJ87: 0 | DK87: 0 | DL87: 0 | DM87: 0 | DN87: 0 | DO87: 0 | DP87: 0 | DQ87: 0 | DR87: 0 | DS87: 0 | DT87: 0 | DU87: 0 | DV87: 0 | DW87: 0 | DX87: 0 | DY87: 0 | DZ87: 0 | EA87: 0 | EB87: 0 | EC87: 0 | ED87: 0 | EE87: 0 | EF87: 0 | EG87: 0 | EH87: 0 | EI87: 0 | EJ87: 0 | EK87: 0 | EL87: 0 | EM87: 0 | EN87: 0 | EO87: 0 | EP87: 3126 | EQ87: 3126 | ER87: 3126 | ES87: 3126 | ET87: 3126 | EU87: 3126 | EV87: 3126 | EW87: 3126 | EX87: 3126 | EY87: 3126 | EZ87: 3126 | FA87: 3126 | FB87: 3126 | FC87: 10 | FD87: 10 | FE87: 10 | FF87: 10 | FG87: 10 | FH87: 10 | FI87: 10 | FJ87: 10 | FK87: 10 | FL87: 10 | FM87: 10 | FN87: 10 | FO87: 10
B88: SERVIU Ñuble | C88: 0 | D88: 0 | E88: 0 | F88: 0 | G88: 0 | H88: 0 | I88: 0 | J88: 0 | K88: 0 | L88: 0 | M88: 0 | N88: 0 | O88: 0 | P88: 0 | Q88: 0 | R88: 0 | S88: 0 | T88: 0 | U88: 0 | V88: 0 | W88: 0 | X88: 0 | Y88: 0 | Z88: 0 | AA88: 0 | AB88: 0 | AC88: 0 | AD88: 0 | AE88: 0 | AF88: 0 | AG88: 0 | AH88: 0 | AI88: 0 | AJ88: 0 | AK88: 0 | AL88: 0 | AM88: 0 | AN88: 0 | AO88: 0 | AP88: 0 | AQ88: 0 | AR88: 0 | AS88: 0 | AT88: 0 | AU88: 0 | AV88: 0 | AW88: 0 | AX88: 0 | AY88: 0 | AZ88: 0 | BA88: 0 | BB88: 0 | BC88: 0 | BD88: 0 | BE88: 0 | BF88: 0 | BG88: 0 | BH88: 0 | BI88: 0 | BJ88: 0 | BK88: 0 | BL88: 0 | BM88: 0 | BN88: 0 | BO88: 0 | BP88: 68447 | BQ88: 68447 | BR88: 68447 | BS88: 68447 | BT88: 68447 | BU88: 68447 | BV88: 68447 | BW88: 68447 | BX88: 68447 | BY88: 68447 | BZ88: 68447 | CA88: 68447 | CB88: 68447 | CC88: 21975 | CD88: 21975 | CE88: 21975 | CF88: 21975 | CG88: 21975 | CH88: 21975 | CI88: 21975 | CJ88: 21975 | CK88: 21975 | CL88: 21975 | CM88: 21975 | CN88: 21975 | CO88: 21975 | CP88: 15569 | CQ88: 15569 | CR88: 15569 | CS88: 15569 | CT88: 15569 | CU88: 15569 | CV88: 15569 | CW88: 15569 | CX88: 15569 | CY88: 15569 | CZ88: 15569 | DA88: 15569 | DB88: 15569 | DC88: 0 | DD88: 0 | DE88: 0 | DF88: 0 | DG88: 0 | DH88: 0 | DI88: 0 | DJ88: 0 | DK88: 0 | DL88: 0 | DM88: 0 | DN88: 0 | DO88: 0 | DP88: 3986250 | DQ88: 3986250 | DR88: 3986250 | DS88: 3986250 | DT88: 3986250 | DU88: 3986250 | DV88: 3986250 | DW88: 3986250 | DX88: 3986250 | DY88: 3986250 | DZ88: 3986250 | EA88: 3986250 | EB88: 3986250 | EC88: 0 | ED88: 0 | EE88: 0 | EF88: 0 | EG88: 0 | EH88: 0 | EI88: 0 | EJ88: 0 | EK88: 0 | EL88: 0 | EM88: 0 | EN88: 0 | EO88: 0 | EP88: 9378 | EQ88: 9378 | ER88: 9378 | ES88: 9378 | ET88: 9378 | EU88: 9378 | EV88: 9378 | EW88: 9378 | EX88: 9378 | EY88: 9378 | EZ88: 9378 | FA88: 9378 | FB88: 9378 | FC88: 10 | FD88: 10 | FE88: 10 | FF88: 10 | FG88: 10 | FH88: 10 | FI88: 10 | FJ88: 10 | FK88: 10 | FL88: 10 | FM88: 10 | FN88: 10 | FO88: 10
... B94: SERVIU Magallanes | C94: 7804 | D94: 7804 | E94: 7804 | F94: 7804 | G94: 7804 | H94: 7804 | I94: 7804 | J94: 7804 | K94: 7804 | L94: 7804 | M94: 7804 | N94: 7804 | O94: 7804 | P94: 14053 | Q94: 14053 | R94: 14053 | S94: 14053 | T94: 14053 | U94: 14053 | V94: 14053 | W94: 14053 | X94: 14053 | Y94: 14053 | Z94: 14053 | AA94: 14053 | AB94: 14053 | AC94: 16140 | AD94: 16140 | AE94: 16140 | AF94: 16140 | AG94: 16140 | AH94: 16140 | AI94: 16140 | AJ94: 16140 | AK94: 16140 | AL94: 16140 | AM94: 16140 | AN94: 16140 | AO94: 16140 | AP94: 16480 | AQ94: 16480 | AR94: 16480 | AS94: 16480 | AT94: 16480 | AU94: 16480 | AV94: 16480 | AW94: 16480 | AX94: 16480 | AY94: 16480 | AZ94: 16480 | BA94: 16480 | BB94: 16480 | BC94: 24722 | BD94: 24722 | BE94: 24722 | BF94: 24722 | BG94: 24722 | BH94: 24722 | BI94: 24722 | BJ94: 24722 | BK94: 24722 | BL94: 24722 | BM94: 24722 | BN94: 24722 | BO94: 24722 | BP94: 12364 | BQ94: 12364 | BR94: 12364 | BS94: 12364 | BT94: 12364 | BU94: 12364 | BV94: 12364 | BW94: 12364 | BX94: 12364 | BY94: 12364 | BZ94: 12364 | CA94: 12364 | CB94: 12364 | CC94: 12685 | CD94: 12685 | CE94: 12685 | CF94: 12685 | CG94: 12685 | CH94: 12685 | CI94: 12685 | CJ94: 12685 | CK94: 12685 | CL94: 12685 | CM94: 12685 | CN94: 12685 | CO94: 12685 | CP94: 8750 | CQ94: 8750 | CR94: 8750 | CS94: 8750 | CT94: 8750 | CU94: 8750 | CV94: 8750 | CW94: 8750 | CX94: 8750 | CY94: 8750 | CZ94: 8750 | DA94: 8750 | DB94: 8750 | DC94: 0 | DD94: 0 | DE94: 0 | DF94: 0 | DG94: 0 | DH94: 0 | DI94: 0 | DJ94: 0 | DK94: 0 | DL94: 0 | DM94: 0 | DN94: 0 | DO94: 0 | DP94: 0 | DQ94: 0 | DR94: 0 | DS94: 0 | DT94: 0 | DU94: 0 | DV94: 0 | DW94: 0 | DX94: 0 | DY94: 0 | DZ94: 0 | EA94: 0 | EB94: 0 | EC94: 0 | ED94: 0 | EE94: 0 | EF94: 0 | EG94: 0 | EH94: 0 | EI94: 0 | EJ94: 0 | EK94: 0 | EL94: 0 | EM94: 0 | EN94: 0 | EO94: 0 | EP94: 4168 | EQ94: 4168 | ER94: 4168 | ES94: 4168 | ET94: 4168 | EU94: 4168 | EV94: 4168 | EW94: 4168 | EX94: 4168 | EY94: 4168 | EZ94: 4168 | FA94: 4168 | FB94: 4168 | FC94: 10 | FD94: 10 | FE94: 10 | FF94: 10 | FG94: 10 | FH94: 10 | FI94: 10 | FJ94: 10 | FK94: 10 | FL94: 10 | FM94: 10 | FN94: 10 | FO94: 10
B95: Total Presupuesto Ley (Subtítulo 29) | C95: =SUM(C77:C94) -> 4451662 | D95: =SUM(D77:D94) -> 4451662 | E95: =SUM(E77:E94) -> 16220442 | F95: =SUM(F77:F94) -> 16220442 | G95: =SUM(G77:G94) -> 16220442 | H95: =SUM(H77:H94) -> 16220442 | I95: =SUM(I77:I94) -> 16220442 | J95: =SUM(J77:J94) -> 16220442 | ... FO95: =SUM(FO77:FO94) -> 4182864
B96: Presupuesto Vigente (Subtítulo 29)
C97: 2014 | P97: 2015 | AC97: 2016 | AP97: 2017 | BC97: 2018 | BP97: 2019 | CC97: 2020 | CP97: 2021 | DC97: 2022 | DP97: 2023 | EC97: 2024 | EP97: 2025 | FC97: 2026
B98: Programa / Entidad | C98: Ene | D98: Feb | E98: Mar | F98: Abr | G98: May | H98: Jun | I98: Jul | J98: Ago | K98: Sep | L98: Oct | M98: Nov | N98: Dic | O98: Total 2014 | P98: Ene | Q98: Feb | R98: Mar | S98: Abr | T98: May | U98: Jun | V98: Jul | W98: Ago | X98: Sep | Y98: Oct | Z98: Nov | AA98: Dic | AB98: Total 2015 | AC98: Ene | AD98: Feb | AE98: Mar | AF98: Abr | AG98: May | AH98: Jun | AI98: Jul | AJ98: Ago | AK98: Sep | AL98: Oct | AM98: Nov | AN98: Dic | AO98: Total 2016 | AP98: Ene | AQ98: Feb | AR98: Mar | AS98: Abr | AT98: May | AU98: Jun | AV98: Jul | AW98: Ago | AX98: Sep | AY98: Oct | AZ98: Nov | BA98: Dic | BB98: Total 2017 | BC98: Ene | BD98: Feb | BE98: Mar | BF98: Abr | BG98: May | BH98: Jun | BI98: Jul | BJ98: Ago | BK98: Sep | BL98: Oct | BM98: Nov | BN98: Dic | BO98: Total 2018 | BP98: Ene | BQ98: Feb | BR98: Mar | BS98: Abr | BT98: May | BU98: Jun | BV98: Jul | BW98: Ago | BX98: Sep | BY98: Oct | BZ98: Nov | CA98: Dic | CB98: Total 2019 | CC98: Ene | CD98: Feb | CE98: Mar | CF98: Abr | CG98: May | CH98: Jun | CI98: Jul | CJ98: Ago | CK98: Sep | CL98: Oct | CM98: Nov | CN98: Dic | CO98: Total 2020 | CP98: Ene | CQ98: Feb | CR98: Mar | CS98: Abr | CT98: May | CU98: Jun | CV98: Jul | CW98: Ago | CX98: Sep | CY98: Oct | CZ98: Nov | DA98: Dic | DB98: Total 2021 | DC98: Ene | DD98: Feb | DE98: Mar | DF98: Abr | DG98: May | DH98: Jun | DI98: Jul | DJ98: Ago | DK98: Sep | DL98: Oct | DM98: Nov | DN98: Dic | DO98: Total 2022 | DP98: Ene | DQ98: Feb | DR98: Mar | DS98: Abr | DT98: May | DU98: Jun | DV98: Jul | DW98: Ago | DX98: Sep | DY98: Oct | DZ98: Nov | EA98: Dic | EB98: Total 2023 | EC98: Ene | ED98: Feb | EE98: Mar | EF98: Abr | EG98: May | EH98: Jun | EI98: Jul | EJ98: Ago | EK98: Sep | EL98: Oct | EM98: Nov | EN98: Dic | EO98: Total 2024 | EP98: Ene | EQ98: Feb | ER98: Mar | ES98: Abr | ET98: May | EU98: Jun | EV98: Jul | EW98: Ago | EX98: Sep | EY98: Oct | EZ98: Nov | FA98: Dic | FB98: Total 2025 | FC98: Ene | FD98: Feb | FE98: Mar | FF98: Abr | FG98: May | FH98: Jun | FI98: Jul | FJ98: Ago | FK98: Sep | FL98: Oct | FM98: Nov | FN98: Dic | FO98: Total 2026
B99: Subsecretaría y Programas Centrales | C99: 4128812 | D99: 4128812 | E99: 15897592 | F99: 15897592 | G99: 15897592 | H99: 15891592 | I99: 15891592 | J99: 15765687 | K99: 4289447 | L99: 4289447 | M99: 4752812 | N99: 4752812 | O99: 4752812 | P99: 4693552 | Q99: 4693552 | R99: 4693552 | S99: 4693552 | T99: 4693552 | U99: 4693552 | V99: 4693552 | W99: 4702608 | X99: 4702608 | Y99: 4702608 | Z99: 4702608 | AA99: 4702608 | AB99: 4702608 | AC99: 3911026 | AD99: 3911026 | AE99: 3911026 | AF99: 3801216 | AG99: 3801216 | AH99: 3756148 | AI99: 3756148 | AJ99: 3756148 | AK99: 3771148 | AL99: 3871148 | AM99: 3871148 | AN99: 3871148 | AO99: 3871148 | AP99: 4389807 | AQ99: 4389807 | AR99: 4389807 | AS99: 4389807 | AT99: 4377222 | AU99: 4377222 | AV99: 4377222 | AW99: 4350459 | AX99: 4353459 | AY99: 4353459 | AZ99: 4353459 | BA99: 4352479 | BB99: 4352479 | BC99: 4513827 | BD99: 4513827 | BE99: 4513827 | BF99: 4513827 | BG99: 4513827 | BH99: 4513827 | BI99: 3946764 | BJ99: 3946764 | BK99: 3946764 | BL99: 3946764 | BM99: 3977035 | BN99: 3977035 | BO99: 3977035 | BP99: 4195666 | BQ99: 4195666 | BR99: 4195666 | BS99: 4195666 | BT99: 4195666 | BU99: 4195666 | BV99: 4195666 | BW99: 4195666 | BX99: 4195666 | BY99: 4195666 | BZ99: 4195666 | CA99: 4202266 | CB99: 4202266 | CC99: 4783688 | CD99: 4783688 | CE99: 4783688 | CF99: 4101143 | CG99: 3490652 | CH99: 3490652 | CI99: 3490652 | CJ99: 3490652 | CK99: 3490652 | CL99: 3490652 | CM99: 3532198 | CN99: 2924379 | CO99: 2924379 | CP99: 3949109 | CQ99: 3949109 | CR99: 3949109 | CS99: 3949109 | CT99: 3949109 | CU99: 3938465 | CV99: 3938465 | CW99: 3938465 | CX99: 3938465 | CY99: 3938465 | CZ99: 3928965 | DA99: 3199280 | DB99: 3199280 | DC99: 3677484 | DD99: 3677484 | DE99: 3677484 | DF99: 3677484 | DG99: 3771152 | DH99: 3841152 | DI99: 3841152 | DJ99: 3841152 | DK99: 3841152 | DL99: 3928152 | DM99: 3928152 | DN99: 3784939 | DO99: 3784939 | DP99: 4127526 | DQ99: 4127526 | DR99: 4127526 | DS99: 4127526 | DT99: 4127526 | DU99: 4127526 | DV99: 4127526 | DW99: 4127526 | DX99: 4127526 | DY99: 4127526 | DZ99: 4127526 | EA99: 3999809 | EB99: 3999809 | EC99: 30674754 | ED99: 30674754 | EE99: 30674754 | EF99: 30674754 | EG99: 30710139 | EH99: 27678180 | EI99: 27678180 | EJ99: 27678180 | EK99: 27678180 | EL99: 27641880 | EM99: 3168714 | EN99: 3168714 | EO99: 3168714 | EP99: 4435821 | EQ99: 4435821 | ER99: 4435821 | ES99: 4435821 | ET99: 4435821 | EU99: 4435821 | EV99: 4435821 | EW99: 4435821 | EX99: 4435821 | EY99: 4435821 | EZ99: 4435821 | FA99: 4435821 | FB99: 4435821 | FC99: 4182704 | FD99: 4182704 | FE99: 4182704 | FF99: 4182704 | FG99: 4182704 | FH99: 4182704 | FI99: 4182704 | FJ99: 4182704 | FK99: 4182704 | FL99: 4182704 | FM99: 4182704 | FN99: 4182704 | FO99: 4182704
B100: Parque Metropolitano (PARQUEMET) | C100: 54576 | D100: 54576 | E100: 54576 | F100: 54576 | G100: 54576 | H100: 54576 | I100: 54576 | J100: 54576 | K100: 54576 | L100: 54576 | M100: 54576 | N100: 54576 | O100: 54576 | P100: 56213 | Q100: 56213 | R100: 56213 | S100: 56213 | T100: 116213 | U100: 116213 | V100: 116213 | W100: 116213 | X100: 116213 | Y100: 116213 | Z100: 116213 | AA100: 116213 | AB100: 116213 | AC100: 58349 | AD100: 58349 | AE100: 58349 | AF100: 58349 | AG100: 58349 | AH100: 58349 | AI100: 58349 | AJ100: 58349 | AK100: 58349 | AL100: 58349 | AM100: 58349 | AN100: 58349 | AO100: 58349 | AP100: 64890 | AQ100: 64890 | AR100: 64890 | AS100: 64890 | AT100: 64890 | AU100: 64890 | AV100: 64890 | AW100: 78955 | AX100: 78955 | AY100: 78955 | AZ100: 78955 | BA100: 78955 | BB100: 78955 | BC100: 104652 | BD100: 104652 | BE100: 104652 | BF100: 104652 | BG100: 104652 | BH100: 104652 | BI100: 90187 | BJ100: 90187 | BK100: 90187 | BL100: 90187 | BM100: 90187 | BN100: 90187 | BO100: 90187 | BP100: 141261 | BQ100: 141261 | BR100: 141261 | BS100: 141261 | BT100: 141261 | BU100: 141261 | BV100: 141261 | BW100: 141261 | BX100: 141261 | BY100: 141261 | BZ100: 141261 | CA100: 141261 | CB100: 141261 | CC100: 144934 | CD100: 144934 | CE100: 144934 | CF100: 132217 | CG100: 68090 | CH100: 68090 | CI100: 68090 | CJ100: 68090 | CK100: 68090 | CL100: 68090 | CM100: 144934 | CN100: 144934 | CO100: 144934 | CP100: 71111 | CQ100: 71111 | CR100: 71111 | CS100: 71111 | CT100: 71111 | CU100: 71111 | CV100: 71111 | CW100: 71111 | CX100: 71111 | CY100: 71111 | CZ100: 80111 | DA100: 80111 | DB100: 80111 | DC100: 33328 | DD100: 33328 | DE100: 33328 | DF100: 33328 | DG100: 33328 | DH100: 33328 | DI100: 33328 | DJ100: 33328 | DK100: 33328 | DL100: 33328 | DM100: 33328 | DN100: 33328 | DO100: 33328 | DP100: 0 | DQ100: 0 | DR100: 0 | DS100: 0 | DT100: 0 | DU100: 0 | DV100: 0 | DW100: 0 | DX100: 0 | DY100: 0 | DZ100: 0 | EA100: 0 | EB100: 0 | EC100: 0 | ED100: 0 | EE100: 0 | EF100: 0 | EG100: 6773 | EH100: 6773 | EI100: 6773 | EJ100: 240920 | EK100: 240920 | EL100: 240920 | EM100: 240920 | EN100: 240920 | EO100: 240920 | EP100: 6929 | EQ100: 6929 | ER100: 6929 | ES100: 6929 | ET100: 6929 | EU100: 6929 | EV100: 6929 | EW100: 6929 | EX100: 6929 | EY100: 6929 | EZ100: 6929 | FA100: 6929 | FB100: 6929 | FC100: 0 | FD100: 0 | FE100: 0 | FF100: 0 | FG100: 0 | FH100: 0 | FI100: 0 | FJ100: 0 | FK100: 0 | FL100: 0 | FM100: 0 | FN100: 0 | FO100: 0
B101: SERVIU Arica y Parinacota | C101: 23059 | D101: 23059 | E101: 23059 | F101: 23059 | G101: 23059 | H101: 23059 | I101: 23059 | J101: 23059 | K101: 4525059 | L101: 4525059 | M101: 5264599 | N101: 5264599 | O101: 5264599 | P101: 24642 | Q101: 24642 | R101: 24642 | S101: 24642 | T101: 24642 | U101: 24642 | V101: 4477642 | W101: 4477642 | X101: 4477642 | Y101: 4477642 | Z101: 4477642 | AA101: 3795311 | AB101: 3795311 | AC101: 23431 | AD101: 23431 | AE101: 23431 | AF101: 23431 | AG101: 23431 | AH101: 33414 | AI101: 33414 | AJ101: 33414 | AK101: 33414 | AL101: 214280 | AM101: 214280 | AN101: 214280 | AO101: 214280 | AP101: 13390 | AQ101: 13390 | AR101: 13390 | AS101: 13390 | AT101: 13390 | AU101: 13390 | AV101: 13390 | AW101: 13390 | AX101: 13390 | AY101: 263946 | AZ101: 263946 | BA101: 385001 | BB101: 385001 | BC101: 18468 | BD101: 18468 | BE101: 18468 | BF101: 18468 | BG101: 18468 | BH101: 18468 | BI101: 15354 | BJ101: 15354 | BK101: 15354 | BL101: 15354 | BM101: 15354 | BN101: 15354 | BO101: 15354 | BP101: 11102 | BQ101: 11102 | BR101: 11102 | BS101: 11102 | BT101: 161557 | BU101: 161557 | BV101: 161557 | BW101: 161557 | BX101: 161557 | BY101: 161557 | BZ101: 161557 | CA101: 161557 | CB101: 161557 | CC101: 11391 | CD101: 11391 | CE101: 11391 | CF101: 7974 | CG101: 3986 | CH101: 3986 | CI101: 3986 | CJ101: 3986 | CK101: 3986 | CL101: 88628 | CM101: 96033 | CN101: 96033 | CO101: 96033 | CP101: 8967 | CQ101: 8967 | CR101: 8967 | CS101: 8967 | CT101: 8967 | CU101: 8967 | CV101: 8967 | CW101: 8967 | CX101: 8967 | CY101: 8967 | CZ101: 6258817 | DA101: 6258817 | DB101: 6258817 | DC101: 0 | DD101: 0 | DE101: 0 | DF101: 0 | DG101: 0 | DH101: 0 | DI101: 0 | DJ101: 0 | DK101: 7943900 | DL101: 7943900 | DM101: 9744243 | DN101: 9744243 | DO101: 9744243 | DP101: 0 | DQ101: 0 | DR101: 0 | DS101: 0 | DT101: 0 | DU101: 0 | DV101: 0 | DW101: 0 | DX101: 0 | DY101: 0 | DZ101: 0 | EA101: 0 | EB101: 0 | EC101: 0 | ED101: 0 | EE101: 0 | EF101: 0 | EG101: 5926 | EH101: 5926 | EI101: 5926 | EJ101: 5926 | EK101: 5926 | EL101: 7496 | EM101: 7496 | EN101: 7496 | EO101: 7496 | EP101: 2970 | EQ101: 2970 | ER101: 2970 | ES101: 2970 | ET101: 2970 | EU101: 2970 | EV101: 2970 | EW101: 2970 | EX101: 2970 | EY101: 2970 | EZ101: 2970 | FA101: 2970 | FB101: 2970 | FC101: 10 | FD101: 10 | FE101: 10 | FF101: 10 | FG101: 10 | FH101: 10 | FI101: 10 | FJ101: 10 | FK101: 10 | FL101: 10 | FM101: 10 | FN101: 10 | FO101: 10
B102: SERVIU Tarapacá | C102: 9750 | D102: 9750 | E102: 9750 | F102: 9750 | G102: 9750 | H102: 9750 | I102: 9750 | J102: 9750 | K102: 9750 | L102: 9750 | M102: 9750 | N102: 1673736 | O102: 1673736 | P102: 15091 | Q102: 3847256 | R102: 3847256 | S102: 6300204 | T102: 6300204 | U102: 6527454 | V102: 6527454 | W102: 6527454 | X102: 6527454 | Y102: 9418442 | Z102: 11296606 | AA102: 11296606 | AB102: 11296606 | AC102: 14630 | AD102: 14630 | AE102: 14630 | AF102: 34819 | AG102: 8652905 | AH102: 8652905 | AI102: 8652905 | AJ102: 8790900 | AK102: 8790900 | AL102: 8790900 | AM102: 8790900 | AN102: 8790900 | AO102: 8790900 | AP102: 15965 | AQ102: 15965 | AR102: 15965 | AS102: 15965 | AT102: 18965 | AU102: 665828 | AV102: 665828 | AW102: 665828 | AX102: 665828 | AY102: 678411 | AZ102: 678411 | BA102: 678411 | BB102: 678411 | BC102: 15148 | BD102: 15148 | BE102: 15148 | BF102: 15148 | BG102: 15148 | BH102: 15148 | BI102: 12510 | BJ102: 12510 | BK102: 12510 | BL102: 12510 | BM102: 12510 | BN102: 12510 | BO102: 12510 | BP102: 17987 | BQ102: 17987 | BR102: 17987 | BS102: 17987 | BT102: 17987 | BU102: 17987 | BV102: 17987 | BW102: 17987 | BX102: 17987 | BY102: 17987 | BZ102: 17987 | CA102: 60987 | CB102: 60987 | CC102: 18455 | CD102: 18455 | CE102: 18455 | CF102: 12918 | CG102: 7232 | CH102: 2243714 | CI102: 2243714 | CJ102: 2243714 | CK102: 2243714 | CL102: 2243714 | CM102: 2254937 | CN102: 2254937 | CO102: 2254937 | CP102: 13147 | CQ102: 13147 | CR102: 13147 | CS102: 13147 | CT102: 13147 | CU102: 13147 | CV102: 13147 | CW102: 13147 | CX102: 77908 | CY102: 77908 | CZ102: 78408 | DA102: 78408 | DB102: 78408 | DC102: 0 | DD102: 0 | DE102: 0 | DF102: 0 | DG102: 0 | DH102: 0 | DI102: 0 | DJ102: 0 | DK102: 0 | DL102: 0 | DM102: 0 | DN102: 0 | DO102: 0 | DP102: 0 | DQ102: 3978246 | DR102: 3978246 | DS102: 3978246 | DT102: 3978246 | DU102: 3978246 | DV102: 3978246 | DW102: 3978246 | DX102: 3978246 | DY102: 3978246 | DZ102: 3978246 | EA102: 3978246 | EB102: 3978246 | EC102: 0 | ED102: 0 | EE102: 0 | EF102: 0 | EG102: 1694 | EH102: 1694 | EI102: 1694 | EJ102: 1694 | EK102: 1694 | EL102: 3479 | EM102: 3479 | EN102: 3479 | EO102: 3479 | EP102: 5863 | EQ102: 5863 | ER102: 5863 | ES102: 5863 | ET102: 5863 | EU102: 5863 | EV102: 5863 | EW102: 5863 | EX102: 5863 | EY102: 5863 | EZ102: 5863 | FA102: 5863 | FB102: 5863 | FC102: 10 | FD102: 10 | FE102: 10 | FF102: 10 | FG102: 10 | FH102: 10 | FI102: 10 | FJ102: 10 | FK102: 10 | FL102: 10 | FM102: 10 | FN102: 10 | FO102: 10
B103: SERVIU Antofagasta | C103: 6703 | D103: 6703 | E103: 6703 | F103: 6703 | G103: 6703 | H103: 6703 | I103: 6703 | J103: 6703 | K103: 6703 | L103: 6703 | M103: 6703 | N103: 6703 | O103: 6703 | P103: 8171 | Q103: 8171 | R103: 8171 | S103: 8171 | T103: 8171 | U103: 8171 | V103: 8171 | W103: 14207 | X103: 14207 | Y103: 16617 | Z103: 16617 | AA103: 16617 | AB103: 16617 | AC103: 10165 | AD103: 10165 | AE103: 10165 | AF103: 10165 | AG103: 10165 | AH103: 10165 | AI103: 10165 | AJ103: 10165 | AK103: 10165 | AL103: 10165 | AM103: 10165 | AN103: 10165 | AO103: 10165 | AP103: 11330 | AQ103: 11330 | AR103: 11330 | AS103: 11330 | AT103: 14330 | AU103: 14330 | AV103: 14330 | AW103: 14330 | AX103: 1148670 | AY103: 1148670 | AZ103: 1148670 | BA103: 1158975 | BB103: 1158975 | BC103: 1530650 | BD103: 1530650 | BE103: 1530650 | BF103: 1530650 | BG103: 1530650 | BH103: 1530650 | BI103: 1374479 | BJ103: 1374479 | BK103: 1374479 | BL103: 1374479 | BM103: 1374479 | BN103: 1374479 | BO103: 1374479 | BP103: 8728 | BQ103: 8728 | BR103: 8728 | BS103: 8728 | BT103: 8728 | BU103: 8728 | BV103: 8728 | BW103: 664448 | BX103: 664448 | BY103: 664448 | BZ103: 664448 | CA103: 3064448 | CB103: 3064448 | CC103: 7563 | CD103: 7563 | CE103: 7563 | CF103: 5294 | CG103: 2646 | CH103: 2646 | CI103: 2646 | CJ103: 2646 | CK103: 2646 | CL103: 2646 | CM103: 100486 | CN103: 100486 | CO103: 100486 | CP103: 1616 | CQ103: 1616 | CR103: 1616 | CS103: 1616 | CT103: 1616 | CU103: 1926 | CV103: 1926 | CW103: 1926 | CX103: 1926 | CY103: 1926 | CZ103: 1926 | DA103: 1926 | DB103: 1926 | DC103: 0 | DD103: 0 | DE103: 0 | DF103: 0 | DG103: 0 | DH103: 0 | DI103: 0 | DJ103: 0 | DK103: 0 | DL103: 0 | DM103: 5960113 | DN103: 5960113 | DO103: 5960113 | DP103: 0 | DQ103: 0 | DR103: 0 | DS103: 0 | DT103: 0 | DU103: 0 | DV103: 0 | DW103: 0 | DX103: 0 | DY103: 0 | DZ103: 0 | EA103: 0 | EB103: 0 | EC103: 0 | ED103: 0 | EE103: 0 | EF103: 0 | EG103: 5080 | EH103: 5080 | EI103: 5080 | EJ103: 5080 | EK103: 5080 | EL103: 6270 | EM103: 6270 | EN103: 6270 | EO103: 6270 | EP103: 710 | EQ103: 710 | ER103: 710 | ES103: 710 | ET103: 710 | EU103: 710 | EV103: 710 | EW103: 710 | EX103: 710 | EY103: 710 | EZ103: 710 | FA103: 710 | FB103: 710 | FC103: 10 | FD103: 10 | FE103: 10 | FF103: 10 | FG103: 10 | FH103: 10 | FI103: 10 | FJ103: 10 | FK103: 10 | FL103: 10 | FM103: 10 | FN103: 10 | FO103: 10
B104: SERVIU Atacama | C104: 8794 | D104: 8794 | E104: 8794 | F104: 8794 | G104: 8794 | H104: 8794 | I104: 8794 | J104: 8794 | K104: 8794 | L104: 8794 | M104: 8794 | N104: 8794 | O104: 8794 | P104: 13274 | Q104: 13274 | R104: 13274 | S104: 13274 | T104: 13274 | U104: 13274 | V104: 13274 | W104: 13274 | X104: 13274 | Y104: 13274 | Z104: 13274 | AA104: 13274 | AB104: 13274 | AC104: 15315 | AD104: 15315 | AE104: 15315 | AF104: 354259 | AG104: 354259 | AH104: 354259 | AI104: 354259 | AJ104: 354259 | AK104: 354259 | AL104: 354259 | AM104: 354259 | AN104: 354259 | AO104: 354259 | AP104: 13699 | AQ104: 13699 | AR104: 13699 | AS104: 13699 | AT104: 13699 | AU104: 13699 | AV104: 13699 | AW104: 13699 | AX104: 1243966 | AY104: 1243966 | AZ104: 1243966 | BA104: 1243966 | BB104: 1243966 | BC104: 18833 | BD104: 18833 | BE104: 18833 | BF104: 18833 | BG104: 18833 | BH104: 18833 | BI104: 15578 | BJ104: 15578 | BK104: 15578 | BL104: 15578 | BM104: 15578 | BN104: 15578 | BO104: 15578 | BP104: 13337 | BQ104: 13337 | BR104: 13337 | BS104: 13337 | BT104: 13337 | BU104: 13337 | BV104: 13337 | BW104: 13337 | BX104: 1232119 | BY104: 1232119 | BZ104: 1232119 | CA104: 1232119 | CB104: 1232119 | CC104: 13684 | CD104: 13684 | CE104: 13684 | CF104: 9579 | CG104: 4789 | CH104: 4789 | CI104: 4789 | CJ104: 4789 | CK104: 4789 | CL104: 4789 | CM104: 13684 | CN104: 13684 | CO104: 13684 | CP104: 7771 | CQ104: 7771 | CR104: 7771 | CS104: 7771 | CT104: 7771 | CU104: 7771 | CV104: 7771 | CW104: 7771 | CX104: 7771 | CY104: 7771 | CZ104: 7771 | DA104: 7771 | DB104: 7771 | DC104: 0 | DD104: 0 | DE104: 0 | DF104: 0 | DG104: 0 | DH104: 0 | DI104: 0 | DJ104: 0 | DK104: 0 | DL104: 0 | DM104: 8335525 | DN104: 8335525 | DO104: 8335525 | DP104: 0 | DQ104: 0 | DR104: 0 | DS104: 0 | DT104: 0 | DU104: 0 | DV104: 0 | DW104: 0 | DX104: 0 | DY104: 0 | DZ104: 0 | EA104: 329064 | EB104: 329064 | EC104: 0 | ED104: 0 | EE104: 0 | EF104: 0 | EG104: 5926 | EH104: 5926 | EI104: 5926 | EJ104: 5926 | EK104: 5926 | EL104: 6646 | EM104: 6646 | EN104: 6646 | EO104: 6646 | EP104: 6540 | EQ104: 6540 | ER104: 6540 | ES104: 6540 | ET104: 6540 | EU104: 6540 | EV104: 6540 | EW104: 6540 | EX104: 6540 | EY104: 6540 | EZ104: 6540 | FA104: 6540 | FB104: 6540 | FC104: 10 | FD104: 10 | FE104: 10 | FF104: 10 | FG104: 10 | FH104: 10 | FI104: 10 | FJ104: 10 | FK104: 10 | FL104: 10 | FM104: 10 | FN104: 10 | FO104: 10
B105: SERVIU Coquimbo | C105: 19164 | D105: 19164 | E105: 19164 | F105: 19164 | G105: 19164 | H105: 19164 | I105: 19164 | J105: 19164 | K105: 19164 | L105: 19164 | M105: 19164 | N105: 19164 | O105: 19164 | P105: 20898 | Q105: 20898 | R105: 1337840 | S105: 1337840 | T105: 1337840 | U105: 1337840 | V105: 1337840 | W105: 1337840 | X105: 1355440 | Y105: 1375440 | Z105: 1375440 | AA105: 1375440 | AB105: 1375440 | AC105: 16233 | AD105: 16233 | AE105: 87066 | AF105: 87066 | AG105: 87066 | AH105: 87066 | AI105: 87066 | AJ105: 87066 | AK105: 87066 | AL105: 87066 | AM105: 897066 | AN105: 2291726 | AO105: 2291726 | AP105: 15038 | AQ105: 15038 | AR105: 15038 | AS105: 1127220 | AT105: 1127220 | AU105: 1156953 | AV105: 1156953 | AW105: 1156953 | AX105: 1156953 | AY105: 1156953 | AZ105: 1156953 | BA105: 2133191 | BB105: 2133191 | BC105: 17276 | BD105: 17276 | BE105: 17276 | BF105: 17276 | BG105: 17276 | BH105: 17276 | BI105: 14167 | BJ105: 14167 | BK105: 14167 | BL105: 14167 | BM105: 14167 | BN105: 82639 | BO105: 82639 | BP105: 11951 | BQ105: 11951 | BR105: 11951 | BS105: 11951 | BT105: 11951 | BU105: 11951 | BV105: 11951 | BW105: 11951 | BX105: 11951 | BY105: 11951 | BZ105: 11951 | CA105: 11951 | CB105: 11951 | CC105: 12262 | CD105: 12262 | CE105: 12262 | CF105: 8584 | CG105: 4330 | CH105: 4330 | CI105: 4330 | CJ105: 4330 | CK105: 4330 | CL105: 4330 | CM105: 1149753 | CN105: 1149753 | CO105: 1149753 | CP105: 9458 | CQ105: 9458 | CR105: 9458 | CS105: 9458 | CT105: 1661590 | CU105: 1662157 | CV105: 1662157 | CW105: 1662157 | CX105: 1662157 | CY105: 1662778 | CZ105: 1662778 | DA105: 1662778 | DB105: 1662778 | DC105: 0 | DD105: 0 | DE105: 0 | DF105: 0 | DG105: 0 | DH105: 0 | DI105: 0 | DJ105: 0 | DK105: 0 | DL105: 0 | DM105: 5385954 | DN105: 25574386 | DO105: 25574386 | DP105: 0 | DQ105: 0 | DR105: 0 | DS105: 0 | DT105: 0 | DU105: 0 | DV105: 0 | DW105: 0 | DX105: 0 | DY105: 0 | DZ105: 0 | EA105: 115827 | EB105: 115827 | EC105: 0 | ED105: 0 | EE105: 0 | EF105: 0 | EG105: 8466 | EH105: 6091623 | EI105: 6091623 | EJ105: 6091623 | EK105: 6091623 | EL105: 6092813 | EM105: 6092813 | EN105: 6092813 | EO105: 6092813 | EP105: 6033 | EQ105: 6033 | ER105: 6033 | ES105: 6033 | ET105: 6033 | EU105: 6033 | EV105: 6033 | EW105: 6033 | EX105: 6033 | EY105: 6033 | EZ105: 6033 | FA105: 6033 | FB105: 6033 | FC105: 10 | FD105: 10 | FE105: 10 | FF105: 10 | FG105: 10 | FH105: 10 | FI105: 10 | FJ105: 10 | FK105: 10 | FL105: 10 | FM105: 10 | FN105: 10 | FO105: 10
