Workbook

Sheet MINVU_Mes_Corriente
B1: Ministerio de Salud — Partida 16
B2: Miles de pesos — moneda corriente — montos devengados
B4: SUBTÍTULO 31 – INICIATIVAS DE INVERSIÓN
B5: Presupuesto Ley (Subtítulo 31)
C6: 2014 | P6: 2015 | AC6: 2016 | AP6: 2017 | BC6: 2018 | BP6: 2019 | CC6: 2020 | CP6: 2021 | DC6: 2022 | DP6: 2023 | EC6: 2024 | EP6: 2025 | FC6: 2026
B7: Programa / Entidad | C7: Ene | D7: Feb | E7: Mar | F7: Abr | G7: May | H7: Jun | I7: Jul | J7: Ago | K7: Sep | L7: Oct | M7: Nov | N7: Dic | O7: Total 2014 | P7: Ene | Q7: Feb | R7: Mar | S7: Abr | T7: May | U7: Jun | V7: Jul | W7: Ago | X7: Sep | Y7: Oct | Z7: Nov | AA7: Dic | AB7: Total 2015 | AC7: Ene | AD7: Feb | AE7: Mar | AF7: Abr | AG7: May | AH7: Jun | AI7: Jul | AJ7: Ago | AK7: Sep | AL7: Oct | AM7: Nov | AN7: Dic | AO7: Total 2016 | AP7: Ene | AQ7: Feb | AR7: Mar | AS7: Abr | AT7: May | AU7: Jun | AV7: Jul | AW7: Ago | AX7: Sep | AY7: Oct | AZ7: Nov | BA7: Dic | BB7: Total 2017 | BC7: Ene | BD7: Feb | BE7: Mar | BF7: Abr | BG7: May | BH7: Jun | BI7: Jul | BJ7: Ago | BK7: Sep | BL7: Oct | BM7: Nov | BN7: Dic | BO7: Total 2018 | BP7: Ene | BQ7: Feb | BR7: Mar | BS7: Abr | BT7: May | BU7: Jun | BV7: Jul | BW7: Ago | BX7: Sep | BY7: Oct | BZ7: Nov | CA7: Dic | CB7: Total 2019 | CC7: Ene | CD7: Feb | CE7: Mar | CF7: Abr | CG7: May | CH7: Jun | CI7: Jul | CJ7: Ago | CK7: Sep | CL7: Oct | CM7: Nov | CN7: Dic | CO7: Total 2020 | CP7: Ene | CQ7: Feb | CR7: Mar | CS7: Abr | CT7: May | CU7: Jun | CV7: Jul | CW7: Ago | CX7: Sep | CY7: Oct | CZ7: Nov | DA7: Dic | DB7: Total 2021 | DC7: Ene | DD7: Feb | DE7: Mar | DF7: Abr | DG7: May | DH7: Jun | DI7: Jul | DJ7: Ago | DK7: Sep | DL7: Oct | DM7: Nov | DN7: Dic | DO7: Total 2022 | DP7: Ene | DQ7: Feb | DR7: Mar | DS7: Abr | DT7: May | DU7: Jun | DV7: Jul | DW7: Ago | DX7: Sep | DY7: Oct | DZ7: Nov | EA7: Dic | EB7: Total 2023 | EC7: Ene | ED7: Feb | EE7: Mar | EF7: Abr | EG7: May | EH7: Jun | EI7: Jul | EJ7: Ago | EK7: Sep | EL7: Oct | EM7: Nov | EN7: Dic | EO7: Total 2024 | EP7: Ene | EQ7: Feb | ER7: Mar | ES7: Abr | ET7: May | EU7: Jun | EV7: Jul | EW7: Ago | EX7: Sep | EY7: Oct | EZ7: Nov | FA7: Dic | FB7: Total 2025 | FC7: Ene | FD7: Feb | FE7: Mar | FF7: Abr | FG7: May | FH7: Jun | FI7: Jul | FJ7: Ago | FK7: Sep | FL7: Oct | FM7: Nov | FN7: Dic | FO7: Total 2026
B8: Instituto de Salud Pública | C8: 747570 | D8: 747570 | E8: 747570 | F8: 747570 | G8: 747570 | H8: 747570 | I8: 747570 | J8: 747570 | K8: 747570 | L8: 747570 | M8: 747570 | N8: 747570 | O8: =N8 -> 747570 | P8: 206000 | Q8: 206000 | R8: 206000 | S8: 206000 | T8: 206000 | U8: 206000 | V8: 206000 | W8: 206000 | X8: 206000 | Y8: 206000 | Z8: 206000 | AA8: 206000 | AB8: =AA8 -> 206000 | AC8: 0 | AD8: 0 | AE8: 0 | AF8: 0 | AG8: 0 | AH8: 0 | AI8: 0 | AJ8: 0 | AK8: 0 | AL8: 0 | AM8: 0 | AN8: 0 | AO8: =AN8 -> 0 | AP8: 237364 | AQ8: 237364 | AR8: 237364 | AS8: 237364 | AT8: 237364 | AU8: 237364 | AV8: 237364 | AW8: 237364 | AX8: 237364 | AY8: 237364 | AZ8: 237364 | BA8: 237364 | BB8: =BA8 -> 237364 | BC8: 0 | BD8: 0 | BE8: 0 | BF8: 0 | BG8: 0 | BH8: 0 | BI8: 0 | BJ8: 0 | BK8: 0 | BL8: 0 | BM8: 0 | BN8: 0 | BO8: =BN8 -> 0 | BP8: 0 | BQ8: 0 | BR8: 0 | BS8: 0 | BT8: 0 | BU8: 0 | BV8: 0 | BW8: 0 | BX8: 0 | BY8: 0 | BZ8: 0 | CA8: 0 | CB8: =CA8 -> 0 | CC8: 1026000 | CD8: 1026000 | CE8: 1026000 | CF8: 1026000 | CG8: 1026000 | CH8: 1026000 | CI8: 1026000 | CJ8: 1026000 | CK8: 1026000 | CL8: 1026000 | CM8: 1026000 | CN8: 1026000 | CO8: =CN8 -> 1026000 | CP8: 800605 | CQ8: 800605 | CR8: 800605 | CS8: 800605 | CT8: 800605 | CU8: 800605 | CV8: 800605 | CW8: 800605 | CX8: 800605 | CY8: 800605 | CZ8: 800605 | DA8: 800605 | DB8: =DA8 -> 800605 | DC8: 2301909 | DD8: 2301909 | DE8: 2301909 | DF8: 2301909 | DG8: 2301909 | DH8: 2301909 | DI8: 2301909 | DJ8: 2301909 | DK8: 2301909 | DL8: 2301909 | DM8: 2301909 | DN8: 2301909 | DO8: =DN8 -> 2301909 | DP8: 1324402 | DQ8: 1324402 | DR8: 1324402 | DS8: 1324402 | DT8: 1324402 | DU8: 1324402 | DV8: 1324402 | DW8: 1324402 | DX8: 1324402 | DY8: 1324402 | DZ8: 1324402 | EA8: 1324402 | EB8: =EA8 -> 1324402 | EC8: 1459534 | ED8: 1459534 | EE8: 1459534 | EF8: 1459534 | EG8: 1459534 | EH8: 1459534 | EI8: 1459534 | EJ8: 1459534 | EK8: 1459534 | EL8: 1459534 | EM8: 1459534 | EN8: 1459534 | EO8: =EN8 -> 1459534 | EP8: 781455 | EQ8: 781455 | ER8: 781455 | ES8: 781455 | ET8: 781455 | EU8: 781455 | EV8: 781455 | EW8: 781455 | EX8: 781455 | EY8: 781455 | EZ8: 781455 | FA8: 781455 | FB8: =FA8 -> 781455 | FC8: 657325 | FD8: 657325 | FE8: 657325 | FF8: 657325 | FG8: 657325 | FH8: 657325 | FI8: 657325 | FO8: =FI8 -> 657325
B9: Subsecretaría de Salud Pública | C9: 0 | D9: 0 | E9: 0 | F9: 0 | G9: 0 | H9: 0 | I9: 0 | J9: 0 | K9: 0 | L9: 0 | M9: 0 | N9: 0 | O9: =N9 -> 0 | P9: 0 | Q9: 0 | R9: 0 | S9: 0 | T9: 0 | U9: 0 | V9: 0 | W9: 0 | X9: 0 | Y9: 0 | Z9: 0 | AA9: 0 | AB9: =AA9 -> 0 | AC9: 0 | AD9: 0 | AE9: 0 | AF9: 0 | AG9: 0 | AH9: 0 | AI9: 0 | AJ9: 0 | AK9: 0 | AL9: 0 | AM9: 0 | AN9: 0 | AO9: =AN9 -> 0 | AP9: 0 | AQ9: 0 | AR9: 0 | AS9: 0 | AT9: 0 | AU9: 0 | AV9: 0 | AW9: 0 | AX9: 0 | AY9: 0 | AZ9: 0 | BA9: 0 | BB9: =BA9 -> 0 | BC9: 0 | BD9: 0 | BE9: 0 | BF9: 0 | BG9: 0 | BH9: 0 | BI9: 0 | BJ9: 0 | BK9: 0 | BL9: 0 | BM9: 0 | BN9: 0 | BO9: =BN9 -> 0 | BP9: 0 | BQ9: 0 | BR9: 0 | BS9: 0 | BT9: 0 | BU9: 0 | BV9: 0 | BW9: 0 | BX9: 0 | BY9: 0 | BZ9: 0 | CA9: 0 | CB9: =CA9 -> 0 | CC9: 0 | CD9: 0 | CE9: 0 | CF9: 0 | CG9: 0 | CH9: 0 | CI9: 0 | CJ9: 0 | CK9: 0 | CL9: 0 | CM9: 0 | CN9: 0 | CO9: =CN9 -> 0 | CP9: 0 | CQ9: 0 | CR9: 0 | CS9: 0 | CT9: 0 | CU9: 0 | CV9: 0 | CW9: 0 | CX9: 0 | CY9: 0 | CZ9: 0 | DA9: 0 | DB9: =DA9 -> 0 | DC9: 0 | DD9: 0 | DE9: 0 | DF9: 0 | DG9: 0 | DH9: 0 | DI9: 0 | DJ9: 0 | DK9: 0 | DL9: 0 | DM9: 0 | DN9: 0 | DO9: =DN9 -> 0 | DP9: 0 | DQ9: 0 | DR9: 0 | DS9: 0 | DT9: 0 | DU9: 0 | DV9: 0 | DW9: 0 | DX9: 0 | DY9: 0 | DZ9: 0 | EA9: 0 | EB9: =EA9 -> 0 | EC9: 0 | ED9: 0 | EE9: 0 | EF9: 0 | EG9: 0 | EH9: 0 | EI9: 0 | EJ9: 0 | EK9: 0 | EL9: 0 | EM9: 0 | EN9: 0 | EO9: =EN9 -> 0 | EP9: 0 | EQ9: 0 | ER9: 0 | ES9: 0 | ET9: 0 | EU9: 0 | EV9: 0 | EW9: 0 | EX9: 0 | EY9: 0 | EZ9: 0 | FA9: 0 | FB9: =FA9 -> 0 | FC9: 3133791 | FD9: 3133791 | FE9: 3133791 | FF9: 3133791 | FG9: 3133791 | FH9: 3133791 | FI9: 3133791 | FO9: =FI9 -> 3133791
B10: Inversión Sectorial en Salud | C10: 274548673 | D10: 274548673 | E10: 274548673 | F10: 274548673 | G10: 274548673 | H10: 274548673 | I10: 274548673 | J10: 274548673 | K10: 274548673 | L10: 274548673 | M10: 274548673 | N10: 274548673 | O10: =N10 -> 274548673 | P10: 528813287 | Q10: 528813287 | R10: 528813287 | S10: 528813287 | T10: 528813287 | U10: 528813287 | V10: 528813287 | W10: 528813287 | X10: 528813287 | Y10: 528813287 | Z10: 528813287 | AA10: 528813287 | AB10: =AA10 -> 528813287 | AC10: 497824800 | AD10: 497824800 | AE10: 497824800 | AF10: 497824800 | AG10: 497824800 | AH10: 497824800 | AI10: 497824800 | AJ10: 497824800 | AK10: 497824800 | AL10: 497824800 | AM10: 497824800 | AN10: 497824800 | AO10: =AN10 -> 497824800 | AP10: 349316570 | AQ10: 349316570 | AR10: 349316570 | AS10: 349316570 | AT10: 349316570 | AU10: 349316570 | AV10: 349316570 | AW10: 349316570 | AX10: 349316570 | AY10: 349316570 | AZ10: 349316570 | BA10: 349316570 | BB10: =BA10 -> 349316570 | BC10: 439600285 | BD10: 439600285 | BE10: 439600285 | BF10: 439600285 | BG10: 439600285 | BH10: 439600285 | BI10: 439600285 | BJ10: 439600285 | BK10: 439600285 | BL10: 439600285 | BM10: 439600285 | BN10: 439600285 | BO10: =BN10 -> 439600285 | BP10: 418874044 | BQ10: 418874044 | BR10: 418874044 | BS10: 418874044 | BT10: 418874044 | BU10: 418874044 | BV10: 418874044 | BW10: 418874044 | BX10: 418874044 | BY10: 418874044 | BZ10: 418874044 | CA10: 418874044 | CB10: =CA10 -> 418874044 | CC10: 733952985 | CD10: 733952985 | CE10: 733952985 | CF10: 733952985 | CG10: 733952985 | CH10: 733952985 | CI10: 733952985 | CJ10: 733952985 | CK10: 733952985 | CL10: 733952985 | CM10: 733952985 | CN10: 733952985 | CO10: =CN10 -> 733952985 | CP10: 653979311 | CQ10: 653979311 | CR10: 653979311 | CS10: 653979311 | CT10: 653979311 | CU10: 653979311 | CV10: 653979311 | CW10: 653979311 | CX10: 653979311 | CY10: 653979311 | CZ10: 653979311 | DA10: 653979311 | DB10: =DA10 -> 653979311 | DC10: 642175866 | DD10: 642175866 | DE10: 642175866 | DF10: 642175866 | DG10: 642175866 | DH10: 642175866 | DI10: 642175866 | DJ10: 642175866 | DK10: 642175866 | DL10: 642175866 | DM10: 642175866 | DN10: 642175866 | DO10: =DN10 -> 642175866 | DP10: 709260889 | DQ10: 709260889 | DR10: 709260889 | DS10: 709260889 | DT10: 709260889 | DU10: 709260889 | DV10: 709260889 | DW10: 709260889 | DX10: 709260889 | DY10: 709260889 | DZ10: 709260889 | EA10: 709260889 | EB10: =EA10 -> 709260889 | EC10: 581851338 | ED10: 581851338 | EE10: 581851338 | EF10: 581851338 | EG10: 581851338 | EH10: 581851338 | EI10: 581851338 | EJ10: 581851338 | EK10: 581851338 | EL10: 581851338 | EM10: 581851338 | EN10: 581851338 | EO10: =EN10 -> 581851338 | EP10: 573366549 | EQ10: 573366549 | ER10: 573366549 | ES10: 573366549 | ET10: 573366549 | EU10: 573366549 | EV10: 573366549 | EW10: 573366549 | EX10: 573366549 | EY10: 573366549 | EZ10: 573366549 | FA10: 573366549 | FB10: =FA10 -> 573366549 | FC10: 201002151 | FD10: 201002151 | FE10: 201002151 | FF10: 201002151 | FG10: 201002151 | FH10: 201002151 | FI10: 201002151 | FO10: =FI10 -> 201002151
B11: Servicio de Salud Arica y Parinacota | C11: 0 | D11: 0 | E11: 0 | F11: 0 | G11: 0 | H11: 0 | I11: 0 | J11: 0 | K11: 0 | L11: 0 | M11: 0 | N11: 0 | O11: =N11 -> 0 | P11: 0 | Q11: 0 | R11: 0 | S11: 0 | T11: 0 | U11: 0 | V11: 0 | W11: 0 | X11: 0 | Y11: 0 | Z11: 0 | AA11: 0 | AB11: =AA11 -> 0 | AC11: 0 | AD11: 0 | AE11: 0 | AF11: 0 | AG11: 0 | AH11: 0 | AI11: 0 | AJ11: 0 | AK11: 0 | AL11: 0 | AM11: 0 | AN11: 0 | AO11: =AN11 -> 0 | AP11: 0 | AQ11: 0 | AR11: 0 | AS11: 0 | AT11: 0 | AU11: 0 | AV11: 0 | AW11: 0 | AX11: 0 | AY11: 0 | AZ11: 0 | BA11: 0 | BB11: =BA11 -> 0 | BC11: 0 | BD11: 0 | BE11: 0 | BF11: 0 | BG11: 0 | BH11: 0 | BI11: 0 | BJ11: 0 | BK11: 0 | BL11: 0 | BM11: 0 | BN11: 0 | BO11: =BN11 -> 0 | BP11: 0 | BQ11: 0 | BR11: 0 | BS11: 0 | BT11: 0 | BU11: 0 | BV11: 0 | BW11: 0 | BX11: 0 | BY11: 0 | BZ11: 0 | CA11: 0 | CB11: =CA11 -> 0 | CC11: 0 | CD11: 0 | CE11: 0 | CF11: 0 | CG11: 0 | CH11: 0 | CI11: 0 | CJ11: 0 | CK11: 0 | CL11: 0 | CM11: 0 | CN11: 0 | CO11: =CN11 -> 0 | CP11: 0 | CQ11: 0 | CR11: 0 | CS11: 0 | CT11: 0 | CU11: 0 | CV11: 0 | CW11: 0 | CX11: 0 | CY11: 0 | CZ11: 0 | DA11: 0 | DB11: =DA11 -> 0 | DC11: 0 | DD11: 0 | DE11: 0 | DF11: 0 | DG11: 0 | DH11: 0 | DI11: 0 | DJ11: 0 | DK11: 0 | DL11: 0 | DM11: 0 | DN11: 0 | DO11: =DN11 -> 0 | DP11: 0 | DQ11: 0 | DR11: 0 | DS11: 0 | DT11: 0 | DU11: 0 | DV11: 0 | DW11: 0 | DX11: 0 | DY11: 0 | DZ11: 0 | EA11: 0 | EB11: =EA11 -> 0 | EC11: 0 | ED11: 0 | EE11: 0 | EF11: 0 | EG11: 0 | EH11: 0 | EI11: 0 | EJ11: 0 | EK11: 0 | EL11: 0 | EM11: 0 | EN11: 0 | EO11: =EN11 -> 0 | EP11: 0 | EQ11: 0 | ER11: 0 | ES11: 0 | ET11: 0 | EU11: 0 | EV11: 0 | EW11: 0 | EX11: 0 | EY11: 0 | EZ11: 0 | FA11: 0 | FB11: =FA11 -> 0 | FC11: 3783756 | FD11: 3783756 | FE11: 3783756 | FF11: 3783756 | FG11: 3783756 | FH11: 3783756 | FI11: 3783756 | FO11: =FI11 -> 3783756
B12: Servicio de Salud Tarapacá | C12: 0 | D12: 0 | E12: 0 | F12: 0 | G12: 0 | H12: 0 | I12: 0 | J12: 0 | K12: 0 | L12: 0 | M12: 0 | N12: 0 | O12: =N12 -> 0 | P12: 0 | Q12: 0 | R12: 0 | S12: 0 | T12: 0 | U12: 0 | V12: 0 | W12: 0 | X12: 0 | Y12: 0 | Z12: 0 | AA12: 0 | AB12: =AA12 -> 0 | AC12: 0 | AD12: 0 | AE12: 0 | AF12: 0 | AG12: 0 | AH12: 0 | AI12: 0 | AJ12: 0 | AK12: 0 | AL12: 0 | AM12: 0 | AN12: 0 | AO12: =AN12 -> 0 | AP12: 0 | AQ12: 0 | AR12: 0 | AS12: 0 | AT12: 0 | AU12: 0 | AV12: 0 | AW12: 0 | AX12: 0 | AY12: 0 | AZ12: 0 | BA12: 0 | BB12: =BA12 -> 0 | BC12: 0 | BD12: 0 | BE12: 0 | BF12: 0 | BG12: 0 | BH12: 0 | BI12: 0 | BJ12: 0 | BK12: 0 | BL12: 0 | BM12: 0 | BN12: 0 | BO12: =BN12 -> 0 | BP12: 0 | BQ12: 0 | BR12: 0 | BS12: 0 | BT12: 0 | BU12: 0 | BV12: 0 | BW12: 0 | BX12: 0 | BY12: 0 | BZ12: 0 | CA12: 0 | CB12: =CA12 -> 0 | CC12: 0 | CD12: 0 | CE12: 0 | CF12: 0 | CG12: 0 | CH12: 0 | CI12: 0 | CJ12: 0 | CK12: 0 | CL12: 0 | CM12: 0 | CN12: 0 | CO12: =CN12 -> 0 | CP12: 0 | CQ12: 0 | CR12: 0 | CS12: 0 | CT12: 0 | CU12: 0 | CV12: 0 | CW12: 0 | CX12: 0 | CY12: 0 | CZ12: 0 | DA12: 0 | DB12: =DA12 -> 0 | DC12: 0 | DD12: 0 | DE12: 0 | DF12: 0 | DG12: 0 | DH12: 0 | DI12: 0 | DJ12: 0 | DK12: 0 | DL12: 0 | DM12: 0 | DN12: 0 | DO12: =DN12 -> 0 | DP12: 0 | DQ12: 0 | DR12: 0 | DS12: 0 | DT12: 0 | DU12: 0 | DV12: 0 | DW12: 0 | DX12: 0 | DY12: 0 | DZ12: 0 | EA12: 0 | EB12: =EA12 -> 0 | EC12: 0 | ED12: 0 | EE12: 0 | EF12: 0 | EG12: 0 | EH12: 0 | EI12: 0 | EJ12: 0 | EK12: 0 | EL12: 0 | EM12: 0 | EN12: 0 | EO12: =EN12 -> 0 | EP12: 0 | EQ12: 0 | ER12: 0 | ES12: 0 | ET12: 0 | EU12: 0 | EV12: 0 | EW12: 0 | EX12: 0 | EY12: 0 | EZ12: 0 | FA12: 0 | FB12: =FA12 -> 0 | FC12: 22899006 | FD12: 22899006 | FE12: 22899006 | FF12: 22899006 | FG12: 22899006 | FH12: 22899006 | FI12: 22899006 | FO12: =FI12 -> 22899006
B13: Servicio de Salud Antofagasta | C13: 0 | D13: 0 | E13: 0 | F13: 0 | G13: 0 | H13: 0 | I13: 0 | J13: 0 | K13: 0 | L13: 0 | M13: 0 | N13: 0 | O13: =N13 -> 0 | P13: 0 | Q13: 0 | R13: 0 | S13: 0 | T13: 0 | U13: 0 | V13: 0 | W13: 0 | X13: 0 | Y13: 0 | Z13: 0 | AA13: 0 | AB13: =AA13 -> 0 | AC13: 0 | AD13: 0 | AE13: 0 | AF13: 0 | AG13: 0 | AH13: 0 | AI13: 0 | AJ13: 0 | AK13: 0 | AL13: 0 | AM13: 0 | AN13: 0 | AO13: =AN13 -> 0 | AP13: 0 | AQ13: 0 | AR13: 0 | AS13: 0 | AT13: 0 | AU13: 0 | AV13: 0 | AW13: 0 | AX13: 0 | AY13: 0 | AZ13: 0 | BA13: 0 | BB13: =BA13 -> 0 | BC13: 4104000 | BD13: 4104000 | BE13: 4104000 | BF13: 4104000 | BG13: 4104000 | BH13: 4104000 | BI13: 4104000 | BJ13: 4104000 | BK13: 4104000 | BL13: 4104000 | BM13: 4104000 | BN13: 4104000 | BO13: =BN13 -> 4104000 | BP13: 0 | BQ13: 0 | BR13: 0 | BS13: 0 | BT13: 0 | BU13: 0 | BV13: 0 | BW13: 0 | BX13: 0 | BY13: 0 | BZ13: 0 | CA13: 0 | CB13: =CA13 -> 0 | CC13: 0 | CD13: 0 | CE13: 0 | CF13: 0 | CG13: 0 | CH13: 0 | CI13: 0 | CJ13: 0 | CK13: 0 | CL13: 0 | CM13: 0 | CN13: 0 | CO13: =CN13 -> 0 | CP13: 0 | CQ13: 0 | CR13: 0 | CS13: 0 | CT13: 0 | CU13: 0 | CV13: 0 | CW13: 0 | CX13: 0 | CY13: 0 | CZ13: 0 | DA13: 0 | DB13: =DA13 -> 0 | DC13: 0 | DD13: 0 | DE13: 0 | DF13: 0 | DG13: 0 | DH13: 0 | DI13: 0 | DJ13: 0 | DK13: 0 | DL13: 0 | DM13: 0 | DN13: 0 | DO13: =DN13 -> 0 | DP13: 0 | DQ13: 0 | DR13: 0 | DS13: 0 | DT13: 0 | DU13: 0 | DV13: 0 | DW13: 0 | DX13: 0 | DY13: 0 | DZ13: 0 | EA13: 0 | EB13: =EA13 -> 0 | EC13: 0 | ED13: 0 | EE13: 0 | EF13: 0 | EG13: 0 | EH13: 0 | EI13: 0 | EJ13: 0 | EK13: 0 | EL13: 0 | EM13: 0 | EN13: 0 | EO13: =EN13 -> 0 | EP13: 0 | EQ13: 0 | ER13: 0 | ES13: 0 | ET13: 0 | EU13: 0 | EV13: 0 | EW13: 0 | EX13: 0 | EY13: 0 | EZ13: 0 | FA13: 0 | FB13: =FA13 -> 0 | FC13: 3191908 | FD13: 3191908 | FE13: 3191908 | FF13: 3191908 | FG13: 3191908 | FH13: 3191908 | FI13: 3191908 | FO13: =FI13 -> 3191908
B14: Servicio de Salud Atacama | C14: 0 | D14: 0 | E14: 0 | F14: 0 | G14: 0 | H14: 0 | I14: 0 | J14: 0 | K14: 0 | L14: 0 | M14: 0 | N14: 0 | O14: =N14 -> 0 | P14: 0 | Q14: 0 | R14: 0 | S14: 0 | T14: 0 | U14: 0 | V14: 0 | W14: 0 | X14: 0 | Y14: 0 | Z14: 0 | AA14: 0 | AB14: =AA14 -> 0 | AC14: 0 | AD14: 0 | AE14: 0 | AF14: 0 | AG14: 0 | AH14: 0 | AI14: 0 | AJ14: 0 | AK14: 0 | AL14: 0 | AM14: 0 | AN14: 0 | AO14: =AN14 -> 0 | AP14: 0 | AQ14: 0 | AR14: 0 | AS14: 0 | AT14: 0 | AU14: 0 | AV14: 0 | AW14: 0 | AX14: 0 | AY14: 0 | AZ14: 0 | BA14: 0 | BB14: =BA14 -> 0 | BC14: 0 | BD14: 0 | BE14: 0 | BF14: 0 | BG14: 0 | BH14: 0 | BI14: 0 | BJ14: 0 | BK14: 0 | BL14: 0 | BM14: 0 | BN14: 0 | BO14: =BN14 -> 0 | BP14: 0 | BQ14: 0 | BR14: 0 | BS14: 0 | BT14: 0 | BU14: 0 | BV14: 0 | BW14: 0 | BX14: 0 | BY14: 0 | BZ14: 0 | CA14: 0 | CB14: =CA14 -> 0 | CC14: 0 | CD14: 0 | CE14: 0 | CF14: 0 | CG14: 0 | CH14: 0 | CI14: 0 | CJ14: 0 | CK14: 0 | CL14: 0 | CM14: 0 | CN14: 0 | CO14: =CN14 -> 0 | CP14: 0 | CQ14: 0 | CR14: 0 | CS14: 0 | CT14: 0 | CU14: 0 | CV14: 0 | CW14: 0 | CX14: 0 | CY14: 0 | CZ14: 0 | DA14: 0 | DB14: =DA14 -> 0 | DC14: 0 | DD14: 0 | DE14: 0 | DF14: 0 | DG14: 0 | DH14: 0 | DI14: 0 | DJ14: 0 | DK14: 0 | DL14: 0 | DM14: 0 | DN14: 0 | DO14: =DN14 -> 0 | DP14: 0 | DQ14: 0 | DR14: 0 | DS14: 0 | DT14: 0 | DU14: 0 | DV14: 0 | DW14: 0 | DX14: 0 | DY14: 0 | DZ14: 0 | EA14: 0 | EB14: =EA14 -> 0 | EC14: 0 | ED14: 0 | EE14: 0 | EF14: 0 | EG14: 0 | EH14: 0 | EI14: 0 | EJ14: 0 | EK14: 0 | EL14: 0 | EM14: 0 | EN14: 0 | EO14: =EN14 -> 0 | EP14: 0 | EQ14: 0 | ER14: 0 | ES14: 0 | ET14: 0 | EU14: 0 | EV14: 0 | EW14: 0 | EX14: 0 | EY14: 0 | EZ14: 0 | FA14: 0 | FB14: =FA14 -> 0 | FC14: 14546113 | FD14: 14546113 | FE14: 14546113 | FF14: 14546113 | FG14: 14546113 | FH14: 14546113 | FI14: 14546113 | FO14: =FI14 -> 14546113
B15: Servicio de Salud Coquimbo | C15: 0 | D15: 0 | E15: 0 | F15: 0 | G15: 0 | H15: 0 | I15: 0 | J15: 0 | K15: 0 | L15: 0 | M15: 0 | N15: 0 | O15: =N15 -> 0 | P15: 0 | Q15: 0 | R15: 0 | S15: 0 | T15: 0 | U15: 0 | V15: 0 | W15: 0 | X15: 0 | Y15: 0 | Z15: 0 | AA15: 0 | AB15: =AA15 -> 0 | AC15: 0 | AD15: 0 | AE15: 0 | AF15: 0 | AG15: 0 | AH15: 0 | AI15: 0 | AJ15: 0 | AK15: 0 | AL15: 0 | AM15: 0 | AN15: 0 | AO15: =AN15 -> 0 | AP15: 0 | AQ15: 0 | AR15: 0 | AS15: 0 | AT15: 0 | AU15: 0 | AV15: 0 | AW15: 0 | AX15: 0 | AY15: 0 | AZ15: 0 | BA15: 0 | BB15: =BA15 -> 0 | BC15: 0 | BD15: 0 | BE15: 0 | BF15: 0 | BG15: 0 | BH15: 0 | BI15: 0 | BJ15: 0 | BK15: 0 | BL15: 0 | BM15: 0 | BN15: 0 | BO15: =BN15 -> 0 | BP15: 0 | BQ15: 0 | BR15: 0 | BS15: 0 | BT15: 0 | BU15: 0 | BV15: 0 | BW15: 0 | BX15: 0 | BY15: 0 | BZ15: 0 | CA15: 0 | CB15: =CA15 -> 0 | CC15: 0 | CD15: 0 | CE15: 0 | CF15: 0 | CG15: 0 | CH15: 0 | CI15: 0 | CJ15: 0 | CK15: 0 | CL15: 0 | CM15: 0 | CN15: 0 | CO15: =CN15 -> 0 | CP15: 0 | CQ15: 0 | CR15: 0 | CS15: 0 | CT15: 0 | CU15: 0 | CV15: 0 | CW15: 0 | CX15: 0 | CY15: 0 | CZ15: 0 | DA15: 0 | DB15: =DA15 -> 0 | DC15: 0 | DD15: 0 | DE15: 0 | DF15: 0 | DG15: 0 | DH15: 0 | DI15: 0 | DJ15: 0 | DK15: 0 | DL15: 0 | DM15: 0 | DN15: 0 | DO15: =DN15 -> 0 | DP15: 0 | DQ15: 0 | DR15: 0 | DS15: 0 | DT15: 0 | DU15: 0 | DV15: 0 | DW15: 0 | DX15: 0 | DY15: 0 | DZ15: 0 | EA15: 0 | EB15: =EA15 -> 0 | EC15: 0 | ED15: 0 | EE15: 0 | EF15: 0 | EG15: 0 | EH15: 0 | EI15: 0 | EJ15: 0 | EK15: 0 | EL15: 0 | EM15: 0 | EN15: 0 | EO15: =EN15 -> 0 | EP15: 0 | EQ15: 0 | ER15: 0 | ES15: 0 | ET15: 0 | EU15: 0 | EV15: 0 | EW15: 0 | EX15: 0 | EY15: 0 | EZ15: 0 | FA15: 0 | FB15: =FA15 -> 0 | FC15: 15086131 | FD15: 15086131 | FE15: 15086131 | FF15: 15086131 | FG15: 15086131 | FH15: 15086131 | FI15: 15086131 | FO15: =FI15 -> 15086131
B16: Servicio de Salud Valparaíso - San Antonio | C16: 0 | D16: 0 | E16: 0 | F16: 0 | G16: 0 | H16: 0 | I16: 0 | J16: 0 | K16: 0 | L16: 0 | M16: 0 | N16: 0 | O16: =N16 -> 0 | P16: 0 | Q16: 0 | R16: 0 | S16: 0 | T16: 0 | U16: 0 | V16: 0 | W16: 0 | X16: 0 | Y16: 0 | Z16: 0 | AA16: 0 | AB16: =AA16 -> 0 | AC16: 0 | AD16: 0 | AE16: 0 | AF16: 0 | AG16: 0 | AH16: 0 | AI16: 0 | AJ16: 0 | AK16: 0 | AL16: 0 | AM16: 0 | AN16: 0 | AO16: =AN16 -> 0 | AP16: 0 | AQ16: 0 | AR16: 0 | AS16: 0 | AT16: 0 | AU16: 0 | AV16: 0 | AW16: 0 | AX16: 0 | AY16: 0 | AZ16: 0 | BA16: 0 | BB16: =BA16 -> 0 | BC16: 0 | BD16: 0 | BE16: 0 | BF16: 0 | BG16: 0 | BH16: 0 | BI16: 0 | BJ16: 0 | BK16: 0 | BL16: 0 | BM16: 0 | BN16: 0 | BO16: =BN16 -> 0 | BP16: 0 | BQ16: 0 | BR16: 0 | BS16: 0 | BT16: 0 | BU16: 0 | BV16: 0 | BW16: 0 | BX16: 0 | BY16: 0 | BZ16: 0 | CA16: 0 | CB16: =CA16 -> 0 | CC16: 0 | CD16: 0 | CE16: 0 | CF16: 0 | CG16: 0 | CH16: 0 | CI16: 0 | CJ16: 0 | CK16: 0 | CL16: 0 | CM16: 0 | CN16: 0 | CO16: =CN16 -> 0 | CP16: 0 | CQ16: 0 | CR16: 0 | CS16: 0 | CT16: 0 | CU16: 0 | CV16: 0 | CW16: 0 | CX16: 0 | CY16: 0 | CZ16: 0 | DA16: 0 | DB16: =DA16 -> 0 | DC16: 0 | DD16: 0 | DE16: 0 | DF16: 0 | DG16: 0 | DH16: 0 | DI16: 0 | DJ16: 0 | DK16: 0 | DL16: 0 | DM16: 0 | DN16: 0 | DO16: =DN16 -> 0 | DP16: 0 | DQ16: 0 | DR16: 0 | DS16: 0 | DT16: 0 | DU16: 0 | DV16: 0 | DW16: 0 | DX16: 0 | DY16: 0 | DZ16: 0 | EA16: 0 | EB16: =EA16 -> 0 | EC16: 0 | ED16: 0 | EE16: 0 | EF16: 0 | EG16: 0 | EH16: 0 | EI16: 0 | EJ16: 0 | EK16: 0 | EL16: 0 | EM16: 0 | EN16: 0 | EO16: =EN16 -> 0 | EP16: 0 | EQ16: 0 | ER16: 0 | ES16: 0 | ET16: 0 | EU16: 0 | EV16: 0 | EW16: 0 | EX16: 0 | EY16: 0 | EZ16: 0 | FA16: 0 | FB16: =FA16 -> 0 | FC16: 21931475 | FD16: 21931475 | FE16: 21931475 | FF16: 21931475 | FG16: 21931475 | FH16: 21931475 | FI16: 21931475 | FO16: =FI16 -> 21931475
B17: Servicio de Salud Viña del Mar - Quillota | C17: 0 | D17: 0 | E17: 0 | F17: 0 | G17: 0 | H17: 0 | I17: 0 | J17: 0 | K17: 0 | L17: 0 | M17: 0 | N17: 0 | O17: =N17 -> 0 | P17: 0 | Q17: 0 | R17: 0 | S17: 0 | T17: 0 | U17: 0 | V17: 0 | W17: 0 | X17: 0 | Y17: 0 | Z17: 0 | AA17: 0 | AB17: =AA17 -> 0 | AC17: 0 | AD17: 0 | AE17: 0 | AF17: 0 | AG17: 0 | AH17: 0 | AI17: 0 | AJ17: 0 | AK17: 0 | AL17: 0 | AM17: 0 | AN17: 0 | AO17: =AN17 -> 0 | AP17: 0 | AQ17: 0 | AR17: 0 | AS17: 0 | AT17: 0 | AU17: 0 | AV17: 0 | AW17: 0 | AX17: 0 | AY17: 0 | AZ17: 0 | BA17: 0 | BB17: =BA17 -> 0 | BC17: 0 | BD17: 0 | BE17: 0 | BF17: 0 | BG17: 0 | BH17: 0 | BI17: 0 | BJ17: 0 | BK17: 0 | BL17: 0 | BM17: 0 | BN17: 0 | BO17: =BN17 -> 0 | BP17: 0 | BQ17: 0 | BR17: 0 | BS17: 0 | BT17: 0 | BU17: 0 | BV17: 0 | BW17: 0 | BX17: 0 | BY17: 0 | BZ17: 0 | CA17: 0 | CB17: =CA17 -> 0 | CC17: 0 | CD17: 0 | CE17: 0 | CF17: 0 | CG17: 0 | CH17: 0 | CI17: 0 | CJ17: 0 | CK17: 0 | CL17: 0 | CM17: 0 | CN17: 0 | CO17: =CN17 -> 0 | CP17: 0 | CQ17: 0 | CR17: 0 | CS17: 0 | CT17: 0 | CU17: 0 | CV17: 0 | CW17: 0 | CX17: 0 | CY17: 0 | CZ17: 0 | DA17: 0 | DB17: =DA17 -> 0 | DC17: 0 | DD17: 0 | DE17: 0 | DF17: 0 | DG17: 0 | DH17: 0 | DI17: 0 | DJ17: 0 | DK17: 0 | DL17: 0 | DM17: 0 | DN17: 0 | DO17: =DN17 -> 0 | DP17: 0 | DQ17: 0 | DR17: 0 | DS17: 0 | DT17: 0 | DU17: 0 | DV17: 0 | DW17: 0 | DX17: 0 | DY17: 0 | DZ17: 0 | EA17: 0 | EB17: =EA17 -> 0 | EC17: 0 | ED17: 0 | EE17: 0 | EF17: 0 | EG17: 0 | EH17: 0 | EI17: 0 | EJ17: 0 | EK17: 0 | EL17: 0 | EM17: 0 | EN17: 0 | EO17: =EN17 -> 0 | EP17: 0 | EQ17: 0 | ER17: 0 | ES17: 0 | ET17: 0 | EU17: 0 | EV17: 0 | EW17: 0 | EX17: 0 | EY17: 0 | EZ17: 0 | FA17: 0 | FB17: =FA17 -> 0 | FC17: 50768194 | FD17: 50768194 | FE17: 50768194 | FF17: 50768194 | FG17: 50768194 | FH17: 50768194 | FI17: 50768194 | FO17: =FI17 -> 50768194
B18: Servicio de Salud Aconcagua | C18: 0 | D18: 0 | E18: 0 | F18: 0 | G18: 0 | H18: 0 | I18: 0 | J18: 0 | K18: 0 | L18: 0 | M18: 0 | N18: 0 | O18: =N18 -> 0 | P18: 0 | Q18: 0 | R18: 0 | S18: 0 | T18: 0 | U18: 0 | V18: 0 | W18: 0 | X18: 0 | Y18: 0 | Z18: 0 | AA18: 0 | AB18: =AA18 -> 0 | AC18: 0 | AD18: 0 | AE18: 0 | AF18: 0 | AG18: 0 | AH18: 0 | AI18: 0 | AJ18: 0 | AK18: 0 | AL18: 0 | AM18: 0 | AN18: 0 | AO18: =AN18 -> 0 | AP18: 0 | AQ18: 0 | AR18: 0 | AS18: 0 | AT18: 0 | AU18: 0 | AV18: 0 | AW18: 0 | AX18: 0 | AY18: 0 | AZ18: 0 | BA18: 0 | BB18: =BA18 -> 0 | BC18: 0 | BD18: 0 | BE18: 0 | BF18: 0 | BG18: 0 | BH18: 0 | BI18: 0 | BJ18: 0 | BK18: 0 | BL18: 0 | BM18: 0 | BN18: 0 | BO18: =BN18 -> 0 | BP18: 0 | BQ18: 0 | BR18: 0 | BS18: 0 | BT18: 0 | BU18: 0 | BV18: 0 | BW18: 0 | BX18: 0 | BY18: 0 | BZ18: 0 | CA18: 0 | CB18: =CA18 -> 0 | CC18: 0 | CD18: 0 | CE18: 0 | CF18: 0 | CG18: 0 | CH18: 0 | CI18: 0 | CJ18: 0 | CK18: 0 | CL18: 0 | CM18: 0 | CN18: 0 | CO18: =CN18 -> 0 | CP18: 0 | CQ18: 0 | CR18: 0 | CS18: 0 | CT18: 0 | CU18: 0 | CV18: 0 | CW18: 0 | CX18: 0 | CY18: 0 | CZ18: 0 | DA18: 0 | DB18: =DA18 -> 0 | DC18: 0 | DD18: 0 | DE18: 0 | DF18: 0 | DG18: 0 | DH18: 0 | DI18: 0 | DJ18: 0 | DK18: 0 | DL18: 0 | DM18: 0 | DN18: 0 | DO18: =DN18 -> 0 | DP18: 0 | DQ18: 0 | DR18: 0 | DS18: 0 | DT18: 0 | DU18: 0 | DV18: 0 | DW18: 0 | DX18: 0 | DY18: 0 | DZ18: 0 | EA18: 0 | EB18: =EA18 -> 0 | EC18: 0 | ED18: 0 | EE18: 0 | EF18: 0 | EG18: 0 | EH18: 0 | EI18: 0 | EJ18: 0 | EK18: 0 | EL18: 0 | EM18: 0 | EN18: 0 | EO18: =EN18 -> 0 | EP18: 0 | EQ18: 0 | ER18: 0 | ES18: 0 | ET18: 0 | EU18: 0 | EV18: 0 | EW18: 0 | EX18: 0 | EY18: 0 | EZ18: 0 | FA18: 0 | FB18: =FA18 -> 0 | FC18: 1204885 | FD18: 1204885 | FE18: 1204885 | FF18: 1204885 | FG18: 1204885 | FH18: 1204885 | FI18: 1204885 | FO18: =FI18 -> 1204885
B19: Servicio de Salud O'Higgins | C19: 0 | D19: 0 | E19: 0 | F19: 0 | G19: 0 | H19: 0 | I19: 0 | J19: 0 | K19: 0 | L19: 0 | M19: 0 | N19: 0 | O19: =N19 -> 0 | P19: 0 | Q19: 0 | R19: 0 | S19: 0 | T19: 0 | U19: 0 | V19: 0 | W19: 0 | X19: 0 | Y19: 0 | Z19: 0 | AA19: 0 | AB19: =AA19 -> 0 | AC19: 0 | AD19: 0 | AE19: 0 | AF19: 0 | AG19: 0 | AH19: 0 | AI19: 0 | AJ19: 0 | AK19: 0 | AL19: 0 | AM19: 0 | AN19: 0 | AO19: =AN19 -> 0 | AP19: 0 | AQ19: 0 | AR19: 0 | AS19: 0 | AT19: 0 | AU19: 0 | AV19: 0 | AW19: 0 | AX19: 0 | AY19: 0 | AZ19: 0 | BA19: 0 | BB19: =BA19 -> 0 | BC19: 0 | BD19: 0 | BE19: 0 | BF19: 0 | BG19: 0 | BH19: 0 | BI19: 0 | BJ19: 0 | BK19: 0 | BL19: 0 | BM19: 0 | BN19: 0 | BO19: =BN19 -> 0 | BP19: 0 | BQ19: 0 | BR19: 0 | BS19: 0 | BT19: 0 | BU19: 0 | BV19: 0 | BW19: 0 | BX19: 0 | BY19: 0 | BZ19: 0 | CA19: 0 | CB19: =CA19 -> 0 | CC19: 0 | CD19: 0 | CE19: 0 | CF19: 0 | CG19: 0 | CH19: 0 | CI19: 0 | CJ19: 0 | CK19: 0 | CL19: 0 | CM19: 0 | CN19: 0 | CO19: =CN19 -> 0 | CP19: 0 | CQ19: 0 | CR19: 0 | CS19: 0 | CT19: 0 | CU19: 0 | CV19: 0 | CW19: 0 | CX19: 0 | CY19: 0 | CZ19: 0 | DA19: 0 | DB19: =DA19 -> 0 | DC19: 0 | DD19: 0 | DE19: 0 | DF19: 0 | DG19: 0 | DH19: 0 | DI19: 0 | DJ19: 0 | DK19: 0 | DL19: 0 | DM19: 0 | DN19: 0 | DO19: =DN19 -> 0 | DP19: 0 | DQ19: 0 | DR19: 0 | DS19: 0 | DT19: 0 | DU19: 0 | DV19: 0 | DW19: 0 | DX19: 0 | DY19: 0 | DZ19: 0 | EA19: 0 | EB19: =EA19 -> 0 | EC19: 0 | ED19: 0 | EE19: 0 | EF19: 0 | EG19: 0 | EH19: 0 | EI19: 0 | EJ19: 0 | EK19: 0 | EL19: 0 | EM19: 0 | EN19: 0 | EO19: =EN19 -> 0 | EP19: 0 | EQ19: 0 | ER19: 0 | ES19: 0 | ET19: 0 | EU19: 0 | EV19: 0 | EW19: 0 | EX19: 0 | EY19: 0 | EZ19: 0 | FA19: 0 | FB19: =FA19 -> 0 | FC19: 1473262 | FD19: 1473262 | FE19: 1473262 | FF19: 1473262 | FG19: 1473262 | FH19: 1473262 | FI19: 1473262 | FO19: =FI19 -> 1473262
... B39: Servicio de Salud Chiloé | C39: 0 | D39: 0 | E39: 0 | F39: 0 | G39: 0 | H39: 0 | I39: 0 | J39: 0 | K39: 0 | L39: 0 | M39: 0 | N39: 0 | O39: =N39 -> 0 | P39: 0 | Q39: 0 | R39: 0 | S39: 0 | T39: 0 | U39: 0 | V39: 0 | W39: 0 | X39: 0 | Y39: 0 | Z39: 0 | AA39: 0 | AB39: =AA39 -> 0 | AC39: 0 | AD39: 0 | AE39: 0 | AF39: 0 | AG39: 0 | AH39: 0 | AI39: 0 | AJ39: 0 | AK39: 0 | AL39: 0 | AM39: 0 | AN39: 0 | AO39: =AN39 -> 0 | AP39: 0 | AQ39: 0 | AR39: 0 | AS39: 0 | AT39: 0 | AU39: 0 | AV39: 0 | AW39: 0 | AX39: 0 | AY39: 0 | AZ39: 0 | BA39: 0 | BB39: =BA39 -> 0 | BC39: 0 | BD39: 0 | BE39: 0 | BF39: 0 | BG39: 0 | BH39: 0 | BI39: 0 | BJ39: 0 | BK39: 0 | BL39: 0 | BM39: 0 | BN39: 0 | BO39: =BN39 -> 0 | BP39: 0 | BQ39: 0 | BR39: 0 | BS39: 0 | BT39: 0 | BU39: 0 | BV39: 0 | BW39: 0 | BX39: 0 | BY39: 0 | BZ39: 0 | CA39: 0 | CB39: =CA39 -> 0 | CC39: 0 | CD39: 0 | CE39: 0 | CF39: 0 | CG39: 0 | CH39: 0 | CI39: 0 | CJ39: 0 | CK39: 0 | CL39: 0 | CM39: 0 | CN39: 0 | CO39: =CN39 -> 0 | CP39: 0 | CQ39: 0 | CR39: 0 | CS39: 0 | CT39: 0 | CU39: 0 | CV39: 0 | CW39: 0 | CX39: 0 | CY39: 0 | CZ39: 0 | DA39: 0 | DB39: =DA39 -> 0 | DC39: 0 | DD39: 0 | DE39: 0 | DF39: 0 | DG39: 0 | DH39: 0 | DI39: 0 | DJ39: 0 | DK39: 0 | DL39: 0 | DM39: 0 | DN39: 0 | DO39: =DN39 -> 0 | DP39: 0 | DQ39: 0 | DR39: 0 | DS39: 0 | DT39: 0 | DU39: 0 | DV39: 0 | DW39: 0 | DX39: 0 | DY39: 0 | DZ39: 0 | EA39: 0 | EB39: =EA39 -> 0 | EC39: 0 | ED39: 0 | EE39: 0 | EF39: 0 | EG39: 0 | EH39: 0 | EI39: 0 | EJ39: 0 | EK39: 0 | EL39: 0 | EM39: 0 | EN39: 0 | EO39: =EN39 -> 0 | EP39: 0 | EQ39: 0 | ER39: 0 | ES39: 0 | ET39: 0 | EU39: 0 | EV39: 0 | EW39: 0 | EX39: 0 | EY39: 0 | EZ39: 0 | FA39: 0 | FB39: =FA39 -> 0 | FC39: 9165660 | FD39: 9165660 | FE39: 9165660 | FF39: 9165660 | FG39: 9165660 | FH39: 9165660 | FI39: 9165660 | FO39: =FI39 -> 9165660
B40: Total Presupuesto Ley (Subtítulo 31) | C40: =SUM(C8:C39) -> 275296243 | D40: =SUM(D8:D39) -> 275296243 | E40: =SUM(E8:E39) -> 275296243 | F40: =SUM(F8:F39) -> 275296243 | G40: =SUM(G8:G39) -> 275296243 | H40: =SUM(H8:H39) -> 275296243 | I40: =SUM(I8:I39) -> 275296243 | J40: =SUM(J8:J39) -> 275296243 | ... FO40: =SUM(FO8:FO39) -> 648268110
B41: Presupuesto Vigente (Subtítulo 31)
C42: 2014 | P42: 2015 | AC42: 2016 | AP42: 2017 | BC42: 2018 | BP42: 2019 | CC42: 2020 | CP42: 2021 | DC42: 2022 | DP42: 2023 | EC42: 2024 | EP42: 2025 | FC42: 2026
B43: Programa / Entidad | C43: Ene | D43: Feb | E43: Mar | F43: Abr | G43: May | H43: Jun | I43: Jul | J43: Ago | K43: Sep | L43: Oct | M43: Nov | N43: Dic | O43: Total 2014 | P43: Ene | Q43: Feb | R43: Mar | S43: Abr | T43: May | U43: Jun | V43: Jul | W43: Ago | X43: Sep | Y43: Oct | Z43: Nov | AA43: Dic | AB43: Total 2015 | AC43: Ene | AD43: Feb | AE43: Mar | AF43: Abr | AG43: May | AH43: Jun | AI43: Jul | AJ43: Ago | AK43: Sep | AL43: Oct | AM43: Nov | AN43: Dic | AO43: Total 2016 | AP43: Ene | AQ43: Feb | AR43: Mar | AS43: Abr | AT43: May | AU43: Jun | AV43: Jul | AW43: Ago | AX43: Sep | AY43: Oct | AZ43: Nov | BA43: Dic | BB43: Total 2017 | BC43: Ene | BD43: Feb | BE43: Mar | BF43: Abr | BG43: May | BH43: Jun | BI43: Jul | BJ43: Ago | BK43: Sep | BL43: Oct | BM43: Nov | BN43: Dic | BO43: Total 2018 | BP43: Ene | BQ43: Feb | BR43: Mar | BS43: Abr | BT43: May | BU43: Jun | BV43: Jul | BW43: Ago | BX43: Sep | BY43: Oct | BZ43: Nov | CA43: Dic | CB43: Total 2019 | CC43: Ene | CD43: Feb | CE43: Mar | CF43: Abr | CG43: May | CH43: Jun | CI43: Jul | CJ43: Ago | CK43: Sep | CL43: Oct | CM43: Nov | CN43: Dic | CO43: Total 2020 | CP43: Ene | CQ43: Feb | CR43: Mar | CS43: Abr | CT43: May | CU43: Jun | CV43: Jul | CW43: Ago | CX43: Sep | CY43: Oct | CZ43: Nov | DA43: Dic | DB43: Total 2021 | DC43: Ene | DD43: Feb | DE43: Mar | DF43: Abr | DG43: May | DH43: Jun | DI43: Jul | DJ43: Ago | DK43: Sep | DL43: Oct | DM43: Nov | DN43: Dic | DO43: Total 2022 | DP43: Ene | DQ43: Feb | DR43: Mar | DS43: Abr | DT43: May | DU43: Jun | DV43: Jul | DW43: Ago | DX43: Sep | DY43: Oct | DZ43: Nov | EA43: Dic | EB43: Total 2023 | EC43: Ene | ED43: Feb | EE43: Mar | EF43: Abr | EG43: May | EH43: Jun | EI43: Jul | EJ43: Ago | EK43: Sep | EL43: Oct | EM43: Nov | EN43: Dic | EO43: Total 2024 | EP43: Ene | EQ43: Feb | ER43: Mar | ES43: Abr | ET43: May | EU43: Jun | EV43: Jul | EW43: Ago | EX43: Sep | EY43: Oct | EZ43: Nov | FA43: Dic | FB43: Total 2025 | FC43: Ene | FD43: Feb | FE43: Mar | FF43: Abr | FG43: May | FH43: Jun | FI43: Jul | FJ43: Ago | FK43: Sep | FL43: Oct | FM43: Nov | FN43: Dic | FO43: Total 2026
B44: Instituto de Salud Pública | C44: 747570 | D44: 747570 | E44: 747570 | F44: 747570 | G44: 747570 | H44: 747570 | I44: 747570 | J44: 747570 | K44: 747570 | L44: 747570 | M44: 747570 | N44: 80263 | O44: =N44 -> 80263 | P44: 206000 | Q44: 206000 | R44: 206000 | S44: 206000 | T44: 206000 | U44: 206000 | V44: 206000 | W44: 206000 | X44: 128319 | Y44: 128319 | Z44: 128319 | AA44: 128319 | AB44: =AA44 -> 128319 | AC44: 0 | AD44: 0 | AE44: 0 | AF44: 0 | AG44: 0 | AH44: 0 | AI44: 0 | AJ44: 0 | AK44: 79759 | AL44: 79759 | AM44: 79759 | AN44: 79759 | AO44: =AN44 -> 79759 | AP44: 237364 | AQ44: 237364 | AR44: 237364 | AS44: 237364 | AT44: 237364 | AU44: 237364 | AV44: 237364 | AW44: 237364 | AX44: 237364 | AY44: 237364 | AZ44: 237364 | BA44: 237365 | BB44: =BA44 -> 237365 | BC44: 0 | BD44: 0 | BE44: 0 | BF44: 0 | BG44: 0 | BH44: 0 | BI44: 0 | BJ44: 0 | BK44: 0 | BL44: 0 | BM44: 0 | BN44: 0 | BO44: =BN44 -> 0 | BP44: 0 | BQ44: 0 | BR44: 0 | BS44: 0 | BT44: 0 | BU44: 0 | BV44: 0 | BW44: 0 | BX44: 0 | BY44: 0 | BZ44: 0 | CA44: 0 | CB44: =CA44 -> 0 | CC44: 1026000 | CD44: 1026000 | CE44: 1026000 | CF44: 1026000 | CG44: 1026000 | CH44: 1026000 | CI44: 1026000 | CJ44: 1026000 | CK44: 1026000 | CL44: 1026000 | CM44: 1026000 | CN44: 10000 | CO44: =CN44 -> 10000 | CP44: 800605 | CQ44: 800605 | CR44: 800605 | CS44: 800605 | CT44: 800605 | CU44: 800605 | CV44: 800605 | CW44: 800605 | CX44: 800605 | CY44: 800605 | CZ44: 800605 | DA44: 6000 | DB44: =DA44 -> 6000 | DC44: 2301909 | DD44: 2301909 | DE44: 2301909 | DF44: 2301909 | DG44: 2301909 | DH44: 2301909 | DI44: 2301909 | DJ44: 908340 | DK44: 358340 | DL44: 358340 | DM44: 358340 | DN44: 198608 | DO44: =DN44 -> 198608 | DP44: 1324402 | DQ44: 1324402 | DR44: 1324402 | DS44: 1324402 | DT44: 1324402 | DU44: 1324402 | DV44: 1324402 | DW44: 1324402 | DX44: 1324402 | DY44: 1324402 | DZ44: 1324402 | EA44: 319465 | EB44: =EA44 -> 319465 | EC44: 1459534 | ED44: 1459534 | EE44: 1459534 | EF44: 1459534 | EG44: 1459534 | EH44: 933233 | EI44: 933233 | EJ44: 933233 | EK44: 933233 | EL44: 933233 | EM44: 890106 | EN44: 788149 | EO44: =EN44 -> 788149 | EP44: 781455 | EQ44: 781455 | ER44: 781455 | ES44: 781455 | ET44: 781455 | EU44: 781455 | EV44: 781455 | EW44: 781455 | EX44: 781455 | EY44: 781455 | EZ44: 781455 | FA44: 707580 | FB44: =FA44 -> 707580 | FC44: 657325 | FD44: 657325 | FE44: 657325 | FF44: 657325 | FG44: 657325 | FH44: 657325 | FI44: 657325 | FO44: =FI44 -> 657325
B45: Subsecretaría de Salud Pública | C45: 0 | D45: 750633 | E45: 750633 | F45: 750633 | G45: 750633 | H45: 750633 | I45: 750633 | J45: 750633 | K45: 827570 | L45: 827570 | M45: 1487216 | N45: 1487216 | O45: =N45 -> 1487216 | P45: 0 | Q45: 3549492 | R45: 3549492 | S45: 3549492 | T45: 3549492 | U45: 3788029 | V45: 4410235 | W45: 3972874 | X45: 3972874 | Y45: 1926749 | Z45: 1926749 | AA45: 1405037 | AB45: =AA45 -> 1405037 | AC45: 0 | AD45: 3247660 | AE45: 3247660 | AF45: 3247660 | AG45: 3247660 | AH45: 3247660 | AI45: 3247660 | AJ45: 3247660 | AK45: 3247660 | AL45: 3247660 | AM45: 3247660 | AN45: 2185033 | AO45: =AN45 -> 2185033 | AP45: 0 | AQ45: 0 | AR45: 5429494 | AS45: 5429494 | AT45: 5429494 | AU45: 5429494 | AV45: 5429494 | AW45: 5429494 | AX45: 5117881 | AY45: 5117881 | AZ45: 5117881 | BA45: 5117881 | BB45: =BA45 -> 5117881 | BC45: 0 | BD45: 0 | BE45: 7088322 | BF45: 7088322 | BG45: 7088322 | BH45: 7088322 | BI45: 3593921 | BJ45: 3593921 | BK45: 3593921 | BL45: 3593921 | BM45: 3744869 | BN45: 2622679 | BO45: =BN45 -> 2622679 | BP45: 0 | BQ45: 0 | BR45: 0 | BS45: 2225014 | BT45: 2225014 | BU45: 2225014 | BV45: 2225014 | BW45: 1650553 | BX45: 1650553 | BY45: 1650553 | BZ45: 1650553 | CA45: 1363609 | CB45: =CA45 -> 1363609 | CC45: 0 | CD45: 0 | CE45: 803087 | CF45: 803087 | CG45: 803087 | CH45: 1233087 | CI45: 1233087 | CJ45: 1233087 | CK45: 1233087 | CL45: 1233087 | CM45: 1233087 | CN45: 1233087 | CO45: =CN45 -> 1233087 | CP45: 0 | CQ45: 2660955 | CR45: 2660955 | CS45: 2660955 | CT45: 2660955 | CU45: 2660955 | CV45: 2660955 | CW45: 2660955 | CX45: 2660955 | CY45: 2660955 | CZ45: 2183561 | DA45: 2183561 | DB45: =DA45 -> 2183561 | DC45: 0 | DD45: 5771729 | DE45: 5771729 | DF45: 5771729 | DG45: 5771729 | DH45: 5771729 | DI45: 5771729 | DJ45: 5771729 | DK45: 4001508 | DL45: 4001508 | DM45: 1706851 | DN45: 1706851 | DO45: =DN45 -> 1706851 | DP45: 0 | DQ45: 3873629 | DR45: 3873629 | DS45: 3873629 | DT45: 3873629 | DU45: 4435938 | DV45: 4435938 | DW45: 4435938 | DX45: 4435938 | DY45: 4435938 | DZ45: 4435938 | EA45: 3219261 | EB45: =EA45 -> 3219261 | EC45: 0 | ED45: 0 | EE45: 3831000 | EF45: 3831000 | EG45: 3831000 | EH45: 3880281 | EI45: 3880281 | EJ45: 3880281 | EK45: 3921585 | EL45: 4149585 | EM45: 3920742 | EN45: 3670742 | EO45: =EN45 -> 3670742 | EP45: 0 | EQ45: 2843210 | ER45: 2843210 | ES45: 2843210 | ET45: 2843210 | EU45: 2843210 | EV45: 2843210 | EW45: 2843210 | EX45: 2843210 | EY45: 2877119 | EZ45: 2019159 | FA45: 1493716 | FB45: =FA45 -> 1493716 | FC45: 3133791 | FD45: 3133791 | FE45: 3133791 | FF45: 3133791 | FG45: 3133791 | FH45: 3133791 | FI45: 3133791 | FO45: =FI45 -> 3133791
B46: Inversión Sectorial en Salud | C46: 274548673 | D46: 150121133 | E46: 31215164 | F46: 31215164 | G46: 31215164 | H46: 37715555 | I46: 37437770 | J46: 37437770 | K46: 249893 | L46: 249893 | M46: 12546246 | N46: 416473 | O46: =N46 -> 416473 | P46: 528813287 | Q46: 358253969 | R46: 152865381 | S46: 124037746 | T46: 119885657 | U46: 108081968 | V46: 79852267 | W46: 82163159 | X46: 74844726 | Y46: 60792289 | Z46: 5401287 | AA46: -6864505 | AB46: =AA46 -> -6864505 | AC46: 497824800 | AD46: 232511416 | AE46: 209153984 | AF46: 107272608 | AG46: 49900020 | AH46: 45194077 | AI46: 24782680 | AJ46: 9231280 | AK46: 6143223 | AL46: 13151410 | AM46: 20153093 | AN46: 39813989 | AO46: =AN46 -> 39813989 | AP46: 349316570 | AQ46: 166700292 | AR46: 54265806 | AS46: 49451706 | AT46: 40784024 | AU46: 16177516 | AV46: 10305477 | AW46: 7619787 | AX46: 12091504 | AY46: 6660514 | AZ46: 6660514 | BA46: 7733812 | BB46: =BA46 -> 7733812 | BC46: 439600285 | BD46: 439600285 | BE46: 308112580 | BF46: 157413097 | BG46: 66811661 | BH46: 20245463 | BI46: 22882943 | BJ46: 6774352 | BK46: -10059378 | BL46: 947927 | BM46: 692735 | BN46: 5158801 | BO46: =BN46 -> 5158801 | BP46: 418874044 | BQ46: 386527607 | BR46: 3457344 | BS46: 16001650 | BT46: 1554910 | BU46: 11275 | BV46: 0 | BW46: 0 | BX46: 1309068 | BY46: 1309068 | BZ46: 331587 | CA46: 1708355 | CB46: =CA46 -> 1708355 | CC46: 733952985 | CD46: 573847941 | CE46: 124149289 | CF46: 72300655 | CG46: 73061576 | CH46: 3855700 | CI46: 4244680 | CJ46: 19381846 | CK46: 2591847 | CL46: 8137191 | CM46: 48121228 | CN46: 701310 | CO46: =CN46 -> 701310 | CP46: 653979311 | CQ46: 62477958 | CR46: 38977535 | CS46: 10314489 | CT46: 13682093 | CU46: 8737222 | CV46: 12487969 | CW46: 23205049 | CX46: 23205049 | CY46: 86696492 | CZ46: 100114500 | DA46: 0 | DB46: =DA46 -> 0 | DC46: 642175866 | DD46: 166328149 | DE46: 111071146 | DF46: 111071146 | DG46: 20272961 | DH46: 17508 | DI46: 21741755 | DJ46: 21421965 | DK46: 87759254 | DL46: 84617599 | DM46: 53927937 | DN46: 0 | DO46: =DN46 -> 0 | DP46: 709260889 | DQ46: 312198013 | DR46: 271703488 | DS46: 266360982 | DT46: 214176069 | DU46: 202257983 | DV46: 142541359 | DW46: 74241870 | DX46: 74241870 | DY46: 49385560 | DZ46: 14812250 | EA46: 463 | EB46: =EA46 -> 463 | EC46: 581851338 | ED46: 28935584 | EE46: -22048777 | EF46: 9105205 | EG46: 5262741 | EH46: 10901732 | EI46: 15558025 | EJ46: 67379 | EK46: 622246 | EL46: 28875009 | EM46: 26189376 | EN46: 0 | EO46: =EN46 -> 0 | EP46: 573366549 | EQ46: 53140143 | ER46: 41684097 | ES46: 41684097 | ET46: 15687112 | EU46: 2508407 | EV46: 1553156 | EW46: 7169832 | EX46: 10580484 | EY46: 8375929 | EZ46: 298318 | FA46: 0 | FB46: =FA46 -> 0 | FC46: 201002151 | FD46: 176224317 | FE46: 176224317 | FF46: 176224317 | FG46: 111319589 | FH46: 30121356 | FI46: 30121356 | FO46: =FI46 -> 30121356
B47: Servicio de Salud Arica y Parinacota | C47: 0 | D47: 0 | E47: 146938 | F47: 146938 | G47: 146938 | H47: 146938 | I47: 146938 | J47: 146938 | K47: 167749 | L47: 167749 | M47: 167749 | N47: 167749 | O47: =N47 -> 167749 | P47: 0 | Q47: 0 | R47: 0 | S47: 0 | T47: 0 | U47: 419336 | V47: 559389 | W47: 559389 | X47: 559389 | Y47: 559389 | Z47: 559389 | AA47: 196429 | AB47: =AA47 -> 196429 | AC47: 0 | AD47: 1437282 | AE47: 1437282 | AF47: 1437282 | AG47: 2025995 | AH47: 2025995 | AI47: 2025995 | AJ47: 2025995 | AK47: 2102131 | AL47: 2102131 | AM47: 616651 | AN47: 616651 | AO47: =AN47 -> 616651 | AP47: 0 | AQ47: 0 | AR47: 0 | AS47: 0 | AT47: 1567112 | AU47: 1567112 | AV47: 1567112 | AW47: 1567112 | AX47: 985447 | AY47: 985447 | AZ47: 985447 | BA47: 776176 | BB47: =BA47 -> 776176 | BC47: 0 | BD47: 0 | BE47: 0 | BF47: 1796003 | BG47: 1796003 | BH47: 1796003 | BI47: 1796003 | BJ47: 1796003 | BK47: 1176839 | BL47: 1176839 | BM47: 1176839 | BN47: 1176839 | BO47: =BN47 -> 1176839 | BP47: 0 | BQ47: 0 | BR47: 0 | BS47: 0 | BT47: 411667 | BU47: 411667 | BV47: 411667 | BW47: 417070 | BX47: 417070 | BY47: 417070 | BZ47: 417070 | CA47: 417070 | CB47: =CA47 -> 417070 | CC47: 0 | CD47: 0 | CE47: 1045022 | CF47: 1045022 | CG47: 1391169 | CH47: 1391169 | CI47: 1391169 | CJ47: 1391169 | CK47: 1391169 | CL47: 1391169 | CM47: 1391169 | CN47: 1026451 | CO47: =CN47 -> 1026451 | CP47: 0 | CQ47: 0 | CR47: 427986 | CS47: 427986 | CT47: 427986 | CU47: 427986 | CV47: 427986 | CW47: 427986 | CX47: 427986 | CY47: 427986 | CZ47: 427986 | DA47: 150921 | DB47: =DA47 -> 150921 | DC47: 0 | DD47: 277067 | DE47: 277067 | DF47: 277067 | DG47: 277067 | DH47: 277067 | DI47: 277067 | DJ47: 277067 | DK47: 277067 | DL47: 277067 | DM47: 277068 | DN47: 277068 | DO47: =DN47 -> 277068 | DP47: 0 | DQ47: 0 | DR47: 0 | DS47: 0 | DT47: 0 | DU47: 0 | DV47: 0 | DW47: 0 | DX47: 0 | DY47: 0 | DZ47: 0 | EA47: 10 | EB47: =EA47 -> 10 | EC47: 0 | ED47: 0 | EE47: 0 | EF47: 664444 | EG47: 664444 | EH47: 744659 | EI47: 744659 | EJ47: 744659 | EK47: 744659 | EL47: 40227 | EM47: 40227 | EN47: 40227 | EO47: =EN47 -> 40227 | EP47: 0 | EQ47: 1899765 | ER47: 1899765 | ES47: 1899765 | ET47: 1899765 | EU47: 1899765 | EV47: 1899765 | EW47: 303882 | EX47: 303882 | EY47: 303882 | EZ47: 303882 | FA47: 11953 | FB47: =FA47 -> 11953 | FC47: 3783756 | FD47: 3783756 | FE47: 3783756 | FF47: 3783756 | FG47: 3783756 | FH47: 3783756 | FI47: 3783756 | FO47: =FI47 -> 3783756
B48: Servicio de Salud Tarapacá | C48: 0 | D48: 9330792 | E48: 12114237 | F48: 12114237 | G48: 12114237 | H48: 12114237 | I48: 12114237 | J48: 12127183 | K48: 12127183 | L48: 12127183 | M48: 4489148 | N48: 4489148 | O48: =N48 -> 4489148 | P48: 0 | Q48: 2686505 | R48: 24386332 | S48: 24386332 | T48: 24386332 | U48: 24838693 | V48: 24838693 | W48: 25140945 | X48: 25140945 | Y48: 25309999 | Z48: 24085402 | AA48: 12068846 | AB48: =AA48 -> 12068846 | AC48: 0 | AD48: 11123386 | AE48: 11204910 | AF48: 11226518 | AG48: 11226518 | AH48: 11226518 | AI48: 11226518 | AJ48: 11226518 | AK48: 11226518 | AL48: 7677344 | AM48: 7015437 | AN48: 5076846 | AO48: =AN48 -> 5076846 | AP48: 0 | AQ48: 7310545 | AR48: 7625611 | AS48: 7625611 | AT48: 7899831 | AU48: 7961206 | AV48: 7961206 | AW48: 9736372 | AX48: 9736372 | AY48: 9826369 | AZ48: 9826369 | BA48: 9995842 | BB48: =BA48 -> 9995842 | BC48: 0 | BD48: 0 | BE48: 1594476 | BF48: 1594476 | BG48: 1594476 | BH48: 3740428 | BI48: 3740428 | BJ48: 3936840 | BK48: 3232335 | BL48: 3232335 | BM48: 3232335 | BN48: 2166427 | BO48: =BN48 -> 2166427 | BP48: 0 | BQ48: 0 | BR48: 23550759 | BS48: 23550759 | BT48: 23550759 | BU48: 21844806 | BV48: 21339907 | BW48: 21339907 | BX48: 20637777 | BY48: 20637777 | BZ48: 20637777 | CA48: 23000558 | CB48: =CA48 -> 23000558 | CC48: 0 | CD48: 0 | CE48: 43224315 | CF48: 43224315 | CG48: 43224315 | CH48: 43224315 | CI48: 43224315 | CJ48: 43224315 | CK48: 45576985 | CL48: 45627985 | CM48: 39471769 | CN48: 38865928 | CO48: =CN48 -> 38865928 | CP48: 0 | CQ48: 46961726 | CR48: 46961726 | CS48: 46961726 | CT48: 46961726 | CU48: 46961726 | CV48: 46961726 | CW48: 46961726 | CX48: 46961726 | CY48: 46807023 | CZ48: 46807023 | DA48: 28698759 | DB48: =DA48 -> 28698759 | DC48: 0 | DD48: 25034876 | DE48: 25034876 | DF48: 25034876 | DG48: 25034876 | DH48: 25374884 | DI48: 25374884 | DJ48: 25374884 | DK48: 9379245 | DL48: 9800349 | DM48: 9748221 | DN48: 7674856 | DO48: =DN48 -> 7674856 | DP48: 0 | DQ48: 24810484 | DR48: 24810484 | DS48: 24810484 | DT48: 24869844 | DU48: 24869844 | DV48: 25248939 | DW48: 24208690 | DX48: 24208690 | DY48: 24350128 | DZ48: 18475646 | EA48: 17778770 | EB48: =EA48 -> 17778770 | EC48: 0 | ED48: 14776835 | EE48: 16008220 | EF48: 16276948 | EG48: 16276948 | EH48: 16276948 | EI48: 18371513 | EJ48: 17302216 | EK48: 17302216 | EL48: 15384683 | EM48: 11016165 | EN48: 10745147 | EO48: =EN48 -> 10745147 | EP48: 0 | EQ48: 19414328 | ER48: 19414328 | ES48: 19414328 | ET48: 19414328 | EU48: 19414328 | EV48: 21993341 | EW48: 21993341 | EX48: 22644417 | EY48: 22644417 | EZ48: 22644417 | FA48: 23461897 | FB48: =FA48 -> 23461897 | FC48: 22899006 | FD48: 22899006 | FE48: 22899006 | FF48: 22899006 | FG48: 22899006 | FH48: 22899006 | FI48: 22899006 | FO48: =FI48 -> 22899006
B49: Servicio de Salud Antofagasta | C49: 0 | D49: 0 | E49: 3169356 | F49: 3169356 | G49: 3169356 | H49: 3169356 | I49: 3169356 | J49: 3169356 | K49: 3169356 | L49: 3169356 | M49: 2417883 | N49: 2417883 | O49: =N49 -> 2417883 | P49: 0 | Q49: 0 | R49: 8626880 | S49: 8128929 | T49: 8148822 | U49: 8591077 | V49: 8980944 | W49: 8980944 | X49: 18799697 | Y49: 18799697 | Z49: 19025203 | AA49: 19025203 | AB49: =AA49 -> 19025203 | AC49: 0 | AD49: 1189930 | AE49: 1189930 | AF49: 21881976 | AG49: 21881976 | AH49: 21881976 | AI49: 22465335 | AJ49: 22465335 | AK49: 22465335 | AL49: 22465335 | AM49: 17839555 | AN49: 17583523 | AO49: =AN49 -> 17583523 | AP49: 0 | AQ49: 619993 | AR49: 619993 | AS49: 1168432 | AT49: 5168432 | AU49: 29442306 | AV49: 29442306 | AW49: 29442306 | AX49: 29442306 | AY49: 25719657 | AZ49: 25719657 | BA49: 39734626 | BB49: =BA49 -> 39734626 | BC49: 4104000 | BD49: 4104000 | BE49: 7244308 | BF49: 7244308 | BG49: 24288326 | BH49: 24288326 | BI49: 24288326 | BJ49: 24288326 | BK49: 23970739 | BL49: 19359839 | BM49: 19255839 | BN49: 16135811 | BO49: =BN49 -> 16135811 | BP49: 0 | BQ49: 0 | BR49: 9974536 | BS49: 9974536 | BT49: 9974536 | BU49: 9974536 | BV49: 9974536 | BW49: 9858013 | BX49: 9858013 | BY49: 9858013 | BZ49: 9858013 | CA49: 9458568 | CB49: =CA49 -> 9458568 | CC49: 0 | CD49: 0 | CE49: 659657 | CF49: 5524930 | CG49: 5524930 | CH49: 5542363 | CI49: 5542363 | CJ49: 5542363 | CK49: 5542363 | CL49: 5542363 | CM49: 5299317 | CN49: 1256956 | CO49: =CN49 -> 1256956 | CP49: 0 | CQ49: 0 | CR49: 510743 | CS49: 510743 | CT49: 510743 | CU49: 840656 | CV49: 840656 | CW49: 840656 | CX49: 840656 | CY49: 831012 | CZ49: 831012 | DA49: 738988 | DB49: =DA49 -> 738988 | DC49: 0 | DD49: 0 | DE49: 0 | DF49: 0 | DG49: 0 | DH49: 0 | DI49: 41470 | DJ49: 41470 | DK49: 41470 | DL49: 41470 | DM49: 41470 | DN49: 6490 | DO49: =DN49 -> 6490 | DP49: 0 | DQ49: 34980 | DR49: 34980 | DS49: 34980 | DT49: 34980 | DU49: 34980 | DV49: 34980 | DW49: 34980 | DX49: 34980 | DY49: 101007 | DZ49: 126276 | EA49: 126286 | EB49: =EA49 -> 126286 | EC49: 0 | ED49: 516417 | EE49: 516417 | EF49: 516417 | EG49: 516417 | EH49: 516417 | EI49: 516417 | EJ49: 676071 | EK49: 676071 | EL49: 737349 | EM49: 372584 | EN49: 361585 | EO49: =EN49 -> 361585 | EP49: 0 | EQ49: 3180410 | ER49: 3180410 | ES49: 3180410 | ET49: 3180410 | EU49: 3180410 | EV49: 3408370 | EW49: 3408370 | EX49: 3408370 | EY49: 3408370 | EZ49: 481841 | FA49: 3808031 | FB49: =FA49 -> 3808031 | FC49: 3191908 | FD49: 3191908 | FE49: 3191908 | FF49: 3191908 | FG49: 3191908 | FH49: 3368346 | FI49: 3368346 | FO49: =FI49 -> 3368346
B50: Servicio de Salud Atacama | C50: 0 | D50: 2641266 | E50: 2641266 | F50: 2641266 | G50: 2641266 | H50: 2641266 | I50: 2641266 | J50: 2641266 | K50: 2641266 | L50: 2641266 | M50: 4210322 | N50: 4210322 | O50: =N50 -> 4210322 | P50: 0 | Q50: 3537372 | R50: 3537372 | S50: 3546863 | T50: 3546863 | U50: 3546863 | V50: 3546863 | W50: 5764045 | X50: 5764045 | Y50: 5764045 | Z50: 6059318 | AA50: 7177293 | AB50: =AA50 -> 7177293 | AC50: 0 | AD50: 5239778 | AE50: 5239778 | AF50: 5239778 | AG50: 5328458 | AH50: 5328458 | AI50: 5328458 | AJ50: 5328458 | AK50: 5328458 | AL50: 5328458 | AM50: 5492902 | AN50: 6438977 | AO50: =AN50 -> 6438977 | AP50: 0 | AQ50: 0 | AR50: 0 | AS50: 0 | AT50: 0 | AU50: 35657 | AV50: 35657 | AW50: 35657 | AX50: 35657 | AY50: 35657 | AZ50: 35657 | BA50: 184164 | BB50: =BA50 -> 184164 | BC50: 0 | BD50: 0 | BE50: 7846290 | BF50: 7987290 | BG50: 7987290 | BH50: 7987290 | BI50: 7987290 | BJ50: 3757264 | BK50: 3757264 | BL50: 3757264 | BM50: 3757264 | BN50: 179417 | BO50: =BN50 -> 179417 | BP50: 0 | BQ50: 0 | BR50: 2875419 | BS50: 2875419 | BT50: 2875419 | BU50: 2875419 | BV50: 1345290 | BW50: 471574 | BX50: 471574 | BY50: 471574 | BZ50: 471574 | CA50: 202802 | CB50: =CA50 -> 202802 | CC50: 0 | CD50: 2492104 | CE50: 4964848 | CF50: 5213320 | CG50: 5213320 | CH50: 5213320 | CI50: 5830861 | CJ50: 5830861 | CK50: 5838195 | CL50: 5838195 | CM50: 5834329 | CN50: 5146527 | CO50: =CN50 -> 5146527 | CP50: 0 | CQ50: 7781605 | CR50: 7781605 | CS50: 7781605 | CT50: 7781605 | CU50: 13029086 | CV50: 12015839 | CW50: 12015839 | CX50: 12015839 | CY50: 3499181 | CZ50: 3499181 | DA50: 3495147 | DB50: =DA50 -> 3495147 | DC50: 0 | DD50: 6510718 | DE50: 6510718 | DF50: 6510718 | DG50: 6510718 | DH50: 5241843 | DI50: 3391074 | DJ50: 3391074 | DK50: 3391074 | DL50: 3391074 | DM50: 500372 | DN50: 500372 | DO50: =DN50 -> 500372 | DP50: 0 | DQ50: 2286234 | DR50: 2286234 | DS50: 2286234 | DT50: 2286234 | DU50: 2822620 | DV50: 3113391 | DW50: 3149621 | DX50: 3149621 | DY50: 3149621 | DZ50: 2694759 | EA50: 1914003 | EB50: =EA50 -> 1914003 | EC50: 0 | ED50: 9351608 | EE50: 10474268 | EF50: 10622073 | EG50: 10622073 | EH50: 10622073 | EI50: 9056514 | EJ50: 9056514 | EK50: 10477544 | EL50: 9210176 | EM50: 8848694 | EN50: 8848694 | EO50: =EN50 -> 8848694 | EP50: 0 | EQ50: 18012526 | ER50: 18012526 | ES50: 18012526 | ET50: 19119938 | EU50: 19119938 | EV50: 19119938 | EW50: 19119938 | EX50: 25642997 | EY50: 25642997 | EZ50: 25642997 | FA50: 24091722 | FB50: =FA50 -> 24091722 | FC50: 14546113 | FD50: 14546113 | FE50: 14546113 | FF50: 14546113 | FG50: 14546113 | FH50: 14546113 | FI50: 14546113 | FO50: =FI50 -> 14546113
B51: Servicio de Salud Coquimbo | C51: 0 | D51: 345904 | E51: 4454874 | F51: 4454874 | G51: 4454874 | H51: 4454874 | I51: 4454874 | J51: 4454874 | K51: 4454874 | L51: 4454874 | M51: 1397898 | N51: 1397898 | O51: =N51 -> 1397898 | P51: 0 | Q51: 1959512 | R51: 29207336 | S51: 29207336 | T51: 29207336 | U51: 29595225 | V51: 31607082 | W51: 32938652 | X51: 32938652 | Y51: 32938652 | Z51: 30368502 | AA51: 32433196 | AB51: =AA51 -> 32433196 | AC51: 0 | AD51: 22924268 | AE51: 22924268 | AF51: 34137329 | AG51: 34945433 | AH51: 38549075 | AI51: 40544693 | AJ51: 40544693 | AK51: 40544693 | AL51: 39796581 | AM51: 39796581 | AN51: 33732703 | AO51: =AN51 -> 33732703 | AP51: 0 | AQ51: 10642316 | AR51: 31177412 | AS51: 31223104 | AT51: 31223104 | AU51: 31684092 | AV51: 32047649 | AW51: 32047649 | AX51: 32063275 | AY51: 34825129 | AZ51: 34825129 | BA51: 39387368 | BB51: =BA51 -> 39387368 | BC51: 0 | BD51: 0 | BE51: 3596099 | BF51: 31372988 | BG51: 31372988 | BH51: 33133147 | BI51: 33133147 | BJ51: 31916936 | BK51: 31233271 | BL51: 31233271 | BM51: 31233271 | BN51: 33998210 | BO51: =BN51 -> 33998210 | BP51: 0 | BQ51: 0 | BR51: 7711373 | BS51: 8159373 | BT51: 19850079 | BU51: 33035158 | BV51: 34001547 | BW51: 42902399 | BX51: 43252598 | BY51: 43252598 | BZ51: 43380504 | CA51: 42990744 | CB51: =CA51 -> 42990744 | CC51: 0 | CD51: 3548906 | CE51: 27589071 | CF51: 27769405 | CG51: 27786080 | CH51: 27786080 | CI51: 27786080 | CJ51: 27786080 | CK51: 36726968 | CL51: 36726968 | CM51: 36667691 | CN51: 34799647 | CO51: =CN51 -> 34799647 | CP51: 0 | CQ51: 25983059 | CR51: 25983059 | CS51: 25983059 | CT51: 25983059 | CU51: 25983059 | CV51: 25983059 | CW51: 25983059 | CX51: 25983059 | CY51: 23060165 | CZ51: 23060165 | DA51: 19776064 | DB51: =DA51 -> 19776064 | DC51: 0 | DD51: 5175093 | DE51: 11939315 | DF51: 11939315 | DG51: 11939315 | DH51: 11939315 | DI51: 11945115 | DJ51: 11945115 | DK51: 12989257 | DL51: 9044189 | DM51: 9044189 | DN51: 5887868 | DO51: =DN51 -> 5887868 | DP51: 0 | DQ51: 742082 | DR51: 1842082 | DS51: 1842082 | DT51: 1842082 | DU51: 2332216 | DV51: 2580761 | DW51: 2580761 | DX51: 2580761 | DY51: 2630763 | DZ51: 2130764 | EA51: 2231319 | EB51: =EA51 -> 2231319 | EC51: 0 | ED51: 9632104 | EE51: 11190703 | EF51: 13715752 | EG51: 13715752 | EH51: 14086953 | EI51: 6041399 | EJ51: 6071748 | EK51: 6071748 | EL51: 4664885 | EM51: 4664886 | EN51: 4432051 | EO51: =EN51 -> 4432051 | EP51: 0 | EQ51: 12759484 | ER51: 12759484 | ES51: 12759484 | ET51: 12759484 | EU51: 12759484 | EV51: 12759484 | EW51: 12759484 | EX51: 21660342 | EY51: 21660352 | EZ51: 21660352 | FA51: 23225106 | FB51: =FA51 -> 23225106 | FC51: 15086131 | FD51: 15086131 | FE51: 15086131 | FF51: 15086131 | FG51: 15086131 | FH51: 32743030 | FI51: 32743030 | FO51: =FI51 -> 32743030
B52: Servicio de Salud Valparaíso - San Antonio | C52: 0 | D52: 1916581 | E52: 3977404 | F52: 3977404 | G52: 3977404 | H52: 3977404 | I52: 3977404 | J52: 4173083 | K52: 4084865 | L52: 4084865 | M52: 2845839 | N52: 2845839 | O52: =N52 -> 2845839 | P52: 0 | Q52: 6374294 | R52: 6374294 | S52: 7287916 | T52: 7352711 | U52: 7352711 | V52: 8276225 | W52: 8276225 | X52: 8318756 | Y52: 8318756 | Z52: 9978629 | AA52: 9901229 | AB52: =AA52 -> 9901229 | AC52: 0 | AD52: 1350133 | AE52: 1350133 | AF52: 8952099 | AG52: 8952099 | AH52: 8952099 | AI52: 17067911 | AJ52: 17537003 | AK52: 17537003 | AL52: 17537003 | AM52: 16297726 | AN52: 7280150 | AO52: =AN52 -> 7280150 | AP52: 0 | AQ52: 0 | AR52: 4173687 | AS52: 4173687 | AT52: 4490532 | AU52: 4726084 | AV52: 4847908 | AW52: 4847908 | AX52: 4847908 | AY52: 9847908 | AZ52: 9847908 | BA52: 11580328 | BB52: =BA52 -> 11580328 | BC52: 0 | BD52: 0 | BE52: 1816004 | BF52: 7498429 | BG52: 20549147 | BH52: 20600725 | BI52: 20600725 | BJ52: 21065317 | BK52: 21811505 | BL52: 21811505 | BM52: 21811505 | BN52: 25096798 | BO52: =BN52 -> 25096798 | BP52: 0 | BQ52: 0 | BR52: 23839105 | BS52: 23839105 | BT52: 24267388 | BU52: 25551163 | BV52: 32469688 | BW52: 31819239 | BX52: 27176964 | BY52: 27176964 | BZ52: 27176964 | CA52: 24461848 | CB52: =CA52 -> 24461848 | CC52: 0 | CD52: 1194232 | CE52: 35224056 | CF52: 35224056 | CG52: 35224056 | CH52: 35224056 | CI52: 35224056 | CJ52: 35224056 | CK52: 39183354 | CL52: 38137553 | CM52: 38137553 | CN52: 39764885 | CO52: =CN52 -> 39764885 | CP52: 0 | CQ52: 94212588 | CR52: 94622434 | CS52: 94670565 | CT52: 94670565 | CU52: 94670565 | CV52: 94670565 | CW52: 94670565 | CX52: 94670565 | CY52: 94670565 | CZ52: 88981177 | DA52: 43077057 | DB52: =DA52 -> 43077057 | DC52: 0 | DD52: 61947100 | DE52: 61988684 | DF52: 61988684 | DG52: 61988684 | DH52: 61988684 | DI52: 61988684 | DJ52: 61993761 | DK52: 21670003 | DL52: 21670003 | DM52: 21546967 | DN52: 21371187 | DO52: =DN52 -> 21371187 | DP52: 0 | DQ52: 22148995 | DR52: 22148995 | DS52: 22148995 | DT52: 22521554 | DU52: 23131185 | DV52: 28207827 | DW52: 39289940 | DX52: 39289940 | DY52: 40072382 | DZ52: 40072382 | EA52: 27799825 | EB52: =EA52 -> 27799825 | EC52: 0 | ED52: 38060055 | EE52: 38884554 | EF52: 38913763 | EG52: 35119896 | EH52: 35134211 | EI52: 35134211 | EJ52: 35805869 | EK52: 34287274 | EL52: 20231382 | EM52: 19568840 | EN52: 16696164 | EO52: =EN52 -> 16696164 | EP52: 0 | EQ52: 11138854 | ER52: 14916172 | ES52: 14916172 | ET52: 14916172 | EU52: 14916172 | EV52: 14916172 | EW52: 22787635 | EX52: 19742032 | EY52: 19742032 | EZ52: 20748661 | FA52: 14450372 | FB52: =FA52 -> 14450372 | FC52: 21931475 | FD52: 21931475 | FE52: 21931475 | FF52: 21931475 | FG52: 21931475 | FH52: 21931475 | FI52: 21931475 | FO52: =FI52 -> 21931475
B53: Servicio de Salud Viña del Mar - Quillota | C53: 0 | D53: 14200952 | E53: 17211877 | F53: 17211877 | G53: 17211877 | H53: 17211877 | I53: 17211877 | J53: 17211877 | K53: 17571737 | L53: 17571737 | M53: 14432839 | N53: 14432839 | O53: =N53 -> 14432839 | P53: 0 | Q53: 37349058 | R53: 38544000 | S53: 38544000 | T53: 38544000 | U53: 19364883 | V53: 20174823 | W53: 20174823 | X53: 20174823 | Y53: 20174823 | Z53: 19731820 | AA53: 13971514 | AB53: =AA53 -> 13971514 | AC53: 0 | AD53: 28445774 | AE53: 28445774 | AF53: 28445774 | AG53: 28785782 | AH53: 28785782 | AI53: 28785782 | AJ53: 28785782 | AK53: 28785782 | AL53: 27934856 | AM53: 31293072 | AN53: 31036612 | AO53: =AN53 -> 31036612 | AP53: 0 | AQ53: 26170758 | AR53: 33080922 | AS53: 33080922 | AT53: 33352044 | AU53: 28542723 | AV53: 28542723 | AW53: 28542723 | AX53: 26202259 | AY53: 26222661 | AZ53: 26222661 | BA53: 32500455 | BB53: =BA53 -> 32500455 | BC53: 0 | BD53: 0 | BE53: 6767614 | BF53: 8951625 | BG53: 60797954 | BH53: 65607599 | BI53: 65607599 | BJ53: 65229175 | BK53: 59682383 | BL53: 54000995 | BM53: 54000995 | BN53: 57311644 | BO53: =BN53 -> 57311644 | BP53: 0 | BQ53: 0 | BR53: 68655332 | BS53: 68655332 | BT53: 68655332 | BU53: 87719084 | BV53: 109889410 | BW53: 105140785 | BX53: 81119392 | BY53: 81119392 | BZ53: 81119392 | CA53: 79006256 | CB53: =CA53 -> 79006256 | CC53: 0 | CD53: 1699139 | CE53: 59438757 | CF53: 59438757 | CG53: 59438757 | CH53: 59438757 | CI53: 70389228 | CJ53: 70389228 | CK53: 68983371 | CL53: 71283152 | CM53: 87062635 | CN53: 76996230 | CO53: =CN53 -> 76996230 | CP53: 0 | CQ53: 73129143 | CR53: 84952896 | CS53: 92682381 | CT53: 87098904 | CU53: 88402567 | CV53: 88402567 | CW53: 88402567 | CX53: 88402567 | CY53: 63708029 | CZ53: 63708029 | DA53: 58124956 | DB53: =DA53 -> 58124956 | DC53: 0 | DD53: 28198290 | DE53: 49698791 | DF53: 49698791 | DG53: 49822842 | DH53: 46663035 | DI53: 46668035 | DJ53: 46668036 | DK53: 40949590 | DL53: 40949590 | DM53: 38104655 | DN53: 38105075 | DO53: =DN53 -> 38105075 | DP53: 0 | DQ53: 37954062 | DR53: 37954062 | DS53: 37954062 | DT53: 37954062 | DU53: 37954062 | DV53: 40069991 | DW53: 38849601 | DX53: 38849601 | DY53: 53081099 | DZ53: 53081099 | EA53: 46577194 | EB53: =EA53 -> 46577194 | EC53: 0 | ED53: 54853078 | EE53: 60054090 | EF53: 60150724 | EG53: 60150724 | EH53: 60150724 | EI53: 88041423 | EJ53: 88041423 | EK53: 87680374 | EL53: 84793012 | EM53: 86351205 | EN53: 86176977 | EO53: =EN53 -> 86176977 | EP53: 0 | EQ53: 69438475 | ER53: 69438475 | ES53: 69438475 | ET53: 69438475 | EU53: 69438475 | EV53: 69438475 | EW53: 69438475 | EX53: 69438475 | EY53: 62110568 | EZ53: 62646658 | FA53: 53192169 | FB53: =FA53 -> 53192169 | FC53: 50768194 | FD53: 50768194 | FE53: 50768194 | FF53: 50768194 | FG53: 50768194 | FH53: 50768194 | FI53: 50768194 | FO53: =FI53 -> 50768194
B54: Servicio de Salud Aconcagua | C54: 0 | D54: 0 | E54: 5701337 | F54: 5701337 | G54: 5701337 | H54: 5701337 | I54: 5701337 | J54: 5701337 | K54: 5749103 | L54: 5749103 | M54: 6880351 | N54: 6880351 | O54: =N54 -> 6880351 | P54: 0 | Q54: 523372 | R54: 4092998 | S54: 4092998 | T54: 4094118 | U54: 4094118 | V54: 4481933 | W54: 4820379 | X54: 4820379 | Y54: 4820379 | Z54: 4820379 | AA54: 4712903 | AB54: =AA54 -> 4712903 | AC54: 0 | AD54: 2033337 | AE54: 2033337 | AF54: 2929829 | AG54: 2929829 | AH54: 2929829 | AI54: 5974542 | AJ54: 5974542 | AK54: 5974542 | AL54: 5974542 | AM54: 5974542 | AN54: 1090165 | AO54: =AN54 -> 1090165 | AP54: 0 | AQ54: 7995190 | AR54: 7995190 | AS54: 7995190 | AT54: 7995190 | AU54: 7995190 | AV54: 8235664 | AW54: 8235664 | AX54: 8235664 | AY54: 8235664 | AZ54: 8235664 | BA54: 7375229 | BB54: =BA54 -> 7375229 | BC54: 0 | BD54: 0 | BE54: 2769431 | BF54: 2938550 | BG54: 2938550 | BH54: 6638550 | BI54: 6638550 | BJ54: 7105224 | BK54: 4332695 | BL54: 4332695 | BM54: 4332695 | BN54: 5721273 | BO54: =BN54 -> 5721273 | BP54: 0 | BQ54: 0 | BR54: 6114000 | BS54: 6114000 | BT54: 6114000 | BU54: 8207493 | BV54: 8207493 | BW54: 7457441 | BX54: 7457441 | BY54: 7457441 | BZ54: 7457441 | CA54: 7222477 | CB54: =CA54 -> 7222477 | CC54: 0 | CD54: 161686 | CE54: 11162577 | CF54: 11803716 | CG54: 11803716 | CH54: 11803716 | CI54: 11803716 | CJ54: 11803716 | CK54: 11941495 | CL54: 11941495 | CM54: 5749218 | CN54: 5749218 | CO54: =CN54 -> 5749218 | CP54: 0 | CQ54: 7480282 | CR54: 7480282 | CS54: 7480282 | CT54: 7480282 | CU54: 7480282 | CV54: 7480282 | CW54: 7480282 | CX54: 7480282 | CY54: 6924886 | CZ54: 5513920 | DA54: 5518920 | DB54: =DA54 -> 5518920 | DC54: 0 | DD54: 0 | DE54: 8515350 | DF54: 8515350 | DG54: 8515350 | DH54: 8515350 | DI54: 8725865 | DJ54: 8747938 | DK54: 8747938 | DL54: 8839092 | DM54: 9730433 | DN54: 9586115 | DO54: =DN54 -> 9586115 | DP54: 0 | DQ54: 4526012 | DR54: 4526012 | DS54: 4526012 | DT54: 5166889 | DU54: 5166889 | DV54: 5878289 | DW54: 5878289 | DX54: 5878289 | DY54: 6239810 | DZ54: 6239810 | EA54: 4774007 | EB54: =EA54 -> 4774007 | EC54: 0 | ED54: 0 | EE54: 1726303 | EF54: 1726303 | EG54: 1726303 | EH54: 2913565 | EI54: 3098352 | EJ54: 3098352 | EK54: 2659288 | EL54: 1559535 | EM54: 1405224 | EN54: 1335225 | EO54: =EN54 -> 1335225 | EP54: 0 | EQ54: 4801570 | ER54: 4801570 | ES54: 4801570 | ET54: 4801570 | EU54: 5337303 | EV54: 5337303 | EW54: 5337303 | EX54: 5337303 | EY54: 5337303 | EZ54: 5337303 | FA54: 3499759 | FB54: =FA54 -> 3499759 | FC54: 1204885 | FD54: 1204885 | FE54: 1204885 | FF54: 1204885 | FG54: 1204885 | FH54: 1204885 | FI54: 1204885 | FO54: =FI54 -> 1204885
B55: Servicio de Salud O'Higgins | C55: 0 | D55: 677977 | E55: 19799480 | F55: 19799480 | G55: 19799480 | H55: 19799480 | I55: 19799480 | J55: 19958552 | K55: 29146596 | L55: 29146596 | M55: 25161182 | N55: 24065884 | O55: =N55 -> 24065884 | P55: 0 | Q55: 2149861 | R55: 11124605 | S55: 11124605 | T55: 11124605 | U55: 12744569 | V55: 12744569 | W55: 13269216 | X55: 13269216 | Y55: 13704241 | Z55: 15246075 | AA55: 14725343 | AB55: =AA55 -> 14725343 | AC55: 0 | AD55: 7086764 | AE55: 10778454 | AF55: 14508313 | AG55: 16819818 | AH55: 16819818 | AI55: 16837758 | AJ55: 16831025 | AK55: 16831025 | AL55: 19701524 | AM55: 19701524 | AN55: 10955055 | AO55: =AN55 -> 10955055 | AP55: 0 | AQ55: 7481603 | AR55: 7481603 | AS55: 7481603 | AT55: 7481603 | AU55: 8260505 | AV55: 9160652 | AW55: 9160652 | AX55: 9160652 | AY55: 9256549 | AZ55: 9256549 | BA55: 12611145 | BB55: =BA55 -> 12611145 | BC55: 0 | BD55: 0 | BE55: 3809389 | BF55: 4646891 | BG55: 4646891 | BH55: 7824234 | BI55: 7824234 | BJ55: 6202605 | BK55: 5761388 | BL55: 5761388 | BM55: 5761388 | BN55: 4542890 | BO55: =BN55 -> 4542890 | BP55: 0 | BQ55: 0 | BR55: 8204529 | BS55: 8204529 | BT55: 8204529 | BU55: 8265763 | BV55: 9699974 | BW55: 9699974 | BX55: 9666612 | BY55: 9666612 | BZ55: 9666612 | CA55: 10131723 | CB55: =CA55 -> 10131723 | CC55: 0 | CD55: 0 | CE55: 3225551 | CF55: 3225551 | CG55: 3225551 | CH55: 3225551 | CI55: 3225551 | CJ55: 3225551 | CK55: 1770446 | CL55: 1770446 | CM55: 1770446 | CN55: 1606025 | CO55: =CN55 -> 1606025 | CP55: 0 | CQ55: 1248525 | CR55: 1248525 | CS55: 1248525 | CT55: 1248525 | CU55: 1248525 | CV55: 1297030 | CW55: 422087 | CX55: 422087 | CY55: 422087 | CZ55: 329151 | DA55: 329151 | DB55: =DA55 -> 329151 | DC55: 0 | DD55: 2368363 | DE55: 2368363 | DF55: 2368363 | DG55: 2368363 | DH55: 2368363 | DI55: 621715 | DJ55: 621715 | DK55: 621715 | DL55: 621715 | DM55: 417098 | DN55: 417098 | DO55: =DN55 -> 417098 | DP55: 0 | DQ55: 4073367 | DR55: 4073367 | DS55: 4073367 | DT55: 4073367 | DU55: 4073367 | DV55: 3462868 | DW55: 3462868 | DX55: 3462868 | DY55: 3462868 | DZ55: 3462868 | EA55: 3790966 | EB55: =EA55 -> 3790966 | EC55: 0 | ED55: 4248637 | EE55: 4248637 | EF55: 4248637 | EG55: 4483836 | EH55: 4483836 | EI55: 4483836 | EJ55: 4483836 | EK55: 6019574 | EL55: 5139751 | EM55: 5139751 | EN55: 5139751 | EO55: =EN55 -> 5139751 | EP55: 0 | EQ55: 4699720 | ER55: 4699720 | ES55: 4699720 | ET55: 4699720 | EU55: 4699720 | EV55: 4699720 | EW55: 4699720 | EX55: 3072070 | EY55: 3601813 | EZ55: 3601813 | FA55: 2365042 | FB55: =FA55 -> 2365042 | FC55: 1473262 | FD55: 1473262 | FE55: 1473262 | FF55: 1473262 | FG55: 1473262 | FH55: 1729150 | FI55: 1729150 | FO55: =FI55 -> 1729150
... B75: Servicio de Salud Chiloé | C75: 0 | D75: 1271674 | E75: 1271674 | F75: 1271674 | G75: 1271674 | H75: 1271674 | I75: 1271674 | J75: 1271674 | K75: 1271674 | L75: 1271674 | M75: 681165 | N75: 682622 | O75: =N75 -> 682622 | P75: 0 | Q75: 2960931 | R75: 6775108 | S75: 6775108 | T75: 6775108 | U75: 6775108 | V75: 8301701 | W75: 8942547 | X75: 7125510 | Y75: 7125510 | Z75: 7056593 | AA75: 5769292 | AB75: =AA75 -> 5769292 | AC75: 0 | AD75: 10015980 | AE75: 14074038 | AF75: 14074038 | AG75: 14074038 | AH75: 14074038 | AI75: 16035695 | AJ75: 16035695 | AK75: 16035695 | AL75: 16071937 | AM75: 10325746 | AN75: 3566921 | AO75: =AN75 -> 3566921 | AP75: 0 | AQ75: 6552678 | AR75: 6552678 | AS75: 6552678 | AT75: 8047104 | AU75: 8455718 | AV75: 6192125 | AW75: 6117950 | AX75: 6119178 | AY75: 6120501 | AZ75: 6120501 | BA75: 3994046 | BB75: =BA75 -> 3994046 | BC75: 0 | BD75: 0 | BE75: 13143393 | BF75: 15425183 | BG75: 21883950 | BH75: 21883950 | BI75: 21883950 | BJ75: 27091863 | BK75: 25156140 | BL75: 25156140 | BM75: 25156140 | BN75: 22327963 | BO75: =BN75 -> 22327963 | BP75: 0 | BQ75: 0 | BR75: 36078821 | BS75: 36078821 | BT75: 36078821 | BU75: 36078821 | BV75: 37415015 | BW75: 35544307 | BX75: 35451308 | BY75: 35451308 | BZ75: 35451308 | CA75: 35431815 | CB75: =CA75 -> 35431815 | CC75: 0 | CD75: 27416748 | CE75: 28674843 | CF75: 28674843 | CG75: 28674843 | CH75: 28674843 | CI75: 28746994 | CJ75: 41919303 | CK75: 41919303 | CL75: 41919303 | CM75: 41919303 | CN75: 39170355 | CO75: =CN75 -> 39170355 | CP75: 0 | CQ75: 30650605 | CR75: 38234031 | CS75: 38234031 | CT75: 38234031 | CU75: 38234031 | CV75: 38234031 | CW75: 38234031 | CX75: 38234031 | CY75: 35301165 | CZ75: 35301165 | DA75: 35119670 | DB75: =DA75 -> 35119670 | DC75: 0 | DD75: 29939195 | DE75: 29939195 | DF75: 29939195 | DG75: 29939195 | DH75: 29939195 | DI75: 29941049 | DJ75: 29941049 | DK75: 29941049 | DL75: 34255571 | DM75: 32849144 | DN75: 30478138 | DO75: =DN75 -> 30478138 | DP75: 0 | DQ75: 21688499 | DR75: 21688499 | DS75: 21688499 | DT75: 37169814 | DU75: 37977508 | DV75: 40365139 | DW75: 40365139 | DX75: 40365139 | DY75: 40544437 | DZ75: 40544437 | EA75: 27448313 | EB75: =EA75 -> 27448313 | EC75: 0 | ED75: 37649448 | EE75: 39923719 | EF75: 39994550 | EG75: 39994550 | EH75: 39994550 | EI75: 51179211 | EJ75: 52617185 | EK75: 52617185 | EL75: 49930384 | EM75: 47527578 | EN75: 47527578 | EO75: =EN75 -> 47527578 | EP75: 0 | EQ75: 22007344 | ER75: 22007344 | ES75: 22007344 | ET75: 39627780 | EU75: 39627780 | EV75: 39627780 | EW75: 39627780 | EX75: 44659454 | EY75: 44659454 | EZ75: 44659454 | FA75: 37774937 | FB75: =FA75 -> 37774937 | FC75: 9165660 | FD75: 9165660 | FE75: 9165660 | FF75: 9165660 | FG75: 9165660 | FH75: 16509780 | FI75: 16509780 | FO75: =FI75 -> 16509780
B76: Total Presupuesto Vigente (Subtítulo 31) | C76: =SUM(C44:C75) -> 275296243 | D76: =SUM(D44:D75) -> 269860741 | E76: =SUM(E44:E75) -> 269860741 | F76: =SUM(F44:F75) -> 269860741 | G76: =SUM(G44:G75) -> 269860741 | H76: =SUM(H44:H75) -> 276361132 | I76: =SUM(I44:I75) -> 276083347 | J76: =SUM(J44:J75) -> 278808626 | ... FO76: =SUM(FO44:FO75) -> 558585548
B77: Ejecución Acumulada (Subtítulo 31)
C78: 2014 | P78: 2015 | AC78: 2016 | AP78: 2017 | BC78: 2018 | BP78: 2019 | CC78: 2020 | CP78: 2021 | DC78: 2022 | DP78: 2023 | EC78: 2024 | EP78: 2025 | FC78: 2026
B79: Programa / Entidad | C79: Ene | D79: Feb | E79: Mar | F79: Abr | G79: May | H79: Jun | I79: Jul | J79: Ago | K79: Sep | L79: Oct | M79: Nov | N79: Dic | O79: Total 2014 | P79: Ene | Q79: Feb | R79: Mar | S79: Abr | T79: May | U79: Jun | V79: Jul | W79: Ago | X79: Sep | Y79: Oct | Z79: Nov | AA79: Dic | AB79: Total 2015 | AC79: Ene | AD79: Feb | AE79: Mar | AF79: Abr | AG79: May | AH79: Jun | AI79: Jul | AJ79: Ago | AK79: Sep | AL79: Oct | AM79: Nov | AN79: Dic | AO79: Total 2016 | AP79: Ene | AQ79: Feb | AR79: Mar | AS79: Abr | AT79: May | AU79: Jun | AV79: Jul | AW79: Ago | AX79: Sep | AY79: Oct | AZ79: Nov | BA79: Dic | BB79: Total 2017 | BC79: Ene | BD79: Feb | BE79: Mar | BF79: Abr | BG79: May | BH79: Jun | BI79: Jul | BJ79: Ago | BK79: Sep | BL79: Oct | BM79: Nov | BN79: Dic | BO79: Total 2018 | BP79: Ene | BQ79: Feb | BR79: Mar | BS79: Abr | BT79: May | BU79: Jun | BV79: Jul | BW79: Ago | BX79: Sep | BY79: Oct | BZ79: Nov | CA79: Dic | CB79: Total 2019 | CC79: Ene | CD79: Feb | CE79: Mar | CF79: Abr | CG79: May | CH79: Jun | CI79: Jul | CJ79: Ago | CK79: Sep | CL79: Oct | CM79: Nov | CN79: Dic | CO79: Total 2020 | CP79: Ene | CQ79: Feb | CR79: Mar | CS79: Abr | CT79: May | CU79: Jun | CV79: Jul | CW79: Ago | CX79: Sep | CY79: Oct | CZ79: Nov | DA79: Dic | DB79: Total 2021 | DC79: Ene | DD79: Feb | DE79: Mar | DF79: Abr | DG79: May | DH79: Jun | DI79: Jul | DJ79: Ago | DK79: Sep | DL79: Oct | DM79: Nov | DN79: Dic | DO79: Total 2022 | DP79: Ene | DQ79: Feb | DR79: Mar | DS79: Abr | DT79: May | DU79: Jun | DV79: Jul | DW79: Ago | DX79: Sep | DY79: Oct | DZ79: Nov | EA79: Dic | EB79: Total 2023 | EC79: Ene | ED79: Feb | EE79: Mar | EF79: Abr | EG79: May | EH79: Jun | EI79: Jul | EJ79: Ago | EK79: Sep | EL79: Oct | EM79: Nov | EN79: Dic | EO79: Total 2024 | EP79: Ene | EQ79: Feb | ER79: Mar | ES79: Abr | ET79: May | EU79: Jun | EV79: Jul | EW79: Ago | EX79: Sep | EY79: Oct | EZ79: Nov | FA79: Dic | FB79: Total 2025 | FC79: Ene | FD79: Feb | FE79: Mar | FF79: Abr | FG79: May | FH79: Jun | FI79: Jul | FJ79: Ago | FK79: Sep | FL79: Oct | FM79: Nov | FN79: Dic | FO79: Total 2026
B80: Instituto de Salud Pública | C80: 0 | D80: 0 | E80: 0 | F80: 0 | G80: 0 | H80: 0 | I80: 0 | J80: 0 | K80: 0 | L80: 0 | M80: 0 | N80: 18274 | O80: =N80 -> 18274 | P80: 0 | Q80: 0 | R80: 9137 | S80: 9137 | T80: 13706 | U80: 13706 | V80: 61676 | W80: 61676 | X80: 61676 | Y80: 61676 | Z80: 61676 | AA80: 126440 | AB80: =AA80 -> 126440 | AC80: 0 | AD80: 0 | AE80: 0 | AF80: 0 | AG80: 0 | AH80: 0 | AI80: 0 | AJ80: 0 | AK80: 0 | AL80: 0 | AM80: 10600 | AN80: 72643 | AO80: =AN80 -> 72643 | AP80: 12860 | AQ80: 15183 | AR80: 15733 | AS80: 29155 | AT80: 47966 | AU80: 71070 | AV80: 108892 | AW80: 137892 | AX80: 156703 | AY80: 186175 | AZ80: 214308 | BA80: 234908 | BB80: =BA80 -> 234908 | BC80: 0 | BD80: 0 | BE80: 0 | BF80: 0 | BG80: 0 | BH80: 0 | BI80: 0 | BJ80: 0 | BK80: 0 | BL80: 0 | BM80: 0 | BN80: 0 | BO80: =BN80 -> 0 | BP80: 0 | BQ80: 0 | BR80: 0 | BS80: 0 | BT80: 0 | BU80: 0 | BV80: 0 | BW80: 0 | BX80: 0 | BY80: 0 | BZ80: 0 | CA80: 0 | CB80: =CA80 -> 0 | CC80: 0 | CD80: 0 | CE80: 0 | CF80: 0 | CG80: 0 | CH80: 0 | CI80: 0 | CJ80: 0 | CK80: 0 | CL80: 0 | CM80: 0 | CN80: 0 | CO80: =CN80 -> 0 | CP80: 0 | CQ80: 0 | CR80: 0 | CS80: 0 | CT80: 0 | CU80: 0 | CV80: 0 | CW80: 0 | CX80: 0 | CY80: 0 | CZ80: 0 | DA80: 2970 | DB80: =DA80 -> 2970 | DC80: 2970 | DD80: 6930 | DE80: 6930 | DF80: 6930 | DG80: 6930 | DH80: 6930 | DI80: 6930 | DJ80: 6930 | DK80: 6930 | DL80: 6930 | DM80: 6930 | DN80: 198608 | DO80: =DN80 -> 198608 | DP80: 0 | DQ80: 0 | DR80: 0 | DS80: 0 | DT80: 0 | DU80: 41512 | DV80: 41512 | DW80: 41512 | DX80: 41512 | DY80: 41512 | DZ80: 201244 | EA80: 319464 | EB80: =EA80 -> 319464 | EC80: 23577 | ED80: 23577 | EE80: 23577 | EF80: 23577 | EG80: 23577 | EH80: 23577 | EI80: 23577 | EJ80: 183309 | EK80: 183309 | EL80: 183309 | EM80: 231807 | EN80: 655474 | EO80: =EN80 -> 655474 | EP80: 0 | EQ80: 138356 | ER80: 460131 | ES80: 460131 | ET80: 496450 | EU80: 496450 | EV80: 496450 | EW80: 707580 | EX80: 707580 | EY80: 707580 | EZ80: 707580 | FA80: 707580 | FB80: =FA80 -> 707580 | FC80: 0 | FD80: 0 | FE80: 0 | FF80: 0 | FG80: 0 | FH80: 0 | FI80: 0 | FO80: =FI80 -> 0
B81: Subsecretaría de Salud Pública | C81: 0 | D81: 0 | E81: 250248 | F81: 338777 | G81: 439496 | H81: 439496 | I81: 514529 | J81: 621936 | K81: 633794 | L81: 636503 | M81: 799873 | N81: 811954 | O81: =N81 -> 811954 | P81: 0 | Q81: 0 | R81: 0 | S81: 5921 | T81: 5921 | U81: 109570 | V81: 242651 | W81: 313266 | X81: 434350 | Y81: 422320 | Z81: 484177 | AA81: 1071651 | AB81: =AA81 -> 1071651 | AC81: 0 | AD81: 8328 | AE81: 21653 | AF81: 29317 | AG81: 255075 | AH81: 289979 | AI81: 383152 | AJ81: 693407 | AK81: 706331 | AL81: 998191 | AM81: 1008191 | AN81: 1143519 | AO81: =AN81 -> 1143519 | AP81: 0 | AQ81: 0 | AR81: 0 | AS81: 78 | AT81: 1164979 | AU81: 1180015 | AV81: 1272041 | AW81: 1549472 | AX81: 1817385 | AY81: 2077433 | AZ81: 2637716 | BA81: 2997453 | BB81: =BA81 -> 2997453 | BC81: 0 | BD81: 0 | BE81: 646462 | BF81: 651073 | BG81: 676358 | BH81: 683039 | BI81: 691021 | BJ81: 707176 | BK81: 973753 | BL81: 1161262 | BM81: 1167652 | BN81: 1693597 | BO81: =BN81 -> 1693597 | BP81: 0 | BQ81: 0 | BR81: 0 | BS81: 0 | BT81: 350605 | BU81: 358916 | BV81: 367958 | BW81: 515473 | BX81: 522875 | BY81: 522875 | BZ81: 522912 | CA81: 744822 | CB81: =CA81 -> 744822 | CC81: 0 | CD81: 0 | CE81: 18026 | CF81: 25897 | CG81: 31532 | CH81: 39452 | CI81: 593047 | CJ81: 686256 | CK81: 692942 | CL81: 700181 | CM81: 864838 | CN81: 1132282 | CO81: =CN81 -> 1132282 | CP81: 0 | CQ81: 92988 | CR81: 97642 | CS81: 103528 | CT81: 148337 | CU81: 303232 | CV81: 630041 | CW81: 965549 | CX81: 975935 | CY81: 984603 | CZ81: 1575334 | DA81: 1944971 | DB81: =DA81 -> 1944971 | DC81: 0 | DD81: 0 | DE81: 16627 | DF81: 322685 | DG81: 341136 | DH81: 688597 | DI81: 815528 | DJ81: 934499 | DK81: 1014976 | DL81: 1083133 | DM81: 1162517 | DN81: 1499447 | DO81: =DN81 -> 1499447 | DP81: 0 | DQ81: 118763 | DR81: 350112 | DS81: 456403 | DT81: 601738 | DU81: 880069 | DV81: 1190080 | DW81: 1835946 | DX81: 2131892 | DY81: 2306275 | DZ81: 2515365 | EA81: 2759829 | EB81: =EA81 -> 2759829 | EC81: 0 | ED81: 0 | EE81: 585262 | EF81: 868990 | EG81: 1267229 | EH81: 1608938 | EI81: 1938517 | EJ81: 1954642 | EK81: 2643471 | EL81: 3127961 | EM81: 3145389 | EN81: 3622691 | EO81: =EN81 -> 3622691 | EP81: 0 | EQ81: 0 | ER81: 385605 | ES81: 685990 | ET81: 839926 | EU81: 990638 | EV81: 1017931 | EW81: 1178621 | EX81: 1268857 | EY81: 1419361 | EZ81: 1444308 | FA81: 1463647 | FB81: =FA81 -> 1463647 | FC81: 0 | FD81: 19530 | FE81: 38500 | FF81: 49260 | FG81: 58615 | FH81: 83045 | FI81: 776488 | FO81: =FI81 -> 776488
B82: Inversión Sectorial en Salud | C82: 0 | D82: 0 | E82: 0 | F82: 0 | G82: 0 | H82: 0 | I82: 0 | J82: 0 | K82: 0 | L82: 0 | M82: 0 | N82: 0 | O82: =N82 -> 0 | P82: 0 | Q82: 0 | R82: 0 | S82: 0 | T82: 0 | U82: 0 | V82: 0 | W82: 0 | X82: 0 | Y82: 0 | Z82: 0 | AA82: 0 | AB82: =AA82 -> 0 | AC82: 0 | AD82: 0 | AE82: 0 | AF82: 0 | AG82: 0 | AH82: 0 | AI82: 0 | AJ82: 0 | AK82: 0 | AL82: 0 | AM82: 0 | AN82: 0 | AO82: =AN82 -> 0 | AP82: 0 | AQ82: 0 | AR82: 0 | AS82: 0 | AT82: 0 | AU82: 0 | AV82: 0 | AW82: 0 | AX82: 0 | AY82: 0 | AZ82: 0 | BA82: 3215569 | BB82: =BA82 -> 3215569 | BC82: 0 | BD82: 0 | BE82: 0 | BF82: 0 | BG82: 0 | BH82: 0 | BI82: 0 | BJ82: 0 | BK82: 0 | BL82: 0 | BM82: 0 | BN82: 0 | BO82: =BN82 -> 0 | BP82: 0 | BQ82: 0 | BR82: 0 | BS82: 0 | BT82: 0 | BU82: 0 | BV82: 0 | BW82: 0 | BX82: 0 | BY82: 0 | BZ82: 0 | CA82: 0 | CB82: =CA82 -> 0 | CC82: 0 | CD82: 0 | CE82: 0 | CF82: 0 | CG82: 0 | CH82: 0 | CI82: 0 | CJ82: 0 | CK82: 0 | CL82: 0 | CM82: 0 | CN82: 0 | CO82: =CN82 -> 0 | CP82: 0 | CQ82: 0 | CR82: 0 | CS82: 0 | CT82: 0 | CU82: 0 | CV82: 0 | CW82: 0 | CX82: 0 | CY82: 0 | CZ82: 0 | DA82: 0 | DB82: =DA82 -> 0 | DC82: 0 | DD82: 0 | DE82: 0 | DF82: 0 | DG82: 0 | DH82: 0 | DI82: 0 | DJ82: 0 | DK82: 0 | DL82: 0 | DM82: 0 | DN82: 0 | DO82: =DN82 -> 0 | DP82: 0 | DQ82: 0 | DR82: 0 | DS82: 0 | DT82: 0 | DU82: 0 | DV82: 0 | DW82: 0 | DX82: 0 | DY82: 0 | DZ82: 0 | EA82: 0 | EB82: =EA82 -> 0 | EC82: 0 | ED82: 0 | EE82: 0 | EF82: 0 | EG82: 0 | EH82: 0 | EI82: 0 | EJ82: 0 | EK82: 0 | EL82: 0 | EM82: 0 | EN82: 0 | EO82: =EN82 -> 0 | EP82: 0 | EQ82: 0 | ER82: 0 | ES82: 0 | ET82: 0 | EU82: 0 | EV82: 0 | EW82: 0 | EX82: 0 | EY82: 0 | EZ82: 0 | FA82: 0 | FB82: =FA82 -> 0 | FC82: 0 | FD82: 0 | FE82: 0 | FF82: 0 | FG82: 0 | FH82: 0 | FI82: 0 | FO82: =FI82 -> 0
B83: Servicio de Salud Arica y Parinacota | C83: 0 | D83: 29225 | E83: 69058 | F83: 74058 | G83: 129130 | H83: 129130 | I83: 129130 | J83: 129130 | K83: 129130 | L83: 129130 | M83: 146741 | N83: 158192 | O83: =N83 -> 158192 | P83: 0 | Q83: 0 | R83: 0 | S83: 0 | T83: 0 | U83: 0 | V83: 0 | W83: 0 | X83: 12000 | Y83: 12012 | Z83: 27167 | AA83: 63295 | AB83: =AA83 -> 63295 | AC83: 0 | AD83: 0 | AE83: 31419 | AF83: 55162 | AG83: 72894 | AH83: 151247 | AI83: 202026 | AJ83: 298520 | AK83: 337383 | AL83: 355093 | AM83: 363139 | AN83: 470207 | AO83: =AN83 -> 470207 | AP83: 2400 | AQ83: 4800 | AR83: 7200 | AS83: 11200 | AT83: 13600 | AU83: 16000 | AV83: 18400 | AW83: 68369 | AX83: 135750 | AY83: 239172 | AZ83: 296689 | BA83: 530169 | BB83: =BA83 -> 530169 | BC83: 0 | BD83: 0 | BE83: 0 | BF83: 277471 | BG83: 286638 | BH83: 301198 | BI83: 302376 | BJ83: 306496 | BK83: 439336 | BL83: 462932 | BM83: 533800 | BN83: 725074 | BO83: =BN83 -> 725074 | BP83: 0 | BQ83: 0 | BR83: 0 | BS83: 0 | BT83: 97410 | BU83: 126176 | BV83: 197629 | BW83: 326695 | BX83: 326695 | BY83: 380257 | BZ83: 380257 | CA83: 404792 | CB83: =CA83 -> 404792 | CC83: 0 | CD83: 0 | CE83: 88711 | CF83: 106962 | CG83: 106962 | CH83: 153139 | CI83: 236335 | CJ83: 304100 | CK83: 400970 | CL83: 448202 | CM83: 538989 | CN83: 831265 | CO83: =CN83 -> 831265 | CP83: 0 | CQ83: 0 | CR83: 0 | CS83: 0 | CT83: 0 | CU83: 0 | CV83: 0 | CW83: 0 | CX83: 0 | CY83: 0 | CZ83: 89082 | DA83: 150919 | DB83: =DA83 -> 150919 | DC83: 0 | DD83: 0 | DE83: 154450 | DF83: 154450 | DG83: 154450 | DH83: 260662 | DI83: 260662 | DJ83: 260662 | DK83: 260662 | DL83: 260662 | DM83: 260662 | DN83: 277067 | DO83: =DN83 -> 277067 | DP83: 0 | DQ83: 0 | DR83: 0 | DS83: 0 | DT83: 0 | DU83: 0 | DV83: 0 | DW83: 0 | DX83: 0 | DY83: 0 | DZ83: 0 | EA83: 0 | EB83: =EA83 -> 0 | EC83: 0 | ED83: 0 | EE83: 0 | EF83: 0 | EG83: 0 | EH83: 0 | EI83: 0 | EJ83: 0 | EK83: 0 | EL83: 0 | EM83: 6129 | EN83: 31725 | EO83: =EN83 -> 31725 | EP83: 0 | EQ83: 0 | ER83: 6500 | ES83: 6500 | ET83: 6500 | EU83: 6500 | EV83: 6500 | EW83: 6500 | EX83: 6500 | EY83: 6500 | EZ83: 6500 | FA83: 6500 | FB83: =FA83 -> 6500 | FC83: 0 | FD83: 0 | FE83: 0 | FF83: 0 | FG83: 0 | FH83: 0 | FI83: 0 | FO83: =FI83 -> 0
B84: Servicio de Salud Tarapacá | C84: 0 | D84: 0 | E84: 99950 | F84: 187664 | G84: 549294 | H84: 948248 | I84: 1210671 | J84: 1601023 | K84: 1939391 | L84: 2040169 | M84: 2466757 | N84: 4218165 | O84: =N84 -> 4218165 | P84: 0 | Q84: 7756 | R84: 307278 | S84: 464100 | T84: 688185 | U84: 930271 | V84: 1190533 | W84: 1461267 | X84: 1710817 | Y84: 2039694 | Z84: 2779508 | AA84: 4432291 | AB84: =AA84 -> 4432291 | AC84: 0 | AD84: 9824 | AE84: 186132 | AF84: 520530 | AG84: 730517 | AH84: 1669661 | AI84: 2107498 | AJ84: 2629343 | AK84: 3537971 | AL84: 3902063 | AM84: 4604540 | AN84: 4966426 | AO84: =AN84 -> 4966426 | AP84: 0 | AQ84: 399741 | AR84: 1209250 | AS84: 1835534 | AT84: 2434431 | AU84: 3363544 | AV84: 4014404 | AW84: 4701477 | AX84: 5680050 | AY84: 6787579 | AZ84: 7711168 | BA84: 9984754 | BB84: =BA84 -> 9984754 | BC84: 0 | BD84: 0 | BE84: 82527 | BF84: 381213 | BG84: 416251 | BH84: 525709 | BI84: 866549 | BJ84: 1251935 | BK84: 1625846 | BL84: 1770104 | BM84: 1797103 | BN84: 2166368 | BO84: =BN84 -> 2166368 | BP84: 0 | BQ84: 121037 | BR84: 333748 | BS84: 467959 | BT84: 534698 | BU84: 649068 | BV84: 748721 | BW84: 10927123 | BX84: 11010600 | BY84: 11276770 | BZ84: 11687879 | CA84: 22878198 | CB84: =CA84 -> 22878198 | CC84: 0 | CD84: 0 | CE84: 596855 | CF84: 8947203 | CG84: 13625416 | CH84: 13741815 | CI84: 13752867 | CJ84: 13830018 | CK84: 26845839 | CL84: 26941067 | CM84: 27243897 | CN84: 38695681 | CO84: =CN84 -> 38695681 | CP84: 0 | CQ84: 0 | CR84: 346612 | CS84: 694724 | CT84: 761389 | CU84: 12664052 | CV84: 19315642 | CW84: 20195380 | CX84: 25452421 | CY84: 25564233 | CZ84: 26717509 | DA84: 28687564 | DB84: =DA84 -> 28687564 | DC84: 0 | DD84: 0 | DE84: 67741 | DF84: 279671 | DG84: 665386 | DH84: 1619698 | DI84: 2468195 | DJ84: 3037558 | DK84: 4678404 | DL84: 4908377 | DM84: 5274507 | DN84: 7447366 | DO84: =DN84 -> 7447366 | DP84: 0 | DQ84: 413783 | DR84: 8309697 | DS84: 9654934 | DT84: 11034686 | DU84: 11420529 | DV84: 12320473 | DW84: 12767924 | DX84: 13281680 | DY84: 14193730 | DZ84: 15232153 | EA84: 17549584 | EB84: =EA84 -> 17549584 | EC84: 0 | ED84: 0 | EE84: 1248489 | EF84: 1386002 | EG84: 2365414 | EH84: 3481044 | EI84: 4062198 | EJ84: 4757993 | EK84: 5225037 | EL84: 5920373 | EM84: 6606171 | EN84: 10095390 | EO84: =EN84 -> 10095390 | EP84: 0 | EQ84: 0 | ER84: 0 | ES84: 3779031 | ET84: 5550793 | EU84: 7430022 | EV84: 9527495 | EW84: 11199392 | EX84: 14053482 | EY84: 15593114 | EZ84: 15833450 | FA84: 23391269 | FB84: =FA84 -> 23391269 | FC84: 0 | FD84: 0 | FE84: 0 | FF84: 5400368 | FG84: 6193550 | FH84: 7262433 | FI84: 8340232 | FO84: =FI84 -> 8340232
B85: Servicio de Salud Antofagasta | C85: 0 | D85: 19767 | E85: 26804 | F85: 32987 | G85: 70136 | H85: 343930 | I85: 357594 | J85: 708363 | K85: 900458 | L85: 1366890 | M85: 1728162 | N85: 2353508 | O85: =N85 -> 2353508 | P85: 0 | Q85: 117483 | R85: 285039 | S85: 560804 | T85: 706288 | U85: 777717 | V85: 850893 | W85: 936069 | X85: 1046644 | Y85: 1212614 | Z85: 1420437 | AA85: 18184473 | AB85: =AA85 -> 18184473 | AC85: 0 | AD85: 116466 | AE85: 116466 | AF85: 859999 | AG85: 1196764 | AH85: 1885301 | AI85: 2702612 | AJ85: 4033254 | AK85: 5513730 | AL85: 7636136 | AM85: 10250450 | AN85: 17427367 | AO85: =AN85 -> 17427367 | AP85: 0 | AQ85: 0 | AR85: 94790 | AS85: 577738 | AT85: 698925 | AU85: 8291578 | AV85: 10022337 | AW85: 12291666 | AX85: 16047063 | AY85: 19238034 | AZ85: 22813423 | BA85: 35848416 | BB85: =BA85 -> 35848416 | BC85: 0 | BD85: 0 | BE85: 0 | BF85: 2139684 | BG85: 3452122 | BH85: 5647064 | BI85: 6572783 | BJ85: 6920711 | BK85: 6942180 | BL85: 8168811 | BM85: 8669944 | BN85: 12422988 | BO85: =BN85 -> 12422988 | BP85: 0 | BQ85: 778 | BR85: 591404 | BS85: 609676 | BT85: 622074 | BU85: 664297 | BV85: 667621 | BW85: 901924 | BX85: 1310713 | BY85: 2965430 | BZ85: 3681088 | CA85: 6702376 | CB85: =CA85 -> 6702376 | CC85: 0 | CD85: 0 | CE85: 0 | CF85: 0 | CG85: 0 | CH85: 0 | CI85: 0 | CJ85: 1761 | CK85: 1761 | CL85: 1761 | CM85: 1761 | CN85: 945018 | CO85: =CN85 -> 945018 | CP85: 0 | CQ85: 0 | CR85: 0 | CS85: 216486 | CT85: 216486 | CU85: 218394 | CV85: 274246 | CW85: 274246 | CX85: 277559 | CY85: 277559 | CZ85: 277559 | DA85: 689027 | DB85: =DA85 -> 689027 | DC85: 0 | DD85: 0 | DE85: 0 | DF85: 0 | DG85: 0 | DH85: 0 | DI85: 0 | DJ85: 0 | DK85: 0 | DL85: 0 | DM85: 0 | DN85: 6489 | DO85: =DN85 -> 6489 | DP85: 0 | DQ85: 0 | DR85: 17172 | DS85: 17172 | DT85: 17172 | DU85: 30636 | DV85: 30636 | DW85: 30636 | DX85: 30636 | DY85: 30636 | DZ85: 30636 | EA85: 100920 | EB85: =EA85 -> 100920 | EC85: 0 | ED85: 0 | EE85: 0 | EF85: 0 | EG85: 24040 | EH85: 63893 | EI85: 63893 | EJ85: 63893 | EK85: 151543 | EL85: 151543 | EM85: 199293 | EN85: 345022 | EO85: =EN85 -> 345022 | EP85: 0 | EQ85: 0 | ER85: 184525 | ES85: 184525 | ET85: 184525 | EU85: 184525 | EV85: 191260 | EW85: 191260 | EX85: 218077 | EY85: 218457 | EZ85: 218457 | FA85: 322185 | FB85: =FA85 -> 322185 | FC85: 0 | FD85: 0 | FE85: 0 | FF85: 0 | FG85: 0 | FH85: 0 | FI85: 0 | FO85: =FI85 -> 0
B86: Servicio de Salud Atacama | C86: 0 | D86: 175159 | E86: 340792 | F86: 460714 | G86: 530539 | H86: 620689 | I86: 922992 | J86: 1310019 | K86: 1825900 | L86: 2332943 | M86: 3211073 | N86: 4187386 | O86: =N86 -> 4187386 | P86: 0 | Q86: 557108 | R86: 1515287 | S86: 2358467 | T86: 2521407 | U86: 3094173 | V86: 3253020 | W86: 4023312 | X86: 4716798 | Y86: 5317540 | Z86: 5617593 | AA86: 7134317 | AB86: =AA86 -> 7134317 | AC86: 0 | AD86: 0 | AE86: 0 | AF86: 1012198 | AG86: 1495876 | AH86: 1940459 | AI86: 2453379 | AJ86: 3144405 | AK86: 3313946 | AL86: 3645733 | AM86: 4904241 | AN86: 6428492 | AO86: =AN86 -> 6428492 | AP86: 0 | AQ86: 0 | AR86: 0 | AS86: 0 | AT86: 0 | AU86: 0 | AV86: 0 | AW86: 14113 | AX86: 22284 | AY86: 22284 | AZ86: 22284 | BA86: 22284 | BB86: =BA86 -> 22284 | BC86: 0 | BD86: 0 | BE86: 0 | BF86: 0 | BG86: 0 | BH86: 139258 | BI86: 139258 | BJ86: 139258 | BK86: 139666 | BL86: 140752 | BM86: 149772 | BN86: 173759 | BO86: =BN86 -> 173759 | BP86: 0 | BQ86: 0 | BR86: 33222 | BS86: 33222 | BT86: 45535 | BU86: 45646 | BV86: 63260 | BW86: 64165 | BX86: 64189 | BY86: 86150 | BZ86: 121270 | CA86: 197214 | CB86: =CA86 -> 197214 | CC86: 0 | CD86: 127587 | CE86: 390907 | CF86: 706557 | CG86: 936910 | CH86: 1186243 | CI86: 1638194 | CJ86: 2130337 | CK86: 2516834 | CL86: 2838664 | CM86: 3568116 | CN86: 5005029 | CO86: =CN86 -> 5005029 | CP86: 266285 | CQ86: 666372 | CR86: 1038189 | CS86: 1229700 | CT86: 1363827 | CU86: 1614604 | CV86: 1663102 | CW86: 1946994 | CX86: 2245219 | CY86: 2457551 | CZ86: 2680152 | DA86: 3424169 | DB86: =DA86 -> 3424169 | DC86: 0 | DD86: 0 | DE86: 0 | DF86: 0 | DG86: 0 | DH86: 0 | DI86: 0 | DJ86: 0 | DK86: 0 | DL86: 0 | DM86: 0 | DN86: 452203 | DO86: =DN86 -> 452203 | DP86: 0 | DQ86: 0 | DR86: 0 | DS86: 0 | DT86: 0 | DU86: 3450 | DV86: 63675 | DW86: 321098 | DX86: 601250 | DY86: 901929 | DZ86: 1345302 | EA86: 1884959 | EB86: =EA86 -> 1884959 | EC86: 0 | ED86: 63671 | EE86: 736483 | EF86: 1112355 | EG86: 1788852 | EH86: 2726594 | EI86: 3367865 | EJ86: 4162139 | EK86: 5201129 | EL86: 6295100 | EM86: 7710017 | EN86: 8835329 | EO86: =EN86 -> 8835329 | EP86: 0 | EQ86: 2473211 | ER86: 5063264 | ES86: 7443310 | ET86: 9019759 | EU86: 11034973 | EV86: 12839745 | EW86: 13807011 | EX86: 16429292 | EY86: 18472114 | EZ86: 20464638 | FA86: 23883565 | FB86: =FA86 -> 23883565 | FC86: 1405629 | FD86: 2781911 | FE86: 4021748 | FF86: 4968047 | FG86: 6444038 | FH86: 8044713 | FI86: 10105068 | FO86: =FI86 -> 10105068
B87: Servicio de Salud Coquimbo | C87: 0 | D87: 0 | E87: 709815 | F87: 1201622 | G87: 1223234 | H87: 1226066 | I87: 1252833 | J87: 1261618 | K87: 1299992 | L87: 1301873 | M87: 1301873 | N87: 1331602 | O87: =N87 -> 1331602 | P87: 0 | Q87: 0 | R87: 16923 | S87: 68629 | T87: 113531 | U87: 129023 | V87: 349769 | W87: 604892 | X87: 815068 | Y87: 991552 | Z87: 12826386 | AA87: 20995283 | AB87: =AA87 -> 20995283 | AC87: 0 | AD87: 595073 | AE87: 1035725 | AF87: 2673180 | AG87: 4363190 | AH87: 6039102 | AI87: 7430112 | AJ87: 10519955 | AK87: 12339690 | AL87: 16199764 | AM87: 22126510 | AN87: 31375463 | AO87: =AN87 -> 31375463 | AP87: 0 | AQ87: 67665 | AR87: 3780190 | AS87: 6171167 | AT87: 8411908 | AU87: 11959728 | AV87: 15944164 | AW87: 19098351 | AX87: 21504776 | AY87: 24535341 | AZ87: 25032532 | BA87: 38370880 | BB87: =BA87 -> 38370880 | BC87: 0 | BD87: 0 | BE87: 0 | BF87: 5882150 | BG87: 8872787 | BH87: 10995606 | BI87: 13291093 | BJ87: 17845311 | BK87: 19821342 | BL87: 21937465 | BM87: 27807719 | BN87: 33990091 | BO87: =BN87 -> 33990091 | BP87: 0 | BQ87: 0 | BR87: 1578574 | BS87: 2506221 | BT87: 8144474 | BU87: 12260837 | BV87: 18315296 | BW87: 20734146 | BX87: 22820894 | BY87: 25853739 | BZ87: 29896087 | CA87: 41375734 | CB87: =CA87 -> 41375734 | CC87: 0 | CD87: 546271 | CE87: 4938870 | CF87: 8539075 | CG87: 11795273 | CH87: 13877436 | CI87: 15990091 | CJ87: 16085620 | CK87: 19850900 | CL87: 20461467 | CM87: 23579729 | CN87: 32688999 | CO87: =CN87 -> 32688999 | CP87: 0 | CQ87: 1651658 | CR87: 4628110 | CS87: 5916555 | CT87: 7145361 | CU87: 8348930 | CV87: 9526754 | CW87: 10078045 | CX87: 10141998 | CY87: 11664560 | CZ87: 13017982 | DA87: 18587899 | DB87: =DA87 -> 18587899 | DC87: 0 | DD87: 0 | DE87: 12621 | DF87: 253739 | DG87: 253739 | DH87: 384163 | DI87: 704337 | DJ87: 731651 | DK87: 1832814 | DL87: 2095775 | DM87: 3235840 | DN87: 5482528 | DO87: =DN87 -> 5482528 | DP87: 0 | DQ87: 0 | DR87: 0 | DS87: 0 | DT87: 0 | DU87: 113226 | DV87: 203356 | DW87: 579853 | DX87: 579963 | DY87: 730817 | DZ87: 1613286 | EA87: 2215508 | EB87: =EA87 -> 2215508 | EC87: 0 | ED87: 0 | EE87: 181703 | EF87: 457499 | EG87: 580001 | EH87: 685584 | EI87: 1082622 | EJ87: 1201998 | EK87: 1313986 | EL87: 1445885 | EM87: 1510510 | EN87: 4265327 | EO87: =EN87 -> 4265327 | EP87: 0 | EQ87: 0 | ER87: 732208 | ES87: 767674 | ET87: 1224165 | EU87: 2555008 | EV87: 3699754 | EW87: 5572712 | EX87: 8721988 | EY87: 8834841 | EZ87: 12002178 | FA87: 22939144 | FB87: =FA87 -> 22939144 | FC87: 0 | FD87: 0 | FE87: 2638785 | FF87: 4892743 | FG87: 5759141 | FH87: 8450936 | FI87: 11836020 | FO87: =FI87 -> 11836020
B88: Servicio de Salud Valparaíso - San Antonio | C88: 0 | D88: 0 | E88: 201301 | F88: 286784 | G88: 599966 | H88: 745481 | I88: 875059 | J88: 886426 | K88: 895599 | L88: 1168234 | M88: 1269163 | N88: 1854183 | O88: =N88 -> 1854183 | P88: 0 | Q88: 0 | R88: 50171 | S88: 417017 | T88: 685329 | U88: 948725 | V88: 1089617 | W88: 1509585 | X88: 2240081 | Y88: 2337719 | Z88: 3713898 | AA88: 7035843 | AB88: =AA88 -> 7035843 | AC88: 0 | AD88: 0 | AE88: 0 | AF88: 693824 | AG88: 736718 | AH88: 1558666 | AI88: 2397935 | AJ88: 3430441 | AK88: 4061710 | AL88: 4272097 | AM88: 4990976 | AN88: 6163730 | AO88: =AN88 -> 6163730 | AP88: 0 | AQ88: 0 | AR88: 0 | AS88: 148911 | AT88: 390409 | AU88: 567676 | AV88: 620857 | AW88: 858248 | AX88: 971593 | AY88: 1237553 | AZ88: 1547143 | BA88: 2311055 | BB88: =BA88 -> 2311055 | BC88: 0 | BD88: 0 | BE88: 0 | BF88: 0 | BG88: 2455961 | BH88: 3205359 | BI88: 4054793 | BJ88: 5415039 | BK88: 5475804 | BL88: 5576380 | BM88: 5745363 | BN88: 15756415 | BO88: =BN88 -> 15756415 | BP88: 0 | BQ88: 0 | BR88: 1201570 | BS88: 3951275 | BT88: 7417232 | BU88: 8766561 | BV88: 9957407 | BW88: 10156955 | BX88: 10581499 | BY88: 12764907 | BZ88: 14398285 | CA88: 22884915 | CB88: =CA88 -> 22884915 | CC88: 0 | CD88: 0 | CE88: 1471666 | CF88: 4745395 | CG88: 6704317 | CH88: 11065140 | CI88: 11419367 | CJ88: 12666444 | CK88: 18140163 | CL88: 18930122 | CM88: 24469095 | CN88: 35649692 | CO88: =CN88 -> 35649692 | CP88: 0 | CQ88: 0 | CR88: 6150231 | CS88: 8905149 | CT88: 9533316 | CU88: 15784006 | CV88: 18197346 | CW88: 20402332 | CX88: 23085283 | CY88: 25192870 | CZ88: 25295817 | DA88: 38081001 | DB88: =DA88 -> 38081001 | DC88: 0 | DD88: 52025 | DE88: 2690821 | DF88: 4373949 | DG88: 5498005 | DH88: 6803459 | DI88: 8300642 | DJ88: 8733222 | DK88: 10485025 | DL88: 12848276 | DM88: 15355940 | DN88: 19878895 | DO88: =DN88 -> 19878895 | DP88: 0 | DQ88: 0 | DR88: 354009 | DS88: 948502 | DT88: 1307100 | DU88: 1708778 | DV88: 3102537 | DW88: 5238372 | DX88: 6906449 | DY88: 8763981 | DZ88: 11443221 | EA88: 15331951 | EB88: =EA88 -> 15331951 | EC88: 0 | ED88: 3793 | EE88: 1889723 | EF88: 3618662 | EG88: 5124294 | EH88: 8743996 | EI88: 10065404 | EJ88: 11559141 | EK88: 12119750 | EL88: 12635531 | EM88: 14378325 | EN88: 15745622 | EO88: =EN88 -> 15745622 | EP88: 0 | EQ88: 0 | ER88: 363126 | ES88: 1223295 | ET88: 1557034 | EU88: 1676025 | EV88: 2190991 | EW88: 2566584 | EX88: 10544554 | EY88: 10881112 | EZ88: 11518430 | FA88: 12702103 | FB88: =FA88 -> 12702103 | FC88: 0 | FD88: 0 | FE88: 207423 | FF88: 903843 | FG88: 1043342 | FH88: 1537759 | FI88: 1940057 | FO88: =FI88 -> 1940057
B89: Servicio de Salud Viña del Mar - Quillota | C89: 0 | D89: 1076991 | E89: 1742888 | F89: 2440558 | G89: 3418882 | H89: 4307629 | I89: 5293250 | J89: 6346878 | K89: 7599403 | L89: 8690189 | M89: 9884649 | N89: 13799293 | O89: =N89 -> 13799293 | P89: 0 | Q89: 0 | R89: 1109556 | S89: 1534184 | T89: 2323691 | U89: 3383329 | V89: 4511976 | W89: 5489824 | X89: 7089714 | Y89: 8241408 | Z89: 9530613 | AA89: 13142928 | AB89: =AA89 -> 13142928 | AC89: 0 | AD89: 0 | AE89: 851850 | AF89: 3499780 | AG89: 5071535 | AH89: 7026196 | AI89: 11038855 | AJ89: 12298861 | AK89: 13376802 | AL89: 15552350 | AM89: 18155976 | AN89: 29865010 | AO89: =AN89 -> 29865010 | AP89: 0 | AQ89: 983332 | AR89: 2072475 | AS89: 3179440 | AT89: 5053200 | AU89: 6006908 | AV89: 11251268 | AW89: 14105926 | AX89: 15931261 | AY89: 18795254 | AZ89: 19176294 | BA89: 31121067 | BB89: =BA89 -> 31121067 | BC89: 0 | BD89: 0 | BE89: 0 | BF89: 14585750 | BG89: 17258761 | BH89: 20446188 | BI89: 31500133 | BJ89: 34578599 | BK89: 36125947 | BL89: 45811346 | BM89: 47791770 | BN89: 56094267 | BO89: =BN89 -> 56094267 | BP89: 0 | BQ89: 0 | BR89: 8998085 | BS89: 11137062 | BT89: 16977785 | BU89: 22730466 | BV89: 29050541 | BW89: 30329045 | BX89: 44069106 | BY89: 46068547 | BZ89: 59423516 | CA89: 77161620 | CB89: =CA89 -> 77161620 | CC89: 0 | CD89: 0 | CE89: 10763723 | CF89: 18838339 | CG89: 19937472 | CH89: 29729335 | CI89: 31375887 | CJ89: 41925526 | CK89: 52803715 | CL89: 55155717 | CM89: 60010596 | CN89: 74770612 | CO89: =CN89 -> 74770612 | CP89: 0 | CQ89: 4193300 | CR89: 6289421 | CS89: 10874656 | CT89: 14347851 | CU89: 17934120 | CV89: 23492834 | CW89: 26334481 | CX89: 31209158 | CY89: 36618365 | CZ89: 41515018 | DA89: 51127415 | DB89: =DA89 -> 51127415 | DC89: 0 | DD89: 0 | DE89: 1408391 | DF89: 4279463 | DG89: 6339769 | DH89: 8882130 | DI89: 11065876 | DJ89: 17186576 | DK89: 19399476 | DL89: 21966573 | DM89: 25704385 | DN89: 35431654 | DO89: =DN89 -> 35431654 | DP89: 0 | DQ89: 646877 | DR89: 1910359 | DS89: 8873923 | DT89: 10683792 | DU89: 16111228 | DV89: 20670838 | DW89: 22396585 | DX89: 26630089 | DY89: 27372100 | DZ89: 33133993 | EA89: 41895788 | EB89: =EA89 -> 41895788 | EC89: 0 | ED89: 0 | EE89: 1149160 | EF89: 7639668 | EG89: 11265562 | EH89: 14484146 | EI89: 18016722 | EJ89: 51616947 | EK89: 58856054 | EL89: 63545882 | EM89: 71727558 | EN89: 84834322 | EO89: =EN89 -> 84834322 | EP89: 0 | EQ89: 155103 | ER89: 16727385 | ES89: 23173932 | ET89: 28829845 | EU89: 31035704 | EV89: 35219090 | EW89: 37989279 | EX89: 40229586 | EY89: 42897538 | EZ89: 45488629 | FA89: 51816598 | FB89: =FA89 -> 51816598 | FC89: 0 | FD89: 0 | FE89: 4072814 | FF89: 6426971 | FG89: 7944500 | FH89: 9687821 | FI89: 10600915 | FO89: =FI89 -> 10600915
B90: Servicio de Salud Aconcagua | C90: 0 | D90: 0 | E90: 1367991 | F90: 1859571 | G90: 2200368 | H90: 2629034 | I90: 3212319 | J90: 3780452 | K90: 4280228 | L90: 4716888 | M90: 5238854 | N90: 6857635 | O90: =N90 -> 6857635 | P90: 0 | Q90: 0 | R90: 29721 | S90: 76973 | T90: 97158 | U90: 511740 | V90: 582650 | W90: 616564 | X90: 665659 | Y90: 796527 | Z90: 918305 | AA90: 4174429 | AB90: =AA90 -> 4174429 | AC90: 0 | AD90: 1326 | AE90: 1326 | AF90: 36642 | AG90: 57730 | AH90: 104354 | AI90: 270218 | AJ90: 359390 | AK90: 427504 | AL90: 4015648 | AM90: 4031412 | AN90: 1060743 | AO90: =AN90 -> 1060743 | AP90: 0 | AQ90: 410588 | AR90: 845482 | AS90: 1296153 | AT90: 1800171 | AU90: 2408373 | AV90: 3129292 | AW90: 3885733 | AX90: 4278386 | AY90: 4651432 | AZ90: 4905170 | BA90: 6495636 | BB90: =BA90 -> 6495636 | BC90: 0 | BD90: 0 | BE90: 0 | BF90: 921 | BG90: 163532 | BH90: 915777 | BI90: 2066718 | BJ90: 2603409 | BK90: 3475200 | BL90: 4602553 | BM90: 5398847 | BN90: 5688570 | BO90: =BN90 -> 5688570 | BP90: 0 | BQ90: 804475 | BR90: 1173894 | BS90: 1797719 | BT90: 1807682 | BU90: 1862648 | BV90: 3779232 | BW90: 4404168 | BX90: 5440094 | BY90: 5886291 | BZ90: 6276228 | CA90: 7120607 | CB90: =CA90 -> 7120607 | CC90: 0 | CD90: 0 | CE90: 0 | CF90: 238121 | CG90: 815703 | CH90: 1244882 | CI90: 1342060 | CJ90: 1440547 | CK90: 1542397 | CL90: 3517785 | CM90: 3965900 | CN90: 5496913 | CO90: =CN90 -> 5496913 | CP90: 0 | CQ90: 27517 | CR90: 326619 | CS90: 480756 | CT90: 755464 | CU90: 1358420 | CV90: 1414026 | CW90: 1425434 | CX90: 1568827 | CY90: 1584192 | CZ90: 1848877 | DA90: 5093885 | DB90: =DA90 -> 5093885 | DC90: 0 | DD90: 0 | DE90: 0 | DF90: 1183279 | DG90: 1673754 | DH90: 2070968 | DI90: 2421326 | DJ90: 2969641 | DK90: 3403331 | DL90: 5137005 | DM90: 5785496 | DN90: 9381755 | DO90: =DN90 -> 9381755 | DP90: 0 | DQ90: 7850 | DR90: 537746 | DS90: 977628 | DT90: 1605388 | DU90: 1994221 | DV90: 2232666 | DW90: 2366610 | DX90: 2368581 | DY90: 2417008 | DZ90: 2949534 | EA90: 4484538 | EB90: =EA90 -> 4484538 | EC90: 0 | ED90: 0 | EE90: 76378 | EF90: 77324 | EG90: 85449 | EH90: 160543 | EI90: 222737 | EJ90: 331064 | EK90: 400556 | EL90: 541909 | EM90: 733649 | EN90: 1324722 | EO90: =EN90 -> 1324722 | EP90: 0 | EQ90: 0 | ER90: 689770 | ES90: 1051244 | ET90: 1276682 | EU90: 1496824 | EV90: 1718944 | EW90: 1951104 | EX90: 2230181 | EY90: 2408430 | EZ90: 2588641 | FA90: 2964460 | FB90: =FA90 -> 2964460 | FC90: 0 | FD90: 13541 | FE90: 227257 | FF90: 840801 | FG90: 845195 | FH90: 876974 | FI90: 903120 | FO90: =FI90 -> 903120
B91: Servicio de Salud O'Higgins | C91: 0 | D91: 111299 | E91: 3324466 | F91: 4964998 | G91: 5001726 | H91: 5414546 | I91: 5510623 | J91: 5626167 | K91: 6081225 | L91: 7510852 | M91: 7700538 | N91: 23760031 | O91: =N91 -> 23760031 | P91: 0 | Q91: 0 | R91: 74464 | S91: 100566 | T91: 139491 | U91: 251731 | V91: 790817 | W91: 2267145 | X91: 3203010 | Y91: 4108623 | Z91: 4500774 | AA91: 14253720 | AB91: =AA91 -> 14253720 | AC91: 0 | AD91: 0 | AE91: 428508 | AF91: 916582 | AG91: 1482498 | AH91: 2189530 | AI91: 2958386 | AJ91: 5734850 | AK91: 6759369 | AL91: 7589090 | AM91: 8279370 | AN91: 10743646 | AO91: =AN91 -> 10743646 | AP91: 0 | AQ91: 233074 | AR91: 1889861 | AS91: 3376538 | AT91: 4309398 | AU91: 5887497 | AV91: 7251521 | AW91: 8334063 | AX91: 9117509 | AY91: 9583523 | AZ91: 9869279 | BA91: 12369380 | BB91: =BA91 -> 12369380 | BC91: 0 | BD91: 0 | BE91: 0 | BF91: 992851 | BG91: 1175415 | BH91: 1204031 | BI91: 1230651 | BJ91: 1604955 | BK91: 1657932 | BL91: 1904349 | BM91: 2162426 | BN91: 3894624 | BO91: =BN91 -> 3894624 | BP91: 0 | BQ91: 0 | BR91: 826782 | BS91: 1585737 | BT91: 2308647 | BU91: 3534549 | BV91: 4043033 | BW91: 4586162 | BX91: 6338463 | BY91: 7207271 | BZ91: 7539091 | CA91: 9800434 | CB91: =CA91 -> 9800434 | CC91: 0 | CD91: 0 | CE91: 288346 | CF91: 452786 | CG91: 622159 | CH91: 625352 | CI91: 702294 | CJ91: 853255 | CK91: 916368 | CL91: 1157723 | CM91: 1238701 | CN91: 1497395 | CO91: =CN91 -> 1497395 | CP91: 0 | CQ91: 30294 | CR91: 30294 | CS91: 35694 | CT91: 56037 | CU91: 73966 | CV91: 102699 | CW91: 134150 | CX91: 214200 | CY91: 246490 | CZ91: 279491 | DA91: 308425 | DB91: =DA91 -> 308425 | DC91: 0 | DD91: 0 | DE91: 0 | DF91: 1950 | DG91: 1950 | DH91: 63072 | DI91: 138228 | DJ91: 144031 | DK91: 145981 | DL91: 147931 | DM91: 149881 | DN91: 415560 | DO91: =DN91 -> 415560 | DP91: 0 | DQ91: 0 | DR91: 0 | DS91: 0 | DT91: 82928 | DU91: 513334 | DV91: 513334 | DW91: 925767 | DX91: 1371777 | DY91: 1689708 | DZ91: 2214296 | EA91: 3563937 | EB91: =EA91 -> 3563937 | EC91: 0 | ED91: 897455 | EE91: 897455 | EF91: 1720709 | EG91: 2014796 | EH91: 2014796 | EI91: 2724185 | EJ91: 2724185 | EK91: 4406681 | EL91: 4921244 | EM91: 4925100 | EN91: 5132360 | EO91: =EN91 -> 5132360 | EP91: 0 | EQ91: 0 | ER91: 347212 | ES91: 546793 | ET91: 546793 | EU91: 904938 | EV91: 904938 | EW91: 904938 | EX91: 982169 | EY91: 1153086 | EZ91: 1181536 | FA91: 2055961 | FB91: =FA91 -> 2055961 | FC91: 0 | FD91: 21783 | FE91: 21783 | FF91: 21783 | FG91: 21783 | FH91: 21783 | FI91: 25219 | FO91: =FI91 -> 25219
... B111: Servicio de Salud Chiloé | C111: 0 | D111: 162243 | E111: 177457 | F111: 179505 | G111: 366049 | H111: 381784 | I111: 280527 | J111: 282586 | K111: 282586 | L111: 375551 | M111: 399133 | N111: 621232 | O111: =N111 -> 621232 | P111: 0 | Q111: 0 | R111: 66421 | S111: 77034 | T111: 115315 | U111: 140483 | V111: 209157 | W111: 634100 | X111: 651445 | Y111: 775442 | Z111: 1348111 | AA111: 3373697 | AB111: =AA111 -> 3373697 | AC111: 0 | AD111: 39777 | AE111: 205697 | AF111: 562917 | AG111: 898674 | AH111: 1352348 | AI111: 1698763 | AJ111: 1938777 | AK111: 2097630 | AL111: 2449505 | AM111: 2577163 | AN111: 3165465 | AO111: =AN111 -> 3165465 | AP111: 0 | AQ111: 8208 | AR111: 169808 | AS111: 316964 | AT111: 662240 | AU111: 1108374 | AV111: 1419456 | AW111: 1708982 | AX111: 2127746 | AY111: 2417674 | AZ111: 2617617 | BA111: 3343257 | BB111: =BA111 -> 3343257 | BC111: 0 | BD111: 0 | BE111: 18275 | BF111: 231203 | BG111: 902195 | BH111: 2028202 | BI111: 2479627 | BJ111: 3495726 | BK111: 5148004 | BL111: 6647300 | BM111: 8290770 | BN111: 12738213 | BO111: =BN111 -> 12738213 | BP111: 0 | BQ111: 3001612 | BR111: 4310799 | BS111: 6428282 | BT111: 8766526 | BU111: 12783005 | BV111: 15129562 | BW111: 17888964 | BX111: 21614369 | BY111: 25138824 | BZ111: 28205718 | CA111: 34944671 | CB111: =CA111 -> 34944671 | CC111: 0 | CD111: 5824859 | CE111: 8866834 | CF111: 12123172 | CG111: 12342078 | CH111: 18572666 | CI111: 18684444 | CJ111: 20853826 | CK111: 24590056 | CL111: 26105903 | CM111: 26295002 | CN111: 38790543 | CO111: =CN111 -> 38790543 | CP111: 0 | CQ111: 0 | CR111: 5155090 | CS111: 8198001 | CT111: 9828485 | CU111: 12305451 | CV111: 15838264 | CW111: 17961471 | CX111: 20436199 | CY111: 22008387 | CZ111: 26349775 | DA111: 34916094 | DB111: =DA111 -> 34916094 | DC111: 0 | DD111: 0 | DE111: 41022 | DF111: 5582056 | DG111: 8197314 | DH111: 12077742 | DI111: 17232575 | DJ111: 17296502 | DK111: 20350420 | DL111: 20605980 | DM111: 23236716 | DN111: 29141323 | DO111: =DN111 -> 29141323 | DP111: 0 | DQ111: 0 | DR111: 3138037 | DS111: 4070863 | DT111: 7015142 | DU111: 10474580 | DV111: 12694002 | DW111: 15346764 | DX111: 17789278 | DY111: 18656678 | DZ111: 20583996 | EA111: 27002928 | EB111: =EA111 -> 27002928 | EC111: 0 | ED111: 0 | EE111: 8671968 | EF111: 10129094 | EG111: 13618471 | EH111: 15812861 | EI111: 18963389 | EJ111: 33657743 | EK111: 35270334 | EL111: 36504888 | EM111: 42935974 | EN111: 46136287 | EO111: =EN111 -> 46136287 | EP111: 0 | EQ111: 32751 | ER111: 152668 | ES111: 9696654 | ET111: 12442925 | EU111: 15201758 | EV111: 17467837 | EW111: 20509799 | EX111: 24199624 | EY111: 26723133 | EZ111: 27334623 | FA111: 36682249 | FB111: =FA111 -> 36682249 | FC111: 0 | FD111: 0 | FE111: 1001786 | FF111: 1619224 | FG111: 2338453 | FH111: 2746674 | FI111: 3558099 | FO111: =FI111 -> 3558099
B112: Total Ejecución Acumulada (Subtítulo 31) | C112: =SUM(C80:C111) -> 0 | D112: =SUM(D80:D111) -> 9528305 | E112: =SUM(E80:E111) -> 33820190 | F112: =SUM(F80:F111) -> 42618999 | G112: =SUM(G80:G111) -> 54441027 | H112: =SUM(H80:H111) -> 67915882 | I112: =SUM(I80:I111) -> 78004734 | J112: =SUM(J80:J111) -> 88632670 | ... FO112: =SUM(FO80:FO111) -> 186272538
B115: SUBTÍTULO 29 – ADQUISICIÓN DE ACTIVOS NO FINANCIEROS
B116: Presupuesto Ley (Subtítulo 29)
C117: 2014 | P117: 2015 | AC117: 2016 | AP117: 2017 | BC117: 2018 | BP117: 2019 | CC117: 2020 | CP117: 2021 | DC117: 2022 | DP117: 2023 | EC117: 2024 | EP117: 2025 | FC117: 2026
B118: Programa / Entidad | C118: Ene | D118: Feb | E118: Mar | F118: Abr | G118: May | H118: Jun | I118: Jul | J118: Ago | K118: Sep | L118: Oct | M118: Nov | N118: Dic | O118: Total 2014 | P118: Ene | Q118: Feb | R118: Mar | S118: Abr | T118: May | U118: Jun | V118: Jul | W118: Ago | X118: Sep | Y118: Oct | Z118: Nov | AA118: Dic | AB118: Total 2015 | AC118: Ene | AD118: Feb | AE118: Mar | AF118: Abr | AG118: May | AH118: Jun | AI118: Jul | AJ118: Ago | AK118: Sep | AL118: Oct | AM118: Nov | AN118: Dic | AO118: Total 2016 | AP118: Ene | AQ118: Feb | AR118: Mar | AS118: Abr | AT118: May | AU118: Jun | AV118: Jul | AW118: Ago | AX118: Sep | AY118: Oct | AZ118: Nov | BA118: Dic | BB118: Total 2017 | BC118: Ene | BD118: Feb | BE118: Mar | BF118: Abr | BG118: May | BH118: Jun | BI118: Jul | BJ118: Ago | BK118: Sep | BL118: Oct | BM118: Nov | BN118: Dic | BO118: Total 2018 | BP118: Ene | BQ118: Feb | BR118: Mar | BS118: Abr | BT118: May | BU118: Jun | BV118: Jul | BW118: Ago | BX118: Sep | BY118: Oct | BZ118: Nov | CA118: Dic | CB118: Total 2019 | CC118: Ene | CD118: Feb | CE118: Mar | CF118: Abr | CG118: May | CH118: Jun | CI118: Jul | CJ118: Ago | CK118: Sep | CL118: Oct | CM118: Nov | CN118: Dic | CO118: Total 2020 | CP118: Ene | CQ118: Feb | CR118: Mar | CS118: Abr | CT118: May | CU118: Jun | CV118: Jul | CW118: Ago | CX118: Sep | CY118: Oct | CZ118: Nov | DA118: Dic | DB118: Total 2021 | DC118: Ene | DD118: Feb | DE118: Mar | DF118: Abr | DG118: May | DH118: Jun | DI118: Jul | DJ118: Ago | DK118: Sep | DL118: Oct | DM118: Nov | DN118: Dic | DO118: Total 2022 | DP118: Ene | DQ118: Feb | DR118: Mar | DS118: Abr | DT118: May | DU118: Jun | DV118: Jul | DW118: Ago | DX118: Sep | DY118: Oct | DZ118: Nov | EA118: Dic | EB118: Total 2023 | EC118: Ene | ED118: Feb | EE118: Mar | EF118: Abr | EG118: May | EH118: Jun | EI118: Jul | EJ118: Ago | EK118: Sep | EL118: Oct | EM118: Nov | EN118: Dic | EO118: Total 2024 | EP118: Ene | EQ118: Feb | ER118: Mar | ES118: Abr | ET118: May | EU118: Jun | EV118: Jul | EW118: Ago | EX118: Sep | EY118: Oct | EZ118: Nov | FA118: Dic | FB118: Total 2025 | FC118: Ene | FD118: Feb | FE118: Mar | FF118: Abr | FG118: May | FH118: Jun | FI118: Jul | FJ118: Ago | FK118: Sep | FL118: Oct | FM118: Nov | FN118: Dic | FO118: Total 2026
B119: Instituto de Salud Pública | C119: 2783719 | D119: 2783719 | E119: 2783719 | F119: 2783719 | G119: 2783719 | H119: 2783719 | I119: 2783719 | J119: 2783719 | K119: 2783719 | L119: 2783719 | M119: 2783719 | N119: 2783719 | O119: =N119 -> 2783719 | P119: 1773229 | Q119: 1773229 | R119: 1773229 | S119: 1773229 | T119: 1773229 | U119: 1773229 | V119: 1773229 | W119: 1773229 | X119: 1773229 | Y119: 1773229 | Z119: 1773229 | AA119: 1773229 | AB119: =AA119 -> 1773229 | AC119: 2883073 | AD119: 2883073 | AE119: 2883073 | AF119: 2883073 | AG119: 2883073 | AH119: 2883073 | AI119: 2883073 | AJ119: 2883073 | AK119: 2883073 | AL119: 2883073 | AM119: 2883073 | AN119: 2883073 | AO119: =AN119 -> 2883073 | AP119: 2166982 | AQ119: 2166982 | AR119: 2166982 | AS119: 2166982 | AT119: 2166982 | AU119: 2166982 | AV119: 2166982 | AW119: 2166982 | AX119: 2166982 | AY119: 2166982 | AZ119: 2166982 | BA119: 2166982 | BB119: =BA119 -> 2166982 | BC119: 2101547 | BD119: 2101547 | BE119: 2101547 | BF119: 2101547 | BG119: 2101547 | BH119: 2101547 | BI119: 2101547 | BJ119: 2101547 | BK119: 2101547 | BL119: 2101547 | BM119: 2101547 | BN119: 2101547 | BO119: =BN119 -> 2101547 | BP119: 423742 | BQ119: 423742 | BR119: 423742 | BS119: 423742 | BT119: 423742 | BU119: 423742 | BV119: 423742 | BW119: 423742 | BX119: 423742 | BY119: 423742 | BZ119: 423742 | CA119: 423742 | CB119: =CA119 -> 423742 | CC119: 1120574 | CD119: 1120574 | CE119: 1120574 | CF119: 1120574 | CG119: 1120574 | CH119: 1120574 | CI119: 1120574 | CJ119: 1120574 | CK119: 1120574 | CL119: 1120574 | CM119: 1120574 | CN119: 1120574 | CO119: =CN119 -> 1120574 | CP119: 591755 | CQ119: 591755 | CR119: 591755 | CS119: 591755 | CT119: 591755 | CU119: 591755 | CV119: 591755 | CW119: 591755 | CX119: 591755 | CY119: 591755 | CZ119: 591755 | DA119: 591755 | DB119: =DA119 -> 591755 | DC119: 357119 | DD119: 357119 | DE119: 357119 | DF119: 357119 | DG119: 357119 | DH119: 357119 | DI119: 357119 | DJ119: 357119 | DK119: 357119 | DL119: 357119 | DM119: 357119 | DN119: 357119 | DO119: =DN119 -> 357119 | DP119: 1836870 | DQ119: 1836870 | DR119: 1836870 | DS119: 1836870 | DT119: 1836870 | DU119: 1836870 | DV119: 1836870 | DW119: 1836870 | DX119: 1836870 | DY119: 1836870 | DZ119: 1836870 | EA119: 1836870 | EB119: =EA119 -> 1836870 | EC119: 1306612 | ED119: 1306612 | EE119: 1306612 | EF119: 1306612 | EG119: 1306612 | EH119: 1306612 | EI119: 1306612 | EJ119: 1306612 | EK119: 1306612 | EL119: 1306612 | EM119: 1306612 | EN119: 1306612 | EO119: =EN119 -> 1306612 | EP119: 2331468 | EQ119: 2331468 | ER119: 2331468 | ES119: 2331468 | ET119: 2331468 | EU119: 2331468 | EV119: 2331468 | EW119: 2331468 | EX119: 2331468 | EY119: 2331468 | EZ119: 2331468 | FA119: 2331468 | FB119: =FA119 -> 2331468 | FC119: 1538024 | FD119: 1538024 | FE119: 1538024 | FF119: 1538024 | FG119: 1538024 | FH119: 1538024 | FI119: 1538024 | FO119: =FI119 -> 1538024
B120: Subsecretaría de Salud Pública | C120: 5390419 | D120: 5390419 | E120: 5390419 | F120: 5390419 | G120: 5390419 | H120: 5390419 | I120: 5390419 | J120: 5390419 | K120: 5390419 | L120: 5390419 | M120: 5390419 | N120: 5390419 | O120: =N120 -> 5390419 | P120: 8769976 | Q120: 8769976 | R120: 8769976 | S120: 8769976 | T120: 8769976 | U120: 8769976 | V120: 8769976 | W120: 8769976 | X120: 8769976 | Y120: 8769976 | Z120: 8769976 | AA120: 8769976 | AB120: =AA120 -> 8769976 | AC120: 6200127 | AD120: 6200127 | AE120: 6200127 | AF120: 6200127 | AG120: 6200127 | AH120: 6200127 | AI120: 6200127 | AJ120: 6200127 | AK120: 6200127 | AL120: 6200127 | AM120: 6200127 | AN120: 6200127 | AO120: =AN120 -> 6200127 | AP120: 9626144 | AQ120: 9626144 | AR120: 9626144 | AS120: 9626144 | AT120: 9626144 | AU120: 9626144 | AV120: 9626144 | AW120: 9626144 | AX120: 9626144 | AY120: 9626144 | AZ120: 9626144 | BA120: 9626144 | BB120: =BA120 -> 9626144 | BC120: 16225714 | BD120: 16225714 | BE120: 16225714 | BF120: 16225714 | BG120: 16225714 | BH120: 16225714 | BI120: 16225714 | BJ120: 16225714 | BK120: 16225714 | BL120: 16225714 | BM120: 16225714 | BN120: 16225714 | BO120: =BN120 -> 16225714 | BP120: 448058 | BQ120: 448058 | BR120: 448058 | BS120: 448058 | BT120: 448058 | BU120: 448058 | BV120: 448058 | BW120: 448058 | BX120: 448058 | BY120: 448058 | BZ120: 448058 | CA120: 448058 | CB120: =CA120 -> 448058 | CC120: 8785966 | CD120: 8785966 | CE120: 8785966 | CF120: 8785966 | CG120: 8785966 | CH120: 8785966 | CI120: 8785966 | CJ120: 8785966 | CK120: 8785966 | CL120: 8785966 | CM120: 8785966 | CN120: 8785966 | CO120: =CN120 -> 8785966 | CP120: 880275 | CQ120: 880275 | CR120: 880275 | CS120: 880275 | CT120: 880275 | CU120: 880275 | CV120: 880275 | CW120: 880275 | CX120: 880275 | CY120: 880275 | CZ120: 880275 | DA120: 880275 | DB120: =DA120 -> 880275 | DC120: 82069 | DD120: 82069 | DE120: 82069 | DF120: 82069 | DG120: 82069 | DH120: 82069 | DI120: 82069 | DJ120: 82069 | DK120: 82069 | DL120: 82069 | DM120: 82069 | DN120: 82069 | DO120: =DN120 -> 82069 | DP120: 5308686 | DQ120: 5308686 | DR120: 5308686 | DS120: 5308686 | DT120: 5308686 | DU120: 5308686 | DV120: 5308686 | DW120: 5308686 | DX120: 5308686 | DY120: 5308686 | DZ120: 5308686 | EA120: 5308686 | EB120: =EA120 -> 5308686 | EC120: 1027424 | ED120: 1027424 | EE120: 1027424 | EF120: 1027424 | EG120: 1027424 | EH120: 1027424 | EI120: 1027424 | EJ120: 1027424 | EK120: 1027424 | EL120: 1027424 | EM120: 1027424 | EN120: 1027424 | EO120: =EN120 -> 1027424 | EP120: 1340005 | EQ120: 1340005 | ER120: 1340005 | ES120: 1340005 | ET120: 1340005 | EU120: 1340005 | EV120: 1340005 | EW120: 1340005 | EX120: 1340005 | EY120: 1340005 | EZ120: 1340005 | FA120: 1340005 | FB120: =FA120 -> 1340005 | FC120: 770529 | FD120: 770529 | FE120: 770529 | FF120: 770529 | FG120: 770529 | FH120: 770529 | FI120: 770529 | FO120: =FI120 -> 770529
B121: Inversión Sectorial en Salud | C121: 1091201 | D121: 1091201 | E121: 1091201 | F121: 1091201 | G121: 1091201 | H121: 1091201 | I121: 1091201 | J121: 1091201 | K121: 1091201 | L121: 1091201 | M121: 1091201 | N121: 1091201 | O121: =N121 -> 1091201 | P121: 1232319 | Q121: 1232319 | R121: 1232319 | S121: 1232319 | T121: 1232319 | U121: 1232319 | V121: 1232319 | W121: 1232319 | X121: 1232319 | Y121: 1232319 | Z121: 1232319 | AA121: 1232319 | AB121: =AA121 -> 1232319 | AC121: 1265135 | AD121: 1265135 | AE121: 1265135 | AF121: 1265135 | AG121: 1265135 | AH121: 1265135 | AI121: 1265135 | AJ121: 1265135 | AK121: 1265135 | AL121: 1265135 | AM121: 1265135 | AN121: 1265135 | AO121: =AN121 -> 1265135 | AP121: 1426689 | AQ121: 1426689 | AR121: 1426689 | AS121: 1426689 | AT121: 1426689 | AU121: 1426689 | AV121: 1426689 | AW121: 1426689 | AX121: 1426689 | AY121: 1426689 | AZ121: 1426689 | BA121: 1426689 | BB121: =BA121 -> 1426689 | BC121: 1203274 | BD121: 1203274 | BE121: 1203274 | BF121: 1203274 | BG121: 1203274 | BH121: 1203274 | BI121: 1203274 | BJ121: 1203274 | BK121: 1203274 | BL121: 1203274 | BM121: 1203274 | BN121: 1203274 | BO121: =BN121 -> 1203274 | BP121: 43149437 | BQ121: 43149437 | BR121: 43149437 | BS121: 43149437 | BT121: 43149437 | BU121: 43149437 | BV121: 43149437 | BW121: 43149437 | BX121: 43149437 | BY121: 43149437 | BZ121: 43149437 | CA121: 43149437 | CB121: =CA121 -> 43149437 | CC121: 58306578 | CD121: 58306578 | CE121: 58306578 | CF121: 58306578 | CG121: 58306578 | CH121: 58306578 | CI121: 58306578 | CJ121: 58306578 | CK121: 58306578 | CL121: 58306578 | CM121: 58306578 | CN121: 58306578 | CO121: =CN121 -> 58306578 | CP121: 42343611 | CQ121: 42343611 | CR121: 42343611 | CS121: 42343611 | CT121: 42343611 | CU121: 42343611 | CV121: 42343611 | CW121: 42343611 | CX121: 42343611 | CY121: 42343611 | CZ121: 42343611 | DA121: 42343611 | DB121: =DA121 -> 42343611 | DC121: 65419989 | DD121: 65419989 | DE121: 65419989 | DF121: 65419989 | DG121: 65419989 | DH121: 65419989 | DI121: 65419989 | DJ121: 65419989 | DK121: 65419989 | DL121: 65419989 | DM121: 65419989 | DN121: 65419989 | DO121: =DN121 -> 65419989 | DP121: 58041909 | DQ121: 58041909 | DR121: 58041909 | DS121: 58041909 | DT121: 58041909 | DU121: 58041909 | DV121: 58041909 | DW121: 58041909 | DX121: 58041909 | DY121: 58041909 | DZ121: 58041909 | EA121: 58041909 | EB121: =EA121 -> 58041909 | EC121: 40737248 | ED121: 40737248 | EE121: 40737248 | EF121: 40737248 | EG121: 40737248 | EH121: 40737248 | EI121: 40737248 | EJ121: 40737248 | EK121: 40737248 | EL121: 40737248 | EM121: 40737248 | EN121: 40737248 | EO121: =EN121 -> 40737248 | EP121: 51826213 | EQ121: 51826213 | ER121: 51826213 | ES121: 51826213 | ET121: 51826213 | EU121: 51826213 | EV121: 51826213 | EW121: 51826213 | EX121: 51826213 | EY121: 51826213 | EZ121: 51826213 | FA121: 51826213 | FB121: =FA121 -> 51826213 | FC121: 51314706 | FD121: 51314706 | FE121: 51314706 | FF121: 51314706 | FG121: 51314706 | FH121: 51314706 | FI121: 51314706 | FO121: =FI121 -> 51314706
B122: Servicio de Salud Arica y Parinacota | C122: 152433 | D122: 152433 | E122: 152433 | F122: 152433 | G122: 152433 | H122: 152433 | I122: 152433 | J122: 152433 | K122: 152433 | L122: 152433 | M122: 152433 | N122: 152433 | O122: =N122 -> 152433 | P122: 157006 | Q122: 157006 | R122: 157006 | S122: 157006 | T122: 157006 | U122: 157006 | V122: 157006 | W122: 157006 | X122: 157006 | Y122: 157006 | Z122: 157006 | AA122: 157006 | AB122: =AA122 -> 157006 | AC122: 162972 | AD122: 162972 | AE122: 162972 | AF122: 162972 | AG122: 162972 | AH122: 162972 | AI122: 162972 | AJ122: 162972 | AK122: 162972 | AL122: 162972 | AM122: 162972 | AN122: 162972 | AO122: =AN122 -> 162972 | AP122: 167861 | AQ122: 167861 | AR122: 167861 | AS122: 167861 | AT122: 167861 | AU122: 167861 | AV122: 167861 | AW122: 167861 | AX122: 167861 | AY122: 167861 | AZ122: 167861 | BA122: 167861 | BB122: =BA122 -> 167861 | BC122: 172225 | BD122: 172225 | BE122: 172225 | BF122: 172225 | BG122: 172225 | BH122: 172225 | BI122: 172225 | BJ122: 172225 | BK122: 172225 | BL122: 172225 | BM122: 172225 | BN122: 172225 | BO122: =BN122 -> 172225 | BP122: 0 | BQ122: 0 | BR122: 0 | BS122: 0 | BT122: 0 | BU122: 0 | BV122: 0 | BW122: 0 | BX122: 0 | BY122: 0 | BZ122: 0 | CA122: 0 | CB122: =CA122 -> 0 | CC122: 33183 | CD122: 33183 | CE122: 33183 | CF122: 33183 | CG122: 33183 | CH122: 33183 | CI122: 33183 | CJ122: 33183 | CK122: 33183 | CL122: 33183 | CM122: 33183 | CN122: 33183 | CO122: =CN122 -> 33183 | CP122: 142663 | CQ122: 142663 | CR122: 142663 | CS122: 142663 | CT122: 142663 | CU122: 142663 | CV122: 142663 | CW122: 142663 | CX122: 142663 | CY122: 142663 | CZ122: 142663 | DA122: 142663 | DB122: =DA122 -> 142663 | DC122: 193368 | DD122: 193368 | DE122: 193368 | DF122: 193368 | DG122: 193368 | DH122: 193368 | DI122: 193368 | DJ122: 193368 | DK122: 193368 | DL122: 193368 | DM122: 193368 | DN122: 193368 | DO122: =DN122 -> 193368 | DP122: 205550 | DQ122: 205550 | DR122: 205550 | DS122: 205550 | DT122: 205550 | DU122: 205550 | DV122: 205550 | DW122: 205550 | DX122: 205550 | DY122: 205550 | DZ122: 205550 | EA122: 205550 | EB122: =EA122 -> 205550 | EC122: 188275 | ED122: 188275 | EE122: 188275 | EF122: 188275 | EG122: 188275 | EH122: 188275 | EI122: 188275 | EJ122: 188275 | EK122: 188275 | EL122: 188275 | EM122: 188275 | EN122: 188275 | EO122: =EN122 -> 188275 | EP122: 196182 | EQ122: 196182 | ER122: 196182 | ES122: 196182 | ET122: 196182 | EU122: 196182 | EV122: 196182 | EW122: 196182 | EX122: 196182 | EY122: 196182 | EZ122: 196182 | FA122: 196182 | FB122: =FA122 -> 196182 | FC122: 202264 | FD122: 202264 | FE122: 202264 | FF122: 202264 | FG122: 202264 | FH122: 202264 | FI122: 202264 | FO122: =FI122 -> 202264
B123: Servicio de Salud Tarapacá | C123: 215595 | D123: 215595 | E123: 215595 | F123: 215595 | G123: 215595 | H123: 215595 | I123: 215595 | J123: 215595 | K123: 215595 | L123: 215595 | M123: 215595 | N123: 215595 | O123: =N123 -> 215595 | P123: 222063 | Q123: 222063 | R123: 222063 | S123: 222063 | T123: 222063 | U123: 222063 | V123: 222063 | W123: 222063 | X123: 222063 | Y123: 222063 | Z123: 222063 | AA123: 222063 | AB123: =AA123 -> 222063 | AC123: 230501 | AD123: 230501 | AE123: 230501 | AF123: 230501 | AG123: 230501 | AH123: 230501 | AI123: 230501 | AJ123: 230501 | AK123: 230501 | AL123: 230501 | AM123: 230501 | AN123: 230501 | AO123: =AN123 -> 230501 | AP123: 237416 | AQ123: 237416 | AR123: 237416 | AS123: 237416 | AT123: 237416 | AU123: 237416 | AV123: 237416 | AW123: 237416 | AX123: 237416 | AY123: 237416 | AZ123: 237416 | BA123: 237416 | BB123: =BA123 -> 237416 | BC123: 243589 | BD123: 243589 | BE123: 243589 | BF123: 243589 | BG123: 243589 | BH123: 243589 | BI123: 243589 | BJ123: 243589 | BK123: 243589 | BL123: 243589 | BM123: 243589 | BN123: 243589 | BO123: =BN123 -> 243589 | BP123: 0 | BQ123: 0 | BR123: 0 | BS123: 0 | BT123: 0 | BU123: 0 | BV123: 0 | BW123: 0 | BX123: 0 | BY123: 0 | BZ123: 0 | CA123: 0 | CB123: =CA123 -> 0 | CC123: 42579 | CD123: 42579 | CE123: 42579 | CF123: 42579 | CG123: 42579 | CH123: 42579 | CI123: 42579 | CJ123: 42579 | CK123: 42579 | CL123: 42579 | CM123: 42579 | CN123: 42579 | CO123: =CN123 -> 42579 | CP123: 185100 | CQ123: 185100 | CR123: 185100 | CS123: 185100 | CT123: 185100 | CU123: 185100 | CV123: 185100 | CW123: 185100 | CX123: 185100 | CY123: 185100 | CZ123: 185100 | DA123: 185100 | DB123: =DA123 -> 185100 | DC123: 251177 | DD123: 251177 | DE123: 251177 | DF123: 251177 | DG123: 251177 | DH123: 251177 | DI123: 251177 | DJ123: 251177 | DK123: 251177 | DL123: 251177 | DM123: 251177 | DN123: 251177 | DO123: =DN123 -> 251177 | DP123: 267001 | DQ123: 267001 | DR123: 267001 | DS123: 267001 | DT123: 267001 | DU123: 267001 | DV123: 267001 | DW123: 267001 | DX123: 267001 | DY123: 267001 | DZ123: 267001 | EA123: 267001 | EB123: =EA123 -> 267001 | EC123: 244561 | ED123: 244561 | EE123: 244561 | EF123: 244561 | EG123: 244561 | EH123: 244561 | EI123: 244561 | EJ123: 244561 | EK123: 244561 | EL123: 244561 | EM123: 244561 | EN123: 244561 | EO123: =EN123 -> 244561 | EP123: 254832 | EQ123: 254832 | ER123: 254832 | ES123: 254832 | ET123: 254832 | EU123: 254832 | EV123: 254832 | EW123: 254832 | EX123: 254832 | EY123: 254832 | EZ123: 254832 | FA123: 254832 | FB123: =FA123 -> 254832 | FC123: 262732 | FD123: 262732 | FE123: 262732 | FF123: 262732 | FG123: 262732 | FH123: 262732 | FI123: 262732 | FO123: =FI123 -> 262732
B124: Servicio de Salud Antofagasta | C124: 202258 | D124: 202258 | E124: 202258 | F124: 202258 | G124: 202258 | H124: 202258 | I124: 202258 | J124: 202258 | K124: 202258 | L124: 202258 | M124: 202258 | N124: 202258 | O124: =N124 -> 202258 | P124: 208326 | Q124: 208326 | R124: 208326 | S124: 208326 | T124: 208326 | U124: 208326 | V124: 208326 | W124: 208326 | X124: 208326 | Y124: 208326 | Z124: 208326 | AA124: 208326 | AB124: =AA124 -> 208326 | AC124: 216242 | AD124: 216242 | AE124: 216242 | AF124: 216242 | AG124: 216242 | AH124: 216242 | AI124: 216242 | AJ124: 216242 | AK124: 216242 | AL124: 216242 | AM124: 216242 | AN124: 216242 | AO124: =AN124 -> 216242 | AP124: 222729 | AQ124: 222729 | AR124: 222729 | AS124: 222729 | AT124: 222729 | AU124: 222729 | AV124: 222729 | AW124: 222729 | AX124: 222729 | AY124: 222729 | AZ124: 222729 | BA124: 222729 | BB124: =BA124 -> 222729 | BC124: 228520 | BD124: 228520 | BE124: 228520 | BF124: 228520 | BG124: 228520 | BH124: 228520 | BI124: 228520 | BJ124: 228520 | BK124: 228520 | BL124: 228520 | BM124: 228520 | BN124: 228520 | BO124: =BN124 -> 228520 | BP124: 0 | BQ124: 0 | BR124: 0 | BS124: 0 | BT124: 0 | BU124: 0 | BV124: 0 | BW124: 0 | BX124: 0 | BY124: 0 | BZ124: 0 | CA124: 0 | CB124: =CA124 -> 0 | CC124: 80375 | CD124: 80375 | CE124: 80375 | CF124: 80375 | CG124: 80375 | CH124: 80375 | CI124: 80375 | CJ124: 80375 | CK124: 80375 | CL124: 80375 | CM124: 80375 | CN124: 80375 | CO124: =CN124 -> 80375 | CP124: 376018 | CQ124: 376018 | CR124: 376018 | CS124: 376018 | CT124: 376018 | CU124: 376018 | CV124: 376018 | CW124: 376018 | CX124: 376018 | CY124: 376018 | CZ124: 376018 | DA124: 376018 | DB124: =DA124 -> 376018 | DC124: 511002 | DD124: 511002 | DE124: 511002 | DF124: 511002 | DG124: 511002 | DH124: 511002 | DI124: 511002 | DJ124: 511002 | DK124: 511002 | DL124: 511002 | DM124: 511002 | DN124: 511002 | DO124: =DN124 -> 511002 | DP124: 543195 | DQ124: 543195 | DR124: 543195 | DS124: 543195 | DT124: 543195 | DU124: 543195 | DV124: 543195 | DW124: 543195 | DX124: 543195 | DY124: 543195 | DZ124: 543195 | EA124: 543195 | EB124: =EA124 -> 543195 | EC124: 497544 | ED124: 497544 | EE124: 497544 | EF124: 497544 | EG124: 497544 | EH124: 497544 | EI124: 497544 | EJ124: 497544 | EK124: 497544 | EL124: 497544 | EM124: 497544 | EN124: 497544 | EO124: =EN124 -> 497544 | EP124: 518441 | EQ124: 518441 | ER124: 518441 | ES124: 518441 | ET124: 518441 | EU124: 518441 | EV124: 518441 | EW124: 518441 | EX124: 518441 | EY124: 518441 | EZ124: 518441 | FA124: 518441 | FB124: =FA124 -> 518441 | FC124: 534512 | FD124: 534512 | FE124: 534512 | FF124: 534512 | FG124: 534512 | FH124: 534512 | FI124: 534512 | FO124: =FI124 -> 534512
B125: Servicio de Salud Atacama | C125: 118004 | D125: 118004 | E125: 118004 | F125: 118004 | G125: 118004 | H125: 118004 | I125: 118004 | J125: 118004 | K125: 118004 | L125: 118004 | M125: 118004 | N125: 118004 | O125: =N125 -> 118004 | P125: 121544 | Q125: 121544 | R125: 121544 | S125: 121544 | T125: 121544 | U125: 121544 | V125: 121544 | W125: 121544 | X125: 121544 | Y125: 121544 | Z125: 121544 | AA125: 121544 | AB125: =AA125 -> 121544 | AC125: 126163 | AD125: 126163 | AE125: 126163 | AF125: 126163 | AG125: 126163 | AH125: 126163 | AI125: 126163 | AJ125: 126163 | AK125: 126163 | AL125: 126163 | AM125: 126163 | AN125: 126163 | AO125: =AN125 -> 126163 | AP125: 129948 | AQ125: 129948 | AR125: 129948 | AS125: 129948 | AT125: 129948 | AU125: 129948 | AV125: 129948 | AW125: 129948 | AX125: 129948 | AY125: 129948 | AZ125: 129948 | BA125: 129948 | BB125: =BA125 -> 129948 | BC125: 133327 | BD125: 133327 | BE125: 133327 | BF125: 133327 | BG125: 133327 | BH125: 133327 | BI125: 133327 | BJ125: 133327 | BK125: 133327 | BL125: 133327 | BM125: 133327 | BN125: 133327 | BO125: =BN125 -> 133327 | BP125: 0 | BQ125: 0 | BR125: 0 | BS125: 0 | BT125: 0 | BU125: 0 | BV125: 0 | BW125: 0 | BX125: 0 | BY125: 0 | BZ125: 0 | CA125: 0 | CB125: =CA125 -> 0 | CC125: 42543 | CD125: 42543 | CE125: 42543 | CF125: 42543 | CG125: 42543 | CH125: 42543 | CI125: 42543 | CJ125: 42543 | CK125: 42543 | CL125: 42543 | CM125: 42543 | CN125: 42543 | CO125: =CN125 -> 42543 | CP125: 183254 | CQ125: 183254 | CR125: 183254 | CS125: 183254 | CT125: 183254 | CU125: 183254 | CV125: 183254 | CW125: 183254 | CX125: 183254 | CY125: 183254 | CZ125: 183254 | DA125: 183254 | DB125: =DA125 -> 183254 | DC125: 248523 | DD125: 248523 | DE125: 248523 | DF125: 248523 | DG125: 248523 | DH125: 248523 | DI125: 248523 | DJ125: 248523 | DK125: 248523 | DL125: 248523 | DM125: 248523 | DN125: 248523 | DO125: =DN125 -> 248523 | DP125: 264180 | DQ125: 264180 | DR125: 264180 | DS125: 264180 | DT125: 264180 | DU125: 264180 | DV125: 264180 | DW125: 264180 | DX125: 264180 | DY125: 264180 | DZ125: 264180 | EA125: 264180 | EB125: =EA125 -> 264180 | EC125: 241977 | ED125: 241977 | EE125: 241977 | EF125: 241977 | EG125: 241977 | EH125: 241977 | EI125: 241977 | EJ125: 241977 | EK125: 241977 | EL125: 241977 | EM125: 241977 | EN125: 241977 | EO125: =EN125 -> 241977 | EP125: 252140 | EQ125: 252140 | ER125: 252140 | ES125: 252140 | ET125: 252140 | EU125: 252140 | EV125: 252140 | EW125: 252140 | EX125: 252140 | EY125: 252140 | EZ125: 252140 | FA125: 252140 | FB125: =FA125 -> 252140 | FC125: 259957 | FD125: 259957 | FE125: 259957 | FF125: 259957 | FG125: 259957 | FH125: 259957 | FI125: 259957 | FO125: =FI125 -> 259957
B126: Servicio de Salud Coquimbo | C126: 288212 | D126: 288212 | E126: 288212 | F126: 288212 | G126: 288212 | H126: 288212 | I126: 288212 | J126: 288212 | K126: 288212 | L126: 288212 | M126: 288212 | N126: 288212 | O126: =N126 -> 288212 | P126: 296858 | Q126: 296858 | R126: 296858 | S126: 296858 | T126: 296858 | U126: 296858 | V126: 296858 | W126: 296858 | X126: 296858 | Y126: 296858 | Z126: 296858 | AA126: 296858 | AB126: =AA126 -> 296858 | AC126: 308139 | AD126: 308139 | AE126: 308139 | AF126: 308139 | AG126: 308139 | AH126: 308139 | AI126: 308139 | AJ126: 308139 | AK126: 308139 | AL126: 308139 | AM126: 308139 | AN126: 308139 | AO126: =AN126 -> 308139 | AP126: 317383 | AQ126: 317383 | AR126: 317383 | AS126: 317383 | AT126: 317383 | AU126: 317383 | AV126: 317383 | AW126: 317383 | AX126: 317383 | AY126: 317383 | AZ126: 317383 | BA126: 317383 | BB126: =BA126 -> 317383 | BC126: 325635 | BD126: 325635 | BE126: 325635 | BF126: 325635 | BG126: 325635 | BH126: 325635 | BI126: 325635 | BJ126: 325635 | BK126: 325635 | BL126: 325635 | BM126: 325635 | BN126: 325635 | BO126: =BN126 -> 325635 | BP126: 0 | BQ126: 0 | BR126: 0 | BS126: 0 | BT126: 0 | BU126: 0 | BV126: 0 | BW126: 0 | BX126: 0 | BY126: 0 | BZ126: 0 | CA126: 0 | CB126: =CA126 -> 0 | CC126: 93134 | CD126: 93134 | CE126: 93134 | CF126: 93134 | CG126: 93134 | CH126: 93134 | CI126: 93134 | CJ126: 93134 | CK126: 93134 | CL126: 93134 | CM126: 93134 | CN126: 93134 | CO126: =CN126 -> 93134 | CP126: 413232 | CQ126: 413232 | CR126: 413232 | CS126: 413232 | CT126: 413232 | CU126: 413232 | CV126: 413232 | CW126: 413232 | CX126: 413232 | CY126: 413232 | CZ126: 413232 | DA126: 413232 | DB126: =DA126 -> 413232 | DC126: 561294 | DD126: 561294 | DE126: 561294 | DF126: 561294 | DG126: 561294 | DH126: 561294 | DI126: 561294 | DJ126: 561294 | DK126: 561294 | DL126: 561294 | DM126: 561294 | DN126: 561294 | DO126: =DN126 -> 561294 | DP126: 596656 | DQ126: 596656 | DR126: 596656 | DS126: 596656 | DT126: 596656 | DU126: 596656 | DV126: 596656 | DW126: 596656 | DX126: 596656 | DY126: 596656 | DZ126: 596656 | EA126: 596656 | EB126: =EA126 -> 596656 | EC126: 546510 | ED126: 546510 | EE126: 546510 | EF126: 546510 | EG126: 546510 | EH126: 546510 | EI126: 546510 | EJ126: 546510 | EK126: 546510 | EL126: 546510 | EM126: 546510 | EN126: 546510 | EO126: =EN126 -> 546510 | EP126: 569463 | EQ126: 569463 | ER126: 569463 | ES126: 569463 | ET126: 569463 | EU126: 569463 | EV126: 569463 | EW126: 569463 | EX126: 569463 | EY126: 569463 | EZ126: 569463 | FA126: 569463 | FB126: =FA126 -> 569463 | FC126: 587116 | FD126: 587116 | FE126: 587116 | FF126: 587116 | FG126: 587116 | FH126: 587116 | FI126: 587116 | FO126: =FI126 -> 587116
B127: Servicio de Salud Valparaíso - San Antonio | C127: 346611 | D127: 346611 | E127: 346611 | F127: 346611 | G127: 346611 | H127: 346611 | I127: 346611 | J127: 346611 | K127: 346611 | L127: 346611 | M127: 346611 | N127: 346611 | O127: =N127 -> 346611 | P127: 357009 | Q127: 357009 | R127: 357009 | S127: 357009 | T127: 357009 | U127: 357009 | V127: 357009 | W127: 357009 | X127: 357009 | Y127: 357009 | Z127: 357009 | AA127: 357009 | AB127: =AA127 -> 357009 | AC127: 370575 | AD127: 370575 | AE127: 370575 | AF127: 370575 | AG127: 370575 | AH127: 370575 | AI127: 370575 | AJ127: 370575 | AK127: 370575 | AL127: 370575 | AM127: 370575 | AN127: 370575 | AO127: =AN127 -> 370575 | AP127: 381692 | AQ127: 381692 | AR127: 381692 | AS127: 381692 | AT127: 381692 | AU127: 381692 | AV127: 381692 | AW127: 381692 | AX127: 381692 | AY127: 381692 | AZ127: 381692 | BA127: 381692 | BB127: =BA127 -> 381692 | BC127: 391616 | BD127: 391616 | BE127: 391616 | BF127: 391616 | BG127: 391616 | BH127: 391616 | BI127: 391616 | BJ127: 391616 | BK127: 391616 | BL127: 391616 | BM127: 391616 | BN127: 391616 | BO127: =BN127 -> 391616 | BP127: 0 | BQ127: 0 | BR127: 0 | BS127: 0 | BT127: 0 | BU127: 0 | BV127: 0 | BW127: 0 | BX127: 0 | BY127: 0 | BZ127: 0 | CA127: 0 | CB127: =CA127 -> 0 | CC127: 79142 | CD127: 79142 | CE127: 79142 | CF127: 79142 | CG127: 79142 | CH127: 79142 | CI127: 79142 | CJ127: 79142 | CK127: 79142 | CL127: 79142 | CM127: 79142 | CN127: 79142 | CO127: =CN127 -> 79142 | CP127: 333094 | CQ127: 333094 | CR127: 333094 | CS127: 333094 | CT127: 333094 | CU127: 333094 | CV127: 333094 | CW127: 333094 | CX127: 333094 | CY127: 333094 | CZ127: 333094 | DA127: 333094 | DB127: =DA127 -> 333094 | DC127: 451628 | DD127: 451628 | DE127: 451628 | DF127: 451628 | DG127: 451628 | DH127: 451628 | DI127: 451628 | DJ127: 451628 | DK127: 451628 | DL127: 451628 | DM127: 451628 | DN127: 451628 | DO127: =DN127 -> 451628 | DP127: 480081 | DQ127: 480081 | DR127: 480081 | DS127: 480081 | DT127: 480081 | DU127: 480081 | DV127: 480081 | DW127: 480081 | DX127: 480081 | DY127: 480081 | DZ127: 480081 | EA127: 480081 | EB127: =EA127 -> 480081 | EC127: 439733 | ED127: 439733 | EE127: 439733 | EF127: 439733 | EG127: 439733 | EH127: 439733 | EI127: 439733 | EJ127: 439733 | EK127: 439733 | EL127: 439733 | EM127: 439733 | EN127: 439733 | EO127: =EN127 -> 439733 | EP127: 458202 | EQ127: 458202 | ER127: 458202 | ES127: 458202 | ET127: 458202 | EU127: 458202 | EV127: 458202 | EW127: 458202 | EX127: 458202 | EY127: 458202 | EZ127: 458202 | FA127: 458202 | FB127: =FA127 -> 458202 | FC127: 472406 | FD127: 472406 | FE127: 472406 | FF127: 472406 | FG127: 472406 | FH127: 472406 | FI127: 472406 | FO127: =FI127 -> 472406
B128: Servicio de Salud Viña del Mar - Quillota | C128: 357298 | D128: 357298 | E128: 357298 | F128: 357298 | G128: 357298 | H128: 357298 | I128: 357298 | J128: 357298 | K128: 357298 | L128: 357298 | M128: 357298 | N128: 357298 | O128: =N128 -> 357298 | P128: 368017 | Q128: 368017 | R128: 368017 | S128: 368017 | T128: 368017 | U128: 368017 | V128: 368017 | W128: 368017 | X128: 368017 | Y128: 368017 | Z128: 368017 | AA128: 368017 | AB128: =AA128 -> 368017 | AC128: 382002 | AD128: 382002 | AE128: 382002 | AF128: 382002 | AG128: 382002 | AH128: 382002 | AI128: 382002 | AJ128: 382002 | AK128: 382002 | AL128: 382002 | AM128: 382002 | AN128: 382002 | AO128: =AN128 -> 382002 | AP128: 393462 | AQ128: 393462 | AR128: 393462 | AS128: 393462 | AT128: 393462 | AU128: 393462 | AV128: 393462 | AW128: 393462 | AX128: 393462 | AY128: 393462 | AZ128: 393462 | BA128: 393462 | BB128: =BA128 -> 393462 | BC128: 403692 | BD128: 403692 | BE128: 403692 | BF128: 403692 | BG128: 403692 | BH128: 403692 | BI128: 403692 | BJ128: 403692 | BK128: 403692 | BL128: 403692 | BM128: 403692 | BN128: 403692 | BO128: =BN128 -> 403692 | BP128: 0 | BQ128: 0 | BR128: 0 | BS128: 0 | BT128: 0 | BU128: 0 | BV128: 0 | BW128: 0 | BX128: 0 | BY128: 0 | BZ128: 0 | CA128: 0 | CB128: =CA128 -> 0 | CC128: 108890 | CD128: 108890 | CE128: 108890 | CF128: 108890 | CG128: 108890 | CH128: 108890 | CI128: 108890 | CJ128: 108890 | CK128: 108890 | CL128: 108890 | CM128: 108890 | CN128: 108890 | CO128: =CN128 -> 108890 | CP128: 476890 | CQ128: 476890 | CR128: 476890 | CS128: 476890 | CT128: 476890 | CU128: 476890 | CV128: 476890 | CW128: 476890 | CX128: 476890 | CY128: 476890 | CZ128: 476890 | DA128: 476890 | DB128: =DA128 -> 476890 | DC128: 651404 | DD128: 651404 | DE128: 651404 | DF128: 651404 | DG128: 651404 | DH128: 651404 | DI128: 651404 | DJ128: 651404 | DK128: 651404 | DL128: 651404 | DM128: 651404 | DN128: 651404 | DO128: =DN128 -> 651404 | DP128: 692443 | DQ128: 692443 | DR128: 692443 | DS128: 692443 | DT128: 692443 | DU128: 692443 | DV128: 692443 | DW128: 692443 | DX128: 692443 | DY128: 692443 | DZ128: 692443 | EA128: 692443 | EB128: =EA128 -> 692443 | EC128: 634247 | ED128: 634247 | EE128: 634247 | EF128: 634247 | EG128: 634247 | EH128: 634247 | EI128: 634247 | EJ128: 634247 | EK128: 634247 | EL128: 634247 | EM128: 634247 | EN128: 634247 | EO128: =EN128 -> 634247 | EP128: 660885 | EQ128: 660885 | ER128: 660885 | ES128: 660885 | ET128: 660885 | EU128: 660885 | EV128: 660885 | EW128: 660885 | EX128: 660885 | EY128: 660885 | EZ128: 660885 | FA128: 660885 | FB128: =FA128 -> 660885 | FC128: 681372 | FD128: 681372 | FE128: 681372 | FF128: 681372 | FG128: 681372 | FH128: 681372 | FI128: 681372 | FO128: =FI128 -> 681372
B129: Servicio de Salud Aconcagua | C129: 286402 | D129: 286402 | E129: 286402 | F129: 286402 | G129: 286402 | H129: 286402 | I129: 286402 | J129: 286402 | K129: 286402 | L129: 286402 | M129: 286402 | N129: 286402 | O129: =N129 -> 286402 | P129: 294994 | Q129: 294994 | R129: 294994 | S129: 294994 | T129: 294994 | U129: 294994 | V129: 294994 | W129: 294994 | X129: 294994 | Y129: 294994 | Z129: 294994 | AA129: 294994 | AB129: =AA129 -> 294994 | AC129: 306204 | AD129: 306204 | AE129: 306204 | AF129: 306204 | AG129: 306204 | AH129: 306204 | AI129: 306204 | AJ129: 306204 | AK129: 306204 | AL129: 306204 | AM129: 306204 | AN129: 306204 | AO129: =AN129 -> 306204 | AP129: 315390 | AQ129: 315390 | AR129: 315390 | AS129: 315390 | AT129: 315390 | AU129: 315390 | AV129: 315390 | AW129: 315390 | AX129: 315390 | AY129: 315390 | AZ129: 315390 | BA129: 315390 | BB129: =BA129 -> 315390 | BC129: 323590 | BD129: 323590 | BE129: 323590 | BF129: 323590 | BG129: 323590 | BH129: 323590 | BI129: 323590 | BJ129: 323590 | BK129: 323590 | BL129: 323590 | BM129: 323590 | BN129: 323590 | BO129: =BN129 -> 323590 | BP129: 0 | BQ129: 0 | BR129: 0 | BS129: 0 | BT129: 0 | BU129: 0 | BV129: 0 | BW129: 0 | BX129: 0 | BY129: 0 | BZ129: 0 | CA129: 0 | CB129: =CA129 -> 0 | CC129: 40833 | CD129: 40833 | CE129: 40833 | CF129: 40833 | CG129: 40833 | CH129: 40833 | CI129: 40833 | CJ129: 40833 | CK129: 40833 | CL129: 40833 | CM129: 40833 | CN129: 40833 | CO129: =CN129 -> 40833 | CP129: 180349 | CQ129: 180349 | CR129: 180349 | CS129: 180349 | CT129: 180349 | CU129: 180349 | CV129: 180349 | CW129: 180349 | CX129: 180349 | CY129: 180349 | CZ129: 180349 | DA129: 180349 | DB129: =DA129 -> 180349 | DC129: 250008 | DD129: 250008 | DE129: 250008 | DF129: 250008 | DG129: 250008 | DH129: 250008 | DI129: 250008 | DJ129: 250008 | DK129: 250008 | DL129: 250008 | DM129: 250008 | DN129: 250008 | DO129: =DN129 -> 250008 | DP129: 265759 | DQ129: 265759 | DR129: 265759 | DS129: 265759 | DT129: 265759 | DU129: 265759 | DV129: 265759 | DW129: 265759 | DX129: 265759 | DY129: 265759 | DZ129: 265759 | EA129: 265759 | EB129: =EA129 -> 265759 | EC129: 243422 | ED129: 243422 | EE129: 243422 | EF129: 243422 | EG129: 243422 | EH129: 243422 | EI129: 243422 | EJ129: 243422 | EK129: 243422 | EL129: 243422 | EM129: 243422 | EN129: 243422 | EO129: =EN129 -> 243422 | EP129: 253646 | EQ129: 253646 | ER129: 253646 | ES129: 253646 | ET129: 253646 | EU129: 253646 | EV129: 253646 | EW129: 253646 | EX129: 253646 | EY129: 253646 | EZ129: 253646 | FA129: 253646 | FB129: =FA129 -> 253646 | FC129: 261509 | FD129: 261509 | FE129: 261509 | FF129: 261509 | FG129: 261509 | FH129: 261509 | FI129: 261509 | FO129: =FI129 -> 261509
B130: Servicio de Salud O'Higgins | C130: 282051 | D130: 282051 | E130: 282051 | F130: 282051 | G130: 282051 | H130: 282051 | I130: 282051 | J130: 282051 | K130: 282051 | L130: 282051 | M130: 282051 | N130: 282051 | O130: =N130 -> 282051 | P130: 290513 | Q130: 290513 | R130: 290513 | S130: 290513 | T130: 290513 | U130: 290513 | V130: 290513 | W130: 290513 | X130: 290513 | Y130: 290513 | Z130: 290513 | AA130: 290513 | AB130: =AA130 -> 290513 | AC130: 301552 | AD130: 301552 | AE130: 301552 | AF130: 301552 | AG130: 301552 | AH130: 301552 | AI130: 301552 | AJ130: 301552 | AK130: 301552 | AL130: 301552 | AM130: 301552 | AN130: 301552 | AO130: =AN130 -> 301552 | AP130: 310599 | AQ130: 310599 | AR130: 310599 | AS130: 310599 | AT130: 310599 | AU130: 310599 | AV130: 310599 | AW130: 310599 | AX130: 310599 | AY130: 310599 | AZ130: 310599 | BA130: 310599 | BB130: =BA130 -> 310599 | BC130: 318675 | BD130: 318675 | BE130: 318675 | BF130: 318675 | BG130: 318675 | BH130: 318675 | BI130: 318675 | BJ130: 318675 | BK130: 318675 | BL130: 318675 | BM130: 318675 | BN130: 318675 | BO130: =BN130 -> 318675 | BP130: 0 | BQ130: 0 | BR130: 0 | BS130: 0 | BT130: 0 | BU130: 0 | BV130: 0 | BW130: 0 | BX130: 0 | BY130: 0 | BZ130: 0 | CA130: 0 | CB130: =CA130 -> 0 | CC130: 103121 | CD130: 103121 | CE130: 103121 | CF130: 103121 | CG130: 103121 | CH130: 103121 | CI130: 103121 | CJ130: 103121 | CK130: 103121 | CL130: 103121 | CM130: 103121 | CN130: 103121 | CO130: =CN130 -> 103121 | CP130: 444000 | CQ130: 444000 | CR130: 444000 | CS130: 444000 | CT130: 444000 | CU130: 444000 | CV130: 444000 | CW130: 444000 | CX130: 444000 | CY130: 444000 | CZ130: 444000 | DA130: 444000 | DB130: =DA130 -> 444000 | DC130: 609864 | DD130: 609864 | DE130: 609864 | DF130: 609864 | DG130: 609864 | DH130: 609864 | DI130: 609864 | DJ130: 609864 | DK130: 609864 | DL130: 609864 | DM130: 609864 | DN130: 609864 | DO130: =DN130 -> 609864 | DP130: 648285 | DQ130: 648285 | DR130: 648285 | DS130: 648285 | DT130: 648285 | DU130: 648285 | DV130: 648285 | DW130: 648285 | DX130: 648285 | DY130: 648285 | DZ130: 648285 | EA130: 648285 | EB130: =EA130 -> 648285 | EC130: 593801 | ED130: 593801 | EE130: 593801 | EF130: 593801 | EG130: 593801 | EH130: 593801 | EI130: 593801 | EJ130: 593801 | EK130: 593801 | EL130: 593801 | EM130: 593801 | EN130: 593801 | EO130: =EN130 -> 593801 | EP130: 618741 | EQ130: 618741 | ER130: 618741 | ES130: 618741 | ET130: 618741 | EU130: 618741 | EV130: 618741 | EW130: 618741 | EX130: 618741 | EY130: 618741 | EZ130: 618741 | FA130: 618741 | FB130: =FA130 -> 618741 | FC130: 637922 | FD130: 637922 | FE130: 637922 | FF130: 637922 | FG130: 637922 | FH130: 637922 | FI130: 637922 | FO130: =FI130 -> 637922
... B150: Servicio de Salud Chiloé | C150: 39141 | D150: 39141 | E150: 39141 | F150: 39141 | G150: 39141 | H150: 39141 | I150: 39141 | J150: 39141 | K150: 39141 | L150: 39141 | M150: 39141 | N150: 39141 | O150: =N150 -> 39141 | P150: 40315 | Q150: 40315 | R150: 40315 | S150: 40315 | T150: 40315 | U150: 40315 | V150: 40315 | W150: 40315 | X150: 40315 | Y150: 40315 | Z150: 40315 | AA150: 40315 | AB150: =AA150 -> 40315 | AC150: 41847 | AD150: 41847 | AE150: 41847 | AF150: 41847 | AG150: 41847 | AH150: 41847 | AI150: 41847 | AJ150: 41847 | AK150: 41847 | AL150: 41847 | AM150: 41847 | AN150: 41847 | AO150: =AN150 -> 41847 | AP150: 43102 | AQ150: 43102 | AR150: 43102 | AS150: 43102 | AT150: 43102 | AU150: 43102 | AV150: 43102 | AW150: 43102 | AX150: 43102 | AY150: 43102 | AZ150: 43102 | BA150: 43102 | BB150: =BA150 -> 43102 | BC150: 44223 | BD150: 44223 | BE150: 44223 | BF150: 44223 | BG150: 44223 | BH150: 44223 | BI150: 44223 | BJ150: 44223 | BK150: 44223 | BL150: 44223 | BM150: 44223 | BN150: 44223 | BO150: =BN150 -> 44223 | BP150: 0 | BQ150: 0 | BR150: 0 | BS150: 0 | BT150: 0 | BU150: 0 | BV150: 0 | BW150: 0 | BX150: 0 | BY150: 0 | BZ150: 0 | CA150: 0 | CB150: =CA150 -> 0 | CC150: 33782 | CD150: 33782 | CE150: 33782 | CF150: 33782 | CG150: 33782 | CH150: 33782 | CI150: 33782 | CJ150: 33782 | CK150: 33782 | CL150: 33782 | CM150: 33782 | CN150: 33782 | CO150: =CN150 -> 33782 | CP150: 146225 | CQ150: 146225 | CR150: 146225 | CS150: 146225 | CT150: 146225 | CU150: 146225 | CV150: 146225 | CW150: 146225 | CX150: 146225 | CY150: 146225 | CZ150: 146225 | DA150: 146225 | DB150: =DA150 -> 146225 | DC150: 206622 | DD150: 206622 | DE150: 206622 | DF150: 206622 | DG150: 206622 | DH150: 206622 | DI150: 206622 | DJ150: 206622 | DK150: 206622 | DL150: 206622 | DM150: 206622 | DN150: 206622 | DO150: =DN150 -> 206622 | DP150: 219639 | DQ150: 219639 | DR150: 219639 | DS150: 219639 | DT150: 219639 | DU150: 219639 | DV150: 219639 | DW150: 219639 | DX150: 219639 | DY150: 219639 | DZ150: 219639 | EA150: 219639 | EB150: =EA150 -> 219639 | EC150: 201180 | ED150: 201180 | EE150: 201180 | EF150: 201180 | EG150: 201180 | EH150: 201180 | EI150: 201180 | EJ150: 201180 | EK150: 201180 | EL150: 201180 | EM150: 201180 | EN150: 201180 | EO150: =EN150 -> 201180 | EP150: 209629 | EQ150: 209629 | ER150: 209629 | ES150: 209629 | ET150: 209629 | EU150: 209629 | EV150: 209629 | EW150: 209629 | EX150: 209629 | EY150: 209629 | EZ150: 209629 | FA150: 209629 | FB150: =FA150 -> 209629 | FC150: 216128 | FD150: 216128 | FE150: 216128 | FF150: 216128 | FG150: 216128 | FH150: 216128 | FI150: 216128 | FO150: =FI150 -> 216128
B151: Total Presupuesto Ley (Subtítulo 29) | C151: =SUM(C119:C150) -> 16323134 | D151: =SUM(D119:D150) -> 16323134 | E151: =SUM(E119:E150) -> 16323134 | F151: =SUM(F119:F150) -> 16323134 | G151: =SUM(G119:G150) -> 16323134 | H151: =SUM(H119:H150) -> 16323134 | I151: =SUM(I119:I150) -> 16323134 | J151: =SUM(J119:J150) -> 16323134 | ... FO151: =SUM(FO119:FO150) -> 68987694
B152: Presupuesto Vigente (Subtítulo 29)
C153: 2014 | P153: 2015 | AC153: 2016 | AP153: 2017 | BC153: 2018 | BP153: 2019 | CC153: 2020 | CP153: 2021 | DC153: 2022 | DP153: 2023 | EC153: 2024 | EP153: 2025 | FC153: 2026
B154: Programa / Entidad | C154: Ene | D154: Feb | E154: Mar | F154: Abr | G154: May | H154: Jun | I154: Jul | J154: Ago | K154: Sep | L154: Oct | M154: Nov | N154: Dic | O154: Total 2014 | P154: Ene | Q154: Feb | R154: Mar | S154: Abr | T154: May | U154: Jun | V154: Jul | W154: Ago | X154: Sep | Y154: Oct | Z154: Nov | AA154: Dic | AB154: Total 2015 | AC154: Ene | AD154: Feb | AE154: Mar | AF154: Abr | AG154: May | AH154: Jun | AI154: Jul | AJ154: Ago | AK154: Sep | AL154: Oct | AM154: Nov | AN154: Dic | AO154: Total 2016 | AP154: Ene | AQ154: Feb | AR154: Mar | AS154: Abr | AT154: May | AU154: Jun | AV154: Jul | AW154: Ago | AX154: Sep | AY154: Oct | AZ154: Nov | BA154: Dic | BB154: Total 2017 | BC154: Ene | BD154: Feb | BE154: Mar | BF154: Abr | BG154: May | BH154: Jun | BI154: Jul | BJ154: Ago | BK154: Sep | BL154: Oct | BM154: Nov | BN154: Dic | BO154: Total 2018 | BP154: Ene | BQ154: Feb | BR154: Mar | BS154: Abr | BT154: May | BU154: Jun | BV154: Jul | BW154: Ago | BX154: Sep | BY154: Oct | BZ154: Nov | CA154: Dic | CB154: Total 2019 | CC154: Ene | CD154: Feb | CE154: Mar | CF154: Abr | CG154: May | CH154: Jun | CI154: Jul | CJ154: Ago | CK154: Sep | CL154: Oct | CM154: Nov | CN154: Dic | CO154: Total 2020 | CP154: Ene | CQ154: Feb | CR154: Mar | CS154: Abr | CT154: May | CU154: Jun | CV154: Jul | CW154: Ago | CX154: Sep | CY154: Oct | CZ154: Nov | DA154: Dic | DB154: Total 2021 | DC154: Ene | DD154: Feb | DE154: Mar | DF154: Abr | DG154: May | DH154: Jun | DI154: Jul | DJ154: Ago | DK154: Sep | DL154: Oct | DM154: Nov | DN154: Dic | DO154: Total 2022 | DP154: Ene | DQ154: Feb | DR154: Mar | DS154: Abr | DT154: May | DU154: Jun | DV154: Jul | DW154: Ago | DX154: Sep | DY154: Oct | DZ154: Nov | EA154: Dic | EB154: Total 2023 | EC154: Ene | ED154: Feb | EE154: Mar | EF154: Abr | EG154: May | EH154: Jun | EI154: Jul | EJ154: Ago | EK154: Sep | EL154: Oct | EM154: Nov | EN154: Dic | EO154: Total 2024 | EP154: Ene | EQ154: Feb | ER154: Mar | ES154: Abr | ET154: May | EU154: Jun | EV154: Jul | EW154: Ago | EX154: Sep | EY154: Oct | EZ154: Nov | FA154: Dic | FB154: Total 2025 | FC154: Ene | FD154: Feb | FE154: Mar | FF154: Abr | FG154: May | FH154: Jun | FI154: Jul | FJ154: Ago | FK154: Sep | FL154: Oct | FM154: Nov | FN154: Dic | FO154: Total 2026
B155: Instituto de Salud Pública | C155: 2783719 | D155: 2783719 | E155: 2783719 | F155: 2783719 | G155: 2783719 | H155: 2844719 | I155: 2844719 | J155: 2844719 | K155: 2844719 | L155: 2844719 | M155: 2844719 | N155: 3512026 | O155: =N155 -> 3512026 | P155: 1773229 | Q155: 1773229 | R155: 1773229 | S155: 1773229 | T155: 1773229 | U155: 1773229 | V155: 1773229 | W155: 1774756 | X155: 2777756 | Y155: 2777756 | Z155: 2777756 | AA155: 2632756 | AB155: =AA155 -> 2632756 | AC155: 2883073 | AD155: 2883073 | AE155: 2883073 | AF155: 2883073 | AG155: 2883073 | AH155: 2883073 | AI155: 2883073 | AJ155: 2883073 | AK155: 2803314 | AL155: 2803314 | AM155: 2803314 | AN155: 2805456 | AO155: =AN155 -> 2805456 | AP155: 2166982 | AQ155: 2166982 | AR155: 2166982 | AS155: 2166982 | AT155: 2166982 | AU155: 2166982 | AV155: 2166982 | AW155: 2166982 | AX155: 2166982 | AY155: 2166982 | AZ155: 2166982 | BA155: 2166982 | BB155: =BA155 -> 2166982 | BC155: 2101547 | BD155: 2101547 | BE155: 2101547 | BF155: 2101547 | BG155: 2101547 | BH155: 2101547 | BI155: 1857122 | BJ155: 1857122 | BK155: 1857122 | BL155: 1857122 | BM155: 1857122 | BN155: 1857122 | BO155: =BN155 -> 1857122 | BP155: 423742 | BQ155: 423742 | BR155: 423742 | BS155: 423742 | BT155: 423742 | BU155: 423742 | BV155: 423742 | BW155: 423742 | BX155: 423742 | BY155: 423742 | BZ155: 423742 | CA155: 423742 | CB155: =CA155 -> 423742 | CC155: 1120574 | CD155: 1120574 | CE155: 1120574 | CF155: 1120574 | CG155: 1120574 | CH155: 1120574 | CI155: 2062273 | CJ155: 2062273 | CK155: 2062273 | CL155: 2062273 | CM155: 2062273 | CN155: 1977173 | CO155: =CN155 -> 1977173 | CP155: 591755 | CQ155: 591755 | CR155: 1238335 | CS155: 1238335 | CT155: 1238335 | CU155: 1238335 | CV155: 1320513 | CW155: 1320513 | CX155: 1320513 | CY155: 1879775 | CZ155: 1879775 | DA155: 1730212 | DB155: =DA155 -> 1730212 | DC155: 357119 | DD155: 357119 | DE155: 357119 | DF155: 357119 | DG155: 357119 | DH155: 357119 | DI155: 357119 | DJ155: 1355672 | DK155: 1355672 | DL155: 1355672 | DM155: 1355672 | DN155: 1320987 | DO155: =DN155 -> 1320987 | DP155: 1836870 | DQ155: 1836870 | DR155: 1836870 | DS155: 2205041 | DT155: 2205041 | DU155: 2205041 | DV155: 2205041 | DW155: 2205041 | DX155: 2205041 | DY155: 2205041 | DZ155: 2205041 | EA155: 2258745 | EB155: =EA155 -> 2258745 | EC155: 1306612 | ED155: 1306612 | EE155: 1306612 | EF155: 1306612 | EG155: 1306612 | EH155: 2289220 | EI155: 2289220 | EJ155: 2289220 | EK155: 2289220 | EL155: 2289220 | EM155: 2074245 | EN155: 1895469 | EO155: =EN155 -> 1895469 | EP155: 2214895 | EQ155: 2214895 | ER155: 2214895 | ES155: 2214895 | ET155: 2214895 | EU155: 2214895 | EV155: 2214895 | EW155: 2214895 | EX155: 2214895 | EY155: 2214895 | EZ155: 1884304 | FA155: 1832451 | FB155: =FA155 -> 1832451 | FC155: 1538024 | FD155: 1538024 | FE155: 1538024 | FF155: 1538024 | FG155: 1491883 | FH155: 1491883 | FI155: 1491883 | FO155: =FI155 -> 1491883
B156: Subsecretaría de Salud Pública | C156: 5390419 | D156: 5390419 | E156: 5390419 | F156: 5390419 | G156: 5390419 | H156: 4639553 | I156: 4373245 | J156: 4373245 | K156: 2983961 | L156: 2983961 | M156: 1957332 | N156: 4490035 | O156: =N156 -> 4490035 | P156: 8769976 | Q156: 8769976 | R156: 8769976 | S156: 8769976 | T156: 9374262 | U156: 9374262 | V156: 9084262 | W156: 8517384 | X156: 8534231 | Y156: 9077511 | Z156: 6293643 | AA156: 10235618 | AB156: =AA156 -> 10235618 | AC156: 6200127 | AD156: 6200127 | AE156: 6200127 | AF156: 6280992 | AG156: 12560604 | AH156: 11877406 | AI156: 10953396 | AJ156: 10953396 | AK156: 10953396 | AL156: 11372146 | AM156: 10040909 | AN156: 10390595 | AO156: =AN156 -> 10390595 | AP156: 9626144 | AQ156: 9626144 | AR156: 9626144 | AS156: 9626144 | AT156: 9716694 | AU156: 8686810 | AV156: 8062338 | AW156: 8082067 | AX156: 6748697 | AY156: 6709409 | AZ156: 9881233 | BA156: 9881233 | BB156: =BA156 -> 9881233 | BC156: 16225714 | BD156: 16230226 | BE156: 16230226 | BF156: 16230226 | BG156: 16230226 | BH156: 16364505 | BI156: 14205776 | BJ156: 7002299 | BK156: 7002299 | BL156: 7025099 | BM156: 7025099 | BN156: 5595616 | BO156: =BN156 -> 5595616 | BP156: 448058 | BQ156: 448058 | BR156: 476672 | BS156: 476672 | BT156: 802682 | BU156: 2746808 | BV156: 2780808 | BW156: 2895219 | BX156: 3222564 | BY156: 3222564 | BZ156: 3188313 | CA156: 3307376 | CB156: =CA156 -> 3307376 | CC156: 8785966 | CD156: 8785966 | CE156: 9197882 | CF156: 9197882 | CG156: 9197882 | CH156: 10506084 | CI156: 10455322 | CJ156: 4691951 | CK156: 4691951 | CL156: 5038786 | CM156: 5553998 | CN156: 5870339 | CO156: =CN156 -> 5870339 | CP156: 880275 | CQ156: 880275 | CR156: 880275 | CS156: 880275 | CT156: 1028494 | CU156: 1082747 | CV156: 1228644 | CW156: 1466373 | CX156: 1466373 | CY156: 1466373 | CZ156: 1466373 | DA156: 1625122 | DB156: =DA156 -> 1625122 | DC156: 82069 | DD156: 98970 | DE156: 100592 | DF156: 100592 | DG156: 100592 | DH156: 130997 | DI156: 714634 | DJ156: 776951 | DK156: 1124385 | DL156: 1144917 | DM156: 1630835 | DN156: 1780600 | DO156: =DN156 -> 1780600 | DP156: 5308686 | DQ156: 5308686 | DR156: 5308686 | DS156: 6009205 | DT156: 6009205 | DU156: 3677155 | DV156: 3688155 | DW156: 3688155 | DX156: 2141510 | DY156: 2141510 | DZ156: 2141510 | EA156: 2141510 | EB156: =EA156 -> 2141510 | EC156: 1027424 | ED156: 1245409 | EE156: 1271649 | EF156: 1271649 | EG156: 1542754 | EH156: 1542754 | EI156: 1588734 | EJ156: 1274158 | EK156: 1274158 | EL156: 795238 | EM156: 795238 | EN156: 795228 | EO156: =EN156 -> 795228 | EP156: 1291061 | EQ156: 1291061 | ER156: 1291061 | ES156: 1242530 | ET156: 1242530 | EU156: 1262530 | EV156: 949932 | EW156: 949932 | EX156: 949932 | EY156: 949932 | EZ156: 949932 | FA156: 949932 | FB156: =FA156 -> 949932 | FC156: 770529 | FD156: 770529 | FE156: 770529 | FF156: 770529 | FG156: 770529 | FH156: 770529 | FI156: 770529 | FO156: =FI156 -> 770529
B157: Inversión Sectorial en Salud | C157: 1091201 | D157: 1091201 | E157: 1091201 | F157: 1091201 | G157: 1091201 | H157: 1091201 | I157: 1091201 | J157: 1091201 | K157: 1249569 | L157: 1249569 | M157: 1249569 | N157: 1293569 | O157: =N157 -> 1293569 | P157: 1232319 | Q157: 1232319 | R157: 1232319 | S157: 1232319 | T157: 1285004 | U157: 1285004 | V157: 1285004 | W157: 1286022 | X157: 1286022 | Y157: 1286022 | Z157: 1293639 | AA157: 1293639 | AB157: =AA157 -> 1293639 | AC157: 1265135 | AD157: 1265135 | AE157: 1265135 | AF157: 1265135 | AG157: 1265135 | AH157: 1265135 | AI157: 1265135 | AJ157: 1265135 | AK157: 1265135 | AL157: 1265135 | AM157: 1265135 | AN157: 1265135 | AO157: =AN157 -> 1265135 | AP157: 1426689 | AQ157: 1426689 | AR157: 1426689 | AS157: 1426689 | AT157: 1426689 | AU157: 1448189 | AV157: 1448189 | AW157: 1448189 | AX157: 1448189 | AY157: 1448189 | AZ157: 1448189 | BA157: 1448189 | BB157: =BA157 -> 1448189 | BC157: 1203274 | BD157: 1203274 | BE157: 1203274 | BF157: 1203274 | BG157: 1203274 | BH157: 1203274 | BI157: 1075406 | BJ157: 1075406 | BK157: 1075406 | BL157: 1075406 | BM157: 1075406 | BN157: 1304981 | BO157: =BN157 -> 1304981 | BP157: 43149437 | BQ157: 40900637 | BR157: 37186258 | BS157: 16686426 | BT157: 9512087 | BU157: 4858061 | BV157: 4411578 | BW157: 3660787 | BX157: 1483185 | BY157: 1483185 | BZ157: 1335249 | CA157: 22400 | CB157: =CA157 -> 22400 | CC157: 58306578 | CD157: 58306578 | CE157: 58306578 | CF157: 61989460 | CG157: 61991243 | CH157: 67791619 | CI157: 91041488 | CJ157: 89152758 | CK157: 88848510 | CL157: 82179240 | CM157: 81973260 | CN157: 94266425 | CO157: =CN157 -> 94266425 | CP157: 42343611 | CQ157: 42343611 | CR157: 36477101 | CS157: 33087429 | CT157: 16629733 | CU157: 14567748 | CV157: 11345253 | CW157: 25437332 | CX157: 25437332 | CY157: 25541647 | CZ157: 24844856 | DA157: 47576599 | DB157: =DA157 -> 47576599 | DC157: 65419989 | DD157: 65419989 | DE157: 65419989 | DF157: 65419989 | DG157: 38468282 | DH157: 23353792 | DI157: 13307054 | DJ157: 1891332 | DK157: 92000 | DL157: 96594 | DM157: 96594 | DN157: 96594 | DO157: =DN157 -> 96594 | DP157: 58041909 | DQ157: 15778601 | DR157: 7029865 | DS157: 8973 | DT157: 8973 | DU157: 209845 | DV157: 209845 | DW157: 5133616 | DX157: 5138210 | DY157: 5138210 | DZ157: 5138210 | EA157: 5138210 | EB157: =EA157 -> 5138210 | EC157: 40737248 | ED157: 40737248 | EE157: 16379569 | EF157: 9016304 | EG157: 632930 | EH157: 563786 | EI157: 361460 | EJ157: 361460 | EK157: 370452 | EL157: 432778 | EM157: 432778 | EN157: 584578 | EO157: =EN157 -> 584578 | EP157: 49234902 | EQ157: 35584662 | ER157: 35584662 | ES157: 1214080 | ET157: 1214080 | EU157: 1214080 | EV157: 1214080 | EW157: 510216 | EX157: 510216 | EY157: 510213 | EZ157: 510213 | FA157: 510213 | FB157: =FA157 -> 510213 | FC157: 51314706 | FD157: 47133923 | FE157: 46119731 | FF157: 46119731 | FG157: 22842836 | FH157: 22842836 | FI157: 0 | FO157: =FI157 -> 0
B158: Servicio de Salud Arica y Parinacota | C158: 152433 | D158: 152433 | E158: 152433 | F158: 152433 | G158: 157473 | H158: 198247 | I158: 284629 | J158: 284629 | K158: 322945 | L158: 322945 | M158: 434310 | N158: 469310 | O158: =N158 -> 469310 | P158: 157006 | Q158: 157006 | R158: 189966 | S158: 714795 | T158: 714795 | U158: 714795 | V158: 714795 | W158: 822744 | X158: 822744 | Y158: 831729 | Z158: 912455 | AA158: 912455 | AB158: =AA158 -> 912455 | AC158: 162972 | AD158: 411972 | AE158: 446185 | AF158: 446185 | AG158: 446185 | AH158: 449818 | AI158: 449818 | AJ158: 449818 | AK158: 449818 | AL158: 449818 | AM158: 453876 | AN158: 446073 | AO158: =AN158 -> 446073 | AP158: 167861 | AQ158: 167861 | AR158: 167861 | AS158: 167861 | AT158: 167861 | AU158: 289889 | AV158: 289889 | AW158: 289889 | AX158: 329889 | AY158: 329889 | AZ158: 409789 | BA158: 409789 | BB158: =BA158 -> 409789 | BC158: 172225 | BD158: 172225 | BE158: 172225 | BF158: 172225 | BG158: 172225 | BH158: 172225 | BI158: 156261 | BJ158: 258311 | BK158: 1157977 | BL158: 1678875 | BM158: 1694675 | BN158: 1741199 | BO158: =BN158 -> 1741199 | BP158: 0 | BQ158: 0 | BR158: 0 | BS158: 293000 | BT158: 310936 | BU158: 647572 | BV158: 673177 | BW158: 837670 | BX158: 2582986 | BY158: 2582986 | BZ158: 2582986 | CA158: 2582986 | CB158: =CA158 -> 2582986 | CC158: 33183 | CD158: 33183 | CE158: 33183 | CF158: 86136 | CG158: 91691 | CH158: 91691 | CI158: 91691 | CJ158: 264907 | CK158: 285427 | CL158: 285427 | CM158: 407405 | CN158: 407405 | CO158: =CN158 -> 407405 | CP158: 142663 | CQ158: 142663 | CR158: 342572 | CS158: 342572 | CT158: 342572 | CU158: 492822 | CV158: 492822 | CW158: 532822 | CX158: 532822 | CY158: 538910 | CZ158: 538910 | DA158: 538910 | DB158: =DA158 -> 538910 | DC158: 193368 | DD158: 193368 | DE158: 193368 | DF158: 193368 | DG158: 193368 | DH158: 193368 | DI158: 274350 | DJ158: 378460 | DK158: 617826 | DL158: 617826 | DM158: 617826 | DN158: 617826 | DO158: =DN158 -> 617826 | DP158: 205550 | DQ158: 1400894 | DR158: 1503541 | DS158: 1506041 | DT158: 1506041 | DU158: 1533939 | DV158: 1623346 | DW158: 1634008 | DX158: 1636413 | DY158: 1636413 | DZ158: 1636413 | EA158: 1636413 | EB158: =EA158 -> 1636413 | EC158: 188275 | ED158: 188275 | EE158: 472951 | EF158: 479477 | EG158: 589433 | EH158: 589433 | EI158: 589433 | EJ158: 589433 | EK158: 589433 | EL158: 596839 | EM158: 596839 | EN158: 551164 | EO158: =EN158 -> 551164 | EP158: 196182 | EQ158: 196182 | ER158: 196182 | ES158: 1053558 | ET158: 1056570 | EU158: 1056570 | EV158: 1056570 | EW158: 1056570 | EX158: 1056570 | EY158: 1056570 | EZ158: 1056570 | FA158: 900167 | FB158: =FA158 -> 900167 | FC158: 202264 | FD158: 202264 | FE158: 209064 | FF158: 209064 | FG158: 209064 | FH158: 209064 | FI158: 291028 | FO158: =FI158 -> 291028
B159: Servicio de Salud Tarapacá | C159: 215595 | D159: 281045 | E159: 281045 | F159: 281045 | G159: 283925 | H159: 285778 | I159: 285778 | J159: 285778 | K159: 303211 | L159: 304001 | M159: 785443 | N159: 820443 | O159: =N159 -> 820443 | P159: 222063 | Q159: 222063 | R159: 255023 | S159: 255023 | T159: 255023 | U159: 255023 | V159: 255023 | W159: 593023 | X159: 593023 | Y159: 597843 | Z159: 1382078 | AA159: 651979 | AB159: =AA159 -> 651979 | AC159: 230501 | AD159: 479501 | AE159: 479501 | AF159: 479501 | AG159: 479501 | AH159: 479501 | AI159: 538938 | AJ159: 538938 | AK159: 538938 | AL159: 539288 | AM159: 549934 | AN159: 549934 | AO159: =AN159 -> 549934 | AP159: 237416 | AQ159: 237416 | AR159: 237416 | AS159: 237416 | AT159: 237416 | AU159: 237416 | AV159: 237416 | AW159: 237416 | AX159: 280416 | AY159: 305916 | AZ159: 308916 | BA159: 486119 | BB159: =BA159 -> 486119 | BC159: 243589 | BD159: 243589 | BE159: 243589 | BF159: 243589 | BG159: 243589 | BH159: 243589 | BI159: 218756 | BJ159: 218756 | BK159: 401508 | BL159: 401508 | BM159: 405258 | BN159: 791175 | BO159: =BN159 -> 791175 | BP159: 0 | BQ159: 0 | BR159: 0 | BS159: 325443 | BT159: 341580 | BU159: 482635 | BV159: 517085 | BW159: 533585 | BX159: 1425019 | BY159: 1425019 | BZ159: 1449866 | CA159: 1459505 | CB159: =CA159 -> 1459505 | CC159: 42579 | CD159: 42579 | CE159: 42579 | CF159: 165724 | CG159: 165724 | CH159: 487252 | CI159: 487252 | CJ159: 522821 | CK159: 525193 | CL159: 668728 | CM159: 668728 | CN159: 668728 | CO159: =CN159 -> 668728 | CP159: 185100 | CQ159: 185100 | CR159: 185100 | CS159: 185100 | CT159: 562274 | CU159: 562274 | CV159: 562274 | CW159: 1182885 | CX159: 1182885 | CY159: 1230135 | CZ159: 1286164 | DA159: 1229189 | DB159: =DA159 -> 1229189 | DC159: 251177 | DD159: 251177 | DE159: 251177 | DF159: 251177 | DG159: 251177 | DH159: 251177 | DI159: 259177 | DJ159: 259177 | DK159: 898004 | DL159: 898004 | DM159: 898004 | DN159: 898004 | DO159: =DN159 -> 898004 | DP159: 267001 | DQ159: 2503017 | DR159: 2946390 | DS159: 4135083 | DT159: 4135083 | DU159: 4169088 | DV159: 4185134 | DW159: 4239969 | DX159: 4240239 | DY159: 4240239 | DZ159: 4240239 | EA159: 4177362 | EB159: =EA159 -> 4177362 | EC159: 244561 | ED159: 244561 | EE159: 790722 | EF159: 790722 | EG159: 790722 | EH159: 790722 | EI159: 790722 | EJ159: 790722 | EK159: 790722 | EL159: 833422 | EM159: 833422 | EN159: 626430 | EO159: =EN159 -> 626430 | EP159: 254832 | EQ159: 691438 | ER159: 691438 | ES159: 701336 | ET159: 704336 | EU159: 704336 | EV159: 704336 | EW159: 893824 | EX159: 893824 | EY159: 893824 | EZ159: 893824 | FA159: 734910 | FB159: =FA159 -> 734910 | FC159: 262732 | FD159: 262732 | FE159: 262732 | FF159: 262732 | FG159: 262732 | FH159: 262732 | FI159: 262732 | FO159: =FI159 -> 262732
B160: Servicio de Salud Antofagasta | C160: 202258 | D160: 202258 | E160: 202258 | F160: 202258 | G160: 228878 | H160: 231530 | I160: 231530 | J160: 231530 | K160: 283829 | L160: 286329 | M160: 789430 | N160: 845945 | O160: =N160 -> 845945 | P160: 208326 | Q160: 208326 | R160: 241286 | S160: 1249286 | T160: 1383844 | U160: 1383844 | V160: 1383844 | W160: 1472973 | X160: 1472973 | Y160: 1858773 | Z160: 2114923 | AA160: 2175312 | AB160: =AA160 -> 2175312 | AC160: 216242 | AD160: 465242 | AE160: 602092 | AF160: 602092 | AG160: 602092 | AH160: 605725 | AI160: 702318 | AJ160: 702318 | AK160: 702318 | AL160: 703218 | AM160: 708198 | AN160: 710382 | AO160: =AN160 -> 710382 | AP160: 222729 | AQ160: 222729 | AR160: 222729 | AS160: 222729 | AT160: 222729 | AU160: 286345 | AV160: 286345 | AW160: 286345 | AX160: 366345 | AY160: 366345 | AZ160: 532922 | BA160: 532922 | BB160: =BA160 -> 532922 | BC160: 228520 | BD160: 228520 | BE160: 228520 | BF160: 228520 | BG160: 228520 | BH160: 228520 | BI160: 205488 | BJ160: 256488 | BK160: 256488 | BL160: 256488 | BM160: 257157 | BN160: 304886 | BO160: =BN160 -> 304886 | BP160: 0 | BQ160: 0 | BR160: 0 | BS160: 170500 | BT160: 203366 | BU160: 219882 | BV160: 220551 | BW160: 248551 | BX160: 353029 | BY160: 353029 | BZ160: 353029 | CA160: 353029 | CB160: =CA160 -> 353029 | CC160: 80375 | CD160: 80375 | CE160: 80375 | CF160: 206164 | CG160: 207764 | CH160: 2511459 | CI160: 2511459 | CJ160: 2539995 | CK160: 4808346 | CL160: 4808346 | CM160: 4808346 | CN160: 4808346 | CO160: =CN160 -> 4808346 | CP160: 376018 | CQ160: 376018 | CR160: 376018 | CS160: 376018 | CT160: 702053 | CU160: 702053 | CV160: 702053 | CW160: 702453 | CX160: 702453 | CY160: 840053 | CZ160: 815986 | DA160: 699986 | DB160: =DA160 -> 699986 | DC160: 511002 | DD160: 511002 | DE160: 511002 | DF160: 511002 | DG160: 511002 | DH160: 511002 | DI160: 512402 | DJ160: 581505 | DK160: 661994 | DL160: 661994 | DM160: 661994 | DN160: 661994 | DO160: =DN160 -> 661994 | DP160: 543195 | DQ160: 700855 | DR160: 1086746 | DS160: 1089246 | DT160: 1089246 | DU160: 1140868 | DV160: 1167825 | DW160: 1189150 | DX160: 1455859 | DY160: 1455859 | DZ160: 1455859 | EA160: 1455859 | EB160: =EA160 -> 1455859 | EC160: 497544 | ED160: 497544 | EE160: 1531885 | EF160: 1548211 | EG160: 1878079 | EH160: 1878079 | EI160: 1878079 | EJ160: 1878079 | EK160: 1878079 | EL160: 1990514 | EM160: 1990514 | EN160: 1681782 | EO160: =EN160 -> 1681782 | EP160: 518441 | EQ160: 751685 | ER160: 751685 | ES160: 1489199 | ET160: 1548925 | EU160: 1548925 | EV160: 1548925 | EW160: 1548925 | EX160: 1548925 | EY160: 1548925 | EZ160: 1548925 | FA160: 1519802 | FB160: =FA160 -> 1519802 | FC160: 534512 | FD160: 534512 | FE160: 534512 | FF160: 534512 | FG160: 534512 | FH160: 534512 | FI160: 558518 | FO160: =FI160 -> 558518
B161: Servicio de Salud Atacama | C161: 118004 | D161: 118004 | E161: 118004 | F161: 118004 | G161: 129524 | H161: 129524 | I161: 129524 | J161: 129524 | K161: 201706 | L161: 201706 | M161: 547437 | N161: 1536899 | O161: =N161 -> 1536899 | P161: 121544 | Q161: 121544 | R161: 888504 | S161: 888504 | T161: 1197502 | U161: 1197502 | V161: 1197502 | W161: 1252114 | X161: 1252114 | Y161: 1272814 | Z161: 1279060 | AA161: 1435366 | AB161: =AA161 -> 1435366 | AC161: 126163 | AD161: 345163 | AE161: 345163 | AF161: 345163 | AG161: 345163 | AH161: 373845 | AI161: 399429 | AJ161: 399429 | AK161: 399429 | AL161: 399429 | AM161: 399429 | AN161: 558234 | AO161: =AN161 -> 558234 | AP161: 129948 | AQ161: 129948 | AR161: 129948 | AS161: 129948 | AT161: 129948 | AU161: 216532 | AV161: 216532 | AW161: 216532 | AX161: 216532 | AY161: 218664 | AZ161: 371688 | BA161: 371688 | BB161: =BA161 -> 371688 | BC161: 133327 | BD161: 133327 | BE161: 133327 | BF161: 133327 | BG161: 133327 | BH161: 133327 | BI161: 119735 | BJ161: 584719 | BK161: 2034074 | BL161: 2034074 | BM161: 2034909 | BN161: 2227011 | BO161: =BN161 -> 2227011 | BP161: 0 | BQ161: 0 | BR161: 202703 | BS161: 373566 | BT161: 390322 | BU161: 390322 | BV161: 399257 | BW161: 595194 | BX161: 852287 | BY161: 852287 | BZ161: 852287 | CA161: 796938 | CB161: =CA161 -> 796938 | CC161: 42543 | CD161: 42543 | CE161: 42543 | CF161: 160258 | CG161: 160258 | CH161: 1123678 | CI161: 1123678 | CJ161: 1185705 | CK161: 1194101 | CL161: 1353101 | CM161: 1353101 | CN161: 1353101 | CO161: =CN161 -> 1353101 | CP161: 183254 | CQ161: 183254 | CR161: 183254 | CS161: 183254 | CT161: 495257 | CU161: 495257 | CV161: 597573 | CW161: 1142614 | CX161: 1142614 | CY161: 1190867 | CZ161: 1190867 | DA161: 1190867 | DB161: =DA161 -> 1190867 | DC161: 248523 | DD161: 248523 | DE161: 248523 | DF161: 248523 | DG161: 248523 | DH161: 307416 | DI161: 973578 | DJ161: 1309656 | DK161: 1663015 | DL161: 1663015 | DM161: 1663015 | DN161: 1663015 | DO161: =DN161 -> 1663015 | DP161: 264180 | DQ161: 535594 | DR161: 817447 | DS161: 819947 | DT161: 819947 | DU161: 866739 | DV161: 876354 | DW161: 905295 | DX161: 905565 | DY161: 905565 | DZ161: 905565 | EA161: 905565 | EB161: =EA161 -> 905565 | EC161: 241977 | ED161: 241977 | EE161: 450227 | EF161: 572077 | EG161: 682033 | EH161: 682033 | EI161: 682033 | EJ161: 707505 | EK161: 780680 | EL161: 792240 | EM161: 792240 | EN161: 763247 | EO161: =EN161 -> 763247 | EP161: 252140 | EQ161: 258131 | ER161: 258131 | ES161: 1148885 | ET161: 1152842 | EU161: 1152842 | EV161: 1152842 | EW161: 1152842 | EX161: 1152842 | EY161: 1152842 | EZ161: 1152842 | FA161: 1142868 | FB161: =FA161 -> 1142868 | FC161: 259957 | FD161: 259957 | FE161: 259957 | FF161: 259957 | FG161: 259957 | FH161: 259957 | FI161: 259957 | FO161: =FI161 -> 259957
B162: Servicio de Salud Coquimbo | C162: 288212 | D162: 288212 | E162: 288212 | F162: 288212 | G162: 308422 | H162: 331266 | I162: 331266 | J162: 331266 | K162: 438314 | L162: 440761 | M162: 1740346 | N162: 1798442 | O162: =N162 -> 1798442 | P162: 296858 | Q162: 296858 | R162: 535738 | S162: 1486738 | T162: 2479079 | U162: 2762693 | V162: 2772693 | W162: 2951113 | X162: 2951113 | Y162: 3650357 | Z162: 4731425 | AA162: 5785975 | AB162: =AA162 -> 5785975 | AC162: 308139 | AD162: 658139 | AE162: 658139 | AF162: 658139 | AG162: 658139 | AH162: 661772 | AI162: 727222 | AJ162: 727222 | AK162: 2362818 | AL162: 2362818 | AM162: 2369188 | AN162: 2438823 | AO162: =AN162 -> 2438823 | AP162: 317383 | AQ162: 317383 | AR162: 317383 | AS162: 317383 | AT162: 317383 | AU162: 317939 | AV162: 395652 | AW162: 395652 | AX162: 504682 | AY162: 2721429 | AZ162: 2733429 | BA162: 3295084 | BB162: =BA162 -> 3295084 | BC162: 325635 | BD162: 325635 | BE162: 325635 | BF162: 325635 | BG162: 325635 | BH162: 468813 | BI162: 435614 | BJ162: 435614 | BK162: 4325881 | BL162: 4325881 | BM162: 4325881 | BN162: 4387211 | BO162: =BN162 -> 4387211 | BP162: 0 | BQ162: 0 | BR162: 190709 | BS162: 502014 | BT162: 540681 | BU162: 540681 | BV162: 567681 | BW162: 604181 | BX162: 835174 | BY162: 835174 | BZ162: 835174 | CA162: 910046 | CB162: =CA162 -> 910046 | CC162: 93134 | CD162: 93134 | CE162: 93134 | CF162: 260800 | CG162: 260800 | CH162: 1802849 | CI162: 1802849 | CJ162: 2174431 | CK162: 2208531 | CL162: 2534206 | CM162: 2534206 | CN162: 2534206 | CO162: =CN162 -> 2534206 | CP162: 413232 | CQ162: 413232 | CR162: 413232 | CS162: 413232 | CT162: 967942 | CU162: 967942 | CV162: 967942 | CW162: 986827 | CX162: 986827 | CY162: 1358595 | CZ162: 1412916 | DA162: 1374811 | DB162: =DA162 -> 1374811 | DC162: 561294 | DD162: 561294 | DE162: 561294 | DF162: 561294 | DG162: 561294 | DH162: 561294 | DI162: 583294 | DJ162: 1073046 | DK162: 2257513 | DL162: 2257513 | DM162: 2257513 | DN162: 2257513 | DO162: =DN162 -> 2257513 | DP162: 596656 | DQ162: 1360772 | DR162: 1373900 | DS162: 1376400 | DT162: 1376400 | DU162: 1545847 | DV162: 1590893 | DW162: 1638112 | DX162: 1759862 | DY162: 1759862 | DZ162: 1759862 | EA162: 1822739 | EB162: =EA162 -> 1822739 | EC162: 546510 | ED162: 546510 | EE162: 1678086 | EF162: 1685743 | EG162: 1905655 | EH162: 1905655 | EI162: 1905655 | EJ162: 1905655 | EK162: 1819245 | EL162: 1907160 | EM162: 1907160 | EN162: 1400867 | EO162: =EN162 -> 1400867 | EP162: 569463 | EQ162: 1050249 | ER162: 1050249 | ES162: 3006178 | ET162: 3006178 | EU162: 3006178 | EV162: 3006178 | EW162: 3006178 | EX162: 3006198 | EY162: 3006198 | EZ162: 3006198 | FA162: 2534859 | FB162: =FA162 -> 2534859 | FC162: 587116 | FD162: 587116 | FE162: 587534 | FF162: 587534 | FG162: 587534 | FH162: 587534 | FI162: 1151154 | FO162: =FI162 -> 1151154
B163: Servicio de Salud Valparaíso - San Antonio | C163: 346611 | D163: 346611 | E163: 346611 | F163: 346611 | G163: 369281 | H163: 507597 | I163: 507597 | J163: 507597 | K163: 542463 | L163: 553880 | M163: 1337688 | N163: 1372688 | O163: =N163 -> 1372688 | P163: 357009 | Q163: 357009 | R163: 422929 | S163: 1656436 | T163: 1734569 | U163: 3498338 | V163: 3508338 | W163: 3598365 | X163: 3598365 | Y163: 4356365 | Z163: 5152610 | AA163: 5990325 | AB163: =AA163 -> 5990325 | AC163: 370575 | AD163: 662575 | AE163: 662575 | AF163: 662575 | AG163: 662575 | AH163: 691255 | AI163: 739524 | AJ163: 736459 | AK163: 736459 | AL163: 742007 | AM163: 818464 | AN163: 853395 | AO163: =AN163 -> 853395 | AP163: 381692 | AQ163: 381692 | AR163: 381692 | AS163: 381692 | AT163: 381692 | AU163: 458591 | AV163: 472611 | AW163: 472611 | AX163: 2975611 | AY163: 3672449 | AZ163: 3780433 | BA163: 3531734 | BB163: =BA163 -> 3531734 | BC163: 391616 | BD163: 391616 | BE163: 391616 | BF163: 391616 | BG163: 391616 | BH163: 698625 | BI163: 659943 | BJ163: 694943 | BK163: 6955892 | BL163: 6955892 | BM163: 6973152 | BN163: 7815128 | BO163: =BN163 -> 7815128 | BP163: 0 | BQ163: 0 | BR163: 0 | BS163: 1020120 | BT163: 1812566 | BU163: 1812566 | BV163: 1898034 | BW163: 1939534 | BX163: 3445236 | BY163: 3445236 | BZ163: 3445236 | CA163: 3445236 | CB163: =CA163 -> 3445236 | CC163: 79142 | CD163: 79142 | CE163: 79142 | CF163: 283165 | CG163: 306594 | CH163: 597410 | CI163: 597410 | CJ163: 895498 | CK163: 1007299 | CL163: 1340974 | CM163: 1340974 | CN163: 1340974 | CO163: =CN163 -> 1340974 | CP163: 333094 | CQ163: 333094 | CR163: 333094 | CS163: 333094 | CT163: 712298 | CU163: 733172 | CV163: 733172 | CW163: 1705224 | CX163: 1705224 | CY163: 1797398 | CZ163: 1830576 | DA163: 1625578 | DB163: =DA163 -> 1625578 | DC163: 451628 | DD163: 451628 | DE163: 451628 | DF163: 451628 | DG163: 451628 | DH163: 451628 | DI163: 633034 | DJ163: 1541642 | DK163: 3049061 | DL163: 3049061 | DM163: 3049061 | DN163: 2868690 | DO163: =DN163 -> 2868690 | DP163: 480081 | DQ163: 1529959 | DR163: 1529959 | DS163: 1532459 | DT163: 1532459 | DU163: 1690049 | DV163: 1747814 | DW163: 1782847 | DX163: 3285806 | DY163: 3285806 | DZ163: 3285806 | EA163: 3285806 | EB163: =EA163 -> 3285806 | EC163: 439733 | ED163: 439733 | EE163: 2258764 | EF163: 2680186 | EG163: 2680186 | EH163: 2680186 | EI163: 2680186 | EJ163: 2680186 | EK163: 2680186 | EL163: 2739894 | EM163: 2739894 | EN163: 2727496 | EO163: =EN163 -> 2727496 | EP163: 458202 | EQ163: 790158 | ER163: 790158 | ES163: 1671529 | ET163: 1721513 | EU163: 1721513 | EV163: 1776874 | EW163: 1776874 | EX163: 1776874 | EY163: 1776874 | EZ163: 1776874 | FA163: 1708295 | FB163: =FA163 -> 1708295 | FC163: 472406 | FD163: 472406 | FE163: 472406 | FF163: 472406 | FG163: 472406 | FH163: 472406 | FI163: 1260420 | FO163: =FI163 -> 1260420
B164: Servicio de Salud Viña del Mar - Quillota | C164: 357298 | D164: 357298 | E164: 357298 | F164: 357298 | G164: 378198 | H164: 415690 | I164: 415690 | J164: 415690 | K164: 502854 | L164: 502854 | M164: 4809106 | N164: 4838921 | O164: =N164 -> 4838921 | P164: 368017 | Q164: 368017 | R164: 1468937 | S164: 1924619 | T164: 2340414 | U164: 2340414 | V164: 2350414 | W164: 2429212 | X164: 2429212 | Y164: 2629212 | Z164: 4739879 | AA164: 4151755 | AB164: =AA164 -> 4151755 | AC164: 382002 | AD164: 732002 | AE164: 800427 | AF164: 800427 | AG164: 800427 | AH164: 804060 | AI164: 804060 | AJ164: 804060 | AK164: 804060 | AL164: 804060 | AM164: 1479556 | AN164: 1479556 | AO164: =AN164 -> 1479556 | AP164: 393462 | AQ164: 393462 | AR164: 393462 | AS164: 393462 | AT164: 393462 | AU164: 393462 | AV164: 408240 | AW164: 408240 | AX164: 488240 | AY164: 488240 | AZ164: 488240 | BA164: 488240 | BB164: =BA164 -> 488240 | BC164: 403692 | BD164: 403692 | BE164: 403692 | BF164: 403692 | BG164: 403692 | BH164: 403692 | BI164: 362535 | BJ164: 2140811 | BK164: 2769757 | BL164: 2769757 | BM164: 2874001 | BN164: 3232343 | BO164: =BN164 -> 3232343 | BP164: 0 | BQ164: 0 | BR164: 0 | BS164: 1947580 | BT164: 1992675 | BU164: 1992675 | BV164: 2022175 | BW164: 2096747 | BX164: 3111252 | BY164: 3111252 | BZ164: 3111252 | CA164: 3111252 | CB164: =CA164 -> 3111252 | CC164: 108890 | CD164: 108890 | CE164: 108890 | CF164: 240268 | CG164: 240268 | CH164: 2072980 | CI164: 2072980 | CJ164: 2102480 | CK164: 2348826 | CL164: 2460522 | CM164: 2460522 | CN164: 2460522 | CO164: =CN164 -> 2460522 | CP164: 476890 | CQ164: 476890 | CR164: 476890 | CS164: 476890 | CT164: 595266 | CU164: 597646 | CV164: 597646 | CW164: 601846 | CX164: 601846 | CY164: 601846 | CZ164: 601846 | DA164: 599466 | DB164: =DA164 -> 599466 | DC164: 651404 | DD164: 651404 | DE164: 651404 | DF164: 651404 | DG164: 651404 | DH164: 651404 | DI164: 678104 | DJ164: 2366467 | DK164: 2603136 | DL164: 2603136 | DM164: 2603136 | DN164: 2662738 | DO164: =DN164 -> 2662738 | DP164: 692443 | DQ164: 1304443 | DR164: 1317571 | DS164: 1320071 | DT164: 1320071 | DU164: 1604204 | DV164: 1637027 | DW164: 1699478 | DX164: 1700288 | DY164: 1700288 | DZ164: 1700288 | EA164: 1700288 | EB164: =EA164 -> 1700288 | EC164: 634247 | ED164: 634247 | EE164: 719425 | EF164: 1680204 | EG164: 2120028 | EH164: 2120028 | EI164: 2120028 | EJ164: 2187472 | EK164: 2187472 | EL164: 2277412 | EM164: 2277412 | EN164: 1758674 | EO164: =EN164 -> 1758674 | EP164: 660885 | EQ164: 1107600 | ER164: 1107600 | ES164: 1677844 | ET164: 1697444 | EU164: 1697444 | EV164: 1752781 | EW164: 1752781 | EX164: 1752781 | EY164: 1752781 | EZ164: 1752781 | FA164: 1748472 | FB164: =FA164 -> 1748472 | FC164: 681372 | FD164: 794731 | FE164: 794731 | FF164: 794731 | FG164: 794731 | FH164: 794731 | FI164: 901891 | FO164: =FI164 -> 901891
B165: Servicio de Salud Aconcagua | C165: 286402 | D165: 479302 | E165: 479302 | F165: 479302 | G165: 498042 | H165: 498042 | I165: 498042 | J165: 498042 | K165: 541624 | L165: 541624 | M165: 999624 | N165: 1019624 | O165: =N165 -> 1019624 | P165: 294994 | Q165: 294994 | R165: 765954 | S165: 1289744 | T165: 1289744 | U165: 1289744 | V165: 1390653 | W165: 1521649 | X165: 1521649 | Y165: 1909649 | Z165: 2103410 | AA165: 3096056 | AB165: =AA165 -> 3096056 | AC165: 306204 | AD165: 598204 | AE165: 598204 | AF165: 598204 | AG165: 598204 | AH165: 601837 | AI165: 601837 | AJ165: 601837 | AK165: 601837 | AL165: 603067 | AM165: 1260877 | AN165: 1305751 | AO165: =AN165 -> 1305751 | AP165: 315390 | AQ165: 315390 | AR165: 315390 | AS165: 315390 | AT165: 315390 | AU165: 403925 | AV165: 449913 | AW165: 449913 | AX165: 489913 | AY165: 489913 | AZ165: 489913 | BA165: 489913 | BB165: =BA165 -> 489913 | BC165: 323590 | BD165: 323590 | BE165: 323590 | BF165: 323590 | BG165: 323590 | BH165: 323590 | BI165: 290957 | BJ165: 290957 | BK165: 5745197 | BL165: 5745197 | BM165: 5758697 | BN165: 11894614 | BO165: =BN165 -> 11894614 | BP165: 0 | BQ165: 0 | BR165: 186802 | BS165: 199497 | BT165: 214396 | BU165: 214396 | BV165: 227896 | BW165: 250396 | BX165: 1166577 | BY165: 1166577 | BZ165: 1166577 | CA165: 1166577 | CB165: =CA165 -> 1166577 | CC165: 40833 | CD165: 40833 | CE165: 40833 | CF165: 77177 | CG165: 77177 | CH165: 77177 | CI165: 77177 | CJ165: 119767 | CK165: 143338 | CL165: 447478 | CM165: 653458 | CN165: 653458 | CO165: =CN165 -> 653458 | CP165: 180349 | CQ165: 180349 | CR165: 180349 | CS165: 180349 | CT165: 1497360 | CU165: 1497360 | CV165: 1497360 | CW165: 1497360 | CX165: 1497360 | CY165: 1497360 | CZ165: 1497360 | DA165: 1468684 | DB165: =DA165 -> 1468684 | DC165: 250008 | DD165: 250008 | DE165: 250008 | DF165: 250008 | DG165: 566644 | DH165: 649349 | DI165: 1567813 | DJ165: 1801330 | DK165: 1977482 | DL165: 1977482 | DM165: 1977482 | DN165: 1977482 | DO165: =DN165 -> 1977482 | DP165: 265759 | DQ165: 1162039 | DR165: 1162039 | DS165: 1164539 | DT165: 1164539 | DU165: 1209847 | DV165: 1220286 | DW165: 1235518 | DX165: 1269271 | DY165: 1269271 | DZ165: 1269271 | EA165: 1269271 | EB165: =EA165 -> 1269271 | EC165: 243422 | ED165: 243422 | EE165: 432149 | EF165: 432149 | EG165: 802465 | EH165: 802465 | EI165: 802465 | EJ165: 802465 | EK165: 802465 | EL165: 809206 | EM165: 809206 | EN165: 801033 | EO165: =EN165 -> 801033 | EP165: 253646 | EQ165: 267319 | ER165: 267319 | ES165: 699830 | ET165: 699830 | EU165: 699830 | EV165: 699830 | EW165: 1036337 | EX165: 1036337 | EY165: 1036337 | EZ165: 1036337 | FA165: 1036337 | FB165: =FA165 -> 1036337 | FC165: 261509 | FD165: 488227 | FE165: 488227 | FF165: 488227 | FG165: 488227 | FH165: 488227 | FI165: 488227 | FO165: =FI165 -> 488227
B166: Servicio de Salud O'Higgins | C166: 282051 | D166: 282051 | E166: 282051 | F166: 282051 | G166: 310501 | H166: 368181 | I166: 368181 | J166: 368181 | K166: 420480 | L166: 420480 | M166: 963360 | N166: 998360 | O166: =N166 -> 998360 | P166: 290513 | Q166: 290513 | R166: 746393 | S166: 746393 | T166: 746393 | U166: 1553571 | V166: 1553571 | W166: 1645861 | X166: 1645861 | Y166: 1965706 | Z166: 2089601 | AA166: 2740115 | AB166: =AA166 -> 2740115 | AC166: 301552 | AD166: 593552 | AE166: 593552 | AF166: 593552 | AG166: 593552 | AH166: 597185 | AI166: 680309 | AJ166: 680309 | AK166: 680309 | AL166: 684004 | AM166: 684004 | AN166: 696901 | AO166: =AN166 -> 696901 | AP166: 310599 | AQ166: 310599 | AR166: 310599 | AS166: 310599 | AT166: 310599 | AU166: 380208 | AV166: 380208 | AW166: 380208 | AX166: 463208 | AY166: 474208 | AZ166: 474208 | BA166: 474208 | BB166: =BA166 -> 474208 | BC166: 318675 | BD166: 318675 | BE166: 318675 | BF166: 318675 | BG166: 318675 | BH166: 318675 | BI166: 290386 | BJ166: 800891 | BK166: 2145513 | BL166: 2145513 | BM166: 3592285 | BN166: 4402128 | BO166: =BN166 -> 4402128 | BP166: 0 | BQ166: 0 | BR166: 376230 | BS166: 743954 | BT166: 788930 | BU166: 788930 | BV166: 795531 | BW166: 2455542 | BX166: 5817087 | BY166: 5817087 | BZ166: 5849872 | CA166: 5849872 | CB166: =CA166 -> 5849872 | CC166: 103121 | CD166: 103121 | CE166: 3861902 | CF166: 4258106 | CG166: 4265106 | CH166: 4265106 | CI166: 4265106 | CJ166: 4327108 | CK166: 4336217 | CL166: 4579217 | CM166: 4579217 | CN166: 4579217 | CO166: =CN166 -> 4579217 | CP166: 444000 | CQ166: 444000 | CR166: 444000 | CS166: 444000 | CT166: 621564 | CU166: 621564 | CV166: 621564 | CW166: 679564 | CX166: 679564 | CY166: 1147582 | CZ166: 1773611 | DA166: 1773611 | DB166: =DA166 -> 1773611 | DC166: 609864 | DD166: 609864 | DE166: 609864 | DF166: 609864 | DG166: 609864 | DH166: 609864 | DI166: 1164367 | DJ166: 1164367 | DK166: 2633267 | DL166: 2633267 | DM166: 2633267 | DN166: 2692869 | DO166: =DN166 -> 2692869 | DP166: 648285 | DQ166: 1987915 | DR166: 2001043 | DS166: 3362141 | DT166: 3362141 | DU166: 3606498 | DV166: 3645098 | DW166: 3716688 | DX166: 3716958 | DY166: 3716958 | DZ166: 3716958 | EA166: 3716958 | EB166: =EA166 -> 3716958 | EC166: 593801 | ED166: 593801 | EE166: 1112927 | EF166: 1909166 | EG166: 1909166 | EH166: 1909166 | EI166: 1909166 | EJ166: 1909166 | EK166: 1909166 | EL166: 2022987 | EM166: 2022987 | EN166: 1196010 | EO166: =EN166 -> 1196010 | EP166: 618741 | EQ166: 1194219 | ER166: 1194219 | ES166: 1906958 | ET166: 1933308 | EU166: 1933308 | EV166: 1933308 | EW166: 1933308 | EX166: 1933308 | EY166: 1933308 | EZ166: 1933308 | FA166: 1757241 | FB166: =FA166 -> 1757241 | FC166: 637922 | FD166: 751281 | FE166: 751281 | FF166: 751281 | FG166: 751281 | FH166: 751281 | FI166: 991805 | FO166: =FI166 -> 991805
... B186: Servicio de Salud Chiloé | C186: 39141 | D186: 93561 | E186: 93561 | F186: 93561 | G186: 113346 | H186: 114442 | I186: 305845 | J186: 305845 | K186: 349427 | L186: 349427 | M186: 409940 | N186: 744396 | O186: =N186 -> 744396 | P186: 40315 | Q186: 217601 | R186: 250561 | S186: 544482 | T186: 1767825 | U186: 2042220 | V186: 2340491 | W186: 2340491 | X186: 2340491 | Y186: 3991672 | Z186: 4199071 | AA186: 5158719 | AB186: =AA186 -> 5158719 | AC186: 41847 | AD186: 217847 | AE186: 217847 | AF186: 217847 | AG186: 217847 | AH186: 217847 | AI186: 217847 | AJ186: 217847 | AK186: 217847 | AL186: 217847 | AM186: 272528 | AN186: 2120843 | AO186: =AN186 -> 2120843 | AP186: 43102 | AQ186: 43102 | AR186: 43102 | AS186: 43102 | AT186: 43102 | AU186: 43102 | AV186: 43102 | AW186: 43102 | AX186: 46102 | AY186: 46102 | AZ186: 46102 | BA186: 46102 | BB186: =BA186 -> 46102 | BC186: 44223 | BD186: 44223 | BE186: 44223 | BF186: 44223 | BG186: 44223 | BH186: 44223 | BI186: 39715 | BJ186: 215810 | BK186: 857817 | BL186: 857817 | BM186: 857817 | BN186: 2289943 | BO186: =BN186 -> 2289943 | BP186: 0 | BQ186: 0 | BR186: 0 | BS186: 790528 | BT186: 803030 | BU186: 803030 | BV186: 805730 | BW186: 805730 | BX186: 3155194 | BY186: 3155194 | BZ186: 3155194 | CA186: 3155194 | CB186: =CA186 -> 3155194 | CC186: 33782 | CD186: 33782 | CE186: 33782 | CF186: 71669 | CG186: 164501 | CH186: 189962 | CI186: 189962 | CJ186: 261100 | CK186: 263984 | CL186: 423519 | CM186: 423519 | CN186: 423519 | CO186: =CN186 -> 423519 | CP186: 146225 | CQ186: 146225 | CR186: 146225 | CS186: 146225 | CT186: 1356754 | CU186: 1356754 | CV186: 1356754 | CW186: 1357754 | CX186: 1357754 | CY186: 1369754 | CZ186: 1334862 | DA186: 1334862 | DB186: =DA186 -> 1334862 | DC186: 206622 | DD186: 206622 | DE186: 206622 | DF186: 206622 | DG186: 206622 | DH186: 206622 | DI186: 220322 | DJ186: 220322 | DK186: 1274792 | DL186: 1274792 | DM186: 1274792 | DN186: 1274792 | DO186: =DN186 -> 1274792 | DP186: 219639 | DQ186: 453220 | DR186: 561356 | DS186: 563856 | DT186: 563856 | DU186: 631749 | DV186: 634029 | DW186: 649261 | DX186: 700280 | DY186: 700280 | DZ186: 700280 | EA186: 700280 | EB186: =EA186 -> 700280 | EC186: 201180 | ED186: 201180 | EE186: 338642 | EF186: 557108 | EG186: 1842209 | EH186: 1842209 | EI186: 1842209 | EJ186: 1916083 | EK186: 1916083 | EL186: 1918083 | EM186: 2409228 | EN186: 2287782 | EO186: =EN186 -> 2287782 | EP186: 209629 | EQ186: 1498945 | ER186: 1498945 | ES186: 2526550 | ET186: 2528050 | EU186: 2528050 | EV186: 2528050 | EW186: 2528050 | EX186: 2528050 | EY186: 2655160 | EZ186: 2655160 | FA186: 1296498 | FB186: =FA186 -> 1296498 | FC186: 216128 | FD186: 1522485 | FE186: 1522485 | FF186: 1522485 | FG186: 1522485 | FH186: 1522485 | FI186: 1593058 | FO186: =FI186 -> 1593058
B187: Total Presupuesto Vigente (Subtítulo 29) | C187: =SUM(C155:C186) -> 16323134 | D187: =SUM(D155:D186) -> 21758636 | E187: =SUM(E155:E186) -> 21758636 | F187: =SUM(F155:F186) -> 21758636 | G187: =SUM(G155:G186) -> 22329916 | H187: =SUM(H155:H186) -> 22535451 | I187: =SUM(I155:I186) -> 22813236 | J187: =SUM(J155:J186) -> 22813236 | ... FO187: =SUM(FO155:FO186) -> 45683963
B188: Ejecución Acumulada (Subtítulo 29)
C189: 2014 | P189: 2015 | AC189: 2016 | AP189: 2017 | BC189: 2018 | BP189: 2019 | CC189: 2020 | CP189: 2021 | DC189: 2022 | DP189: 2023 | EC189: 2024 | EP189: 2025 | FC189: 2026
B190: Programa / Entidad | C190: Ene | D190: Feb | E190: Mar | F190: Abr | G190: May | H190: Jun | I190: Jul | J190: Ago | K190: Sep | L190: Oct | M190: Nov | N190: Dic | O190: Total 2014 | P190: Ene | Q190: Feb | R190: Mar | S190: Abr | T190: May | U190: Jun | V190: Jul | W190: Ago | X190: Sep | Y190: Oct | Z190: Nov | AA190: Dic | AB190: Total 2015 | AC190: Ene | AD190: Feb | AE190: Mar | AF190: Abr | AG190: May | AH190: Jun | AI190: Jul | AJ190: Ago | AK190: Sep | AL190: Oct | AM190: Nov | AN190: Dic | AO190: Total 2016 | AP190: Ene | AQ190: Feb | AR190: Mar | AS190: Abr | AT190: May | AU190: Jun | AV190: Jul | AW190: Ago | AX190: Sep | AY190: Oct | AZ190: Nov | BA190: Dic | BB190: Total 2017 | BC190: Ene | BD190: Feb | BE190: Mar | BF190: Abr | BG190: May | BH190: Jun | BI190: Jul | BJ190: Ago | BK190: Sep | BL190: Oct | BM190: Nov | BN190: Dic | BO190: Total 2018 | BP190: Ene | BQ190: Feb | BR190: Mar | BS190: Abr | BT190: May | BU190: Jun | BV190: Jul | BW190: Ago | BX190: Sep | BY190: Oct | BZ190: Nov | CA190: Dic | CB190: Total 2019 | CC190: Ene | CD190: Feb | CE190: Mar | CF190: Abr | CG190: May | CH190: Jun | CI190: Jul | CJ190: Ago | CK190: Sep | CL190: Oct | CM190: Nov | CN190: Dic | CO190: Total 2020 | CP190: Ene | CQ190: Feb | CR190: Mar | CS190: Abr | CT190: May | CU190: Jun | CV190: Jul | CW190: Ago | CX190: Sep | CY190: Oct | CZ190: Nov | DA190: Dic | DB190: Total 2021 | DC190: Ene | DD190: Feb | DE190: Mar | DF190: Abr | DG190: May | DH190: Jun | DI190: Jul | DJ190: Ago | DK190: Sep | DL190: Oct | DM190: Nov | DN190: Dic | DO190: Total 2022 | DP190: Ene | DQ190: Feb | DR190: Mar | DS190: Abr | DT190: May | DU190: Jun | DV190: Jul | DW190: Ago | DX190: Sep | DY190: Oct | DZ190: Nov | EA190: Dic | EB190: Total 2023 | EC190: Ene | ED190: Feb | EE190: Mar | EF190: Abr | EG190: May | EH190: Jun | EI190: Jul | EJ190: Ago | EK190: Sep | EL190: Oct | EM190: Nov | EN190: Dic | EO190: Total 2024 | EP190: Ene | EQ190: Feb | ER190: Mar | ES190: Abr | ET190: May | EU190: Jun | EV190: Jul | EW190: Ago | EX190: Sep | EY190: Oct | EZ190: Nov | FA190: Dic | FB190: Total 2025 | FC190: Ene | FD190: Feb | FE190: Mar | FF190: Abr | FG190: May | FH190: Jun | FI190: Jul | FJ190: Ago | FK190: Sep | FL190: Oct | FM190: Nov | FN190: Dic | FO190: Total 2026
B191: Instituto de Salud Pública | C191: 10118 | D191: 41755 | E191: 395934 | F191: 438597 | G191: 473245 | H191: 553292 | I191: 596322 | J191: 732540 | K191: 980997 | L191: 1061248 | M191: 1203613 | N191: 1705072 | O191: =N191 -> 1705072 | P191: 234289 | Q191: 280864 | R191: 389212 | S191: 392496 | T191: 611271 | U191: 1083953 | V191: 1162762 | W191: 1169373 | X191: 1337490 | Y191: 1497095 | Z191: 1550823 | AA191: 2541880 | AB191: =AA191 -> 2541880 | AC191: 296297 | AD191: 366244 | AE191: 530044 | AF191: 667360 | AG191: 884182 | AH191: 941102 | AI191: 1118959 | AJ191: 1260279 | AK191: 1329427 | AL191: 1451411 | AM191: 1484515 | AN191: 2202137 | AO191: =AN191 -> 2202137 | AP191: 49620 | AQ191: 112581 | AR191: 336577 | AS191: 379328 | AT191: 387962 | AU191: 562084 | AV191: 615047 | AW191: 764328 | AX191: 843215 | AY191: 936541 | AZ191: 1097412 | BA191: 2144094 | BB191: =BA191 -> 2144094 | BC191: 11330 | BD191: 256250 | BE191: 307465 | BF191: 359216 | BG191: 492849 | BH191: 654592 | BI191: 722270 | BJ191: 749076 | BK191: 756398 | BL191: 779064 | BM191: 815527 | BN191: 1832630 | BO191: =BN191 -> 1832630 | BP191: 20973 | BQ191: 38684 | BR191: 50595 | BS191: 52541 | BT191: 54303 | BU191: 57528 | BV191: 61788 | BW191: 62832 | BX191: 78213 | BY191: 91084 | BZ191: 94232 | CA191: 414610 | CB191: =CA191 -> 414610 | CC191: 48185 | CD191: 62496 | CE191: 64641 | CF191: 64641 | CG191: 64641 | CH191: 221638 | CI191: 222542 | CJ191: 228257 | CK191: 253516 | CL191: 314141 | CM191: 1037111 | CN191: 1766253 | CO191: =CN191 -> 1766253 | CP191: 2206 | CQ191: 2206 | CR191: 15228 | CS191: 65203 | CT191: 262225 | CU191: 401055 | CV191: 465494 | CW191: 498622 | CX191: 564762 | CY191: 624333 | CZ191: 683715 | DA191: 1710920 | DB191: =DA191 -> 1710920 | DC191: 0 | DD191: 49204 | DE191: 67301 | DF191: 67301 | DG191: 89474 | DH191: 91209 | DI191: 99748 | DJ191: 131689 | DK191: 189236 | DL191: 271566 | DM191: 292561 | DN191: 1265060 | DO191: =DN191 -> 1265060 | DP191: 54994 | DQ191: 54994 | DR191: 83552 | DS191: 112261 | DT191: 172047 | DU191: 194204 | DV191: 243359 | DW191: 454804 | DX191: 703948 | DY191: 837804 | DZ191: 1221484 | EA191: 2191029 | EB191: =EA191 -> 2191029 | EC191: 204322 | ED191: 288294 | EE191: 300935 | EF191: 300935 | EG191: 586628 | EH191: 599154 | EI191: 681921 | EJ191: 692831 | EK191: 925855 | EL191: 1032205 | EM191: 1040938 | EN191: 1866164 | EO191: =EN191 -> 1866164 | EP191: 5763 | EQ191: 76721 | ER191: 77970 | ES191: 123568 | ET191: 123568 | EU191: 123891 | EV191: 202838 | EW191: 289738 | EX191: 306386 | EY191: 791612 | EZ191: 1263445 | FA191: 1552207 | FB191: =FA191 -> 1552207 | FC191: 29482 | FD191: 119876 | FE191: 151962 | FF191: 186702 | FG191: 197519 | FH191: 197519 | FI191: 197519 | FO191: =FI191 -> 197519
B192: Subsecretaría de Salud Pública | C192: 1396 | D192: 9124 | E192: 35586 | F192: 78695 | G192: 256019 | H192: 316297 | I192: 418072 | J192: 475809 | K192: 536348 | L192: 727469 | M192: 950618 | N192: 3450310 | O192: =N192 -> 3450310 | P192: 12237 | Q192: 39921 | R192: 88492 | S192: 393010 | T192: 441357 | U192: 501061 | V192: 604377 | W192: 700796 | X192: 1022957 | Y192: 1131654 | Z192: 1670144 | AA192: 6864144 | AB192: =AA192 -> 6864144 | AC192: 21714 | AD192: 152401 | AE192: 285497 | AF192: 319413 | AG192: 1726854 | AH192: 2505950 | AI192: 5165331 | AJ192: 5520124 | AK192: 5678996 | AL192: 6505005 | AM192: 8037211 | AN192: 9580437 | AO192: =AN192 -> 9580437 | AP192: 10135 | AQ192: 86469 | AR192: 336859 | AS192: 1642400 | AT192: 1583477 | AU192: 1665938 | AV192: 1721530 | AW192: 1795093 | AX192: 1872680 | AY192: 2103801 | AZ192: 4609956 | BA192: 9137604 | BB192: =BA192 -> 9137604 | BC192: 5570 | BD192: 54170 | BE192: 1379846 | BF192: 1497960 | BG192: 1409400 | BH192: 1466822 | BI192: 1623624 | BJ192: 1906766 | BK192: 2188123 | BL192: 2416760 | BM192: 2856319 | BN192: 3922193 | BO192: =BN192 -> 3922193 | BP192: 8139 | BQ192: 18877 | BR192: 50498 | BS192: 62422 | BT192: 90188 | BU192: 1530673 | BV192: 1588455 | BW192: 1623780 | BX192: 1917793 | BY192: 1974530 | BZ192: 2186222 | CA192: 2834888 | CB192: =CA192 -> 2834888 | CC192: 83 | CD192: 12143 | CE192: 1685894 | CF192: 1721923 | CG192: 1733011 | CH192: 1820859 | CI192: 2118378 | CJ192: 2253795 | CK192: 2521246 | CL192: 2755622 | CM192: 3285055 | CN192: 4423810 | CO192: =CN192 -> 4423810 | CP192: 45176 | CQ192: 75678 | CR192: 116645 | CS192: 137851 | CT192: 171316 | CU192: 174373 | CV192: 186397 | CW192: 396798 | CX192: 466942 | CY192: 488378 | CZ192: 707014 | DA192: 1286979 | DB192: =DA192 -> 1286979 | DC192: 28591 | DD192: 32373 | DE192: 46304 | DF192: 46304 | DG192: 55244 | DH192: 55655 | DI192: 68230 | DJ192: 80614 | DK192: 93234 | DL192: 150644 | DM192: 454323 | DN192: 1543008 | DO192: =DN192 -> 1543008 | DP192: 841 | DQ192: 841 | DR192: 25582 | DS192: 31740 | DT192: 62776 | DU192: 80498 | DV192: 170859 | DW192: 358224 | DX192: 453628 | DY192: 591099 | DZ192: 893192 | EA192: 2028479 | EB192: =EA192 -> 2028479 | EC192: 0 | ED192: 0 | EE192: 0 | EF192: 0 | EG192: 3536 | EH192: 294788 | EI192: 321560 | EJ192: 331042 | EK192: 335085 | EL192: 390566 | EM192: 411547 | EN192: 733331 | EO192: =EN192 -> 733331 | EP192: 0 | EQ192: 1294 | ER192: 1294 | ES192: 36508 | ET192: 36508 | EU192: 39078 | EV192: 162201 | EW192: 254134 | EX192: 287265 | EY192: 350937 | EZ192: 754718 | FA192: 849806 | FB192: =FA192 -> 849806 | FC192: 0 | FD192: 0 | FE192: 0 | FF192: 0 | FG192: 0 | FH192: 0 | FI192: 0 | FO192: =FI192 -> 0
B193: Inversión Sectorial en Salud | C193: 0 | D193: 0 | E193: 332102 | F193: 332102 | G193: 332102 | H193: 332415 | I193: 333125 | J193: 333448 | K193: 333448 | L193: 333448 | M193: 916598 | N193: 1216982 | O193: =N193 -> 1216982 | P193: 0 | Q193: 0 | R193: 225031 | S193: 225477 | T193: 229296 | U193: 229250 | V193: 229250 | W193: 396781 | X193: 398391 | Y193: 402039 | Z193: 402303 | AA193: 981688 | AB193: =AA193 -> 981688 | AC193: 5746 | AD193: 21707 | AE193: 47382 | AF193: 62718 | AG193: 65355 | AH193: 66490 | AI193: 564370 | AJ193: 566623 | AK193: 566623 | AL193: 585921 | AM193: 586503 | AN193: 1123760 | AO193: =AN193 -> 1123760 | AP193: 0 | AQ193: 2950 | AR193: 3182 | AS193: 3182 | AT193: 3182 | AU193: 5572 | AV193: 24862 | AW193: 31754 | AX193: 459314 | AY193: 459505 | AZ193: 459671 | BA193: 945719 | BB193: =BA193 -> 945719 | BC193: 15619 | BD193: 15619 | BE193: 28819 | BF193: 28819 | BG193: 46601 | BH193: 596973 | BI193: 605002 | BJ193: 605723 | BK193: 691963 | BL193: 848552 | BM193: 852581 | BN193: 1163852 | BO193: =BN193 -> 1163852 | BP193: 0 | BQ193: 0 | BR193: 0 | BS193: 0 | BT193: 0 | BU193: 0 | BV193: 0 | BW193: 0 | BX193: 0 | BY193: 0 | BZ193: 5347 | CA193: 5347 | CB193: =CA193 -> 5347 | CC193: 0 | CD193: 0 | CE193: 0 | CF193: 0 | CG193: 948 | CH193: 1821650 | CI193: 4246519 | CJ193: 4379541 | CK193: 4393821 | CL193: 9521196 | CM193: 30028437 | CN193: 87163302 | CO193: =CN193 -> 87163302 | CP193: 0 | CQ193: 0 | CR193: 0 | CS193: 0 | CT193: 0 | CU193: 2829849 | CV193: 2862985 | CW193: 13366199 | CX193: 16914426 | CY193: 18166720 | CZ193: 24429405 | DA193: 47217628 | DB193: =DA193 -> 47217628 | DC193: 0 | DD193: 0 | DE193: 0 | DF193: 0 | DG193: 0 | DH193: 0 | DI193: 0 | DJ193: 0 | DK193: 0 | DL193: 0 | DM193: 0 | DN193: 186 | DO193: =DN193 -> 186 | DP193: 0 | DQ193: 0 | DR193: 0 | DS193: 0 | DT193: 0 | DU193: 0 | DV193: 0 | DW193: 0 | DX193: 1233198 | DY193: 1275419 | DZ193: 2754161 | EA193: 5129200 | EB193: =EA193 -> 5129200 | EC193: 0 | ED193: 0 | EE193: 0 | EF193: 0 | EG193: 285303 | EH193: 285303 | EI193: 285303 | EJ193: 285303 | EK193: 285303 | EL193: 285303 | EM193: 314286 | EN193: 581899 | EO193: =EN193 -> 581899 | EP193: 0 | EQ193: 0 | ER193: 510213 | ES193: 510213 | ET193: 510213 | EU193: 510213 | EV193: 510213 | EW193: 510213 | EX193: 510213 | EY193: 510213 | EZ193: 510213 | FA193: 510213 | FB193: =FA193 -> 510213 | FC193: 0 | FD193: 0 | FE193: 0 | FF193: 0 | FG193: 0 | FH193: 0 | FI193: 0 | FO193: =FI193 -> 0
B194: Servicio de Salud Arica y Parinacota | C194: 978 | D194: 3395 | E194: 3395 | F194: 22982 | G194: 29801 | H194: 37273 | I194: 57763 | J194: 61391 | K194: 63617 | L194: 91311 | M194: 99509 | N194: 250908 | O194: =N194 -> 250908 | P194: 2474 | Q194: 18159 | R194: 27772 | S194: 33278 | T194: 58333 | U194: 66561 | V194: 74129 | W194: 80936 | X194: 101442 | Y194: 105274 | Z194: 219564 | AA194: 758119 | AB194: =AA194 -> 758119 | AC194: 0 | AD194: 7907 | AE194: 31019 | AF194: 37712 | AG194: 65352 | AH194: 70285 | AI194: 77190 | AJ194: 84616 | AK194: 88825 | AL194: 92047 | AM194: 101071 | AN194: 409951 | AO194: =AN194 -> 409951 | AP194: 460 | AQ194: 18162 | AR194: 42694 | AS194: 50314 | AT194: 61860 | AU194: 71790 | AV194: 97379 | AW194: 104432 | AX194: 119591 | AY194: 126796 | AZ194: 127194 | BA194: 364255 | BB194: =BA194 -> 364255 | BC194: 0 | BD194: 290 | BE194: 4246 | BF194: 26426 | BG194: 53026 | BH194: 84870 | BI194: 96108 | BJ194: 98890 | BK194: 99802 | BL194: 126217 | BM194: 167413 | BN194: 1355173 | BO194: =BN194 -> 1355173 | BP194: 0 | BQ194: 0 | BR194: 0 | BS194: 0 | BT194: 0 | BU194: 0 | BV194: 0 | BW194: 0 | BX194: 2056 | BY194: 2056 | BZ194: 7687 | CA194: 2242437 | CB194: =CA194 -> 2242437 | CC194: 0 | CD194: 0 | CE194: 0 | CF194: 774 | CG194: 49514 | CH194: 78788 | CI194: 81183 | CJ194: 81183 | CK194: 87480 | CL194: 87480 | CM194: 88834 | CN194: 274995 | CO194: =CN194 -> 274995 | CP194: 0 | CQ194: 1519 | CR194: 7323 | CS194: 10864 | CT194: 17463 | CU194: 22280 | CV194: 27184 | CW194: 41556 | CX194: 174121 | CY194: 236472 | CZ194: 309937 | DA194: 463683 | DB194: =DA194 -> 463683 | DC194: 2629 | DD194: 3224 | DE194: 5683 | DF194: 7311 | DG194: 7829 | DH194: 13065 | DI194: 13065 | DJ194: 19037 | DK194: 50336 | DL194: 77955 | DM194: 240848 | DN194: 429145 | DO194: =DN194 -> 429145 | DP194: 0 | DQ194: 1974 | DR194: 6068 | DS194: 6630 | DT194: 18709 | DU194: 65620 | DV194: 109466 | DW194: 110490 | DX194: 234808 | DY194: 266638 | DZ194: 385446 | EA194: 1188574 | EB194: =EA194 -> 1188574 | EC194: 417 | ED194: 417 | EE194: 417 | EF194: 71294 | EG194: 72446 | EH194: 72446 | EI194: 92097 | EJ194: 105082 | EK194: 212007 | EL194: 271116 | EM194: 286064 | EN194: 512541 | EO194: =EN194 -> 512541 | EP194: 1080 | EQ194: 2340 | ER194: 5226 | ES194: 15451 | ET194: 30700 | EU194: 41291 | EV194: 63764 | EW194: 88713 | EX194: 101157 | EY194: 231967 | EZ194: 599236 | FA194: 855579 | FB194: =FA194 -> 855579 | FC194: 4485 | FD194: 4985 | FE194: 20789 | FF194: 86770 | FG194: 86770 | FH194: 110607 | FI194: 117802 | FO194: =FI194 -> 117802
B195: Servicio de Salud Tarapacá | C195: 40674 | D195: 64932 | E195: 77235 | F195: 89945 | G195: 161909 | H195: 171718 | I195: 184772 | J195: 188977 | K195: 200050 | L195: 207541 | M195: 334799 | N195: 485976 | O195: =N195 -> 485976 | P195: 8500 | Q195: 14231 | R195: 16552 | S195: 44155 | T195: 58114 | U195: 62814 | V195: 71329 | W195: 338603 | X195: 341436 | Y195: 341436 | Z195: 377739 | AA195: 400800 | AB195: =AA195 -> 400800 | AC195: 14078 | AD195: 30963 | AE195: 44242 | AF195: 51297 | AG195: 91554 | AH195: 153540 | AI195: 175277 | AJ195: 407638 | AK195: 416427 | AL195: 416671 | AM195: 418669 | AN195: 582972 | AO195: =AN195 -> 582972 | AP195: 3475 | AQ195: 20116 | AR195: 36103 | AS195: 41030 | AT195: 57941 | AU195: 68114 | AV195: 68394 | AW195: 73726 | AX195: 77131 | AY195: 92899 | AZ195: 206053 | BA195: 297922 | BB195: =BA195 -> 297922 | BC195: 52766 | BD195: 70260 | BE195: 107883 | BF195: 157253 | BG195: 176123 | BH195: 179866 | BI195: 191830 | BJ195: 210058 | BK195: 215023 | BL195: 241171 | BM195: 362527 | BN195: 470464 | BO195: =BN195 -> 470464 | BP195: 0 | BQ195: 0 | BR195: 0 | BS195: 0 | BT195: 0 | BU195: 0 | BV195: 0 | BW195: 141055 | BX195: 141055 | BY195: 153573 | BZ195: 172137 | CA195: 1389096 | CB195: =CA195 -> 1389096 | CC195: 0 | CD195: 796 | CE195: 796 | CF195: 796 | CG195: 796 | CH195: 796 | CI195: 71682 | CJ195: 71682 | CK195: 73348 | CL195: 73348 | CM195: 74919 | CN195: 473327 | CO195: =CN195 -> 473327 | CP195: 238 | CQ195: 5401 | CR195: 16372 | CS195: 28155 | CT195: 31315 | CU195: 35243 | CV195: 39222 | CW195: 45437 | CX195: 51150 | CY195: 99287 | CZ195: 529583 | DA195: 1109914 | DB195: =DA195 -> 1109914 | DC195: 4632 | DD195: 9488 | DE195: 20834 | DF195: 24788 | DG195: 34721 | DH195: 78114 | DI195: 74964 | DJ195: 96825 | DK195: 140853 | DL195: 150439 | DM195: 152238 | DN195: 857246 | DO195: =DN195 -> 857246 | DP195: 7923 | DQ195: 69716 | DR195: 109019 | DS195: 115221 | DT195: 150018 | DU195: 288811 | DV195: 567988 | DW195: 629698 | DX195: 629698 | DY195: 630608 | DZ195: 714801 | EA195: 4061138 | EB195: =EA195 -> 4061138 | EC195: 290 | ED195: 27991 | EE195: 38461 | EF195: 39395 | EG195: 49104 | EH195: 50047 | EI195: 50593 | EJ195: 50593 | EK195: 80202 | EL195: 125185 | EM195: 134961 | EN195: 520963 | EO195: =EN195 -> 520963 | EP195: 27322 | EQ195: 58931 | ER195: 85879 | ES195: 110594 | ET195: 121409 | EU195: 136950 | EV195: 137913 | EW195: 138151 | EX195: 467717 | EY195: 487561 | EZ195: 571824 | FA195: 682772 | FB195: =FA195 -> 682772 | FC195: 1898 | FD195: 9070 | FE195: 12542 | FF195: 14851 | FG195: 32899 | FH195: 53108 | FI195: 53108 | FO195: =FI195 -> 53108
B196: Servicio de Salud Antofagasta | C196: 45616 | D196: 49087 | E196: 65352 | F196: 96649 | G196: 125523 | H196: 135142 | I196: 146714 | J196: 184911 | K196: 188935 | L196: 201063 | M196: 216189 | N196: 851466 | O196: =N196 -> 851466 | P196: 556 | Q196: 37958 | R196: 57113 | S196: 84907 | T196: 95453 | U196: 130335 | V196: 187135 | W196: 216981 | X196: 277656 | Y196: 370589 | Z196: 474970 | AA196: 2588721 | AB196: =AA196 -> 2588721 | AC196: 4613 | AD196: 45155 | AE196: 67931 | AF196: 95217 | AG196: 108452 | AH196: 150575 | AI196: 156812 | AJ196: 159264 | AK196: 191007 | AL196: 209836 | AM196: 370461 | AN196: 711067 | AO196: =AN196 -> 711067 | AP196: 304 | AQ196: 5348 | AR196: 27019 | AS196: 36395 | AT196: 51008 | AU196: 59697 | AV196: 64607 | AW196: 152903 | AX196: 162059 | AY196: 168281 | AZ196: 234343 | BA196: 535330 | BB196: =BA196 -> 535330 | BC196: 108 | BD196: 3791 | BE196: 20555 | BF196: 37403 | BG196: 44326 | BH196: 136736 | BI196: 155505 | BJ196: 185987 | BK196: 207750 | BL196: 272659 | BM196: 307592 | BN196: 408912 | BO196: =BN196 -> 408912 | BP196: 692 | BQ196: 6974 | BR196: 8233 | BS196: 15973 | BT196: 16894 | BU196: 17105 | BV196: 17105 | BW196: 18006 | BX196: 18451 | BY196: 28317 | BZ196: 39553 | CA196: 309300 | CB196: =CA196 -> 309300 | CC196: 43903 | CD196: 43903 | CE196: 44895 | CF196: 45322 | CG196: 103696 | CH196: 109474 | CI196: 1149223 | CJ196: 1318697 | CK196: 1358779 | CL196: 2317962 | CM196: 2322522 | CN196: 4779621 | CO196: =CN196 -> 4779621 | CP196: 4720 | CQ196: 23500 | CR196: 87812 | CS196: 120790 | CT196: 136678 | CU196: 161269 | CV196: 167532 | CW196: 178470 | CX196: 195920 | CY196: 218818 | CZ196: 236570 | DA196: 534159 | DB196: =DA196 -> 534159 | DC196: 4491 | DD196: 9300 | DE196: 68828 | DF196: 136279 | DG196: 156162 | DH196: 192894 | DI196: 222413 | DJ196: 228771 | DK196: 326167 | DL196: 333749 | DM196: 403931 | DN196: 633585 | DO196: =DN196 -> 633585 | DP196: 4768 | DQ196: 18519 | DR196: 28061 | DS196: 43165 | DT196: 53084 | DU196: 61323 | DV196: 136838 | DW196: 168483 | DX196: 221982 | DY196: 249660 | DZ196: 308493 | EA196: 1424080 | EB196: =EA196 -> 1424080 | EC196: 13008 | ED196: 39559 | EE196: 66046 | EF196: 86941 | EG196: 125290 | EH196: 138148 | EI196: 175446 | EJ196: 478092 | EK196: 517537 | EL196: 871085 | EM196: 953728 | EN196: 1522298 | EO196: =EN196 -> 1522298 | EP196: 0 | EQ196: 8644 | ER196: 13667 | ES196: 33858 | ET196: 231286 | EU196: 257693 | EV196: 271067 | EW196: 395271 | EX196: 420100 | EY196: 809184 | EZ196: 879934 | FA196: 1266693 | FB196: =FA196 -> 1266693 | FC196: 12152 | FD196: 16836 | FE196: 26941 | FF196: 30736 | FG196: 49163 | FH196: 53217 | FI196: 69537 | FO196: =FI196 -> 69537
B197: Servicio de Salud Atacama | C197: 7098 | D197: 19046 | E197: 32013 | F197: 43498 | G197: 55885 | H197: 64841 | I197: 66992 | J197: 81600 | K197: 84031 | L197: 91530 | M197: 102090 | N197: 1351748 | O197: =N197 -> 1351748 | P197: 4779 | Q197: 5337 | R197: 10511 | S197: 257652 | T197: 258708 | U197: 264162 | V197: 287878 | W197: 578376 | X197: 723834 | Y197: 826680 | Z197: 963642 | AA197: 2020689 | AB197: =AA197 -> 2020689 | AC197: 17247 | AD197: 33594 | AE197: 67560 | AF197: 101608 | AG197: 104954 | AH197: 121207 | AI197: 121950 | AJ197: 124352 | AK197: 237276 | AL197: 240838 | AM197: 263613 | AN197: 536499 | AO197: =AN197 -> 536499 | AP197: 1557 | AQ197: 2023 | AR197: 12235 | AS197: 25449 | AT197: 28566 | AU197: 48194 | AV197: 56504 | AW197: 59898 | AX197: 63957 | AY197: 70783 | AZ197: 75838 | BA197: 343666 | BB197: =BA197 -> 343666 | BC197: 3716 | BD197: 8759 | BE197: 13520 | BF197: 33682 | BG197: 37008 | BH197: 58239 | BI197: 65076 | BJ197: 72572 | BK197: 73511 | BL197: 79149 | BM197: 82629 | BN197: 1896806 | BO197: =BN197 -> 1896806 | BP197: 0 | BQ197: 0 | BR197: 0 | BS197: 0 | BT197: 0 | BU197: 0 | BV197: 0 | BW197: 128520 | BX197: 128520 | BY197: 139598 | BZ197: 173191 | CA197: 756910 | CB197: =CA197 -> 756910 | CC197: 0 | CD197: 1246 | CE197: 1246 | CF197: 123837 | CG197: 123837 | CH197: 199392 | CI197: 218513 | CJ197: 227169 | CK197: 307304 | CL197: 383453 | CM197: 584437 | CN197: 814213 | CO197: =CN197 -> 814213 | CP197: 0 | CQ197: 42307 | CR197: 55404 | CS197: 151090 | CT197: 151090 | CU197: 195264 | CV197: 183106 | CW197: 203863 | CX197: 203863 | CY197: 483916 | CZ197: 492238 | DA197: 1187835 | DB197: =DA197 -> 1187835 | DC197: 0 | DD197: 0 | DE197: 2011 | DF197: 7418 | DG197: 16712 | DH197: 24338 | DI197: 62632 | DJ197: 89363 | DK197: 129706 | DL197: 288475 | DM197: 313880 | DN197: 1615483 | DO197: =DN197 -> 1615483 | DP197: 0 | DQ197: 0 | DR197: 0 | DS197: 0 | DT197: 0 | DU197: 140301 | DV197: 308588 | DW197: 312286 | DX197: 357836 | DY197: 383522 | DZ197: 572784 | EA197: 824019 | EB197: =EA197 -> 824019 | EC197: 0 | ED197: 0 | EE197: 5397 | EF197: 11722 | EG197: 19621 | EH197: 25307 | EI197: 35466 | EJ197: 89146 | EK197: 205984 | EL197: 340824 | EM197: 401366 | EN197: 713431 | EO197: =EN197 -> 713431 | EP197: 2634 | EQ197: 15498 | ER197: 29564 | ES197: 34598 | ET197: 67061 | EU197: 84871 | EV197: 90609 | EW197: 101428 | EX197: 155528 | EY197: 231983 | EZ197: 573229 | FA197: 1133324 | FB197: =FA197 -> 1133324 | FC197: 0 | FD197: 1998 | FE197: 1998 | FF197: 16954 | FG197: 32342 | FH197: 33019 | FI197: 65902 | FO197: =FI197 -> 65902
